Workbook

Sheet Resumo UF
A1: Comparativo PASSARO – PROPOSTA 2 (07/10/2026) x fretes realizados – Top 10 cidades por UF (Nordeste, Ago/2026)
A2: Valores com ICMS. Frete atual = coluna J (Valor CTe). Passaro = tabela proposta, origem SP. Diferença negativa = Passaro mais barata.
A4: UF | B4: Pedidos | C4: Peso total (kg) | D4: Valor NF total (R$) | E4: Frete atual (R$) | F4: Frete PASSARO (R$) | G4: Diferença (R$) | H4: Dif. % | I4: % frete/NF atual | J4: % frete/NF Passaro | K4: Pedidos em que Passaro é mais barata | L4: % pedidos Passaro mais barata | M4: Desconto que a Passaro precisa dar p/ empatar
A5: AL | B5: =COUNTIFS('Pedidos Top10'!$A$2:$A$1839,A5) -> 167 | C5: =SUMIFS('Pedidos Top10'!$J$2:$J$1839,'Pedidos Top10'!$A$2:$A$1839,A5) -> 8123.94 | D5: =SUMIFS('Pedidos Top10'!$K$2:$K$1839,'Pedidos Top10'!$A$2:$A$1839,A5) -> 156881.45 | E5: =SUMIFS('Pedidos Top10'!$L$2:$L$1839,'Pedidos Top10'!$A$2:$A$1839,A5) -> 29157.55 | F5: =SUMIFS('Pedidos Top10'!$AD$2:$AD$1839,'Pedidos Top10'!$A$2:$A$1839,A5) -> 25733.4 | G5: =F5-E5 -> -3424.15 | H5: =IF(E5=0,0,G5/E5) -> -0.11743614 | I5: =IF(D5=0,0,E5/D5) -> 0.18585722 | J5: =IF(D5=0,0,F5/D5) -> 0.16403087 | K5: =COUNTIFS('Pedidos Top10'!$A$2:$A$1839,A5,'Pedidos Top10'!$AG$2:$AG$1839,"PASSARO") -> 115 | L5: =IF(B5=0,0,K5/B5) -> 0.68862275 | M5: =IF(F5<=E5,0,1-E5/F5) -> 0
A6: BA | B6: =COUNTIFS('Pedidos Top10'!$A$2:$A$1839,A6) -> 501 | C6: =SUMIFS('Pedidos Top10'!$J$2:$J$1839,'Pedidos Top10'!$A$2:$A$1839,A6) -> 26699.12 | D6: =SUMIFS('Pedidos Top10'!$K$2:$K$1839,'Pedidos Top10'!$A$2:$A$1839,A6) -> 458094.85 | E6: =SUMIFS('Pedidos Top10'!$L$2:$L$1839,'Pedidos Top10'!$A$2:$A$1839,A6) -> 87126.83 | F6: =SUMIFS('Pedidos Top10'!$AD$2:$AD$1839,'Pedidos Top10'!$A$2:$A$1839,A6) -> 65815.37 | G6: =F6-E6 -> -21311.46 | H6: =IF(E6=0,0,G6/E6) -> -0.24460272 | I6: =IF(D6=0,0,E6/D6) -> 0.19019386 | J6: =IF(D6=0,0,F6/D6) -> 0.14367193 | K6: =COUNTIFS('Pedidos Top10'!$A$2:$A$1839,A6,'Pedidos Top10'!$AG$2:$AG$1839,"PASSARO") -> 439 | L6: =IF(B6=0,0,K6/B6) -> 0.8762475 | M6: =IF(F6<=E6,0,1-E6/F6) -> 0
A7: CE | B7: =COUNTIFS('Pedidos Top10'!$A$2:$A$1839,A7) -> 259 | C7: =SUMIFS('Pedidos Top10'!$J$2:$J$1839,'Pedidos Top10'!$A$2:$A$1839,A7) -> 13113.76 | D7: =SUMIFS('Pedidos Top10'!$K$2:$K$1839,'Pedidos Top10'!$A$2:$A$1839,A7) -> 239912.91 | E7: =SUMIFS('Pedidos Top10'!$L$2:$L$1839,'Pedidos Top10'!$A$2:$A$1839,A7) -> 49566.26 | F7: =SUMIFS('Pedidos Top10'!$AD$2:$AD$1839,'Pedidos Top10'!$A$2:$A$1839,A7) -> 61581.4 | G7: =F7-E7 -> 12015.14 | H7: =IF(E7=0,0,G7/E7) -> 0.24240562 | I7: =IF(D7=0,0,E7/D7) -> 0.20660105 | J7: =IF(D7=0,0,F7/D7) -> 0.25668231 | K7: =COUNTIFS('Pedidos Top10'!$A$2:$A$1839,A7,'Pedidos Top10'!$AG$2:$AG$1839,"PASSARO") -> 24 | L7: =IF(B7=0,0,K7/B7) -> 0.092664093 | M7: =IF(F7<=E7,0,1-E7/F7) -> 0.19510989
A8: MA | B8: =COUNTIFS('Pedidos Top10'!$A$2:$A$1839,A8) -> 152 | C8: =SUMIFS('Pedidos Top10'!$J$2:$J$1839,'Pedidos Top10'!$A$2:$A$1839,A8) -> 8439.19 | D8: =SUMIFS('Pedidos Top10'!$K$2:$K$1839,'Pedidos Top10'!$A$2:$A$1839,A8) -> 156324.13 | E8: =SUMIFS('Pedidos Top10'!$L$2:$L$1839,'Pedidos Top10'!$A$2:$A$1839,A8) -> 27876.98 | F8: =SUMIFS('Pedidos Top10'!$AD$2:$AD$1839,'Pedidos Top10'!$A$2:$A$1839,A8) -> 48379.73 | G8: =F8-E8 -> 20502.75 | H8: =IF(E8=0,0,G8/E8) -> 0.73547242 | I8: =IF(D8=0,0,E8/D8) -> 0.17832807 | J8: =IF(D8=0,0,F8/D8) -> 0.30948344 | K8: =COUNTIFS('Pedidos Top10'!$A$2:$A$1839,A8,'Pedidos Top10'!$AG$2:$AG$1839,"PASSARO") -> 0 | L8: =IF(B8=0,0,K8/B8) -> 0 | M8: =IF(F8<=E8,0,1-E8/F8) -> 0.42378802
A9: PB | B9: =COUNTIFS('Pedidos Top10'!$A$2:$A$1839,A9) -> 117 | C9: =SUMIFS('Pedidos Top10'!$J$2:$J$1839,'Pedidos Top10'!$A$2:$A$1839,A9) -> 5471.92 | D9: =SUMIFS('Pedidos Top10'!$K$2:$K$1839,'Pedidos Top10'!$A$2:$A$1839,A9) -> 101595.23 | E9: =SUMIFS('Pedidos Top10'!$L$2:$L$1839,'Pedidos Top10'!$A$2:$A$1839,A9) -> 20680.9 | F9: =SUMIFS('Pedidos Top10'!$AD$2:$AD$1839,'Pedidos Top10'!$A$2:$A$1839,A9) -> 18903.35 | G9: =F9-E9 -> -1777.55 | H9: =IF(E9=0,0,G9/E9) -> -0.085951288 | I9: =IF(D9=0,0,E9/D9) -> 0.20356172 | J9: =IF(D9=0,0,F9/D9) -> 0.18606533 | K9: =COUNTIFS('Pedidos Top10'!$A$2:$A$1839,A9,'Pedidos Top10'!$AG$2:$AG$1839,"PASSARO") -> 62 | L9: =IF(B9=0,0,K9/B9) -> 0.52991453 | M9: =IF(F9<=E9,0,1-E9/F9) -> 0
A10: PE | B10: =COUNTIFS('Pedidos Top10'!$A$2:$A$1839,A10) -> 349 | C10: =SUMIFS('Pedidos Top10'!$J$2:$J$1839,'Pedidos Top10'!$A$2:$A$1839,A10) -> 16860.63 | D10: =SUMIFS('Pedidos Top10'!$K$2:$K$1839,'Pedidos Top10'!$A$2:$A$1839,A10) -> 309095.04 | E10: =SUMIFS('Pedidos Top10'!$L$2:$L$1839,'Pedidos Top10'!$A$2:$A$1839,A10) -> 61261.87 | F10: =SUMIFS('Pedidos Top10'!$AD$2:$AD$1839,'Pedidos Top10'!$A$2:$A$1839,A10) -> 55213.96 | G10: =F10-E10 -> -6047.91 | H10: =IF(E10=0,0,G10/E10) -> -0.098722256 | I10: =IF(D10=0,0,E10/D10) -> 0.19819752 | J10: =IF(D10=0,0,F10/D10) -> 0.17863101 | K10: =COUNTIFS('Pedidos Top10'!$A$2:$A$1839,A10,'Pedidos Top10'!$AG$2:$AG$1839,"PASSARO") -> 229 | L10: =IF(B10=0,0,K10/B10) -> 0.65616046 | M10: =IF(F10<=E10,0,1-E10/F10) -> 0
A11: PI | B11: =COUNTIFS('Pedidos Top10'!$A$2:$A$1839,A11) -> 109 | C11: =SUMIFS('Pedidos Top10'!$J$2:$J$1839,'Pedidos Top10'!$A$2:$A$1839,A11) -> 6382.36 | D11: =SUMIFS('Pedidos Top10'!$K$2:$K$1839,'Pedidos Top10'!$A$2:$A$1839,A11) -> 121179.11 | E11: =SUMIFS('Pedidos Top10'!$L$2:$L$1839,'Pedidos Top10'!$A$2:$A$1839,A11) -> 22463.82 | F11: =SUMIFS('Pedidos Top10'!$AD$2:$AD$1839,'Pedidos Top10'!$A$2:$A$1839,A11) -> 38265.91 | G11: =F11-E11 -> 15802.09 | H11: =IF(E11=0,0,G11/E11) -> 0.70344625 | I11: =IF(D11=0,0,E11/D11) -> 0.185377 | J11: =IF(D11=0,0,F11/D11) -> 0.31577976 | K11: =COUNTIFS('Pedidos Top10'!$A$2:$A$1839,A11,'Pedidos Top10'!$AG$2:$AG$1839,"PASSARO") -> 0 | L11: =IF(B11=0,0,K11/B11) -> 0 | M11: =IF(F11<=E11,0,1-E11/F11) -> 0.41295477
A12: RN | B12: =COUNTIFS('Pedidos Top10'!$A$2:$A$1839,A12) -> 87 | C12: =SUMIFS('Pedidos Top10'!$J$2:$J$1839,'Pedidos Top10'!$A$2:$A$1839,A12) -> 3596.46 | D12: =SUMIFS('Pedidos Top10'!$K$2:$K$1839,'Pedidos Top10'!$A$2:$A$1839,A12) -> 72403.64 | E12: =SUMIFS('Pedidos Top10'!$L$2:$L$1839,'Pedidos Top10'!$A$2:$A$1839,A12) -> 15341.02 | F12: =SUMIFS('Pedidos Top10'!$AD$2:$AD$1839,'Pedidos Top10'!$A$2:$A$1839,A12) -> 17311.51 | G12: =F12-E12 -> 1970.49 | H12: =IF(E12=0,0,G12/E12) -> 0.12844583 | I12: =IF(D12=0,0,E12/D12) -> 0.21188189 | J12: =IF(D12=0,0,F12/D12) -> 0.23909723 | K12: =COUNTIFS('Pedidos Top10'!$A$2:$A$1839,A12,'Pedidos Top10'!$AG$2:$AG$1839,"PASSARO") -> 37 | L12: =IF(B12=0,0,K12/B12) -> 0.42528736 | M12: =IF(F12<=E12,0,1-E12/F12) -> 0.11382543
A13: SE | B13: =COUNTIFS('Pedidos Top10'!$A$2:$A$1839,A13) -> 97 | C13: =SUMIFS('Pedidos Top10'!$J$2:$J$1839,'Pedidos Top10'!$A$2:$A$1839,A13) -> 5118.27 | D13: =SUMIFS('Pedidos Top10'!$K$2:$K$1839,'Pedidos Top10'!$A$2:$A$1839,A13) -> 90462.68 | E13: =SUMIFS('Pedidos Top10'!$L$2:$L$1839,'Pedidos Top10'!$A$2:$A$1839,A13) -> 17913.36 | F13: =SUMIFS('Pedidos Top10'!$AD$2:$AD$1839,'Pedidos Top10'!$A$2:$A$1839,A13) -> 14694.3 | G13: =F13-E13 -> -3219.06 | H13: =IF(E13=0,0,G13/E13) -> -0.17970163 | I13: =IF(D13=0,0,E13/D13) -> 0.19801934 | J13: =IF(D13=0,0,F13/D13) -> 0.16243494 | K13: =COUNTIFS('Pedidos Top10'!$A$2:$A$1839,A13,'Pedidos Top10'!$AG$2:$AG$1839,"PASSARO") -> 72 | L13: =IF(B13=0,0,K13/B13) -> 0.74226804 | M13: =IF(F13<=E13,0,1-E13/F13) -> 0
A14: TOTAL | B14: =SUM(B5:B13) -> 1838 | C14: =SUM(C5:C13) -> 93805.65 | D14: =SUM(D5:D13) -> 1705949 | E14: =SUM(E5:E13) -> 331388.59 | F14: =SUM(F5:F13) -> 345898.93 | G14: =F14-E14 -> 14510.34 | H14: =IF(E14=0,0,G14/E14) -> 0.04378648 | I14: =IF(D14=0,0,E14/D14) -> 0.19425468 | J14: =IF(D14=0,0,F14/D14) -> 0.20276041 | K14: =SUM(K5:K13) -> 978 | L14: =IF(B14=0,0,K14/B14) -> 0.53210011 | M14: =IF(F14<=E14,0,1-E14/F14) -> 0.041949653
A17: Por transportadora atual (mesmos pedidos, Top 10 cidades)
A18: Transportadora | B18: Pedidos | C18: Peso total (kg) | D18: Valor NF total (R$) | E18: Frete atual (R$) | F18: Frete PASSARO (R$) | G18: Diferença (R$) | H18: Dif. % | I18: Ticket médio atual | J18: Ticket médio Passaro | K18: Pedidos em que Passaro é mais barata | L18: % pedidos Passaro mais barata | M18: R$/kg atual
A19: DOMINALOG | B19: =COUNTIFS('Pedidos Top10'!$D$2:$D$1839,A19) -> 1515 | C19: =SUMIFS('Pedidos Top10'!$J$2:$J$1839,'Pedidos Top10'!$D$2:$D$1839,A19) -> 80915.33 | D19: =SUMIFS('Pedidos Top10'!$K$2:$K$1839,'Pedidos Top10'!$D$2:$D$1839,A19) -> 1449016 | E19: =SUMIFS('Pedidos Top10'!$L$2:$L$1839,'Pedidos Top10'!$D$2:$D$1839,A19) -> 287729.07 | F19: =SUMIFS('Pedidos Top10'!$AD$2:$AD$1839,'Pedidos Top10'!$D$2:$D$1839,A19) -> 276618.41 | G19: =F19-E19 -> -11110.66 | H19: =IF(E19=0,0,G19/E19) -> -0.038615007 | I19: =IF(B19=0,0,E19/B19) -> 189.92018 | J19: =IF(B19=0,0,F19/B19) -> 182.58641 | K19: =COUNTIFS('Pedidos Top10'!$D$2:$D$1839,A19,'Pedidos Top10'!$AG$2:$AG$1839,"PASSARO") -> 952 | L19: =IF(B19=0,0,K19/B19) -> 0.62838284 | M19: =IF(C19=0,0,E19/C19) -> 3.5559278
A20: JADLOG | B20: =COUNTIFS('Pedidos Top10'!$D$2:$D$1839,A20) -> 193 | C20: =SUMIFS('Pedidos Top10'!$J$2:$J$1839,'Pedidos Top10'!$D$2:$D$1839,A20) -> 3725.4 | D20: =SUMIFS('Pedidos Top10'!$K$2:$K$1839,'Pedidos Top10'!$D$2:$D$1839,A20) -> 93526.9 | E20: =SUMIFS('Pedidos Top10'!$L$2:$L$1839,'Pedidos Top10'!$D$2:$D$1839,A20) -> 15437.82 | F20: =SUMIFS('Pedidos Top10'!$AD$2:$AD$1839,'Pedidos Top10'!$D$2:$D$1839,A20) -> 29194.04 | G20: =F20-E20 -> 13756.22 | H20: =IF(E20=0,0,G20/E20) -> 0.8910727 | I20: =IF(B20=0,0,E20/B20) -> 79.988705 | J20: =IF(B20=0,0,F20/B20) -> 151.26446 | K20: =COUNTIFS('Pedidos Top10'!$D$2:$D$1839,A20,'Pedidos Top10'!$AG$2:$AG$1839,"PASSARO") -> 0 | L20: =IF(B20=0,0,K20/B20) -> 0 | M20: =IF(C20=0,0,E20/C20) -> 4.1439362
A21: Bento Brasil | B21: =COUNTIFS('Pedidos Top10'!$D$2:$D$1839,A21) -> 100 | C21: =SUMIFS('Pedidos Top10'!$J$2:$J$1839,'Pedidos Top10'!$D$2:$D$1839,A21) -> 7362.73 | D21: =SUMIFS('Pedidos Top10'!$K$2:$K$1839,'Pedidos Top10'!$D$2:$D$1839,A21) -> 131134.43 | E21: =SUMIFS('Pedidos Top10'!$L$2:$L$1839,'Pedidos Top10'!$D$2:$D$1839,A21) -> 21243.1 | F21: =SUMIFS('Pedidos Top10'!$AD$2:$AD$1839,'Pedidos Top10'!$D$2:$D$1839,A21) -> 34564.99 | G21: =F21-E21 -> 13321.89 | H21: =IF(E21=0,0,G21/E21) -> 0.6271161 | I21: =IF(B21=0,0,E21/B21) -> 212.431 | J21: =IF(B21=0,0,F21/B21) -> 345.6499 | K21: =COUNTIFS('Pedidos Top10'!$D$2:$D$1839,A21,'Pedidos Top10'!$AG$2:$AG$1839,"PASSARO") -> 0 | L21: =IF(B21=0,0,K21/B21) -> 0 | M21: =IF(C21=0,0,E21/C21) -> 2.8852206
A22: Atual Cargas | B22: =COUNTIFS('Pedidos Top10'!$D$2:$D$1839,A22) -> 18 | C22: =SUMIFS('Pedidos Top10'!$J$2:$J$1839,'Pedidos Top10'!$D$2:$D$1839,A22) -> 998.13 | D22: =SUMIFS('Pedidos Top10'!$K$2:$K$1839,'Pedidos Top10'!$D$2:$D$1839,A22) -> 19241.74 | E22: =SUMIFS('Pedidos Top10'!$L$2:$L$1839,'Pedidos Top10'!$D$2:$D$1839,A22) -> 4141.87 | F22: =SUMIFS('Pedidos Top10'!$AD$2:$AD$1839,'Pedidos Top10'!$D$2:$D$1839,A22) -> 3131.26 | G22: =F22-E22 -> -1010.61 | H22: =IF(E22=0,0,G22/E22) -> -0.24399848 | I22: =IF(B22=0,0,E22/B22) -> 230.10389 | J22: =IF(B22=0,0,F22/B22) -> 173.95889 | K22: =COUNTIFS('Pedidos Top10'!$D$2:$D$1839,A22,'Pedidos Top10'!$AG$2:$AG$1839,"PASSARO") -> 15 | L22: =IF(B22=0,0,K22/B22) -> 0.83333333 | M22: =IF(C22=0,0,E22/C22) -> 4.1496298
A23: FORMATO TRANSPORTES | B23: =COUNTIFS('Pedidos Top10'!$D$2:$D$1839,A23) -> 10 | C23: =SUMIFS('Pedidos Top10'!$J$2:$J$1839,'Pedidos Top10'!$D$2:$D$1839,A23) -> 681.96 | D23: =SUMIFS('Pedidos Top10'!$K$2:$K$1839,'Pedidos Top10'!$D$2:$D$1839,A23) -> 10834.21 | E23: =SUMIFS('Pedidos Top10'!$L$2:$L$1839,'Pedidos Top10'!$D$2:$D$1839,A23) -> 2402.66 | F23: =SUMIFS('Pedidos Top10'!$AD$2:$AD$1839,'Pedidos Top10'!$D$2:$D$1839,A23) -> 2083.78 | G23: =F23-E23 -> -318.88 | H23: =IF(E23=0,0,G23/E23) -> -0.13271957 | I23: =IF(B23=0,0,E23/B23) -> 240.266 | J23: =IF(B23=0,0,F23/B23) -> 208.378 | K23: =COUNTIFS('Pedidos Top10'!$D$2:$D$1839,A23,'Pedidos Top10'!$AG$2:$AG$1839,"PASSARO") -> 9 | L23: =IF(B23=0,0,K23/B23) -> 0.9 | M23: =IF(C23=0,0,E23/C23) -> 3.5231685
A24: ZAFER | B24: =COUNTIFS('Pedidos Top10'!$D$2:$D$1839,A24) -> 2 | C24: =SUMIFS('Pedidos Top10'!$J$2:$J$1839,'Pedidos Top10'!$D$2:$D$1839,A24) -> 122.1 | D24: =SUMIFS('Pedidos Top10'!$K$2:$K$1839,'Pedidos Top10'!$D$2:$D$1839,A24) -> 2195.74 | E24: =SUMIFS('Pedidos Top10'!$L$2:$L$1839,'Pedidos Top10'!$D$2:$D$1839,A24) -> 434.07 | F24: =SUMIFS('Pedidos Top10'!$AD$2:$AD$1839,'Pedidos Top10'!$D$2:$D$1839,A24) -> 306.45 | G24: =F24-E24 -> -127.62 | H24: =IF(E24=0,0,G24/E24) -> -0.29400788 | I24: =IF(B24=0,0,E24/B24) -> 217.035 | J24: =IF(B24=0,0,F24/B24) -> 153.225 | K24: =COUNTIFS('Pedidos Top10'!$D$2:$D$1839,A24,'Pedidos Top10'!$AG$2:$AG$1839,"PASSARO") -> 2 | L24: =IF(B24=0,0,K24/B24) -> 1 | M24: =IF(C24=0,0,E24/C24) -> 3.5550369
A27: Por faixa de peso (onde a tabela Passaro é mais competitiva)
A28: Faixa de peso | B28: Pedidos | C28: Peso total (kg) | D28: Valor NF total (R$) | E28: Frete atual (R$) | F28: Frete PASSARO (R$) | G28: Diferença (R$) | H28: Dif. % | I28: Ticket médio atual | J28: Ticket médio Passaro | K28: Pedidos em que Passaro é mais barata | L28: % pedidos Passaro mais barata
A29: até 10 kg | B29: =COUNTIFS('Pedidos Top10'!$J$2:$J$1839,">"&0,'Pedidos Top10'!$J$2:$J$1839,"<="&10) -> 22 | C29: =SUMIFS('Pedidos Top10'!$J$2:$J$1839,'Pedidos Top10'!$J$2:$J$1839,">"&0,'Pedidos Top10'!$J$2:$J$1839,"<="&10) -> 132.93 | D29: =SUMIFS('Pedidos Top10'!$K$2:$K$1839,'Pedidos Top10'!$J$2:$J$1839,">"&0,'Pedidos Top10'!$J$2:$J$1839,"<="&10) -> 10157.63 | E29: =SUMIFS('Pedidos Top10'!$L$2:$L$1839,'Pedidos Top10'!$J$2:$J$1839,">"&0,'Pedidos Top10'!$J$2:$J$1839,"<="&10) -> 1364.48 | F29: =SUMIFS('Pedidos Top10'!$AD$2:$AD$1839,'Pedidos Top10'!$J$2:$J$1839,">"&0,'Pedidos Top10'!$J$2:$J$1839,"<="&10) -> 2929.13 | G29: =F29-E29 -> 1564.65 | H29: =IF(E29=0,0,G29/E29) -> 1.1467006 | I29: =IF(B29=0,0,E29/B29) -> 62.021818 | J29: =IF(B29=0,0,F29/B29) -> 133.14227 | K29: =COUNTIFS('Pedidos Top10'!$J$2:$J$1839,">"&0,'Pedidos Top10'!$J$2:$J$1839,"<="&10,'Pedidos Top10'!$AG$2:$AG$1839,"PASSARO") -> 0 | L29: =IF(B29=0,0,K29/B29) -> 0
A30: 10–30 kg | B30: =COUNTIFS('Pedidos Top10'!$J$2:$J$1839,">"&10,'Pedidos Top10'!$J$2:$J$1839,"<="&30) -> 528 | C30: =SUMIFS('Pedidos Top10'!$J$2:$J$1839,'Pedidos Top10'!$J$2:$J$1839,">"&10,'Pedidos Top10'!$J$2:$J$1839,"<="&30) -> 11946.07 | D30: =SUMIFS('Pedidos Top10'!$K$2:$K$1839,'Pedidos Top10'!$J$2:$J$1839,">"&10,'Pedidos Top10'!$J$2:$J$1839,"<="&30) -> 305423.88 | E30: =SUMIFS('Pedidos Top10'!$L$2:$L$1839,'Pedidos Top10'!$J$2:$J$1839,">"&10,'Pedidos Top10'!$J$2:$J$1839,"<="&30) -> 56316.91 | F30: =SUMIFS('Pedidos Top10'!$AD$2:$AD$1839,'Pedidos Top10'!$J$2:$J$1839,">"&10,'Pedidos Top10'!$J$2:$J$1839,"<="&30) -> 82983.09 | G30: =F30-E30 -> 26666.18 | H30: =IF(E30=0,0,G30/E30) -> 0.47350219 | I30: =IF(B30=0,0,E30/B30) -> 106.66081 | J30: =IF(B30=0,0,F30/B30) -> 157.16494 | K30: =COUNTIFS('Pedidos Top10'!$J$2:$J$1839,">"&10,'Pedidos Top10'!$J$2:$J$1839,"<="&30,'Pedidos Top10'!$AG$2:$AG$1839,"PASSARO") -> 120 | L30: =IF(B30=0,0,K30/B30) -> 0.22727273
A31: 30–50 kg | B31: =COUNTIFS('Pedidos Top10'!$J$2:$J$1839,">"&30,'Pedidos Top10'!$J$2:$J$1839,"<="&50) -> 533 | C31: =SUMIFS('Pedidos Top10'!$J$2:$J$1839,'Pedidos Top10'!$J$2:$J$1839,">"&30,'Pedidos Top10'!$J$2:$J$1839,"<="&50) -> 21075.53 | D31: =SUMIFS('Pedidos Top10'!$K$2:$K$1839,'Pedidos Top10'!$J$2:$J$1839,">"&30,'Pedidos Top10'!$J$2:$J$1839,"<="&50) -> 379477.45 | E31: =SUMIFS('Pedidos Top10'!$L$2:$L$1839,'Pedidos Top10'!$J$2:$J$1839,">"&30,'Pedidos Top10'!$J$2:$J$1839,"<="&50) -> 87391.89 | F31: =SUMIFS('Pedidos Top10'!$AD$2:$AD$1839,'Pedidos Top10'!$J$2:$J$1839,">"&30,'Pedidos Top10'!$J$2:$J$1839,"<="&50) -> 92274.79 | G31: =F31-E31 -> 4882.9 | H31: =IF(E31=0,0,G31/E31) -> 0.055873606 | I31: =IF(B31=0,0,E31/B31) -> 163.96227 | J31: =IF(B31=0,0,F31/B31) -> 173.12343 | K31: =COUNTIFS('Pedidos Top10'!$J$2:$J$1839,">"&30,'Pedidos Top10'!$J$2:$J$1839,"<="&50,'Pedidos Top10'!$AG$2:$AG$1839,"PASSARO") -> 333 | L31: =IF(B31=0,0,K31/B31) -> 0.62476548
A32: 50–70 kg | B32: =COUNTIFS('Pedidos Top10'!$J$2:$J$1839,">"&50,'Pedidos Top10'!$J$2:$J$1839,"<="&70) -> 456 | C32: =SUMIFS('Pedidos Top10'!$J$2:$J$1839,'Pedidos Top10'!$J$2:$J$1839,">"&50,'Pedidos Top10'!$J$2:$J$1839,"<="&70) -> 27589.22 | D32: =SUMIFS('Pedidos Top10'!$K$2:$K$1839,'Pedidos Top10'!$J$2:$J$1839,">"&50,'Pedidos Top10'!$J$2:$J$1839,"<="&70) -> 479901.08 | E32: =SUMIFS('Pedidos Top10'!$L$2:$L$1839,'Pedidos Top10'!$J$2:$J$1839,">"&50,'Pedidos Top10'!$J$2:$J$1839,"<="&70) -> 92754.76 | F32: =SUMIFS('Pedidos Top10'!$AD$2:$AD$1839,'Pedidos Top10'!$J$2:$J$1839,">"&50,'Pedidos Top10'!$J$2:$J$1839,"<="&70) -> 88503.04 | G32: =F32-E32 -> -4251.72 | H32: =IF(E32=0,0,G32/E32) -> -0.045838294 | I32: =IF(B32=0,0,E32/B32) -> 203.40956 | J32: =IF(B32=0,0,F32/B32) -> 194.08561 | K32: =COUNTIFS('Pedidos Top10'!$J$2:$J$1839,">"&50,'Pedidos Top10'!$J$2:$J$1839,"<="&70,'Pedidos Top10'!$AG$2:$AG$1839,"PASSARO") -> 300 | L32: =IF(B32=0,0,K32/B32) -> 0.65789474
A33: 70–100 kg | B33: =COUNTIFS('Pedidos Top10'!$J$2:$J$1839,">"&70,'Pedidos Top10'!$J$2:$J$1839,"<="&100) -> 109 | C33: =SUMIFS('Pedidos Top10'!$J$2:$J$1839,'Pedidos Top10'!$J$2:$J$1839,">"&70,'Pedidos Top10'!$J$2:$J$1839,"<="&100) -> 8662.37 | D33: =SUMIFS('Pedidos Top10'!$K$2:$K$1839,'Pedidos Top10'!$J$2:$J$1839,">"&70,'Pedidos Top10'!$J$2:$J$1839,"<="&100) -> 143464 | E33: =SUMIFS('Pedidos Top10'!$L$2:$L$1839,'Pedidos Top10'!$J$2:$J$1839,">"&70,'Pedidos Top10'!$J$2:$J$1839,"<="&100) -> 27897.63 | F33: =SUMIFS('Pedidos Top10'!$AD$2:$AD$1839,'Pedidos Top10'!$J$2:$J$1839,">"&70,'Pedidos Top10'!$J$2:$J$1839,"<="&100) -> 22871.45 | G33: =F33-E33 -> -5026.18 | H33: =IF(E33=0,0,G33/E33) -> -0.18016513 | I33: =IF(B33=0,0,E33/B33) -> 255.94156 | J33: =IF(B33=0,0,F33/B33) -> 209.82982 | K33: =COUNTIFS('Pedidos Top10'!$J$2:$J$1839,">"&70,'Pedidos Top10'!$J$2:$J$1839,"<="&100,'Pedidos Top10'!$AG$2:$AG$1839,"PASSARO") -> 87 | L33: =IF(B33=0,0,K33/B33) -> 0.79816514
A34: acima de 100 kg | B34: =COUNTIFS('Pedidos Top10'!$J$2:$J$1839,">"&100,'Pedidos Top10'!$J$2:$J$1839,"<="&1000000000) -> 190 | C34: =SUMIFS('Pedidos Top10'!$J$2:$J$1839,'Pedidos Top10'!$J$2:$J$1839,">"&100,'Pedidos Top10'!$J$2:$J$1839,"<="&1000000000) -> 24399.53 | D34: =SUMIFS('Pedidos Top10'!$K$2:$K$1839,'Pedidos Top10'!$J$2:$J$1839,">"&100,'Pedidos Top10'!$J$2:$J$1839,"<="&1000000000) -> 387525 | E34: =SUMIFS('Pedidos Top10'!$L$2:$L$1839,'Pedidos Top10'!$J$2:$J$1839,">"&100,'Pedidos Top10'!$J$2:$J$1839,"<="&1000000000) -> 65662.92 | F34: =SUMIFS('Pedidos Top10'!$AD$2:$AD$1839,'Pedidos Top10'!$J$2:$J$1839,">"&100,'Pedidos Top10'!$J$2:$J$1839,"<="&1000000000) -> 56337.43 | G34: =F34-E34 -> -9325.49 | H34: =IF(E34=0,0,G34/E34) -> -0.14202064 | I34: =IF(B34=0,0,E34/B34) -> 345.59432 | J34: =IF(B34=0,0,F34/B34) -> 296.51279 | K34: =COUNTIFS('Pedidos Top10'!$J$2:$J$1839,">"&100,'Pedidos Top10'!$J$2:$J$1839,"<="&1000000000,'Pedidos Top10'!$AG$2:$AG$1839,"PASSARO") -> 138 | L34: =IF(B34=0,0,K34/B34) -> 0.72631579
A37: Proposta 1 (com TRT/TDA) x Proposta 2 – mesmos pedidos
A38: UF | B38: Pedidos comparáveis | C38: Frete atual (R$) | D38: Passaro PROPOSTA 1 (R$) | E38: Passaro PROPOSTA 2 (R$) | F38: Variação P2 − P1 (R$) | G38: Variação % | H38: Dif. % PROPOSTA 1 x atual | I38: Dif. % PROPOSTA 2 x atual
A39: AL | B39: =COUNTIFS('Pedidos Top10'!$A$2:$A$1839,A39,'Pedidos Top10'!$AI$2:$AI$1839,"<>") -> 167 | C39: =SUMIFS('Pedidos Top10'!$L$2:$L$1839,'Pedidos Top10'!$A$2:$A$1839,A39,'Pedidos Top10'!$AI$2:$AI$1839,"<>") -> 29157.55 | D39: =SUMIFS('Pedidos Top10'!$AI$2:$AI$1839,'Pedidos Top10'!$A$2:$A$1839,A39) -> 31156.23 | E39: =SUMIFS('Pedidos Top10'!$AD$2:$AD$1839,'Pedidos Top10'!$A$2:$A$1839,A39,'Pedidos Top10'!$AI$2:$AI$1839,"<>") -> 25733.4 | F39: =E39-D39 -> -5422.83 | G39: =IF(D39=0,0,F39/D39) -> -0.17405283 | H39: =IF(C39=0,0,D39/C39-1) -> 0.068547597 | I39: =IF(C39=0,0,E39/C39-1) -> -0.11743614
A40: BA | B40: =COUNTIFS('Pedidos Top10'!$A$2:$A$1839,A40,'Pedidos Top10'!$AI$2:$AI$1839,"<>") -> 501 | C40: =SUMIFS('Pedidos Top10'!$L$2:$L$1839,'Pedidos Top10'!$A$2:$A$1839,A40,'Pedidos Top10'!$AI$2:$AI$1839,"<>") -> 87126.83 | D40: =SUMIFS('Pedidos Top10'!$AI$2:$AI$1839,'Pedidos Top10'!$A$2:$A$1839,A40) -> 81429.66 | E40: =SUMIFS('Pedidos Top10'!$AD$2:$AD$1839,'Pedidos Top10'!$A$2:$A$1839,A40,'Pedidos Top10'!$AI$2:$AI$1839,"<>") -> 65815.37 | F40: =E40-D40 -> -15614.29 | G40: =IF(D40=0,0,F40/D40) -> -0.19175188 | H40: =IF(C40=0,0,D40/C40-1) -> -0.065389387 | I40: =IF(C40=0,0,E40/C40-1) -> -0.24460272
A41: CE | B41: =COUNTIFS('Pedidos Top10'!$A$2:$A$1839,A41,'Pedidos Top10'!$AI$2:$AI$1839,"<>") -> 259 | C41: =SUMIFS('Pedidos Top10'!$L$2:$L$1839,'Pedidos Top10'!$A$2:$A$1839,A41,'Pedidos Top10'!$AI$2:$AI$1839,"<>") -> 49566.26 | D41: =SUMIFS('Pedidos Top10'!$AI$2:$AI$1839,'Pedidos Top10'!$A$2:$A$1839,A41) -> 71205.24 | E41: =SUMIFS('Pedidos Top10'!$AD$2:$AD$1839,'Pedidos Top10'!$A$2:$A$1839,A41,'Pedidos Top10'!$AI$2:$AI$1839,"<>") -> 61581.4 | F41: =E41-D41 -> -9623.84 | G41: =IF(D41=0,0,F41/D41) -> -0.13515635 | H41: =IF(C41=0,0,D41/C41-1) -> 0.43656673 | I41: =IF(C41=0,0,E41/C41-1) -> 0.24240562
A42: MA | B42: =COUNTIFS('Pedidos Top10'!$A$2:$A$1839,A42,'Pedidos Top10'!$AI$2:$AI$1839,"<>") -> 152 | C42: =SUMIFS('Pedidos Top10'!$L$2:$L$1839,'Pedidos Top10'!$A$2:$A$1839,A42,'Pedidos Top10'!$AI$2:$AI$1839,"<>") -> 27876.98 | D42: =SUMIFS('Pedidos Top10'!$AI$2:$AI$1839,'Pedidos Top10'!$A$2:$A$1839,A42) -> 54495.97 | E42: =SUMIFS('Pedidos Top10'!$AD$2:$AD$1839,'Pedidos Top10'!$A$2:$A$1839,A42,'Pedidos Top10'!$AI$2:$AI$1839,"<>") -> 48379.73 | F42: =E42-D42 -> -6116.24 | G42: =IF(D42=0,0,F42/D42) -> -0.11223289 | H42: =IF(C42=0,0,D42/C42-1) -> 0.95487352 | I42: =IF(C42=0,0,E42/C42-1) -> 0.73547242
A43: PB | B43: =COUNTIFS('Pedidos Top10'!$A$2:$A$1839,A43,'Pedidos Top10'!$AI$2:$AI$1839,"<>") -> 117 | C43: =SUMIFS('Pedidos Top10'!$L$2:$L$1839,'Pedidos Top10'!$A$2:$A$1839,A43,'Pedidos Top10'!$AI$2:$AI$1839,"<>") -> 20680.9 | D43: =SUMIFS('Pedidos Top10'!$AI$2:$AI$1839,'Pedidos Top10'!$A$2:$A$1839,A43) -> 23356.17 | E43: =SUMIFS('Pedidos Top10'!$AD$2:$AD$1839,'Pedidos Top10'!$A$2:$A$1839,A43,'Pedidos Top10'!$AI$2:$AI$1839,"<>") -> 18903.35 | F43: =E43-D43 -> -4452.82 | G43: =IF(D43=0,0,F43/D43) -> -0.19064855 | H43: =IF(C43=0,0,D43/C43-1) -> 0.12935946 | I43: =IF(C43=0,0,E43/C43-1) -> -0.085951288
A44: PE | B44: =COUNTIFS('Pedidos Top10'!$A$2:$A$1839,A44,'Pedidos Top10'!$AI$2:$AI$1839,"<>") -> 349 | C44: =SUMIFS('Pedidos Top10'!$L$2:$L$1839,'Pedidos Top10'!$A$2:$A$1839,A44,'Pedidos Top10'!$AI$2:$AI$1839,"<>") -> 61261.87 | D44: =SUMIFS('Pedidos Top10'!$AI$2:$AI$1839,'Pedidos Top10'!$A$2:$A$1839,A44) -> 67195.61 | E44: =SUMIFS('Pedidos Top10'!$AD$2:$AD$1839,'Pedidos Top10'!$A$2:$A$1839,A44,'Pedidos Top10'!$AI$2:$AI$1839,"<>") -> 55213.96 | F44: =E44-D44 -> -11981.65 | G44: =IF(D44=0,0,F44/D44) -> -0.17831001 | H44: =IF(C44=0,0,D44/C44-1) -> 0.096858617 | I44: =IF(C44=0,0,E44/C44-1) -> -0.098722256
A45: PI | B45: =COUNTIFS('Pedidos Top10'!$A$2:$A$1839,A45,'Pedidos Top10'!$AI$2:$AI$1839,"<>") -> 109 | C45: =SUMIFS('Pedidos Top10'!$L$2:$L$1839,'Pedidos Top10'!$A$2:$A$1839,A45,'Pedidos Top10'!$AI$2:$AI$1839,"<>") -> 22463.82 | D45: =SUMIFS('Pedidos Top10'!$AI$2:$AI$1839,'Pedidos Top10'!$A$2:$A$1839,A45) -> 43050.97 | E45: =SUMIFS('Pedidos Top10'!$AD$2:$AD$1839,'Pedidos Top10'!$A$2:$A$1839,A45,'Pedidos Top10'!$AI$2:$AI$1839,"<>") -> 38265.91 | F45: =E45-D45 -> -4785.06 | G45: =IF(D45=0,0,F45/D45) -> -0.11114872 | H45: =IF(C45=0,0,D45/C45-1) -> 0.91645811 | I45: =IF(C45=0,0,E45/C45-1) -> 0.70344625
A46: RN | B46: =COUNTIFS('Pedidos Top10'!$A$2:$A$1839,A46,'Pedidos Top10'!$AI$2:$AI$1839,"<>") -> 87 | C46: =SUMIFS('Pedidos Top10'!$L$2:$L$1839,'Pedidos Top10'!$A$2:$A$1839,A46,'Pedidos Top10'!$AI$2:$AI$1839,"<>") -> 15341.02 | D46: =SUMIFS('Pedidos Top10'!$AI$2:$AI$1839,'Pedidos Top10'!$A$2:$A$1839,A46) -> 20833.87 | E46: =SUMIFS('Pedidos Top10'!$AD$2:$AD$1839,'Pedidos Top10'!$A$2:$A$1839,A46,'Pedidos Top10'!$AI$2:$AI$1839,"<>") -> 17311.51 | F46: =E46-D46 -> -3522.36 | G46: =IF(D46=0,0,F46/D46) -> -0.16906892 | H46: =IF(C46=0,0,D46/C46-1) -> 0.35804986 | I46: =IF(C46=0,0,E46/C46-1) -> 0.12844583
A47: SE | B47: =COUNTIFS('Pedidos Top10'!$A$2:$A$1839,A47,'Pedidos Top10'!$AI$2:$AI$1839,"<>") -> 97 | C47: =SUMIFS('Pedidos Top10'!$L$2:$L$1839,'Pedidos Top10'!$A$2:$A$1839,A47,'Pedidos Top10'!$AI$2:$AI$1839,"<>") -> 17913.36 | D47: =SUMIFS('Pedidos Top10'!$AI$2:$AI$1839,'Pedidos Top10'!$A$2:$A$1839,A47) -> 17802.36 | E47: =SUMIFS('Pedidos Top10'!$AD$2:$AD$1839,'Pedidos Top10'!$A$2:$A$1839,A47,'Pedidos Top10'!$AI$2:$AI$1839,"<>") -> 14694.3 | F47: =E47-D47 -> -3108.06 | G47: =IF(D47=0,0,F47/D47) -> -0.17458696 | H47: =IF(C47=0,0,D47/C47-1) -> -0.0061964925 | I47: =IF(C47=0,0,E47/C47-1) -> -0.17970163
A48: TOTAL | B48: =SUM(B39:B47) -> 1838 | C48: =SUM(C39:C47) -> 331388.59 | D48: =SUM(D39:D47) -> 410526.08 | E48: =SUM(E39:E47) -> 345898.93 | F48: =E48-D48 -> -64627.15 | G48: =IF(D48=0,0,F48/D48) -> -0.1574252 | H48: =IF(C48=0,0,D48/C48-1) -> 0.23880572 | I48: =IF(C48=0,0,E48/C48-1) -> 0.04378648

Sheet Top10 Cidades
A1: UF | B1: Rank | C1: Cidade | D1: Pedidos | E1: Peso total (kg) | F1: Frete atual (R$) | G1: Frete PASSARO (R$) | H1: Diferença (R$) | I1: Dif. % | J1: Ticket médio atual | K1: Ticket médio Passaro | L1: R$/kg atual | M1: R$/kg Passaro | N1: Prazo Passaro (dias) | O1: % pedidos Passaro mais barata | P1: Transportadora principal hoje | Q1: Transportadoras atuantes | R1: Veredito
A2: AL | B2: 1 | C2: MACEIO | D2: =COUNTIFS('Pedidos Top10'!$A$2:$A$1839,A2,'Pedidos Top10'!$C$2:$C$1839,C2) -> 110 | E2: =SUMIFS('Pedidos Top10'!$J$2:$J$1839,'Pedidos Top10'!$A$2:$A$1839,A2,'Pedidos Top10'!$C$2:$C$1839,C2) -> 5274.84 | F2: =SUMIFS('Pedidos Top10'!$L$2:$L$1839,'Pedidos Top10'!$A$2:$A$1839,A2,'Pedidos Top10'!$C$2:$C$1839,C2) -> 18085.24 | G2: =SUMIFS('Pedidos Top10'!$AD$2:$AD$1839,'Pedidos Top10'!$A$2:$A$1839,A2,'Pedidos Top10'!$C$2:$C$1839,C2) -> 15398.57 | H2: =G2-F2 -> -2686.67 | I2: =IF(F2=0,0,H2/F2) -> -0.14855595 | J2: =IF(D2=0,0,F2/D2) -> 164.41127 | K2: =IF(D2=0,0,G2/D2) -> 139.987 | L2: =IF(E2=0,0,F2/E2) -> 3.4285855 | M2: =IF(E2=0,0,G2/E2) -> 2.9192487 | N2: 8 | O2: =IF(D2=0,0,COUNTIFS('Pedidos Top10'!$A$2:$A$1839,A2,'Pedidos Top10'!$C$2:$C$1839,C2,'Pedidos Top10'!$AG$2:$AG$1839,"PASSARO")/D2) -> 0.78181818 | P2: DOMINALOG | Q2: DOMINALOG (90), JADLOG (19), ZAFER (1) | R2: =IF(I2<=-0.05,"Passaro mais barata",IF(I2<0.05,"Empate técnico (±5%)","Passaro mais cara")) -> Passaro mais barata
A3: AL | B3: 2 | C3: ARAPIRACA | D3: =COUNTIFS('Pedidos Top10'!$A$2:$A$1839,A3,'Pedidos Top10'!$C$2:$C$1839,C3) -> 26 | E3: =SUMIFS('Pedidos Top10'!$J$2:$J$1839,'Pedidos Top10'!$A$2:$A$1839,A3,'Pedidos Top10'!$C$2:$C$1839,C3) -> 921.45 | F3: =SUMIFS('Pedidos Top10'!$L$2:$L$1839,'Pedidos Top10'!$A$2:$A$1839,A3,'Pedidos Top10'!$C$2:$C$1839,C3) -> 3849.53 | G3: =SUMIFS('Pedidos Top10'!$AD$2:$AD$1839,'Pedidos Top10'!$A$2:$A$1839,A3,'Pedidos Top10'!$C$2:$C$1839,C3) -> 4064.41 | H3: =G3-F3 -> 214.88 | I3: =IF(F3=0,0,H3/F3) -> 0.055819801 | J3: =IF(D3=0,0,F3/D3) -> 148.05885 | K3: =IF(D3=0,0,G3/D3) -> 156.32346 | L3: =IF(E3=0,0,F3/E3) -> 4.1776873 | M3: =IF(E3=0,0,G3/E3) -> 4.410885 | N3: 10 | O3: =IF(D3=0,0,COUNTIFS('Pedidos Top10'!$A$2:$A$1839,A3,'Pedidos Top10'!$C$2:$C$1839,C3,'Pedidos Top10'!$AG$2:$AG$1839,"PASSARO")/D3) -> 0.34615385 | P3: DOMINALOG | Q3: DOMINALOG (22), JADLOG (4) | R3: =IF(I3<=-0.05,"Passaro mais barata",IF(I3<0.05,"Empate técnico (±5%)","Passaro mais cara")) -> Passaro mais cara
A4: AL | B4: 3 | C4: MARECHAL DEODORO | D4: =COUNTIFS('Pedidos Top10'!$A$2:$A$1839,A4,'Pedidos Top10'!$C$2:$C$1839,C4) -> 6 | E4: =SUMIFS('Pedidos Top10'!$J$2:$J$1839,'Pedidos Top10'!$A$2:$A$1839,A4,'Pedidos Top10'!$C$2:$C$1839,C4) -> 427 | F4: =SUMIFS('Pedidos Top10'!$L$2:$L$1839,'Pedidos Top10'!$A$2:$A$1839,A4,'Pedidos Top10'!$C$2:$C$1839,C4) -> 1414.13 | G4: =SUMIFS('Pedidos Top10'!$AD$2:$AD$1839,'Pedidos Top10'!$A$2:$A$1839,A4,'Pedidos Top10'!$C$2:$C$1839,C4) -> 1161.84 | H4: =G4-F4 -> -252.29 | I4: =IF(F4=0,0,H4/F4) -> -0.17840651 | J4: =IF(D4=0,0,F4/D4) -> 235.68833 | K4: =IF(D4=0,0,G4/D4) -> 193.64 | L4: =IF(E4=0,0,F4/E4) -> 3.3117799 | M4: =IF(E4=0,0,G4/E4) -> 2.7209368 | N4: 10 | O4: =IF(D4=0,0,COUNTIFS('Pedidos Top10'!$A$2:$A$1839,A4,'Pedidos Top10'!$C$2:$C$1839,C4,'Pedidos Top10'!$AG$2:$AG$1839,"PASSARO")/D4) -> 0.5 | P4: DOMINALOG | Q4: DOMINALOG (6) | R4: =IF(I4<=-0.05,"Passaro mais barata",IF(I4<0.05,"Empate técnico (±5%)","Passaro mais cara")) -> Passaro mais barata
A5: AL | B5: 4 | C5: RIO LARGO | D5: =COUNTIFS('Pedidos Top10'!$A$2:$A$1839,A5,'Pedidos Top10'!$C$2:$C$1839,C5) -> 6 | E5: =SUMIFS('Pedidos Top10'!$J$2:$J$1839,'Pedidos Top10'!$A$2:$A$1839,A5,'Pedidos Top10'!$C$2:$C$1839,C5) -> 277.41 | F5: =SUMIFS('Pedidos Top10'!$L$2:$L$1839,'Pedidos Top10'!$A$2:$A$1839,A5,'Pedidos Top10'!$C$2:$C$1839,C5) -> 1067.67 | G5: =SUMIFS('Pedidos Top10'!$AD$2:$AD$1839,'Pedidos Top10'!$A$2:$A$1839,A5,'Pedidos Top10'!$C$2:$C$1839,C5) -> 821.11 | H5: =G5-F5 -> -246.56 | I5: =IF(F5=0,0,H5/F5) -> -0.23093278 | J5: =IF(D5=0,0,F5/D5) -> 177.945 | K5: =IF(D5=0,0,G5/D5) -> 136.85167 | L5: =IF(E5=0,0,F5/E5) -> 3.8487077 | M5: =IF(E5=0,0,G5/E5) -> 2.9599149 | N5: 8 | O5: =IF(D5=0,0,COUNTIFS('Pedidos Top10'!$A$2:$A$1839,A5,'Pedidos Top10'!$C$2:$C$1839,C5,'Pedidos Top10'!$AG$2:$AG$1839,"PASSARO")/D5) -> 1 | P5: DOMINALOG | Q5: DOMINALOG (6) | R5: =IF(I5<=-0.05,"Passaro mais barata",IF(I5<0.05,"Empate técnico (±5%)","Passaro mais cara")) -> Passaro mais barata
A6: AL | B6: 5 | C6: MARAGOGI | D6: =COUNTIFS('Pedidos Top10'!$A$2:$A$1839,A6,'Pedidos Top10'!$C$2:$C$1839,C6) -> 4 | E6: =SUMIFS('Pedidos Top10'!$J$2:$J$1839,'Pedidos Top10'!$A$2:$A$1839,A6,'Pedidos Top10'!$C$2:$C$1839,C6) -> 134.2 | F6: =SUMIFS('Pedidos Top10'!$L$2:$L$1839,'Pedidos Top10'!$A$2:$A$1839,A6,'Pedidos Top10'!$C$2:$C$1839,C6) -> 652.13 | G6: =SUMIFS('Pedidos Top10'!$AD$2:$AD$1839,'Pedidos Top10'!$A$2:$A$1839,A6,'Pedidos Top10'!$C$2:$C$1839,C6) -> 720.53 | H6: =G6-F6 -> 68.4 | I6: =IF(F6=0,0,H6/F6) -> 0.10488706 | J6: =IF(D6=0,0,F6/D6) -> 163.0325 | K6: =IF(D6=0,0,G6/D6) -> 180.1325 | L6: =IF(E6=0,0,F6/E6) -> 4.859389 | M6: =IF(E6=0,0,G6/E6) -> 5.369076 | N6: 13 | O6: =IF(D6=0,0,COUNTIFS('Pedidos Top10'!$A$2:$A$1839,A6,'Pedidos Top10'!$C$2:$C$1839,C6,'Pedidos Top10'!$AG$2:$AG$1839,"PASSARO")/D6) -> 0.25 | P6: DOMINALOG | Q6: DOMINALOG (4) | R6: =IF(I6<=-0.05,"Passaro mais barata",IF(I6<0.05,"Empate técnico (±5%)","Passaro mais cara")) -> Passaro mais cara
A7: AL | B7: 6 | C7: DELMIRO GOUVEIA | D7: =COUNTIFS('Pedidos Top10'!$A$2:$A$1839,A7,'Pedidos Top10'!$C$2:$C$1839,C7) -> 3 | E7: =SUMIFS('Pedidos Top10'!$J$2:$J$1839,'Pedidos Top10'!$A$2:$A$1839,A7,'Pedidos Top10'!$C$2:$C$1839,C7) -> 349.7 | F7: =SUMIFS('Pedidos Top10'!$L$2:$L$1839,'Pedidos Top10'!$A$2:$A$1839,A7,'Pedidos Top10'!$C$2:$C$1839,C7) -> 1136.84 | G7: =SUMIFS('Pedidos Top10'!$AD$2:$AD$1839,'Pedidos Top10'!$A$2:$A$1839,A7,'Pedidos Top10'!$C$2:$C$1839,C7) -> 968.53 | H7: =G7-F7 -> -168.31 | I7: =IF(F7=0,0,H7/F7) -> -0.14805074 | J7: =IF(D7=0,0,F7/D7) -> 378.94667 | K7: =IF(D7=0,0,G7/D7) -> 322.84333 | L7: =IF(E7=0,0,F7/E7) -> 3.2509008 | M7: =IF(E7=0,0,G7/E7) -> 2.7696025 | N7: 13 | O7: =IF(D7=0,0,COUNTIFS('Pedidos Top10'!$A$2:$A$1839,A7,'Pedidos Top10'!$C$2:$C$1839,C7,'Pedidos Top10'!$AG$2:$AG$1839,"PASSARO")/D7) -> 0.66666667 | P7: DOMINALOG | Q7: DOMINALOG (3) | R7: =IF(I7<=-0.05,"Passaro mais barata",IF(I7<0.05,"Empate técnico (±5%)","Passaro mais cara")) -> Passaro mais barata
A8: AL | B8: 7 | C8: PIRANHAS | D8: =COUNTIFS('Pedidos Top10'!$A$2:$A$1839,A8,'Pedidos Top10'!$C$2:$C$1839,C8) -> 3 | E8: =SUMIFS('Pedidos Top10'!$J$2:$J$1839,'Pedidos Top10'!$A$2:$A$1839,A8,'Pedidos Top10'!$C$2:$C$1839,C8) -> 203.78 | F8: =SUMIFS('Pedidos Top10'!$L$2:$L$1839,'Pedidos Top10'!$A$2:$A$1839,A8,'Pedidos Top10'!$C$2:$C$1839,C8) -> 862.25 | G8: =SUMIFS('Pedidos Top10'!$AD$2:$AD$1839,'Pedidos Top10'!$A$2:$A$1839,A8,'Pedidos Top10'!$C$2:$C$1839,C8) -> 694.83 | H8: =G8-F8 -> -167.42 | I8: =IF(F8=0,0,H8/F8) -> -0.19416643 | J8: =IF(D8=0,0,F8/D8) -> 287.41667 | K8: =IF(D8=0,0,G8/D8) -> 231.61 | L8: =IF(E8=0,0,F8/E8) -> 4.2312788 | M8: =IF(E8=0,0,G8/E8) -> 3.4097065 | N8: 13 | O8: =IF(D8=0,0,COUNTIFS('Pedidos Top10'!$A$2:$A$1839,A8,'Pedidos Top10'!$C$2:$C$1839,C8,'Pedidos Top10'!$AG$2:$AG$1839,"PASSARO")/D8) -> 1 | P8: DOMINALOG | Q8: DOMINALOG (3) | R8: =IF(I8<=-0.05,"Passaro mais barata",IF(I8<0.05,"Empate técnico (±5%)","Passaro mais cara")) -> Passaro mais barata
A9: AL | B9: 8 | C9: SAO MIGUEL DOS MILAGRES | D9: =COUNTIFS('Pedidos Top10'!$A$2:$A$1839,A9,'Pedidos Top10'!$C$2:$C$1839,C9) -> 3 | E9: =SUMIFS('Pedidos Top10'!$J$2:$J$1839,'Pedidos Top10'!$A$2:$A$1839,A9,'Pedidos Top10'!$C$2:$C$1839,C9) -> 230.38 | F9: =SUMIFS('Pedidos Top10'!$L$2:$L$1839,'Pedidos Top10'!$A$2:$A$1839,A9,'Pedidos Top10'!$C$2:$C$1839,C9) -> 850.42 | G9: =SUMIFS('Pedidos Top10'!$AD$2:$AD$1839,'Pedidos Top10'!$A$2:$A$1839,A9,'Pedidos Top10'!$C$2:$C$1839,C9) -> 701.54 | H9: =G9-F9 -> -148.88 | I9: =IF(F9=0,0,H9/F9) -> -0.17506644 | J9: =IF(D9=0,0,F9/D9) -> 283.47333 | K9: =IF(D9=0,0,G9/D9) -> 233.84667 | L9: =IF(E9=0,0,F9/E9) -> 3.6913795 | M9: =IF(E9=0,0,G9/E9) -> 3.0451428 | N9: 13 | O9: =IF(D9=0,0,COUNTIFS('Pedidos Top10'!$A$2:$A$1839,A9,'Pedidos Top10'!$C$2:$C$1839,C9,'Pedidos Top10'!$AG$2:$AG$1839,"PASSARO")/D9) -> 0.66666667 | P9: DOMINALOG | Q9: DOMINALOG (2), FORMATO TRANSPORTES (1) | R9: =IF(I9<=-0.05,"Passaro mais barata",IF(I9<0.05,"Empate técnico (±5%)","Passaro mais cara")) -> Passaro mais barata
A10: AL | B10: 9 | C10: PORTO CALVO | D10: =COUNTIFS('Pedidos Top10'!$A$2:$A$1839,A10,'Pedidos Top10'!$C$2:$C$1839,C10) -> 3 | E10: =SUMIFS('Pedidos Top10'!$J$2:$J$1839,'Pedidos Top10'!$A$2:$A$1839,A10,'Pedidos Top10'!$C$2:$C$1839,C10) -> 186.48 | F10: =SUMIFS('Pedidos Top10'!$L$2:$L$1839,'Pedidos Top10'!$A$2:$A$1839,A10,'Pedidos Top10'!$C$2:$C$1839,C10) -> 686.94 | G10: =SUMIFS('Pedidos Top10'!$AD$2:$AD$1839,'Pedidos Top10'!$A$2:$A$1839,A10,'Pedidos Top10'!$C$2:$C$1839,C10) -> 633.64 | H10: =G10-F10 -> -53.3 | I10: =IF(F10=0,0,H10/F10) -> -0.077590474 | J10: =IF(D10=0,0,F10/D10) -> 228.98 | K10: =IF(D10=0,0,G10/D10) -> 211.21333 | L10: =IF(E10=0,0,F10/E10) -> 3.6837194 | M10: =IF(E10=0,0,G10/E10) -> 3.3978979 | N10: 13 | O10: =IF(D10=0,0,COUNTIFS('Pedidos Top10'!$A$2:$A$1839,A10,'Pedidos Top10'!$C$2:$C$1839,C10,'Pedidos Top10'!$AG$2:$AG$1839,"PASSARO")/D10) -> 0.66666667 | P10: DOMINALOG | Q10: DOMINALOG (3) | R10: =IF(I10<=-0.05,"Passaro mais barata",IF(I10<0.05,"Empate técnico (±5%)","Passaro mais cara")) -> Passaro mais barata
A11: AL | B11: 10 | C11: SAO LUIS DO QUITUNDE | D11: =COUNTIFS('Pedidos Top10'!$A$2:$A$1839,A11,'Pedidos Top10'!$C$2:$C$1839,C11) -> 3 | E11: =SUMIFS('Pedidos Top10'!$J$2:$J$1839,'Pedidos Top10'!$A$2:$A$1839,A11,'Pedidos Top10'!$C$2:$C$1839,C11) -> 118.7 | F11: =SUMIFS('Pedidos Top10'!$L$2:$L$1839,'Pedidos Top10'!$A$2:$A$1839,A11,'Pedidos Top10'!$C$2:$C$1839,C11) -> 552.4 | G11: =SUMIFS('Pedidos Top10'!$AD$2:$AD$1839,'Pedidos Top10'!$A$2:$A$1839,A11,'Pedidos Top10'!$C$2:$C$1839,C11) -> 568.4 | H11: =G11-F11 -> 16 | I11: =IF(F11=0,0,H11/F11) -> 0.028964518 | J11: =IF(D11=0,0,F11/D11) -> 184.13333 | K11: =IF(D11=0,0,G11/D11) -> 189.46667 | L11: =IF(E11=0,0,F11/E11) -> 4.6537489 | M11: =IF(E11=0,0,G11/E11) -> 4.7885425 | N11: 13 | O11: =IF(D11=0,0,COUNTIFS('Pedidos Top10'!$A$2:$A$1839,A11,'Pedidos Top10'!$C$2:$C$1839,C11,'Pedidos Top10'!$AG$2:$AG$1839,"PASSARO")/D11) -> 0.33333333 | P11: DOMINALOG | Q11: DOMINALOG (3) | R11: =IF(I11<=-0.05,"Passaro mais barata",IF(I11<0.05,"Empate técnico (±5%)","Passaro mais cara")) -> Empate técnico (±5%)
A12: BA | B12: 1 | C12: SALVADOR | D12: =COUNTIFS('Pedidos Top10'!$A$2:$A$1839,A12,'Pedidos Top10'!$C$2:$C$1839,C12) -> 296 | E12: =SUMIFS('Pedidos Top10'!$J$2:$J$1839,'Pedidos Top10'!$A$2:$A$1839,A12,'Pedidos Top10'!$C$2:$C$1839,C12) -> 15122.53 | F12: =SUMIFS('Pedidos Top10'!$L$2:$L$1839,'Pedidos Top10'!$A$2:$A$1839,A12,'Pedidos Top10'!$C$2:$C$1839,C12) -> 47672.61 | G12: =SUMIFS('Pedidos Top10'!$AD$2:$AD$1839,'Pedidos Top10'!$A$2:$A$1839,A12,'Pedidos Top10'!$C$2:$C$1839,C12) -> 36586.8 | H12: =G12-F12 -> -11085.81 | I12: =IF(F12=0,0,H12/F12) -> -0.23254045 | J12: =IF(D12=0,0,F12/D12) -> 161.05611 | K12: =IF(D12=0,0,G12/D12) -> 123.60405 | L12: =IF(E12=0,0,F12/E12) -> 3.1524229 | M12: =IF(E12=0,0,G12/E12) -> 2.4193571 | N12: 6 | O12: =IF(D12=0,0,COUNTIFS('Pedidos Top10'!$A$2:$A$1839,A12,'Pedidos Top10'!$C$2:$C$1839,C12,'Pedidos Top10'!$AG$2:$AG$1839,"PASSARO")/D12) -> 0.88175676 | P12: DOMINALOG | Q12: DOMINALOG (261), JADLOG (33), Atual Cargas (2) | R12: =IF(I12<=-0.05,"Passaro mais barata",IF(I12<0.05,"Empate técnico (±5%)","Passaro mais cara")) -> Passaro mais barata
A13: BA | B13: 2 | C13: FEIRA DE SANTANA | D13: =COUNTIFS('Pedidos Top10'!$A$2:$A$1839,A13,'Pedidos Top10'!$C$2:$C$1839,C13) -> 42 | E13: =SUMIFS('Pedidos Top10'!$J$2:$J$1839,'Pedidos Top10'!$A$2:$A$1839,A13,'Pedidos Top10'!$C$2:$C$1839,C13) -> 2552.96 | F13: =SUMIFS('Pedidos Top10'!$L$2:$L$1839,'Pedidos Top10'!$A$2:$A$1839,A13,'Pedidos Top10'!$C$2:$C$1839,C13) -> 8347.68 | G13: =SUMIFS('Pedidos Top10'!$AD$2:$AD$1839,'Pedidos Top10'!$A$2:$A$1839,A13,'Pedidos Top10'!$C$2:$C$1839,C13) -> 5453.87 | H13: =G13-F13 -> -2893.81 | I13: =IF(F13=0,0,H13/F13) -> -0.34666039 | J13: =IF(D13=0,0,F13/D13) -> 198.75429 | K13: =IF(D13=0,0,G13/D13) -> 129.85405 | L13: =IF(E13=0,0,F13/E13) -> 3.2698045 | M13: =IF(E13=0,0,G13/E13) -> 2.1362928 | N13: 5 | O13: =IF(D13=0,0,COUNTIFS('Pedidos Top10'!$A$2:$A$1839,A13,'Pedidos Top10'!$C$2:$C$1839,C13,'Pedidos Top10'!$AG$2:$AG$1839,"PASSARO")/D13) -> 0.9047619 | P13: DOMINALOG | Q13: DOMINALOG (39), JADLOG (3) | R13: =IF(I13<=-0.05,"Passaro mais barata",IF(I13<0.05,"Empate técnico (±5%)","Passaro mais cara")) -> Passaro mais barata
... A91: SE | B91: 10 | C91: CRISTINAPOLIS | D91: =COUNTIFS('Pedidos Top10'!$A$2:$A$1839,A91,'Pedidos Top10'!$C$2:$C$1839,C91) -> 2 | E91: =SUMIFS('Pedidos Top10'!$J$2:$J$1839,'Pedidos Top10'!$A$2:$A$1839,A91,'Pedidos Top10'!$C$2:$C$1839,C91) -> 223.9 | F91: =SUMIFS('Pedidos Top10'!$L$2:$L$1839,'Pedidos Top10'!$A$2:$A$1839,A91,'Pedidos Top10'!$C$2:$C$1839,C91) -> 712.9 | G91: =SUMIFS('Pedidos Top10'!$AD$2:$AD$1839,'Pedidos Top10'!$A$2:$A$1839,A91,'Pedidos Top10'!$C$2:$C$1839,C91) -> 559.48 | H91: =G91-F91 -> -153.42 | I91: =IF(F91=0,0,H91/F91) -> -0.2152055 | J91: =IF(D91=0,0,F91/D91) -> 356.45 | K91: =IF(D91=0,0,G91/D91) -> 279.74 | L91: =IF(E91=0,0,F91/E91) -> 3.1840107 | M91: =IF(E91=0,0,G91/E91) -> 2.4987941 | N91: 10 | O91: =IF(D91=0,0,COUNTIFS('Pedidos Top10'!$A$2:$A$1839,A91,'Pedidos Top10'!$C$2:$C$1839,C91,'Pedidos Top10'!$AG$2:$AG$1839,"PASSARO")/D91) -> 1 | P91: DOMINALOG | Q91: DOMINALOG (2) | R91: =IF(I91<=-0.05,"Passaro mais barata",IF(I91<0.05,"Empate técnico (±5%)","Passaro mais cara")) -> Passaro mais barata

Sheet Concorrência Praças
A1: UF | B1: Rank cidade | C1: Cidade | D1: Transportadora atual | E1: Pedidos | F1: Share da praça | G1: Peso total (kg) | H1: Frete atual (R$) | I1: Frete PASSARO nos mesmos pedidos (R$) | J1: Diferença (R$) | K1: Dif. % | L1: Ticket médio atual | M1: Ticket médio Passaro | N1: R$/kg atual | O1: R$/kg Passaro | P1: % pedidos Passaro mais barata | Q1: Leitura
A2: AL | B2: 1 | C2: MACEIO | D2: DOMINALOG | E2: =COUNTIFS('Pedidos Top10'!$A$2:$A$1839,A2,'Pedidos Top10'!$C$2:$C$1839,C2,'Pedidos Top10'!$D$2:$D$1839,D2) -> 90 | F2: =E2/COUNTIFS('Pedidos Top10'!$A$2:$A$1839,A2,'Pedidos Top10'!$C$2:$C$1839,C2) -> 0.81818182 | G2: =SUMIFS('Pedidos Top10'!$J$2:$J$1839,'Pedidos Top10'!$A$2:$A$1839,A2,'Pedidos Top10'!$C$2:$C$1839,C2,'Pedidos Top10'!$D$2:$D$1839,D2) -> 4819.05 | H2: =SUMIFS('Pedidos Top10'!$L$2:$L$1839,'Pedidos Top10'!$A$2:$A$1839,A2,'Pedidos Top10'!$C$2:$C$1839,C2,'Pedidos Top10'!$D$2:$D$1839,D2) -> 16352.14 | I2: =SUMIFS('Pedidos Top10'!$AD$2:$AD$1839,'Pedidos Top10'!$A$2:$A$1839,A2,'Pedidos Top10'!$C$2:$C$1839,C2,'Pedidos Top10'!$D$2:$D$1839,D2) -> 12990.97 | J2: =I2-H2 -> -3361.17 | K2: =IF(H2=0,0,J2/H2) -> -0.20554924 | L2: =IF(E2=0,0,H2/E2) -> 181.69044 | M2: =IF(E2=0,0,I2/E2) -> 144.34411 | N2: =IF(G2=0,0,H2/G2) -> 3.393229 | O2: =IF(G2=0,0,I2/G2) -> 2.6957533 | P2: =IF(E2=0,0,COUNTIFS('Pedidos Top10'!$A$2:$A$1839,A2,'Pedidos Top10'!$C$2:$C$1839,C2,'Pedidos Top10'!$D$2:$D$1839,D2,'Pedidos Top10'!$AG$2:$AG$1839,"PASSARO")/E2) -> 0.94444444 | Q2: =IF(K2<=-0.05,"Passaro compete: "&TEXT(-K2,"0%")&" abaixo de "&D2,IF(K2<0.05,"Empate técnico com "&D2,D2&" é "&TEXT(1-H2/I2,"0%")&" mais barata que a Passaro")) -> Passaro compete: 21% abaixo de DOMINALOG
A3: AL | B3: 1 | C3: MACEIO | D3: JADLOG | E3: =COUNTIFS('Pedidos Top10'!$A$2:$A$1839,A3,'Pedidos Top10'!$C$2:$C$1839,C3,'Pedidos Top10'!$D$2:$D$1839,D3) -> 19 | F3: =E3/COUNTIFS('Pedidos Top10'!$A$2:$A$1839,A3,'Pedidos Top10'!$C$2:$C$1839,C3) -> 0.17272727 | G3: =SUMIFS('Pedidos Top10'!$J$2:$J$1839,'Pedidos Top10'!$A$2:$A$1839,A3,'Pedidos Top10'!$C$2:$C$1839,C3,'Pedidos Top10'!$D$2:$D$1839,D3) -> 388.99 | H3: =SUMIFS('Pedidos Top10'!$L$2:$L$1839,'Pedidos Top10'!$A$2:$A$1839,A3,'Pedidos Top10'!$C$2:$C$1839,C3,'Pedidos Top10'!$D$2:$D$1839,D3) -> 1557.14 | I3: =SUMIFS('Pedidos Top10'!$AD$2:$AD$1839,'Pedidos Top10'!$A$2:$A$1839,A3,'Pedidos Top10'!$C$2:$C$1839,C3,'Pedidos Top10'!$D$2:$D$1839,D3) -> 2262.53 | J3: =I3-H3 -> 705.39 | K3: =IF(H3=0,0,J3/H3) -> 0.45300358 | L3: =IF(E3=0,0,H3/E3) -> 81.954737 | M3: =IF(E3=0,0,I3/E3) -> 119.08053 | N3: =IF(G3=0,0,H3/G3) -> 4.0030335 | O3: =IF(G3=0,0,I3/G3) -> 5.816422 | P3: =IF(E3=0,0,COUNTIFS('Pedidos Top10'!$A$2:$A$1839,A3,'Pedidos Top10'!$C$2:$C$1839,C3,'Pedidos Top10'!$D$2:$D$1839,D3,'Pedidos Top10'!$AG$2:$AG$1839,"PASSARO")/E3) -> 0 | Q3: =IF(K3<=-0.05,"Passaro compete: "&TEXT(-K3,"0%")&" abaixo de "&D3,IF(K3<0.05,"Empate técnico com "&D3,D3&" é "&TEXT(1-H3/I3,"0%")&" mais barata que a Passaro")) -> JADLOG é 31% mais barata que a Passaro
A4: AL | B4: 1 | C4: MACEIO | D4: ZAFER | E4: =COUNTIFS('Pedidos Top10'!$A$2:$A$1839,A4,'Pedidos Top10'!$C$2:$C$1839,C4,'Pedidos Top10'!$D$2:$D$1839,D4) -> 1 | F4: =E4/COUNTIFS('Pedidos Top10'!$A$2:$A$1839,A4,'Pedidos Top10'!$C$2:$C$1839,C4) -> 0.0090909091 | G4: =SUMIFS('Pedidos Top10'!$J$2:$J$1839,'Pedidos Top10'!$A$2:$A$1839,A4,'Pedidos Top10'!$C$2:$C$1839,C4,'Pedidos Top10'!$D$2:$D$1839,D4) -> 66.8 | H4: =SUMIFS('Pedidos Top10'!$L$2:$L$1839,'Pedidos Top10'!$A$2:$A$1839,A4,'Pedidos Top10'!$C$2:$C$1839,C4,'Pedidos Top10'!$D$2:$D$1839,D4) -> 175.96 | I4: =SUMIFS('Pedidos Top10'!$AD$2:$AD$1839,'Pedidos Top10'!$A$2:$A$1839,A4,'Pedidos Top10'!$C$2:$C$1839,C4,'Pedidos Top10'!$D$2:$D$1839,D4) -> 145.07 | J4: =I4-H4 -> -30.89 | K4: =IF(H4=0,0,J4/H4) -> -0.17555126 | L4: =IF(E4=0,0,H4/E4) -> 175.96 | M4: =IF(E4=0,0,I4/E4) -> 145.07 | N4: =IF(G4=0,0,H4/G4) -> 2.6341317 | O4: =IF(G4=0,0,I4/G4) -> 2.1717066 | P4: =IF(E4=0,0,COUNTIFS('Pedidos Top10'!$A$2:$A$1839,A4,'Pedidos Top10'!$C$2:$C$1839,C4,'Pedidos Top10'!$D$2:$D$1839,D4,'Pedidos Top10'!$AG$2:$AG$1839,"PASSARO")/E4) -> 1 | Q4: =IF(K4<=-0.05,"Passaro compete: "&TEXT(-K4,"0%")&" abaixo de "&D4,IF(K4<0.05,"Empate técnico com "&D4,D4&" é "&TEXT(1-H4/I4,"0%")&" mais barata que a Passaro")) -> Passaro compete: 18% abaixo de ZAFER
A5: AL | B5: 2 | C5: ARAPIRACA | D5: DOMINALOG | E5: =COUNTIFS('Pedidos Top10'!$A$2:$A$1839,A5,'Pedidos Top10'!$C$2:$C$1839,C5,'Pedidos Top10'!$D$2:$D$1839,D5) -> 22 | F5: =E5/COUNTIFS('Pedidos Top10'!$A$2:$A$1839,A5,'Pedidos Top10'!$C$2:$C$1839,C5) -> 0.84615385 | G5: =SUMIFS('Pedidos Top10'!$J$2:$J$1839,'Pedidos Top10'!$A$2:$A$1839,A5,'Pedidos Top10'!$C$2:$C$1839,C5,'Pedidos Top10'!$D$2:$D$1839,D5) -> 838.36 | H5: =SUMIFS('Pedidos Top10'!$L$2:$L$1839,'Pedidos Top10'!$A$2:$A$1839,A5,'Pedidos Top10'!$C$2:$C$1839,C5,'Pedidos Top10'!$D$2:$D$1839,D5) -> 3498.11 | I5: =SUMIFS('Pedidos Top10'!$AD$2:$AD$1839,'Pedidos Top10'!$A$2:$A$1839,A5,'Pedidos Top10'!$C$2:$C$1839,C5,'Pedidos Top10'!$D$2:$D$1839,D5) -> 3501.79 | J5: =I5-H5 -> 3.68 | K5: =IF(H5=0,0,J5/H5) -> 0.0010519966 | L5: =IF(E5=0,0,H5/E5) -> 159.005 | M5: =IF(E5=0,0,I5/E5) -> 159.17227 | N5: =IF(G5=0,0,H5/G5) -> 4.1725631 | O5: =IF(G5=0,0,I5/G5) -> 4.1769526 | P5: =IF(E5=0,0,COUNTIFS('Pedidos Top10'!$A$2:$A$1839,A5,'Pedidos Top10'!$C$2:$C$1839,C5,'Pedidos Top10'!$D$2:$D$1839,D5,'Pedidos Top10'!$AG$2:$AG$1839,"PASSARO")/E5) -> 0.40909091 | Q5: =IF(K5<=-0.05,"Passaro compete: "&TEXT(-K5,"0%")&" abaixo de "&D5,IF(K5<0.05,"Empate técnico com "&D5,D5&" é "&TEXT(1-H5/I5,"0%")&" mais barata que a Passaro")) -> Empate técnico com DOMINALOG
A6: AL | B6: 2 | C6: ARAPIRACA | D6: JADLOG | E6: =COUNTIFS('Pedidos Top10'!$A$2:$A$1839,A6,'Pedidos Top10'!$C$2:$C$1839,C6,'Pedidos Top10'!$D$2:$D$1839,D6) -> 4 | F6: =E6/COUNTIFS('Pedidos Top10'!$A$2:$A$1839,A6,'Pedidos Top10'!$C$2:$C$1839,C6) -> 0.15384615 | G6: =SUMIFS('Pedidos Top10'!$J$2:$J$1839,'Pedidos Top10'!$A$2:$A$1839,A6,'Pedidos Top10'!$C$2:$C$1839,C6,'Pedidos Top10'!$D$2:$D$1839,D6) -> 83.09 | H6: =SUMIFS('Pedidos Top10'!$L$2:$L$1839,'Pedidos Top10'!$A$2:$A$1839,A6,'Pedidos Top10'!$C$2:$C$1839,C6,'Pedidos Top10'!$D$2:$D$1839,D6) -> 351.42 | I6: =SUMIFS('Pedidos Top10'!$AD$2:$AD$1839,'Pedidos Top10'!$A$2:$A$1839,A6,'Pedidos Top10'!$C$2:$C$1839,C6,'Pedidos Top10'!$D$2:$D$1839,D6) -> 562.62 | J6: =I6-H6 -> 211.2 | K6: =IF(H6=0,0,J6/H6) -> 0.60099027 | L6: =IF(E6=0,0,H6/E6) -> 87.855 | M6: =IF(E6=0,0,I6/E6) -> 140.655 | N6: =IF(G6=0,0,H6/G6) -> 4.2293898 | O6: =IF(G6=0,0,I6/G6) -> 6.7712119 | P6: =IF(E6=0,0,COUNTIFS('Pedidos Top10'!$A$2:$A$1839,A6,'Pedidos Top10'!$C$2:$C$1839,C6,'Pedidos Top10'!$D$2:$D$1839,D6,'Pedidos Top10'!$AG$2:$AG$1839,"PASSARO")/E6) -> 0 | Q6: =IF(K6<=-0.05,"Passaro compete: "&TEXT(-K6,"0%")&" abaixo de "&D6,IF(K6<0.05,"Empate técnico com "&D6,D6&" é "&TEXT(1-H6/I6,"0%")&" mais barata que a Passaro")) -> JADLOG é 38% mais barata que a Passaro
A7: AL | B7: 3 | C7: MARECHAL DEODORO | D7: DOMINALOG | E7: =COUNTIFS('Pedidos Top10'!$A$2:$A$1839,A7,'Pedidos Top10'!$C$2:$C$1839,C7,'Pedidos Top10'!$D$2:$D$1839,D7) -> 6 | F7: =E7/COUNTIFS('Pedidos Top10'!$A$2:$A$1839,A7,'Pedidos Top10'!$C$2:$C$1839,C7) -> 1 | G7: =SUMIFS('Pedidos Top10'!$J$2:$J$1839,'Pedidos Top10'!$A$2:$A$1839,A7,'Pedidos Top10'!$C$2:$C$1839,C7,'Pedidos Top10'!$D$2:$D$1839,D7) -> 427 | H7: =SUMIFS('Pedidos Top10'!$L$2:$L$1839,'Pedidos Top10'!$A$2:$A$1839,A7,'Pedidos Top10'!$C$2:$C$1839,C7,'Pedidos Top10'!$D$2:$D$1839,D7) -> 1414.13 | I7: =SUMIFS('Pedidos Top10'!$AD$2:$AD$1839,'Pedidos Top10'!$A$2:$A$1839,A7,'Pedidos Top10'!$C$2:$C$1839,C7,'Pedidos Top10'!$D$2:$D$1839,D7) -> 1161.84 | J7: =I7-H7 -> -252.29 | K7: =IF(H7=0,0,J7/H7) -> -0.17840651 | L7: =IF(E7=0,0,H7/E7) -> 235.68833 | M7: =IF(E7=0,0,I7/E7) -> 193.64 | N7: =IF(G7=0,0,H7/G7) -> 3.3117799 | O7: =IF(G7=0,0,I7/G7) -> 2.7209368 | P7: =IF(E7=0,0,COUNTIFS('Pedidos Top10'!$A$2:$A$1839,A7,'Pedidos Top10'!$C$2:$C$1839,C7,'Pedidos Top10'!$D$2:$D$1839,D7,'Pedidos Top10'!$AG$2:$AG$1839,"PASSARO")/E7) -> 0.5 | Q7: =IF(K7<=-0.05,"Passaro compete: "&TEXT(-K7,"0%")&" abaixo de "&D7,IF(K7<0.05,"Empate técnico com "&D7,D7&" é "&TEXT(1-H7/I7,"0%")&" mais barata que a Passaro")) -> Passaro compete: 18% abaixo de DOMINALOG
A8: AL | B8: 4 | C8: RIO LARGO | D8: DOMINALOG | E8: =COUNTIFS('Pedidos Top10'!$A$2:$A$1839,A8,'Pedidos Top10'!$C$2:$C$1839,C8,'Pedidos Top10'!$D$2:$D$1839,D8) -> 6 | F8: =E8/COUNTIFS('Pedidos Top10'!$A$2:$A$1839,A8,'Pedidos Top10'!$C$2:$C$1839,C8) -> 1 | G8: =SUMIFS('Pedidos Top10'!$J$2:$J$1839,'Pedidos Top10'!$A$2:$A$1839,A8,'Pedidos Top10'!$C$2:$C$1839,C8,'Pedidos Top10'!$D$2:$D$1839,D8) -> 277.41 | H8: =SUMIFS('Pedidos Top10'!$L$2:$L$1839,'Pedidos Top10'!$A$2:$A$1839,A8,'Pedidos Top10'!$C$2:$C$1839,C8,'Pedidos Top10'!$D$2:$D$1839,D8) -> 1067.67 | I8: =SUMIFS('Pedidos Top10'!$AD$2:$AD$1839,'Pedidos Top10'!$A$2:$A$1839,A8,'Pedidos Top10'!$C$2:$C$1839,C8,'Pedidos Top10'!$D$2:$D$1839,D8) -> 821.11 | J8: =I8-H8 -> -246.56 | K8: =IF(H8=0,0,J8/H8) -> -0.23093278 | L8: =IF(E8=0,0,H8/E8) -> 177.945 | M8: =IF(E8=0,0,I8/E8) -> 136.85167 | N8: =IF(G8=0,0,H8/G8) -> 3.8487077 | O8: =IF(G8=0,0,I8/G8) -> 2.9599149 | P8: =IF(E8=0,0,COUNTIFS('Pedidos Top10'!$A$2:$A$1839,A8,'Pedidos Top10'!$C$2:$C$1839,C8,'Pedidos Top10'!$D$2:$D$1839,D8,'Pedidos Top10'!$AG$2:$AG$1839,"PASSARO")/E8) -> 1 | Q8: =IF(K8<=-0.05,"Passaro compete: "&TEXT(-K8,"0%")&" abaixo de "&D8,IF(K8<0.05,"Empate técnico com "&D8,D8&" é "&TEXT(1-H8/I8,"0%")&" mais barata que a Passaro")) -> Passaro compete: 23% abaixo de DOMINALOG
A9: AL | B9: 5 | C9: MARAGOGI | D9: DOMINALOG | E9: =COUNTIFS('Pedidos Top10'!$A$2:$A$1839,A9,'Pedidos Top10'!$C$2:$C$1839,C9,'Pedidos Top10'!$D$2:$D$1839,D9) -> 4 | F9: =E9/COUNTIFS('Pedidos Top10'!$A$2:$A$1839,A9,'Pedidos Top10'!$C$2:$C$1839,C9) -> 1 | G9: =SUMIFS('Pedidos Top10'!$J$2:$J$1839,'Pedidos Top10'!$A$2:$A$1839,A9,'Pedidos Top10'!$C$2:$C$1839,C9,'Pedidos Top10'!$D$2:$D$1839,D9) -> 134.2 | H9: =SUMIFS('Pedidos Top10'!$L$2:$L$1839,'Pedidos Top10'!$A$2:$A$1839,A9,'Pedidos Top10'!$C$2:$C$1839,C9,'Pedidos Top10'!$D$2:$D$1839,D9) -> 652.13 | I9: =SUMIFS('Pedidos Top10'!$AD$2:$AD$1839,'Pedidos Top10'!$A$2:$A$1839,A9,'Pedidos Top10'!$C$2:$C$1839,C9,'Pedidos Top10'!$D$2:$D$1839,D9) -> 720.53 | J9: =I9-H9 -> 68.4 | K9: =IF(H9=0,0,J9/H9) -> 0.10488706 | L9: =IF(E9=0,0,H9/E9) -> 163.0325 | M9: =IF(E9=0,0,I9/E9) -> 180.1325 | N9: =IF(G9=0,0,H9/G9) -> 4.859389 | O9: =IF(G9=0,0,I9/G9) -> 5.369076 | P9: =IF(E9=0,0,COUNTIFS('Pedidos Top10'!$A$2:$A$1839,A9,'Pedidos Top10'!$C$2:$C$1839,C9,'Pedidos Top10'!$D$2:$D$1839,D9,'Pedidos Top10'!$AG$2:$AG$1839,"PASSARO")/E9) -> 0.25 | Q9: =IF(K9<=-0.05,"Passaro compete: "&TEXT(-K9,"0%")&" abaixo de "&D9,IF(K9<0.05,"Empate técnico com "&D9,D9&" é "&TEXT(1-H9/I9,"0%")&" mais barata que a Passaro")) -> DOMINALOG é 9% mais barata que a Passaro
A10: AL | B10: 6 | C10: DELMIRO GOUVEIA | D10: DOMINALOG | E10: =COUNTIFS('Pedidos Top10'!$A$2:$A$1839,A10,'Pedidos Top10'!$C$2:$C$1839,C10,'Pedidos Top10'!$D$2:$D$1839,D10) -> 3 | F10: =E10/COUNTIFS('Pedidos Top10'!$A$2:$A$1839,A10,'Pedidos Top10'!$C$2:$C$1839,C10) -> 1 | G10: =SUMIFS('Pedidos Top10'!$J$2:$J$1839,'Pedidos Top10'!$A$2:$A$1839,A10,'Pedidos Top10'!$C$2:$C$1839,C10,'Pedidos Top10'!$D$2:$D$1839,D10) -> 349.7 | H10: =SUMIFS('Pedidos Top10'!$L$2:$L$1839,'Pedidos Top10'!$A$2:$A$1839,A10,'Pedidos Top10'!$C$2:$C$1839,C10,'Pedidos Top10'!$D$2:$D$1839,D10) -> 1136.84 | I10: =SUMIFS('Pedidos Top10'!$AD$2:$AD$1839,'Pedidos Top10'!$A$2:$A$1839,A10,'Pedidos Top10'!$C$2:$C$1839,C10,'Pedidos Top10'!$D$2:$D$1839,D10) -> 968.53 | J10: =I10-H10 -> -168.31 | K10: =IF(H10=0,0,J10/H10) -> -0.14805074 | L10: =IF(E10=0,0,H10/E10) -> 378.94667 | M10: =IF(E10=0,0,I10/E10) -> 322.84333 | N10: =IF(G10=0,0,H10/G10) -> 3.2509008 | O10: =IF(G10=0,0,I10/G10) -> 2.7696025 | P10: =IF(E10=0,0,COUNTIFS('Pedidos Top10'!$A$2:$A$1839,A10,'Pedidos Top10'!$C$2:$C$1839,C10,'Pedidos Top10'!$D$2:$D$1839,D10,'Pedidos Top10'!$AG$2:$AG$1839,"PASSARO")/E10) -> 0.66666667 | Q10: =IF(K10<=-0.05,"Passaro compete: "&TEXT(-K10,"0%")&" abaixo de "&D10,IF(K10<0.05,"Empate técnico com "&D10,D10&" é "&TEXT(1-H10/I10,"0%")&" mais barata que a Passaro")) -> Passaro compete: 15% abaixo de DOMINALOG
A11: AL | B11: 7 | C11: PIRANHAS | D11: DOMINALOG | E11: =COUNTIFS('Pedidos Top10'!$A$2:$A$1839,A11,'Pedidos Top10'!$C$2:$C$1839,C11,'Pedidos Top10'!$D$2:$D$1839,D11) -> 3 | F11: =E11/COUNTIFS('Pedidos Top10'!$A$2:$A$1839,A11,'Pedidos Top10'!$C$2:$C$1839,C11) -> 1 | G11: =SUMIFS('Pedidos Top10'!$J$2:$J$1839,'Pedidos Top10'!$A$2:$A$1839,A11,'Pedidos Top10'!$C$2:$C$1839,C11,'Pedidos Top10'!$D$2:$D$1839,D11) -> 203.78 | H11: =SUMIFS('Pedidos Top10'!$L$2:$L$1839,'Pedidos Top10'!$A$2:$A$1839,A11,'Pedidos Top10'!$C$2:$C$1839,C11,'Pedidos Top10'!$D$2:$D$1839,D11) -> 862.25 | I11: =SUMIFS('Pedidos Top10'!$AD$2:$AD$1839,'Pedidos Top10'!$A$2:$A$1839,A11,'Pedidos Top10'!$C$2:$C$1839,C11,'Pedidos Top10'!$D$2:$D$1839,D11) -> 694.83 | J11: =I11-H11 -> -167.42 | K11: =IF(H11=0,0,J11/H11) -> -0.19416643 | L11: =IF(E11=0,0,H11/E11) -> 287.41667 | M11: =IF(E11=0,0,I11/E11) -> 231.61 | N11: =IF(G11=0,0,H11/G11) -> 4.2312788 | O11: =IF(G11=0,0,I11/G11) -> 3.4097065 | P11: =IF(E11=0,0,COUNTIFS('Pedidos Top10'!$A$2:$A$1839,A11,'Pedidos Top10'!$C$2:$C$1839,C11,'Pedidos Top10'!$D$2:$D$1839,D11,'Pedidos Top10'!$AG$2:$AG$1839,"PASSARO")/E11) -> 1 | Q11: =IF(K11<=-0.05,"Passaro compete: "&TEXT(-K11,"0%")&" abaixo de "&D11,IF(K11<0.05,"Empate técnico com "&D11,D11&" é "&TEXT(1-H11/I11,"0%")&" mais barata que a Passaro")) -> Passaro compete: 19% abaixo de DOMINALOG
A12: AL | B12: 8 | C12: SAO MIGUEL DOS MILAGRES | D12: DOMINALOG | E12: =COUNTIFS('Pedidos Top10'!$A$2:$A$1839,A12,'Pedidos Top10'!$C$2:$C$1839,C12,'Pedidos Top10'!$D$2:$D$1839,D12) -> 2 | F12: =E12/COUNTIFS('Pedidos Top10'!$A$2:$A$1839,A12,'Pedidos Top10'!$C$2:$C$1839,C12) -> 0.66666667 | G12: =SUMIFS('Pedidos Top10'!$J$2:$J$1839,'Pedidos Top10'!$A$2:$A$1839,A12,'Pedidos Top10'!$C$2:$C$1839,C12,'Pedidos Top10'!$D$2:$D$1839,D12) -> 156.9 | H12: =SUMIFS('Pedidos Top10'!$L$2:$L$1839,'Pedidos Top10'!$A$2:$A$1839,A12,'Pedidos Top10'!$C$2:$C$1839,C12,'Pedidos Top10'!$D$2:$D$1839,D12) -> 583.47 | I12: =SUMIFS('Pedidos Top10'!$AD$2:$AD$1839,'Pedidos Top10'!$A$2:$A$1839,A12,'Pedidos Top10'!$C$2:$C$1839,C12,'Pedidos Top10'!$D$2:$D$1839,D12) -> 474.61 | J12: =I12-H12 -> -108.86 | K12: =IF(H12=0,0,J12/H12) -> -0.18657343 | L12: =IF(E12=0,0,H12/E12) -> 291.735 | M12: =IF(E12=0,0,I12/E12) -> 237.305 | N12: =IF(G12=0,0,H12/G12) -> 3.718738 | O12: =IF(G12=0,0,I12/G12) -> 3.0249203 | P12: =IF(E12=0,0,COUNTIFS('Pedidos Top10'!$A$2:$A$1839,A12,'Pedidos Top10'!$C$2:$C$1839,C12,'Pedidos Top10'!$D$2:$D$1839,D12,'Pedidos Top10'!$AG$2:$AG$1839,"PASSARO")/E12) -> 0.5 | Q12: =IF(K12<=-0.05,"Passaro compete: "&TEXT(-K12,"0%")&" abaixo de "&D12,IF(K12<0.05,"Empate técnico com "&D12,D12&" é "&TEXT(1-H12/I12,"0%")&" mais barata que a Passaro")) -> Passaro compete: 19% abaixo de DOMINALOG
A13: AL | B13: 8 | C13: SAO MIGUEL DOS MILAGRES | D13: FORMATO TRANSPORTES | E13: =COUNTIFS('Pedidos Top10'!$A$2:$A$1839,A13,'Pedidos Top10'!$C$2:$C$1839,C13,'Pedidos Top10'!$D$2:$D$1839,D13) -> 1 | F13: =E13/COUNTIFS('Pedidos Top10'!$A$2:$A$1839,A13,'Pedidos Top10'!$C$2:$C$1839,C13) -> 0.33333333 | G13: =SUMIFS('Pedidos Top10'!$J$2:$J$1839,'Pedidos Top10'!$A$2:$A$1839,A13,'Pedidos Top10'!$C$2:$C$1839,C13,'Pedidos Top10'!$D$2:$D$1839,D13) -> 73.48 | H13: =SUMIFS('Pedidos Top10'!$L$2:$L$1839,'Pedidos Top10'!$A$2:$A$1839,A13,'Pedidos Top10'!$C$2:$C$1839,C13,'Pedidos Top10'!$D$2:$D$1839,D13) -> 266.95 | I13: =SUMIFS('Pedidos Top10'!$AD$2:$AD$1839,'Pedidos Top10'!$A$2:$A$1839,A13,'Pedidos Top10'!$C$2:$C$1839,C13,'Pedidos Top10'!$D$2:$D$1839,D13) -> 226.93 | J13: =I13-H13 -> -40.02 | K13: =IF(H13=0,0,J13/H13) -> -0.14991571 | L13: =IF(E13=0,0,H13/E13) -> 266.95 | M13: =IF(E13=0,0,I13/E13) -> 226.93 | N13: =IF(G13=0,0,H13/G13) -> 3.6329614 | O13: =IF(G13=0,0,I13/G13) -> 3.0883234 | P13: =IF(E13=0,0,COUNTIFS('Pedidos Top10'!$A$2:$A$1839,A13,'Pedidos Top10'!$C$2:$C$1839,C13,'Pedidos Top10'!$D$2:$D$1839,D13,'Pedidos Top10'!$AG$2:$AG$1839,"PASSARO")/E13) -> 1 | Q13: =IF(K13<=-0.05,"Passaro compete: "&TEXT(-K13,"0%")&" abaixo de "&D13,IF(K13<0.05,"Empate técnico com "&D13,D13&" é "&TEXT(1-H13/I13,"0%")&" mais barata que a Passaro")) -> Passaro compete: 15% abaixo de FORMATO TRANSPORTES
... A160: SE | B160: 10 | C160: CRISTINAPOLIS | D160: DOMINALOG | E160: =COUNTIFS('Pedidos Top10'!$A$2:$A$1839,A160,'Pedidos Top10'!$C$2:$C$1839,C160,'Pedidos Top10'!$D$2:$D$1839,D160) -> 2 | F160: =E160/COUNTIFS('Pedidos Top10'!$A$2:$A$1839,A160,'Pedidos Top10'!$C$2:$C$1839,C160) -> 1 | G160: =SUMIFS('Pedidos Top10'!$J$2:$J$1839,'Pedidos Top10'!$A$2:$A$1839,A160,'Pedidos Top10'!$C$2:$C$1839,C160,'Pedidos Top10'!$D$2:$D$1839,D160) -> 223.9 | H160: =SUMIFS('Pedidos Top10'!$L$2:$L$1839,'Pedidos Top10'!$A$2:$A$1839,A160,'Pedidos Top10'!$C$2:$C$1839,C160,'Pedidos Top10'!$D$2:$D$1839,D160) -> 712.9 | I160: =SUMIFS('Pedidos Top10'!$AD$2:$AD$1839,'Pedidos Top10'!$A$2:$A$1839,A160,'Pedidos Top10'!$C$2:$C$1839,C160,'Pedidos Top10'!$D$2:$D$1839,D160) -> 559.48 | J160: =I160-H160 -> -153.42 | K160: =IF(H160=0,0,J160/H160) -> -0.2152055 | L160: =IF(E160=0,0,H160/E160) -> 356.45 | M160: =IF(E160=0,0,I160/E160) -> 279.74 | N160: =IF(G160=0,0,H160/G160) -> 3.1840107 | O160: =IF(G160=0,0,I160/G160) -> 2.4987941 | P160: =IF(E160=0,0,COUNTIFS('Pedidos Top10'!$A$2:$A$1839,A160,'Pedidos Top10'!$C$2:$C$1839,C160,'Pedidos Top10'!$D$2:$D$1839,D160,'Pedidos Top10'!$AG$2:$AG$1839,"PASSARO")/E160) -> 1 | Q160: =IF(K160<=-0.05,"Passaro compete: "&TEXT(-K160,"0%")&" abaixo de "&D160,IF(K160<0.05,"Empate técnico com "&D160,D160&" é "&TEXT(1-H160/I160,"0%")&" mais barata que a Passaro")) -> Passaro compete: 22% abaixo de DOMINALOG

Sheet Premissas
A1: Premissas e metodologia – Simulação PASSARO TRANSPORTES – PROPOSTA 2 de 07/10/2026 (origem SP capital) x fretes realizados Ago/2026 – Nordeste
A3: ICMS por UF de destino (origem SP)
A4: UF | B4: Alíquota ICMS
A5: AL | B5: 0.07 | C5: Alíquota interestadual SP → Nordeste = 7% para todas as UFs (Resolução do Senado 22/1989). Células amarelas são editáveis.
A6: BA | B6: 0.07 | C6: ICMS aplicado "por dentro": Total = Subtotal / (1 − alíquota), igual à forma como o ICMS compõe o valor do CT-e.
A7: CE | B7: 0.07
A8: MA | B8: 0.07
A9: PB | B9: 0.07
A10: PE | B10: 0.07
A11: PI | B11: 0.07
A12: RN | B12: 0.07
A13: SE | B13: 0.07
A15: Metodologia
A16: Base de pedidos | B16: 2933 CT-es no arquivo. Excluídos: 44 CT-es de redespacho (cobrem só um trecho da viagem), 24 CT-es repetidos da mesma NF (2º CT-e da mesma nota, normalmente reentrega ou complemento; mantido só o 1º emitido), 3 CT-es com CEP fora das faixas da Passaro (Porto Seguro/BA, CEPs 46xxx). Sobram 2862 pedidos atendidos pela Passaro; desses, 1838 caem nas Top 10 cidades de cada UF: 1838 com preço na proposta, que são os comparados, e 0 de São Luís/MA, sem preço. Os outros 1024 pedidos (cidades fora do Top 10) ficam fora da análise.
A17: Cruzamento por CEP | B17: O CEP de entrega (col. S) é comparado com as faixas CEPI–CEPF da Passaro. Onde duas faixas se sobrepõem (3 casos na tabela), vale a faixa mais estreita.
A18: Top 10 cidades | B18: Ranking por número de pedidos (NF) em cada UF, entre as cidades atendidas pela Passaro. Em caso de empate, desempata pelo maior valor de frete atual. PB, RN e SE têm vários empates perto da 10ª posição.
A19: Proposta 2 – como a tabela foi montada | B19: O preço por peso segue a "área de atendimento" de cada faixa de CEP, conforme a planilha de prazos/áreas da Passaro: Capital (inclui região metropolitana), Feira de Santana (só BA), Interior 1, Interior 2 e Interior 3 (só BA). As 1.794 faixas de CEP são as mesmas da tabela anterior. O prazo também foi atualizado pela planilha de áreas.
A20: ATENÇÃO – UF usada no preço | B20: 56 faixas continuam cadastradas com a UF de uma cidade homônima de outro estado (ex.: Paulista/PE aparece como "PB"). Nessas faixas usamos o preço da UF real do CEP + a área informada (ex.: Paulista/PE = Capital PE). A coluna "UF pelo CEP" da aba Tabela Passaro mostra a UF usada.
A21: ATENÇÃO – TDA | B21: A proposta diz "TDA conforme listagem em anexo", mas a listagem não veio. Mantivemos os TDAs da tabela anterior (R$ 250/400/500 em 277 faixas). Nas Top 10 isso afeta 15 pedidos. Pedir a listagem para confirmar.
A22: Taxas que saíram | B22: A Proposta 2 não tem TRT (R$ 15 nas capitais) nem a "outra taxa" de R$ 0,45/kg da proposta anterior. O despacho passou de R$ 20 para R$ 30 por CT-e.
A23: Não considerado | B23: TDE (R$ 349,83, só em entregas com dificuldade), reentrega (50%), devolução (100%), armazenagem após 7 dias (R$ 50/ton/dia + 0,20% de seguro sobre a NF), serviços adicionais (veículo dedicado, pernoite, paletização etc.) e cubagem (300 kg/m³; a base não tem dimensões, então usamos o peso bruto).
A24: Valor atual | B24: Coluna J (Valor CTe), já com impostos.
A25: Peso | B25: Peso bruto da NF (col. P).
A26: Valor da NF | B26: Valor Total da NF (col. O), base do Frete Valor (ad valorem) e do GRIS.
A27: Frete peso | B27: Faixas até 10 / 11–30 / 31–50 / 51–70 / 71–100 kg, pela UF e área da faixa de CEP. Acima de 100 kg: valor da faixa de 100 kg + (peso − 100) × Valor Excedente.
... A34: ICMS | B34: "Conforme legislação": o ICMS não está incluso nos preços, então foi somado conforme a tabela acima.

Sheet Tabela Passaro
A1: ID | B1: UF | C1: CIDADE | D1: CEPI | E1: CEPF | F1: PRAZO (dias) | G1: Até 10 kg | H1: Até 30 kg | I1: Até 50 kg | J1: Até 70 kg | K1: Até 100 kg | L1: Excedente R$/kg (>100) | M1: Frete Valor (% NF) | N1: GRIS (% NF) | O1: TAS fixo | P1: Pedágio fixo | Q1: Faixa pedágio (kg) | R1: CT-e fixo | S1: Outra taxa fixo | T1: Faixa outra taxa (kg) | U1: TRT fixo | V1: TDA fixo | W1: UF pelo CEP (UF do preço) | X1: Área de atendimento
A2: PAS0001 | B2: AL | C2: MACEIO | D2: 57000-001 | E2: 57099-999 | F2: 8 | G2: 55.92 | H2: 66.94 | I2: 77.96 | J2: 88.98 | K2: 105.51 | L2: 1.5 | M2: 0.005 | N2: 0.002 | O2: 5 | P2: 5 | Q2: 100 | R2: 30 | S2: 0 | T2: 1 | U2: 0 | V2: 0 | W2: AL | X2: CAPITAL
A3: PAS0002 | B3: AL | C3: RIO LARGO | D3: 57100-000 | E3: 57119-999 | F3: 8 | G3: 55.92 | H3: 66.94 | I3: 77.96 | J3: 88.98 | K3: 105.51 | L3: 1.5 | M3: 0.005 | N3: 0.002 | O3: 5 | P3: 5 | Q3: 100 | R3: 30 | S3: 0 | T3: 1 | U3: 0 | V3: 0 | W3: AL | X3: CAPITAL
A4: PAS0003 | B4: AL | C4: ARAPIRACA | D4: 57300-001 | E4: 57319-999 | F4: 10 | G4: 76.24 | H4: 87.26 | I4: 109.29 | J4: 120.31 | K4: 136.84 | L4: 1.59 | M4: 0.005 | N4: 0.002 | O4: 5 | P4: 5 | Q4: 100 | R4: 30 | S4: 0 | T4: 1 | U4: 0 | V4: 0 | W4: AL | X4: INTERIOR 1
A5: PAS0004 | B5: AL | C5: ATALAIA | D5: 57690-000 | E5: 57699-999 | F5: 10 | G5: 76.24 | H5: 87.26 | I5: 109.29 | J5: 120.31 | K5: 136.84 | L5: 1.59 | M5: 0.005 | N5: 0.002 | O5: 5 | P5: 5 | Q5: 100 | R5: 30 | S5: 0 | T5: 1 | U5: 0 | V5: 0 | W5: AL | X5: INTERIOR 1
A6: PAS0005 | B6: AL | C6: BARRA DE SANTO ANTONIO | D6: 57925-000 | E6: 57929-999 | F6: 10 | G6: 76.24 | H6: 87.26 | I6: 109.29 | J6: 120.31 | K6: 136.84 | L6: 1.59 | M6: 0.005 | N6: 0.002 | O6: 5 | P6: 5 | Q6: 100 | R6: 30 | S6: 0 | T6: 1 | U6: 0 | V6: 0 | W6: AL | X6: INTERIOR 1
A7: PAS0006 | B7: AL | C7: BARRA DE SAO MIGUEL | D7: 57180-000 | E7: 57199-999 | F7: 10 | G7: 76.24 | H7: 87.26 | I7: 109.29 | J7: 120.31 | K7: 136.84 | L7: 1.59 | M7: 0.005 | N7: 0.002 | O7: 5 | P7: 5 | Q7: 100 | R7: 30 | S7: 0 | T7: 1 | U7: 0 | V7: 0 | W7: AL | X7: INTERIOR 1
A8: PAS0007 | B8: AL | C8: BRANQUINHA | D8: 57830-000 | E8: 57839-999 | F8: 10 | G8: 76.24 | H8: 87.26 | I8: 109.29 | J8: 120.31 | K8: 136.84 | L8: 1.59 | M8: 0.005 | N8: 0.002 | O8: 5 | P8: 5 | Q8: 100 | R8: 30 | S8: 0 | T8: 1 | U8: 0 | V8: 0 | W8: AL | X8: INTERIOR 1
A9: PAS0008 | B9: AL | C9: CAJUEIRO | D9: 57770-000 | E9: 57779-999 | F9: 10 | G9: 76.24 | H9: 87.26 | I9: 109.29 | J9: 120.31 | K9: 136.84 | L9: 1.59 | M9: 0.005 | N9: 0.002 | O9: 5 | P9: 5 | Q9: 100 | R9: 30 | S9: 0 | T9: 1 | U9: 0 | V9: 0 | W9: AL | X9: INTERIOR 1
A10: PAS0009 | B10: AL | C10: CAPELA | D10: 49700-000 | E10: 49739-999 | F10: 10 | G10: 75.1 | H10: 86.62 | I10: 98.13 | J10: 109.65 | K10: 126.93 | L10: 1.93 | M10: 0.005 | N10: 0.002 | O10: 5 | P10: 5 | Q10: 100 | R10: 30 | S10: 0 | T10: 1 | U10: 0 | V10: 0 | W10: SE | X10: INTERIOR 1
A11: PAS0010 | B11: AL | C11: COQUEIRO SECO | D11: 57140-000 | E11: 57149-999 | F11: 10 | G11: 76.24 | H11: 87.26 | I11: 109.29 | J11: 120.31 | K11: 136.84 | L11: 1.59 | M11: 0.005 | N11: 0.002 | O11: 5 | P11: 5 | Q11: 100 | R11: 30 | S11: 0 | T11: 1 | U11: 0 | V11: 0 | W11: AL | X11: INTERIOR 1
A12: PAS0011 | B12: AL | C12: MARECHAL DEODORO | D12: 57160-000 | E12: 57179-999 | F12: 10 | G12: 76.24 | H12: 87.26 | I12: 109.29 | J12: 120.31 | K12: 136.84 | L12: 1.59 | M12: 0.005 | N12: 0.002 | O12: 5 | P12: 5 | Q12: 100 | R12: 30 | S12: 0 | T12: 1 | U12: 0 | V12: 0 | W12: AL | X12: INTERIOR 1
A13: PAS0012 | B13: AL | C13: MESSIAS | D13: 57990-000 | E13: 57994-999 | F13: 10 | G13: 76.24 | H13: 87.26 | I13: 109.29 | J13: 120.31 | K13: 136.84 | L13: 1.59 | M13: 0.005 | N13: 0.002 | O13: 5 | P13: 5 | Q13: 100 | R13: 30 | S13: 0 | T13: 1 | U13: 0 | V13: 0 | W13: AL | X13: INTERIOR 1
... A1795: PAS1794 | B1795: SE | C1795: TOMAR DO GERU | D1795: 49280-000 | E1795: 49289-999 | F1795: 10 | G1795: 91.58 | H1795: 103.1 | I1795: 114.62 | J1795: 126.14 | K1795: 143.42 | L1795: 2.06 | M1795: 0.005 | N1795: 0.002 | O1795: 5 | P1795: 5 | Q1795: 100 | R1795: 30 | S1795: 0 | T1795: 1 | U1795: 0 | V1795: 0 | W1795: SE | X1795: INTERIOR 2

Sheet Pedidos Top10
A1: UF | B1: Rank cidade | C1: Cidade | D1: Transportadora atual | E1: UF emissão CT-e | F1: Nº CT-e | G1: Data CT-e | H1: NF | I1: CEP | J1: Peso bruto (kg) | K1: Valor NF (R$) | L1: Frete atual c/ imp. (R$) | M1: ID faixa Passaro | N1: Linha tabela | O1: Cidade (tabela Passaro) | P1: UF (tabela Passaro) | Q1: Prazo Passaro (dias) | R1: Frete peso | S1: Frete valor (ad valorem) | T1: GRIS | U1: TAS | V1: Pedágio | W1: Taxa CT-e | X1: Outra taxa | Y1: TRT | Z1: TDA | AA1: Subtotal s/ ICMS | AB1: Alíquota ICMS | AC1: ICMS | AD1: Frete PASSARO c/ ICMS (R$) | AE1: Diferença (Passaro − Atual) | AF1: Dif. % | AG1: Mais barato | AH1: Alerta | AI1: Passaro PROPOSTA 1 c/ TRT/TDA (R$) | AJ1: Área Passaro
A2: AL | B2: 1 | C2: MACEIO | D2: DOMINALOG | E2: PE | F2: 837685 | G2: 46237 | H2: 32362 | I2: 57038620 | J2: 79.26 | K2: 1083.23 | L2: 202.76 | M2: PAS0001 | N2: =MATCH(M2,'Tabela Passaro'!$A$2:$A$1795,0) -> 1 | O2: =INDEX('Tabela Passaro'!$C$2:$C$1795,$N2) -> MACEIO | P2: =INDEX('Tabela Passaro'!$B$2:$B$1795,$N2) -> AL | Q2: =INDEX('Tabela Passaro'!$F$2:$F$1795,$N2) -> 8 | R2: =IF(J2<=10,INDEX('Tabela Passaro'!$G$2:$G$1795,$N2),IF(J2<=30,INDEX('Tabela Passaro'!$H$2:$H$1795,$N2),IF(J2<=50,INDEX('Tabela Passaro'!$I$2:$I$1795,$N2),IF(J2<=70,INDEX('Tabela Passaro'!$J$2:$J$1795,$N2),IF(J2<=100,INDEX('Tabela Passaro'!$K$2:$K$1795,$N2),INDEX('Tabela Passaro'!$K$2:$K$1795,$N2)+(J2-100)*INDEX('Tabela Passaro'!$L$2:$L$1795,$N2)))))) -> 105.51 | S2: =K2*INDEX('Tabela Passaro'!$M$2:$M$1795,$N2) -> 5.41615 | T2: =K2*INDEX('Tabela Passaro'!$N$2:$N$1795,$N2) -> 2.16646 | U2: =INDEX('Tabela Passaro'!$O$2:$O$1795,$N2) -> 5 | V2: =ROUNDUP(J2/INDEX('Tabela Passaro'!$Q$2:$Q$1795,$N2),0)*INDEX('Tabela Passaro'!$P$2:$P$1795,$N2) -> 5 | W2: =INDEX('Tabela Passaro'!$R$2:$R$1795,$N2) -> 30 | X2: =ROUNDUP(J2/INDEX('Tabela Passaro'!$T$2:$T$1795,$N2),0)*INDEX('Tabela Passaro'!$S$2:$S$1795,$N2) -> 0 | Y2: =INDEX('Tabela Passaro'!$U$2:$U$1795,$N2) -> 0 | Z2: =INDEX('Tabela Passaro'!$V$2:$V$1795,$N2) -> 0 | AA2: =SUM(R2:Z2) -> 153.09261 | AB2: =INDEX(Premissas!$B$5:$B$13,MATCH(A2,Premissas!$A$5:$A$13,0)) -> 0.07 | AC2: =AA2/(1-AB2)-AA2 -> 11.5231 | AD2: =ROUND(AA2+AC2,2) -> 164.62 | AE2: =AD2-L2 -> -38.14 | AF2: =IF(L2=0,0,AE2/L2) -> -0.18810416 | AG2: =IF(AD2<L2,"PASSARO","ATUAL") -> PASSARO | AH2: =IF(P2<>A2,"Faixa cadastrada como "&P2&" na tabela; preço aplicado pela UF do CEP","") | AI2: 217.5 | AJ2: =INDEX('Tabela Passaro'!$X$2:$X$1795,$N2) -> CAPITAL
A3: AL | B3: 1 | C3: MACEIO | D3: DOMINALOG | E3: RS | F3: 521934 | G3: 46237 | H3: 619520 | I3: 57018400 | J3: 44.5 | K3: 1054 | L3: 180.27 | M3: PAS0001 | N3: =MATCH(M3,'Tabela Passaro'!$A$2:$A$1795,0) -> 1 | O3: =INDEX('Tabela Passaro'!$C$2:$C$1795,$N3) -> MACEIO | P3: =INDEX('Tabela Passaro'!$B$2:$B$1795,$N3) -> AL | Q3: =INDEX('Tabela Passaro'!$F$2:$F$1795,$N3) -> 8 | R3: =IF(J3<=10,INDEX('Tabela Passaro'!$G$2:$G$1795,$N3),IF(J3<=30,INDEX('Tabela Passaro'!$H$2:$H$1795,$N3),IF(J3<=50,INDEX('Tabela Passaro'!$I$2:$I$1795,$N3),IF(J3<=70,INDEX('Tabela Passaro'!$J$2:$J$1795,$N3),IF(J3<=100,INDEX('Tabela Passaro'!$K$2:$K$1795,$N3),INDEX('Tabela Passaro'!$K$2:$K$1795,$N3)+(J3-100)*INDEX('Tabela Passaro'!$L$2:$L$1795,$N3)))))) -> 77.96 | S3: =K3*INDEX('Tabela Passaro'!$M$2:$M$1795,$N3) -> 5.27 | T3: =K3*INDEX('Tabela Passaro'!$N$2:$N$1795,$N3) -> 2.108 | U3: =INDEX('Tabela Passaro'!$O$2:$O$1795,$N3) -> 5 | V3: =ROUNDUP(J3/INDEX('Tabela Passaro'!$Q$2:$Q$1795,$N3),0)*INDEX('Tabela Passaro'!$P$2:$P$1795,$N3) -> 5 | W3: =INDEX('Tabela Passaro'!$R$2:$R$1795,$N3) -> 30 | X3: =ROUNDUP(J3/INDEX('Tabela Passaro'!$T$2:$T$1795,$N3),0)*INDEX('Tabela Passaro'!$S$2:$S$1795,$N3) -> 0 | Y3: =INDEX('Tabela Passaro'!$U$2:$U$1795,$N3) -> 0 | Z3: =INDEX('Tabela Passaro'!$V$2:$V$1795,$N3) -> 0 | AA3: =SUM(R3:Z3) -> 125.338 | AB3: =INDEX(Premissas!$B$5:$B$13,MATCH(A3,Premissas!$A$5:$A$13,0)) -> 0.07 | AC3: =AA3/(1-AB3)-AA3 -> 9.434043 | AD3: =ROUND(AA3+AC3,2) -> 134.77 | AE3: =AD3-L3 -> -45.5 | AF3: =IF(L3=0,0,AE3/L3) -> -0.25239918 | AG3: =IF(AD3<L3,"PASSARO","ATUAL") -> PASSARO | AH3: =IF(P3<>A3,"Faixa cadastrada como "&P3&" na tabela; preço aplicado pela UF do CEP","") | AI3: 168.97 | AJ3: =INDEX('Tabela Passaro'!$X$2:$X$1795,$N3) -> CAPITAL
A4: AL | B4: 1 | C4: MACEIO | D4: DOMINALOG | E4: MG | F4: 2307459 | G4: 46238 | H4: 131331 | I4: 57010050 | J4: 34.4 | K4: 620.46 | L4: 155.77 | M4: PAS0001 | N4: =MATCH(M4,'Tabela Passaro'!$A$2:$A$1795,0) -> 1 | O4: =INDEX('Tabela Passaro'!$C$2:$C$1795,$N4) -> MACEIO | P4: =INDEX('Tabela Passaro'!$B$2:$B$1795,$N4) -> AL | Q4: =INDEX('Tabela Passaro'!$F$2:$F$1795,$N4) -> 8 | R4: =IF(J4<=10,INDEX('Tabela Passaro'!$G$2:$G$1795,$N4),IF(J4<=30,INDEX('Tabela Passaro'!$H$2:$H$1795,$N4),IF(J4<=50,INDEX('Tabela Passaro'!$I$2:$I$1795,$N4),IF(J4<=70,INDEX('Tabela Passaro'!$J$2:$J$1795,$N4),IF(J4<=100,INDEX('Tabela Passaro'!$K$2:$K$1795,$N4),INDEX('Tabela Passaro'!$K$2:$K$1795,$N4)+(J4-100)*INDEX('Tabela Passaro'!$L$2:$L$1795,$N4)))))) -> 77.96 | S4: =K4*INDEX('Tabela Passaro'!$M$2:$M$1795,$N4) -> 3.1023 | T4: =K4*INDEX('Tabela Passaro'!$N$2:$N$1795,$N4) -> 1.24092 | U4: =INDEX('Tabela Passaro'!$O$2:$O$1795,$N4) -> 5 | V4: =ROUNDUP(J4/INDEX('Tabela Passaro'!$Q$2:$Q$1795,$N4),0)*INDEX('Tabela Passaro'!$P$2:$P$1795,$N4) -> 5 | W4: =INDEX('Tabela Passaro'!$R$2:$R$1795,$N4) -> 30 | X4: =ROUNDUP(J4/INDEX('Tabela Passaro'!$T$2:$T$1795,$N4),0)*INDEX('Tabela Passaro'!$S$2:$S$1795,$N4) -> 0 | Y4: =INDEX('Tabela Passaro'!$U$2:$U$1795,$N4) -> 0 | Z4: =INDEX('Tabela Passaro'!$V$2:$V$1795,$N4) -> 0 | AA4: =SUM(R4:Z4) -> 122.30322 | AB4: =INDEX(Premissas!$B$5:$B$13,MATCH(A4,Premissas!$A$5:$A$13,0)) -> 0.07 | AC4: =AA4/(1-AB4)-AA4 -> 9.2056187 | AD4: =ROUND(AA4+AC4,2) -> 131.51 | AE4: =AD4-L4 -> -24.26 | AF4: =IF(L4=0,0,AE4/L4) -> -0.15574244 | AG4: =IF(AD4<L4,"PASSARO","ATUAL") -> PASSARO | AH4: =IF(P4<>A4,"Faixa cadastrada como "&P4&" na tabela; preço aplicado pela UF do CEP","") | AI4: 159.94 | AJ4: =INDEX('Tabela Passaro'!$X$2:$X$1795,$N4) -> CAPITAL
A5: AL | B5: 1 | C5: MACEIO | D5: DOMINALOG | E5: MG | F5: 2307461 | G5: 46238 | H5: 131333 | I5: 57015111 | J5: 66.4 | K5: 827.32 | L5: 184.85 | M5: PAS0001 | N5: =MATCH(M5,'Tabela Passaro'!$A$2:$A$1795,0) -> 1 | O5: =INDEX('Tabela Passaro'!$C$2:$C$1795,$N5) -> MACEIO | P5: =INDEX('Tabela Passaro'!$B$2:$B$1795,$N5) -> AL | Q5: =INDEX('Tabela Passaro'!$F$2:$F$1795,$N5) -> 8 | R5: =IF(J5<=10,INDEX('Tabela Passaro'!$G$2:$G$1795,$N5),IF(J5<=30,INDEX('Tabela Passaro'!$H$2:$H$1795,$N5),IF(J5<=50,INDEX('Tabela Passaro'!$I$2:$I$1795,$N5),IF(J5<=70,INDEX('Tabela Passaro'!$J$2:$J$1795,$N5),IF(J5<=100,INDEX('Tabela Passaro'!$K$2:$K$1795,$N5),INDEX('Tabela Passaro'!$K$2:$K$1795,$N5)+(J5-100)*INDEX('Tabela Passaro'!$L$2:$L$1795,$N5)))))) -> 88.98 | S5: =K5*INDEX('Tabela Passaro'!$M$2:$M$1795,$N5) -> 4.1366 | T5: =K5*INDEX('Tabela Passaro'!$N$2:$N$1795,$N5) -> 1.65464 | U5: =INDEX('Tabela Passaro'!$O$2:$O$1795,$N5) -> 5 | V5: =ROUNDUP(J5/INDEX('Tabela Passaro'!$Q$2:$Q$1795,$N5),0)*INDEX('Tabela Passaro'!$P$2:$P$1795,$N5) -> 5 | W5: =INDEX('Tabela Passaro'!$R$2:$R$1795,$N5) -> 30 | X5: =ROUNDUP(J5/INDEX('Tabela Passaro'!$T$2:$T$1795,$N5),0)*INDEX('Tabela Passaro'!$S$2:$S$1795,$N5) -> 0 | Y5: =INDEX('Tabela Passaro'!$U$2:$U$1795,$N5) -> 0 | Z5: =INDEX('Tabela Passaro'!$V$2:$V$1795,$N5) -> 0 | AA5: =SUM(R5:Z5) -> 134.77124 | AB5: =INDEX(Premissas!$B$5:$B$13,MATCH(A5,Premissas!$A$5:$A$13,0)) -> 0.07 | AC5: =AA5/(1-AB5)-AA5 -> 10.144072 | AD5: =ROUND(AA5+AC5,2) -> 144.92 | AE5: =AD5-L5 -> -39.93 | AF5: =IF(L5=0,0,AE5/L5) -> -0.21601298 | AG5: =IF(AD5<L5,"PASSARO","ATUAL") -> PASSARO | AH5: =IF(P5<>A5,"Faixa cadastrada como "&P5&" na tabela; preço aplicado pela UF do CEP","") | AI5: 189.95 | AJ5: =INDEX('Tabela Passaro'!$X$2:$X$1795,$N5) -> CAPITAL
A6: AL | B6: 1 | C6: MACEIO | D6: DOMINALOG | E6: PE | F6: 837961 | G6: 46239 | H6: 32407 | I6: 57074400 | J6: 22.4 | K6: 605.63 | L6: 109.74 | M6: PAS0001 | N6: =MATCH(M6,'Tabela Passaro'!$A$2:$A$1795,0) -> 1 | O6: =INDEX('Tabela Passaro'!$C$2:$C$1795,$N6) -> MACEIO | P6: =INDEX('Tabela Passaro'!$B$2:$B$1795,$N6) -> AL | Q6: =INDEX('Tabela Passaro'!$F$2:$F$1795,$N6) -> 8 | R6: =IF(J6<=10,INDEX('Tabela Passaro'!$G$2:$G$1795,$N6),IF(J6<=30,INDEX('Tabela Passaro'!$H$2:$H$1795,$N6),IF(J6<=50,INDEX('Tabela Passaro'!$I$2:$I$1795,$N6),IF(J6<=70,INDEX('Tabela Passaro'!$J$2:$J$1795,$N6),IF(J6<=100,INDEX('Tabela Passaro'!$K$2:$K$1795,$N6),INDEX('Tabela Passaro'!$K$2:$K$1795,$N6)+(J6-100)*INDEX('Tabela Passaro'!$L$2:$L$1795,$N6)))))) -> 66.94 | S6: =K6*INDEX('Tabela Passaro'!$M$2:$M$1795,$N6) -> 3.02815 | T6: =K6*INDEX('Tabela Passaro'!$N$2:$N$1795,$N6) -> 1.21126 | U6: =INDEX('Tabela Passaro'!$O$2:$O$1795,$N6) -> 5 | V6: =ROUNDUP(J6/INDEX('Tabela Passaro'!$Q$2:$Q$1795,$N6),0)*INDEX('Tabela Passaro'!$P$2:$P$1795,$N6) -> 5 | W6: =INDEX('Tabela Passaro'!$R$2:$R$1795,$N6) -> 30 | X6: =ROUNDUP(J6/INDEX('Tabela Passaro'!$T$2:$T$1795,$N6),0)*INDEX('Tabela Passaro'!$S$2:$S$1795,$N6) -> 0 | Y6: =INDEX('Tabela Passaro'!$U$2:$U$1795,$N6) -> 0 | Z6: =INDEX('Tabela Passaro'!$V$2:$V$1795,$N6) -> 0 | AA6: =SUM(R6:Z6) -> 111.17941 | AB6: =INDEX(Premissas!$B$5:$B$13,MATCH(A6,Premissas!$A$5:$A$13,0)) -> 0.07 | AC6: =AA6/(1-AB6)-AA6 -> 8.3683427 | AD6: =ROUND(AA6+AC6,2) -> 119.55 | AE6: =AD6-L6 -> 9.81 | AF6: =IF(L6=0,0,AE6/L6) -> 0.089393111 | AG6: =IF(AD6<L6,"PASSARO","ATUAL") -> ATUAL | AH6: =IF(P6<>A6,"Faixa cadastrada como "&P6&" na tabela; preço aplicado pela UF do CEP","") | AI6: 141.46 | AJ6: =INDEX('Tabela Passaro'!$X$2:$X$1795,$N6) -> CAPITAL
A7: AL | B7: 1 | C7: MACEIO | D7: DOMINALOG | E7: MG | F7: 2307924 | G7: 46239 | H7: 131899 | I7: 57043000 | J7: 66.4 | K7: 966.75 | L7: 185.94 | M7: PAS0001 | N7: =MATCH(M7,'Tabela Passaro'!$A$2:$A$1795,0) -> 1 | O7: =INDEX('Tabela Passaro'!$C$2:$C$1795,$N7) -> MACEIO | P7: =INDEX('Tabela Passaro'!$B$2:$B$1795,$N7) -> AL | Q7: =INDEX('Tabela Passaro'!$F$2:$F$1795,$N7) -> 8 | R7: =IF(J7<=10,INDEX('Tabela Passaro'!$G$2:$G$1795,$N7),IF(J7<=30,INDEX('Tabela Passaro'!$H$2:$H$1795,$N7),IF(J7<=50,INDEX('Tabela Passaro'!$I$2:$I$1795,$N7),IF(J7<=70,INDEX('Tabela Passaro'!$J$2:$J$1795,$N7),IF(J7<=100,INDEX('Tabela Passaro'!$K$2:$K$1795,$N7),INDEX('Tabela Passaro'!$K$2:$K$1795,$N7)+(J7-100)*INDEX('Tabela Passaro'!$L$2:$L$1795,$N7)))))) -> 88.98 | S7: =K7*INDEX('Tabela Passaro'!$M$2:$M$1795,$N7) -> 4.83375 | T7: =K7*INDEX('Tabela Passaro'!$N$2:$N$1795,$N7) -> 1.9335 | U7: =INDEX('Tabela Passaro'!$O$2:$O$1795,$N7) -> 5 | V7: =ROUNDUP(J7/INDEX('Tabela Passaro'!$Q$2:$Q$1795,$N7),0)*INDEX('Tabela Passaro'!$P$2:$P$1795,$N7) -> 5 | W7: =INDEX('Tabela Passaro'!$R$2:$R$1795,$N7) -> 30 | X7: =ROUNDUP(J7/INDEX('Tabela Passaro'!$T$2:$T$1795,$N7),0)*INDEX('Tabela Passaro'!$S$2:$S$1795,$N7) -> 0 | Y7: =INDEX('Tabela Passaro'!$U$2:$U$1795,$N7) -> 0 | Z7: =INDEX('Tabela Passaro'!$V$2:$V$1795,$N7) -> 0 | AA7: =SUM(R7:Z7) -> 135.74725 | AB7: =INDEX(Premissas!$B$5:$B$13,MATCH(A7,Premissas!$A$5:$A$13,0)) -> 0.07 | AC7: =AA7/(1-AB7)-AA7 -> 10.217535 | AD7: =ROUND(AA7+AC7,2) -> 145.96 | AE7: =AD7-L7 -> -39.98 | AF7: =IF(L7=0,0,AE7/L7) -> -0.2150156 | AG7: =IF(AD7<L7,"PASSARO","ATUAL") -> PASSARO | AH7: =IF(P7<>A7,"Faixa cadastrada como "&P7&" na tabela; preço aplicado pela UF do CEP","") | AI7: 191.3 | AJ7: =INDEX('Tabela Passaro'!$X$2:$X$1795,$N7) -> CAPITAL
A8: AL | B8: 1 | C8: MACEIO | D8: DOMINALOG | E8: MG | F8: 2307937 | G8: 46239 | H8: 131908 | I8: 57035400 | J8: 51.06 | K8: 911.83 | L8: 185.51 | M8: PAS0001 | N8: =MATCH(M8,'Tabela Passaro'!$A$2:$A$1795,0) -> 1 | O8: =INDEX('Tabela Passaro'!$C$2:$C$1795,$N8) -> MACEIO | P8: =INDEX('Tabela Passaro'!$B$2:$B$1795,$N8) -> AL | Q8: =INDEX('Tabela Passaro'!$F$2:$F$1795,$N8) -> 8 | R8: =IF(J8<=10,INDEX('Tabela Passaro'!$G$2:$G$1795,$N8),IF(J8<=30,INDEX('Tabela Passaro'!$H$2:$H$1795,$N8),IF(J8<=50,INDEX('Tabela Passaro'!$I$2:$I$1795,$N8),IF(J8<=70,INDEX('Tabela Passaro'!$J$2:$J$1795,$N8),IF(J8<=100,INDEX('Tabela Passaro'!$K$2:$K$1795,$N8),INDEX('Tabela Passaro'!$K$2:$K$1795,$N8)+(J8-100)*INDEX('Tabela Passaro'!$L$2:$L$1795,$N8)))))) -> 88.98 | S8: =K8*INDEX('Tabela Passaro'!$M$2:$M$1795,$N8) -> 4.55915 | T8: =K8*INDEX('Tabela Passaro'!$N$2:$N$1795,$N8) -> 1.82366 | U8: =INDEX('Tabela Passaro'!$O$2:$O$1795,$N8) -> 5 | V8: =ROUNDUP(J8/INDEX('Tabela Passaro'!$Q$2:$Q$1795,$N8),0)*INDEX('Tabela Passaro'!$P$2:$P$1795,$N8) -> 5 | W8: =INDEX('Tabela Passaro'!$R$2:$R$1795,$N8) -> 30 | X8: =ROUNDUP(J8/INDEX('Tabela Passaro'!$T$2:$T$1795,$N8),0)*INDEX('Tabela Passaro'!$S$2:$S$1795,$N8) -> 0 | Y8: =INDEX('Tabela Passaro'!$U$2:$U$1795,$N8) -> 0 | Z8: =INDEX('Tabela Passaro'!$V$2:$V$1795,$N8) -> 0 | AA8: =SUM(R8:Z8) -> 135.36281 | AB8: =INDEX(Premissas!$B$5:$B$13,MATCH(A8,Premissas!$A$5:$A$13,0)) -> 0.07 | AC8: =AA8/(1-AB8)-AA8 -> 10.188599 | AD8: =ROUND(AA8+AC8,2) -> 145.55 | AE8: =AD8-L8 -> -39.96 | AF8: =IF(L8=0,0,AE8/L8) -> -0.21540618 | AG8: =IF(AD8<L8,"PASSARO","ATUAL") -> PASSARO | AH8: =IF(P8<>A8,"Faixa cadastrada como "&P8&" na tabela; preço aplicado pela UF do CEP","") | AI8: 183.51 | AJ8: =INDEX('Tabela Passaro'!$X$2:$X$1795,$N8) -> CAPITAL
A9: AL | B9: 1 | C9: MACEIO | D9: DOMINALOG | E9: MG | F9: 2307899 | G9: 46239 | H9: 131917 | I9: 57052827 | J9: 34.4 | K9: 689.51 | L9: 156.32 | M9: PAS0001 | N9: =MATCH(M9,'Tabela Passaro'!$A$2:$A$1795,0) -> 1 | O9: =INDEX('Tabela Passaro'!$C$2:$C$1795,$N9) -> MACEIO | P9: =INDEX('Tabela Passaro'!$B$2:$B$1795,$N9) -> AL | Q9: =INDEX('Tabela Passaro'!$F$2:$F$1795,$N9) -> 8 | R9: =IF(J9<=10,INDEX('Tabela Passaro'!$G$2:$G$1795,$N9),IF(J9<=30,INDEX('Tabela Passaro'!$H$2:$H$1795,$N9),IF(J9<=50,INDEX('Tabela Passaro'!$I$2:$I$1795,$N9),IF(J9<=70,INDEX('Tabela Passaro'!$J$2:$J$1795,$N9),IF(J9<=100,INDEX('Tabela Passaro'!$K$2:$K$1795,$N9),INDEX('Tabela Passaro'!$K$2:$K$1795,$N9)+(J9-100)*INDEX('Tabela Passaro'!$L$2:$L$1795,$N9)))))) -> 77.96 | S9: =K9*INDEX('Tabela Passaro'!$M$2:$M$1795,$N9) -> 3.44755 | T9: =K9*INDEX('Tabela Passaro'!$N$2:$N$1795,$N9) -> 1.37902 | U9: =INDEX('Tabela Passaro'!$O$2:$O$1795,$N9) -> 5 | V9: =ROUNDUP(J9/INDEX('Tabela Passaro'!$Q$2:$Q$1795,$N9),0)*INDEX('Tabela Passaro'!$P$2:$P$1795,$N9) -> 5 | W9: =INDEX('Tabela Passaro'!$R$2:$R$1795,$N9) -> 30 | X9: =ROUNDUP(J9/INDEX('Tabela Passaro'!$T$2:$T$1795,$N9),0)*INDEX('Tabela Passaro'!$S$2:$S$1795,$N9) -> 0 | Y9: =INDEX('Tabela Passaro'!$U$2:$U$1795,$N9) -> 0 | Z9: =INDEX('Tabela Passaro'!$V$2:$V$1795,$N9) -> 0 | AA9: =SUM(R9:Z9) -> 122.78657 | AB9: =INDEX(Premissas!$B$5:$B$13,MATCH(A9,Premissas!$A$5:$A$13,0)) -> 0.07 | AC9: =AA9/(1-AB9)-AA9 -> 9.2419999 | AD9: =ROUND(AA9+AC9,2) -> 132.03 | AE9: =AD9-L9 -> -24.29 | AF9: =IF(L9=0,0,AE9/L9) -> -0.15538639 | AG9: =IF(AD9<L9,"PASSARO","ATUAL") -> PASSARO | AH9: =IF(P9<>A9,"Faixa cadastrada como "&P9&" na tabela; preço aplicado pela UF do CEP","") | AI9: 160.61 | AJ9: =INDEX('Tabela Passaro'!$X$2:$X$1795,$N9) -> CAPITAL
A10: AL | B10: 1 | C10: MACEIO | D10: DOMINALOG | E10: MG | F10: 2307964 | G10: 46239 | H10: 131952 | I10: 57035740 | J10: 25.8 | K10: 498.08 | L10: 118.94 | M10: PAS0001 | N10: =MATCH(M10,'Tabela Passaro'!$A$2:$A$1795,0) -> 1 | O10: =INDEX('Tabela Passaro'!$C$2:$C$1795,$N10) -> MACEIO | P10: =INDEX('Tabela Passaro'!$B$2:$B$1795,$N10) -> AL | Q10: =INDEX('Tabela Passaro'!$F$2:$F$1795,$N10) -> 8 | R10: =IF(J10<=10,INDEX('Tabela Passaro'!$G$2:$G$1795,$N10),IF(J10<=30,INDEX('Tabela Passaro'!$H$2:$H$1795,$N10),IF(J10<=50,INDEX('Tabela Passaro'!$I$2:$I$1795,$N10),IF(J10<=70,INDEX('Tabela Passaro'!$J$2:$J$1795,$N10),IF(J10<=100,INDEX('Tabela Passaro'!$K$2:$K$1795,$N10),INDEX('Tabela Passaro'!$K$2:$K$1795,$N10)+(J10-100)*INDEX('Tabela Passaro'!$L$2:$L$1795,$N10)))))) -> 66.94 | S10: =K10*INDEX('Tabela Passaro'!$M$2:$M$1795,$N10) -> 2.4904 | T10: =K10*INDEX('Tabela Passaro'!$N$2:$N$1795,$N10) -> 0.99616 | U10: =INDEX('Tabela Passaro'!$O$2:$O$1795,$N10) -> 5 | V10: =ROUNDUP(J10/INDEX('Tabela Passaro'!$Q$2:$Q$1795,$N10),0)*INDEX('Tabela Passaro'!$P$2:$P$1795,$N10) -> 5 | W10: =INDEX('Tabela Passaro'!$R$2:$R$1795,$N10) -> 30 | X10: =ROUNDUP(J10/INDEX('Tabela Passaro'!$T$2:$T$1795,$N10),0)*INDEX('Tabela Passaro'!$S$2:$S$1795,$N10) -> 0 | Y10: =INDEX('Tabela Passaro'!$U$2:$U$1795,$N10) -> 0 | Z10: =INDEX('Tabela Passaro'!$V$2:$V$1795,$N10) -> 0 | AA10: =SUM(R10:Z10) -> 110.42656 | AB10: =INDEX(Premissas!$B$5:$B$13,MATCH(A10,Premissas!$A$5:$A$13,0)) -> 0.07 | AC10: =AA10/(1-AB10)-AA10 -> 8.3116766 | AD10: =ROUND(AA10+AC10,2) -> 118.74 | AE10: =AD10-L10 -> -0.2 | AF10: =IF(L10=0,0,AE10/L10) -> -0.0016815201 | AG10: =IF(AD10<L10,"PASSARO","ATUAL") -> PASSARO | AH10: =IF(P10<>A10,"Faixa cadastrada como "&P10&" na tabela; preço aplicado pela UF do CEP","") | AI10: 141.87 | AJ10: =INDEX('Tabela Passaro'!$X$2:$X$1795,$N10) -> CAPITAL
A11: AL | B11: 1 | C11: MACEIO | D11: DOMINALOG | E11: RS | F11: 522632 | G11: 46239 | H11: 620534 | I11: 57035230 | J11: 107.7 | K11: 1609.93 | L11: 332 | M11: PAS0001 | N11: =MATCH(M11,'Tabela Passaro'!$A$2:$A$1795,0) -> 1 | O11: =INDEX('Tabela Passaro'!$C$2:$C$1795,$N11) -> MACEIO | P11: =INDEX('Tabela Passaro'!$B$2:$B$1795,$N11) -> AL | Q11: =INDEX('Tabela Passaro'!$F$2:$F$1795,$N11) -> 8 | R11: =IF(J11<=10,INDEX('Tabela Passaro'!$G$2:$G$1795,$N11),IF(J11<=30,INDEX('Tabela Passaro'!$H$2:$H$1795,$N11),IF(J11<=50,INDEX('Tabela Passaro'!$I$2:$I$1795,$N11),IF(J11<=70,INDEX('Tabela Passaro'!$J$2:$J$1795,$N11),IF(J11<=100,INDEX('Tabela Passaro'!$K$2:$K$1795,$N11),INDEX('Tabela Passaro'!$K$2:$K$1795,$N11)+(J11-100)*INDEX('Tabela Passaro'!$L$2:$L$1795,$N11)))))) -> 117.06 | S11: =K11*INDEX('Tabela Passaro'!$M$2:$M$1795,$N11) -> 8.04965 | T11: =K11*INDEX('Tabela Passaro'!$N$2:$N$1795,$N11) -> 3.21986 | U11: =INDEX('Tabela Passaro'!$O$2:$O$1795,$N11) -> 5 | V11: =ROUNDUP(J11/INDEX('Tabela Passaro'!$Q$2:$Q$1795,$N11),0)*INDEX('Tabela Passaro'!$P$2:$P$1795,$N11) -> 10 | W11: =INDEX('Tabela Passaro'!$R$2:$R$1795,$N11) -> 30 | X11: =ROUNDUP(J11/INDEX('Tabela Passaro'!$T$2:$T$1795,$N11),0)*INDEX('Tabela Passaro'!$S$2:$S$1795,$N11) -> 0 | Y11: =INDEX('Tabela Passaro'!$U$2:$U$1795,$N11) -> 0 | Z11: =INDEX('Tabela Passaro'!$V$2:$V$1795,$N11) -> 0 | AA11: =SUM(R11:Z11) -> 173.32951 | AB11: =INDEX(Premissas!$B$5:$B$13,MATCH(A11,Premissas!$A$5:$A$13,0)) -> 0.07 | AC11: =AA11/(1-AB11)-AA11 -> 13.046307 | AD11: =ROUND(AA11+AC11,2) -> 186.38 | AE11: =AD11-L11 -> -145.62 | AF11: =IF(L11=0,0,AE11/L11) -> -0.43861446 | AG11: =IF(AD11<L11,"PASSARO","ATUAL") -> PASSARO | AH11: =IF(P11<>A11,"Faixa cadastrada como "&P11&" na tabela; preço aplicado pela UF do CEP","") | AI11: 255.52 | AJ11: =INDEX('Tabela Passaro'!$X$2:$X$1795,$N11) -> CAPITAL
A12: AL | B12: 1 | C12: MACEIO | D12: DOMINALOG | E12: PE | F12: 838069 | G12: 46240 | H12: 32413 | I12: 57043310 | J12: 19.5 | K12: 679.65 | L12: 110.42 | M12: PAS0001 | N12: =MATCH(M12,'Tabela Passaro'!$A$2:$A$1795,0) -> 1 | O12: =INDEX('Tabela Passaro'!$C$2:$C$1795,$N12) -> MACEIO | P12: =INDEX('Tabela Passaro'!$B$2:$B$1795,$N12) -> AL | Q12: =INDEX('Tabela Passaro'!$F$2:$F$1795,$N12) -> 8 | R12: =IF(J12<=10,INDEX('Tabela Passaro'!$G$2:$G$1795,$N12),IF(J12<=30,INDEX('Tabela Passaro'!$H$2:$H$1795,$N12),IF(J12<=50,INDEX('Tabela Passaro'!$I$2:$I$1795,$N12),IF(J12<=70,INDEX('Tabela Passaro'!$J$2:$J$1795,$N12),IF(J12<=100,INDEX('Tabela Passaro'!$K$2:$K$1795,$N12),INDEX('Tabela Passaro'!$K$2:$K$1795,$N12)+(J12-100)*INDEX('Tabela Passaro'!$L$2:$L$1795,$N12)))))) -> 66.94 | S12: =K12*INDEX('Tabela Passaro'!$M$2:$M$1795,$N12) -> 3.39825 | T12: =K12*INDEX('Tabela Passaro'!$N$2:$N$1795,$N12) -> 1.3593 | U12: =INDEX('Tabela Passaro'!$O$2:$O$1795,$N12) -> 5 | V12: =ROUNDUP(J12/INDEX('Tabela Passaro'!$Q$2:$Q$1795,$N12),0)*INDEX('Tabela Passaro'!$P$2:$P$1795,$N12) -> 5 | W12: =INDEX('Tabela Passaro'!$R$2:$R$1795,$N12) -> 30 | X12: =ROUNDUP(J12/INDEX('Tabela Passaro'!$T$2:$T$1795,$N12),0)*INDEX('Tabela Passaro'!$S$2:$S$1795,$N12) -> 0 | Y12: =INDEX('Tabela Passaro'!$U$2:$U$1795,$N12) -> 0 | Z12: =INDEX('Tabela Passaro'!$V$2:$V$1795,$N12) -> 0 | AA12: =SUM(R12:Z12) -> 111.69755 | AB12: =INDEX(Premissas!$B$5:$B$13,MATCH(A12,Premissas!$A$5:$A$13,0)) -> 0.07 | AC12: =AA12/(1-AB12)-AA12 -> 8.4073425 | AD12: =ROUND(AA12+AC12,2) -> 120.1 | AE12: =AD12-L12 -> 9.68 | AF12: =IF(L12=0,0,AE12/L12) -> 0.087665278 | AG12: =IF(AD12<L12,"PASSARO","ATUAL") -> ATUAL | AH12: =IF(P12<>A12,"Faixa cadastrada como "&P12&" na tabela; preço aplicado pela UF do CEP","") | AI12: 140.73 | AJ12: =INDEX('Tabela Passaro'!$X$2:$X$1795,$N12) -> CAPITAL
A13: AL | B13: 1 | C13: MACEIO | D13: DOMINALOG | E13: RS | F13: 522862 | G13: 46240 | H13: 621116 | I13: 57017255 | J13: 107.7 | K13: 1776.12 | L13: 333.42 | M13: PAS0001 | N13: =MATCH(M13,'Tabela Passaro'!$A$2:$A$1795,0) -> 1 | O13: =INDEX('Tabela Passaro'!$C$2:$C$1795,$N13) -> MACEIO | P13: =INDEX('Tabela Passaro'!$B$2:$B$1795,$N13) -> AL | Q13: =INDEX('Tabela Passaro'!$F$2:$F$1795,$N13) -> 8 | R13: =IF(J13<=10,INDEX('Tabela Passaro'!$G$2:$G$1795,$N13),IF(J13<=30,INDEX('Tabela Passaro'!$H$2:$H$1795,$N13),IF(J13<=50,INDEX('Tabela Passaro'!$I$2:$I$1795,$N13),IF(J13<=70,INDEX('Tabela Passaro'!$J$2:$J$1795,$N13),IF(J13<=100,INDEX('Tabela Passaro'!$K$2:$K$1795,$N13),INDEX('Tabela Passaro'!$K$2:$K$1795,$N13)+(J13-100)*INDEX('Tabela Passaro'!$L$2:$L$1795,$N13)))))) -> 117.06 | S13: =K13*INDEX('Tabela Passaro'!$M$2:$M$1795,$N13) -> 8.8806 | T13: =K13*INDEX('Tabela Passaro'!$N$2:$N$1795,$N13) -> 3.55224 | U13: =INDEX('Tabela Passaro'!$O$2:$O$1795,$N13) -> 5 | V13: =ROUNDUP(J13/INDEX('Tabela Passaro'!$Q$2:$Q$1795,$N13),0)*INDEX('Tabela Passaro'!$P$2:$P$1795,$N13) -> 10 | W13: =INDEX('Tabela Passaro'!$R$2:$R$1795,$N13) -> 30 | X13: =ROUNDUP(J13/INDEX('Tabela Passaro'!$T$2:$T$1795,$N13),0)*INDEX('Tabela Passaro'!$S$2:$S$1795,$N13) -> 0 | Y13: =INDEX('Tabela Passaro'!$U$2:$U$1795,$N13) -> 0 | Z13: =INDEX('Tabela Passaro'!$V$2:$V$1795,$N13) -> 0 | AA13: =SUM(R13:Z13) -> 174.49284 | AB13: =INDEX(Premissas!$B$5:$B$13,MATCH(A13,Premissas!$A$5:$A$13,0)) -> 0.07 | AC13: =AA13/(1-AB13)-AA13 -> 13.13387 | AD13: =ROUND(AA13+AC13,2) -> 187.63 | AE13: =AD13-L13 -> -145.79 | AF13: =IF(L13=0,0,AE13/L13) -> -0.43725631 | AG13: =IF(AD13<L13,"PASSARO","ATUAL") -> PASSARO | AH13: =IF(P13<>A13,"Faixa cadastrada como "&P13&" na tabela; preço aplicado pela UF do CEP","") | AI13: 257.13 | AJ13: =INDEX('Tabela Passaro'!$X$2:$X$1795,$N13) -> CAPITAL
... A1839: SE | B1839: 10 | C1839: CRISTINAPOLIS | D1839: DOMINALOG | E1839: RS | F1839: 528309 | G1839: 46262 | H1839: 630149 | I1839: 49270000 | J1839: 174.3 | K1839: 2508.79 | L1839: 510.82 | M1839: PAS1759 | N1839: =MATCH(M1839,'Tabela Passaro'!$A$2:$A$1795,0) -> 1759 | O1839: =INDEX('Tabela Passaro'!$C$2:$C$1795,$N1839) -> CRISTINAPOLIS | P1839: =INDEX('Tabela Passaro'!$B$2:$B$1795,$N1839) -> SE | Q1839: =INDEX('Tabela Passaro'!$F$2:$F$1795,$N1839) -> 10 | R1839: =IF(J1839<=10,INDEX('Tabela Passaro'!$G$2:$G$1795,$N1839),IF(J1839<=30,INDEX('Tabela Passaro'!$H$2:$H$1795,$N1839),IF(J1839<=50,INDEX('Tabela Passaro'!$I$2:$I$1795,$N1839),IF(J1839<=70,INDEX('Tabela Passaro'!$J$2:$J$1795,$N1839),IF(J1839<=100,INDEX('Tabela Passaro'!$K$2:$K$1795,$N1839),INDEX('Tabela Passaro'!$K$2:$K$1795,$N1839)+(J1839-100)*INDEX('Tabela Passaro'!$L$2:$L$1795,$N1839)))))) -> 296.478 | S1839: =K1839*INDEX('Tabela Passaro'!$M$2:$M$1795,$N1839) -> 12.54395 | T1839: =K1839*INDEX('Tabela Passaro'!$N$2:$N$1795,$N1839) -> 5.01758 | U1839: =INDEX('Tabela Passaro'!$O$2:$O$1795,$N1839) -> 5 | V1839: =ROUNDUP(J1839/INDEX('Tabela Passaro'!$Q$2:$Q$1795,$N1839),0)*INDEX('Tabela Passaro'!$P$2:$P$1795,$N1839) -> 10 | W1839: =INDEX('Tabela Passaro'!$R$2:$R$1795,$N1839) -> 30 | X1839: =ROUNDUP(J1839/INDEX('Tabela Passaro'!$T$2:$T$1795,$N1839),0)*INDEX('Tabela Passaro'!$S$2:$S$1795,$N1839) -> 0 | Y1839: =INDEX('Tabela Passaro'!$U$2:$U$1795,$N1839) -> 0 | Z1839: =INDEX('Tabela Passaro'!$V$2:$V$1795,$N1839) -> 0 | AA1839: =SUM(R1839:Z1839) -> 359.03953 | AB1839: =INDEX(Premissas!$B$5:$B$13,MATCH(A1839,Premissas!$A$5:$A$13,0)) -> 0.07 | AC1839: =AA1839/(1-AB1839)-AA1839 -> 27.024481 | AD1839: =ROUND(AA1839+AC1839,2) -> 386.06 | AE1839: =AD1839-L1839 -> -124.76 | AF1839: =IF(L1839=0,0,AE1839/L1839) -> -0.24423476 | AG1839: =IF(AD1839<L1839,"PASSARO","ATUAL") -> PASSARO | AH1839: =IF(P1839<>A1839,"Faixa cadastrada como "&P1839&" na tabela; preço aplicado pela UF do CEP","") | AI1839: 487.88 | AJ1839: =INDEX('Tabela Passaro'!$X$2:$X$1795,$N1839) -> INTERIOR 2
