Workbook

Sheet Resumo
A1: PROLOG FILIAL SP x TSL FILIAL SP — pedidos RJ com origem de cotação FILIAL SP (jul–set/2026)
A3: PREMISSAS (células em azul podem ser alteradas)
A4: Parâmetro | B4: PROLOG | C4: TSL | D4: Fonte / observação
A5: ICMS por fora (gross-up: total = subtotal / (1 − alíquota)) | B5: 0.12 | C5: 0.12 | D5: Confirmado pelo usuário: 12% por fora. Ambas as tabelas marcadas "ICMS incluso = N".
A6: Ad valorem / frete valor (% NF) | B6: 0.001 | C6: 0 | D6: Tabelas Intelipost
A7: GRIS (% NF) | B7: 0.002 | C7: 0.002 | D7: Tabelas Intelipost
A8: Seguro (% NF) | B8: 0 | C8: 0.002 | D8: Tabela TSL
A9: TAS / entrega fixo (R$ por pedido) | B9: 1 | C9: 11.9 | D9: PROLOG: TAS R$ 1,00 | TSL: entrega fixo R$ 11,90
A10: Pedágio (R$ por fração de 100 kg) | B10: 4.5 | C10: 1 | D10: Tabelas Intelipost
A11: TRT (% sobre o subtotal) | B11: 0 | C11: 0.055 | D11: TSL 5,5%. Base validada: subtotal (frete peso + taxas) — reproduz 100% das cotações reais TSL Filial SP ao centavo
A12: CTe (R$ por kg) | B12: 0.06 | C12: 0 | D12: Tabela PROLOG (faixa de 1 kg)
A13: Taxa interna (R$ por kg) — levar produto até a filial SP | B13: 0.45 | C13: 0 | D13: Confirmado pelo usuário: taxa interna obrigatória, lançada na tabela PROLOG como "outra taxa". NÃO consta na tabela TSL.
A14: Cubagem (kg/m³) | B14: 0 | C14: 300 | D14: Sem dimensões na base: simulado por peso real (as cotações TSL reais batem com peso real)
A17: VISÃO GERAL — mesmos 2.223 pedidos cotados pelas duas tabelas
A18: Indicador | B18: TSL FILIAL SP | C18: PROLOG FILIAL SP | D18: Diferença
A19: Pedidos | B19: =COUNTA(Pedidos!$A$2:$A$2224) -> 2223 | C19: =COUNTA(Pedidos!$A$2:$A$2224) -> 2223
A20: Custo total de frete | B20: =SUM(Pedidos!$T$2:$T$2224) -> 270019.88 | C20: =SUM(Pedidos!$AC$2:$AC$2224) -> 386659.64 | D20: =C20/B20-1 -> 0.43196731
A21: Custo médio por pedido | B21: =AVERAGE(Pedidos!$T$2:$T$2224) -> 121.46643 | C21: =AVERAGE(Pedidos!$AC$2:$AC$2224) -> 173.93596 | D21: =C21/B21-1 -> 0.43196731
A22: Frete / NF | B22: =SUM(Pedidos!$T$2:$T$2224)/SUM(Pedidos!$J$2:$J$2224) -> 0.18924884 | C22: =SUM(Pedidos!$AC$2:$AC$2224)/SUM(Pedidos!$J$2:$J$2224) -> 0.27099816 | D22: =C22-B22 -> 0.081749314
A23: % pedidos em que a PROLOG ganharia a cotação | C23: =COUNTIF(Pedidos!$AG$2:$AG$2224,"SIM")/B19 -> 0.0067476383
A24: PROLOG sem a taxa interna — custo médio | B24: =B21 -> 121.46643 | C24: =AVERAGE(Pedidos!$AD$2:$AD$2224) -> 148.22769 | D24: =C24/B24-1 -> 0.22031812
A25: Prazo médio (dias úteis) | B25: =AVERAGE(Pedidos!$AH$2:$AH$2224) -> 9.9518668 | C25: =AVERAGE(Pedidos!$AI$2:$AI$2224) -> 6.4669366 | D25: =C25-B25 -> -3.4849303
A26: Conferência: custo real cotado (todas transportadoras) | B26: =SUM(Pedidos!$L$2:$L$2224) -> 269909.92
A27: A tabela TSL simulada reproduz as cotações reais da TSL Filial SP (1.592 pedidos) com diferença máxima de R$ 0,01 — o motor de cálculo está validado.
A29: DE ONDE VEM A DIFERENÇA — média por pedido (R$)
A30: Componente | B30: TSL | C30: PROLOG | D30: PROLOG − TSL | E30: % da diferença
A31: Frete peso | B31: =AVERAGE(Pedidos!$M$2:$M$2224) -> 85.783608 | C31: =AVERAGE(Pedidos!$U$2:$U$2224) -> 119.69681 | D31: =C31-B31 -> 33.913198 | E31: =D31/$D$42 -> 0.64634083
A32: Ad valorem | B32: 0 | C32: =AVERAGE(Pedidos!$V$2:$V$2224) -> 0.64183448 | D32: =C32-B32 -> 0.64183448 | E32: =D32/$D$42 -> 0.012232519
A33: GRIS | B33: =AVERAGE(Pedidos!$N$2:$N$2224) -> 1.283669 | C33: =AVERAGE(Pedidos!$W$2:$W$2224) -> 1.283669 | D33: =C33-B33 -> 0 | E33: =D33/$D$42 -> 0
A34: Seguro | B34: =AVERAGE(Pedidos!$O$2:$O$2224) -> 1.283669 | C34: 0 | D34: =C34-B34 -> -1.283669 | E34: =D34/$D$42 -> -0.024465037
A35: TAS / Entrega fixo | B35: =AVERAGE(Pedidos!$Q$2:$Q$2224) -> 11.9 | C35: =AVERAGE(Pedidos!$X$2:$X$2224) -> 1 | D35: =C35-B35 -> -10.9 | E35: =D35/$D$42 -> -0.20773962
A36: Pedágio | B36: =AVERAGE(Pedidos!$P$2:$P$2224) -> 1.0670265 | C36: =AVERAGE(Pedidos!$Y$2:$Y$2224) -> 4.8016194 | D36: =C36-B36 -> 3.7345929 | E36: =D36/$D$42 -> 0.071176414
A37: TRT 5,5% | B37: =AVERAGE(Pedidos!$R$2:$R$2224) -> 5.5724885 | C37: 0 | D37: =C37-B37 -> -5.5724885 | E37: =D37/$D$42 -> -0.10620428
A38: CTe por kg | B38: 0 | C38: =AVERAGE(Pedidos!$Z$2:$Z$2224) -> 3.0164372 | D38: =C38-B38 -> 3.0164372 | E38: =D38/$D$42 -> 0.057489315
A39: Taxa interna R$ 0,45/kg | B39: 0 | C39: =AVERAGE(Pedidos!$AA$2:$AA$2224) -> 22.623279 | D39: =C39-B39 -> 22.623279 | E39: =D39/$D$42 -> 0.43116986
A40: ICMS 12% por fora | B40: =AVERAGE(Pedidos!$T$2:$T$2224)-AVERAGE(Pedidos!$S$2:$S$2224) -> 14.575972 | C40: =AVERAGE(Pedidos!$AC$2:$AC$2224)-AVERAGE(Pedidos!$AB$2:$AB$2224) -> 20.872315 | D40: =C40-B40 -> 6.2963434 | E40: =D40/$D$42 -> 0.12
A42: TOTAL | B42: =SUM(B31:B40) -> 121.46643 | C42: =SUM(C31:C40) -> 173.93596 | D42: =C42-B42 -> 52.469528 | E42: =D42/$D$42 -> 1

Sheet Comparativo Tabelas
A1: Estrutura das tabelas — principais diferenças
A3: Item | B3: PROLOG FILIAL SP | C3: TSL FILIAL SP | D3: Quem leva vantagem | E3: Comentário / oportunidade
A4: Regionalização do RJ | B4: 93 faixas de CEP, 9 níveis de preço | C4: 93 faixas de CEP, só 3 níveis: Capital, Metropolitana (10 faixas), Interior (82) | D4: — | E4: A TSL tem preço único por região; a PROLOG pode ser agressiva onde tem operação própria
A5: Frete peso — Capital (20 a 35 kg) | B5: R$ 82,21 | C5: R$ 54,10 | D5: TSL | E5: A PROLOG está 52% acima na base; é o maior gap de valor (46% dos pedidos)
A6: Frete peso — Capital (40 a 50 kg) | B6: R$ 93,97 | C6: R$ 71,00 | D6: TSL | E6: +32%
A7: Frete peso — Capital (50 a 60 kg) | B7: R$ 112,30 | C7: R$ 79,81 | D7: TSL | E7: +41%
A8: Taxa fixa por pedido | B8: TAS R$ 1,00 | C8: Entrega R$ 11,90 | D8: PROLOG | E8: R$ 10,90 a menos por pedido — vantagem forte em pedidos leves
A9: TRT | B9: não cobra | C9: 5,5% sobre o subtotal | D9: PROLOG | E9: ≈ R$ 5,57 por pedido a favor da PROLOG
A10: Ad valorem / Seguro | B10: 0,1% NF | C10: 0,2% NF | D10: PROLOG | E10: Pequeno (≈ R$ 0,64 a favor)
A11: GRIS | B11: 0,2% NF | C11: 0,2% NF | D11: Empate
A12: Pedágio | B12: R$ 4,50 / 100 kg | C12: R$ 1,00 / 100 kg | D12: TSL | E12: R$ 3,50 a mais por pedido — fácil de negociar para R$ 1,00
A13: CTe | B13: R$ 0,06 por kg | C13: não cobra | D13: TSL | E13: ≈ R$ 3,00 por pedido; pedir para transformar em fixo ou zerar
A14: Taxa interna (filial SP) | B14: R$ 0,45 por kg (na tabela) | C14: não consta | D14: TSL | E14: ≈ R$ 22,60 + ICMS = R$ 25,70 por pedido de penalidade. Se é um custo da operação da filial SP, deveria estar em TODAS as tabelas que saem da filial (inclusive TSL), senão a PROLOG concorre em desvantagem na Intelipost
A15: Cubagem | B15: não aplica (0) | C15: 300 kg/m³ | D15: PROLOG | E15: Vantagem para produtos volumosos (não medida: base sem dimensões)
A16: Excedente acima de 250 kg | B16: R$ 7,71 a 12,05 / kg | C16: R$ 0,91 a 1,28 / kg | D16: TSL | E16: Sem pedidos acima de 250 kg no período; mesmo assim, o excedente da PROLOG está fora de mercado
A17: Prazo — Capital | B17: 5 dias úteis | C17: 8 dias úteis | D17: PROLOG | E17: 3 dias mais rápido
A18: Prazo — Metropolitana | B18: 5 a 7 dias úteis | C18: 10 dias úteis | D18: PROLOG | E18: 3 a 5 dias mais rápido
A19: Prazo — Interior | B19: 6 a 11 dias úteis | C19: 13 dias úteis | D19: PROLOG | E19: 2 a 7 dias mais rápido
A20: Inconsistência na tabela TSL | B20: — | C20: Interior, faixa 170 a 200 kg = R$ 143,51 (menor que a faixa 150 a 170 kg = R$ 215,70) | D20: — | E20: Provável erro de digitação na TSL (deveria ser ~R$ 243). Hoje favorece a TSL nessa faixa

Sheet Top 20 Cidades
A1: Top 20 cidades RJ — preço final (com taxas e ICMS) PROLOG x TSL nos mesmos pedidos
A3: # | B3: Cidade | C3: Região TSL | D3: Pedidos | E3: % pedidos RJ | F3: Peso médio (kg) | G3: NF média | H3: TSL médio | I3: PROLOG médio | J3: PROLOG vs TSL | K3: PROLOG s/ taxa interna vs TSL | L3: Frete/NF TSL | M3: Frete/NF PROLOG | N3: % pedidos PROLOG ganharia | O3: Frete peso PROLOG vs TSL | P3: Prazo TSL | Q3: Prazo PROLOG | R3: Redução necessária no preço PROLOG p/ empatar | S3: Avaliação
A4: 1 | B4: Rio de Janeiro | C4: =INDEX(Pedidos!$G$2:$G$2224,MATCH($B4,Pedidos!$F$2:$F$2224,0)) -> Capital | D4: =COUNTIFS(Pedidos!$F$2:$F$2224,$B4) -> 1030 | E4: =D4/Resumo!$B$19 -> 0.46333783 | F4: =AVERAGEIFS(Pedidos!$I$2:$I$2224,Pedidos!$F$2:$F$2224,$B4) -> 47.579631 | G4: =AVERAGEIFS(Pedidos!$J$2:$J$2224,Pedidos!$F$2:$F$2224,$B4) -> 617.43493 | H4: =AVERAGEIFS(Pedidos!$T$2:$T$2224,Pedidos!$F$2:$F$2224,$B4) -> 106.76312 | I4: =AVERAGEIFS(Pedidos!$AC$2:$AC$2224,Pedidos!$F$2:$F$2224,$B4) -> 156.29299 | J4: =I4/H4-1 -> 0.46392307 | K4: =AVERAGEIFS(Pedidos!$AD$2:$AD$2224,Pedidos!$F$2:$F$2224,$B4)/H4-1 -> 0.23404986 | L4: =SUMIFS(Pedidos!$T$2:$T$2224,Pedidos!$F$2:$F$2224,$B4)/SUMIFS(Pedidos!$J$2:$J$2224,Pedidos!$F$2:$F$2224,$B4) -> 0.17291395 | M4: =SUMIFS(Pedidos!$AC$2:$AC$2224,Pedidos!$F$2:$F$2224,$B4)/SUMIFS(Pedidos!$J$2:$J$2224,Pedidos!$F$2:$F$2224,$B4) -> 0.25313273 | N4: =COUNTIFS(Pedidos!$F$2:$F$2224,$B4,Pedidos!$AG$2:$AG$2224,"SIM")/D4 -> 0 | O4: =SUMIFS(Pedidos!$U$2:$U$2224,Pedidos!$F$2:$F$2224,$B4)/SUMIFS(Pedidos!$M$2:$M$2224,Pedidos!$F$2:$F$2224,$B4)-1 -> 0.43204181 | P4: =AVERAGEIFS(Pedidos!$AH$2:$AH$2224,Pedidos!$F$2:$F$2224,$B4) -> 8 | Q4: =AVERAGEIFS(Pedidos!$AI$2:$AI$2224,Pedidos!$F$2:$F$2224,$B4) -> 5 | R4: =MAX(0,1-H4/I4) -> 0.31690399 | S4: =IF(J4<=0,"Muito bem",IF(J4<=0.32,"Melhor posição",IF(J4<=0.45,"Intermediária","Precisa melhorar"))) -> Precisa melhorar
A5: 2 | B5: São Gonçalo | C5: =INDEX(Pedidos!$G$2:$G$2224,MATCH($B5,Pedidos!$F$2:$F$2224,0)) -> Metropolitana | D5: =COUNTIFS(Pedidos!$F$2:$F$2224,$B5) -> 135 | E5: =D5/Resumo!$B$19 -> 0.060728745 | F5: =AVERAGEIFS(Pedidos!$I$2:$I$2224,Pedidos!$F$2:$F$2224,$B5) -> 50.268593 | G5: =AVERAGEIFS(Pedidos!$J$2:$J$2224,Pedidos!$F$2:$F$2224,$B5) -> 636.66911 | H5: =AVERAGEIFS(Pedidos!$T$2:$T$2224,Pedidos!$F$2:$F$2224,$B5) -> 124.74222 | I5: =AVERAGEIFS(Pedidos!$AC$2:$AC$2224,Pedidos!$F$2:$F$2224,$B5) -> 180.34462 | J5: =I5/H5-1 -> 0.44573846 | K5: =AVERAGEIFS(Pedidos!$AD$2:$AD$2224,Pedidos!$F$2:$F$2224,$B5)/H5-1 -> 0.23818923 | L5: =SUMIFS(Pedidos!$T$2:$T$2224,Pedidos!$F$2:$F$2224,$B5)/SUMIFS(Pedidos!$J$2:$J$2224,Pedidos!$F$2:$F$2224,$B5) -> 0.19592943 | M5: =SUMIFS(Pedidos!$AC$2:$AC$2224,Pedidos!$F$2:$F$2224,$B5)/SUMIFS(Pedidos!$J$2:$J$2224,Pedidos!$F$2:$F$2224,$B5) -> 0.28326272 | N5: =COUNTIFS(Pedidos!$F$2:$F$2224,$B5,Pedidos!$AG$2:$AG$2224,"SIM")/D5 -> 0 | O5: =SUMIFS(Pedidos!$U$2:$U$2224,Pedidos!$F$2:$F$2224,$B5)/SUMIFS(Pedidos!$M$2:$M$2224,Pedidos!$F$2:$F$2224,$B5)-1 -> 0.41404108 | P5: =AVERAGEIFS(Pedidos!$AH$2:$AH$2224,Pedidos!$F$2:$F$2224,$B5) -> 10 | Q5: =AVERAGEIFS(Pedidos!$AI$2:$AI$2224,Pedidos!$F$2:$F$2224,$B5) -> 7 | R5: =MAX(0,1-H5/I5) -> 0.30831196 | S5: =IF(J5<=0,"Muito bem",IF(J5<=0.32,"Melhor posição",IF(J5<=0.45,"Intermediária","Precisa melhorar"))) -> Intermediária
A6: 3 | B6: Duque de Caxias | C6: =INDEX(Pedidos!$G$2:$G$2224,MATCH($B6,Pedidos!$F$2:$F$2224,0)) -> Metropolitana | D6: =COUNTIFS(Pedidos!$F$2:$F$2224,$B6) -> 106 | E6: =D6/Resumo!$B$19 -> 0.047683311 | F6: =AVERAGEIFS(Pedidos!$I$2:$I$2224,Pedidos!$F$2:$F$2224,$B6) -> 52.422453 | G6: =AVERAGEIFS(Pedidos!$J$2:$J$2224,Pedidos!$F$2:$F$2224,$B6) -> 663.55302 | H6: =AVERAGEIFS(Pedidos!$T$2:$T$2224,Pedidos!$F$2:$F$2224,$B6) -> 128.03769 | I6: =AVERAGEIFS(Pedidos!$AC$2:$AC$2224,Pedidos!$F$2:$F$2224,$B6) -> 166.37382 | J6: =I6/H6-1 -> 0.29941283 | K6: =AVERAGEIFS(Pedidos!$AD$2:$AD$2224,Pedidos!$F$2:$F$2224,$B6)/H6-1 -> 0.088492211 | L6: =SUMIFS(Pedidos!$T$2:$T$2224,Pedidos!$F$2:$F$2224,$B6)/SUMIFS(Pedidos!$J$2:$J$2224,Pedidos!$F$2:$F$2224,$B6) -> 0.19295774 | M6: =SUMIFS(Pedidos!$AC$2:$AC$2224,Pedidos!$F$2:$F$2224,$B6)/SUMIFS(Pedidos!$J$2:$J$2224,Pedidos!$F$2:$F$2224,$B6) -> 0.25073176 | N6: =COUNTIFS(Pedidos!$F$2:$F$2224,$B6,Pedidos!$AG$2:$AG$2224,"SIM")/D6 -> 0.056603774 | O6: =SUMIFS(Pedidos!$U$2:$U$2224,Pedidos!$F$2:$F$2224,$B6)/SUMIFS(Pedidos!$M$2:$M$2224,Pedidos!$F$2:$F$2224,$B6)-1 -> 0.22424679 | P6: =AVERAGEIFS(Pedidos!$AH$2:$AH$2224,Pedidos!$F$2:$F$2224,$B6) -> 10 | Q6: =AVERAGEIFS(Pedidos!$AI$2:$AI$2224,Pedidos!$F$2:$F$2224,$B6) -> 5 | R6: =MAX(0,1-H6/I6) -> 0.23042164 | S6: =IF(J6<=0,"Muito bem",IF(J6<=0.32,"Melhor posição",IF(J6<=0.45,"Intermediária","Precisa melhorar"))) -> Melhor posição
A7: 4 | B7: Nova Iguaçu | C7: =INDEX(Pedidos!$G$2:$G$2224,MATCH($B7,Pedidos!$F$2:$F$2224,0)) -> Metropolitana | D7: =COUNTIFS(Pedidos!$F$2:$F$2224,$B7) -> 95 | E7: =D7/Resumo!$B$19 -> 0.042735043 | F7: =AVERAGEIFS(Pedidos!$I$2:$I$2224,Pedidos!$F$2:$F$2224,$B7) -> 55.083474 | G7: =AVERAGEIFS(Pedidos!$J$2:$J$2224,Pedidos!$F$2:$F$2224,$B7) -> 676.70926 | H7: =AVERAGEIFS(Pedidos!$T$2:$T$2224,Pedidos!$F$2:$F$2224,$B7) -> 130.60571 | I7: =AVERAGEIFS(Pedidos!$AC$2:$AC$2224,Pedidos!$F$2:$F$2224,$B7) -> 172.30948 | J7: =I7/H7-1 -> 0.3193104 | K7: =AVERAGEIFS(Pedidos!$AD$2:$AD$2224,Pedidos!$F$2:$F$2224,$B7)/H7-1 -> 0.10194812 | L7: =SUMIFS(Pedidos!$T$2:$T$2224,Pedidos!$F$2:$F$2224,$B7)/SUMIFS(Pedidos!$J$2:$J$2224,Pedidos!$F$2:$F$2224,$B7) -> 0.19300122 | M7: =SUMIFS(Pedidos!$AC$2:$AC$2224,Pedidos!$F$2:$F$2224,$B7)/SUMIFS(Pedidos!$J$2:$J$2224,Pedidos!$F$2:$F$2224,$B7) -> 0.25462852 | N7: =COUNTIFS(Pedidos!$F$2:$F$2224,$B7,Pedidos!$AG$2:$AG$2224,"SIM")/D7 -> 0.021052632 | O7: =SUMIFS(Pedidos!$U$2:$U$2224,Pedidos!$F$2:$F$2224,$B7)/SUMIFS(Pedidos!$M$2:$M$2224,Pedidos!$F$2:$F$2224,$B7)-1 -> 0.23727191 | P7: =AVERAGEIFS(Pedidos!$AH$2:$AH$2224,Pedidos!$F$2:$F$2224,$B7) -> 10 | Q7: =AVERAGEIFS(Pedidos!$AI$2:$AI$2224,Pedidos!$F$2:$F$2224,$B7) -> 5 | R7: =MAX(0,1-H7/I7) -> 0.24202826 | S7: =IF(J7<=0,"Muito bem",IF(J7<=0.32,"Melhor posição",IF(J7<=0.45,"Intermediária","Precisa melhorar"))) -> Melhor posição
A8: 5 | B8: Niterói | C8: =INDEX(Pedidos!$G$2:$G$2224,MATCH($B8,Pedidos!$F$2:$F$2224,0)) -> Metropolitana | D8: =COUNTIFS(Pedidos!$F$2:$F$2224,$B8) -> 68 | E8: =D8/Resumo!$B$19 -> 0.030589294 | F8: =AVERAGEIFS(Pedidos!$I$2:$I$2224,Pedidos!$F$2:$F$2224,$B8) -> 47.945882 | G8: =AVERAGEIFS(Pedidos!$J$2:$J$2224,Pedidos!$F$2:$F$2224,$B8) -> 603.64809 | H8: =AVERAGEIFS(Pedidos!$T$2:$T$2224,Pedidos!$F$2:$F$2224,$B8) -> 122.05811 | I8: =AVERAGEIFS(Pedidos!$AC$2:$AC$2224,Pedidos!$F$2:$F$2224,$B8) -> 175.73135 | J8: =I8/H8-1 -> 0.43973517 | K8: =AVERAGEIFS(Pedidos!$AD$2:$AD$2224,Pedidos!$F$2:$F$2224,$B8)/H8-1 -> 0.23716005 | L8: =SUMIFS(Pedidos!$T$2:$T$2224,Pedidos!$F$2:$F$2224,$B8)/SUMIFS(Pedidos!$J$2:$J$2224,Pedidos!$F$2:$F$2224,$B8) -> 0.20220077 | M8: =SUMIFS(Pedidos!$AC$2:$AC$2224,Pedidos!$F$2:$F$2224,$B8)/SUMIFS(Pedidos!$J$2:$J$2224,Pedidos!$F$2:$F$2224,$B8) -> 0.29111556 | N8: =COUNTIFS(Pedidos!$F$2:$F$2224,$B8,Pedidos!$AG$2:$AG$2224,"SIM")/D8 -> 0 | O8: =SUMIFS(Pedidos!$U$2:$U$2224,Pedidos!$F$2:$F$2224,$B8)/SUMIFS(Pedidos!$M$2:$M$2224,Pedidos!$F$2:$F$2224,$B8)-1 -> 0.41718327 | P8: =AVERAGEIFS(Pedidos!$AH$2:$AH$2224,Pedidos!$F$2:$F$2224,$B8) -> 10 | Q8: =AVERAGEIFS(Pedidos!$AI$2:$AI$2224,Pedidos!$F$2:$F$2224,$B8) -> 7 | R8: =MAX(0,1-H8/I8) -> 0.30542782 | S8: =IF(J8<=0,"Muito bem",IF(J8<=0.32,"Melhor posição",IF(J8<=0.45,"Intermediária","Precisa melhorar"))) -> Intermediária
A9: 6 | B9: Campos dos Goytacazes | C9: =INDEX(Pedidos!$G$2:$G$2224,MATCH($B9,Pedidos!$F$2:$F$2224,0)) -> Interior | D9: =COUNTIFS(Pedidos!$F$2:$F$2224,$B9) -> 53 | E9: =D9/Resumo!$B$19 -> 0.023841655 | F9: =AVERAGEIFS(Pedidos!$I$2:$I$2224,Pedidos!$F$2:$F$2224,$B9) -> 49.475283 | G9: =AVERAGEIFS(Pedidos!$J$2:$J$2224,Pedidos!$F$2:$F$2224,$B9) -> 649.88434 | H9: =AVERAGEIFS(Pedidos!$T$2:$T$2224,Pedidos!$F$2:$F$2224,$B9) -> 136.90877 | I9: =AVERAGEIFS(Pedidos!$AC$2:$AC$2224,Pedidos!$F$2:$F$2224,$B9) -> 218.07379 | J9: =I9/H9-1 -> 0.59284021 | K9: =AVERAGEIFS(Pedidos!$AD$2:$AD$2224,Pedidos!$F$2:$F$2224,$B9)/H9-1 -> 0.40686199 | L9: =SUMIFS(Pedidos!$T$2:$T$2224,Pedidos!$F$2:$F$2224,$B9)/SUMIFS(Pedidos!$J$2:$J$2224,Pedidos!$F$2:$F$2224,$B9) -> 0.21066636 | M9: =SUMIFS(Pedidos!$AC$2:$AC$2224,Pedidos!$F$2:$F$2224,$B9)/SUMIFS(Pedidos!$J$2:$J$2224,Pedidos!$F$2:$F$2224,$B9) -> 0.33555785 | N9: =COUNTIFS(Pedidos!$F$2:$F$2224,$B9,Pedidos!$AG$2:$AG$2224,"SIM")/D9 -> 0 | O9: =SUMIFS(Pedidos!$U$2:$U$2224,Pedidos!$F$2:$F$2224,$B9)/SUMIFS(Pedidos!$M$2:$M$2224,Pedidos!$F$2:$F$2224,$B9)-1 -> 0.60936358 | P9: =AVERAGEIFS(Pedidos!$AH$2:$AH$2224,Pedidos!$F$2:$F$2224,$B9) -> 13 | Q9: =AVERAGEIFS(Pedidos!$AI$2:$AI$2224,Pedidos!$F$2:$F$2224,$B9) -> 11 | R9: =MAX(0,1-H9/I9) -> 0.37219064 | S9: =IF(J9<=0,"Muito bem",IF(J9<=0.32,"Melhor posição",IF(J9<=0.45,"Intermediária","Precisa melhorar"))) -> Precisa melhorar
A10: 7 | B10: Belford Roxo | C10: =INDEX(Pedidos!$G$2:$G$2224,MATCH($B10,Pedidos!$F$2:$F$2224,0)) -> Metropolitana | D10: =COUNTIFS(Pedidos!$F$2:$F$2224,$B10) -> 49 | E10: =D10/Resumo!$B$19 -> 0.022042285 | F10: =AVERAGEIFS(Pedidos!$I$2:$I$2224,Pedidos!$F$2:$F$2224,$B10) -> 54.08 | G10: =AVERAGEIFS(Pedidos!$J$2:$J$2224,Pedidos!$F$2:$F$2224,$B10) -> 687.52816 | H10: =AVERAGEIFS(Pedidos!$T$2:$T$2224,Pedidos!$F$2:$F$2224,$B10) -> 128.18998 | I10: =AVERAGEIFS(Pedidos!$AC$2:$AC$2224,Pedidos!$F$2:$F$2224,$B10) -> 166.98856 | J10: =I10/H10-1 -> 0.30266472 | K10: =AVERAGEIFS(Pedidos!$AD$2:$AD$2224,Pedidos!$F$2:$F$2224,$B10)/H10-1 -> 0.08513623 | L10: =SUMIFS(Pedidos!$T$2:$T$2224,Pedidos!$F$2:$F$2224,$B10)/SUMIFS(Pedidos!$J$2:$J$2224,Pedidos!$F$2:$F$2224,$B10) -> 0.18645051 | M10: =SUMIFS(Pedidos!$AC$2:$AC$2224,Pedidos!$F$2:$F$2224,$B10)/SUMIFS(Pedidos!$J$2:$J$2224,Pedidos!$F$2:$F$2224,$B10) -> 0.2428825 | N10: =COUNTIFS(Pedidos!$F$2:$F$2224,$B10,Pedidos!$AG$2:$AG$2224,"SIM")/D10 -> 0.081632653 | O10: =SUMIFS(Pedidos!$U$2:$U$2224,Pedidos!$F$2:$F$2224,$B10)/SUMIFS(Pedidos!$M$2:$M$2224,Pedidos!$F$2:$F$2224,$B10)-1 -> 0.22020884 | P10: =AVERAGEIFS(Pedidos!$AH$2:$AH$2224,Pedidos!$F$2:$F$2224,$B10) -> 10 | Q10: =AVERAGEIFS(Pedidos!$AI$2:$AI$2224,Pedidos!$F$2:$F$2224,$B10) -> 5 | R10: =MAX(0,1-H10/I10) -> 0.23234277 | S10: =IF(J10<=0,"Muito bem",IF(J10<=0.32,"Melhor posição",IF(J10<=0.45,"Intermediária","Precisa melhorar"))) -> Melhor posição
A11: 8 | B11: Macaé | C11: =INDEX(Pedidos!$G$2:$G$2224,MATCH($B11,Pedidos!$F$2:$F$2224,0)) -> Interior | D11: =COUNTIFS(Pedidos!$F$2:$F$2224,$B11) -> 45 | E11: =D11/Resumo!$B$19 -> 0.020242915 | F11: =AVERAGEIFS(Pedidos!$I$2:$I$2224,Pedidos!$F$2:$F$2224,$B11) -> 60.060222 | G11: =AVERAGEIFS(Pedidos!$J$2:$J$2224,Pedidos!$F$2:$F$2224,$B11) -> 746.16467 | H11: =AVERAGEIFS(Pedidos!$T$2:$T$2224,Pedidos!$F$2:$F$2224,$B11) -> 151.23824 | I11: =AVERAGEIFS(Pedidos!$AC$2:$AC$2224,Pedidos!$F$2:$F$2224,$B11) -> 241.39778 | J11: =I11/H11-1 -> 0.59614254 | K11: =AVERAGEIFS(Pedidos!$AD$2:$AD$2224,Pedidos!$F$2:$F$2224,$B11)/H11-1 -> 0.39184416 | L11: =SUMIFS(Pedidos!$T$2:$T$2224,Pedidos!$F$2:$F$2224,$B11)/SUMIFS(Pedidos!$J$2:$J$2224,Pedidos!$F$2:$F$2224,$B11) -> 0.20268748 | M11: =SUMIFS(Pedidos!$AC$2:$AC$2224,Pedidos!$F$2:$F$2224,$B11)/SUMIFS(Pedidos!$J$2:$J$2224,Pedidos!$F$2:$F$2224,$B11) -> 0.32351811 | N11: =COUNTIFS(Pedidos!$F$2:$F$2224,$B11,Pedidos!$AG$2:$AG$2224,"SIM")/D11 -> 0 | O11: =SUMIFS(Pedidos!$U$2:$U$2224,Pedidos!$F$2:$F$2224,$B11)/SUMIFS(Pedidos!$M$2:$M$2224,Pedidos!$F$2:$F$2224,$B11)-1 -> 0.57333132 | P11: =AVERAGEIFS(Pedidos!$AH$2:$AH$2224,Pedidos!$F$2:$F$2224,$B11) -> 13 | Q11: =AVERAGEIFS(Pedidos!$AI$2:$AI$2224,Pedidos!$F$2:$F$2224,$B11) -> 11 | R11: =MAX(0,1-H11/I11) -> 0.37348954 | S11: =IF(J11<=0,"Muito bem",IF(J11<=0.32,"Melhor posição",IF(J11<=0.45,"Intermediária","Precisa melhorar"))) -> Precisa melhorar
A12: 9 | B12: São João de Meriti | C12: =INDEX(Pedidos!$G$2:$G$2224,MATCH($B12,Pedidos!$F$2:$F$2224,0)) -> Metropolitana | D12: =COUNTIFS(Pedidos!$F$2:$F$2224,$B12) -> 37 | E12: =D12/Resumo!$B$19 -> 0.016644175 | F12: =AVERAGEIFS(Pedidos!$I$2:$I$2224,Pedidos!$F$2:$F$2224,$B12) -> 55.930541 | G12: =AVERAGEIFS(Pedidos!$J$2:$J$2224,Pedidos!$F$2:$F$2224,$B12) -> 698.24405 | H12: =AVERAGEIFS(Pedidos!$T$2:$T$2224,Pedidos!$F$2:$F$2224,$B12) -> 133.32206 | I12: =AVERAGEIFS(Pedidos!$AC$2:$AC$2224,Pedidos!$F$2:$F$2224,$B12) -> 175.04377 | J12: =I12/H12-1 -> 0.31293922 | K12: =AVERAGEIFS(Pedidos!$AD$2:$AD$2224,Pedidos!$F$2:$F$2224,$B12)/H12-1 -> 0.097215371 | L12: =SUMIFS(Pedidos!$T$2:$T$2224,Pedidos!$F$2:$F$2224,$B12)/SUMIFS(Pedidos!$J$2:$J$2224,Pedidos!$F$2:$F$2224,$B12) -> 0.19093906 | M12: =SUMIFS(Pedidos!$AC$2:$AC$2224,Pedidos!$F$2:$F$2224,$B12)/SUMIFS(Pedidos!$J$2:$J$2224,Pedidos!$F$2:$F$2224,$B12) -> 0.25069138 | N12: =COUNTIFS(Pedidos!$F$2:$F$2224,$B12,Pedidos!$AG$2:$AG$2224,"SIM")/D12 -> 0.027027027 | O12: =SUMIFS(Pedidos!$U$2:$U$2224,Pedidos!$F$2:$F$2224,$B12)/SUMIFS(Pedidos!$M$2:$M$2224,Pedidos!$F$2:$F$2224,$B12)-1 -> 0.22920267 | P12: =AVERAGEIFS(Pedidos!$AH$2:$AH$2224,Pedidos!$F$2:$F$2224,$B12) -> 10 | Q12: =AVERAGEIFS(Pedidos!$AI$2:$AI$2224,Pedidos!$F$2:$F$2224,$B12) -> 5 | R12: =MAX(0,1-H12/I12) -> 0.23835012 | S12: =IF(J12<=0,"Muito bem",IF(J12<=0.32,"Melhor posição",IF(J12<=0.45,"Intermediária","Precisa melhorar"))) -> Melhor posição
A13: 10 | B13: Volta Redonda | C13: =INDEX(Pedidos!$G$2:$G$2224,MATCH($B13,Pedidos!$F$2:$F$2224,0)) -> Interior | D13: =COUNTIFS(Pedidos!$F$2:$F$2224,$B13) -> 37 | E13: =D13/Resumo!$B$19 -> 0.016644175 | F13: =AVERAGEIFS(Pedidos!$I$2:$I$2224,Pedidos!$F$2:$F$2224,$B13) -> 50.886757 | G13: =AVERAGEIFS(Pedidos!$J$2:$J$2224,Pedidos!$F$2:$F$2224,$B13) -> 652.92108 | H13: =AVERAGEIFS(Pedidos!$T$2:$T$2224,Pedidos!$F$2:$F$2224,$B13) -> 139.32196 | I13: =AVERAGEIFS(Pedidos!$AC$2:$AC$2224,Pedidos!$F$2:$F$2224,$B13) -> 198.53821 | J13: =I13/H13-1 -> 0.42503171 | K13: =AVERAGEIFS(Pedidos!$AD$2:$AD$2224,Pedidos!$F$2:$F$2224,$B13)/H13-1 -> 0.23655307 | L13: =SUMIFS(Pedidos!$T$2:$T$2224,Pedidos!$F$2:$F$2224,$B13)/SUMIFS(Pedidos!$J$2:$J$2224,Pedidos!$F$2:$F$2224,$B13) -> 0.21338255 | M13: =SUMIFS(Pedidos!$AC$2:$AC$2224,Pedidos!$F$2:$F$2224,$B13)/SUMIFS(Pedidos!$J$2:$J$2224,Pedidos!$F$2:$F$2224,$B13) -> 0.30407689 | N13: =COUNTIFS(Pedidos!$F$2:$F$2224,$B13,Pedidos!$AG$2:$AG$2224,"SIM")/D13 -> 0 | O13: =SUMIFS(Pedidos!$U$2:$U$2224,Pedidos!$F$2:$F$2224,$B13)/SUMIFS(Pedidos!$M$2:$M$2224,Pedidos!$F$2:$F$2224,$B13)-1 -> 0.39918634 | P13: =AVERAGEIFS(Pedidos!$AH$2:$AH$2224,Pedidos!$F$2:$F$2224,$B13) -> 13 | Q13: =AVERAGEIFS(Pedidos!$AI$2:$AI$2224,Pedidos!$F$2:$F$2224,$B13) -> 10 | R13: =MAX(0,1-H13/I13) -> 0.29826123 | S13: =IF(J13<=0,"Muito bem",IF(J13<=0.32,"Melhor posição",IF(J13<=0.45,"Intermediária","Precisa melhorar"))) -> Intermediária
A14: 11 | B14: Angra dos Reis | C14: =INDEX(Pedidos!$G$2:$G$2224,MATCH($B14,Pedidos!$F$2:$F$2224,0)) -> Interior | D14: =COUNTIFS(Pedidos!$F$2:$F$2224,$B14) -> 35 | E14: =D14/Resumo!$B$19 -> 0.015744489 | F14: =AVERAGEIFS(Pedidos!$I$2:$I$2224,Pedidos!$F$2:$F$2224,$B14) -> 44.394286 | G14: =AVERAGEIFS(Pedidos!$J$2:$J$2224,Pedidos!$F$2:$F$2224,$B14) -> 596.41771 | H14: =AVERAGEIFS(Pedidos!$T$2:$T$2224,Pedidos!$F$2:$F$2224,$B14) -> 129.13126 | I14: =AVERAGEIFS(Pedidos!$AC$2:$AC$2224,Pedidos!$F$2:$F$2224,$B14) -> 179.38259 | J14: =I14/H14-1 -> 0.38914922 | K14: =AVERAGEIFS(Pedidos!$AD$2:$AD$2224,Pedidos!$F$2:$F$2224,$B14)/H14-1 -> 0.21173989 | L14: =SUMIFS(Pedidos!$T$2:$T$2224,Pedidos!$F$2:$F$2224,$B14)/SUMIFS(Pedidos!$J$2:$J$2224,Pedidos!$F$2:$F$2224,$B14) -> 0.21651145 | M14: =SUMIFS(Pedidos!$AC$2:$AC$2224,Pedidos!$F$2:$F$2224,$B14)/SUMIFS(Pedidos!$J$2:$J$2224,Pedidos!$F$2:$F$2224,$B14) -> 0.30076671 | N14: =COUNTIFS(Pedidos!$F$2:$F$2224,$B14,Pedidos!$AG$2:$AG$2224,"SIM")/D14 -> 0 | O14: =SUMIFS(Pedidos!$U$2:$U$2224,Pedidos!$F$2:$F$2224,$B14)/SUMIFS(Pedidos!$M$2:$M$2224,Pedidos!$F$2:$F$2224,$B14)-1 -> 0.38186034 | P14: =AVERAGEIFS(Pedidos!$AH$2:$AH$2224,Pedidos!$F$2:$F$2224,$B14) -> 13 | Q14: =AVERAGEIFS(Pedidos!$AI$2:$AI$2224,Pedidos!$F$2:$F$2224,$B14) -> 10 | R14: =MAX(0,1-H14/I14) -> 0.28013493 | S14: =IF(J14<=0,"Muito bem",IF(J14<=0.32,"Melhor posição",IF(J14<=0.45,"Intermediária","Precisa melhorar"))) -> Intermediária
A15: 12 | B15: Petrópolis | C15: =INDEX(Pedidos!$G$2:$G$2224,MATCH($B15,Pedidos!$F$2:$F$2224,0)) -> Interior | D15: =COUNTIFS(Pedidos!$F$2:$F$2224,$B15) -> 32 | E15: =D15/Resumo!$B$19 -> 0.014394962 | F15: =AVERAGEIFS(Pedidos!$I$2:$I$2224,Pedidos!$F$2:$F$2224,$B15) -> 58.889375 | G15: =AVERAGEIFS(Pedidos!$J$2:$J$2224,Pedidos!$F$2:$F$2224,$B15) -> 743.8225 | H15: =AVERAGEIFS(Pedidos!$T$2:$T$2224,Pedidos!$F$2:$F$2224,$B15) -> 149.92911 | I15: =AVERAGEIFS(Pedidos!$AC$2:$AC$2224,Pedidos!$F$2:$F$2224,$B15) -> 216.62809 | J15: =I15/H15-1 -> 0.4448701 | K15: =AVERAGEIFS(Pedidos!$AD$2:$AD$2224,Pedidos!$F$2:$F$2224,$B15)/H15-1 -> 0.24257279 | L15: =SUMIFS(Pedidos!$T$2:$T$2224,Pedidos!$F$2:$F$2224,$B15)/SUMIFS(Pedidos!$J$2:$J$2224,Pedidos!$F$2:$F$2224,$B15) -> 0.20156571 | M15: =SUMIFS(Pedidos!$AC$2:$AC$2224,Pedidos!$F$2:$F$2224,$B15)/SUMIFS(Pedidos!$J$2:$J$2224,Pedidos!$F$2:$F$2224,$B15) -> 0.29123627 | N15: =COUNTIFS(Pedidos!$F$2:$F$2224,$B15,Pedidos!$AG$2:$AG$2224,"SIM")/D15 -> 0 | O15: =SUMIFS(Pedidos!$U$2:$U$2224,Pedidos!$F$2:$F$2224,$B15)/SUMIFS(Pedidos!$M$2:$M$2224,Pedidos!$F$2:$F$2224,$B15)-1 -> 0.39455971 | P15: =AVERAGEIFS(Pedidos!$AH$2:$AH$2224,Pedidos!$F$2:$F$2224,$B15) -> 13 | Q15: =AVERAGEIFS(Pedidos!$AI$2:$AI$2224,Pedidos!$F$2:$F$2224,$B15) -> 8 | R15: =MAX(0,1-H15/I15) -> 0.30789626 | S15: =IF(J15<=0,"Muito bem",IF(J15<=0.32,"Melhor posição",IF(J15<=0.45,"Intermediária","Precisa melhorar"))) -> Intermediária
... A23: 20 | B23: Rio das Ostras | C23: =INDEX(Pedidos!$G$2:$G$2224,MATCH($B23,Pedidos!$F$2:$F$2224,0)) -> Interior | D23: =COUNTIFS(Pedidos!$F$2:$F$2224,$B23) -> 18 | E23: =D23/Resumo!$B$19 -> 0.008097166 | F23: =AVERAGEIFS(Pedidos!$I$2:$I$2224,Pedidos!$F$2:$F$2224,$B23) -> 47.438889 | G23: =AVERAGEIFS(Pedidos!$J$2:$J$2224,Pedidos!$F$2:$F$2224,$B23) -> 604.15056 | H23: =AVERAGEIFS(Pedidos!$T$2:$T$2224,Pedidos!$F$2:$F$2224,$B23) -> 132.43506 | I23: =AVERAGEIFS(Pedidos!$AC$2:$AC$2224,Pedidos!$F$2:$F$2224,$B23) -> 190.52993 | J23: =I23/H23-1 -> 0.43866688 | K23: =AVERAGEIFS(Pedidos!$AD$2:$AD$2224,Pedidos!$F$2:$F$2224,$B23)/H23-1 -> 0.25461441 | L23: =SUMIFS(Pedidos!$T$2:$T$2224,Pedidos!$F$2:$F$2224,$B23)/SUMIFS(Pedidos!$J$2:$J$2224,Pedidos!$F$2:$F$2224,$B23) -> 0.2192087 | M23: =SUMIFS(Pedidos!$AC$2:$AC$2224,Pedidos!$F$2:$F$2224,$B23)/SUMIFS(Pedidos!$J$2:$J$2224,Pedidos!$F$2:$F$2224,$B23) -> 0.3153683 | N23: =COUNTIFS(Pedidos!$F$2:$F$2224,$B23,Pedidos!$AG$2:$AG$2224,"SIM")/D23 -> 0 | O23: =SUMIFS(Pedidos!$U$2:$U$2224,Pedidos!$F$2:$F$2224,$B23)/SUMIFS(Pedidos!$M$2:$M$2224,Pedidos!$F$2:$F$2224,$B23)-1 -> 0.42977503 | P23: =AVERAGEIFS(Pedidos!$AH$2:$AH$2224,Pedidos!$F$2:$F$2224,$B23) -> 13 | Q23: =AVERAGEIFS(Pedidos!$AI$2:$AI$2224,Pedidos!$F$2:$F$2224,$B23) -> 10 | R23: =MAX(0,1-H23/I23) -> 0.30491206 | S23: =IF(J23<=0,"Muito bem",IF(J23<=0.32,"Melhor posição",IF(J23<=0.45,"Intermediária","Precisa melhorar"))) -> Intermediária
B24: TOTAL TOP 20 | D24: =SUM(D4:D23) -> 1912 | E24: =D24/Resumo!$B$19 -> 0.86009897 | F24: =AVERAGEIFS(Pedidos!$I$2:$I$2224,Pedidos!$AJ$2:$AJ$2224,"SIM") -> 49.45444 | G24: =AVERAGEIFS(Pedidos!$J$2:$J$2224,Pedidos!$AJ$2:$AJ$2224,"SIM") -> 636.04536 | H24: =AVERAGEIFS(Pedidos!$T$2:$T$2224,Pedidos!$AJ$2:$AJ$2224,"SIM") -> 118.44739 | I24: =AVERAGEIFS(Pedidos!$AC$2:$AC$2224,Pedidos!$AJ$2:$AJ$2224,"SIM") -> 169.56633 | J24: =I24/H24-1 -> 0.43157508 | K24: =AVERAGEIFS(Pedidos!$AD$2:$AD$2224,Pedidos!$AJ$2:$AJ$2224,"SIM")/H24-1 -> 0.21632815 | L24: =SUMIFS(Pedidos!$T$2:$T$2224,Pedidos!$AJ$2:$AJ$2224,"SIM")/SUMIFS(Pedidos!$J$2:$J$2224,Pedidos!$AJ$2:$AJ$2224,"SIM") -> 0.18622475 | M24: =SUMIFS(Pedidos!$AC$2:$AC$2224,Pedidos!$AJ$2:$AJ$2224,"SIM")/SUMIFS(Pedidos!$J$2:$J$2224,Pedidos!$AJ$2:$AJ$2224,"SIM") -> 0.2665947 | N24: =COUNTIFS(Pedidos!$AJ$2:$AJ$2224,"SIM",Pedidos!$AG$2:$AG$2224,"SIM")/D24 -> 0.0073221757 | O24: =SUMIFS(Pedidos!$U$2:$U$2224,Pedidos!$AJ$2:$AJ$2224,"SIM")/SUMIFS(Pedidos!$M$2:$M$2224,Pedidos!$AJ$2:$AJ$2224,"SIM")-1 -> 0.39376569 | P24: =AVERAGEIFS(Pedidos!$AH$2:$AH$2224,Pedidos!$AJ$2:$AJ$2224,"SIM") -> 9.5047071 | Q24: =AVERAGEIFS(Pedidos!$AI$2:$AI$2224,Pedidos!$AJ$2:$AJ$2224,"SIM") -> 6.0690377 | R24: =MAX(0,1-H24/I24) -> 0.3014687
A26: Avaliação: "Muito bem" = PROLOG mais barata; "Melhor posição" = até +32%; "Intermediária" = +32% a +45%; "Precisa melhorar" = acima de +45%.

Sheet Faixa x Região
A1: Por faixa de peso e região TSL — preço final PROLOG x TSL (mesmos pedidos, top 20 cidades)
A3: Região: TODAS
A4: Faixa (kg) | B4: Pedidos | C4: TSL médio | D4: PROLOG médio | E4: PROLOG vs TSL | F4: PROLOG s/ taxa interna vs TSL | G4: TSL frete peso | H4: PROLOG frete peso | I4: Frete peso PROLOG vs TSL | J4: % pedidos PROLOG ganharia | K4: Redução necessária
A5: 0-20 | B5: =COUNTIFS(Pedidos!$AJ$2:$AJ$2224,"SIM",Pedidos!$H$2:$H$2224,$A5) -> 96 | C5: =IFERROR(AVERAGEIFS(Pedidos!$T$2:$T$2224,Pedidos!$AJ$2:$AJ$2224,"SIM",Pedidos!$H$2:$H$2224,$A5),"") -> 68.642848 | D5: =IFERROR(AVERAGEIFS(Pedidos!$AC$2:$AC$2224,Pedidos!$AJ$2:$AJ$2224,"SIM",Pedidos!$H$2:$H$2224,$A5),"") -> 76.075222 | E5: =IFERROR(D5/C5-1,"") -> 0.10827601 | F5: =IFERROR(AVERAGEIFS(Pedidos!$AD$2:$AD$2224,Pedidos!$AJ$2:$AJ$2224,"SIM",Pedidos!$H$2:$H$2224,$A5)/C5-1,"") -> -0.025351679 | G5: =IFERROR(AVERAGEIFS(Pedidos!$M$2:$M$2224,Pedidos!$AJ$2:$AJ$2224,"SIM",Pedidos!$H$2:$H$2224,$A5),"") -> 43.118333 | H5: =IFERROR(AVERAGEIFS(Pedidos!$U$2:$U$2224,Pedidos!$AJ$2:$AJ$2224,"SIM",Pedidos!$H$2:$H$2224,$A5),"") -> 51.369375 | I5: =IFERROR(H5/G5-1,"") -> 0.19135808 | J5: =IFERROR(COUNTIFS(Pedidos!$AJ$2:$AJ$2224,"SIM",Pedidos!$H$2:$H$2224,$A5,Pedidos!$AG$2:$AG$2224,"SIM")/B5,"") -> 0.14583333 | K5: =IFERROR(MAX(0,1-C5/D5),"") -> 0.097697694
A6: 20-35 | B6: =COUNTIFS(Pedidos!$AJ$2:$AJ$2224,"SIM",Pedidos!$H$2:$H$2224,$A6) -> 431 | C6: =IFERROR(AVERAGEIFS(Pedidos!$T$2:$T$2224,Pedidos!$AJ$2:$AJ$2224,"SIM",Pedidos!$H$2:$H$2224,$A6),"") -> 91.344054 | D6: =IFERROR(AVERAGEIFS(Pedidos!$AC$2:$AC$2224,Pedidos!$AJ$2:$AJ$2224,"SIM",Pedidos!$H$2:$H$2224,$A6),"") -> 127.44455 | E6: =IFERROR(D6/C6-1,"") -> 0.39521448 | F6: =IFERROR(AVERAGEIFS(Pedidos!$AD$2:$AD$2224,Pedidos!$AJ$2:$AJ$2224,"SIM",Pedidos!$H$2:$H$2224,$A6)/C6-1,"") -> 0.23503539 | G6: =IFERROR(AVERAGEIFS(Pedidos!$M$2:$M$2224,Pedidos!$AJ$2:$AJ$2224,"SIM",Pedidos!$H$2:$H$2224,$A6),"") -> 61.564501 | H6: =IFERROR(AVERAGEIFS(Pedidos!$U$2:$U$2224,Pedidos!$AJ$2:$AJ$2224,"SIM",Pedidos!$H$2:$H$2224,$A6),"") -> 90.763039 | I6: =IFERROR(H6/G6-1,"") -> 0.47427556 | J6: =IFERROR(COUNTIFS(Pedidos!$AJ$2:$AJ$2224,"SIM",Pedidos!$H$2:$H$2224,$A6,Pedidos!$AG$2:$AG$2224,"SIM")/B6,"") -> 0 | K6: =IFERROR(MAX(0,1-C6/D6),"") -> 0.28326432
A7: 35-40 | B7: =COUNTIFS(Pedidos!$AJ$2:$AJ$2224,"SIM",Pedidos!$H$2:$H$2224,$A7) -> 299 | C7: =IFERROR(AVERAGEIFS(Pedidos!$T$2:$T$2224,Pedidos!$AJ$2:$AJ$2224,"SIM",Pedidos!$H$2:$H$2224,$A7),"") -> 103.67513 | D7: =IFERROR(AVERAGEIFS(Pedidos!$AC$2:$AC$2224,Pedidos!$AJ$2:$AJ$2224,"SIM",Pedidos!$H$2:$H$2224,$A7),"") -> 146.77366 | E7: =IFERROR(D7/C7-1,"") -> 0.41570759 | F7: =IFERROR(AVERAGEIFS(Pedidos!$AD$2:$AD$2224,Pedidos!$AJ$2:$AJ$2224,"SIM",Pedidos!$H$2:$H$2224,$A7)/C7-1,"") -> 0.22796426 | G7: =IFERROR(AVERAGEIFS(Pedidos!$M$2:$M$2224,Pedidos!$AJ$2:$AJ$2224,"SIM",Pedidos!$H$2:$H$2224,$A7),"") -> 71.714214 | H7: =IFERROR(AVERAGEIFS(Pedidos!$U$2:$U$2224,Pedidos!$AJ$2:$AJ$2224,"SIM",Pedidos!$H$2:$H$2224,$A7),"") -> 102.8507 | I7: =IFERROR(H7/G7-1,"") -> 0.43417457 | J7: =IFERROR(COUNTIFS(Pedidos!$AJ$2:$AJ$2224,"SIM",Pedidos!$H$2:$H$2224,$A7,Pedidos!$AG$2:$AG$2224,"SIM")/B7,"") -> 0 | K7: =IFERROR(MAX(0,1-C7/D7),"") -> 0.29363944
A8: 40-50 | B8: =COUNTIFS(Pedidos!$AJ$2:$AJ$2224,"SIM",Pedidos!$H$2:$H$2224,$A8) -> 305 | C8: =IFERROR(AVERAGEIFS(Pedidos!$T$2:$T$2224,Pedidos!$AJ$2:$AJ$2224,"SIM",Pedidos!$H$2:$H$2224,$A8),"") -> 113.02112 | D8: =IFERROR(AVERAGEIFS(Pedidos!$AC$2:$AC$2224,Pedidos!$AJ$2:$AJ$2224,"SIM",Pedidos!$H$2:$H$2224,$A8),"") -> 153.47146 | E8: =IFERROR(D8/C8-1,"") -> 0.35790074 | F8: =IFERROR(AVERAGEIFS(Pedidos!$AD$2:$AD$2224,Pedidos!$AJ$2:$AJ$2224,"SIM",Pedidos!$H$2:$H$2224,$A8)/C8-1,"") -> 0.14888384 | G8: =IFERROR(AVERAGEIFS(Pedidos!$M$2:$M$2224,Pedidos!$AJ$2:$AJ$2224,"SIM",Pedidos!$H$2:$H$2224,$A8),"") -> 78.958197 | H8: =IFERROR(AVERAGEIFS(Pedidos!$U$2:$U$2224,Pedidos!$AJ$2:$AJ$2224,"SIM",Pedidos!$H$2:$H$2224,$A8),"") -> 104.18305 | I8: =IFERROR(H8/G8-1,"") -> 0.31947098 | J8: =IFERROR(COUNTIFS(Pedidos!$AJ$2:$AJ$2224,"SIM",Pedidos!$H$2:$H$2224,$A8,Pedidos!$AG$2:$AG$2224,"SIM")/B8,"") -> 0 | K8: =IFERROR(MAX(0,1-C8/D8),"") -> 0.26356915
A9: 50-60 | B9: =COUNTIFS(Pedidos!$AJ$2:$AJ$2224,"SIM",Pedidos!$H$2:$H$2224,$A9) -> 361 | C9: =IFERROR(AVERAGEIFS(Pedidos!$T$2:$T$2224,Pedidos!$AJ$2:$AJ$2224,"SIM",Pedidos!$H$2:$H$2224,$A9),"") -> 124.08632 | D9: =IFERROR(AVERAGEIFS(Pedidos!$AC$2:$AC$2224,Pedidos!$AJ$2:$AJ$2224,"SIM",Pedidos!$H$2:$H$2224,$A9),"") -> 176.4498 | E9: =IFERROR(D9/C9-1,"") -> 0.4219923 | F9: =IFERROR(AVERAGEIFS(Pedidos!$AD$2:$AD$2224,Pedidos!$AJ$2:$AJ$2224,"SIM",Pedidos!$H$2:$H$2224,$A9)/C9-1,"") -> 0.19814381 | G9: =IFERROR(AVERAGEIFS(Pedidos!$M$2:$M$2224,Pedidos!$AJ$2:$AJ$2224,"SIM",Pedidos!$H$2:$H$2224,$A9),"") -> 87.816094 | H9: =IFERROR(AVERAGEIFS(Pedidos!$U$2:$U$2224,Pedidos!$AJ$2:$AJ$2224,"SIM",Pedidos!$H$2:$H$2224,$A9),"") -> 119.98296 | I9: =IFERROR(H9/G9-1,"") -> 0.36629812 | J9: =IFERROR(COUNTIFS(Pedidos!$AJ$2:$AJ$2224,"SIM",Pedidos!$H$2:$H$2224,$A9,Pedidos!$AG$2:$AG$2224,"SIM")/B9,"") -> 0 | K9: =IFERROR(MAX(0,1-C9/D9),"") -> 0.29676131
A10: 60-70 | B10: =COUNTIFS(Pedidos!$AJ$2:$AJ$2224,"SIM",Pedidos!$H$2:$H$2224,$A10) -> 228 | C10: =IFERROR(AVERAGEIFS(Pedidos!$T$2:$T$2224,Pedidos!$AJ$2:$AJ$2224,"SIM",Pedidos!$H$2:$H$2224,$A10),"") -> 135.81146 | D10: =IFERROR(AVERAGEIFS(Pedidos!$AC$2:$AC$2224,Pedidos!$AJ$2:$AJ$2224,"SIM",Pedidos!$H$2:$H$2224,$A10),"") -> 206.19741 | E10: =IFERROR(D10/C10-1,"") -> 0.51826217 | F10: =IFERROR(AVERAGEIFS(Pedidos!$AD$2:$AD$2224,Pedidos!$AJ$2:$AJ$2224,"SIM",Pedidos!$H$2:$H$2224,$A10)/C10-1,"") -> 0.26846779 | G10: =IFERROR(AVERAGEIFS(Pedidos!$M$2:$M$2224,Pedidos!$AJ$2:$AJ$2224,"SIM",Pedidos!$H$2:$H$2224,$A10),"") -> 97.341228 | H10: =IFERROR(AVERAGEIFS(Pedidos!$U$2:$U$2224,Pedidos!$AJ$2:$AJ$2224,"SIM",Pedidos!$H$2:$H$2224,$A10),"") -> 139.83754 | I10: =IFERROR(H10/G10-1,"") -> 0.43657057 | J10: =IFERROR(COUNTIFS(Pedidos!$AJ$2:$AJ$2224,"SIM",Pedidos!$H$2:$H$2224,$A10,Pedidos!$AG$2:$AG$2224,"SIM")/B10,"") -> 0 | K10: =IFERROR(MAX(0,1-C10/D10),"") -> 0.34135223
A11: 70-80 | B11: =COUNTIFS(Pedidos!$AJ$2:$AJ$2224,"SIM",Pedidos!$H$2:$H$2224,$A11) -> 24 | C11: =IFERROR(AVERAGEIFS(Pedidos!$T$2:$T$2224,Pedidos!$AJ$2:$AJ$2224,"SIM",Pedidos!$H$2:$H$2224,$A11),"") -> 148.21552 | D11: =IFERROR(AVERAGEIFS(Pedidos!$AC$2:$AC$2224,Pedidos!$AJ$2:$AJ$2224,"SIM",Pedidos!$H$2:$H$2224,$A11),"") -> 211.16087 | E11: =IFERROR(D11/C11-1,"") -> 0.42468802 | F11: =IFERROR(AVERAGEIFS(Pedidos!$AD$2:$AD$2224,Pedidos!$AJ$2:$AJ$2224,"SIM",Pedidos!$H$2:$H$2224,$A11)/C11-1,"") -> 0.1673654 | G11: =IFERROR(AVERAGEIFS(Pedidos!$M$2:$M$2224,Pedidos!$AJ$2:$AJ$2224,"SIM",Pedidos!$H$2:$H$2224,$A11),"") -> 106.88292 | H11: =IFERROR(AVERAGEIFS(Pedidos!$U$2:$U$2224,Pedidos!$AJ$2:$AJ$2224,"SIM",Pedidos!$H$2:$H$2224,$A11),"") -> 139.39875 | I11: =IFERROR(H11/G11-1,"") -> 0.30421918 | J11: =IFERROR(COUNTIFS(Pedidos!$AJ$2:$AJ$2224,"SIM",Pedidos!$H$2:$H$2224,$A11,Pedidos!$AG$2:$AG$2224,"SIM")/B11,"") -> 0 | K11: =IFERROR(MAX(0,1-C11/D11),"") -> 0.29809194
A12: 80-100 | B12: =COUNTIFS(Pedidos!$AJ$2:$AJ$2224,"SIM",Pedidos!$H$2:$H$2224,$A12) -> 43 | C12: =IFERROR(AVERAGEIFS(Pedidos!$T$2:$T$2224,Pedidos!$AJ$2:$AJ$2224,"SIM",Pedidos!$H$2:$H$2224,$A12),"") -> 175.11375 | D12: =IFERROR(AVERAGEIFS(Pedidos!$AC$2:$AC$2224,Pedidos!$AJ$2:$AJ$2224,"SIM",Pedidos!$H$2:$H$2224,$A12),"") -> 262.07559 | E12: =IFERROR(D12/C12-1,"") -> 0.49660203 | F12: =IFERROR(AVERAGEIFS(Pedidos!$AD$2:$AD$2224,Pedidos!$AJ$2:$AJ$2224,"SIM",Pedidos!$H$2:$H$2224,$A12)/C12-1,"") -> 0.2402374 | G12: =IFERROR(AVERAGEIFS(Pedidos!$M$2:$M$2224,Pedidos!$AJ$2:$AJ$2224,"SIM",Pedidos!$H$2:$H$2224,$A12),"") -> 129.31744 | H12: =IFERROR(AVERAGEIFS(Pedidos!$U$2:$U$2224,Pedidos!$AJ$2:$AJ$2224,"SIM",Pedidos!$H$2:$H$2224,$A12),"") -> 177.46651 | I12: =IFERROR(H12/G12-1,"") -> 0.37233237 | J12: =IFERROR(COUNTIFS(Pedidos!$AJ$2:$AJ$2224,"SIM",Pedidos!$H$2:$H$2224,$A12,Pedidos!$AG$2:$AG$2224,"SIM")/B12,"") -> 0 | K12: =IFERROR(MAX(0,1-C12/D12),"") -> 0.3318197
A13: 100-120 | B13: =COUNTIFS(Pedidos!$AJ$2:$AJ$2224,"SIM",Pedidos!$H$2:$H$2224,$A13) -> 47 | C13: =IFERROR(AVERAGEIFS(Pedidos!$T$2:$T$2224,Pedidos!$AJ$2:$AJ$2224,"SIM",Pedidos!$H$2:$H$2224,$A13),"") -> 194.6799 | D13: =IFERROR(AVERAGEIFS(Pedidos!$AC$2:$AC$2224,Pedidos!$AJ$2:$AJ$2224,"SIM",Pedidos!$H$2:$H$2224,$A13),"") -> 316.24233 | E13: =IFERROR(D13/C13-1,"") -> 0.62442207 | F13: =IFERROR(AVERAGEIFS(Pedidos!$AD$2:$AD$2224,Pedidos!$AJ$2:$AJ$2224,"SIM",Pedidos!$H$2:$H$2224,$A13)/C13-1,"") -> 0.33364196 | G13: =IFERROR(AVERAGEIFS(Pedidos!$M$2:$M$2224,Pedidos!$AJ$2:$AJ$2224,"SIM",Pedidos!$H$2:$H$2224,$A13),"") -> 143.59872 | H13: =IFERROR(AVERAGEIFS(Pedidos!$U$2:$U$2224,Pedidos!$AJ$2:$AJ$2224,"SIM",Pedidos!$H$2:$H$2224,$A13),"") -> 208.16894 | I13: =IFERROR(H13/G13-1,"") -> 0.44965729 | J13: =IFERROR(COUNTIFS(Pedidos!$AJ$2:$AJ$2224,"SIM",Pedidos!$H$2:$H$2224,$A13,Pedidos!$AG$2:$AG$2224,"SIM")/B13,"") -> 0 | K13: =IFERROR(MAX(0,1-C13/D13),"") -> 0.38439644
A14: 120-150 | B14: =COUNTIFS(Pedidos!$AJ$2:$AJ$2224,"SIM",Pedidos!$H$2:$H$2224,$A14) -> 73 | C14: =IFERROR(AVERAGEIFS(Pedidos!$T$2:$T$2224,Pedidos!$AJ$2:$AJ$2224,"SIM",Pedidos!$H$2:$H$2224,$A14),"") -> 242.63268 | D14: =IFERROR(AVERAGEIFS(Pedidos!$AC$2:$AC$2224,Pedidos!$AJ$2:$AJ$2224,"SIM",Pedidos!$H$2:$H$2224,$A14),"") -> 369.59085 | E14: =IFERROR(D14/C14-1,"") -> 0.52325259 | F14: =IFERROR(AVERAGEIFS(Pedidos!$AD$2:$AD$2224,Pedidos!$AJ$2:$AJ$2224,"SIM",Pedidos!$H$2:$H$2224,$A14)/C14-1,"") -> 0.25108826 | G14: =IFERROR(AVERAGEIFS(Pedidos!$M$2:$M$2224,Pedidos!$AJ$2:$AJ$2224,"SIM",Pedidos!$H$2:$H$2224,$A14),"") -> 181.90644 | H14: =IFERROR(AVERAGEIFS(Pedidos!$U$2:$U$2224,Pedidos!$AJ$2:$AJ$2224,"SIM",Pedidos!$H$2:$H$2224,$A14),"") -> 244.44575 | I14: =IFERROR(H14/G14-1,"") -> 0.34379935 | J14: =IFERROR(COUNTIFS(Pedidos!$AJ$2:$AJ$2224,"SIM",Pedidos!$H$2:$H$2224,$A14,Pedidos!$AG$2:$AG$2224,"SIM")/B14,"") -> 0 | K14: =IFERROR(MAX(0,1-C14/D14),"") -> 0.34351006
A15: 150-170 | B15: =COUNTIFS(Pedidos!$AJ$2:$AJ$2224,"SIM",Pedidos!$H$2:$H$2224,$A15) -> 3 | C15: =IFERROR(AVERAGEIFS(Pedidos!$T$2:$T$2224,Pedidos!$AJ$2:$AJ$2224,"SIM",Pedidos!$H$2:$H$2224,$A15),"") -> 259.73784 | D15: =IFERROR(AVERAGEIFS(Pedidos!$AC$2:$AC$2224,Pedidos!$AJ$2:$AJ$2224,"SIM",Pedidos!$H$2:$H$2224,$A15),"") -> 423.50097 | E15: =IFERROR(D15/C15-1,"") -> 0.63049395 | F15: =IFERROR(AVERAGEIFS(Pedidos!$AD$2:$AD$2224,Pedidos!$AJ$2:$AJ$2224,"SIM",Pedidos!$H$2:$H$2224,$A15)/C15-1,"") -> 0.31352225 | G15: =IFERROR(AVERAGEIFS(Pedidos!$M$2:$M$2224,Pedidos!$AJ$2:$AJ$2224,"SIM",Pedidos!$H$2:$H$2224,$A15),"") -> 195.11667 | H15: =IFERROR(AVERAGEIFS(Pedidos!$U$2:$U$2224,Pedidos!$AJ$2:$AJ$2224,"SIM",Pedidos!$H$2:$H$2224,$A15),"") -> 274.84333 | I15: =IFERROR(H15/G15-1,"") -> 0.40861023 | J15: =IFERROR(COUNTIFS(Pedidos!$AJ$2:$AJ$2224,"SIM",Pedidos!$H$2:$H$2224,$A15,Pedidos!$AG$2:$AG$2224,"SIM")/B15,"") -> 0 | K15: =IFERROR(MAX(0,1-C15/D15),"") -> 0.38668892
A16: 170-200 | B16: =COUNTIFS(Pedidos!$AJ$2:$AJ$2224,"SIM",Pedidos!$H$2:$H$2224,$A16) -> 1 | C16: =IFERROR(AVERAGEIFS(Pedidos!$T$2:$T$2224,Pedidos!$AJ$2:$AJ$2224,"SIM",Pedidos!$H$2:$H$2224,$A16),"") -> 198.27526 | D16: =IFERROR(AVERAGEIFS(Pedidos!$AC$2:$AC$2224,Pedidos!$AJ$2:$AJ$2224,"SIM",Pedidos!$H$2:$H$2224,$A16),"") -> 529.025 | E16: =IFERROR(D16/C16-1,"") -> 1.6681342 | F16: =IFERROR(AVERAGEIFS(Pedidos!$AD$2:$AD$2224,Pedidos!$AJ$2:$AJ$2224,"SIM",Pedidos!$H$2:$H$2224,$A16)/C16-1,"") -> 1.180692 | G16: =IFERROR(AVERAGEIFS(Pedidos!$M$2:$M$2224,Pedidos!$AJ$2:$AJ$2224,"SIM",Pedidos!$H$2:$H$2224,$A16),"") -> 143.51 | H16: =IFERROR(AVERAGEIFS(Pedidos!$U$2:$U$2224,Pedidos!$AJ$2:$AJ$2224,"SIM",Pedidos!$H$2:$H$2224,$A16),"") -> 353.17 | I16: =IFERROR(H16/G16-1,"") -> 1.4609435 | J16: =IFERROR(COUNTIFS(Pedidos!$AJ$2:$AJ$2224,"SIM",Pedidos!$H$2:$H$2224,$A16,Pedidos!$AG$2:$AG$2224,"SIM")/B16,"") -> 0 | K16: =IFERROR(MAX(0,1-C16/D16),"") -> 0.62520625
A17: 200-250 | B17: =COUNTIFS(Pedidos!$AJ$2:$AJ$2224,"SIM",Pedidos!$H$2:$H$2224,$A17) -> 1 | C17: =IFERROR(AVERAGEIFS(Pedidos!$T$2:$T$2224,Pedidos!$AJ$2:$AJ$2224,"SIM",Pedidos!$H$2:$H$2224,$A17),"") -> 355.2278 | D17: =IFERROR(AVERAGEIFS(Pedidos!$AC$2:$AC$2224,Pedidos!$AJ$2:$AJ$2224,"SIM",Pedidos!$H$2:$H$2224,$A17),"") -> 593.32707 | E17: =IFERROR(D17/C17-1,"") -> 0.67027204 | F17: =IFERROR(AVERAGEIFS(Pedidos!$AD$2:$AD$2224,Pedidos!$AJ$2:$AJ$2224,"SIM",Pedidos!$H$2:$H$2224,$A17)/C17-1,"") -> 0.38092507 | G17: =IFERROR(AVERAGEIFS(Pedidos!$M$2:$M$2224,Pedidos!$AJ$2:$AJ$2224,"SIM",Pedidos!$H$2:$H$2224,$A17),"") -> 272.9 | H17: =IFERROR(AVERAGEIFS(Pedidos!$U$2:$U$2224,Pedidos!$AJ$2:$AJ$2224,"SIM",Pedidos!$H$2:$H$2224,$A17),"") -> 398.74 | I17: =IFERROR(H17/G17-1,"") -> 0.46112129 | J17: =IFERROR(COUNTIFS(Pedidos!$AJ$2:$AJ$2224,"SIM",Pedidos!$H$2:$H$2224,$A17,Pedidos!$AG$2:$AG$2224,"SIM")/B17,"") -> 0 | K17: =IFERROR(MAX(0,1-C17/D17),"") -> 0.40129513
A18: TOTAL | B18: =COUNTIFS(Pedidos!$AJ$2:$AJ$2224,"SIM") -> 1912 | C18: =IFERROR(AVERAGEIFS(Pedidos!$T$2:$T$2224,Pedidos!$AJ$2:$AJ$2224,"SIM"),"") -> 118.44739 | D18: =IFERROR(AVERAGEIFS(Pedidos!$AC$2:$AC$2224,Pedidos!$AJ$2:$AJ$2224,"SIM"),"") -> 169.56633 | E18: =IFERROR(D18/C18-1,"") -> 0.43157508 | F18: =IFERROR(AVERAGEIFS(Pedidos!$AD$2:$AD$2224,Pedidos!$AJ$2:$AJ$2224,"SIM")/C18-1,"") -> 0.21632815 | G18: =IFERROR(AVERAGEIFS(Pedidos!$M$2:$M$2224,Pedidos!$AJ$2:$AJ$2224,"SIM"),"") -> 83.289634 | H18: =IFERROR(AVERAGEIFS(Pedidos!$U$2:$U$2224,Pedidos!$AJ$2:$AJ$2224,"SIM"),"") -> 116.08623 | I18: =IFERROR(H18/G18-1,"") -> 0.39376569 | J18: =IFERROR(COUNTIFS(Pedidos!$AJ$2:$AJ$2224,"SIM",Pedidos!$AG$2:$AG$2224,"SIM")/B18,"") -> 0.0073221757 | K18: =IFERROR(MAX(0,1-C18/D18),"") -> 0.3014687
A20: Região: Capital
A21: Faixa (kg) | B21: Pedidos | C21: TSL médio | D21: PROLOG médio | E21: PROLOG vs TSL | F21: PROLOG s/ taxa interna vs TSL | G21: TSL frete peso | H21: PROLOG frete peso | I21: Frete peso PROLOG vs TSL | J21: % pedidos PROLOG ganharia | K21: Redução necessária
A22: 0-20 | B22: =COUNTIFS(Pedidos!$AJ$2:$AJ$2224,"SIM",Pedidos!$G$2:$G$2224,"Capital",Pedidos!$H$2:$H$2224,$A22) -> 64 | C22: =IFERROR(AVERAGEIFS(Pedidos!$T$2:$T$2224,Pedidos!$AJ$2:$AJ$2224,"SIM",Pedidos!$G$2:$G$2224,"Capital",Pedidos!$H$2:$H$2224,$A22),"") -> 64.649099 | D22: =IFERROR(AVERAGEIFS(Pedidos!$AC$2:$AC$2224,Pedidos!$AJ$2:$AJ$2224,"SIM",Pedidos!$G$2:$G$2224,"Capital",Pedidos!$H$2:$H$2224,$A22),"") -> 70.923919 | E22: =IFERROR(D22/C22-1,"") -> 0.097059663 | F22: =IFERROR(AVERAGEIFS(Pedidos!$AD$2:$AD$2224,Pedidos!$AJ$2:$AJ$2224,"SIM",Pedidos!$G$2:$G$2224,"Capital",Pedidos!$H$2:$H$2224,$A22)/C22-1,"") -> -0.043092706 | G22: =IFERROR(AVERAGEIFS(Pedidos!$M$2:$M$2224,Pedidos!$AJ$2:$AJ$2224,"SIM",Pedidos!$G$2:$G$2224,"Capital",Pedidos!$H$2:$H$2224,$A22),"") -> 39.83 | H22: =IFERROR(AVERAGEIFS(Pedidos!$U$2:$U$2224,Pedidos!$AJ$2:$AJ$2224,"SIM",Pedidos!$G$2:$G$2224,"Capital",Pedidos!$H$2:$H$2224,$A22),"") -> 46.98 | I22: =IFERROR(H22/G22-1,"") -> 0.17951293 | J22: =IFERROR(COUNTIFS(Pedidos!$AJ$2:$AJ$2224,"SIM",Pedidos!$G$2:$G$2224,"Capital",Pedidos!$H$2:$H$2224,$A22,Pedidos!$AG$2:$AG$2224,"SIM")/B22,"") -> 0 | K22: =IFERROR(MAX(0,1-C22/D22),"") -> 0.088472548
A23: 20-35 | B23: =COUNTIFS(Pedidos!$AJ$2:$AJ$2224,"SIM",Pedidos!$G$2:$G$2224,"Capital",Pedidos!$H$2:$H$2224,$A23) -> 263 | C23: =IFERROR(AVERAGEIFS(Pedidos!$T$2:$T$2224,Pedidos!$AJ$2:$AJ$2224,"SIM",Pedidos!$G$2:$G$2224,"Capital",Pedidos!$H$2:$H$2224,$A23),"") -> 82.379886 | D23: =IFERROR(AVERAGEIFS(Pedidos!$AC$2:$AC$2224,Pedidos!$AJ$2:$AJ$2224,"SIM",Pedidos!$G$2:$G$2224,"Capital",Pedidos!$H$2:$H$2224,$A23),"") -> 117.40343 | E23: =IFERROR(D23/C23-1,"") -> 0.42514675 | F23: =IFERROR(AVERAGEIFS(Pedidos!$AD$2:$AD$2224,Pedidos!$AJ$2:$AJ$2224,"SIM",Pedidos!$G$2:$G$2224,"Capital",Pedidos!$H$2:$H$2224,$A23)/C23-1,"") -> 0.25086793 | G23: =IFERROR(AVERAGEIFS(Pedidos!$M$2:$M$2224,Pedidos!$AJ$2:$AJ$2224,"SIM",Pedidos!$G$2:$G$2224,"Capital",Pedidos!$H$2:$H$2224,$A23),"") -> 54.1 | H23: =IFERROR(AVERAGEIFS(Pedidos!$U$2:$U$2224,Pedidos!$AJ$2:$AJ$2224,"SIM",Pedidos!$G$2:$G$2224,"Capital",Pedidos!$H$2:$H$2224,$A23),"") -> 82.21 | I23: =IFERROR(H23/G23-1,"") -> 0.51959335 | J23: =IFERROR(COUNTIFS(Pedidos!$AJ$2:$AJ$2224,"SIM",Pedidos!$G$2:$G$2224,"Capital",Pedidos!$H$2:$H$2224,$A23,Pedidos!$AG$2:$AG$2224,"SIM")/B23,"") -> 0 | K23: =IFERROR(MAX(0,1-C23/D23),"") -> 0.29831787
A24: 35-40 | B24: =COUNTIFS(Pedidos!$AJ$2:$AJ$2224,"SIM",Pedidos!$G$2:$G$2224,"Capital",Pedidos!$H$2:$H$2224,$A24) -> 163 | C24: =IFERROR(AVERAGEIFS(Pedidos!$T$2:$T$2224,Pedidos!$AJ$2:$AJ$2224,"SIM",Pedidos!$G$2:$G$2224,"Capital",Pedidos!$H$2:$H$2224,$A24),"") -> 92.068014 | D24: =IFERROR(AVERAGEIFS(Pedidos!$AC$2:$AC$2224,Pedidos!$AJ$2:$AJ$2224,"SIM",Pedidos!$G$2:$G$2224,"Capital",Pedidos!$H$2:$H$2224,$A24),"") -> 136.60884 | E24: =IFERROR(D24/C24-1,"") -> 0.48378175 | F24: =IFERROR(AVERAGEIFS(Pedidos!$AD$2:$AD$2224,Pedidos!$AJ$2:$AJ$2224,"SIM",Pedidos!$G$2:$G$2224,"Capital",Pedidos!$H$2:$H$2224,$A24)/C24-1,"") -> 0.27292682 | G24: =IFERROR(AVERAGEIFS(Pedidos!$M$2:$M$2224,Pedidos!$AJ$2:$AJ$2224,"SIM",Pedidos!$G$2:$G$2224,"Capital",Pedidos!$H$2:$H$2224,$A24),"") -> 62.05 | H24: =IFERROR(AVERAGEIFS(Pedidos!$U$2:$U$2224,Pedidos!$AJ$2:$AJ$2224,"SIM",Pedidos!$G$2:$G$2224,"Capital",Pedidos!$H$2:$H$2224,$A24),"") -> 93.97 | I24: =IFERROR(H24/G24-1,"") -> 0.51442385 | J24: =IFERROR(COUNTIFS(Pedidos!$AJ$2:$AJ$2224,"SIM",Pedidos!$G$2:$G$2224,"Capital",Pedidos!$H$2:$H$2224,$A24,Pedidos!$AG$2:$AG$2224,"SIM")/B24,"") -> 0 | K24: =IFERROR(MAX(0,1-C24/D24),"") -> 0.32604644
A25: 40-50 | B25: =COUNTIFS(Pedidos!$AJ$2:$AJ$2224,"SIM",Pedidos!$G$2:$G$2224,"Capital",Pedidos!$H$2:$H$2224,$A25) -> 154 | C25: =IFERROR(AVERAGEIFS(Pedidos!$T$2:$T$2224,Pedidos!$AJ$2:$AJ$2224,"SIM",Pedidos!$G$2:$G$2224,"Capital",Pedidos!$H$2:$H$2224,$A25),"") -> 103.46131 | D25: =IFERROR(AVERAGEIFS(Pedidos!$AC$2:$AC$2224,Pedidos!$AJ$2:$AJ$2224,"SIM",Pedidos!$G$2:$G$2224,"Capital",Pedidos!$H$2:$H$2224,$A25),"") -> 141.78335 | E25: =IFERROR(D25/C25-1,"") -> 0.37039977 | F25: =IFERROR(AVERAGEIFS(Pedidos!$AD$2:$AD$2224,Pedidos!$AJ$2:$AJ$2224,"SIM",Pedidos!$G$2:$G$2224,"Capital",Pedidos!$H$2:$H$2224,$A25)/C25-1,"") -> 0.14265691 | G25: =IFERROR(AVERAGEIFS(Pedidos!$M$2:$M$2224,Pedidos!$AJ$2:$AJ$2224,"SIM",Pedidos!$G$2:$G$2224,"Capital",Pedidos!$H$2:$H$2224,$A25),"") -> 71 | H25: =IFERROR(AVERAGEIFS(Pedidos!$U$2:$U$2224,Pedidos!$AJ$2:$AJ$2224,"SIM",Pedidos!$G$2:$G$2224,"Capital",Pedidos!$H$2:$H$2224,$A25),"") -> 93.97 | I25: =IFERROR(H25/G25-1,"") -> 0.32352113 | J25: =IFERROR(COUNTIFS(Pedidos!$AJ$2:$AJ$2224,"SIM",Pedidos!$G$2:$G$2224,"Capital",Pedidos!$H$2:$H$2224,$A25,Pedidos!$AG$2:$AG$2224,"SIM")/B25,"") -> 0 | K25: =IFERROR(MAX(0,1-C25/D25),"") -> 0.27028593
A26: 50-60 | B26: =COUNTIFS(Pedidos!$AJ$2:$AJ$2224,"SIM",Pedidos!$G$2:$G$2224,"Capital",Pedidos!$H$2:$H$2224,$A26) -> 181 | C26: =IFERROR(AVERAGEIFS(Pedidos!$T$2:$T$2224,Pedidos!$AJ$2:$AJ$2224,"SIM",Pedidos!$G$2:$G$2224,"Capital",Pedidos!$H$2:$H$2224,$A26),"") -> 114.45303 | D26: =IFERROR(AVERAGEIFS(Pedidos!$AC$2:$AC$2224,Pedidos!$AJ$2:$AJ$2224,"SIM",Pedidos!$G$2:$G$2224,"Capital",Pedidos!$H$2:$H$2224,$A26),"") -> 167.53521 | E26: =IFERROR(D26/C26-1,"") -> 0.46379014 | F26: =IFERROR(AVERAGEIFS(Pedidos!$AD$2:$AD$2224,Pedidos!$AJ$2:$AJ$2224,"SIM",Pedidos!$G$2:$G$2224,"Capital",Pedidos!$H$2:$H$2224,$A26)/C26-1,"") -> 0.22232656 | G26: =IFERROR(AVERAGEIFS(Pedidos!$M$2:$M$2224,Pedidos!$AJ$2:$AJ$2224,"SIM",Pedidos!$G$2:$G$2224,"Capital",Pedidos!$H$2:$H$2224,$A26),"") -> 79.81 | H26: =IFERROR(AVERAGEIFS(Pedidos!$U$2:$U$2224,Pedidos!$AJ$2:$AJ$2224,"SIM",Pedidos!$G$2:$G$2224,"Capital",Pedidos!$H$2:$H$2224,$A26),"") -> 112.3 | I26: =IFERROR(H26/G26-1,"") -> 0.40709184 | J26: =IFERROR(COUNTIFS(Pedidos!$AJ$2:$AJ$2224,"SIM",Pedidos!$G$2:$G$2224,"Capital",Pedidos!$H$2:$H$2224,$A26,Pedidos!$AG$2:$AG$2224,"SIM")/B26,"") -> 0 | K26: =IFERROR(MAX(0,1-C26/D26),"") -> 0.31684196
A27: 60-70 | B27: =COUNTIFS(Pedidos!$AJ$2:$AJ$2224,"SIM",Pedidos!$G$2:$G$2224,"Capital",Pedidos!$H$2:$H$2224,$A27) -> 112 | C27: =IFERROR(AVERAGEIFS(Pedidos!$T$2:$T$2224,Pedidos!$AJ$2:$AJ$2224,"SIM",Pedidos!$G$2:$G$2224,"Capital",Pedidos!$H$2:$H$2224,$A27),"") -> 124.87712 | D27: =IFERROR(AVERAGEIFS(Pedidos!$AC$2:$AC$2224,Pedidos!$AJ$2:$AJ$2224,"SIM",Pedidos!$G$2:$G$2224,"Capital",Pedidos!$H$2:$H$2224,$A27),"") -> 196.26069 | E27: =IFERROR(D27/C27-1,"") -> 0.57163054 | F27: =IFERROR(AVERAGEIFS(Pedidos!$AD$2:$AD$2224,Pedidos!$AJ$2:$AJ$2224,"SIM",Pedidos!$G$2:$G$2224,"Capital",Pedidos!$H$2:$H$2224,$A27)/C27-1,"") -> 0.2995002 | G27: =IFERROR(AVERAGEIFS(Pedidos!$M$2:$M$2224,Pedidos!$AJ$2:$AJ$2224,"SIM",Pedidos!$G$2:$G$2224,"Capital",Pedidos!$H$2:$H$2224,$A27),"") -> 88.2 | H27: =IFERROR(AVERAGEIFS(Pedidos!$U$2:$U$2224,Pedidos!$AJ$2:$AJ$2224,"SIM",Pedidos!$G$2:$G$2224,"Capital",Pedidos!$H$2:$H$2224,$A27),"") -> 131.02 | I27: =IFERROR(H27/G27-1,"") -> 0.48548753 | J27: =IFERROR(COUNTIFS(Pedidos!$AJ$2:$AJ$2224,"SIM",Pedidos!$G$2:$G$2224,"Capital",Pedidos!$H$2:$H$2224,$A27,Pedidos!$AG$2:$AG$2224,"SIM")/B27,"") -> 0 | K27: =IFERROR(MAX(0,1-C27/D27),"") -> 0.36371814
A28: 70-80 | B28: =COUNTIFS(Pedidos!$AJ$2:$AJ$2224,"SIM",Pedidos!$G$2:$G$2224,"Capital",Pedidos!$H$2:$H$2224,$A28) -> 11 | C28: =IFERROR(AVERAGEIFS(Pedidos!$T$2:$T$2224,Pedidos!$AJ$2:$AJ$2224,"SIM",Pedidos!$G$2:$G$2224,"Capital",Pedidos!$H$2:$H$2224,$A28),"") -> 137.68127 | D28: =IFERROR(AVERAGEIFS(Pedidos!$AC$2:$AC$2224,Pedidos!$AJ$2:$AJ$2224,"SIM",Pedidos!$G$2:$G$2224,"Capital",Pedidos!$H$2:$H$2224,$A28),"") -> 207.02902 | E28: =IFERROR(D28/C28-1,"") -> 0.50368327 | F28: =IFERROR(AVERAGEIFS(Pedidos!$AD$2:$AD$2224,Pedidos!$AJ$2:$AJ$2224,"SIM",Pedidos!$G$2:$G$2224,"Capital",Pedidos!$H$2:$H$2224,$A28)/C28-1,"") -> 0.21938489 | G28: =IFERROR(AVERAGEIFS(Pedidos!$M$2:$M$2224,Pedidos!$AJ$2:$AJ$2224,"SIM",Pedidos!$G$2:$G$2224,"Capital",Pedidos!$H$2:$H$2224,$A28),"") -> 97.6 | H28: =IFERROR(AVERAGEIFS(Pedidos!$U$2:$U$2224,Pedidos!$AJ$2:$AJ$2224,"SIM",Pedidos!$G$2:$G$2224,"Capital",Pedidos!$H$2:$H$2224,$A28),"") -> 134.39 | I28: =IFERROR(H28/G28-1,"") -> 0.37694672 | J28: =IFERROR(COUNTIFS(Pedidos!$AJ$2:$AJ$2224,"SIM",Pedidos!$G$2:$G$2224,"Capital",Pedidos!$H$2:$H$2224,$A28,Pedidos!$AG$2:$AG$2224,"SIM")/B28,"") -> 0 | K28: =IFERROR(MAX(0,1-C28/D28),"") -> 0.33496633
A29: 80-100 | B29: =COUNTIFS(Pedidos!$AJ$2:$AJ$2224,"SIM",Pedidos!$G$2:$G$2224,"Capital",Pedidos!$H$2:$H$2224,$A29) -> 19 | C29: =IFERROR(AVERAGEIFS(Pedidos!$T$2:$T$2224,Pedidos!$AJ$2:$AJ$2224,"SIM",Pedidos!$G$2:$G$2224,"Capital",Pedidos!$H$2:$H$2224,$A29),"") -> 163.75881 | D29: =IFERROR(AVERAGEIFS(Pedidos!$AC$2:$AC$2224,Pedidos!$AJ$2:$AJ$2224,"SIM",Pedidos!$G$2:$G$2224,"Capital",Pedidos!$H$2:$H$2224,$A29),"") -> 251.89439 | E29: =IFERROR(D29/C29-1,"") -> 0.53820355 | F29: =IFERROR(AVERAGEIFS(Pedidos!$AD$2:$AD$2224,Pedidos!$AJ$2:$AJ$2224,"SIM",Pedidos!$G$2:$G$2224,"Capital",Pedidos!$H$2:$H$2224,$A29)/C29-1,"") -> 0.26110827 | G29: =IFERROR(AVERAGEIFS(Pedidos!$M$2:$M$2224,Pedidos!$AJ$2:$AJ$2224,"SIM",Pedidos!$G$2:$G$2224,"Capital",Pedidos!$H$2:$H$2224,$A29),"") -> 119.8 | H29: =IFERROR(AVERAGEIFS(Pedidos!$U$2:$U$2224,Pedidos!$AJ$2:$AJ$2224,"SIM",Pedidos!$G$2:$G$2224,"Capital",Pedidos!$H$2:$H$2224,$A29),"") -> 167.99 | I29: =IFERROR(H29/G29-1,"") -> 0.40225376 | J29: =IFERROR(COUNTIFS(Pedidos!$AJ$2:$AJ$2224,"SIM",Pedidos!$G$2:$G$2224,"Capital",Pedidos!$H$2:$H$2224,$A29,Pedidos!$AG$2:$AG$2224,"SIM")/B29,"") -> 0 | K29: =IFERROR(MAX(0,1-C29/D29),"") -> 0.34989098
A30: 100-120 | B30: =COUNTIFS(Pedidos!$AJ$2:$AJ$2224,"SIM",Pedidos!$G$2:$G$2224,"Capital",Pedidos!$H$2:$H$2224,$A30) -> 21 | C30: =IFERROR(AVERAGEIFS(Pedidos!$T$2:$T$2224,Pedidos!$AJ$2:$AJ$2224,"SIM",Pedidos!$G$2:$G$2224,"Capital",Pedidos!$H$2:$H$2224,$A30),"") -> 185.62398 | D30: =IFERROR(AVERAGEIFS(Pedidos!$AC$2:$AC$2224,Pedidos!$AJ$2:$AJ$2224,"SIM",Pedidos!$G$2:$G$2224,"Capital",Pedidos!$H$2:$H$2224,$A30),"") -> 309.11115 | E30: =IFERROR(D30/C30-1,"") -> 0.66525442 | F30: =IFERROR(AVERAGEIFS(Pedidos!$AD$2:$AD$2224,Pedidos!$AJ$2:$AJ$2224,"SIM",Pedidos!$G$2:$G$2224,"Capital",Pedidos!$H$2:$H$2224,$A30)/C30-1,"") -> 0.35907406 | G30: =IFERROR(AVERAGEIFS(Pedidos!$M$2:$M$2224,Pedidos!$AJ$2:$AJ$2224,"SIM",Pedidos!$G$2:$G$2224,"Capital",Pedidos!$H$2:$H$2224,$A30),"") -> 135.94 | H30: =IFERROR(AVERAGEIFS(Pedidos!$U$2:$U$2224,Pedidos!$AJ$2:$AJ$2224,"SIM",Pedidos!$G$2:$G$2224,"Capital",Pedidos!$H$2:$H$2224,$A30),"") -> 201.59 | I30: =IFERROR(H30/G30-1,"") -> 0.48293365 | J30: =IFERROR(COUNTIFS(Pedidos!$AJ$2:$AJ$2224,"SIM",Pedidos!$G$2:$G$2224,"Capital",Pedidos!$H$2:$H$2224,$A30,Pedidos!$AG$2:$AG$2224,"SIM")/B30,"") -> 0 | K30: =IFERROR(MAX(0,1-C30/D30),"") -> 0.39949116
A31: 120-150 | B31: =COUNTIFS(Pedidos!$AJ$2:$AJ$2224,"SIM",Pedidos!$G$2:$G$2224,"Capital",Pedidos!$H$2:$H$2224,$A31) -> 39 | C31: =IFERROR(AVERAGEIFS(Pedidos!$T$2:$T$2224,Pedidos!$AJ$2:$AJ$2224,"SIM",Pedidos!$G$2:$G$2224,"Capital",Pedidos!$H$2:$H$2224,$A31),"") -> 234.088 | D31: =IFERROR(AVERAGEIFS(Pedidos!$AC$2:$AC$2224,Pedidos!$AJ$2:$AJ$2224,"SIM",Pedidos!$G$2:$G$2224,"Capital",Pedidos!$H$2:$H$2224,$A31),"") -> 363.47249 | E31: =IFERROR(D31/C31-1,"") -> 0.55271733 | F31: =IFERROR(AVERAGEIFS(Pedidos!$AD$2:$AD$2224,Pedidos!$AJ$2:$AJ$2224,"SIM",Pedidos!$G$2:$G$2224,"Capital",Pedidos!$H$2:$H$2224,$A31)/C31-1,"") -> 0.27119777 | G31: =IFERROR(AVERAGEIFS(Pedidos!$M$2:$M$2224,Pedidos!$AJ$2:$AJ$2224,"SIM",Pedidos!$G$2:$G$2224,"Capital",Pedidos!$H$2:$H$2224,$A31),"") -> 174.85 | H31: =IFERROR(AVERAGEIFS(Pedidos!$U$2:$U$2224,Pedidos!$AJ$2:$AJ$2224,"SIM",Pedidos!$G$2:$G$2224,"Capital",Pedidos!$H$2:$H$2224,$A31),"") -> 239.25 | I31: =IFERROR(H31/G31-1,"") -> 0.3683157 | J31: =IFERROR(COUNTIFS(Pedidos!$AJ$2:$AJ$2224,"SIM",Pedidos!$G$2:$G$2224,"Capital",Pedidos!$H$2:$H$2224,$A31,Pedidos!$AG$2:$AG$2224,"SIM")/B31,"") -> 0 | K31: =IFERROR(MAX(0,1-C31/D31),"") -> 0.35596777
A32: 150-170 | B32: =COUNTIFS(Pedidos!$AJ$2:$AJ$2224,"SIM",Pedidos!$G$2:$G$2224,"Capital",Pedidos!$H$2:$H$2224,$A32) -> 2 | C32: =IFERROR(AVERAGEIFS(Pedidos!$T$2:$T$2224,Pedidos!$AJ$2:$AJ$2224,"SIM",Pedidos!$G$2:$G$2224,"Capital",Pedidos!$H$2:$H$2224,$A32),"") -> 255.75965 | D32: =IFERROR(AVERAGEIFS(Pedidos!$AC$2:$AC$2224,Pedidos!$AJ$2:$AJ$2224,"SIM",Pedidos!$G$2:$G$2224,"Capital",Pedidos!$H$2:$H$2224,$A32),"") -> 417.59806 | E32: =IFERROR(D32/C32-1,"") -> 0.63277542 | F32: =IFERROR(AVERAGEIFS(Pedidos!$AD$2:$AD$2224,Pedidos!$AJ$2:$AJ$2224,"SIM",Pedidos!$G$2:$G$2224,"Capital",Pedidos!$H$2:$H$2224,$A32)/C32-1,"") -> 0.31587188 | G32: =IFERROR(AVERAGEIFS(Pedidos!$M$2:$M$2224,Pedidos!$AJ$2:$AJ$2224,"SIM",Pedidos!$G$2:$G$2224,"Capital",Pedidos!$H$2:$H$2224,$A32),"") -> 192.1 | H32: =IFERROR(AVERAGEIFS(Pedidos!$U$2:$U$2224,Pedidos!$AJ$2:$AJ$2224,"SIM",Pedidos!$G$2:$G$2224,"Capital",Pedidos!$H$2:$H$2224,$A32),"") -> 271.15 | I32: =IFERROR(H32/G32-1,"") -> 0.41150442 | J32: =IFERROR(COUNTIFS(Pedidos!$AJ$2:$AJ$2224,"SIM",Pedidos!$G$2:$G$2224,"Capital",Pedidos!$H$2:$H$2224,$A32,Pedidos!$AG$2:$AG$2224,"SIM")/B32,"") -> 0 | K32: =IFERROR(MAX(0,1-C32/D32),"") -> 0.3875459
A33: 170-200 | B33: =COUNTIFS(Pedidos!$AJ$2:$AJ$2224,"SIM",Pedidos!$G$2:$G$2224,"Capital",Pedidos!$H$2:$H$2224,$A33) -> 0 | C33: =IFERROR(AVERAGEIFS(Pedidos!$T$2:$T$2224,Pedidos!$AJ$2:$AJ$2224,"SIM",Pedidos!$G$2:$G$2224,"Capital",Pedidos!$H$2:$H$2224,$A33),"") | D33: =IFERROR(AVERAGEIFS(Pedidos!$AC$2:$AC$2224,Pedidos!$AJ$2:$AJ$2224,"SIM",Pedidos!$G$2:$G$2224,"Capital",Pedidos!$H$2:$H$2224,$A33),"") | E33: =IFERROR(D33/C33-1,"") | F33: =IFERROR(AVERAGEIFS(Pedidos!$AD$2:$AD$2224,Pedidos!$AJ$2:$AJ$2224,"SIM",Pedidos!$G$2:$G$2224,"Capital",Pedidos!$H$2:$H$2224,$A33)/C33-1,"") | G33: =IFERROR(AVERAGEIFS(Pedidos!$M$2:$M$2224,Pedidos!$AJ$2:$AJ$2224,"SIM",Pedidos!$G$2:$G$2224,"Capital",Pedidos!$H$2:$H$2224,$A33),"") | H33: =IFERROR(AVERAGEIFS(Pedidos!$U$2:$U$2224,Pedidos!$AJ$2:$AJ$2224,"SIM",Pedidos!$G$2:$G$2224,"Capital",Pedidos!$H$2:$H$2224,$A33),"") | I33: =IFERROR(H33/G33-1,"") | J33: =IFERROR(COUNTIFS(Pedidos!$AJ$2:$AJ$2224,"SIM",Pedidos!$G$2:$G$2224,"Capital",Pedidos!$H$2:$H$2224,$A33,Pedidos!$AG$2:$AG$2224,"SIM")/B33,"") | K33: =IFERROR(MAX(0,1-C33/D33),"")
A34: 200-250 | B34: =COUNTIFS(Pedidos!$AJ$2:$AJ$2224,"SIM",Pedidos!$G$2:$G$2224,"Capital",Pedidos!$H$2:$H$2224,$A34) -> 1 | C34: =IFERROR(AVERAGEIFS(Pedidos!$T$2:$T$2224,Pedidos!$AJ$2:$AJ$2224,"SIM",Pedidos!$G$2:$G$2224,"Capital",Pedidos!$H$2:$H$2224,$A34),"") -> 355.2278 | D34: =IFERROR(AVERAGEIFS(Pedidos!$AC$2:$AC$2224,Pedidos!$AJ$2:$AJ$2224,"SIM",Pedidos!$G$2:$G$2224,"Capital",Pedidos!$H$2:$H$2224,$A34),"") -> 593.32707 | E34: =IFERROR(D34/C34-1,"") -> 0.67027204 | F34: =IFERROR(AVERAGEIFS(Pedidos!$AD$2:$AD$2224,Pedidos!$AJ$2:$AJ$2224,"SIM",Pedidos!$G$2:$G$2224,"Capital",Pedidos!$H$2:$H$2224,$A34)/C34-1,"") -> 0.38092507 | G34: =IFERROR(AVERAGEIFS(Pedidos!$M$2:$M$2224,Pedidos!$AJ$2:$AJ$2224,"SIM",Pedidos!$G$2:$G$2224,"Capital",Pedidos!$H$2:$H$2224,$A34),"") -> 272.9 | H34: =IFERROR(AVERAGEIFS(Pedidos!$U$2:$U$2224,Pedidos!$AJ$2:$AJ$2224,"SIM",Pedidos!$G$2:$G$2224,"Capital",Pedidos!$H$2:$H$2224,$A34),"") -> 398.74 | I34: =IFERROR(H34/G34-1,"") -> 0.46112129 | J34: =IFERROR(COUNTIFS(Pedidos!$AJ$2:$AJ$2224,"SIM",Pedidos!$G$2:$G$2224,"Capital",Pedidos!$H$2:$H$2224,$A34,Pedidos!$AG$2:$AG$2224,"SIM")/B34,"") -> 0 | K34: =IFERROR(MAX(0,1-C34/D34),"") -> 0.40129513
A35: TOTAL | B35: =COUNTIFS(Pedidos!$AJ$2:$AJ$2224,"SIM",Pedidos!$G$2:$G$2224,"Capital") -> 1030 | C35: =IFERROR(AVERAGEIFS(Pedidos!$T$2:$T$2224,Pedidos!$AJ$2:$AJ$2224,"SIM",Pedidos!$G$2:$G$2224,"Capital"),"") -> 106.76312 | D35: =IFERROR(AVERAGEIFS(Pedidos!$AC$2:$AC$2224,Pedidos!$AJ$2:$AJ$2224,"SIM",Pedidos!$G$2:$G$2224,"Capital"),"") -> 156.29299 | E35: =IFERROR(D35/C35-1,"") -> 0.46392307 | F35: =IFERROR(AVERAGEIFS(Pedidos!$AD$2:$AD$2224,Pedidos!$AJ$2:$AJ$2224,"SIM",Pedidos!$G$2:$G$2224,"Capital")/C35-1,"") -> 0.23404986 | G35: =IFERROR(AVERAGEIFS(Pedidos!$M$2:$M$2224,Pedidos!$AJ$2:$AJ$2224,"SIM",Pedidos!$G$2:$G$2224,"Capital"),"") -> 73.621718 | H35: =IFERROR(AVERAGEIFS(Pedidos!$U$2:$U$2224,Pedidos!$AJ$2:$AJ$2224,"SIM",Pedidos!$G$2:$G$2224,"Capital"),"") -> 105.42938 | I35: =IFERROR(H35/G35-1,"") -> 0.43204181 | J35: =IFERROR(COUNTIFS(Pedidos!$AJ$2:$AJ$2224,"SIM",Pedidos!$G$2:$G$2224,"Capital",Pedidos!$AG$2:$AG$2224,"SIM")/B35,"") -> 0 | K35: =IFERROR(MAX(0,1-C35/D35),"") -> 0.31690399
A37: Região: Metropolitana
A38: Faixa (kg) | B38: Pedidos | C38: TSL médio | D38: PROLOG médio | E38: PROLOG vs TSL | F38: PROLOG s/ taxa interna vs TSL | G38: TSL frete peso | H38: PROLOG frete peso | I38: Frete peso PROLOG vs TSL | J38: % pedidos PROLOG ganharia | K38: Redução necessária
A39: 0-20 | B39: =COUNTIFS(Pedidos!$AJ$2:$AJ$2224,"SIM",Pedidos!$G$2:$G$2224,"Metropolitana",Pedidos!$H$2:$H$2224,$A39) -> 24 | C39: =IFERROR(AVERAGEIFS(Pedidos!$T$2:$T$2224,Pedidos!$AJ$2:$AJ$2224,"SIM",Pedidos!$G$2:$G$2224,"Metropolitana",Pedidos!$H$2:$H$2224,$A39),"") -> 75.475687 | D39: =IFERROR(AVERAGEIFS(Pedidos!$AC$2:$AC$2224,Pedidos!$AJ$2:$AJ$2224,"SIM",Pedidos!$G$2:$G$2224,"Metropolitana",Pedidos!$H$2:$H$2224,$A39),"") -> 76.658069 | E39: =IFERROR(D39/C39-1,"") -> 0.015665734 | F39: =IFERROR(AVERAGEIFS(Pedidos!$AD$2:$AD$2224,Pedidos!$AJ$2:$AJ$2224,"SIM",Pedidos!$G$2:$G$2224,"Metropolitana",Pedidos!$H$2:$H$2224,$A39)/C39-1,"") -> -0.11165176 | G39: =IFERROR(AVERAGEIFS(Pedidos!$M$2:$M$2224,Pedidos!$AJ$2:$AJ$2224,"SIM",Pedidos!$G$2:$G$2224,"Metropolitana",Pedidos!$H$2:$H$2224,$A39),"") -> 48.69 | H39: =IFERROR(AVERAGEIFS(Pedidos!$U$2:$U$2224,Pedidos!$AJ$2:$AJ$2224,"SIM",Pedidos!$G$2:$G$2224,"Metropolitana",Pedidos!$H$2:$H$2224,$A39),"") -> 51.350833 | I39: =IFERROR(H39/G39-1,"") -> 0.054648456 | J39: =IFERROR(COUNTIFS(Pedidos!$AJ$2:$AJ$2224,"SIM",Pedidos!$G$2:$G$2224,"Metropolitana",Pedidos!$H$2:$H$2224,$A39,Pedidos!$AG$2:$AG$2224,"SIM")/B39,"") -> 0.58333333 | K39: =IFERROR(MAX(0,1-C39/D39),"") -> 0.015424104
A40: 20-35 | B40: =COUNTIFS(Pedidos!$AJ$2:$AJ$2224,"SIM",Pedidos!$G$2:$G$2224,"Metropolitana",Pedidos!$H$2:$H$2224,$A40) -> 84 | C40: =IFERROR(AVERAGEIFS(Pedidos!$T$2:$T$2224,Pedidos!$AJ$2:$AJ$2224,"SIM",Pedidos!$G$2:$G$2224,"Metropolitana",Pedidos!$H$2:$H$2224,$A40),"") -> 101.4742 | D40: =IFERROR(AVERAGEIFS(Pedidos!$AC$2:$AC$2224,Pedidos!$AJ$2:$AJ$2224,"SIM",Pedidos!$G$2:$G$2224,"Metropolitana",Pedidos!$H$2:$H$2224,$A40),"") -> 128.00589 | E40: =IFERROR(D40/C40-1,"") -> 0.26146239 | F40: =IFERROR(AVERAGEIFS(Pedidos!$AD$2:$AD$2224,Pedidos!$AJ$2:$AJ$2224,"SIM",Pedidos!$G$2:$G$2224,"Metropolitana",Pedidos!$H$2:$H$2224,$A40)/C40-1,"") -> 0.11442146 | G40: =IFERROR(AVERAGEIFS(Pedidos!$M$2:$M$2224,Pedidos!$AJ$2:$AJ$2224,"SIM",Pedidos!$G$2:$G$2224,"Metropolitana",Pedidos!$H$2:$H$2224,$A40),"") -> 70 | H40: =IFERROR(AVERAGEIFS(Pedidos!$U$2:$U$2224,Pedidos!$AJ$2:$AJ$2224,"SIM",Pedidos!$G$2:$G$2224,"Metropolitana",Pedidos!$H$2:$H$2224,$A40),"") -> 90.957619 | I40: =IFERROR(H40/G40-1,"") -> 0.29939456 | J40: =IFERROR(COUNTIFS(Pedidos!$AJ$2:$AJ$2224,"SIM",Pedidos!$G$2:$G$2224,"Metropolitana",Pedidos!$H$2:$H$2224,$A40,Pedidos!$AG$2:$AG$2224,"SIM")/B40,"") -> 0 | K40: =IFERROR(MAX(0,1-C40/D40),"") -> 0.20726927
A41: 35-40 | B41: =COUNTIFS(Pedidos!$AJ$2:$AJ$2224,"SIM",Pedidos!$G$2:$G$2224,"Metropolitana",Pedidos!$H$2:$H$2224,$A41) -> 72 | C41: =IFERROR(AVERAGEIFS(Pedidos!$T$2:$T$2224,Pedidos!$AJ$2:$AJ$2224,"SIM",Pedidos!$G$2:$G$2224,"Metropolitana",Pedidos!$H$2:$H$2224,$A41),"") -> 113.23346 | D41: =IFERROR(AVERAGEIFS(Pedidos!$AC$2:$AC$2224,Pedidos!$AJ$2:$AJ$2224,"SIM",Pedidos!$G$2:$G$2224,"Metropolitana",Pedidos!$H$2:$H$2224,$A41),"") -> 146.40808 | E41: =IFERROR(D41/C41-1,"") -> 0.29297534 | F41: =IFERROR(AVERAGEIFS(Pedidos!$AD$2:$AD$2224,Pedidos!$AJ$2:$AJ$2224,"SIM",Pedidos!$G$2:$G$2224,"Metropolitana",Pedidos!$H$2:$H$2224,$A41)/C41-1,"") -> 0.12036334 | G41: =IFERROR(AVERAGEIFS(Pedidos!$M$2:$M$2224,Pedidos!$AJ$2:$AJ$2224,"SIM",Pedidos!$G$2:$G$2224,"Metropolitana",Pedidos!$H$2:$H$2224,$A41),"") -> 79.65 | H41: =IFERROR(AVERAGEIFS(Pedidos!$U$2:$U$2224,Pedidos!$AJ$2:$AJ$2224,"SIM",Pedidos!$G$2:$G$2224,"Metropolitana",Pedidos!$H$2:$H$2224,$A41),"") -> 102.42028 | I41: =IFERROR(H41/G41-1,"") -> 0.28587919 | J41: =IFERROR(COUNTIFS(Pedidos!$AJ$2:$AJ$2224,"SIM",Pedidos!$G$2:$G$2224,"Metropolitana",Pedidos!$H$2:$H$2224,$A41,Pedidos!$AG$2:$AG$2224,"SIM")/B41,"") -> 0 | K41: =IFERROR(MAX(0,1-C41/D41),"") -> 0.22659005
A42: 40-50 | B42: =COUNTIFS(Pedidos!$AJ$2:$AJ$2224,"SIM",Pedidos!$G$2:$G$2224,"Metropolitana",Pedidos!$H$2:$H$2224,$A42) -> 89 | C42: =IFERROR(AVERAGEIFS(Pedidos!$T$2:$T$2224,Pedidos!$AJ$2:$AJ$2224,"SIM",Pedidos!$G$2:$G$2224,"Metropolitana",Pedidos!$H$2:$H$2224,$A42),"") -> 117.02836 | D42: =IFERROR(AVERAGEIFS(Pedidos!$AC$2:$AC$2224,Pedidos!$AJ$2:$AJ$2224,"SIM",Pedidos!$G$2:$G$2224,"Metropolitana",Pedidos!$H$2:$H$2224,$A42),"") -> 152.12309 | E42: =IFERROR(D42/C42-1,"") -> 0.29988228 | F42: =IFERROR(AVERAGEIFS(Pedidos!$AD$2:$AD$2224,Pedidos!$AJ$2:$AJ$2224,"SIM",Pedidos!$G$2:$G$2224,"Metropolitana",Pedidos!$H$2:$H$2224,$A42)/C42-1,"") -> 0.09573988 | G42: =IFERROR(AVERAGEIFS(Pedidos!$M$2:$M$2224,Pedidos!$AJ$2:$AJ$2224,"SIM",Pedidos!$G$2:$G$2224,"Metropolitana",Pedidos!$H$2:$H$2224,$A42),"") -> 82.25 | H42: =IFERROR(AVERAGEIFS(Pedidos!$U$2:$U$2224,Pedidos!$AJ$2:$AJ$2224,"SIM",Pedidos!$G$2:$G$2224,"Metropolitana",Pedidos!$H$2:$H$2224,$A42),"") -> 102.69202 | I42: =IFERROR(H42/G42-1,"") -> 0.24853523 | J42: =IFERROR(COUNTIFS(Pedidos!$AJ$2:$AJ$2224,"SIM",Pedidos!$G$2:$G$2224,"Metropolitana",Pedidos!$H$2:$H$2224,$A42,Pedidos!$AG$2:$AG$2224,"SIM")/B42,"") -> 0 | K42: =IFERROR(MAX(0,1-C42/D42),"") -> 0.23069957
A43: 50-60 | B43: =COUNTIFS(Pedidos!$AJ$2:$AJ$2224,"SIM",Pedidos!$G$2:$G$2224,"Metropolitana",Pedidos!$H$2:$H$2224,$A43) -> 116 | C43: =IFERROR(AVERAGEIFS(Pedidos!$T$2:$T$2224,Pedidos!$AJ$2:$AJ$2224,"SIM",Pedidos!$G$2:$G$2224,"Metropolitana",Pedidos!$H$2:$H$2224,$A43),"") -> 128.58617 | D43: =IFERROR(AVERAGEIFS(Pedidos!$AC$2:$AC$2224,Pedidos!$AJ$2:$AJ$2224,"SIM",Pedidos!$G$2:$G$2224,"Metropolitana",Pedidos!$H$2:$H$2224,$A43),"") -> 174.56596 | E43: =IFERROR(D43/C43-1,"") -> 0.35757966 | F43: =IFERROR(AVERAGEIFS(Pedidos!$AD$2:$AD$2224,Pedidos!$AJ$2:$AJ$2224,"SIM",Pedidos!$G$2:$G$2224,"Metropolitana",Pedidos!$H$2:$H$2224,$A43)/C43-1,"") -> 0.14125453 | G43: =IFERROR(AVERAGEIFS(Pedidos!$M$2:$M$2224,Pedidos!$AJ$2:$AJ$2224,"SIM",Pedidos!$G$2:$G$2224,"Metropolitana",Pedidos!$H$2:$H$2224,$A43),"") -> 91.6 | H43: =IFERROR(AVERAGEIFS(Pedidos!$U$2:$U$2224,Pedidos!$AJ$2:$AJ$2224,"SIM",Pedidos!$G$2:$G$2224,"Metropolitana",Pedidos!$H$2:$H$2224,$A43),"") -> 118.30828 | I43: =IFERROR(H43/G43-1,"") -> 0.29157506 | J43: =IFERROR(COUNTIFS(Pedidos!$AJ$2:$AJ$2224,"SIM",Pedidos!$G$2:$G$2224,"Metropolitana",Pedidos!$H$2:$H$2224,$A43,Pedidos!$AG$2:$AG$2224,"SIM")/B43,"") -> 0 | K43: =IFERROR(MAX(0,1-C43/D43),"") -> 0.26339497
A44: 60-70 | B44: =COUNTIFS(Pedidos!$AJ$2:$AJ$2224,"SIM",Pedidos!$G$2:$G$2224,"Metropolitana",Pedidos!$H$2:$H$2224,$A44) -> 69 | C44: =IFERROR(AVERAGEIFS(Pedidos!$T$2:$T$2224,Pedidos!$AJ$2:$AJ$2224,"SIM",Pedidos!$G$2:$G$2224,"Metropolitana",Pedidos!$H$2:$H$2224,$A44),"") -> 139.92021 | D44: =IFERROR(AVERAGEIFS(Pedidos!$AC$2:$AC$2224,Pedidos!$AJ$2:$AJ$2224,"SIM",Pedidos!$G$2:$G$2224,"Metropolitana",Pedidos!$H$2:$H$2224,$A44),"") -> 204.09088 | E44: =IFERROR(D44/C44-1,"") -> 0.45862337 | F44: =IFERROR(AVERAGEIFS(Pedidos!$AD$2:$AD$2224,Pedidos!$AJ$2:$AJ$2224,"SIM",Pedidos!$G$2:$G$2224,"Metropolitana",Pedidos!$H$2:$H$2224,$A44)/C44-1,"") -> 0.2154547 | G44: =IFERROR(AVERAGEIFS(Pedidos!$M$2:$M$2224,Pedidos!$AJ$2:$AJ$2224,"SIM",Pedidos!$G$2:$G$2224,"Metropolitana",Pedidos!$H$2:$H$2224,$A44),"") -> 100.9 | H44: =IFERROR(AVERAGEIFS(Pedidos!$U$2:$U$2224,Pedidos!$AJ$2:$AJ$2224,"SIM",Pedidos!$G$2:$G$2224,"Metropolitana",Pedidos!$H$2:$H$2224,$A44),"") -> 137.98348 | I44: =IFERROR(H44/G44-1,"") -> 0.36752704 | J44: =IFERROR(COUNTIFS(Pedidos!$AJ$2:$AJ$2224,"SIM",Pedidos!$G$2:$G$2224,"Metropolitana",Pedidos!$H$2:$H$2224,$A44,Pedidos!$AG$2:$AG$2224,"SIM")/B44,"") -> 0 | K44: =IFERROR(MAX(0,1-C44/D44),"") -> 0.31442206
A45: 70-80 | B45: =COUNTIFS(Pedidos!$AJ$2:$AJ$2224,"SIM",Pedidos!$G$2:$G$2224,"Metropolitana",Pedidos!$H$2:$H$2224,$A45) -> 9 | C45: =IFERROR(AVERAGEIFS(Pedidos!$T$2:$T$2224,Pedidos!$AJ$2:$AJ$2224,"SIM",Pedidos!$G$2:$G$2224,"Metropolitana",Pedidos!$H$2:$H$2224,$A45),"") -> 152.15189 | D45: =IFERROR(AVERAGEIFS(Pedidos!$AC$2:$AC$2224,Pedidos!$AJ$2:$AJ$2224,"SIM",Pedidos!$G$2:$G$2224,"Metropolitana",Pedidos!$H$2:$H$2224,$A45),"") -> 207.51618 | E45: =IFERROR(D45/C45-1,"") -> 0.36387511 | F45: =IFERROR(AVERAGEIFS(Pedidos!$AD$2:$AD$2224,Pedidos!$AJ$2:$AJ$2224,"SIM",Pedidos!$G$2:$G$2224,"Metropolitana",Pedidos!$H$2:$H$2224,$A45)/C45-1,"") -> 0.1177843 | G45: =IFERROR(AVERAGEIFS(Pedidos!$M$2:$M$2224,Pedidos!$AJ$2:$AJ$2224,"SIM",Pedidos!$G$2:$G$2224,"Metropolitana",Pedidos!$H$2:$H$2224,$A45),"") -> 110.55 | H45: =IFERROR(AVERAGEIFS(Pedidos!$U$2:$U$2224,Pedidos!$AJ$2:$AJ$2224,"SIM",Pedidos!$G$2:$G$2224,"Metropolitana",Pedidos!$H$2:$H$2224,$A45),"") -> 137.17333 | I45: =IFERROR(H45/G45-1,"") -> 0.24082617 | J45: =IFERROR(COUNTIFS(Pedidos!$AJ$2:$AJ$2224,"SIM",Pedidos!$G$2:$G$2224,"Metropolitana",Pedidos!$H$2:$H$2224,$A45,Pedidos!$AG$2:$AG$2224,"SIM")/B45,"") -> 0 | K45: =IFERROR(MAX(0,1-C45/D45),"") -> 0.26679503
A46: 80-100 | B46: =COUNTIFS(Pedidos!$AJ$2:$AJ$2224,"SIM",Pedidos!$G$2:$G$2224,"Metropolitana",Pedidos!$H$2:$H$2224,$A46) -> 11 | C46: =IFERROR(AVERAGEIFS(Pedidos!$T$2:$T$2224,Pedidos!$AJ$2:$AJ$2224,"SIM",Pedidos!$G$2:$G$2224,"Metropolitana",Pedidos!$H$2:$H$2224,$A46),"") -> 173.45528 | D46: =IFERROR(AVERAGEIFS(Pedidos!$AC$2:$AC$2224,Pedidos!$AJ$2:$AJ$2224,"SIM",Pedidos!$G$2:$G$2224,"Metropolitana",Pedidos!$H$2:$H$2224,$A46),"") -> 255.11781 | E46: =IFERROR(D46/C46-1,"") -> 0.47079873 | F46: =IFERROR(AVERAGEIFS(Pedidos!$AD$2:$AD$2224,Pedidos!$AJ$2:$AJ$2224,"SIM",Pedidos!$G$2:$G$2224,"Metropolitana",Pedidos!$H$2:$H$2224,$A46)/C46-1,"") -> 0.21458198 | G46: =IFERROR(AVERAGEIFS(Pedidos!$M$2:$M$2224,Pedidos!$AJ$2:$AJ$2224,"SIM",Pedidos!$G$2:$G$2224,"Metropolitana",Pedidos!$H$2:$H$2224,$A46),"") -> 127.92 | H46: =IFERROR(AVERAGEIFS(Pedidos!$U$2:$U$2224,Pedidos!$AJ$2:$AJ$2224,"SIM",Pedidos!$G$2:$G$2224,"Metropolitana",Pedidos!$H$2:$H$2224,$A46),"") -> 171.78273 | I46: =IFERROR(H46/G46-1,"") -> 0.34289186 | J46: =IFERROR(COUNTIFS(Pedidos!$AJ$2:$AJ$2224,"SIM",Pedidos!$G$2:$G$2224,"Metropolitana",Pedidos!$H$2:$H$2224,$A46,Pedidos!$AG$2:$AG$2224,"SIM")/B46,"") -> 0 | K46: =IFERROR(MAX(0,1-C46/D46),"") -> 0.32009732
A47: 100-120 | B47: =COUNTIFS(Pedidos!$AJ$2:$AJ$2224,"SIM",Pedidos!$G$2:$G$2224,"Metropolitana",Pedidos!$H$2:$H$2224,$A47) -> 18 | C47: =IFERROR(AVERAGEIFS(Pedidos!$T$2:$T$2224,Pedidos!$AJ$2:$AJ$2224,"SIM",Pedidos!$G$2:$G$2224,"Metropolitana",Pedidos!$H$2:$H$2224,$A47),"") -> 195.58484 | D47: =IFERROR(AVERAGEIFS(Pedidos!$AC$2:$AC$2224,Pedidos!$AJ$2:$AJ$2224,"SIM",Pedidos!$G$2:$G$2224,"Metropolitana",Pedidos!$H$2:$H$2224,$A47),"") -> 311.73706 | E47: =IFERROR(D47/C47-1,"") -> 0.59387132 | F47: =IFERROR(AVERAGEIFS(Pedidos!$AD$2:$AD$2224,Pedidos!$AJ$2:$AJ$2224,"SIM",Pedidos!$G$2:$G$2224,"Metropolitana",Pedidos!$H$2:$H$2224,$A47)/C47-1,"") -> 0.30496506 | G47: =IFERROR(AVERAGEIFS(Pedidos!$M$2:$M$2224,Pedidos!$AJ$2:$AJ$2224,"SIM",Pedidos!$G$2:$G$2224,"Metropolitana",Pedidos!$H$2:$H$2224,$A47),"") -> 144.44 | H47: =IFERROR(AVERAGEIFS(Pedidos!$U$2:$U$2224,Pedidos!$AJ$2:$AJ$2224,"SIM",Pedidos!$G$2:$G$2224,"Metropolitana",Pedidos!$H$2:$H$2224,$A47),"") -> 204.37222 | I47: =IFERROR(H47/G47-1,"") -> 0.41492815 | J47: =IFERROR(COUNTIFS(Pedidos!$AJ$2:$AJ$2224,"SIM",Pedidos!$G$2:$G$2224,"Metropolitana",Pedidos!$H$2:$H$2224,$A47,Pedidos!$AG$2:$AG$2224,"SIM")/B47,"") -> 0 | K47: =IFERROR(MAX(0,1-C47/D47),"") -> 0.37259678
A48: 120-150 | B48: =COUNTIFS(Pedidos!$AJ$2:$AJ$2224,"SIM",Pedidos!$G$2:$G$2224,"Metropolitana",Pedidos!$H$2:$H$2224,$A48) -> 18 | C48: =IFERROR(AVERAGEIFS(Pedidos!$T$2:$T$2224,Pedidos!$AJ$2:$AJ$2224,"SIM",Pedidos!$G$2:$G$2224,"Metropolitana",Pedidos!$H$2:$H$2224,$A48),"") -> 244.32342 | D48: =IFERROR(AVERAGEIFS(Pedidos!$AC$2:$AC$2224,Pedidos!$AJ$2:$AJ$2224,"SIM",Pedidos!$G$2:$G$2224,"Metropolitana",Pedidos!$H$2:$H$2224,$A48),"") -> 367.45005 | E48: =IFERROR(D48/C48-1,"") -> 0.50394935 | F48: =IFERROR(AVERAGEIFS(Pedidos!$AD$2:$AD$2224,Pedidos!$AJ$2:$AJ$2224,"SIM",Pedidos!$G$2:$G$2224,"Metropolitana",Pedidos!$H$2:$H$2224,$A48)/C48-1,"") -> 0.23081567 | G48: =IFERROR(AVERAGEIFS(Pedidos!$M$2:$M$2224,Pedidos!$AJ$2:$AJ$2224,"SIM",Pedidos!$G$2:$G$2224,"Metropolitana",Pedidos!$H$2:$H$2224,$A48),"") -> 183.45 | H48: =IFERROR(AVERAGEIFS(Pedidos!$U$2:$U$2224,Pedidos!$AJ$2:$AJ$2224,"SIM",Pedidos!$G$2:$G$2224,"Metropolitana",Pedidos!$H$2:$H$2224,$A48),"") -> 241.96667 | I48: =IFERROR(H48/G48-1,"") -> 0.31897883 | J48: =IFERROR(COUNTIFS(Pedidos!$AJ$2:$AJ$2224,"SIM",Pedidos!$G$2:$G$2224,"Metropolitana",Pedidos!$H$2:$H$2224,$A48,Pedidos!$AG$2:$AG$2224,"SIM")/B48,"") -> 0 | K48: =IFERROR(MAX(0,1-C48/D48),"") -> 0.33508399
A49: 150-170 | B49: =COUNTIFS(Pedidos!$AJ$2:$AJ$2224,"SIM",Pedidos!$G$2:$G$2224,"Metropolitana",Pedidos!$H$2:$H$2224,$A49) -> 1 | C49: =IFERROR(AVERAGEIFS(Pedidos!$T$2:$T$2224,Pedidos!$AJ$2:$AJ$2224,"SIM",Pedidos!$G$2:$G$2224,"Metropolitana",Pedidos!$H$2:$H$2224,$A49),"") -> 267.69421 | D49: =IFERROR(AVERAGEIFS(Pedidos!$AC$2:$AC$2224,Pedidos!$AJ$2:$AJ$2224,"SIM",Pedidos!$G$2:$G$2224,"Metropolitana",Pedidos!$H$2:$H$2224,$A49),"") -> 435.30678 | E49: =IFERROR(D49/C49-1,"") -> 0.62613446 | F49: =IFERROR(AVERAGEIFS(Pedidos!$AD$2:$AD$2224,Pedidos!$AJ$2:$AJ$2224,"SIM",Pedidos!$G$2:$G$2224,"Metropolitana",Pedidos!$H$2:$H$2224,$A49)/C49-1,"") -> 0.30903248 | G49: =IFERROR(AVERAGEIFS(Pedidos!$M$2:$M$2224,Pedidos!$AJ$2:$AJ$2224,"SIM",Pedidos!$G$2:$G$2224,"Metropolitana",Pedidos!$H$2:$H$2224,$A49),"") -> 201.15 | H49: =IFERROR(AVERAGEIFS(Pedidos!$U$2:$U$2224,Pedidos!$AJ$2:$AJ$2224,"SIM",Pedidos!$G$2:$G$2224,"Metropolitana",Pedidos!$H$2:$H$2224,$A49),"") -> 282.23 | I49: =IFERROR(H49/G49-1,"") -> 0.40308228 | J49: =IFERROR(COUNTIFS(Pedidos!$AJ$2:$AJ$2224,"SIM",Pedidos!$G$2:$G$2224,"Metropolitana",Pedidos!$H$2:$H$2224,$A49,Pedidos!$AG$2:$AG$2224,"SIM")/B49,"") -> 0 | K49: =IFERROR(MAX(0,1-C49/D49),"") -> 0.3850447
A50: 170-200 | B50: =COUNTIFS(Pedidos!$AJ$2:$AJ$2224,"SIM",Pedidos!$G$2:$G$2224,"Metropolitana",Pedidos!$H$2:$H$2224,$A50) -> 0 | C50: =IFERROR(AVERAGEIFS(Pedidos!$T$2:$T$2224,Pedidos!$AJ$2:$AJ$2224,"SIM",Pedidos!$G$2:$G$2224,"Metropolitana",Pedidos!$H$2:$H$2224,$A50),"") | D50: =IFERROR(AVERAGEIFS(Pedidos!$AC$2:$AC$2224,Pedidos!$AJ$2:$AJ$2224,"SIM",Pedidos!$G$2:$G$2224,"Metropolitana",Pedidos!$H$2:$H$2224,$A50),"") | E50: =IFERROR(D50/C50-1,"") | F50: =IFERROR(AVERAGEIFS(Pedidos!$AD$2:$AD$2224,Pedidos!$AJ$2:$AJ$2224,"SIM",Pedidos!$G$2:$G$2224,"Metropolitana",Pedidos!$H$2:$H$2224,$A50)/C50-1,"") | G50: =IFERROR(AVERAGEIFS(Pedidos!$M$2:$M$2224,Pedidos!$AJ$2:$AJ$2224,"SIM",Pedidos!$G$2:$G$2224,"Metropolitana",Pedidos!$H$2:$H$2224,$A50),"") | H50: =IFERROR(AVERAGEIFS(Pedidos!$U$2:$U$2224,Pedidos!$AJ$2:$AJ$2224,"SIM",Pedidos!$G$2:$G$2224,"Metropolitana",Pedidos!$H$2:$H$2224,$A50),"") | I50: =IFERROR(H50/G50-1,"") | J50: =IFERROR(COUNTIFS(Pedidos!$AJ$2:$AJ$2224,"SIM",Pedidos!$G$2:$G$2224,"Metropolitana",Pedidos!$H$2:$H$2224,$A50,Pedidos!$AG$2:$AG$2224,"SIM")/B50,"") | K50: =IFERROR(MAX(0,1-C50/D50),"")
A51: 200-250 | B51: =COUNTIFS(Pedidos!$AJ$2:$AJ$2224,"SIM",Pedidos!$G$2:$G$2224,"Metropolitana",Pedidos!$H$2:$H$2224,$A51) -> 0 | C51: =IFERROR(AVERAGEIFS(Pedidos!$T$2:$T$2224,Pedidos!$AJ$2:$AJ$2224,"SIM",Pedidos!$G$2:$G$2224,"Metropolitana",Pedidos!$H$2:$H$2224,$A51),"") | D51: =IFERROR(AVERAGEIFS(Pedidos!$AC$2:$AC$2224,Pedidos!$AJ$2:$AJ$2224,"SIM",Pedidos!$G$2:$G$2224,"Metropolitana",Pedidos!$H$2:$H$2224,$A51),"") | E51: =IFERROR(D51/C51-1,"") | F51: =IFERROR(AVERAGEIFS(Pedidos!$AD$2:$AD$2224,Pedidos!$AJ$2:$AJ$2224,"SIM",Pedidos!$G$2:$G$2224,"Metropolitana",Pedidos!$H$2:$H$2224,$A51)/C51-1,"") | G51: =IFERROR(AVERAGEIFS(Pedidos!$M$2:$M$2224,Pedidos!$AJ$2:$AJ$2224,"SIM",Pedidos!$G$2:$G$2224,"Metropolitana",Pedidos!$H$2:$H$2224,$A51),"") | H51: =IFERROR(AVERAGEIFS(Pedidos!$U$2:$U$2224,Pedidos!$AJ$2:$AJ$2224,"SIM",Pedidos!$G$2:$G$2224,"Metropolitana",Pedidos!$H$2:$H$2224,$A51),"") | I51: =IFERROR(H51/G51-1,"") | J51: =IFERROR(COUNTIFS(Pedidos!$AJ$2:$AJ$2224,"SIM",Pedidos!$G$2:$G$2224,"Metropolitana",Pedidos!$H$2:$H$2224,$A51,Pedidos!$AG$2:$AG$2224,"SIM")/B51,"") | K51: =IFERROR(MAX(0,1-C51/D51),"")
A52: TOTAL | B52: =COUNTIFS(Pedidos!$AJ$2:$AJ$2224,"SIM",Pedidos!$G$2:$G$2224,"Metropolitana") -> 511 | C52: =IFERROR(AVERAGEIFS(Pedidos!$T$2:$T$2224,Pedidos!$AJ$2:$AJ$2224,"SIM",Pedidos!$G$2:$G$2224,"Metropolitana"),"") -> 127.07924 | D52: =IFERROR(AVERAGEIFS(Pedidos!$AC$2:$AC$2224,Pedidos!$AJ$2:$AJ$2224,"SIM",Pedidos!$G$2:$G$2224,"Metropolitana"),"") -> 172.87508 | E52: =IFERROR(D52/C52-1,"") -> 0.36037231 | F52: =IFERROR(AVERAGEIFS(Pedidos!$AD$2:$AD$2224,Pedidos!$AJ$2:$AJ$2224,"SIM",Pedidos!$G$2:$G$2224,"Metropolitana")/C52-1,"") -> 0.1490782 | G52: =IFERROR(AVERAGEIFS(Pedidos!$M$2:$M$2224,Pedidos!$AJ$2:$AJ$2224,"SIM",Pedidos!$G$2:$G$2224,"Metropolitana"),"") -> 90.404207 | H52: =IFERROR(AVERAGEIFS(Pedidos!$U$2:$U$2224,Pedidos!$AJ$2:$AJ$2224,"SIM",Pedidos!$G$2:$G$2224,"Metropolitana"),"") -> 117.5574 | I52: =IFERROR(H52/G52-1,"") -> 0.30035316 | J52: =IFERROR(COUNTIFS(Pedidos!$AJ$2:$AJ$2224,"SIM",Pedidos!$G$2:$G$2224,"Metropolitana",Pedidos!$AG$2:$AG$2224,"SIM")/B52,"") -> 0.02739726 | K52: =IFERROR(MAX(0,1-C52/D52),"") -> 0.26490712
A54: Região: Interior
A55: Faixa (kg) | B55: Pedidos | C55: TSL médio | D55: PROLOG médio | E55: PROLOG vs TSL | F55: PROLOG s/ taxa interna vs TSL | G55: TSL frete peso | H55: PROLOG frete peso | I55: Frete peso PROLOG vs TSL | J55: % pedidos PROLOG ganharia | K55: Redução necessária
A56: 0-20 | B56: =COUNTIFS(Pedidos!$AJ$2:$AJ$2224,"SIM",Pedidos!$G$2:$G$2224,"Interior",Pedidos!$H$2:$H$2224,$A56) -> 8 | C56: =IFERROR(AVERAGEIFS(Pedidos!$T$2:$T$2224,Pedidos!$AJ$2:$AJ$2224,"SIM",Pedidos!$G$2:$G$2224,"Interior",Pedidos!$H$2:$H$2224,$A56),"") -> 80.094323 | D56: =IFERROR(AVERAGEIFS(Pedidos!$AC$2:$AC$2224,Pedidos!$AJ$2:$AJ$2224,"SIM",Pedidos!$G$2:$G$2224,"Interior",Pedidos!$H$2:$H$2224,$A56),"") -> 115.5371 | E56: =IFERROR(D56/C56-1,"") -> 0.44251302 | F56: =IFERROR(AVERAGEIFS(Pedidos!$AD$2:$AD$2224,Pedidos!$AJ$2:$AJ$2224,"SIM",Pedidos!$G$2:$G$2224,"Interior",Pedidos!$H$2:$H$2224,$A56)/C56-1,"") -> 0.33317815 | G56: =IFERROR(AVERAGEIFS(Pedidos!$M$2:$M$2224,Pedidos!$AJ$2:$AJ$2224,"SIM",Pedidos!$G$2:$G$2224,"Interior",Pedidos!$H$2:$H$2224,$A56),"") -> 52.71 | H56: =IFERROR(AVERAGEIFS(Pedidos!$U$2:$U$2224,Pedidos!$AJ$2:$AJ$2224,"SIM",Pedidos!$G$2:$G$2224,"Interior",Pedidos!$H$2:$H$2224,$A56),"") -> 86.54 | I56: =IFERROR(H56/G56-1,"") -> 0.6418137 | J56: =IFERROR(COUNTIFS(Pedidos!$AJ$2:$AJ$2224,"SIM",Pedidos!$G$2:$G$2224,"Interior",Pedidos!$H$2:$H$2224,$A56,Pedidos!$AG$2:$AG$2224,"SIM")/B56,"") -> 0 | K56: =IFERROR(MAX(0,1-C56/D56),"") -> 0.30676535
A57: 20-35 | B57: =COUNTIFS(Pedidos!$AJ$2:$AJ$2224,"SIM",Pedidos!$G$2:$G$2224,"Interior",Pedidos!$H$2:$H$2224,$A57) -> 84 | C57: =IFERROR(AVERAGEIFS(Pedidos!$T$2:$T$2224,Pedidos!$AJ$2:$AJ$2224,"SIM",Pedidos!$G$2:$G$2224,"Interior",Pedidos!$H$2:$H$2224,$A57),"") -> 109.28029 | D57: =IFERROR(AVERAGEIFS(Pedidos!$AC$2:$AC$2224,Pedidos!$AJ$2:$AJ$2224,"SIM",Pedidos!$G$2:$G$2224,"Interior",Pedidos!$H$2:$H$2224,$A57),"") -> 158.32148 | E57: =IFERROR(D57/C57-1,"") -> 0.44876511 | F57: =IFERROR(AVERAGEIFS(Pedidos!$AD$2:$AD$2224,Pedidos!$AJ$2:$AJ$2224,"SIM",Pedidos!$G$2:$G$2224,"Interior",Pedidos!$H$2:$H$2224,$A57)/C57-1,"") -> 0.30966508 | G57: =IFERROR(AVERAGEIFS(Pedidos!$M$2:$M$2224,Pedidos!$AJ$2:$AJ$2224,"SIM",Pedidos!$G$2:$G$2224,"Interior",Pedidos!$H$2:$H$2224,$A57),"") -> 76.5 | H57: =IFERROR(AVERAGEIFS(Pedidos!$U$2:$U$2224,Pedidos!$AJ$2:$AJ$2224,"SIM",Pedidos!$G$2:$G$2224,"Interior",Pedidos!$H$2:$H$2224,$A57),"") -> 117.34762 | I57: =IFERROR(H57/G57-1,"") -> 0.5339558 | J57: =IFERROR(COUNTIFS(Pedidos!$AJ$2:$AJ$2224,"SIM",Pedidos!$G$2:$G$2224,"Interior",Pedidos!$H$2:$H$2224,$A57,Pedidos!$AG$2:$AG$2224,"SIM")/B57,"") -> 0 | K57: =IFERROR(MAX(0,1-C57/D57),"") -> 0.30975699
A58: 35-40 | B58: =COUNTIFS(Pedidos!$AJ$2:$AJ$2224,"SIM",Pedidos!$G$2:$G$2224,"Interior",Pedidos!$H$2:$H$2224,$A58) -> 64 | C58: =IFERROR(AVERAGEIFS(Pedidos!$T$2:$T$2224,Pedidos!$AJ$2:$AJ$2224,"SIM",Pedidos!$G$2:$G$2224,"Interior",Pedidos!$H$2:$H$2224,$A58),"") -> 122.48385 | D58: =IFERROR(AVERAGEIFS(Pedidos!$AC$2:$AC$2224,Pedidos!$AJ$2:$AJ$2224,"SIM",Pedidos!$G$2:$G$2224,"Interior",Pedidos!$H$2:$H$2224,$A58),"") -> 173.07348 | E58: =IFERROR(D58/C58-1,"") -> 0.41303093 | F58: =IFERROR(AVERAGEIFS(Pedidos!$AD$2:$AD$2224,Pedidos!$AJ$2:$AJ$2224,"SIM",Pedidos!$G$2:$G$2224,"Interior",Pedidos!$H$2:$H$2224,$A58)/C58-1,"") -> 0.25379583 | G58: =IFERROR(AVERAGEIFS(Pedidos!$M$2:$M$2224,Pedidos!$AJ$2:$AJ$2224,"SIM",Pedidos!$G$2:$G$2224,"Interior",Pedidos!$H$2:$H$2224,$A58),"") -> 87.4 | H58: =IFERROR(AVERAGEIFS(Pedidos!$U$2:$U$2224,Pedidos!$AJ$2:$AJ$2224,"SIM",Pedidos!$G$2:$G$2224,"Interior",Pedidos!$H$2:$H$2224,$A58),"") -> 125.95297 | I58: =IFERROR(H58/G58-1,"") -> 0.44110948 | J58: =IFERROR(COUNTIFS(Pedidos!$AJ$2:$AJ$2224,"SIM",Pedidos!$G$2:$G$2224,"Interior",Pedidos!$H$2:$H$2224,$A58,Pedidos!$AG$2:$AG$2224,"SIM")/B58,"") -> 0 | K58: =IFERROR(MAX(0,1-C58/D58),"") -> 0.29230141
A59: 40-50 | B59: =COUNTIFS(Pedidos!$AJ$2:$AJ$2224,"SIM",Pedidos!$G$2:$G$2224,"Interior",Pedidos!$H$2:$H$2224,$A59) -> 62 | C59: =IFERROR(AVERAGEIFS(Pedidos!$T$2:$T$2224,Pedidos!$AJ$2:$AJ$2224,"SIM",Pedidos!$G$2:$G$2224,"Interior",Pedidos!$H$2:$H$2224,$A59),"") -> 131.01412 | D59: =IFERROR(AVERAGEIFS(Pedidos!$AC$2:$AC$2224,Pedidos!$AJ$2:$AJ$2224,"SIM",Pedidos!$G$2:$G$2224,"Interior",Pedidos!$H$2:$H$2224,$A59),"") -> 184.43877 | E59: =IFERROR(D59/C59-1,"") -> 0.4077778 | F59: =IFERROR(AVERAGEIFS(Pedidos!$AD$2:$AD$2224,Pedidos!$AJ$2:$AJ$2224,"SIM",Pedidos!$G$2:$G$2224,"Interior",Pedidos!$H$2:$H$2224,$A59)/C59-1,"") -> 0.22924161 | G59: =IFERROR(AVERAGEIFS(Pedidos!$M$2:$M$2224,Pedidos!$AJ$2:$AJ$2224,"SIM",Pedidos!$G$2:$G$2224,"Interior",Pedidos!$H$2:$H$2224,$A59),"") -> 94 | H59: =IFERROR(AVERAGEIFS(Pedidos!$U$2:$U$2224,Pedidos!$AJ$2:$AJ$2224,"SIM",Pedidos!$G$2:$G$2224,"Interior",Pedidos!$H$2:$H$2224,$A59),"") -> 131.69129 | I59: =IFERROR(H59/G59-1,"") -> 0.40097117 | J59: =IFERROR(COUNTIFS(Pedidos!$AJ$2:$AJ$2224,"SIM",Pedidos!$G$2:$G$2224,"Interior",Pedidos!$H$2:$H$2224,$A59,Pedidos!$AG$2:$AG$2224,"SIM")/B59,"") -> 0 | K59: =IFERROR(MAX(0,1-C59/D59),"") -> 0.28966063
A60: 50-60 | B60: =COUNTIFS(Pedidos!$AJ$2:$AJ$2224,"SIM",Pedidos!$G$2:$G$2224,"Interior",Pedidos!$H$2:$H$2224,$A60) -> 64 | C60: =IFERROR(AVERAGEIFS(Pedidos!$T$2:$T$2224,Pedidos!$AJ$2:$AJ$2224,"SIM",Pedidos!$G$2:$G$2224,"Interior",Pedidos!$H$2:$H$2224,$A60),"") -> 143.17453 | D60: =IFERROR(AVERAGEIFS(Pedidos!$AC$2:$AC$2224,Pedidos!$AJ$2:$AJ$2224,"SIM",Pedidos!$G$2:$G$2224,"Interior",Pedidos!$H$2:$H$2224,$A60),"") -> 205.07581 | E60: =IFERROR(D60/C60-1,"") -> 0.4323484 | F60: =IFERROR(AVERAGEIFS(Pedidos!$AD$2:$AD$2224,Pedidos!$AJ$2:$AJ$2224,"SIM",Pedidos!$G$2:$G$2224,"Interior",Pedidos!$H$2:$H$2224,$A60)/C60-1,"") -> 0.23607725 | G60: =IFERROR(AVERAGEIFS(Pedidos!$M$2:$M$2224,Pedidos!$AJ$2:$AJ$2224,"SIM",Pedidos!$G$2:$G$2224,"Interior",Pedidos!$H$2:$H$2224,$A60),"") -> 103.6 | H60: =IFERROR(AVERAGEIFS(Pedidos!$U$2:$U$2224,Pedidos!$AJ$2:$AJ$2224,"SIM",Pedidos!$G$2:$G$2224,"Interior",Pedidos!$H$2:$H$2224,$A60),"") -> 144.74672 | I60: =IFERROR(H60/G60-1,"") -> 0.3971691 | J60: =IFERROR(COUNTIFS(Pedidos!$AJ$2:$AJ$2224,"SIM",Pedidos!$G$2:$G$2224,"Interior",Pedidos!$H$2:$H$2224,$A60,Pedidos!$AG$2:$AG$2224,"SIM")/B60,"") -> 0 | K60: =IFERROR(MAX(0,1-C60/D60),"") -> 0.30184584
A61: 60-70 | B61: =COUNTIFS(Pedidos!$AJ$2:$AJ$2224,"SIM",Pedidos!$G$2:$G$2224,"Interior",Pedidos!$H$2:$H$2224,$A61) -> 47 | C61: =IFERROR(AVERAGEIFS(Pedidos!$T$2:$T$2224,Pedidos!$AJ$2:$AJ$2224,"SIM",Pedidos!$G$2:$G$2224,"Interior",Pedidos!$H$2:$H$2224,$A61),"") -> 155.83578 | D61: =IFERROR(AVERAGEIFS(Pedidos!$AC$2:$AC$2224,Pedidos!$AJ$2:$AJ$2224,"SIM",Pedidos!$G$2:$G$2224,"Interior",Pedidos!$H$2:$H$2224,$A61),"") -> 232.96894 | E61: =IFERROR(D61/C61-1,"") -> 0.49496431 | F61: =IFERROR(AVERAGEIFS(Pedidos!$AD$2:$AD$2224,Pedidos!$AJ$2:$AJ$2224,"SIM",Pedidos!$G$2:$G$2224,"Interior",Pedidos!$H$2:$H$2224,$A61)/C61-1,"") -> 0.27908835 | G61: =IFERROR(AVERAGEIFS(Pedidos!$M$2:$M$2224,Pedidos!$AJ$2:$AJ$2224,"SIM",Pedidos!$G$2:$G$2224,"Interior",Pedidos!$H$2:$H$2224,$A61),"") -> 113.9 | H61: =IFERROR(AVERAGEIFS(Pedidos!$U$2:$U$2224,Pedidos!$AJ$2:$AJ$2224,"SIM",Pedidos!$G$2:$G$2224,"Interior",Pedidos!$H$2:$H$2224,$A61),"") -> 163.57149 | I61: =IFERROR(H61/G61-1,"") -> 0.43609736 | J61: =IFERROR(COUNTIFS(Pedidos!$AJ$2:$AJ$2224,"SIM",Pedidos!$G$2:$G$2224,"Interior",Pedidos!$H$2:$H$2224,$A61,Pedidos!$AG$2:$AG$2224,"SIM")/B61,"") -> 0 | K61: =IFERROR(MAX(0,1-C61/D61),"") -> 0.33108771
A62: 70-80 | B62: =COUNTIFS(Pedidos!$AJ$2:$AJ$2224,"SIM",Pedidos!$G$2:$G$2224,"Interior",Pedidos!$H$2:$H$2224,$A62) -> 4 | C62: =IFERROR(AVERAGEIFS(Pedidos!$T$2:$T$2224,Pedidos!$AJ$2:$AJ$2224,"SIM",Pedidos!$G$2:$G$2224,"Interior",Pedidos!$H$2:$H$2224,$A62),"") -> 168.32784 | D62: =IFERROR(AVERAGEIFS(Pedidos!$AC$2:$AC$2224,Pedidos!$AJ$2:$AJ$2224,"SIM",Pedidos!$G$2:$G$2224,"Interior",Pedidos!$H$2:$H$2224,$A62),"") -> 230.724 | E62: =IFERROR(D62/C62-1,"") -> 0.37068236 | F62: =IFERROR(AVERAGEIFS(Pedidos!$AD$2:$AD$2224,Pedidos!$AJ$2:$AJ$2224,"SIM",Pedidos!$G$2:$G$2224,"Interior",Pedidos!$H$2:$H$2224,$A62)/C62-1,"") -> 0.15119387 | G62: =IFERROR(AVERAGEIFS(Pedidos!$M$2:$M$2224,Pedidos!$AJ$2:$AJ$2224,"SIM",Pedidos!$G$2:$G$2224,"Interior",Pedidos!$H$2:$H$2224,$A62),"") -> 124.16 | H62: =IFERROR(AVERAGEIFS(Pedidos!$U$2:$U$2224,Pedidos!$AJ$2:$AJ$2224,"SIM",Pedidos!$G$2:$G$2224,"Interior",Pedidos!$H$2:$H$2224,$A62),"") -> 158.18 | I62: =IFERROR(H62/G62-1,"") -> 0.27400129 | J62: =IFERROR(COUNTIFS(Pedidos!$AJ$2:$AJ$2224,"SIM",Pedidos!$G$2:$G$2224,"Interior",Pedidos!$H$2:$H$2224,$A62,Pedidos!$AG$2:$AG$2224,"SIM")/B62,"") -> 0 | K62: =IFERROR(MAX(0,1-C62/D62),"") -> 0.27043637
A63: 80-100 | B63: =COUNTIFS(Pedidos!$AJ$2:$AJ$2224,"SIM",Pedidos!$G$2:$G$2224,"Interior",Pedidos!$H$2:$H$2224,$A63) -> 13 | C63: =IFERROR(AVERAGEIFS(Pedidos!$T$2:$T$2224,Pedidos!$AJ$2:$AJ$2224,"SIM",Pedidos!$G$2:$G$2224,"Interior",Pedidos!$H$2:$H$2224,$A63),"") -> 193.11273 | D63: =IFERROR(AVERAGEIFS(Pedidos!$AC$2:$AC$2224,Pedidos!$AJ$2:$AJ$2224,"SIM",Pedidos!$G$2:$G$2224,"Interior",Pedidos!$H$2:$H$2224,$A63),"") -> 282.84316 | E63: =IFERROR(D63/C63-1,"") -> 0.46465306 | F63: =IFERROR(AVERAGEIFS(Pedidos!$AD$2:$AD$2224,Pedidos!$AJ$2:$AJ$2224,"SIM",Pedidos!$G$2:$G$2224,"Interior",Pedidos!$H$2:$H$2224,$A63)/C63-1,"") -> 0.23386917 | G63: =IFERROR(AVERAGEIFS(Pedidos!$M$2:$M$2224,Pedidos!$AJ$2:$AJ$2224,"SIM",Pedidos!$G$2:$G$2224,"Interior",Pedidos!$H$2:$H$2224,$A63),"") -> 144.41 | H63: =IFERROR(AVERAGEIFS(Pedidos!$U$2:$U$2224,Pedidos!$AJ$2:$AJ$2224,"SIM",Pedidos!$G$2:$G$2224,"Interior",Pedidos!$H$2:$H$2224,$A63),"") -> 196.12615 | I63: =IFERROR(H63/G63-1,"") -> 0.35812031 | J63: =IFERROR(COUNTIFS(Pedidos!$AJ$2:$AJ$2224,"SIM",Pedidos!$G$2:$G$2224,"Interior",Pedidos!$H$2:$H$2224,$A63,Pedidos!$AG$2:$AG$2224,"SIM")/B63,"") -> 0 | K63: =IFERROR(MAX(0,1-C63/D63),"") -> 0.31724445
A64: 100-120 | B64: =COUNTIFS(Pedidos!$AJ$2:$AJ$2224,"SIM",Pedidos!$G$2:$G$2224,"Interior",Pedidos!$H$2:$H$2224,$A64) -> 8 | C64: =IFERROR(AVERAGEIFS(Pedidos!$T$2:$T$2224,Pedidos!$AJ$2:$AJ$2224,"SIM",Pedidos!$G$2:$G$2224,"Interior",Pedidos!$H$2:$H$2224,$A64),"") -> 216.41561 | D64: =IFERROR(AVERAGEIFS(Pedidos!$AC$2:$AC$2224,Pedidos!$AJ$2:$AJ$2224,"SIM",Pedidos!$G$2:$G$2224,"Interior",Pedidos!$H$2:$H$2224,$A64),"") -> 345.09854 | E64: =IFERROR(D64/C64-1,"") -> 0.59461021 | F64: =IFERROR(AVERAGEIFS(Pedidos!$AD$2:$AD$2224,Pedidos!$AJ$2:$AJ$2224,"SIM",Pedidos!$G$2:$G$2224,"Interior",Pedidos!$H$2:$H$2224,$A64)/C64-1,"") -> 0.33469365 | G64: =IFERROR(AVERAGEIFS(Pedidos!$M$2:$M$2224,Pedidos!$AJ$2:$AJ$2224,"SIM",Pedidos!$G$2:$G$2224,"Interior",Pedidos!$H$2:$H$2224,$A64),"") -> 161.81 | H64: =IFERROR(AVERAGEIFS(Pedidos!$U$2:$U$2224,Pedidos!$AJ$2:$AJ$2224,"SIM",Pedidos!$G$2:$G$2224,"Interior",Pedidos!$H$2:$H$2224,$A64),"") -> 233.98125 | I64: =IFERROR(H64/G64-1,"") -> 0.44602466 | J64: =IFERROR(COUNTIFS(Pedidos!$AJ$2:$AJ$2224,"SIM",Pedidos!$G$2:$G$2224,"Interior",Pedidos!$H$2:$H$2224,$A64,Pedidos!$AG$2:$AG$2224,"SIM")/B64,"") -> 0 | K64: =IFERROR(MAX(0,1-C64/D64),"") -> 0.3728875
A65: 120-150 | B65: =COUNTIFS(Pedidos!$AJ$2:$AJ$2224,"SIM",Pedidos!$G$2:$G$2224,"Interior",Pedidos!$H$2:$H$2224,$A65) -> 16 | C65: =IFERROR(AVERAGEIFS(Pedidos!$T$2:$T$2224,Pedidos!$AJ$2:$AJ$2224,"SIM",Pedidos!$G$2:$G$2224,"Interior",Pedidos!$H$2:$H$2224,$A65),"") -> 261.55824 | D65: =IFERROR(AVERAGEIFS(Pedidos!$AC$2:$AC$2224,Pedidos!$AJ$2:$AJ$2224,"SIM",Pedidos!$G$2:$G$2224,"Interior",Pedidos!$H$2:$H$2224,$A65),"") -> 386.91276 | E65: =IFERROR(D65/C65-1,"") -> 0.47926044 | F65: =IFERROR(AVERAGEIFS(Pedidos!$AD$2:$AD$2224,Pedidos!$AJ$2:$AJ$2224,"SIM",Pedidos!$G$2:$G$2224,"Interior",Pedidos!$H$2:$H$2224,$A65)/C65-1,"") -> 0.22852322 | G65: =IFERROR(AVERAGEIFS(Pedidos!$M$2:$M$2224,Pedidos!$AJ$2:$AJ$2224,"SIM",Pedidos!$G$2:$G$2224,"Interior",Pedidos!$H$2:$H$2224,$A65),"") -> 197.37 | H65: =IFERROR(AVERAGEIFS(Pedidos!$U$2:$U$2224,Pedidos!$AJ$2:$AJ$2224,"SIM",Pedidos!$G$2:$G$2224,"Interior",Pedidos!$H$2:$H$2224,$A65),"") -> 259.89938 | I65: =IFERROR(H65/G65-1,"") -> 0.31681297 | J65: =IFERROR(COUNTIFS(Pedidos!$AJ$2:$AJ$2224,"SIM",Pedidos!$G$2:$G$2224,"Interior",Pedidos!$H$2:$H$2224,$A65,Pedidos!$AG$2:$AG$2224,"SIM")/B65,"") -> 0 | K65: =IFERROR(MAX(0,1-C65/D65),"") -> 0.32398652
A66: 150-170 | B66: =COUNTIFS(Pedidos!$AJ$2:$AJ$2224,"SIM",Pedidos!$G$2:$G$2224,"Interior",Pedidos!$H$2:$H$2224,$A66) -> 0 | C66: =IFERROR(AVERAGEIFS(Pedidos!$T$2:$T$2224,Pedidos!$AJ$2:$AJ$2224,"SIM",Pedidos!$G$2:$G$2224,"Interior",Pedidos!$H$2:$H$2224,$A66),"") | D66: =IFERROR(AVERAGEIFS(Pedidos!$AC$2:$AC$2224,Pedidos!$AJ$2:$AJ$2224,"SIM",Pedidos!$G$2:$G$2224,"Interior",Pedidos!$H$2:$H$2224,$A66),"") | E66: =IFERROR(D66/C66-1,"") | F66: =IFERROR(AVERAGEIFS(Pedidos!$AD$2:$AD$2224,Pedidos!$AJ$2:$AJ$2224,"SIM",Pedidos!$G$2:$G$2224,"Interior",Pedidos!$H$2:$H$2224,$A66)/C66-1,"") | G66: =IFERROR(AVERAGEIFS(Pedidos!$M$2:$M$2224,Pedidos!$AJ$2:$AJ$2224,"SIM",Pedidos!$G$2:$G$2224,"Interior",Pedidos!$H$2:$H$2224,$A66),"") | H66: =IFERROR(AVERAGEIFS(Pedidos!$U$2:$U$2224,Pedidos!$AJ$2:$AJ$2224,"SIM",Pedidos!$G$2:$G$2224,"Interior",Pedidos!$H$2:$H$2224,$A66),"") | I66: =IFERROR(H66/G66-1,"") | J66: =IFERROR(COUNTIFS(Pedidos!$AJ$2:$AJ$2224,"SIM",Pedidos!$G$2:$G$2224,"Interior",Pedidos!$H$2:$H$2224,$A66,Pedidos!$AG$2:$AG$2224,"SIM")/B66,"") | K66: =IFERROR(MAX(0,1-C66/D66),"")
A67: 170-200 | B67: =COUNTIFS(Pedidos!$AJ$2:$AJ$2224,"SIM",Pedidos!$G$2:$G$2224,"Interior",Pedidos!$H$2:$H$2224,$A67) -> 1 | C67: =IFERROR(AVERAGEIFS(Pedidos!$T$2:$T$2224,Pedidos!$AJ$2:$AJ$2224,"SIM",Pedidos!$G$2:$G$2224,"Interior",Pedidos!$H$2:$H$2224,$A67),"") -> 198.27526 | D67: =IFERROR(AVERAGEIFS(Pedidos!$AC$2:$AC$2224,Pedidos!$AJ$2:$AJ$2224,"SIM",Pedidos!$G$2:$G$2224,"Interior",Pedidos!$H$2:$H$2224,$A67),"") -> 529.025 | E67: =IFERROR(D67/C67-1,"") -> 1.6681342 | F67: =IFERROR(AVERAGEIFS(Pedidos!$AD$2:$AD$2224,Pedidos!$AJ$2:$AJ$2224,"SIM",Pedidos!$G$2:$G$2224,"Interior",Pedidos!$H$2:$H$2224,$A67)/C67-1,"") -> 1.180692 | G67: =IFERROR(AVERAGEIFS(Pedidos!$M$2:$M$2224,Pedidos!$AJ$2:$AJ$2224,"SIM",Pedidos!$G$2:$G$2224,"Interior",Pedidos!$H$2:$H$2224,$A67),"") -> 143.51 | H67: =IFERROR(AVERAGEIFS(Pedidos!$U$2:$U$2224,Pedidos!$AJ$2:$AJ$2224,"SIM",Pedidos!$G$2:$G$2224,"Interior",Pedidos!$H$2:$H$2224,$A67),"") -> 353.17 | I67: =IFERROR(H67/G67-1,"") -> 1.4609435 | J67: =IFERROR(COUNTIFS(Pedidos!$AJ$2:$AJ$2224,"SIM",Pedidos!$G$2:$G$2224,"Interior",Pedidos!$H$2:$H$2224,$A67,Pedidos!$AG$2:$AG$2224,"SIM")/B67,"") -> 0 | K67: =IFERROR(MAX(0,1-C67/D67),"") -> 0.62520625
A68: 200-250 | B68: =COUNTIFS(Pedidos!$AJ$2:$AJ$2224,"SIM",Pedidos!$G$2:$G$2224,"Interior",Pedidos!$H$2:$H$2224,$A68) -> 0 | C68: =IFERROR(AVERAGEIFS(Pedidos!$T$2:$T$2224,Pedidos!$AJ$2:$AJ$2224,"SIM",Pedidos!$G$2:$G$2224,"Interior",Pedidos!$H$2:$H$2224,$A68),"") | D68: =IFERROR(AVERAGEIFS(Pedidos!$AC$2:$AC$2224,Pedidos!$AJ$2:$AJ$2224,"SIM",Pedidos!$G$2:$G$2224,"Interior",Pedidos!$H$2:$H$2224,$A68),"") | E68: =IFERROR(D68/C68-1,"") | F68: =IFERROR(AVERAGEIFS(Pedidos!$AD$2:$AD$2224,Pedidos!$AJ$2:$AJ$2224,"SIM",Pedidos!$G$2:$G$2224,"Interior",Pedidos!$H$2:$H$2224,$A68)/C68-1,"") | G68: =IFERROR(AVERAGEIFS(Pedidos!$M$2:$M$2224,Pedidos!$AJ$2:$AJ$2224,"SIM",Pedidos!$G$2:$G$2224,"Interior",Pedidos!$H$2:$H$2224,$A68),"") | H68: =IFERROR(AVERAGEIFS(Pedidos!$U$2:$U$2224,Pedidos!$AJ$2:$AJ$2224,"SIM",Pedidos!$G$2:$G$2224,"Interior",Pedidos!$H$2:$H$2224,$A68),"") | I68: =IFERROR(H68/G68-1,"") | J68: =IFERROR(COUNTIFS(Pedidos!$AJ$2:$AJ$2224,"SIM",Pedidos!$G$2:$G$2224,"Interior",Pedidos!$H$2:$H$2224,$A68,Pedidos!$AG$2:$AG$2224,"SIM")/B68,"") | K68: =IFERROR(MAX(0,1-C68/D68),"")
A69: TOTAL | B69: =COUNTIFS(Pedidos!$AJ$2:$AJ$2224,"SIM",Pedidos!$G$2:$G$2224,"Interior") -> 371 | C69: =IFERROR(AVERAGEIFS(Pedidos!$T$2:$T$2224,Pedidos!$AJ$2:$AJ$2224,"SIM",Pedidos!$G$2:$G$2224,"Interior"),"") -> 138.99704 | D69: =IFERROR(AVERAGEIFS(Pedidos!$AC$2:$AC$2224,Pedidos!$AJ$2:$AJ$2224,"SIM",Pedidos!$G$2:$G$2224,"Interior"),"") -> 201.8595 | E69: =IFERROR(D69/C69-1,"") -> 0.45225752 | F69: =IFERROR(AVERAGEIFS(Pedidos!$AD$2:$AD$2224,Pedidos!$AJ$2:$AJ$2224,"SIM",Pedidos!$G$2:$G$2224,"Interior")/C69-1,"") -> 0.26322277 | G69: =IFERROR(AVERAGEIFS(Pedidos!$M$2:$M$2224,Pedidos!$AJ$2:$AJ$2224,"SIM",Pedidos!$G$2:$G$2224,"Interior"),"") -> 100.33116 | H69: =IFERROR(AVERAGEIFS(Pedidos!$U$2:$U$2224,Pedidos!$AJ$2:$AJ$2224,"SIM",Pedidos!$G$2:$G$2224,"Interior"),"") -> 143.64633 | I69: =IFERROR(H69/G69-1,"") -> 0.43172207 | J69: =IFERROR(COUNTIFS(Pedidos!$AJ$2:$AJ$2224,"SIM",Pedidos!$G$2:$G$2224,"Interior",Pedidos!$AG$2:$AG$2224,"SIM")/B69,"") -> 0 | K69: =IFERROR(MAX(0,1-C69/D69),"") -> 0.31141689

Sheet Proposta Tabela PROLOG
A1: Frete peso ALVO para a PROLOG empatar com a TSL (mantendo taxa interna, CTe, pedágio e TAS atuais da PROLOG)
A2: Alvo = subtotal TSL (frete peso + GRIS + seguro + pedágio + entrega, × (1 + TRT)) − taxas PROLOG (ad valorem + GRIS + TAS + pedágio + CTe/kg + taxa interna/kg), para um pedido de referência por faixa. ICMS é igual nas duas e se anula.
AG3: Peso de referência (kg) → | AH3: =IFERROR(AVERAGEIFS(Pedidos!$I$2:$I$2224,Pedidos!$H$2:$H$2224,"0-20"),10) -> 17.66757 | AI3: =IFERROR(AVERAGEIFS(Pedidos!$I$2:$I$2224,Pedidos!$H$2:$H$2224,"20-35"),27.5) -> 28.310162 | AJ3: =IFERROR(AVERAGEIFS(Pedidos!$I$2:$I$2224,Pedidos!$H$2:$H$2224,"35-40"),37.5) -> 37.738563 | AK3: =IFERROR(AVERAGEIFS(Pedidos!$I$2:$I$2224,Pedidos!$H$2:$H$2224,"40-50"),45) -> 45.894767 | AL3: =IFERROR(AVERAGEIFS(Pedidos!$I$2:$I$2224,Pedidos!$H$2:$H$2224,"50-60"),55) -> 53.757837 | AM3: =IFERROR(AVERAGEIFS(Pedidos!$I$2:$I$2224,Pedidos!$H$2:$H$2224,"60-70"),65) -> 66.006227 | AN3: =IFERROR(AVERAGEIFS(Pedidos!$I$2:$I$2224,Pedidos!$H$2:$H$2224,"70-80"),75) -> 74.587333 | AO3: =IFERROR(AVERAGEIFS(Pedidos!$I$2:$I$2224,Pedidos!$H$2:$H$2224,"80-100"),90) -> 87.633333 | AP3: =IFERROR(AVERAGEIFS(Pedidos!$I$2:$I$2224,Pedidos!$H$2:$H$2224,"100-120"),110) -> 110.32245 | AQ3: =IFERROR(AVERAGEIFS(Pedidos!$I$2:$I$2224,Pedidos!$H$2:$H$2224,"120-150"),135) -> 128.14698 | AR3: =IFERROR(AVERAGEIFS(Pedidos!$I$2:$I$2224,Pedidos!$H$2:$H$2224,"150-170"),160) -> 160.63333 | AS3: =IFERROR(AVERAGEIFS(Pedidos!$I$2:$I$2224,Pedidos!$H$2:$H$2224,"170-200"),185) -> 188.4 | AT3: =IFERROR(AVERAGEIFS(Pedidos!$I$2:$I$2224,Pedidos!$H$2:$H$2224,"200-250"),225) -> 208.2
AG4: NF de referência (R$) → | AH4: =IFERROR(AVERAGEIFS(Pedidos!$J$2:$J$2224,Pedidos!$H$2:$H$2224,"0-20"),AH3*SUM(Pedidos!$J$2:$J$2224)/SUM(Pedidos!$I$2:$I$2224)) -> 314.90598 | AI4: =IFERROR(AVERAGEIFS(Pedidos!$J$2:$J$2224,Pedidos!$H$2:$H$2224,"20-35"),AI3*SUM(Pedidos!$J$2:$J$2224)/SUM(Pedidos!$I$2:$I$2224)) -> 434.46416 | AJ4: =IFERROR(AVERAGEIFS(Pedidos!$J$2:$J$2224,Pedidos!$H$2:$H$2224,"35-40"),AJ3*SUM(Pedidos!$J$2:$J$2224)/SUM(Pedidos!$I$2:$I$2224)) -> 465.11025 | AK4: =IFERROR(AVERAGEIFS(Pedidos!$J$2:$J$2224,Pedidos!$H$2:$H$2224,"40-50"),AK3*SUM(Pedidos!$J$2:$J$2224)/SUM(Pedidos!$I$2:$I$2224)) -> 603.08035 | AL4: =IFERROR(AVERAGEIFS(Pedidos!$J$2:$J$2224,Pedidos!$H$2:$H$2224,"50-60"),AL3*SUM(Pedidos!$J$2:$J$2224)/SUM(Pedidos!$I$2:$I$2224)) -> 694.48351 | AM4: =IFERROR(AVERAGEIFS(Pedidos!$J$2:$J$2224,Pedidos!$H$2:$H$2224,"60-70"),AM3*SUM(Pedidos!$J$2:$J$2224)/SUM(Pedidos!$I$2:$I$2224)) -> 759.36037 | AN4: =IFERROR(AVERAGEIFS(Pedidos!$J$2:$J$2224,Pedidos!$H$2:$H$2224,"70-80"),AN3*SUM(Pedidos!$J$2:$J$2224)/SUM(Pedidos!$I$2:$I$2224)) -> 951.882 | AO4: =IFERROR(AVERAGEIFS(Pedidos!$J$2:$J$2224,Pedidos!$H$2:$H$2224,"80-100"),AO3*SUM(Pedidos!$J$2:$J$2224)/SUM(Pedidos!$I$2:$I$2224)) -> 970.36649 | AP4: =IFERROR(AVERAGEIFS(Pedidos!$J$2:$J$2224,Pedidos!$H$2:$H$2224,"100-120"),AP3*SUM(Pedidos!$J$2:$J$2224)/SUM(Pedidos!$I$2:$I$2224)) -> 1259.4377 | AQ4: =IFERROR(AVERAGEIFS(Pedidos!$J$2:$J$2224,Pedidos!$H$2:$H$2224,"120-150"),AQ3*SUM(Pedidos!$J$2:$J$2224)/SUM(Pedidos!$I$2:$I$2224)) -> 1647.7808 | AR4: =IFERROR(AVERAGEIFS(Pedidos!$J$2:$J$2224,Pedidos!$H$2:$H$2224,"150-170"),AR3*SUM(Pedidos!$J$2:$J$2224)/SUM(Pedidos!$I$2:$I$2224)) -> 1909.1733 | AS4: =IFERROR(AVERAGEIFS(Pedidos!$J$2:$J$2224,Pedidos!$H$2:$H$2224,"170-200"),AS3*SUM(Pedidos!$J$2:$J$2224)/SUM(Pedidos!$I$2:$I$2224)) -> 1994 | AT4: =IFERROR(AVERAGEIFS(Pedidos!$J$2:$J$2224,Pedidos!$H$2:$H$2224,"200-250"),AT3*SUM(Pedidos!$J$2:$J$2224)/SUM(Pedidos!$I$2:$I$2224)) -> 3070.2767
H5: PROLOG atual — frete peso | U5: TSL — frete peso | AH5: PROLOG ALVO (empate) | AU5: Redução necessária no frete peso PROLOG
A6: UF | B6: Cidade (tabela PROLOG) | C6: CEP inicial | D6: CEP final | E6: Região TSL | F6: Prazo PROLOG / TSL | G6: Pedidos no período | H6: 0-20 | I6: 20-35 | J6: 35-40 | K6: 40-50 | L6: 50-60 | M6: 60-70 | N6: 70-80 | O6: 80-100 | P6: 100-120 | Q6: 120-150 | R6: 150-170 | S6: 170-200 | T6: 200-250 | U6: 0-20 | V6: 20-35 | W6: 35-40 | X6: 40-50 | Y6: 50-60 | Z6: 60-70 | AA6: 70-80 | AB6: 80-100 | AC6: 100-120 | AD6: 120-150 | AE6: 150-170 | AF6: 170-200 | AG6: 200-250 | AH6: 0-20 | AI6: 20-35 | AJ6: 35-40 | AK6: 40-50 | AL6: 50-60 | AM6: 60-70 | AN6: 70-80 | AO6: 80-100 | AP6: 100-120 | AQ6: 120-150 | AR6: 150-170 | AS6: 170-200 | AT6: 200-250 | AU6: 0-20 | AV6: 20-35 | AW6: 35-40 | AX6: 40-50 | AY6: 50-60 | AZ6: 60-70 | BA6: 70-80 | BB6: 80-100 | BC6: 100-120 | BD6: 120-150 | BE6: 150-170 | BF6: 170-200 | BG6: 200-250
A7: RJ | B7: Rio de Janeiro | C7: 20000000 | D7: 23799999 | E7: Capital | F7: 5 / 8 | G7: =COUNTIFS(Pedidos!$E$2:$E$2224,">="&C7,Pedidos!$E$2:$E$2224,"<="&D7) -> 1030 | H7: 46.98 | I7: 82.21 | J7: 93.97 | K7: 93.97 | L7: 112.3 | M7: 131.02 | N7: 134.39 | O7: 167.99 | P7: 201.59 | Q7: 239.25 | R7: 271.15 | S7: 319 | T7: 398.74 | U7: 39.83 | V7: 54.1 | W7: 62.05 | X7: 71 | Y7: 79.81 | Z7: 88.2 | AA7: 97.6 | AB7: 119.8 | AC7: 135.94 | AD7: 174.85 | AE7: 192.1 | AF7: 218 | AG7: 272.9 | AH7: =(U7+AH$4*(Resumo!$C$7+Resumo!$C$8)+Resumo!$C$10*CEILING(AH$3/100,1)+Resumo!$C$9)*(1+Resumo!$C$11)-(AH$4*(Resumo!$B$6+Resumo!$B$7)+Resumo!$B$9+Resumo!$B$10*CEILING(AH$3/100,1)+(Resumo!$B$12+Resumo!$B$13)*CEILING(AH$3,1)) -> 41.334335 | AI7: =(V7+AI$4*(Resumo!$C$7+Resumo!$C$8)+Resumo!$C$10*CEILING(AI$3/100,1)+Resumo!$C$9)*(1+Resumo!$C$11)-(AI$4*(Resumo!$B$6+Resumo!$B$7)+Resumo!$B$9+Resumo!$B$10*CEILING(AI$3/100,1)+(Resumo!$B$12+Resumo!$B$13)*CEILING(AI$3,1)) -> 50.925046 | AJ7: =(W7+AJ$4*(Resumo!$C$7+Resumo!$C$8)+Resumo!$C$10*CEILING(AJ$3/100,1)+Resumo!$C$9)*(1+Resumo!$C$11)-(AJ$4*(Resumo!$B$6+Resumo!$B$7)+Resumo!$B$9+Resumo!$B$10*CEILING(AJ$3/100,1)+(Resumo!$B$12+Resumo!$B$13)*CEILING(AJ$3,1)) -> 54.759685 | AK7: =(X7+AK$4*(Resumo!$C$7+Resumo!$C$8)+Resumo!$C$10*CEILING(AK$3/100,1)+Resumo!$C$9)*(1+Resumo!$C$11)-(AK$4*(Resumo!$B$6+Resumo!$B$7)+Resumo!$B$9+Resumo!$B$10*CEILING(AK$3/100,1)+(Resumo!$B$12+Resumo!$B$13)*CEILING(AK$3,1)) -> 60.290258 | AL7: =(Y7+AL$4*(Resumo!$C$7+Resumo!$C$8)+Resumo!$C$10*CEILING(AL$3/100,1)+Resumo!$C$9)*(1+Resumo!$C$11)-(AL$4*(Resumo!$B$6+Resumo!$B$7)+Resumo!$B$9+Resumo!$B$10*CEILING(AL$3/100,1)+(Resumo!$B$12+Resumo!$B$13)*CEILING(AL$3,1)) -> 65.61632 | AM7: =(Z7+AM$4*(Resumo!$C$7+Resumo!$C$8)+Resumo!$C$10*CEILING(AM$3/100,1)+Resumo!$C$9)*(1+Resumo!$C$11)-(AM$4*(Resumo!$B$6+Resumo!$B$7)+Resumo!$B$9+Resumo!$B$10*CEILING(AM$3/100,1)+(Resumo!$B$12+Resumo!$B$13)*CEILING(AM$3,1)) -> 67.91692 | AN7: =(AA7+AN$4*(Resumo!$C$7+Resumo!$C$8)+Resumo!$C$10*CEILING(AN$3/100,1)+Resumo!$C$9)*(1+Resumo!$C$11)-(AN$4*(Resumo!$B$6+Resumo!$B$7)+Resumo!$B$9+Resumo!$B$10*CEILING(AN$3/100,1)+(Resumo!$B$12+Resumo!$B$13)*CEILING(AN$3,1)) -> 73.988796 | AO7: =(AB7+AO$4*(Resumo!$C$7+Resumo!$C$8)+Resumo!$C$10*CEILING(AO$3/100,1)+Resumo!$C$9)*(1+Resumo!$C$11)-(AO$4*(Resumo!$B$6+Resumo!$B$7)+Resumo!$B$9+Resumo!$B$10*CEILING(AO$3/100,1)+(Resumo!$B$12+Resumo!$B$13)*CEILING(AO$3,1)) -> 90.802347 | ... AT7: =(AG7+AT$4*(Resumo!$C$7+Resumo!$C$8)+Resumo!$C$10*CEILING(AT$3/100,1)+Resumo!$C$9)*(1+Resumo!$C$11)-(AT$4*(Resumo!$B$6+Resumo!$B$7)+Resumo!$B$9+Resumo!$B$10*CEILING(AT$3/100,1)+(Resumo!$B$12+Resumo!$B$13)*CEILING(AT$3,1)) -> 186.28474 | AU7: =1-AH7/H7 -> 0.12017166 | AV7: =1-AI7/I7 -> 0.38054925 | AW7: =1-AJ7/J7 -> 0.41726419 | AX7: =1-AK7/K7 -> 0.35840951 | AY7: =1-AL7/L7 -> 0.41570508 | AZ7: =1-AM7/M7 -> 0.48162937 | BA7: =1-AN7/N7 -> 0.44944716 | BB7: =1-AO7/O7 -> 0.45947766 | ... BG7: =1-AT7/T7 -> 0.53281653
A8: RJ | B8: Itaguaí | C8: 23800000 | D8: 23859999 | E8: Interior | F8: 5 / 13 | G8: =COUNTIFS(Pedidos!$E$2:$E$2224,">="&C8,Pedidos!$E$2:$E$2224,"<="&D8) -> 7 | H8: 56.98 | I8: 92.21 | J8: 103.97 | K8: 103.97 | L8: 122.3 | M8: 141.02 | N8: 144.39 | O8: 177.99 | P8: 211.59 | Q8: 249.25 | R8: 281.15 | S8: 329 | T8: 408.74 | U8: 52.71 | V8: 76.5 | W8: 87.4 | X8: 94 | Y8: 103.6 | Z8: 113.9 | AA8: 124.16 | AB8: 144.41 | AC8: 161.81 | AD8: 197.37 | AE8: 215.7 | AF8: 143.51 | AG8: 304.65 | AH8: =(U8+AH$4*(Resumo!$C$7+Resumo!$C$8)+Resumo!$C$10*CEILING(AH$3/100,1)+Resumo!$C$9)*(1+Resumo!$C$11)-(AH$4*(Resumo!$B$6+Resumo!$B$7)+Resumo!$B$9+Resumo!$B$10*CEILING(AH$3/100,1)+(Resumo!$B$12+Resumo!$B$13)*CEILING(AH$3,1)) -> 54.922735 | AI8: =(V8+AI$4*(Resumo!$C$7+Resumo!$C$8)+Resumo!$C$10*CEILING(AI$3/100,1)+Resumo!$C$9)*(1+Resumo!$C$11)-(AI$4*(Resumo!$B$6+Resumo!$B$7)+Resumo!$B$9+Resumo!$B$10*CEILING(AI$3/100,1)+(Resumo!$B$12+Resumo!$B$13)*CEILING(AI$3,1)) -> 74.557046 | AJ8: =(W8+AJ$4*(Resumo!$C$7+Resumo!$C$8)+Resumo!$C$10*CEILING(AJ$3/100,1)+Resumo!$C$9)*(1+Resumo!$C$11)-(AJ$4*(Resumo!$B$6+Resumo!$B$7)+Resumo!$B$9+Resumo!$B$10*CEILING(AJ$3/100,1)+(Resumo!$B$12+Resumo!$B$13)*CEILING(AJ$3,1)) -> 81.503935 | AK8: =(X8+AK$4*(Resumo!$C$7+Resumo!$C$8)+Resumo!$C$10*CEILING(AK$3/100,1)+Resumo!$C$9)*(1+Resumo!$C$11)-(AK$4*(Resumo!$B$6+Resumo!$B$7)+Resumo!$B$9+Resumo!$B$10*CEILING(AK$3/100,1)+(Resumo!$B$12+Resumo!$B$13)*CEILING(AK$3,1)) -> 84.555258 | AL8: =(Y8+AL$4*(Resumo!$C$7+Resumo!$C$8)+Resumo!$C$10*CEILING(AL$3/100,1)+Resumo!$C$9)*(1+Resumo!$C$11)-(AL$4*(Resumo!$B$6+Resumo!$B$7)+Resumo!$B$9+Resumo!$B$10*CEILING(AL$3/100,1)+(Resumo!$B$12+Resumo!$B$13)*CEILING(AL$3,1)) -> 90.71477 | AM8: =(Z8+AM$4*(Resumo!$C$7+Resumo!$C$8)+Resumo!$C$10*CEILING(AM$3/100,1)+Resumo!$C$9)*(1+Resumo!$C$11)-(AM$4*(Resumo!$B$6+Resumo!$B$7)+Resumo!$B$9+Resumo!$B$10*CEILING(AM$3/100,1)+(Resumo!$B$12+Resumo!$B$13)*CEILING(AM$3,1)) -> 95.03042 | AN8: =(AA8+AN$4*(Resumo!$C$7+Resumo!$C$8)+Resumo!$C$10*CEILING(AN$3/100,1)+Resumo!$C$9)*(1+Resumo!$C$11)-(AN$4*(Resumo!$B$6+Resumo!$B$7)+Resumo!$B$9+Resumo!$B$10*CEILING(AN$3/100,1)+(Resumo!$B$12+Resumo!$B$13)*CEILING(AN$3,1)) -> 102.0096 | AO8: =(AB8+AO$4*(Resumo!$C$7+Resumo!$C$8)+Resumo!$C$10*CEILING(AO$3/100,1)+Resumo!$C$9)*(1+Resumo!$C$11)-(AO$4*(Resumo!$B$6+Resumo!$B$7)+Resumo!$B$9+Resumo!$B$10*CEILING(AO$3/100,1)+(Resumo!$B$12+Resumo!$B$13)*CEILING(AO$3,1)) -> 116.7659 | ... AT8: =(AG8+AT$4*(Resumo!$C$7+Resumo!$C$8)+Resumo!$C$10*CEILING(AT$3/100,1)+Resumo!$C$9)*(1+Resumo!$C$11)-(AT$4*(Resumo!$B$6+Resumo!$B$7)+Resumo!$B$9+Resumo!$B$10*CEILING(AT$3/100,1)+(Resumo!$B$12+Resumo!$B$13)*CEILING(AT$3,1)) -> 219.78099 | AU8: =1-AH8/H8 -> 0.036105032 | AV8: =1-AI8/I8 -> 0.19144294 | AW8: =1-AJ8/J8 -> 0.21608219 | AX8: =1-AK8/K8 -> 0.18673408 | AY8: =1-AL8/L8 -> 0.25826026 | AZ8: =1-AM8/M8 -> 0.32612098 | BA8: =1-AN8/N8 -> 0.29351343 | BB8: =1-AO8/O8 -> 0.34397496 | ... BG8: =1-AT8/T8 -> 0.46229636
A9: RJ | B9: Mangaratiba | C9: 23860000 | D9: 23889999 | E9: Interior | F9: 10 / 13 | G9: =COUNTIFS(Pedidos!$E$2:$E$2224,">="&C9,Pedidos!$E$2:$E$2224,"<="&D9) -> 6 | H9: 77.35 | I9: 108.83 | J9: 124.38 | K9: 124.38 | L9: 142.32 | M9: 166.05 | N9: 157.88 | O9: 197.35 | P9: 236.82 | Q9: 264.84 | R9: 300.15 | S9: 353.12 | T9: 441.4 | U9: 52.71 | V9: 76.5 | W9: 87.4 | X9: 94 | Y9: 103.6 | Z9: 113.9 | AA9: 124.16 | AB9: 144.41 | AC9: 161.81 | AD9: 197.37 | AE9: 215.7 | AF9: 143.51 | AG9: 304.65 | AH9: =(U9+AH$4*(Resumo!$C$7+Resumo!$C$8)+Resumo!$C$10*CEILING(AH$3/100,1)+Resumo!$C$9)*(1+Resumo!$C$11)-(AH$4*(Resumo!$B$6+Resumo!$B$7)+Resumo!$B$9+Resumo!$B$10*CEILING(AH$3/100,1)+(Resumo!$B$12+Resumo!$B$13)*CEILING(AH$3,1)) -> 54.922735 | AI9: =(V9+AI$4*(Resumo!$C$7+Resumo!$C$8)+Resumo!$C$10*CEILING(AI$3/100,1)+Resumo!$C$9)*(1+Resumo!$C$11)-(AI$4*(Resumo!$B$6+Resumo!$B$7)+Resumo!$B$9+Resumo!$B$10*CEILING(AI$3/100,1)+(Resumo!$B$12+Resumo!$B$13)*CEILING(AI$3,1)) -> 74.557046 | AJ9: =(W9+AJ$4*(Resumo!$C$7+Resumo!$C$8)+Resumo!$C$10*CEILING(AJ$3/100,1)+Resumo!$C$9)*(1+Resumo!$C$11)-(AJ$4*(Resumo!$B$6+Resumo!$B$7)+Resumo!$B$9+Resumo!$B$10*CEILING(AJ$3/100,1)+(Resumo!$B$12+Resumo!$B$13)*CEILING(AJ$3,1)) -> 81.503935 | AK9: =(X9+AK$4*(Resumo!$C$7+Resumo!$C$8)+Resumo!$C$10*CEILING(AK$3/100,1)+Resumo!$C$9)*(1+Resumo!$C$11)-(AK$4*(Resumo!$B$6+Resumo!$B$7)+Resumo!$B$9+Resumo!$B$10*CEILING(AK$3/100,1)+(Resumo!$B$12+Resumo!$B$13)*CEILING(AK$3,1)) -> 84.555258 | AL9: =(Y9+AL$4*(Resumo!$C$7+Resumo!$C$8)+Resumo!$C$10*CEILING(AL$3/100,1)+Resumo!$C$9)*(1+Resumo!$C$11)-(AL$4*(Resumo!$B$6+Resumo!$B$7)+Resumo!$B$9+Resumo!$B$10*CEILING(AL$3/100,1)+(Resumo!$B$12+Resumo!$B$13)*CEILING(AL$3,1)) -> 90.71477 | AM9: =(Z9+AM$4*(Resumo!$C$7+Resumo!$C$8)+Resumo!$C$10*CEILING(AM$3/100,1)+Resumo!$C$9)*(1+Resumo!$C$11)-(AM$4*(Resumo!$B$6+Resumo!$B$7)+Resumo!$B$9+Resumo!$B$10*CEILING(AM$3/100,1)+(Resumo!$B$12+Resumo!$B$13)*CEILING(AM$3,1)) -> 95.03042 | AN9: =(AA9+AN$4*(Resumo!$C$7+Resumo!$C$8)+Resumo!$C$10*CEILING(AN$3/100,1)+Resumo!$C$9)*(1+Resumo!$C$11)-(AN$4*(Resumo!$B$6+Resumo!$B$7)+Resumo!$B$9+Resumo!$B$10*CEILING(AN$3/100,1)+(Resumo!$B$12+Resumo!$B$13)*CEILING(AN$3,1)) -> 102.0096 | AO9: =(AB9+AO$4*(Resumo!$C$7+Resumo!$C$8)+Resumo!$C$10*CEILING(AO$3/100,1)+Resumo!$C$9)*(1+Resumo!$C$11)-(AO$4*(Resumo!$B$6+Resumo!$B$7)+Resumo!$B$9+Resumo!$B$10*CEILING(AO$3/100,1)+(Resumo!$B$12+Resumo!$B$13)*CEILING(AO$3,1)) -> 116.7659 | ... AT9: =(AG9+AT$4*(Resumo!$C$7+Resumo!$C$8)+Resumo!$C$10*CEILING(AT$3/100,1)+Resumo!$C$9)*(1+Resumo!$C$11)-(AT$4*(Resumo!$B$6+Resumo!$B$7)+Resumo!$B$9+Resumo!$B$10*CEILING(AT$3/100,1)+(Resumo!$B$12+Resumo!$B$13)*CEILING(AT$3,1)) -> 219.78099 | AU9: =1-AH9/H9 -> 0.28994525 | AV9: =1-AI9/I9 -> 0.31492193 | AW9: =1-AJ9/J9 -> 0.34471833 | AX9: =1-AK9/K9 -> 0.32018606 | AY9: =1-AL9/L9 -> 0.36259999 | AZ9: =1-AM9/M9 -> 0.42769997 | BA9: =1-AN9/N9 -> 0.35387892 | BB9: =1-AO9/O9 -> 0.4083309 | ... BG9: =1-AT9/T9 -> 0.50208204
A10: RJ | B10: Seropédica | C10: 23890000 | D10: 23899999 | E10: Interior | F10: 5 / 13 | G10: =COUNTIFS(Pedidos!$E$2:$E$2224,">="&C10,Pedidos!$E$2:$E$2224,"<="&D10) -> 13 | H10: 56.98 | I10: 92.21 | J10: 103.97 | K10: 103.97 | L10: 122.3 | M10: 141.02 | N10: 144.39 | O10: 177.99 | P10: 211.59 | Q10: 249.25 | R10: 281.15 | S10: 329 | T10: 408.74 | U10: 52.71 | V10: 76.5 | W10: 87.4 | X10: 94 | Y10: 103.6 | Z10: 113.9 | AA10: 124.16 | AB10: 144.41 | AC10: 161.81 | AD10: 197.37 | AE10: 215.7 | AF10: 143.51 | AG10: 304.65 | AH10: =(U10+AH$4*(Resumo!$C$7+Resumo!$C$8)+Resumo!$C$10*CEILING(AH$3/100,1)+Resumo!$C$9)*(1+Resumo!$C$11)-(AH$4*(Resumo!$B$6+Resumo!$B$7)+Resumo!$B$9+Resumo!$B$10*CEILING(AH$3/100,1)+(Resumo!$B$12+Resumo!$B$13)*CEILING(AH$3,1)) -> 54.922735 | AI10: =(V10+AI$4*(Resumo!$C$7+Resumo!$C$8)+Resumo!$C$10*CEILING(AI$3/100,1)+Resumo!$C$9)*(1+Resumo!$C$11)-(AI$4*(Resumo!$B$6+Resumo!$B$7)+Resumo!$B$9+Resumo!$B$10*CEILING(AI$3/100,1)+(Resumo!$B$12+Resumo!$B$13)*CEILING(AI$3,1)) -> 74.557046 | AJ10: =(W10+AJ$4*(Resumo!$C$7+Resumo!$C$8)+Resumo!$C$10*CEILING(AJ$3/100,1)+Resumo!$C$9)*(1+Resumo!$C$11)-(AJ$4*(Resumo!$B$6+Resumo!$B$7)+Resumo!$B$9+Resumo!$B$10*CEILING(AJ$3/100,1)+(Resumo!$B$12+Resumo!$B$13)*CEILING(AJ$3,1)) -> 81.503935 | AK10: =(X10+AK$4*(Resumo!$C$7+Resumo!$C$8)+Resumo!$C$10*CEILING(AK$3/100,1)+Resumo!$C$9)*(1+Resumo!$C$11)-(AK$4*(Resumo!$B$6+Resumo!$B$7)+Resumo!$B$9+Resumo!$B$10*CEILING(AK$3/100,1)+(Resumo!$B$12+Resumo!$B$13)*CEILING(AK$3,1)) -> 84.555258 | AL10: =(Y10+AL$4*(Resumo!$C$7+Resumo!$C$8)+Resumo!$C$10*CEILING(AL$3/100,1)+Resumo!$C$9)*(1+Resumo!$C$11)-(AL$4*(Resumo!$B$6+Resumo!$B$7)+Resumo!$B$9+Resumo!$B$10*CEILING(AL$3/100,1)+(Resumo!$B$12+Resumo!$B$13)*CEILING(AL$3,1)) -> 90.71477 | AM10: =(Z10+AM$4*(Resumo!$C$7+Resumo!$C$8)+Resumo!$C$10*CEILING(AM$3/100,1)+Resumo!$C$9)*(1+Resumo!$C$11)-(AM$4*(Resumo!$B$6+Resumo!$B$7)+Resumo!$B$9+Resumo!$B$10*CEILING(AM$3/100,1)+(Resumo!$B$12+Resumo!$B$13)*CEILING(AM$3,1)) -> 95.03042 | AN10: =(AA10+AN$4*(Resumo!$C$7+Resumo!$C$8)+Resumo!$C$10*CEILING(AN$3/100,1)+Resumo!$C$9)*(1+Resumo!$C$11)-(AN$4*(Resumo!$B$6+Resumo!$B$7)+Resumo!$B$9+Resumo!$B$10*CEILING(AN$3/100,1)+(Resumo!$B$12+Resumo!$B$13)*CEILING(AN$3,1)) -> 102.0096 | AO10: =(AB10+AO$4*(Resumo!$C$7+Resumo!$C$8)+Resumo!$C$10*CEILING(AO$3/100,1)+Resumo!$C$9)*(1+Resumo!$C$11)-(AO$4*(Resumo!$B$6+Resumo!$B$7)+Resumo!$B$9+Resumo!$B$10*CEILING(AO$3/100,1)+(Resumo!$B$12+Resumo!$B$13)*CEILING(AO$3,1)) -> 116.7659 | ... AT10: =(AG10+AT$4*(Resumo!$C$7+Resumo!$C$8)+Resumo!$C$10*CEILING(AT$3/100,1)+Resumo!$C$9)*(1+Resumo!$C$11)-(AT$4*(Resumo!$B$6+Resumo!$B$7)+Resumo!$B$9+Resumo!$B$10*CEILING(AT$3/100,1)+(Resumo!$B$12+Resumo!$B$13)*CEILING(AT$3,1)) -> 219.78099 | AU10: =1-AH10/H10 -> 0.036105032 | AV10: =1-AI10/I10 -> 0.19144294 | AW10: =1-AJ10/J10 -> 0.21608219 | AX10: =1-AK10/K10 -> 0.18673408 | AY10: =1-AL10/L10 -> 0.25826026 | AZ10: =1-AM10/M10 -> 0.32612098 | BA10: =1-AN10/N10 -> 0.29351343 | BB10: =1-AO10/O10 -> 0.34397496 | ... BG10: =1-AT10/T10 -> 0.46229636
A11: RJ | B11: Angra dos Reis | C11: 23900000 | D11: 23969999 | E11: Interior | F11: 10 / 13 | G11: =COUNTIFS(Pedidos!$E$2:$E$2224,">="&C11,Pedidos!$E$2:$E$2224,"<="&D11) -> 35 | H11: 77.35 | I11: 108.83 | J11: 124.38 | K11: 124.38 | L11: 142.32 | M11: 166.05 | N11: 157.88 | O11: 197.35 | P11: 236.82 | Q11: 264.84 | R11: 300.15 | S11: 353.12 | T11: 441.4 | U11: 52.71 | V11: 76.5 | W11: 87.4 | X11: 94 | Y11: 103.6 | Z11: 113.9 | AA11: 124.16 | AB11: 144.41 | AC11: 161.81 | AD11: 197.37 | AE11: 215.7 | AF11: 143.51 | AG11: 304.65 | AH11: =(U11+AH$4*(Resumo!$C$7+Resumo!$C$8)+Resumo!$C$10*CEILING(AH$3/100,1)+Resumo!$C$9)*(1+Resumo!$C$11)-(AH$4*(Resumo!$B$6+Resumo!$B$7)+Resumo!$B$9+Resumo!$B$10*CEILING(AH$3/100,1)+(Resumo!$B$12+Resumo!$B$13)*CEILING(AH$3,1)) -> 54.922735 | AI11: =(V11+AI$4*(Resumo!$C$7+Resumo!$C$8)+Resumo!$C$10*CEILING(AI$3/100,1)+Resumo!$C$9)*(1+Resumo!$C$11)-(AI$4*(Resumo!$B$6+Resumo!$B$7)+Resumo!$B$9+Resumo!$B$10*CEILING(AI$3/100,1)+(Resumo!$B$12+Resumo!$B$13)*CEILING(AI$3,1)) -> 74.557046 | AJ11: =(W11+AJ$4*(Resumo!$C$7+Resumo!$C$8)+Resumo!$C$10*CEILING(AJ$3/100,1)+Resumo!$C$9)*(1+Resumo!$C$11)-(AJ$4*(Resumo!$B$6+Resumo!$B$7)+Resumo!$B$9+Resumo!$B$10*CEILING(AJ$3/100,1)+(Resumo!$B$12+Resumo!$B$13)*CEILING(AJ$3,1)) -> 81.503935 | AK11: =(X11+AK$4*(Resumo!$C$7+Resumo!$C$8)+Resumo!$C$10*CEILING(AK$3/100,1)+Resumo!$C$9)*(1+Resumo!$C$11)-(AK$4*(Resumo!$B$6+Resumo!$B$7)+Resumo!$B$9+Resumo!$B$10*CEILING(AK$3/100,1)+(Resumo!$B$12+Resumo!$B$13)*CEILING(AK$3,1)) -> 84.555258 | AL11: =(Y11+AL$4*(Resumo!$C$7+Resumo!$C$8)+Resumo!$C$10*CEILING(AL$3/100,1)+Resumo!$C$9)*(1+Resumo!$C$11)-(AL$4*(Resumo!$B$6+Resumo!$B$7)+Resumo!$B$9+Resumo!$B$10*CEILING(AL$3/100,1)+(Resumo!$B$12+Resumo!$B$13)*CEILING(AL$3,1)) -> 90.71477 | AM11: =(Z11+AM$4*(Resumo!$C$7+Resumo!$C$8)+Resumo!$C$10*CEILING(AM$3/100,1)+Resumo!$C$9)*(1+Resumo!$C$11)-(AM$4*(Resumo!$B$6+Resumo!$B$7)+Resumo!$B$9+Resumo!$B$10*CEILING(AM$3/100,1)+(Resumo!$B$12+Resumo!$B$13)*CEILING(AM$3,1)) -> 95.03042 | AN11: =(AA11+AN$4*(Resumo!$C$7+Resumo!$C$8)+Resumo!$C$10*CEILING(AN$3/100,1)+Resumo!$C$9)*(1+Resumo!$C$11)-(AN$4*(Resumo!$B$6+Resumo!$B$7)+Resumo!$B$9+Resumo!$B$10*CEILING(AN$3/100,1)+(Resumo!$B$12+Resumo!$B$13)*CEILING(AN$3,1)) -> 102.0096 | AO11: =(AB11+AO$4*(Resumo!$C$7+Resumo!$C$8)+Resumo!$C$10*CEILING(AO$3/100,1)+Resumo!$C$9)*(1+Resumo!$C$11)-(AO$4*(Resumo!$B$6+Resumo!$B$7)+Resumo!$B$9+Resumo!$B$10*CEILING(AO$3/100,1)+(Resumo!$B$12+Resumo!$B$13)*CEILING(AO$3,1)) -> 116.7659 | ... AT11: =(AG11+AT$4*(Resumo!$C$7+Resumo!$C$8)+Resumo!$C$10*CEILING(AT$3/100,1)+Resumo!$C$9)*(1+Resumo!$C$11)-(AT$4*(Resumo!$B$6+Resumo!$B$7)+Resumo!$B$9+Resumo!$B$10*CEILING(AT$3/100,1)+(Resumo!$B$12+Resumo!$B$13)*CEILING(AT$3,1)) -> 219.78099 | AU11: =1-AH11/H11 -> 0.28994525 | AV11: =1-AI11/I11 -> 0.31492193 | AW11: =1-AJ11/J11 -> 0.34471833 | AX11: =1-AK11/K11 -> 0.32018606 | AY11: =1-AL11/L11 -> 0.36259999 | AZ11: =1-AM11/M11 -> 0.42769997 | BA11: =1-AN11/N11 -> 0.35387892 | BB11: =1-AO11/O11 -> 0.4083309 | ... BG11: =1-AT11/T11 -> 0.50208204
A12: RJ | B12: Paraty | C12: 23970000 | D12: 23999999 | E12: Interior | F12: 10 / 13 | G12: =COUNTIFS(Pedidos!$E$2:$E$2224,">="&C12,Pedidos!$E$2:$E$2224,"<="&D12) -> 5 | H12: 77.35 | I12: 108.83 | J12: 124.38 | K12: 124.38 | L12: 142.32 | M12: 166.05 | N12: 157.88 | O12: 197.35 | P12: 236.82 | Q12: 264.84 | R12: 300.15 | S12: 353.12 | T12: 441.4 | U12: 52.71 | V12: 76.5 | W12: 87.4 | X12: 94 | Y12: 103.6 | Z12: 113.9 | AA12: 124.16 | AB12: 144.41 | AC12: 161.81 | AD12: 197.37 | AE12: 215.7 | AF12: 143.51 | AG12: 304.65 | AH12: =(U12+AH$4*(Resumo!$C$7+Resumo!$C$8)+Resumo!$C$10*CEILING(AH$3/100,1)+Resumo!$C$9)*(1+Resumo!$C$11)-(AH$4*(Resumo!$B$6+Resumo!$B$7)+Resumo!$B$9+Resumo!$B$10*CEILING(AH$3/100,1)+(Resumo!$B$12+Resumo!$B$13)*CEILING(AH$3,1)) -> 54.922735 | AI12: =(V12+AI$4*(Resumo!$C$7+Resumo!$C$8)+Resumo!$C$10*CEILING(AI$3/100,1)+Resumo!$C$9)*(1+Resumo!$C$11)-(AI$4*(Resumo!$B$6+Resumo!$B$7)+Resumo!$B$9+Resumo!$B$10*CEILING(AI$3/100,1)+(Resumo!$B$12+Resumo!$B$13)*CEILING(AI$3,1)) -> 74.557046 | AJ12: =(W12+AJ$4*(Resumo!$C$7+Resumo!$C$8)+Resumo!$C$10*CEILING(AJ$3/100,1)+Resumo!$C$9)*(1+Resumo!$C$11)-(AJ$4*(Resumo!$B$6+Resumo!$B$7)+Resumo!$B$9+Resumo!$B$10*CEILING(AJ$3/100,1)+(Resumo!$B$12+Resumo!$B$13)*CEILING(AJ$3,1)) -> 81.503935 | AK12: =(X12+AK$4*(Resumo!$C$7+Resumo!$C$8)+Resumo!$C$10*CEILING(AK$3/100,1)+Resumo!$C$9)*(1+Resumo!$C$11)-(AK$4*(Resumo!$B$6+Resumo!$B$7)+Resumo!$B$9+Resumo!$B$10*CEILING(AK$3/100,1)+(Resumo!$B$12+Resumo!$B$13)*CEILING(AK$3,1)) -> 84.555258 | AL12: =(Y12+AL$4*(Resumo!$C$7+Resumo!$C$8)+Resumo!$C$10*CEILING(AL$3/100,1)+Resumo!$C$9)*(1+Resumo!$C$11)-(AL$4*(Resumo!$B$6+Resumo!$B$7)+Resumo!$B$9+Resumo!$B$10*CEILING(AL$3/100,1)+(Resumo!$B$12+Resumo!$B$13)*CEILING(AL$3,1)) -> 90.71477 | AM12: =(Z12+AM$4*(Resumo!$C$7+Resumo!$C$8)+Resumo!$C$10*CEILING(AM$3/100,1)+Resumo!$C$9)*(1+Resumo!$C$11)-(AM$4*(Resumo!$B$6+Resumo!$B$7)+Resumo!$B$9+Resumo!$B$10*CEILING(AM$3/100,1)+(Resumo!$B$12+Resumo!$B$13)*CEILING(AM$3,1)) -> 95.03042 | AN12: =(AA12+AN$4*(Resumo!$C$7+Resumo!$C$8)+Resumo!$C$10*CEILING(AN$3/100,1)+Resumo!$C$9)*(1+Resumo!$C$11)-(AN$4*(Resumo!$B$6+Resumo!$B$7)+Resumo!$B$9+Resumo!$B$10*CEILING(AN$3/100,1)+(Resumo!$B$12+Resumo!$B$13)*CEILING(AN$3,1)) -> 102.0096 | AO12: =(AB12+AO$4*(Resumo!$C$7+Resumo!$C$8)+Resumo!$C$10*CEILING(AO$3/100,1)+Resumo!$C$9)*(1+Resumo!$C$11)-(AO$4*(Resumo!$B$6+Resumo!$B$7)+Resumo!$B$9+Resumo!$B$10*CEILING(AO$3/100,1)+(Resumo!$B$12+Resumo!$B$13)*CEILING(AO$3,1)) -> 116.7659 | ... AT12: =(AG12+AT$4*(Resumo!$C$7+Resumo!$C$8)+Resumo!$C$10*CEILING(AT$3/100,1)+Resumo!$C$9)*(1+Resumo!$C$11)-(AT$4*(Resumo!$B$6+Resumo!$B$7)+Resumo!$B$9+Resumo!$B$10*CEILING(AT$3/100,1)+(Resumo!$B$12+Resumo!$B$13)*CEILING(AT$3,1)) -> 219.78099 | AU12: =1-AH12/H12 -> 0.28994525 | AV12: =1-AI12/I12 -> 0.31492193 | AW12: =1-AJ12/J12 -> 0.34471833 | AX12: =1-AK12/K12 -> 0.32018606 | AY12: =1-AL12/L12 -> 0.36259999 | AZ12: =1-AM12/M12 -> 0.42769997 | BA12: =1-AN12/N12 -> 0.35387892 | BB12: =1-AO12/O12 -> 0.4083309 | ... BG12: =1-AT12/T12 -> 0.50208204
A13: RJ | B13: Niterói | C13: 24000000 | D13: 24399999 | E13: Metropolitana | F13: 7 / 10 | G13: =COUNTIFS(Pedidos!$E$2:$E$2224,">="&C13,Pedidos!$E$2:$E$2224,"<="&D13) -> 68 | H13: 57.47 | I13: 100.58 | J13: 114.95 | K13: 114.95 | L13: 128.14 | M13: 149.5 | N13: 142.74 | O13: 178.42 | P13: 214.11 | Q13: 249.03 | R13: 282.23 | S13: 332.05 | T13: 415.05 | U13: 48.69 | V13: 70 | W13: 79.65 | X13: 82.25 | Y13: 91.6 | Z13: 100.9 | AA13: 110.55 | AB13: 127.92 | AC13: 144.44 | AD13: 183.45 | AE13: 201.15 | AF13: 227.7 | AG13: 285.09 | AH13: =(U13+AH$4*(Resumo!$C$7+Resumo!$C$8)+Resumo!$C$10*CEILING(AH$3/100,1)+Resumo!$C$9)*(1+Resumo!$C$11)-(AH$4*(Resumo!$B$6+Resumo!$B$7)+Resumo!$B$9+Resumo!$B$10*CEILING(AH$3/100,1)+(Resumo!$B$12+Resumo!$B$13)*CEILING(AH$3,1)) -> 50.681635 | AI13: =(V13+AI$4*(Resumo!$C$7+Resumo!$C$8)+Resumo!$C$10*CEILING(AI$3/100,1)+Resumo!$C$9)*(1+Resumo!$C$11)-(AI$4*(Resumo!$B$6+Resumo!$B$7)+Resumo!$B$9+Resumo!$B$10*CEILING(AI$3/100,1)+(Resumo!$B$12+Resumo!$B$13)*CEILING(AI$3,1)) -> 67.699546 | AJ13: =(W13+AJ$4*(Resumo!$C$7+Resumo!$C$8)+Resumo!$C$10*CEILING(AJ$3/100,1)+Resumo!$C$9)*(1+Resumo!$C$11)-(AJ$4*(Resumo!$B$6+Resumo!$B$7)+Resumo!$B$9+Resumo!$B$10*CEILING(AJ$3/100,1)+(Resumo!$B$12+Resumo!$B$13)*CEILING(AJ$3,1)) -> 73.327685 | AK13: =(X13+AK$4*(Resumo!$C$7+Resumo!$C$8)+Resumo!$C$10*CEILING(AK$3/100,1)+Resumo!$C$9)*(1+Resumo!$C$11)-(AK$4*(Resumo!$B$6+Resumo!$B$7)+Resumo!$B$9+Resumo!$B$10*CEILING(AK$3/100,1)+(Resumo!$B$12+Resumo!$B$13)*CEILING(AK$3,1)) -> 72.159008 | AL13: =(Y13+AL$4*(Resumo!$C$7+Resumo!$C$8)+Resumo!$C$10*CEILING(AL$3/100,1)+Resumo!$C$9)*(1+Resumo!$C$11)-(AL$4*(Resumo!$B$6+Resumo!$B$7)+Resumo!$B$9+Resumo!$B$10*CEILING(AL$3/100,1)+(Resumo!$B$12+Resumo!$B$13)*CEILING(AL$3,1)) -> 78.05477 | AM13: =(Z13+AM$4*(Resumo!$C$7+Resumo!$C$8)+Resumo!$C$10*CEILING(AM$3/100,1)+Resumo!$C$9)*(1+Resumo!$C$11)-(AM$4*(Resumo!$B$6+Resumo!$B$7)+Resumo!$B$9+Resumo!$B$10*CEILING(AM$3/100,1)+(Resumo!$B$12+Resumo!$B$13)*CEILING(AM$3,1)) -> 81.31542 | AN13: =(AA13+AN$4*(Resumo!$C$7+Resumo!$C$8)+Resumo!$C$10*CEILING(AN$3/100,1)+Resumo!$C$9)*(1+Resumo!$C$11)-(AN$4*(Resumo!$B$6+Resumo!$B$7)+Resumo!$B$9+Resumo!$B$10*CEILING(AN$3/100,1)+(Resumo!$B$12+Resumo!$B$13)*CEILING(AN$3,1)) -> 87.651046 | AO13: =(AB13+AO$4*(Resumo!$C$7+Resumo!$C$8)+Resumo!$C$10*CEILING(AO$3/100,1)+Resumo!$C$9)*(1+Resumo!$C$11)-(AO$4*(Resumo!$B$6+Resumo!$B$7)+Resumo!$B$9+Resumo!$B$10*CEILING(AO$3/100,1)+(Resumo!$B$12+Resumo!$B$13)*CEILING(AO$3,1)) -> 99.368947 | ... AT13: =(AG13+AT$4*(Resumo!$C$7+Resumo!$C$8)+Resumo!$C$10*CEILING(AT$3/100,1)+Resumo!$C$9)*(1+Resumo!$C$11)-(AT$4*(Resumo!$B$6+Resumo!$B$7)+Resumo!$B$9+Resumo!$B$10*CEILING(AT$3/100,1)+(Resumo!$B$12+Resumo!$B$13)*CEILING(AT$3,1)) -> 199.14519 | AU13: =1-AH13/H13 -> 0.11812014 | AV13: =1-AI13/I13 -> 0.32690847 | AW13: =1-AJ13/J13 -> 0.36209061 | AX13: =1-AK13/K13 -> 0.37225743 | AY13: =1-AL13/L13 -> 0.39086335 | AZ13: =1-AM13/M13 -> 0.45608415 | BA13: =1-AN13/N13 -> 0.38593915 | BB13: =1-AO13/O13 -> 0.44306161 | ... BG13: =1-AT13/T13 -> 0.52018989
A14: RJ | B14: São Gonçalo | C14: 24400000 | D14: 24799999 | E14: Metropolitana | F14: 7 / 10 | G14: =COUNTIFS(Pedidos!$E$2:$E$2224,">="&C14,Pedidos!$E$2:$E$2224,"<="&D14) -> 135 | H14: 57.47 | I14: 100.58 | J14: 114.95 | K14: 114.95 | L14: 128.14 | M14: 149.5 | N14: 142.74 | O14: 178.42 | P14: 214.11 | Q14: 249.03 | R14: 282.23 | S14: 332.05 | T14: 415.05 | U14: 48.69 | V14: 70 | W14: 79.65 | X14: 82.25 | Y14: 91.6 | Z14: 100.9 | AA14: 110.55 | AB14: 127.92 | AC14: 144.44 | AD14: 183.45 | AE14: 201.15 | AF14: 227.7 | AG14: 285.09 | AH14: =(U14+AH$4*(Resumo!$C$7+Resumo!$C$8)+Resumo!$C$10*CEILING(AH$3/100,1)+Resumo!$C$9)*(1+Resumo!$C$11)-(AH$4*(Resumo!$B$6+Resumo!$B$7)+Resumo!$B$9+Resumo!$B$10*CEILING(AH$3/100,1)+(Resumo!$B$12+Resumo!$B$13)*CEILING(AH$3,1)) -> 50.681635 | AI14: =(V14+AI$4*(Resumo!$C$7+Resumo!$C$8)+Resumo!$C$10*CEILING(AI$3/100,1)+Resumo!$C$9)*(1+Resumo!$C$11)-(AI$4*(Resumo!$B$6+Resumo!$B$7)+Resumo!$B$9+Resumo!$B$10*CEILING(AI$3/100,1)+(Resumo!$B$12+Resumo!$B$13)*CEILING(AI$3,1)) -> 67.699546 | AJ14: =(W14+AJ$4*(Resumo!$C$7+Resumo!$C$8)+Resumo!$C$10*CEILING(AJ$3/100,1)+Resumo!$C$9)*(1+Resumo!$C$11)-(AJ$4*(Resumo!$B$6+Resumo!$B$7)+Resumo!$B$9+Resumo!$B$10*CEILING(AJ$3/100,1)+(Resumo!$B$12+Resumo!$B$13)*CEILING(AJ$3,1)) -> 73.327685 | AK14: =(X14+AK$4*(Resumo!$C$7+Resumo!$C$8)+Resumo!$C$10*CEILING(AK$3/100,1)+Resumo!$C$9)*(1+Resumo!$C$11)-(AK$4*(Resumo!$B$6+Resumo!$B$7)+Resumo!$B$9+Resumo!$B$10*CEILING(AK$3/100,1)+(Resumo!$B$12+Resumo!$B$13)*CEILING(AK$3,1)) -> 72.159008 | AL14: =(Y14+AL$4*(Resumo!$C$7+Resumo!$C$8)+Resumo!$C$10*CEILING(AL$3/100,1)+Resumo!$C$9)*(1+Resumo!$C$11)-(AL$4*(Resumo!$B$6+Resumo!$B$7)+Resumo!$B$9+Resumo!$B$10*CEILING(AL$3/100,1)+(Resumo!$B$12+Resumo!$B$13)*CEILING(AL$3,1)) -> 78.05477 | AM14: =(Z14+AM$4*(Resumo!$C$7+Resumo!$C$8)+Resumo!$C$10*CEILING(AM$3/100,1)+Resumo!$C$9)*(1+Resumo!$C$11)-(AM$4*(Resumo!$B$6+Resumo!$B$7)+Resumo!$B$9+Resumo!$B$10*CEILING(AM$3/100,1)+(Resumo!$B$12+Resumo!$B$13)*CEILING(AM$3,1)) -> 81.31542 | AN14: =(AA14+AN$4*(Resumo!$C$7+Resumo!$C$8)+Resumo!$C$10*CEILING(AN$3/100,1)+Resumo!$C$9)*(1+Resumo!$C$11)-(AN$4*(Resumo!$B$6+Resumo!$B$7)+Resumo!$B$9+Resumo!$B$10*CEILING(AN$3/100,1)+(Resumo!$B$12+Resumo!$B$13)*CEILING(AN$3,1)) -> 87.651046 | AO14: =(AB14+AO$4*(Resumo!$C$7+Resumo!$C$8)+Resumo!$C$10*CEILING(AO$3/100,1)+Resumo!$C$9)*(1+Resumo!$C$11)-(AO$4*(Resumo!$B$6+Resumo!$B$7)+Resumo!$B$9+Resumo!$B$10*CEILING(AO$3/100,1)+(Resumo!$B$12+Resumo!$B$13)*CEILING(AO$3,1)) -> 99.368947 | ... AT14: =(AG14+AT$4*(Resumo!$C$7+Resumo!$C$8)+Resumo!$C$10*CEILING(AT$3/100,1)+Resumo!$C$9)*(1+Resumo!$C$11)-(AT$4*(Resumo!$B$6+Resumo!$B$7)+Resumo!$B$9+Resumo!$B$10*CEILING(AT$3/100,1)+(Resumo!$B$12+Resumo!$B$13)*CEILING(AT$3,1)) -> 199.14519 | AU14: =1-AH14/H14 -> 0.11812014 | AV14: =1-AI14/I14 -> 0.32690847 | AW14: =1-AJ14/J14 -> 0.36209061 | AX14: =1-AK14/K14 -> 0.37225743 | AY14: =1-AL14/L14 -> 0.39086335 | AZ14: =1-AM14/M14 -> 0.45608415 | BA14: =1-AN14/N14 -> 0.38593915 | BB14: =1-AO14/O14 -> 0.44306161 | ... BG14: =1-AT14/T14 -> 0.52018989
A15: RJ | B15: Itaboraí | C15: 24800000 | D15: 24889999 | E15: Interior | F15: 7 / 13 | G15: =COUNTIFS(Pedidos!$E$2:$E$2224,">="&C15,Pedidos!$E$2:$E$2224,"<="&D15) -> 25 | H15: 57.47 | I15: 100.58 | J15: 114.95 | K15: 114.95 | L15: 128.14 | M15: 149.5 | N15: 142.74 | O15: 178.42 | P15: 214.11 | Q15: 249.03 | R15: 282.23 | S15: 332.05 | T15: 415.05 | U15: 52.71 | V15: 76.5 | W15: 87.4 | X15: 94 | Y15: 103.6 | Z15: 113.9 | AA15: 124.16 | AB15: 144.41 | AC15: 161.81 | AD15: 197.37 | AE15: 215.7 | AF15: 143.51 | AG15: 304.65 | AH15: =(U15+AH$4*(Resumo!$C$7+Resumo!$C$8)+Resumo!$C$10*CEILING(AH$3/100,1)+Resumo!$C$9)*(1+Resumo!$C$11)-(AH$4*(Resumo!$B$6+Resumo!$B$7)+Resumo!$B$9+Resumo!$B$10*CEILING(AH$3/100,1)+(Resumo!$B$12+Resumo!$B$13)*CEILING(AH$3,1)) -> 54.922735 | AI15: =(V15+AI$4*(Resumo!$C$7+Resumo!$C$8)+Resumo!$C$10*CEILING(AI$3/100,1)+Resumo!$C$9)*(1+Resumo!$C$11)-(AI$4*(Resumo!$B$6+Resumo!$B$7)+Resumo!$B$9+Resumo!$B$10*CEILING(AI$3/100,1)+(Resumo!$B$12+Resumo!$B$13)*CEILING(AI$3,1)) -> 74.557046 | AJ15: =(W15+AJ$4*(Resumo!$C$7+Resumo!$C$8)+Resumo!$C$10*CEILING(AJ$3/100,1)+Resumo!$C$9)*(1+Resumo!$C$11)-(AJ$4*(Resumo!$B$6+Resumo!$B$7)+Resumo!$B$9+Resumo!$B$10*CEILING(AJ$3/100,1)+(Resumo!$B$12+Resumo!$B$13)*CEILING(AJ$3,1)) -> 81.503935 | AK15: =(X15+AK$4*(Resumo!$C$7+Resumo!$C$8)+Resumo!$C$10*CEILING(AK$3/100,1)+Resumo!$C$9)*(1+Resumo!$C$11)-(AK$4*(Resumo!$B$6+Resumo!$B$7)+Resumo!$B$9+Resumo!$B$10*CEILING(AK$3/100,1)+(Resumo!$B$12+Resumo!$B$13)*CEILING(AK$3,1)) -> 84.555258 | AL15: =(Y15+AL$4*(Resumo!$C$7+Resumo!$C$8)+Resumo!$C$10*CEILING(AL$3/100,1)+Resumo!$C$9)*(1+Resumo!$C$11)-(AL$4*(Resumo!$B$6+Resumo!$B$7)+Resumo!$B$9+Resumo!$B$10*CEILING(AL$3/100,1)+(Resumo!$B$12+Resumo!$B$13)*CEILING(AL$3,1)) -> 90.71477 | AM15: =(Z15+AM$4*(Resumo!$C$7+Resumo!$C$8)+Resumo!$C$10*CEILING(AM$3/100,1)+Resumo!$C$9)*(1+Resumo!$C$11)-(AM$4*(Resumo!$B$6+Resumo!$B$7)+Resumo!$B$9+Resumo!$B$10*CEILING(AM$3/100,1)+(Resumo!$B$12+Resumo!$B$13)*CEILING(AM$3,1)) -> 95.03042 | AN15: =(AA15+AN$4*(Resumo!$C$7+Resumo!$C$8)+Resumo!$C$10*CEILING(AN$3/100,1)+Resumo!$C$9)*(1+Resumo!$C$11)-(AN$4*(Resumo!$B$6+Resumo!$B$7)+Resumo!$B$9+Resumo!$B$10*CEILING(AN$3/100,1)+(Resumo!$B$12+Resumo!$B$13)*CEILING(AN$3,1)) -> 102.0096 | AO15: =(AB15+AO$4*(Resumo!$C$7+Resumo!$C$8)+Resumo!$C$10*CEILING(AO$3/100,1)+Resumo!$C$9)*(1+Resumo!$C$11)-(AO$4*(Resumo!$B$6+Resumo!$B$7)+Resumo!$B$9+Resumo!$B$10*CEILING(AO$3/100,1)+(Resumo!$B$12+Resumo!$B$13)*CEILING(AO$3,1)) -> 116.7659 | ... AT15: =(AG15+AT$4*(Resumo!$C$7+Resumo!$C$8)+Resumo!$C$10*CEILING(AT$3/100,1)+Resumo!$C$9)*(1+Resumo!$C$11)-(AT$4*(Resumo!$B$6+Resumo!$B$7)+Resumo!$B$9+Resumo!$B$10*CEILING(AT$3/100,1)+(Resumo!$B$12+Resumo!$B$13)*CEILING(AT$3,1)) -> 219.78099 | AU15: =1-AH15/H15 -> 0.044323381 | AV15: =1-AI15/I15 -> 0.25872891 | AW15: =1-AJ15/J15 -> 0.29096186 | AX15: =1-AK15/K15 -> 0.26441707 | AY15: =1-AL15/L15 -> 0.29206516 | AZ15: =1-AM15/M15 -> 0.36434502 | BA15: =1-AN15/N15 -> 0.28534681 | BB15: =1-AO15/O15 -> 0.34555601 | ... BG15: =1-AT15/T15 -> 0.47047106
A16: RJ | B16: Tanguá | C16: 24890000 | D16: 24899999 | E16: Interior | F16: 7 / 13 | G16: =COUNTIFS(Pedidos!$E$2:$E$2224,">="&C16,Pedidos!$E$2:$E$2224,"<="&D16) -> 0 | H16: 57.47 | I16: 100.58 | J16: 114.95 | K16: 114.95 | L16: 128.14 | M16: 149.5 | N16: 142.74 | O16: 178.42 | P16: 214.11 | Q16: 249.03 | R16: 282.23 | S16: 332.05 | T16: 415.05 | U16: 52.71 | V16: 76.5 | W16: 87.4 | X16: 94 | Y16: 103.6 | Z16: 113.9 | AA16: 124.16 | AB16: 144.41 | AC16: 161.81 | AD16: 197.37 | AE16: 215.7 | AF16: 143.51 | AG16: 304.65 | AH16: =(U16+AH$4*(Resumo!$C$7+Resumo!$C$8)+Resumo!$C$10*CEILING(AH$3/100,1)+Resumo!$C$9)*(1+Resumo!$C$11)-(AH$4*(Resumo!$B$6+Resumo!$B$7)+Resumo!$B$9+Resumo!$B$10*CEILING(AH$3/100,1)+(Resumo!$B$12+Resumo!$B$13)*CEILING(AH$3,1)) -> 54.922735 | AI16: =(V16+AI$4*(Resumo!$C$7+Resumo!$C$8)+Resumo!$C$10*CEILING(AI$3/100,1)+Resumo!$C$9)*(1+Resumo!$C$11)-(AI$4*(Resumo!$B$6+Resumo!$B$7)+Resumo!$B$9+Resumo!$B$10*CEILING(AI$3/100,1)+(Resumo!$B$12+Resumo!$B$13)*CEILING(AI$3,1)) -> 74.557046 | AJ16: =(W16+AJ$4*(Resumo!$C$7+Resumo!$C$8)+Resumo!$C$10*CEILING(AJ$3/100,1)+Resumo!$C$9)*(1+Resumo!$C$11)-(AJ$4*(Resumo!$B$6+Resumo!$B$7)+Resumo!$B$9+Resumo!$B$10*CEILING(AJ$3/100,1)+(Resumo!$B$12+Resumo!$B$13)*CEILING(AJ$3,1)) -> 81.503935 | AK16: =(X16+AK$4*(Resumo!$C$7+Resumo!$C$8)+Resumo!$C$10*CEILING(AK$3/100,1)+Resumo!$C$9)*(1+Resumo!$C$11)-(AK$4*(Resumo!$B$6+Resumo!$B$7)+Resumo!$B$9+Resumo!$B$10*CEILING(AK$3/100,1)+(Resumo!$B$12+Resumo!$B$13)*CEILING(AK$3,1)) -> 84.555258 | AL16: =(Y16+AL$4*(Resumo!$C$7+Resumo!$C$8)+Resumo!$C$10*CEILING(AL$3/100,1)+Resumo!$C$9)*(1+Resumo!$C$11)-(AL$4*(Resumo!$B$6+Resumo!$B$7)+Resumo!$B$9+Resumo!$B$10*CEILING(AL$3/100,1)+(Resumo!$B$12+Resumo!$B$13)*CEILING(AL$3,1)) -> 90.71477 | AM16: =(Z16+AM$4*(Resumo!$C$7+Resumo!$C$8)+Resumo!$C$10*CEILING(AM$3/100,1)+Resumo!$C$9)*(1+Resumo!$C$11)-(AM$4*(Resumo!$B$6+Resumo!$B$7)+Resumo!$B$9+Resumo!$B$10*CEILING(AM$3/100,1)+(Resumo!$B$12+Resumo!$B$13)*CEILING(AM$3,1)) -> 95.03042 | AN16: =(AA16+AN$4*(Resumo!$C$7+Resumo!$C$8)+Resumo!$C$10*CEILING(AN$3/100,1)+Resumo!$C$9)*(1+Resumo!$C$11)-(AN$4*(Resumo!$B$6+Resumo!$B$7)+Resumo!$B$9+Resumo!$B$10*CEILING(AN$3/100,1)+(Resumo!$B$12+Resumo!$B$13)*CEILING(AN$3,1)) -> 102.0096 | AO16: =(AB16+AO$4*(Resumo!$C$7+Resumo!$C$8)+Resumo!$C$10*CEILING(AO$3/100,1)+Resumo!$C$9)*(1+Resumo!$C$11)-(AO$4*(Resumo!$B$6+Resumo!$B$7)+Resumo!$B$9+Resumo!$B$10*CEILING(AO$3/100,1)+(Resumo!$B$12+Resumo!$B$13)*CEILING(AO$3,1)) -> 116.7659 | ... AT16: =(AG16+AT$4*(Resumo!$C$7+Resumo!$C$8)+Resumo!$C$10*CEILING(AT$3/100,1)+Resumo!$C$9)*(1+Resumo!$C$11)-(AT$4*(Resumo!$B$6+Resumo!$B$7)+Resumo!$B$9+Resumo!$B$10*CEILING(AT$3/100,1)+(Resumo!$B$12+Resumo!$B$13)*CEILING(AT$3,1)) -> 219.78099 | AU16: =1-AH16/H16 -> 0.044323381 | AV16: =1-AI16/I16 -> 0.25872891 | AW16: =1-AJ16/J16 -> 0.29096186 | AX16: =1-AK16/K16 -> 0.26441707 | AY16: =1-AL16/L16 -> 0.29206516 | AZ16: =1-AM16/M16 -> 0.36434502 | BA16: =1-AN16/N16 -> 0.28534681 | BB16: =1-AO16/O16 -> 0.34555601 | ... BG16: =1-AT16/T16 -> 0.47047106
A17: RJ | B17: Maricá | C17: 24900000 | D17: 24999999 | E17: Interior | F17: 7 / 13 | G17: =COUNTIFS(Pedidos!$E$2:$E$2224,">="&C17,Pedidos!$E$2:$E$2224,"<="&D17) -> 32 | H17: 57.47 | I17: 100.58 | J17: 114.95 | K17: 114.95 | L17: 128.14 | M17: 149.5 | N17: 142.74 | O17: 178.42 | P17: 214.11 | Q17: 249.03 | R17: 282.23 | S17: 332.05 | T17: 415.05 | U17: 52.71 | V17: 76.5 | W17: 87.4 | X17: 94 | Y17: 103.6 | Z17: 113.9 | AA17: 124.16 | AB17: 144.41 | AC17: 161.81 | AD17: 197.37 | AE17: 215.7 | AF17: 143.51 | AG17: 304.65 | AH17: =(U17+AH$4*(Resumo!$C$7+Resumo!$C$8)+Resumo!$C$10*CEILING(AH$3/100,1)+Resumo!$C$9)*(1+Resumo!$C$11)-(AH$4*(Resumo!$B$6+Resumo!$B$7)+Resumo!$B$9+Resumo!$B$10*CEILING(AH$3/100,1)+(Resumo!$B$12+Resumo!$B$13)*CEILING(AH$3,1)) -> 54.922735 | AI17: =(V17+AI$4*(Resumo!$C$7+Resumo!$C$8)+Resumo!$C$10*CEILING(AI$3/100,1)+Resumo!$C$9)*(1+Resumo!$C$11)-(AI$4*(Resumo!$B$6+Resumo!$B$7)+Resumo!$B$9+Resumo!$B$10*CEILING(AI$3/100,1)+(Resumo!$B$12+Resumo!$B$13)*CEILING(AI$3,1)) -> 74.557046 | AJ17: =(W17+AJ$4*(Resumo!$C$7+Resumo!$C$8)+Resumo!$C$10*CEILING(AJ$3/100,1)+Resumo!$C$9)*(1+Resumo!$C$11)-(AJ$4*(Resumo!$B$6+Resumo!$B$7)+Resumo!$B$9+Resumo!$B$10*CEILING(AJ$3/100,1)+(Resumo!$B$12+Resumo!$B$13)*CEILING(AJ$3,1)) -> 81.503935 | AK17: =(X17+AK$4*(Resumo!$C$7+Resumo!$C$8)+Resumo!$C$10*CEILING(AK$3/100,1)+Resumo!$C$9)*(1+Resumo!$C$11)-(AK$4*(Resumo!$B$6+Resumo!$B$7)+Resumo!$B$9+Resumo!$B$10*CEILING(AK$3/100,1)+(Resumo!$B$12+Resumo!$B$13)*CEILING(AK$3,1)) -> 84.555258 | AL17: =(Y17+AL$4*(Resumo!$C$7+Resumo!$C$8)+Resumo!$C$10*CEILING(AL$3/100,1)+Resumo!$C$9)*(1+Resumo!$C$11)-(AL$4*(Resumo!$B$6+Resumo!$B$7)+Resumo!$B$9+Resumo!$B$10*CEILING(AL$3/100,1)+(Resumo!$B$12+Resumo!$B$13)*CEILING(AL$3,1)) -> 90.71477 | AM17: =(Z17+AM$4*(Resumo!$C$7+Resumo!$C$8)+Resumo!$C$10*CEILING(AM$3/100,1)+Resumo!$C$9)*(1+Resumo!$C$11)-(AM$4*(Resumo!$B$6+Resumo!$B$7)+Resumo!$B$9+Resumo!$B$10*CEILING(AM$3/100,1)+(Resumo!$B$12+Resumo!$B$13)*CEILING(AM$3,1)) -> 95.03042 | AN17: =(AA17+AN$4*(Resumo!$C$7+Resumo!$C$8)+Resumo!$C$10*CEILING(AN$3/100,1)+Resumo!$C$9)*(1+Resumo!$C$11)-(AN$4*(Resumo!$B$6+Resumo!$B$7)+Resumo!$B$9+Resumo!$B$10*CEILING(AN$3/100,1)+(Resumo!$B$12+Resumo!$B$13)*CEILING(AN$3,1)) -> 102.0096 | AO17: =(AB17+AO$4*(Resumo!$C$7+Resumo!$C$8)+Resumo!$C$10*CEILING(AO$3/100,1)+Resumo!$C$9)*(1+Resumo!$C$11)-(AO$4*(Resumo!$B$6+Resumo!$B$7)+Resumo!$B$9+Resumo!$B$10*CEILING(AO$3/100,1)+(Resumo!$B$12+Resumo!$B$13)*CEILING(AO$3,1)) -> 116.7659 | ... AT17: =(AG17+AT$4*(Resumo!$C$7+Resumo!$C$8)+Resumo!$C$10*CEILING(AT$3/100,1)+Resumo!$C$9)*(1+Resumo!$C$11)-(AT$4*(Resumo!$B$6+Resumo!$B$7)+Resumo!$B$9+Resumo!$B$10*CEILING(AT$3/100,1)+(Resumo!$B$12+Resumo!$B$13)*CEILING(AT$3,1)) -> 219.78099 | AU17: =1-AH17/H17 -> 0.044323381 | AV17: =1-AI17/I17 -> 0.25872891 | AW17: =1-AJ17/J17 -> 0.29096186 | AX17: =1-AK17/K17 -> 0.26441707 | AY17: =1-AL17/L17 -> 0.29206516 | AZ17: =1-AM17/M17 -> 0.36434502 | BA17: =1-AN17/N17 -> 0.28534681 | BB17: =1-AO17/O17 -> 0.34555601 | ... BG17: =1-AT17/T17 -> 0.47047106
A18: RJ | B18: Duque de Caxias | C18: 25000000 | D18: 25499999 | E18: Metropolitana | F18: 5 / 10 | G18: =COUNTIFS(Pedidos!$E$2:$E$2224,">="&C18,Pedidos!$E$2:$E$2224,"<="&D18) -> 106 | H18: 46.98 | I18: 82.21 | J18: 93.97 | K18: 93.97 | L18: 112.3 | M18: 131.02 | N18: 134.39 | O18: 167.99 | P18: 201.59 | Q18: 239.25 | R18: 271.15 | S18: 319 | T18: 398.74 | U18: 48.69 | V18: 70 | W18: 79.65 | X18: 82.25 | Y18: 91.6 | Z18: 100.9 | AA18: 110.55 | AB18: 127.92 | AC18: 144.44 | AD18: 183.45 | AE18: 201.15 | AF18: 227.7 | AG18: 285.09 | AH18: =(U18+AH$4*(Resumo!$C$7+Resumo!$C$8)+Resumo!$C$10*CEILING(AH$3/100,1)+Resumo!$C$9)*(1+Resumo!$C$11)-(AH$4*(Resumo!$B$6+Resumo!$B$7)+Resumo!$B$9+Resumo!$B$10*CEILING(AH$3/100,1)+(Resumo!$B$12+Resumo!$B$13)*CEILING(AH$3,1)) -> 50.681635 | AI18: =(V18+AI$4*(Resumo!$C$7+Resumo!$C$8)+Resumo!$C$10*CEILING(AI$3/100,1)+Resumo!$C$9)*(1+Resumo!$C$11)-(AI$4*(Resumo!$B$6+Resumo!$B$7)+Resumo!$B$9+Resumo!$B$10*CEILING(AI$3/100,1)+(Resumo!$B$12+Resumo!$B$13)*CEILING(AI$3,1)) -> 67.699546 | AJ18: =(W18+AJ$4*(Resumo!$C$7+Resumo!$C$8)+Resumo!$C$10*CEILING(AJ$3/100,1)+Resumo!$C$9)*(1+Resumo!$C$11)-(AJ$4*(Resumo!$B$6+Resumo!$B$7)+Resumo!$B$9+Resumo!$B$10*CEILING(AJ$3/100,1)+(Resumo!$B$12+Resumo!$B$13)*CEILING(AJ$3,1)) -> 73.327685 | AK18: =(X18+AK$4*(Resumo!$C$7+Resumo!$C$8)+Resumo!$C$10*CEILING(AK$3/100,1)+Resumo!$C$9)*(1+Resumo!$C$11)-(AK$4*(Resumo!$B$6+Resumo!$B$7)+Resumo!$B$9+Resumo!$B$10*CEILING(AK$3/100,1)+(Resumo!$B$12+Resumo!$B$13)*CEILING(AK$3,1)) -> 72.159008 | AL18: =(Y18+AL$4*(Resumo!$C$7+Resumo!$C$8)+Resumo!$C$10*CEILING(AL$3/100,1)+Resumo!$C$9)*(1+Resumo!$C$11)-(AL$4*(Resumo!$B$6+Resumo!$B$7)+Resumo!$B$9+Resumo!$B$10*CEILING(AL$3/100,1)+(Resumo!$B$12+Resumo!$B$13)*CEILING(AL$3,1)) -> 78.05477 | AM18: =(Z18+AM$4*(Resumo!$C$7+Resumo!$C$8)+Resumo!$C$10*CEILING(AM$3/100,1)+Resumo!$C$9)*(1+Resumo!$C$11)-(AM$4*(Resumo!$B$6+Resumo!$B$7)+Resumo!$B$9+Resumo!$B$10*CEILING(AM$3/100,1)+(Resumo!$B$12+Resumo!$B$13)*CEILING(AM$3,1)) -> 81.31542 | AN18: =(AA18+AN$4*(Resumo!$C$7+Resumo!$C$8)+Resumo!$C$10*CEILING(AN$3/100,1)+Resumo!$C$9)*(1+Resumo!$C$11)-(AN$4*(Resumo!$B$6+Resumo!$B$7)+Resumo!$B$9+Resumo!$B$10*CEILING(AN$3/100,1)+(Resumo!$B$12+Resumo!$B$13)*CEILING(AN$3,1)) -> 87.651046 | AO18: =(AB18+AO$4*(Resumo!$C$7+Resumo!$C$8)+Resumo!$C$10*CEILING(AO$3/100,1)+Resumo!$C$9)*(1+Resumo!$C$11)-(AO$4*(Resumo!$B$6+Resumo!$B$7)+Resumo!$B$9+Resumo!$B$10*CEILING(AO$3/100,1)+(Resumo!$B$12+Resumo!$B$13)*CEILING(AO$3,1)) -> 99.368947 | ... AT18: =(AG18+AT$4*(Resumo!$C$7+Resumo!$C$8)+Resumo!$C$10*CEILING(AT$3/100,1)+Resumo!$C$9)*(1+Resumo!$C$11)-(AT$4*(Resumo!$B$6+Resumo!$B$7)+Resumo!$B$9+Resumo!$B$10*CEILING(AT$3/100,1)+(Resumo!$B$12+Resumo!$B$13)*CEILING(AT$3,1)) -> 199.14519 | AU18: =1-AH18/H18 -> -0.078791726 | AV18: =1-AI18/I18 -> 0.17650473 | AW18: =1-AJ18/J18 -> 0.21966921 | AX18: =1-AK18/K18 -> 0.23210591 | AY18: =1-AL18/L18 -> 0.30494417 | AZ18: =1-AM18/M18 -> 0.37936636 | BA18: =1-AN18/N18 -> 0.34778595 | BB18: =1-AO18/O18 -> 0.40848296 | ... BG18: =1-AT18/T18 -> 0.50056381
... A99: RJ | B99: Saquarema | C99: 28990000 | D99: 28999999 | E99: Interior | F99: 10 / 13 | G99: =COUNTIFS(Pedidos!$E$2:$E$2224,">="&C99,Pedidos!$E$2:$E$2224,"<="&D99) -> 15 | H99: 100.7 | I99: 114.95 | J99: 124.38 | K99: 129.29 | L99: 142.32 | M99: 166.05 | N99: 166.05 | O99: 197.35 | P99: 236.82 | Q99: 264.84 | R99: 300.15 | S99: 353.12 | T99: 441.4 | U99: 52.71 | V99: 76.5 | W99: 87.4 | X99: 94 | Y99: 103.6 | Z99: 113.9 | AA99: 124.16 | AB99: 144.41 | AC99: 161.81 | AD99: 197.37 | AE99: 215.7 | AF99: 143.51 | AG99: 304.65 | AH99: =(U99+AH$4*(Resumo!$C$7+Resumo!$C$8)+Resumo!$C$10*CEILING(AH$3/100,1)+Resumo!$C$9)*(1+Resumo!$C$11)-(AH$4*(Resumo!$B$6+Resumo!$B$7)+Resumo!$B$9+Resumo!$B$10*CEILING(AH$3/100,1)+(Resumo!$B$12+Resumo!$B$13)*CEILING(AH$3,1)) -> 54.922735 | AI99: =(V99+AI$4*(Resumo!$C$7+Resumo!$C$8)+Resumo!$C$10*CEILING(AI$3/100,1)+Resumo!$C$9)*(1+Resumo!$C$11)-(AI$4*(Resumo!$B$6+Resumo!$B$7)+Resumo!$B$9+Resumo!$B$10*CEILING(AI$3/100,1)+(Resumo!$B$12+Resumo!$B$13)*CEILING(AI$3,1)) -> 74.557046 | AJ99: =(W99+AJ$4*(Resumo!$C$7+Resumo!$C$8)+Resumo!$C$10*CEILING(AJ$3/100,1)+Resumo!$C$9)*(1+Resumo!$C$11)-(AJ$4*(Resumo!$B$6+Resumo!$B$7)+Resumo!$B$9+Resumo!$B$10*CEILING(AJ$3/100,1)+(Resumo!$B$12+Resumo!$B$13)*CEILING(AJ$3,1)) -> 81.503935 | AK99: =(X99+AK$4*(Resumo!$C$7+Resumo!$C$8)+Resumo!$C$10*CEILING(AK$3/100,1)+Resumo!$C$9)*(1+Resumo!$C$11)-(AK$4*(Resumo!$B$6+Resumo!$B$7)+Resumo!$B$9+Resumo!$B$10*CEILING(AK$3/100,1)+(Resumo!$B$12+Resumo!$B$13)*CEILING(AK$3,1)) -> 84.555258 | AL99: =(Y99+AL$4*(Resumo!$C$7+Resumo!$C$8)+Resumo!$C$10*CEILING(AL$3/100,1)+Resumo!$C$9)*(1+Resumo!$C$11)-(AL$4*(Resumo!$B$6+Resumo!$B$7)+Resumo!$B$9+Resumo!$B$10*CEILING(AL$3/100,1)+(Resumo!$B$12+Resumo!$B$13)*CEILING(AL$3,1)) -> 90.71477 | AM99: =(Z99+AM$4*(Resumo!$C$7+Resumo!$C$8)+Resumo!$C$10*CEILING(AM$3/100,1)+Resumo!$C$9)*(1+Resumo!$C$11)-(AM$4*(Resumo!$B$6+Resumo!$B$7)+Resumo!$B$9+Resumo!$B$10*CEILING(AM$3/100,1)+(Resumo!$B$12+Resumo!$B$13)*CEILING(AM$3,1)) -> 95.03042 | AN99: =(AA99+AN$4*(Resumo!$C$7+Resumo!$C$8)+Resumo!$C$10*CEILING(AN$3/100,1)+Resumo!$C$9)*(1+Resumo!$C$11)-(AN$4*(Resumo!$B$6+Resumo!$B$7)+Resumo!$B$9+Resumo!$B$10*CEILING(AN$3/100,1)+(Resumo!$B$12+Resumo!$B$13)*CEILING(AN$3,1)) -> 102.0096 | AO99: =(AB99+AO$4*(Resumo!$C$7+Resumo!$C$8)+Resumo!$C$10*CEILING(AO$3/100,1)+Resumo!$C$9)*(1+Resumo!$C$11)-(AO$4*(Resumo!$B$6+Resumo!$B$7)+Resumo!$B$9+Resumo!$B$10*CEILING(AO$3/100,1)+(Resumo!$B$12+Resumo!$B$13)*CEILING(AO$3,1)) -> 116.7659 | ... AT99: =(AG99+AT$4*(Resumo!$C$7+Resumo!$C$8)+Resumo!$C$10*CEILING(AT$3/100,1)+Resumo!$C$9)*(1+Resumo!$C$11)-(AT$4*(Resumo!$B$6+Resumo!$B$7)+Resumo!$B$9+Resumo!$B$10*CEILING(AT$3/100,1)+(Resumo!$B$12+Resumo!$B$13)*CEILING(AT$3,1)) -> 219.78099 | AU99: =1-AH99/H99 -> 0.45459051 | AV99: =1-AI99/I99 -> 0.35139586 | AW99: =1-AJ99/J99 -> 0.34471833 | AX99: =1-AK99/K99 -> 0.34600311 | AY99: =1-AL99/L99 -> 0.36259999 | AZ99: =1-AM99/M99 -> 0.42769997 | BA99: =1-AN99/N99 -> 0.3856694 | BB99: =1-AO99/O99 -> 0.4083309 | ... BG99: =1-AT99/T99 -> 0.50208204
B101: Redução negativa = a PROLOG já está abaixo do empate nessa faixa/cidade (tem margem).
B102: Se a taxa interna R$ 0,45/kg também for aplicada à TSL (custo comum da filial SP), basta alterar Resumo!C13 para 0,45 — o alvo e todas as abas recalculam.

Sheet Frete Peso Top 20
A1: Frete peso por faixa (valor de tabela, antes de taxas e ICMS) — PROLOG x TSL nas top 20 cidades
A2: Bloco 3 = quanto a PROLOG está acima (+) ou abaixo (−) da TSL apenas no frete peso.
A4: 1) PROLOG — frete peso (R$)
A5: Cidade | B5: Região TSL | C5: 0-20 | D5: 20-35 | E5: 35-40 | F5: 40-50 | G5: 50-60 | H5: 60-70 | I5: 70-80 | J5: 80-100 | K5: 100-120 | L5: 120-150 | M5: 150-170 | N5: 170-200 | O5: 200-250
A6: Rio de Janeiro | B6: Capital | C6: 46.98 | D6: 82.21 | E6: 93.97 | F6: 93.97 | G6: 112.3 | H6: 131.02 | I6: 134.39 | J6: 167.99 | K6: 201.59 | L6: 239.25 | M6: 271.15 | N6: 319 | O6: 398.74
A7: São Gonçalo | B7: Metropolitana | C7: 57.47 | D7: 100.58 | E7: 114.95 | F7: 114.95 | G7: 128.14 | H7: 149.5 | I7: 142.74 | J7: 178.42 | K7: 214.11 | L7: 249.03 | M7: 282.23 | N7: 332.05 | O7: 415.05
A8: Duque de Caxias | B8: Metropolitana | C8: 46.98 | D8: 82.21 | E8: 93.97 | F8: 93.97 | G8: 112.3 | H8: 131.02 | I8: 134.39 | J8: 167.99 | K8: 201.59 | L8: 239.25 | M8: 271.15 | N8: 319 | O8: 398.74
A9: Nova Iguaçu | B9: Metropolitana | C9: 46.98 | D9: 82.21 | E9: 93.97 | F9: 93.97 | G9: 112.3 | H9: 131.02 | I9: 134.39 | J9: 167.99 | K9: 201.59 | L9: 239.25 | M9: 271.15 | N9: 319 | O9: 398.74
A10: Niterói | B10: Metropolitana | C10: 57.47 | D10: 100.58 | E10: 114.95 | F10: 114.95 | G10: 128.14 | H10: 149.5 | I10: 142.74 | J10: 178.42 | K10: 214.11 | L10: 249.03 | M10: 282.23 | N10: 332.05 | O10: 415.05
A11: Campos dos Goytacazes | B11: Interior | C11: 124.04 | D11: 138.29 | E11: 143.04 | F11: 152.54 | G11: 162.04 | H11: 171.54 | I11: 181.04 | J11: 200.04 | K11: 236.82 | L11: 264.84 | M11: 300.15 | N11: 353.17 | O11: 441.4
A12: Belford Roxo | B12: Metropolitana | C12: 46.98 | D12: 82.21 | E12: 93.97 | F12: 93.97 | G12: 112.3 | H12: 131.02 | I12: 134.39 | J12: 167.99 | K12: 201.59 | L12: 239.25 | M12: 271.15 | N12: 319 | O12: 398.74
A13: Macaé | B13: Interior | C13: 124.04 | D13: 138.29 | E13: 143.04 | F13: 152.54 | G13: 162.04 | H13: 171.54 | I13: 181.04 | J13: 200.04 | K13: 236.82 | L13: 264.84 | M13: 300.15 | N13: 353.17 | O13: 441.4
A14: São João de Meriti | B14: Metropolitana | C14: 46.98 | D14: 82.21 | E14: 93.97 | F14: 93.97 | G14: 112.3 | H14: 131.02 | I14: 134.39 | J14: 167.99 | K14: 201.59 | L14: 239.25 | M14: 271.15 | N14: 319 | O14: 398.74
A15: Volta Redonda | B15: Interior | C15: 77.35 | D15: 108.83 | E15: 124.38 | F15: 124.38 | G15: 142.32 | H15: 166.05 | I15: 157.88 | J15: 197.35 | K15: 236.82 | L15: 264.84 | M15: 300.15 | N15: 353.12 | O15: 441.4
A16: Angra dos Reis | B16: Interior | C16: 77.35 | D16: 108.83 | E16: 124.38 | F16: 124.38 | G16: 142.32 | H16: 166.05 | I16: 157.88 | J16: 197.35 | K16: 236.82 | L16: 264.84 | M16: 300.15 | N16: 353.12 | O16: 441.4
A17: Petrópolis | B17: Interior | C17: 89.03 | D17: 108.83 | E17: 124.38 | F17: 124.38 | G17: 142.32 | H17: 166.05 | I17: 166.05 | J17: 197.35 | K17: 236.82 | L17: 264.84 | M17: 300.15 | N17: 353.12 | O17: 441.4
... A25: Rio das Ostras | B25: Interior | C25: 100.7 | D25: 114.95 | E25: 124.38 | F25: 129.29 | G25: 142.32 | H25: 166.05 | I25: 166.05 | J25: 197.35 | K25: 236.82 | L25: 264.84 | M25: 300.15 | N25: 353.12 | O25: 441.4
A27: 2) TSL — frete peso (R$)
A28: Cidade | B28: Região TSL | C28: 0-20 | D28: 20-35 | E28: 35-40 | F28: 40-50 | G28: 50-60 | H28: 60-70 | I28: 70-80 | J28: 80-100 | K28: 100-120 | L28: 120-150 | M28: 150-170 | N28: 170-200 | O28: 200-250
A29: Rio de Janeiro | B29: Capital | C29: 39.83 | D29: 54.1 | E29: 62.05 | F29: 71 | G29: 79.81 | H29: 88.2 | I29: 97.6 | J29: 119.8 | K29: 135.94 | L29: 174.85 | M29: 192.1 | N29: 218 | O29: 272.9
A30: São Gonçalo | B30: Metropolitana | C30: 48.69 | D30: 70 | E30: 79.65 | F30: 82.25 | G30: 91.6 | H30: 100.9 | I30: 110.55 | J30: 127.92 | K30: 144.44 | L30: 183.45 | M30: 201.15 | N30: 227.7 | O30: 285.09
A31: Duque de Caxias | B31: Metropolitana | C31: 48.69 | D31: 70 | E31: 79.65 | F31: 82.25 | G31: 91.6 | H31: 100.9 | I31: 110.55 | J31: 127.92 | K31: 144.44 | L31: 183.45 | M31: 201.15 | N31: 227.7 | O31: 285.09
A32: Nova Iguaçu | B32: Metropolitana | C32: 48.69 | D32: 70 | E32: 79.65 | F32: 82.25 | G32: 91.6 | H32: 100.9 | I32: 110.55 | J32: 127.92 | K32: 144.44 | L32: 183.45 | M32: 201.15 | N32: 227.7 | O32: 285.09
A33: Niterói | B33: Metropolitana | C33: 48.69 | D33: 70 | E33: 79.65 | F33: 82.25 | G33: 91.6 | H33: 100.9 | I33: 110.55 | J33: 127.92 | K33: 144.44 | L33: 183.45 | M33: 201.15 | N33: 227.7 | O33: 285.09
A34: Campos dos Goytacazes | B34: Interior | C34: 52.71 | D34: 76.5 | E34: 87.4 | F34: 94 | G34: 103.6 | H34: 113.9 | I34: 124.16 | J34: 144.41 | K34: 161.81 | L34: 197.37 | M34: 215.7 | N34: 143.51 | O34: 304.65
A35: Belford Roxo | B35: Metropolitana | C35: 48.69 | D35: 70 | E35: 79.65 | F35: 82.25 | G35: 91.6 | H35: 100.9 | I35: 110.55 | J35: 127.92 | K35: 144.44 | L35: 183.45 | M35: 201.15 | N35: 227.7 | O35: 285.09
A36: Macaé | B36: Interior | C36: 52.71 | D36: 76.5 | E36: 87.4 | F36: 94 | G36: 103.6 | H36: 113.9 | I36: 124.16 | J36: 144.41 | K36: 161.81 | L36: 197.37 | M36: 215.7 | N36: 143.51 | O36: 304.65
A37: São João de Meriti | B37: Metropolitana | C37: 48.69 | D37: 70 | E37: 79.65 | F37: 82.25 | G37: 91.6 | H37: 100.9 | I37: 110.55 | J37: 127.92 | K37: 144.44 | L37: 183.45 | M37: 201.15 | N37: 227.7 | O37: 285.09
A38: Volta Redonda | B38: Interior | C38: 52.71 | D38: 76.5 | E38: 87.4 | F38: 94 | G38: 103.6 | H38: 113.9 | I38: 124.16 | J38: 144.41 | K38: 161.81 | L38: 197.37 | M38: 215.7 | N38: 143.51 | O38: 304.65
A39: Angra dos Reis | B39: Interior | C39: 52.71 | D39: 76.5 | E39: 87.4 | F39: 94 | G39: 103.6 | H39: 113.9 | I39: 124.16 | J39: 144.41 | K39: 161.81 | L39: 197.37 | M39: 215.7 | N39: 143.51 | O39: 304.65
A40: Petrópolis | B40: Interior | C40: 52.71 | D40: 76.5 | E40: 87.4 | F40: 94 | G40: 103.6 | H40: 113.9 | I40: 124.16 | J40: 144.41 | K40: 161.81 | L40: 197.37 | M40: 215.7 | N40: 143.51 | O40: 304.65
... A48: Rio das Ostras | B48: Interior | C48: 52.71 | D48: 76.5 | E48: 87.4 | F48: 94 | G48: 103.6 | H48: 113.9 | I48: 124.16 | J48: 144.41 | K48: 161.81 | L48: 197.37 | M48: 215.7 | N48: 143.51 | O48: 304.65
A50: 3) PROLOG vs TSL (%)
A51: Cidade | B51: Região TSL | C51: 0-20 | D51: 20-35 | E51: 35-40 | F51: 40-50 | G51: 50-60 | H51: 60-70 | I51: 70-80 | J51: 80-100 | K51: 100-120 | L51: 120-150 | M51: 150-170 | N51: 170-200 | O51: 200-250
A52: Rio de Janeiro | B52: Capital | C52: =C6/C29-1 -> 0.17951293 | D52: =D6/D29-1 -> 0.51959335 | E52: =E6/E29-1 -> 0.51442385 | F52: =F6/F29-1 -> 0.32352113 | G52: =G6/G29-1 -> 0.40709184 | H52: =H6/H29-1 -> 0.48548753 | I52: =I6/I29-1 -> 0.37694672 | J52: =J6/J29-1 -> 0.40225376 | ... O52: =O6/O29-1 -> 0.46112129
A53: São Gonçalo | B53: Metropolitana | C53: =C7/C30-1 -> 0.1803245 | D53: =D7/D30-1 -> 0.43685714 | E53: =E7/E30-1 -> 0.44318895 | F53: =F7/F30-1 -> 0.39756839 | G53: =G7/G30-1 -> 0.3989083 | H53: =H7/H30-1 -> 0.48166501 | I53: =I7/I30-1 -> 0.29118046 | J53: =J7/J30-1 -> 0.39477799 | ... O53: =O7/O30-1 -> 0.45585605
A54: Duque de Caxias | B54: Metropolitana | C54: =C8/C31-1 -> -0.035120148 | D54: =D8/D31-1 -> 0.17442857 | E54: =E8/E31-1 -> 0.17978657 | F54: =F8/F31-1 -> 0.1424924 | G54: =G8/G31-1 -> 0.22598253 | H54: =H8/H31-1 -> 0.29851338 | I54: =I8/I31-1 -> 0.21564903 | J54: =J8/J31-1 -> 0.31324265 | ... O54: =O8/O31-1 -> 0.39864604
A55: Nova Iguaçu | B55: Metropolitana | C55: =C9/C32-1 -> -0.035120148 | D55: =D9/D32-1 -> 0.17442857 | E55: =E9/E32-1 -> 0.17978657 | F55: =F9/F32-1 -> 0.1424924 | G55: =G9/G32-1 -> 0.22598253 | H55: =H9/H32-1 -> 0.29851338 | I55: =I9/I32-1 -> 0.21564903 | J55: =J9/J32-1 -> 0.31324265 | ... O55: =O9/O32-1 -> 0.39864604
A56: Niterói | B56: Metropolitana | C56: =C10/C33-1 -> 0.1803245 | D56: =D10/D33-1 -> 0.43685714 | E56: =E10/E33-1 -> 0.44318895 | F56: =F10/F33-1 -> 0.39756839 | G56: =G10/G33-1 -> 0.3989083 | H56: =H10/H33-1 -> 0.48166501 | I56: =I10/I33-1 -> 0.29118046 | J56: =J10/J33-1 -> 0.39477799 | ... O56: =O10/O33-1 -> 0.45585605
A57: Campos dos Goytacazes | B57: Interior | C57: =C11/C34-1 -> 1.3532537 | D57: =D11/D34-1 -> 0.80771242 | E57: =E11/E34-1 -> 0.63661327 | F57: =F11/F34-1 -> 0.62276596 | G57: =G11/G34-1 -> 0.56409266 | H57: =H11/H34-1 -> 0.50605795 | I57: =I11/I34-1 -> 0.45811856 | J57: =J11/J34-1 -> 0.38522263 | ... O57: =O11/O34-1 -> 0.44887576
A58: Belford Roxo | B58: Metropolitana | C58: =C12/C35-1 -> -0.035120148 | D58: =D12/D35-1 -> 0.17442857 | E58: =E12/E35-1 -> 0.17978657 | F58: =F12/F35-1 -> 0.1424924 | G58: =G12/G35-1 -> 0.22598253 | H58: =H12/H35-1 -> 0.29851338 | I58: =I12/I35-1 -> 0.21564903 | J58: =J12/J35-1 -> 0.31324265 | ... O58: =O12/O35-1 -> 0.39864604
A59: Macaé | B59: Interior | C59: =C13/C36-1 -> 1.3532537 | D59: =D13/D36-1 -> 0.80771242 | E59: =E13/E36-1 -> 0.63661327 | F59: =F13/F36-1 -> 0.62276596 | G59: =G13/G36-1 -> 0.56409266 | H59: =H13/H36-1 -> 0.50605795 | I59: =I13/I36-1 -> 0.45811856 | J59: =J13/J36-1 -> 0.38522263 | ... O59: =O13/O36-1 -> 0.44887576
A60: São João de Meriti | B60: Metropolitana | C60: =C14/C37-1 -> -0.035120148 | D60: =D14/D37-1 -> 0.17442857 | E60: =E14/E37-1 -> 0.17978657 | F60: =F14/F37-1 -> 0.1424924 | G60: =G14/G37-1 -> 0.22598253 | H60: =H14/H37-1 -> 0.29851338 | I60: =I14/I37-1 -> 0.21564903 | J60: =J14/J37-1 -> 0.31324265 | ... O60: =O14/O37-1 -> 0.39864604
A61: Volta Redonda | B61: Interior | C61: =C15/C38-1 -> 0.46746348 | D61: =D15/D38-1 -> 0.42261438 | E61: =E15/E38-1 -> 0.42311213 | F61: =F15/F38-1 -> 0.32319149 | G61: =G15/G38-1 -> 0.37374517 | H61: =H15/H38-1 -> 0.45785777 | I61: =I15/I38-1 -> 0.27158505 | J61: =J15/J38-1 -> 0.36659511 | ... O61: =O15/O38-1 -> 0.44887576
A62: Angra dos Reis | B62: Interior | C62: =C16/C39-1 -> 0.46746348 | D62: =D16/D39-1 -> 0.42261438 | E62: =E16/E39-1 -> 0.42311213 | F62: =F16/F39-1 -> 0.32319149 | G62: =G16/G39-1 -> 0.37374517 | H62: =H16/H39-1 -> 0.45785777 | I62: =I16/I39-1 -> 0.27158505 | J62: =J16/J39-1 -> 0.36659511 | ... O62: =O16/O39-1 -> 0.44887576
A63: Petrópolis | B63: Interior | C63: =C17/C40-1 -> 0.68905331 | D63: =D17/D40-1 -> 0.42261438 | E63: =E17/E40-1 -> 0.42311213 | F63: =F17/F40-1 -> 0.32319149 | G63: =G17/G40-1 -> 0.37374517 | H63: =H17/H40-1 -> 0.45785777 | I63: =I17/I40-1 -> 0.33738724 | J63: =J17/J40-1 -> 0.36659511 | ... O63: =O17/O40-1 -> 0.44887576
... A71: Rio das Ostras | B71: Interior | C71: =C25/C48-1 -> 0.91045342 | D71: =D25/D48-1 -> 0.50261438 | E71: =E25/E48-1 -> 0.42311213 | F71: =F25/F48-1 -> 0.37542553 | G71: =G25/G48-1 -> 0.37374517 | H71: =H25/H48-1 -> 0.45785777 | I71: =I25/I48-1 -> 0.33738724 | J71: =J25/J48-1 -> 0.36659511 | ... O71: =O25/O48-1 -> 0.44887576

Sheet Pedidos
A1: Pedido HUB | B1: Data pagamento | C1: Canal | D1: CEP | E1: CEP (nº) | F1: Cidade | G1: Região TSL | H1: Faixa (kg) | I1: Peso (kg) | J1: Valor NF (R$) | K1: Transportadora cotada | L1: Custo real cotado (R$) | M1: TSL frete peso | N1: TSL GRIS | O1: TSL seguro | P1: TSL pedágio | Q1: TSL entrega | R1: TSL TRT | S1: TSL subtotal | T1: TSL total c/ ICMS | U1: PROLOG frete peso | V1: PROLOG ad valorem | W1: PROLOG GRIS | X1: PROLOG TAS | Y1: PROLOG pedágio | Z1: PROLOG CTe | AA1: PROLOG taxa interna | AB1: PROLOG subtotal | AC1: PROLOG total c/ ICMS | AD1: PROLOG s/ taxa interna c/ ICMS | AE1: Dif. PROLOG − TSL (R$) | AF1: Dif. % | AG1: PROLOG mais barata? | AH1: Prazo TSL (du) | AI1: Prazo PROLOG (du) | AJ1: Top 20?
A2: 352923342 | B2: 46204.421 | C2: Shopee | D2: 28913240 | E2: 28913240 | F2: Cabo Frio | G2: Interior | H2: 20-35 | I2: 33 | J2: 389.99 | K2: Tsl Filial Sp | L2: 109.05 | M2: 76.5 | N2: =J2*Resumo!$C$7 -> 0.77998 | O2: =J2*Resumo!$C$8 -> 0.77998 | P2: =Resumo!$C$10*CEILING(I2/100,1) -> 1 | Q2: =Resumo!$C$9 -> 11.9 | R2: =SUM(M2:Q2)*Resumo!$C$11 -> 5.0027978 | S2: =SUM(M2:R2) -> 95.962758 | T2: =S2/(1-Resumo!$C$5) -> 109.04859 | U2: 114.95 | V2: =J2*Resumo!$B$6 -> 0.38999 | W2: =J2*Resumo!$B$7 -> 0.77998 | X2: =Resumo!$B$9 -> 1 | Y2: =Resumo!$B$10*CEILING(I2/100,1) -> 4.5 | Z2: =Resumo!$B$12*CEILING(I2,1) -> 1.98 | AA2: =Resumo!$B$13*CEILING(I2,1) -> 14.85 | AB2: =SUM(U2:AA2) -> 138.44997 | AC2: =AB2/(1-Resumo!$B$5) -> 157.32951 | AD2: =(AB2-AA2)/(1-Resumo!$B$5) -> 140.45451 | AE2: =AC2-T2 -> 48.280923 | AF2: =AC2/T2-1 -> 0.44274689 | AG2: =IF(AC2<T2,"SIM","NÃO") -> NÃO | AH2: 13 | AI2: 10 | AJ2: SIM
A3: 352954180 | B3: 46204.475 | C3: Shopee | D3: 21032000 | E3: 21032000 | F3: Rio de Janeiro | G3: Capital | H3: 40-50 | I3: 49.6 | J3: 799.99 | K3: Tsl Filial Sp | L3: 104.42 | M3: 71 | N3: =J3*Resumo!$C$7 -> 1.59998 | O3: =J3*Resumo!$C$8 -> 1.59998 | P3: =Resumo!$C$10*CEILING(I3/100,1) -> 1 | Q3: =Resumo!$C$9 -> 11.9 | R3: =SUM(M3:Q3)*Resumo!$C$11 -> 4.7904978 | S3: =SUM(M3:R3) -> 91.890458 | T3: =S3/(1-Resumo!$C$5) -> 104.42097 | U3: 93.97 | V3: =J3*Resumo!$B$6 -> 0.79999 | W3: =J3*Resumo!$B$7 -> 1.59998 | X3: =Resumo!$B$9 -> 1 | Y3: =Resumo!$B$10*CEILING(I3/100,1) -> 4.5 | Z3: =Resumo!$B$12*CEILING(I3,1) -> 3 | AA3: =Resumo!$B$13*CEILING(I3,1) -> 22.5 | AB3: =SUM(U3:AA3) -> 127.36997 | AC3: =AB3/(1-Resumo!$B$5) -> 144.7386 | AD3: =(AB3-AA3)/(1-Resumo!$B$5) -> 119.17042 | AE3: =AC3-T3 -> 40.317628 | AF3: =AC3/T3-1 -> 0.3861066 | AG3: =IF(AC3<T3,"SIM","NÃO") -> NÃO | AH3: 8 | AI3: 5 | AJ3: SIM
A4: 353020070 | B4: 46204.587 | C4: Mercado Livre Principal | D4: 26545580 | E4: 26545580 | F4: Nilópolis | G4: Metropolitana | H4: 50-60 | I4: 58.5 | J4: 843.2 | K4: Tsl Filial Sp | L4: 129.33 | M4: 91.6 | N4: =J4*Resumo!$C$7 -> 1.6864 | O4: =J4*Resumo!$C$8 -> 1.6864 | P4: =Resumo!$C$10*CEILING(I4/100,1) -> 1 | Q4: =Resumo!$C$9 -> 11.9 | R4: =SUM(M4:Q4)*Resumo!$C$11 -> 5.933004 | S4: =SUM(M4:R4) -> 113.8058 | T4: =S4/(1-Resumo!$C$5) -> 129.32478 | U4: 112.3 | V4: =J4*Resumo!$B$6 -> 0.8432 | W4: =J4*Resumo!$B$7 -> 1.6864 | X4: =Resumo!$B$9 -> 1 | Y4: =Resumo!$B$10*CEILING(I4/100,1) -> 4.5 | Z4: =Resumo!$B$12*CEILING(I4,1) -> 3.54 | AA4: =Resumo!$B$13*CEILING(I4,1) -> 26.55 | AB4: =SUM(U4:AA4) -> 150.4196 | AC4: =AB4/(1-Resumo!$B$5) -> 170.93136 | AD4: =(AB4-AA4)/(1-Resumo!$B$5) -> 140.76091 | AE4: =AC4-T4 -> 41.606586 | AF4: =AC4/T4-1 -> 0.32172169 | AG4: =IF(AC4<T4,"SIM","NÃO") -> NÃO | AH4: 10 | AI4: 5 | AJ4: NÃO
A5: 353076911 | B5: 46204.69 | C5: Mercado Livre Principal | D5: 22471150 | E5: 22471150 | F5: Rio de Janeiro | G5: Capital | H5: 35-40 | I5: 35.4 | J5: 543.69 | K5: Tsl Filial Sp | L5: 92.47 | M5: 62.05 | N5: =J5*Resumo!$C$7 -> 1.08738 | O5: =J5*Resumo!$C$8 -> 1.08738 | P5: =Resumo!$C$10*CEILING(I5/100,1) -> 1 | Q5: =Resumo!$C$9 -> 11.9 | R5: =SUM(M5:Q5)*Resumo!$C$11 -> 4.2418618 | S5: =SUM(M5:R5) -> 81.366622 | T5: =S5/(1-Resumo!$C$5) -> 92.46207 | U5: 93.97 | V5: =J5*Resumo!$B$6 -> 0.54369 | W5: =J5*Resumo!$B$7 -> 1.08738 | X5: =Resumo!$B$9 -> 1 | Y5: =Resumo!$B$10*CEILING(I5/100,1) -> 4.5 | Z5: =Resumo!$B$12*CEILING(I5,1) -> 2.16 | AA5: =Resumo!$B$13*CEILING(I5,1) -> 16.2 | AB5: =SUM(U5:AA5) -> 119.46107 | AC5: =AB5/(1-Resumo!$B$5) -> 135.75122 | AD5: =(AB5-AA5)/(1-Resumo!$B$5) -> 117.34212 | AE5: =AC5-T5 -> 43.289146 | AF5: =AC5/T5-1 -> 0.46818274 | AG5: =IF(AC5<T5,"SIM","NÃO") -> NÃO | AH5: 8 | AI5: 5 | AJ5: SIM
A6: 353103464 | B6: 46204.75 | C6: Shopee | D6: 26325100 | E6: 26325100 | F6: Queimados | G6: Metropolitana | H6: 20-35 | I6: 27 | J6: 329.99 | K6: Tsl Filial Sp | L6: 100.97 | M6: 70 | N6: =J6*Resumo!$C$7 -> 0.65998 | O6: =J6*Resumo!$C$8 -> 0.65998 | P6: =Resumo!$C$10*CEILING(I6/100,1) -> 1 | Q6: =Resumo!$C$9 -> 11.9 | R6: =SUM(M6:Q6)*Resumo!$C$11 -> 4.6320978 | S6: =SUM(M6:R6) -> 88.852058 | T6: =S6/(1-Resumo!$C$5) -> 100.96825 | U6: 82.21 | V6: =J6*Resumo!$B$6 -> 0.32999 | W6: =J6*Resumo!$B$7 -> 0.65998 | X6: =Resumo!$B$9 -> 1 | Y6: =Resumo!$B$10*CEILING(I6/100,1) -> 4.5 | Z6: =Resumo!$B$12*CEILING(I6,1) -> 1.62 | AA6: =Resumo!$B$13*CEILING(I6,1) -> 12.15 | AB6: =SUM(U6:AA6) -> 102.46997 | AC6: =AB6/(1-Resumo!$B$5) -> 116.44315 | AD6: =(AB6-AA6)/(1-Resumo!$B$5) -> 102.63633 | AE6: =AC6-T6 -> 15.4749 | AF6: =AC6/T6-1 -> 0.15326502 | AG6: =IF(AC6<T6,"SIM","NÃO") -> NÃO | AH6: 10 | AI6: 5 | AJ6: NÃO
A7: 353135681 | B7: 46204.806 | C7: Shopee | D7: 21044020 | E7: 21044020 | F7: Rio de Janeiro | G7: Capital | H7: 50-60 | I7: 55 | J7: 739.98 | K7: Tsl Filial Sp | L7: 114.69 | M7: 79.81 | N7: =J7*Resumo!$C$7 -> 1.47996 | O7: =J7*Resumo!$C$8 -> 1.47996 | P7: =Resumo!$C$10*CEILING(I7/100,1) -> 1 | Q7: =Resumo!$C$9 -> 11.9 | R7: =SUM(M7:Q7)*Resumo!$C$11 -> 5.2618456 | S7: =SUM(M7:R7) -> 100.93177 | T7: =S7/(1-Resumo!$C$5) -> 114.69519 | U7: 112.3 | V7: =J7*Resumo!$B$6 -> 0.73998 | W7: =J7*Resumo!$B$7 -> 1.47996 | X7: =Resumo!$B$9 -> 1 | Y7: =Resumo!$B$10*CEILING(I7/100,1) -> 4.5 | Z7: =Resumo!$B$12*CEILING(I7,1) -> 3.3 | AA7: =Resumo!$B$13*CEILING(I7,1) -> 24.75 | AB7: =SUM(U7:AA7) -> 148.06994 | AC7: =AB7/(1-Resumo!$B$5) -> 168.2613 | AD7: =(AB7-AA7)/(1-Resumo!$B$5) -> 140.1363 | AE7: =AC7-T7 -> 53.566107 | AF7: =AC7/T7-1 -> 0.46703012 | AG7: =IF(AC7<T7,"SIM","NÃO") -> NÃO | AH7: 8 | AI7: 5 | AJ7: SIM
A8: 353198915 | B8: 46204.911 | C8: Shopee | D8: 28025537 | E8: 28025537 | F8: Campos dos Goytacazes | G8: Interior | H8: 20-35 | I8: 35 | J8: 459.99 | K8: Tsl Filial Sp | L8: 109.39 | M8: 76.5 | N8: =J8*Resumo!$C$7 -> 0.91998 | O8: =J8*Resumo!$C$8 -> 0.91998 | P8: =Resumo!$C$10*CEILING(I8/100,1) -> 1 | Q8: =Resumo!$C$9 -> 11.9 | R8: =SUM(M8:Q8)*Resumo!$C$11 -> 5.0181978 | S8: =SUM(M8:R8) -> 96.258158 | T8: =S8/(1-Resumo!$C$5) -> 109.38427 | U8: 138.29 | V8: =J8*Resumo!$B$6 -> 0.45999 | W8: =J8*Resumo!$B$7 -> 0.91998 | X8: =Resumo!$B$9 -> 1 | Y8: =Resumo!$B$10*CEILING(I8/100,1) -> 4.5 | Z8: =Resumo!$B$12*CEILING(I8,1) -> 2.1 | AA8: =Resumo!$B$13*CEILING(I8,1) -> 15.75 | AB8: =SUM(U8:AA8) -> 163.01997 | AC8: =AB8/(1-Resumo!$B$5) -> 185.24997 | AD8: =(AB8-AA8)/(1-Resumo!$B$5) -> 167.35224 | AE8: =AC8-T8 -> 75.865696 | AF8: =AC8/T8-1 -> 0.69357043 | AG8: =IF(AC8<T8,"SIM","NÃO") -> NÃO | AH8: 13 | AI8: 11 | AJ8: SIM
A9: 353403729 | B9: 46205.458 | C9: Shopee | D9: 25555570 | E9: 25555570 | F9: São João de Meriti | G9: Metropolitana | H9: 40-50 | I9: 46.8 | J9: 556.99 | K9: Tsl Filial Sp | L9: 116.74 | M9: 82.25 | N9: =J9*Resumo!$C$7 -> 1.11398 | O9: =J9*Resumo!$C$8 -> 1.11398 | P9: =Resumo!$C$10*CEILING(I9/100,1) -> 1 | Q9: =Resumo!$C$9 -> 11.9 | R9: =SUM(M9:Q9)*Resumo!$C$11 -> 5.3557878 | S9: =SUM(M9:R9) -> 102.73375 | T9: =S9/(1-Resumo!$C$5) -> 116.7429 | U9: 93.97 | V9: =J9*Resumo!$B$6 -> 0.55699 | W9: =J9*Resumo!$B$7 -> 1.11398 | X9: =Resumo!$B$9 -> 1 | Y9: =Resumo!$B$10*CEILING(I9/100,1) -> 4.5 | Z9: =Resumo!$B$12*CEILING(I9,1) -> 2.82 | AA9: =Resumo!$B$13*CEILING(I9,1) -> 21.15 | AB9: =SUM(U9:AA9) -> 125.11097 | AC9: =AB9/(1-Resumo!$B$5) -> 142.17156 | AD9: =(AB9-AA9)/(1-Resumo!$B$5) -> 118.13747 | AE9: =AC9-T9 -> 25.428662 | AF9: =AC9/T9-1 -> 0.21781764 | AG9: =IF(AC9<T9,"SIM","NÃO") -> NÃO | AH9: 10 | AI9: 5 | AJ9: SIM
A10: 353405224 | B10: 46205.461 | C10: Shopee | D10: 25947790 | E10: 25947790 | F10: Guapimirim | G10: Interior | H10: 40-50 | I10: 44.5 | J10: 735.99 | K10: Tsl Filial Sp | L10: 131.68 | M10: 94 | N10: =J10*Resumo!$C$7 -> 1.47198 | O10: =J10*Resumo!$C$8 -> 1.47198 | P10: =Resumo!$C$10*CEILING(I10/100,1) -> 1 | Q10: =Resumo!$C$9 -> 11.9 | R10: =SUM(M10:Q10)*Resumo!$C$11 -> 6.0414178 | S10: =SUM(M10:R10) -> 115.88538 | T10: =S10/(1-Resumo!$C$5) -> 131.68793 | U10: 117.23 | V10: =J10*Resumo!$B$6 -> 0.73599 | W10: =J10*Resumo!$B$7 -> 1.47198 | X10: =Resumo!$B$9 -> 1 | Y10: =Resumo!$B$10*CEILING(I10/100,1) -> 4.5 | Z10: =Resumo!$B$12*CEILING(I10,1) -> 2.7 | AA10: =Resumo!$B$13*CEILING(I10,1) -> 20.25 | AB10: =SUM(U10:AA10) -> 147.88797 | AC10: =AB10/(1-Resumo!$B$5) -> 168.05451 | AD10: =(AB10-AA10)/(1-Resumo!$B$5) -> 145.04315 | AE10: =AC10-T10 -> 36.366582 | AF10: =AC10/T10-1 -> 0.27615729 | AG10: =IF(AC10<T10,"SIM","NÃO") -> NÃO | AH10: 13 | AI10: 6 | AJ10: NÃO
A11: 353490842 | B11: 46205.62 | C11: Shopee | D11: 22790725 | E11: 22790725 | F11: Rio de Janeiro | G11: Capital | H11: 20-35 | I11: 29 | J11: 339.99 | K11: Tsl Filial Sp | L11: 81.95 | M11: 54.1 | N11: =J11*Resumo!$C$7 -> 0.67998 | O11: =J11*Resumo!$C$8 -> 0.67998 | P11: =Resumo!$C$10*CEILING(I11/100,1) -> 1 | Q11: =Resumo!$C$9 -> 11.9 | R11: =SUM(M11:Q11)*Resumo!$C$11 -> 3.7597978 | S11: =SUM(M11:R11) -> 72.119758 | T11: =S11/(1-Resumo!$C$5) -> 81.95427 | U11: 82.21 | V11: =J11*Resumo!$B$6 -> 0.33999 | W11: =J11*Resumo!$B$7 -> 0.67998 | X11: =Resumo!$B$9 -> 1 | Y11: =Resumo!$B$10*CEILING(I11/100,1) -> 4.5 | Z11: =Resumo!$B$12*CEILING(I11,1) -> 1.74 | AA11: =Resumo!$B$13*CEILING(I11,1) -> 13.05 | AB11: =SUM(U11:AA11) -> 103.51997 | AC11: =AB11/(1-Resumo!$B$5) -> 117.63633 | AD11: =(AB11-AA11)/(1-Resumo!$B$5) -> 102.80678 | AE11: =AC11-T11 -> 35.682059 | AF11: =AC11/T11-1 -> 0.43538987 | AG11: =IF(AC11<T11,"SIM","NÃO") -> NÃO | AH11: 8 | AI11: 5 | AJ11: SIM
A12: 353510997 | B12: 46205.661 | C12: Shopee | D12: 25811005 | E12: 25811005 | F12: Três Rios | G12: Interior | H12: 40-50 | I12: 48.3 | J12: 459.99 | K12: Tsl Filial Sp | L12: 130.36 | M12: 94 | N12: =J12*Resumo!$C$7 -> 0.91998 | O12: =J12*Resumo!$C$8 -> 0.91998 | P12: =Resumo!$C$10*CEILING(I12/100,1) -> 1 | Q12: =Resumo!$C$9 -> 11.9 | R12: =SUM(M12:Q12)*Resumo!$C$11 -> 5.9806978 | S12: =SUM(M12:R12) -> 114.72066 | T12: =S12/(1-Resumo!$C$5) -> 130.36438 | U12: 124.38 | V12: =J12*Resumo!$B$6 -> 0.45999 | W12: =J12*Resumo!$B$7 -> 0.91998 | X12: =Resumo!$B$9 -> 1 | Y12: =Resumo!$B$10*CEILING(I12/100,1) -> 4.5 | Z12: =Resumo!$B$12*CEILING(I12,1) -> 2.94 | AA12: =Resumo!$B$13*CEILING(I12,1) -> 22.05 | AB12: =SUM(U12:AA12) -> 156.24997 | AC12: =AB12/(1-Resumo!$B$5) -> 177.55678 | AD12: =(AB12-AA12)/(1-Resumo!$B$5) -> 152.49997 | AE12: =AC12-T12 -> 47.1924 | AF12: =AC12/T12-1 -> 0.36200378 | AG12: =IF(AC12<T12,"SIM","NÃO") -> NÃO | AH12: 13 | AI12: 8 | AJ12: NÃO
A13: 353586941 | B13: 46205.811 | C13: Shopee | D13: 24467575 | E13: 24467575 | F13: São Gonçalo | G13: Metropolitana | H13: 35-40 | I13: 40 | J13: 599.99 | K13: Tsl Filial Sp | L13: 113.83 | M13: 79.65 | N13: =J13*Resumo!$C$7 -> 1.19998 | O13: =J13*Resumo!$C$8 -> 1.19998 | P13: =Resumo!$C$10*CEILING(I13/100,1) -> 1 | Q13: =Resumo!$C$9 -> 11.9 | R13: =SUM(M13:Q13)*Resumo!$C$11 -> 5.2222478 | S13: =SUM(M13:R13) -> 100.17221 | T13: =S13/(1-Resumo!$C$5) -> 113.83205 | U13: 114.95 | V13: =J13*Resumo!$B$6 -> 0.59999 | W13: =J13*Resumo!$B$7 -> 1.19998 | X13: =Resumo!$B$9 -> 1 | Y13: =Resumo!$B$10*CEILING(I13/100,1) -> 4.5 | Z13: =Resumo!$B$12*CEILING(I13,1) -> 2.4 | AA13: =Resumo!$B$13*CEILING(I13,1) -> 18 | AB13: =SUM(U13:AA13) -> 142.64997 | AC13: =AB13/(1-Resumo!$B$5) -> 162.10224 | AD13: =(AB13-AA13)/(1-Resumo!$B$5) -> 141.64769 | AE13: =AC13-T13 -> 48.270184 | AF13: =AC13/T13-1 -> 0.42404738 | AG13: =IF(AC13<T13,"SIM","NÃO") -> NÃO | AH13: 10 | AI13: 7 | AJ13: SIM
... A1158: 378105251 | B1158: 46251.795 | C1158: Shopee | D1158: 28949460 | E1158: 28949460 | F1158: São Pedro da Aldeia | G1158: Interior | H1158: 50-60 | I1158: 52.3 | J1158: 577.12 | K1158: Tsl Transportes | L1158: 141.42 | M1158: 103.6 | N1158: =J1158*Resumo!$C$7 -> 1.15424 | O1158: =J1158*Resumo!$C$8 -> 1.15424 | P1158: =Resumo!$C$10*CEILING(I1158/100,1) -> 1 | Q1158: =Resumo!$C$9 -> 11.9 | R1158: =SUM(M1158:Q1158)*Resumo!$C$11 -> 6.5344664 | S1158: =SUM(M1158:R1158) -> 125.34295 | T1158: =S1158/(1-Resumo!$C$5) -> 142.43517 | U1158: 142.32 | V1158: =J1158*Resumo!$B$6 -> 0.57712 | W1158: =J1158*Resumo!$B$7 -> 1.15424 | X1158: =Resumo!$B$9 -> 1 | Y1158: =Resumo!$B$10*CEILING(I1158/100,1) -> 4.5 | Z1158: =Resumo!$B$12*CEILING(I1158,1) -> 3.18 | AA1158: =Resumo!$B$13*CEILING(I1158,1) -> 23.85 | AB1158: =SUM(U1158:AA1158) -> 176.58136 | AC1158: =AB1158/(1-Resumo!$B$5) -> 200.66064 | AD1158: =(AB1158-AA1158)/(1-Resumo!$B$5) -> 173.55836 | AE1158: =AC1158-T1158 -> 58.22547 | AF1158: =AC1158/T1158-1 -> 0.40878578 | AG1158: =IF(AC1158<T1158,"SIM","NÃO") -> NÃO | AH1158: 13 | AI1158: 10 | AJ1158: NÃO
A1159: 378110430 | B1159: 46251.803 | C1159: Shopee | D1159: 27995000 | E1159: 27995000 | G1159: Interior | H1159: 40-50 | I1159: 44.6 | J1159: 579.99 | K1159: Tsl Transportes | L1159: 130.67 | M1159: 94 | N1159: =J1159*Resumo!$C$7 -> 1.15998 | O1159: =J1159*Resumo!$C$8 -> 1.15998 | P1159: =Resumo!$C$10*CEILING(I1159/100,1) -> 1 | Q1159: =Resumo!$C$9 -> 11.9 | R1159: =SUM(M1159:Q1159)*Resumo!$C$11 -> 6.0070978 | S1159: =SUM(M1159:R1159) -> 115.22706 | T1159: =S1159/(1-Resumo!$C$5) -> 130.93984 | U1159: 152.54 | V1159: =J1159*Resumo!$B$6 -> 0.57999 | W1159: =J1159*Resumo!$B$7 -> 1.15998 | X1159: =Resumo!$B$9 -> 1 | Y1159: =Resumo!$B$10*CEILING(I1159/100,1) -> 4.5 | Z1159: =Resumo!$B$12*CEILING(I1159,1) -> 2.7 | AA1159: =Resumo!$B$13*CEILING(I1159,1) -> 20.25 | AB1159: =SUM(U1159:AA1159) -> 182.72997 | AC1159: =AB1159/(1-Resumo!$B$5) -> 207.64769 | AD1159: =(AB1159-AA1159)/(1-Resumo!$B$5) -> 184.63633 | AE1159: =AC1159-T1159 -> 76.707855 | AF1159: =AC1159/T1159-1 -> 0.58582518 | AG1159: =IF(AC1159<T1159,"SIM","NÃO") -> NÃO | AH1159: 13 | AI1159: 11 | AJ1159: NÃO
A1160: 378114617 | B1160: 46251.81 | C1160: Mercado Livre Principal | D1160: 23595200 | E1160: 23595200 | F1160: Rio de Janeiro | G1160: Capital | H1160: 35-40 | I1160: 37.6 | J1160: 399.59 | K1160: Tsl Transportes | L1160: 92.87 | M1160: 62.05 | N1160: =J1160*Resumo!$C$7 -> 0.79918 | O1160: =J1160*Resumo!$C$8 -> 0.79918 | P1160: =Resumo!$C$10*CEILING(I1160/100,1) -> 1 | Q1160: =Resumo!$C$9 -> 11.9 | R1160: =SUM(M1160:Q1160)*Resumo!$C$11 -> 4.2101598 | S1160: =SUM(M1160:R1160) -> 80.75852 | T1160: =S1160/(1-Resumo!$C$5) -> 91.771045 | U1160: 93.97 | V1160: =J1160*Resumo!$B$6 -> 0.39959 | W1160: =J1160*Resumo!$B$7 -> 0.79918 | X1160: =Resumo!$B$9 -> 1 | Y1160: =Resumo!$B$10*CEILING(I1160/100,1) -> 4.5 | Z1160: =Resumo!$B$12*CEILING(I1160,1) -> 2.28 | AA1160: =Resumo!$B$13*CEILING(I1160,1) -> 17.1 | AB1160: =SUM(U1160:AA1160) -> 120.04877 | AC1160: =AB1160/(1-Resumo!$B$5) -> 136.41906 | AD1160: =(AB1160-AA1160)/(1-Resumo!$B$5) -> 116.98724 | AE1160: =AC1160-T1160 -> 44.648012 | AF1160: =AC1160/T1160-1 -> 0.48651523 | AG1160: =IF(AC1160<T1160,"SIM","NÃO") -> NÃO | AH1160: 8 | AI1160: 5 | AJ1160: SIM
A1161: 378123047 | B1161: 46251.825 | C1161: Shopee | D1161: 28634110 | E1161: 28634110 | F1161: Nova Friburgo | G1161: Interior | H1161: 120-150 | I1161: 141.5 | J1161: 1599.99 | K1161: Tsl Transportes | L1161: 261.94 | M1161: 197.37 | N1161: =J1161*Resumo!$C$7 -> 3.19998 | O1161: =J1161*Resumo!$C$8 -> 3.19998 | P1161: =Resumo!$C$10*CEILING(I1161/100,1) -> 2 | Q1161: =Resumo!$C$9 -> 11.9 | R1161: =SUM(M1161:Q1161)*Resumo!$C$11 -> 11.971848 | S1161: =SUM(M1161:R1161) -> 229.64181 | T1161: =S1161/(1-Resumo!$C$5) -> 260.9566 | U1161: 264.84 | V1161: =J1161*Resumo!$B$6 -> 1.59999 | W1161: =J1161*Resumo!$B$7 -> 3.19998 | X1161: =Resumo!$B$9 -> 1 | Y1161: =Resumo!$B$10*CEILING(I1161/100,1) -> 9 | Z1161: =Resumo!$B$12*CEILING(I1161,1) -> 8.52 | AA1161: =Resumo!$B$13*CEILING(I1161,1) -> 63.9 | AB1161: =SUM(U1161:AA1161) -> 352.05997 | AC1161: =AB1161/(1-Resumo!$B$5) -> 400.06815 | AD1161: =(AB1161-AA1161)/(1-Resumo!$B$5) -> 327.45451 | AE1161: =AC1161-T1161 -> 139.11155 | AF1161: =AC1161/T1161-1 -> 0.53308308 | AG1161: =IF(AC1161<T1161,"SIM","NÃO") -> NÃO | AH1161: 13 | AI1161: 10 | AJ1161: SIM
A1162: 378135699 | B1162: 46251.846 | C1162: Mercado Livre Principal | D1162: 24751000 | E1162: 24751000 | F1162: São Gonçalo | G1162: Metropolitana | H1162: 50-60 | I1162: 52.3 | J1162: 637.3 | K1162: Tsl Transportes | L1162: 127.4 | M1162: 91.6 | N1162: =J1162*Resumo!$C$7 -> 1.2746 | O1162: =J1162*Resumo!$C$8 -> 1.2746 | P1162: =Resumo!$C$10*CEILING(I1162/100,1) -> 1 | Q1162: =Resumo!$C$9 -> 11.9 | R1162: =SUM(M1162:Q1162)*Resumo!$C$11 -> 5.887706 | S1162: =SUM(M1162:R1162) -> 112.93691 | T1162: =S1162/(1-Resumo!$C$5) -> 128.33739 | U1162: 128.14 | V1162: =J1162*Resumo!$B$6 -> 0.6373 | W1162: =J1162*Resumo!$B$7 -> 1.2746 | X1162: =Resumo!$B$9 -> 1 | Y1162: =Resumo!$B$10*CEILING(I1162/100,1) -> 4.5 | Z1162: =Resumo!$B$12*CEILING(I1162,1) -> 3.18 | AA1162: =Resumo!$B$13*CEILING(I1162,1) -> 23.85 | AB1162: =SUM(U1162:AA1162) -> 162.5819 | AC1162: =AB1162/(1-Resumo!$B$5) -> 184.75216 | AD1162: =(AB1162-AA1162)/(1-Resumo!$B$5) -> 157.64989 | AE1162: =AC1162-T1162 -> 56.414766 | AF1162: =AC1162/T1162-1 -> 0.43958167 | AG1162: =IF(AC1162<T1162,"SIM","NÃO") -> NÃO | AH1162: 10 | AI1162: 7 | AJ1162: SIM
A1163: 378145147 | B1163: 46251.864 | C1163: Shopee | D1163: 27240559 | E1163: 27240559 | F1163: Volta Redonda | G1163: Interior | H1163: 50-60 | I1163: 51.3 | J1163: 649.99 | K1163: Tsl Transportes | L1163: 141.25 | M1163: 103.6 | N1163: =J1163*Resumo!$C$7 -> 1.29998 | O1163: =J1163*Resumo!$C$8 -> 1.29998 | P1163: =Resumo!$C$10*CEILING(I1163/100,1) -> 1 | Q1163: =Resumo!$C$9 -> 11.9 | R1163: =SUM(M1163:Q1163)*Resumo!$C$11 -> 6.5504978 | S1163: =SUM(M1163:R1163) -> 125.65046 | T1163: =S1163/(1-Resumo!$C$5) -> 142.78461 | U1163: 142.32 | V1163: =J1163*Resumo!$B$6 -> 0.64999 | W1163: =J1163*Resumo!$B$7 -> 1.29998 | X1163: =Resumo!$B$9 -> 1 | Y1163: =Resumo!$B$10*CEILING(I1163/100,1) -> 4.5 | Z1163: =Resumo!$B$12*CEILING(I1163,1) -> 3.12 | AA1163: =Resumo!$B$13*CEILING(I1163,1) -> 23.4 | AB1163: =SUM(U1163:AA1163) -> 176.28997 | AC1163: =AB1163/(1-Resumo!$B$5) -> 200.32951 | AD1163: =(AB1163-AA1163)/(1-Resumo!$B$5) -> 173.7386 | AE1163: =AC1163-T1163 -> 57.5449 | AF1163: =AC1163/T1163-1 -> 0.40301892 | AG1163: =IF(AC1163<T1163,"SIM","NÃO") -> NÃO | AH1163: 13 | AI1163: 10 | AJ1163: SIM
A1164: 378146674 | B1164: 46251.867 | C1164: Shopee | D1164: 24934275 | E1164: 24934275 | F1164: Maricá | G1164: Interior | H1164: 50-60 | I1164: 52.3 | J1164: 699.99 | K1164: Tsl Transportes | L1164: 142.01 | M1164: 103.6 | N1164: =J1164*Resumo!$C$7 -> 1.39998 | O1164: =J1164*Resumo!$C$8 -> 1.39998 | P1164: =Resumo!$C$10*CEILING(I1164/100,1) -> 1 | Q1164: =Resumo!$C$9 -> 11.9 | R1164: =SUM(M1164:Q1164)*Resumo!$C$11 -> 6.5614978 | S1164: =SUM(M1164:R1164) -> 125.86146 | T1164: =S1164/(1-Resumo!$C$5) -> 143.02438 | U1164: 128.14 | V1164: =J1164*Resumo!$B$6 -> 0.69999 | W1164: =J1164*Resumo!$B$7 -> 1.39998 | X1164: =Resumo!$B$9 -> 1 | Y1164: =Resumo!$B$10*CEILING(I1164/100,1) -> 4.5 | Z1164: =Resumo!$B$12*CEILING(I1164,1) -> 3.18 | AA1164: =Resumo!$B$13*CEILING(I1164,1) -> 23.85 | AB1164: =SUM(U1164:AA1164) -> 162.76997 | AC1164: =AB1164/(1-Resumo!$B$5) -> 184.96588 | AD1164: =(AB1164-AA1164)/(1-Resumo!$B$5) -> 157.8636 | AE1164: =AC1164-T1164 -> 41.941491 | AF1164: =AC1164/T1164-1 -> 0.29324714 | AG1164: =IF(AC1164<T1164,"SIM","NÃO") -> NÃO | AH1164: 13 | AI1164: 7 | AJ1164: SIM
A1165: 378153112 | B1165: 46251.878 | C1165: Shopee | D1165: 21875240 | E1165: 21875240 | F1165: Rio de Janeiro | G1165: Capital | H1165: 40-50 | I1165: 46.8 | J1165: 506.56 | K1165: Tsl Filial Sp | L1165: 103.01 | M1165: 71 | N1165: =J1165*Resumo!$C$7 -> 1.01312 | O1165: =J1165*Resumo!$C$8 -> 1.01312 | P1165: =Resumo!$C$10*CEILING(I1165/100,1) -> 1 | Q1165: =Resumo!$C$9 -> 11.9 | R1165: =SUM(M1165:Q1165)*Resumo!$C$11 -> 4.7259432 | S1165: =SUM(M1165:R1165) -> 90.652183 | T1165: =S1165/(1-Resumo!$C$5) -> 103.01384 | U1165: 93.97 | V1165: =J1165*Resumo!$B$6 -> 0.50656 | W1165: =J1165*Resumo!$B$7 -> 1.01312 | X1165: =Resumo!$B$9 -> 1 | Y1165: =Resumo!$B$10*CEILING(I1165/100,1) -> 4.5 | Z1165: =Resumo!$B$12*CEILING(I1165,1) -> 2.82 | AA1165: =Resumo!$B$13*CEILING(I1165,1) -> 21.15 | AB1165: =SUM(U1165:AA1165) -> 124.95968 | AC1165: =AB1165/(1-Resumo!$B$5) -> 141.99964 | AD1165: =(AB1165-AA1165)/(1-Resumo!$B$5) -> 117.96555 | AE1165: =AC1165-T1165 -> 38.985792 | AF1165: =AC1165/T1165-1 -> 0.37845196 | AG1165: =IF(AC1165<T1165,"SIM","NÃO") -> NÃO | AH1165: 8 | AI1165: 5 | AJ1165: SIM
A1166: 378155516 | B1166: 46251.882 | C1166: Shopee | D1166: 25268376 | E1166: 25268376 | F1166: Duque de Caxias | G1166: Metropolitana | H1166: 60-70 | I1166: 66.8 | J1166: 719.99 | K1166: Tsl Filial Sp | L1166: 139.89 | M1166: 100.9 | N1166: =J1166*Resumo!$C$7 -> 1.43998 | O1166: =J1166*Resumo!$C$8 -> 1.43998 | P1166: =Resumo!$C$10*CEILING(I1166/100,1) -> 1 | Q1166: =Resumo!$C$9 -> 11.9 | R1166: =SUM(M1166:Q1166)*Resumo!$C$11 -> 6.4173978 | S1166: =SUM(M1166:R1166) -> 123.09736 | T1166: =S1166/(1-Resumo!$C$5) -> 139.88336 | U1166: 131.02 | V1166: =J1166*Resumo!$B$6 -> 0.71999 | W1166: =J1166*Resumo!$B$7 -> 1.43998 | X1166: =Resumo!$B$9 -> 1 | Y1166: =Resumo!$B$10*CEILING(I1166/100,1) -> 4.5 | Z1166: =Resumo!$B$12*CEILING(I1166,1) -> 4.02 | AA1166: =Resumo!$B$13*CEILING(I1166,1) -> 30.15 | AB1166: =SUM(U1166:AA1166) -> 172.84997 | AC1166: =AB1166/(1-Resumo!$B$5) -> 196.42042 | AD1166: =(AB1166-AA1166)/(1-Resumo!$B$5) -> 162.15906 | AE1166: =AC1166-T1166 -> 56.537059 | AF1166: =AC1166/T1166-1 -> 0.40417287 | AG1166: =IF(AC1166<T1166,"SIM","NÃO") -> NÃO | AH1166: 10 | AI1166: 5 | AJ1166: SIM
A1167: 378156146 | B1167: 46251.884 | C1167: Shopee | D1167: 25268370 | E1167: 25268370 | F1167: Duque de Caxias | G1167: Metropolitana | H1167: 50-60 | I1167: 56.7 | J1167: 673.1 | K1167: Tsl Filial Sp | L1167: 128.52 | M1167: 91.6 | N1167: =J1167*Resumo!$C$7 -> 1.3462 | O1167: =J1167*Resumo!$C$8 -> 1.3462 | P1167: =Resumo!$C$10*CEILING(I1167/100,1) -> 1 | Q1167: =Resumo!$C$9 -> 11.9 | R1167: =SUM(M1167:Q1167)*Resumo!$C$11 -> 5.895582 | S1167: =SUM(M1167:R1167) -> 113.08798 | T1167: =S1167/(1-Resumo!$C$5) -> 128.50907 | U1167: 112.3 | V1167: =J1167*Resumo!$B$6 -> 0.6731 | W1167: =J1167*Resumo!$B$7 -> 1.3462 | X1167: =Resumo!$B$9 -> 1 | Y1167: =Resumo!$B$10*CEILING(I1167/100,1) -> 4.5 | Z1167: =Resumo!$B$12*CEILING(I1167,1) -> 3.42 | AA1167: =Resumo!$B$13*CEILING(I1167,1) -> 25.65 | AB1167: =SUM(U1167:AA1167) -> 148.8893 | AC1167: =AB1167/(1-Resumo!$B$5) -> 169.19239 | AD1167: =(AB1167-AA1167)/(1-Resumo!$B$5) -> 140.04466 | AE1167: =AC1167-T1167 -> 40.683316 | AF1167: =AC1167/T1167-1 -> 0.31657933 | AG1167: =IF(AC1167<T1167,"SIM","NÃO") -> NÃO | AH1167: 10 | AI1167: 5 | AJ1167: SIM
A1168: 378178860 | B1168: 46251.927 | C1168: Mercado Livre Principal | D1168: 22451264 | E1168: 22451264 | F1168: Rio de Janeiro | G1168: Capital | H1168: 60-70 | I1168: 66.8 | J1168: 592 | K1168: Tsl Transportes | L1168: 125.5 | M1168: 88.2 | N1168: =J1168*Resumo!$C$7 -> 1.184 | O1168: =J1168*Resumo!$C$8 -> 1.184 | P1168: =Resumo!$C$10*CEILING(I1168/100,1) -> 1 | Q1168: =Resumo!$C$9 -> 11.9 | R1168: =SUM(M1168:Q1168)*Resumo!$C$11 -> 5.69074 | S1168: =SUM(M1168:R1168) -> 109.15874 | T1168: =S1168/(1-Resumo!$C$5) -> 124.04402 | U1168: 131.02 | V1168: =J1168*Resumo!$B$6 -> 0.592 | W1168: =J1168*Resumo!$B$7 -> 1.184 | X1168: =Resumo!$B$9 -> 1 | Y1168: =Resumo!$B$10*CEILING(I1168/100,1) -> 4.5 | Z1168: =Resumo!$B$12*CEILING(I1168,1) -> 4.02 | AA1168: =Resumo!$B$13*CEILING(I1168,1) -> 30.15 | AB1168: =SUM(U1168:AA1168) -> 172.466 | AC1168: =AB1168/(1-Resumo!$B$5) -> 195.98409 | AD1168: =(AB1168-AA1168)/(1-Resumo!$B$5) -> 161.72273 | AE1168: =AC1168-T1168 -> 71.940068 | AF1168: =AC1168/T1168-1 -> 0.57995594 | AG1168: =IF(AC1168<T1168,"SIM","NÃO") -> NÃO | AH1168: 8 | AI1168: 5 | AJ1168: SIM
A1169: 378188496 | B1169: 46251.946 | C1169: Mercado Livre Principal | D1169: 21720140 | E1169: 21720140 | F1169: Rio de Janeiro | G1169: Capital | H1169: 120-150 | I1169: 134.4 | J1169: 1632.55 | K1169: Tsl Filial Sp | L1169: 234.13 | M1169: 174.85 | N1169: =J1169*Resumo!$C$7 -> 3.2651 | O1169: =J1169*Resumo!$C$8 -> 3.2651 | P1169: =Resumo!$C$10*CEILING(I1169/100,1) -> 2 | Q1169: =Resumo!$C$9 -> 11.9 | R1169: =SUM(M1169:Q1169)*Resumo!$C$11 -> 10.740411 | S1169: =SUM(M1169:R1169) -> 206.02061 | T1169: =S1169/(1-Resumo!$C$5) -> 234.11433 | U1169: 239.25 | V1169: =J1169*Resumo!$B$6 -> 1.63255 | W1169: =J1169*Resumo!$B$7 -> 3.2651 | X1169: =Resumo!$B$9 -> 1 | Y1169: =Resumo!$B$10*CEILING(I1169/100,1) -> 9 | Z1169: =Resumo!$B$12*CEILING(I1169,1) -> 8.1 | AA1169: =Resumo!$B$13*CEILING(I1169,1) -> 60.75 | AB1169: =SUM(U1169:AA1169) -> 322.99765 | AC1169: =AB1169/(1-Resumo!$B$5) -> 367.04278 | AD1169: =(AB1169-AA1169)/(1-Resumo!$B$5) -> 298.00869 | AE1169: =AC1169-T1169 -> 132.92845 | AF1169: =AC1169/T1169-1 -> 0.56779289 | AG1169: =IF(AC1169<T1169,"SIM","NÃO") -> NÃO | AH1169: 8 | AI1169: 5 | AJ1169: SIM
A1170: 378193239 | B1170: 46251.956 | C1170: Shopee | D1170: 23936170 | E1170: 23936170 | F1170: Angra dos Reis | G1170: Interior | H1170: 40-50 | I1170: 44.6 | J1170: 579.99 | K1170: Tsl Transportes | L1170: 130.67 | M1170: 94 | N1170: =J1170*Resumo!$C$7 -> 1.15998 | O1170: =J1170*Resumo!$C$8 -> 1.15998 | P1170: =Resumo!$C$10*CEILING(I1170/100,1) -> 1 | Q1170: =Resumo!$C$9 -> 11.9 | R1170: =SUM(M1170:Q1170)*Resumo!$C$11 -> 6.0070978 | S1170: =SUM(M1170:R1170) -> 115.22706 | T1170: =S1170/(1-Resumo!$C$5) -> 130.93984 | U1170: 124.38 | V1170: =J1170*Resumo!$B$6 -> 0.57999 | W1170: =J1170*Resumo!$B$7 -> 1.15998 | X1170: =Resumo!$B$9 -> 1 | Y1170: =Resumo!$B$10*CEILING(I1170/100,1) -> 4.5 | Z1170: =Resumo!$B$12*CEILING(I1170,1) -> 2.7 | AA1170: =Resumo!$B$13*CEILING(I1170,1) -> 20.25 | AB1170: =SUM(U1170:AA1170) -> 154.56997 | AC1170: =AB1170/(1-Resumo!$B$5) -> 175.64769 | AD1170: =(AB1170-AA1170)/(1-Resumo!$B$5) -> 152.63633 | AE1170: =AC1170-T1170 -> 44.707855 | AF1170: =AC1170/T1170-1 -> 0.34143814 | AG1170: =IF(AC1170<T1170,"SIM","NÃO") -> NÃO | AH1170: 13 | AI1170: 10 | AJ1170: SIM
A1171: 378208287 | B1171: 46251.99 | C1171: Mercado Livre Principal | D1171: 26115729 | E1171: 26115729 | F1171: Belford Roxo | G1171: Metropolitana | H1171: 100-120 | I1171: 109.7 | J1171: 1091 | K1171: Tsl Transportes | L1171: 194.31 | M1171: 144.44 | N1171: =J1171*Resumo!$C$7 -> 2.182 | O1171: =J1171*Resumo!$C$8 -> 2.182 | P1171: =Resumo!$C$10*CEILING(I1171/100,1) -> 2 | Q1171: =Resumo!$C$9 -> 11.9 | R1171: =SUM(M1171:Q1171)*Resumo!$C$11 -> 8.94872 | S1171: =SUM(M1171:R1171) -> 171.65272 | T1171: =S1171/(1-Resumo!$C$5) -> 195.05991 | U1171: 201.59 | V1171: =J1171*Resumo!$B$6 -> 1.091 | W1171: =J1171*Resumo!$B$7 -> 2.182 | X1171: =Resumo!$B$9 -> 1 | Y1171: =Resumo!$B$10*CEILING(I1171/100,1) -> 9 | Z1171: =Resumo!$B$12*CEILING(I1171,1) -> 6.6 | AA1171: =Resumo!$B$13*CEILING(I1171,1) -> 49.5 | AB1171: =SUM(U1171:AA1171) -> 270.963 | AC1171: =AB1171/(1-Resumo!$B$5) -> 307.9125 | AD1171: =(AB1171-AA1171)/(1-Resumo!$B$5) -> 251.6625 | AE1171: =AC1171-T1171 -> 112.85259 | AF1171: =AC1171/T1171-1 -> 0.57855349 | AG1171: =IF(AC1171<T1171,"SIM","NÃO") -> NÃO | AH1171: 10 | AI1171: 5 | AJ1171: SIM
... A2224: 401847972 | B2224: 46295.959 | C2224: Shopee | D2224: 27130360 | E2224: 27130360 | F2224: Barra do Piraí | G2224: Interior | H2224: 50-60 | I2224: 51.5 | J2224: 478.99 | K2224: Tsl Filial Sp | L2224: 141.97 | M2224: 103.6 | N2224: =J2224*Resumo!$C$7 -> 0.95798 | O2224: =J2224*Resumo!$C$8 -> 0.95798 | P2224: =Resumo!$C$10*CEILING(I2224/100,1) -> 1 | Q2224: =Resumo!$C$9 -> 11.9 | R2224: =SUM(M2224:Q2224)*Resumo!$C$11 -> 6.5128778 | S2224: =SUM(M2224:R2224) -> 124.92884 | T2224: =S2224/(1-Resumo!$C$5) -> 141.96459 | U2224: 142.32 | V2224: =J2224*Resumo!$B$6 -> 0.47899 | W2224: =J2224*Resumo!$B$7 -> 0.95798 | X2224: =Resumo!$B$9 -> 1 | Y2224: =Resumo!$B$10*CEILING(I2224/100,1) -> 4.5 | Z2224: =Resumo!$B$12*CEILING(I2224,1) -> 3.12 | AA2224: =Resumo!$B$13*CEILING(I2224,1) -> 23.4 | AB2224: =SUM(U2224:AA2224) -> 175.77697 | AC2224: =AB2224/(1-Resumo!$B$5) -> 199.74656 | AD2224: =(AB2224-AA2224)/(1-Resumo!$B$5) -> 173.15565 | AE2224: =AC2224-T2224 -> 57.781968 | AF2224: =AC2224/T2224-1 -> 0.40701677 | AG2224: =IF(AC2224<T2224,"SIM","NÃO") -> NÃO | AH2224: 13 | AI2224: 10 | AJ2224: NÃO
