Workbook

Sheet Painel
B1: COMPETITIVIDADE DA TABELA PROLOG FILIAL SP — RIO DE JANEIRO
B2: Base: 2.223 pedidos reais do RJ (jul–set/2026), saída filial SP, cotados pela tabela PROLOG e pela tabela de OUTRO PARCEIRO. Preços finais com ICMS 12% por fora e todas as taxas.
B4: PREÇO PROLOG vs OUTRO PARCEIRO | E4: COTAÇÕES QUE A PROLOG GANHARIA HOJE | H4: FRETE PESO PROLOG vs OUTRO PARCEIRO | K4: REDUÇÃO NECESSÁRIA NO FRETE PESO
B5: =SUM(Pedidos!$AB$2:$AB$2224)/SUM(Pedidos!$S$2:$S$2224)-1 -> 0.4347729 | E5: =COUNTIF(Pedidos!$AE$2:$AE$2224,"SIM")/COUNTA(Pedidos!$D$2:$D$2224) -> 0.0067506751 | H5: =SUM(Pedidos!$T$2:$T$2224)/SUM(Pedidos!$I$2:$I$2224)-1 -> 0.79476785 | K5: =1-(SUM(Pedidos!$R$2:$R$2224)-(SUM(Pedidos!$AA$2:$AA$2224)-SUM(Pedidos!$T$2:$T$2224)))/SUM(Pedidos!$T$2:$T$2224) -> 0.3874974
B7: preço final médio por pedido | E7: pedidos em que a PROLOG seria a mais barata | H7: principal causa da diferença | K7: para empatar, mantendo as taxas atuais
B9: QUADRO 1 — Competitividade por região
B10: Região | C10: Pedidos | D10: % do volume | E10: Preço médio PROLOG | F10: Preço médio OUTRO PARCEIRO | G10: PROLOG vs OUTRO PARCEIRO | H10: Frete peso PROLOG vs OUTRO PARCEIRO | I10: Redução necessária no frete peso | J10: Prazo PROLOG (du) | K10: Prazo OUTRO PARCEIRO (du) | L10: Situação
B11: Capital | C11: =COUNTIFS(Pedidos!$E$2:$E$2224,"Capital") -> 1030 | D11: =C11/COUNTA(Pedidos!$D$2:$D$2224) -> 0.46354635 | E11: =AVERAGEIFS(Pedidos!$AB$2:$AB$2224,Pedidos!$E$2:$E$2224,"Capital") -> 156.29299 | F11: =AVERAGEIFS(Pedidos!$S$2:$S$2224,Pedidos!$E$2:$E$2224,"Capital") -> 106.44612 | G11: =E11/F11-1 -> 0.46828261 | H11: =SUMIFS(Pedidos!$T$2:$T$2224,Pedidos!$E$2:$E$2224,"Capital")/SUMIFS(Pedidos!$I$2:$I$2224,Pedidos!$E$2:$E$2224,"Capital")-1 -> 0.923291 | I11: =1-(SUMIFS(Pedidos!$R$2:$R$2224,Pedidos!$E$2:$E$2224,"Capital")-(SUMIFS(Pedidos!$AA$2:$AA$2224,Pedidos!$E$2:$E$2224,"Capital")-SUMIFS(Pedidos!$T$2:$T$2224,Pedidos!$E$2:$E$2224,"Capital")))/SUMIFS(Pedidos!$T$2:$T$2224,Pedidos!$E$2:$E$2224,"Capital") -> 0.41606281 | J11: =AVERAGEIFS(Pedidos!$AG$2:$AG$2224,Pedidos!$E$2:$E$2224,"Capital") -> 5 | K11: =AVERAGEIFS(Pedidos!$AF$2:$AF$2224,Pedidos!$E$2:$E$2224,"Capital") -> 2 | L11: =IF(G11<=0,"COMPETITIVO",IF(G11<=0.25,"AJUSTE MODERADO","AJUSTE FORTE")) -> AJUSTE FORTE
B12: Metropolitana | C12: =COUNTIFS(Pedidos!$E$2:$E$2224,"Metropolitana") -> 542 | D12: =C12/COUNTA(Pedidos!$D$2:$D$2224) -> 0.24392439 | E12: =AVERAGEIFS(Pedidos!$AB$2:$AB$2224,Pedidos!$E$2:$E$2224,"Metropolitana") -> 172.71587 | F12: =AVERAGEIFS(Pedidos!$S$2:$S$2224,Pedidos!$E$2:$E$2224,"Metropolitana") -> 127.2607 | G12: =E12/F12-1 -> 0.35718152 | H12: =SUMIFS(Pedidos!$T$2:$T$2224,Pedidos!$E$2:$E$2224,"Metropolitana")/SUMIFS(Pedidos!$I$2:$I$2224,Pedidos!$E$2:$E$2224,"Metropolitana")-1 -> 0.65576215 | I12: =1-(SUMIFS(Pedidos!$R$2:$R$2224,Pedidos!$E$2:$E$2224,"Metropolitana")-(SUMIFS(Pedidos!$AA$2:$AA$2224,Pedidos!$E$2:$E$2224,"Metropolitana")-SUMIFS(Pedidos!$T$2:$T$2224,Pedidos!$E$2:$E$2224,"Metropolitana")))/SUMIFS(Pedidos!$T$2:$T$2224,Pedidos!$E$2:$E$2224,"Metropolitana") -> 0.3407957 | J12: =AVERAGEIFS(Pedidos!$AG$2:$AG$2224,Pedidos!$E$2:$E$2224,"Metropolitana") -> 5.7490775 | K12: =AVERAGEIFS(Pedidos!$AF$2:$AF$2224,Pedidos!$E$2:$E$2224,"Metropolitana") -> 2 | L12: =IF(G12<=0,"COMPETITIVO",IF(G12<=0.25,"AJUSTE MODERADO","AJUSTE FORTE")) -> AJUSTE FORTE
B13: Interior | C13: =COUNTIFS(Pedidos!$E$2:$E$2224,"Interior") -> 651 | D13: =C13/COUNTA(Pedidos!$D$2:$D$2224) -> 0.2929793 | E13: =AVERAGEIFS(Pedidos!$AB$2:$AB$2224,Pedidos!$E$2:$E$2224,"Interior") -> 202.86615 | F13: =AVERAGEIFS(Pedidos!$S$2:$S$2224,Pedidos!$E$2:$E$2224,"Interior") -> 139.59612 | G13: =E13/F13-1 -> 0.4532363 | H13: =SUMIFS(Pedidos!$T$2:$T$2224,Pedidos!$E$2:$E$2224,"Interior")/SUMIFS(Pedidos!$I$2:$I$2224,Pedidos!$E$2:$E$2224,"Interior")-1 -> 0.75887282 | I13: =1-(SUMIFS(Pedidos!$R$2:$R$2224,Pedidos!$E$2:$E$2224,"Interior")-(SUMIFS(Pedidos!$AA$2:$AA$2224,Pedidos!$E$2:$E$2224,"Interior")-SUMIFS(Pedidos!$T$2:$T$2224,Pedidos!$E$2:$E$2224,"Interior")))/SUMIFS(Pedidos!$T$2:$T$2224,Pedidos!$E$2:$E$2224,"Interior") -> 0.38610223 | J13: =AVERAGEIFS(Pedidos!$AG$2:$AG$2224,Pedidos!$E$2:$E$2224,"Interior") -> 9.3855607 | K13: =AVERAGEIFS(Pedidos!$AF$2:$AF$2224,Pedidos!$E$2:$E$2224,"Interior") -> 13 | L13: =IF(G13<=0,"COMPETITIVO",IF(G13<=0.25,"AJUSTE MODERADO","AJUSTE FORTE")) -> AJUSTE FORTE
B14: TOTAL | C14: =COUNTIFS(Pedidos!$E$2:$E$2224,"<>") -> 2223 | D14: =C14/COUNTA(Pedidos!$D$2:$D$2224) -> 1.00045 | E14: =AVERAGEIFS(Pedidos!$AB$2:$AB$2224,Pedidos!$E$2:$E$2224,"<>") -> 173.93596 | F14: =AVERAGEIFS(Pedidos!$S$2:$S$2224,Pedidos!$E$2:$E$2224,"<>") -> 121.22891 | G14: =E14/F14-1 -> 0.4347729 | H14: =SUMIFS(Pedidos!$T$2:$T$2224,Pedidos!$E$2:$E$2224,"<>")/SUMIFS(Pedidos!$I$2:$I$2224,Pedidos!$E$2:$E$2224,"<>")-1 -> 0.79476785 | I14: =1-(SUMIFS(Pedidos!$R$2:$R$2224,Pedidos!$E$2:$E$2224,"<>")-(SUMIFS(Pedidos!$AA$2:$AA$2224,Pedidos!$E$2:$E$2224,"<>")-SUMIFS(Pedidos!$T$2:$T$2224,Pedidos!$E$2:$E$2224,"<>")))/SUMIFS(Pedidos!$T$2:$T$2224,Pedidos!$E$2:$E$2224,"<>") -> 0.3874974 | J14: =AVERAGEIFS(Pedidos!$AG$2:$AG$2224,Pedidos!$E$2:$E$2224,"<>") -> 6.4669366 | K14: =AVERAGEIFS(Pedidos!$AF$2:$AF$2224,Pedidos!$E$2:$E$2224,"<>") -> 5.2213225 | L14: =IF(G14<=0,"COMPETITIVO",IF(G14<=0.25,"AJUSTE MODERADO","AJUSTE FORTE")) -> AJUSTE FORTE
B15: Capital = CEPs 20000-001 a 23799-999 (município do Rio). Metropolitana = Niterói, São Gonçalo, Duque de Caxias, São João de Meriti, Nova Iguaçu, Belford Roxo, Queimados, Nilópolis e Mesquita. Interior = demais.
B17: QUADRO 2 — PROLOG vs OUTRO PARCEIRO por faixa de peso (preço final) | H17: verde = PROLOG competitiva · vermelho = precisa reduzir
B18: Região | C18: 0-20 kg | D18: 20-35 kg | E18: 35-40 kg | F18: 40-50 kg | G18: 50-60 kg | H18: 60-70 kg | I18: 70-80 kg | J18: 80-100 kg | K18: 100-120 kg | L18: 120-150 kg | M18: Total
B19: Capital | C19: =IFERROR(SUMIFS(Pedidos!$AB$2:$AB$2224,Pedidos!$E$2:$E$2224,"Capital",Pedidos!$F$2:$F$2224,"0-20")/SUMIFS(Pedidos!$S$2:$S$2224,Pedidos!$E$2:$E$2224,"Capital",Pedidos!$F$2:$F$2224,"0-20")-1,"") -> 0.090212475 | D19: =IFERROR(SUMIFS(Pedidos!$AB$2:$AB$2224,Pedidos!$E$2:$E$2224,"Capital",Pedidos!$F$2:$F$2224,"20-35")/SUMIFS(Pedidos!$S$2:$S$2224,Pedidos!$E$2:$E$2224,"Capital",Pedidos!$F$2:$F$2224,"20-35")-1,"") -> 0.45217647 | E19: =IFERROR(SUMIFS(Pedidos!$AB$2:$AB$2224,Pedidos!$E$2:$E$2224,"Capital",Pedidos!$F$2:$F$2224,"35-40")/SUMIFS(Pedidos!$S$2:$S$2224,Pedidos!$E$2:$E$2224,"Capital",Pedidos!$F$2:$F$2224,"35-40")-1,"") -> 0.46655029 | F19: =IFERROR(SUMIFS(Pedidos!$AB$2:$AB$2224,Pedidos!$E$2:$E$2224,"Capital",Pedidos!$F$2:$F$2224,"40-50")/SUMIFS(Pedidos!$S$2:$S$2224,Pedidos!$E$2:$E$2224,"Capital",Pedidos!$F$2:$F$2224,"40-50")-1,"") -> 0.36502388 | G19: =IFERROR(SUMIFS(Pedidos!$AB$2:$AB$2224,Pedidos!$E$2:$E$2224,"Capital",Pedidos!$F$2:$F$2224,"50-60")/SUMIFS(Pedidos!$S$2:$S$2224,Pedidos!$E$2:$E$2224,"Capital",Pedidos!$F$2:$F$2224,"50-60")-1,"") -> 0.46820634 | H19: =IFERROR(SUMIFS(Pedidos!$AB$2:$AB$2224,Pedidos!$E$2:$E$2224,"Capital",Pedidos!$F$2:$F$2224,"60-70")/SUMIFS(Pedidos!$S$2:$S$2224,Pedidos!$E$2:$E$2224,"Capital",Pedidos!$F$2:$F$2224,"60-70")-1,"") -> 0.55690899 | I19: =IFERROR(SUMIFS(Pedidos!$AB$2:$AB$2224,Pedidos!$E$2:$E$2224,"Capital",Pedidos!$F$2:$F$2224,"70-80")/SUMIFS(Pedidos!$S$2:$S$2224,Pedidos!$E$2:$E$2224,"Capital",Pedidos!$F$2:$F$2224,"70-80")-1,"") -> 0.48740184 | J19: =IFERROR(SUMIFS(Pedidos!$AB$2:$AB$2224,Pedidos!$E$2:$E$2224,"Capital",Pedidos!$F$2:$F$2224,"80-100")/SUMIFS(Pedidos!$S$2:$S$2224,Pedidos!$E$2:$E$2224,"Capital",Pedidos!$F$2:$F$2224,"80-100")-1,"") -> 0.55652654 | K19: =IFERROR(SUMIFS(Pedidos!$AB$2:$AB$2224,Pedidos!$E$2:$E$2224,"Capital",Pedidos!$F$2:$F$2224,"100-120")/SUMIFS(Pedidos!$S$2:$S$2224,Pedidos!$E$2:$E$2224,"Capital",Pedidos!$F$2:$F$2224,"100-120")-1,"") -> 0.66629369 | L19: =IFERROR(SUMIFS(Pedidos!$AB$2:$AB$2224,Pedidos!$E$2:$E$2224,"Capital",Pedidos!$F$2:$F$2224,"120-150")/SUMIFS(Pedidos!$S$2:$S$2224,Pedidos!$E$2:$E$2224,"Capital",Pedidos!$F$2:$F$2224,"120-150")-1,"") -> 0.59080036 | M19: =IFERROR(SUMIFS(Pedidos!$AB$2:$AB$2224,Pedidos!$E$2:$E$2224,"Capital")/SUMIFS(Pedidos!$S$2:$S$2224,Pedidos!$E$2:$E$2224,"Capital")-1,"") -> 0.46828261
B20: Metropolitana | C20: =IFERROR(SUMIFS(Pedidos!$AB$2:$AB$2224,Pedidos!$E$2:$E$2224,"Metropolitana",Pedidos!$F$2:$F$2224,"0-20")/SUMIFS(Pedidos!$S$2:$S$2224,Pedidos!$E$2:$E$2224,"Metropolitana",Pedidos!$F$2:$F$2224,"0-20")-1,"") -> 0.0011116464 | D20: =IFERROR(SUMIFS(Pedidos!$AB$2:$AB$2224,Pedidos!$E$2:$E$2224,"Metropolitana",Pedidos!$F$2:$F$2224,"20-35")/SUMIFS(Pedidos!$S$2:$S$2224,Pedidos!$E$2:$E$2224,"Metropolitana",Pedidos!$F$2:$F$2224,"20-35")-1,"") -> 0.2693548 | E20: =IFERROR(SUMIFS(Pedidos!$AB$2:$AB$2224,Pedidos!$E$2:$E$2224,"Metropolitana",Pedidos!$F$2:$F$2224,"35-40")/SUMIFS(Pedidos!$S$2:$S$2224,Pedidos!$E$2:$E$2224,"Metropolitana",Pedidos!$F$2:$F$2224,"35-40")-1,"") -> 0.27306231 | F20: =IFERROR(SUMIFS(Pedidos!$AB$2:$AB$2224,Pedidos!$E$2:$E$2224,"Metropolitana",Pedidos!$F$2:$F$2224,"40-50")/SUMIFS(Pedidos!$S$2:$S$2224,Pedidos!$E$2:$E$2224,"Metropolitana",Pedidos!$F$2:$F$2224,"40-50")-1,"") -> 0.28870004 | G20: =IFERROR(SUMIFS(Pedidos!$AB$2:$AB$2224,Pedidos!$E$2:$E$2224,"Metropolitana",Pedidos!$F$2:$F$2224,"50-60")/SUMIFS(Pedidos!$S$2:$S$2224,Pedidos!$E$2:$E$2224,"Metropolitana",Pedidos!$F$2:$F$2224,"50-60")-1,"") -> 0.35816794 | H20: =IFERROR(SUMIFS(Pedidos!$AB$2:$AB$2224,Pedidos!$E$2:$E$2224,"Metropolitana",Pedidos!$F$2:$F$2224,"60-70")/SUMIFS(Pedidos!$S$2:$S$2224,Pedidos!$E$2:$E$2224,"Metropolitana",Pedidos!$F$2:$F$2224,"60-70")-1,"") -> 0.44290558 | I20: =IFERROR(SUMIFS(Pedidos!$AB$2:$AB$2224,Pedidos!$E$2:$E$2224,"Metropolitana",Pedidos!$F$2:$F$2224,"70-80")/SUMIFS(Pedidos!$S$2:$S$2224,Pedidos!$E$2:$E$2224,"Metropolitana",Pedidos!$F$2:$F$2224,"70-80")-1,"") -> 0.3642043 | J20: =IFERROR(SUMIFS(Pedidos!$AB$2:$AB$2224,Pedidos!$E$2:$E$2224,"Metropolitana",Pedidos!$F$2:$F$2224,"80-100")/SUMIFS(Pedidos!$S$2:$S$2224,Pedidos!$E$2:$E$2224,"Metropolitana",Pedidos!$F$2:$F$2224,"80-100")-1,"") -> 0.49142215 | K20: =IFERROR(SUMIFS(Pedidos!$AB$2:$AB$2224,Pedidos!$E$2:$E$2224,"Metropolitana",Pedidos!$F$2:$F$2224,"100-120")/SUMIFS(Pedidos!$S$2:$S$2224,Pedidos!$E$2:$E$2224,"Metropolitana",Pedidos!$F$2:$F$2224,"100-120")-1,"") -> 0.59793507 | L20: =IFERROR(SUMIFS(Pedidos!$AB$2:$AB$2224,Pedidos!$E$2:$E$2224,"Metropolitana",Pedidos!$F$2:$F$2224,"120-150")/SUMIFS(Pedidos!$S$2:$S$2224,Pedidos!$E$2:$E$2224,"Metropolitana",Pedidos!$F$2:$F$2224,"120-150")-1,"") -> 0.53347538 | M20: =IFERROR(SUMIFS(Pedidos!$AB$2:$AB$2224,Pedidos!$E$2:$E$2224,"Metropolitana")/SUMIFS(Pedidos!$S$2:$S$2224,Pedidos!$E$2:$E$2224,"Metropolitana")-1,"") -> 0.35718152
B21: Interior | C21: =IFERROR(SUMIFS(Pedidos!$AB$2:$AB$2224,Pedidos!$E$2:$E$2224,"Interior",Pedidos!$F$2:$F$2224,"0-20")/SUMIFS(Pedidos!$S$2:$S$2224,Pedidos!$E$2:$E$2224,"Interior",Pedidos!$F$2:$F$2224,"0-20")-1,"") -> 0.53003614 | D21: =IFERROR(SUMIFS(Pedidos!$AB$2:$AB$2224,Pedidos!$E$2:$E$2224,"Interior",Pedidos!$F$2:$F$2224,"20-35")/SUMIFS(Pedidos!$S$2:$S$2224,Pedidos!$E$2:$E$2224,"Interior",Pedidos!$F$2:$F$2224,"20-35")-1,"") -> 0.45279877 | E21: =IFERROR(SUMIFS(Pedidos!$AB$2:$AB$2224,Pedidos!$E$2:$E$2224,"Interior",Pedidos!$F$2:$F$2224,"35-40")/SUMIFS(Pedidos!$S$2:$S$2224,Pedidos!$E$2:$E$2224,"Interior",Pedidos!$F$2:$F$2224,"35-40")-1,"") -> 0.40457711 | F21: =IFERROR(SUMIFS(Pedidos!$AB$2:$AB$2224,Pedidos!$E$2:$E$2224,"Interior",Pedidos!$F$2:$F$2224,"40-50")/SUMIFS(Pedidos!$S$2:$S$2224,Pedidos!$E$2:$E$2224,"Interior",Pedidos!$F$2:$F$2224,"40-50")-1,"") -> 0.40459217 | G21: =IFERROR(SUMIFS(Pedidos!$AB$2:$AB$2224,Pedidos!$E$2:$E$2224,"Interior",Pedidos!$F$2:$F$2224,"50-60")/SUMIFS(Pedidos!$S$2:$S$2224,Pedidos!$E$2:$E$2224,"Interior",Pedidos!$F$2:$F$2224,"50-60")-1,"") -> 0.42464002 | H21: =IFERROR(SUMIFS(Pedidos!$AB$2:$AB$2224,Pedidos!$E$2:$E$2224,"Interior",Pedidos!$F$2:$F$2224,"60-70")/SUMIFS(Pedidos!$S$2:$S$2224,Pedidos!$E$2:$E$2224,"Interior",Pedidos!$F$2:$F$2224,"60-70")-1,"") -> 0.48279866 | I21: =IFERROR(SUMIFS(Pedidos!$AB$2:$AB$2224,Pedidos!$E$2:$E$2224,"Interior",Pedidos!$F$2:$F$2224,"70-80")/SUMIFS(Pedidos!$S$2:$S$2224,Pedidos!$E$2:$E$2224,"Interior",Pedidos!$F$2:$F$2224,"70-80")-1,"") -> 0.38567155 | J21: =IFERROR(SUMIFS(Pedidos!$AB$2:$AB$2224,Pedidos!$E$2:$E$2224,"Interior",Pedidos!$F$2:$F$2224,"80-100")/SUMIFS(Pedidos!$S$2:$S$2224,Pedidos!$E$2:$E$2224,"Interior",Pedidos!$F$2:$F$2224,"80-100")-1,"") -> 0.46611946 | K21: =IFERROR(SUMIFS(Pedidos!$AB$2:$AB$2224,Pedidos!$E$2:$E$2224,"Interior",Pedidos!$F$2:$F$2224,"100-120")/SUMIFS(Pedidos!$S$2:$S$2224,Pedidos!$E$2:$E$2224,"Interior",Pedidos!$F$2:$F$2224,"100-120")-1,"") -> 0.58503505 | L21: =IFERROR(SUMIFS(Pedidos!$AB$2:$AB$2224,Pedidos!$E$2:$E$2224,"Interior",Pedidos!$F$2:$F$2224,"120-150")/SUMIFS(Pedidos!$S$2:$S$2224,Pedidos!$E$2:$E$2224,"Interior",Pedidos!$F$2:$F$2224,"120-150")-1,"") -> 0.52391223 | M21: =IFERROR(SUMIFS(Pedidos!$AB$2:$AB$2224,Pedidos!$E$2:$E$2224,"Interior")/SUMIFS(Pedidos!$S$2:$S$2224,Pedidos!$E$2:$E$2224,"Interior")-1,"") -> 0.4532363
B22: TODAS | C22: =IFERROR(SUMIFS(Pedidos!$AB$2:$AB$2224,Pedidos!$E$2:$E$2224,"<>",Pedidos!$F$2:$F$2224,"0-20")/SUMIFS(Pedidos!$S$2:$S$2224,Pedidos!$E$2:$E$2224,"<>",Pedidos!$F$2:$F$2224,"0-20")-1,"") -> 0.15272413 | D22: =IFERROR(SUMIFS(Pedidos!$AB$2:$AB$2224,Pedidos!$E$2:$E$2224,"<>",Pedidos!$F$2:$F$2224,"20-35")/SUMIFS(Pedidos!$S$2:$S$2224,Pedidos!$E$2:$E$2224,"<>",Pedidos!$F$2:$F$2224,"20-35")-1,"") -> 0.41664093 | E22: =IFERROR(SUMIFS(Pedidos!$AB$2:$AB$2224,Pedidos!$E$2:$E$2224,"<>",Pedidos!$F$2:$F$2224,"35-40")/SUMIFS(Pedidos!$S$2:$S$2224,Pedidos!$E$2:$E$2224,"<>",Pedidos!$F$2:$F$2224,"35-40")-1,"") -> 0.39811542 | F22: =IFERROR(SUMIFS(Pedidos!$AB$2:$AB$2224,Pedidos!$E$2:$E$2224,"<>",Pedidos!$F$2:$F$2224,"40-50")/SUMIFS(Pedidos!$S$2:$S$2224,Pedidos!$E$2:$E$2224,"<>",Pedidos!$F$2:$F$2224,"40-50")-1,"") -> 0.35665037 | G22: =IFERROR(SUMIFS(Pedidos!$AB$2:$AB$2224,Pedidos!$E$2:$E$2224,"<>",Pedidos!$F$2:$F$2224,"50-60")/SUMIFS(Pedidos!$S$2:$S$2224,Pedidos!$E$2:$E$2224,"<>",Pedidos!$F$2:$F$2224,"50-60")-1,"") -> 0.42227189 | H22: =IFERROR(SUMIFS(Pedidos!$AB$2:$AB$2224,Pedidos!$E$2:$E$2224,"<>",Pedidos!$F$2:$F$2224,"60-70")/SUMIFS(Pedidos!$S$2:$S$2224,Pedidos!$E$2:$E$2224,"<>",Pedidos!$F$2:$F$2224,"60-70")-1,"") -> 0.49929853 | I22: =IFERROR(SUMIFS(Pedidos!$AB$2:$AB$2224,Pedidos!$E$2:$E$2224,"<>",Pedidos!$F$2:$F$2224,"70-80")/SUMIFS(Pedidos!$S$2:$S$2224,Pedidos!$E$2:$E$2224,"<>",Pedidos!$F$2:$F$2224,"70-80")-1,"") -> 0.41262021 | J22: =IFERROR(SUMIFS(Pedidos!$AB$2:$AB$2224,Pedidos!$E$2:$E$2224,"<>",Pedidos!$F$2:$F$2224,"80-100")/SUMIFS(Pedidos!$S$2:$S$2224,Pedidos!$E$2:$E$2224,"<>",Pedidos!$F$2:$F$2224,"80-100")-1,"") -> 0.49933513 | K22: =IFERROR(SUMIFS(Pedidos!$AB$2:$AB$2224,Pedidos!$E$2:$E$2224,"<>",Pedidos!$F$2:$F$2224,"100-120")/SUMIFS(Pedidos!$S$2:$S$2224,Pedidos!$E$2:$E$2224,"<>",Pedidos!$F$2:$F$2224,"100-120")-1,"") -> 0.61970309 | L22: =IFERROR(SUMIFS(Pedidos!$AB$2:$AB$2224,Pedidos!$E$2:$E$2224,"<>",Pedidos!$F$2:$F$2224,"120-150")/SUMIFS(Pedidos!$S$2:$S$2224,Pedidos!$E$2:$E$2224,"<>",Pedidos!$F$2:$F$2224,"120-150")-1,"") -> 0.55509108 | M22: =IFERROR(SUMIFS(Pedidos!$AB$2:$AB$2224,Pedidos!$E$2:$E$2224,"<>")/SUMIFS(Pedidos!$S$2:$S$2224,Pedidos!$E$2:$E$2224,"<>")-1,"") -> 0.4347729
B23: % do volume | C23: =COUNTIFS(Pedidos!$F$2:$F$2224,"0-20")/COUNTA(Pedidos!$D$2:$D$2224) -> 0.048154815 | D23: =COUNTIFS(Pedidos!$F$2:$F$2224,"20-35")/COUNTA(Pedidos!$D$2:$D$2224) -> 0.22277228 | E23: =COUNTIFS(Pedidos!$F$2:$F$2224,"35-40")/COUNTA(Pedidos!$D$2:$D$2224) -> 0.15976598 | F23: =COUNTIFS(Pedidos!$F$2:$F$2224,"40-50")/COUNTA(Pedidos!$D$2:$D$2224) -> 0.15481548 | G23: =COUNTIFS(Pedidos!$F$2:$F$2224,"50-60")/COUNTA(Pedidos!$D$2:$D$2224) -> 0.18721872 | H23: =COUNTIFS(Pedidos!$F$2:$F$2224,"60-70")/COUNTA(Pedidos!$D$2:$D$2224) -> 0.12286229 | I23: =COUNTIFS(Pedidos!$F$2:$F$2224,"70-80")/COUNTA(Pedidos!$D$2:$D$2224) -> 0.01350135 | J23: =COUNTIFS(Pedidos!$F$2:$F$2224,"80-100")/COUNTA(Pedidos!$D$2:$D$2224) -> 0.025652565 | K23: =COUNTIFS(Pedidos!$F$2:$F$2224,"100-120")/COUNTA(Pedidos!$D$2:$D$2224) -> 0.023852385 | L23: =COUNTIFS(Pedidos!$F$2:$F$2224,"120-150")/COUNTA(Pedidos!$D$2:$D$2224) -> 0.03870387 | M23: =SUM(C23:L23) -> 0.99729973
B25: QUADRO 3 — Frete peso da tabela: ATUAL x ALVO para empatar (faixas com 80% do volume) | H25: alvo = valor máximo de frete peso para empatar; para ganhar a cotação, ficar alguns % abaixo
B26: Cidade | C26: 0-20 kg | E26: 20-35 kg | G26: 35-40 kg | I26: 40-50 kg | K26: 50-60 kg | M26: 60-70 kg
C27: Atual | D27: Alvo | E27: Atual | F27: Alvo | G27: Atual | H27: Alvo | I27: Atual | J27: Alvo | K27: Atual | L27: Alvo | M27: Atual | N27: Alvo
B28: Rio de Janeiro | C28: =INDEX('Proposta Tabela PROLOG'!H:H,MATCH($B28,'Proposta Tabela PROLOG'!$B:$B,0)) -> 46.98 | D28: =INDEX('Proposta Tabela PROLOG'!AH:AH,MATCH($B28,'Proposta Tabela PROLOG'!$B:$B,0)) -> 41.817887 | E28: =INDEX('Proposta Tabela PROLOG'!I:I,MATCH($B28,'Proposta Tabela PROLOG'!$B:$B,0)) -> 82.21 | F28: =INDEX('Proposta Tabela PROLOG'!AI:AI,MATCH($B28,'Proposta Tabela PROLOG'!$B:$B,0)) -> 49.991357 | G28: =INDEX('Proposta Tabela PROLOG'!J:J,MATCH($B28,'Proposta Tabela PROLOG'!$B:$B,0)) -> 93.97 | H28: =INDEX('Proposta Tabela PROLOG'!AJ:AJ,MATCH($B28,'Proposta Tabela PROLOG'!$B:$B,0)) -> 55.728132 | I28: =INDEX('Proposta Tabela PROLOG'!K:K,MATCH($B28,'Proposta Tabela PROLOG'!$B:$B,0)) -> 93.97 | J28: =INDEX('Proposta Tabela PROLOG'!AK:AK,MATCH($B28,'Proposta Tabela PROLOG'!$B:$B,0)) -> 60.613696 | K28: =INDEX('Proposta Tabela PROLOG'!L:L,MATCH($B28,'Proposta Tabela PROLOG'!$B:$B,0)) -> 112.3 | L28: =INDEX('Proposta Tabela PROLOG'!AL:AL,MATCH($B28,'Proposta Tabela PROLOG'!$B:$B,0)) -> 65.29338 | M28: =INDEX('Proposta Tabela PROLOG'!M:M,MATCH($B28,'Proposta Tabela PROLOG'!$B:$B,0)) -> 131.02 | N28: =INDEX('Proposta Tabela PROLOG'!AM:AM,MATCH($B28,'Proposta Tabela PROLOG'!$B:$B,0)) -> 69.201232
B29: São Gonçalo | C29: =INDEX('Proposta Tabela PROLOG'!H:H,MATCH($B29,'Proposta Tabela PROLOG'!$B:$B,0)) -> 57.47 | D29: =INDEX('Proposta Tabela PROLOG'!AH:AH,MATCH($B29,'Proposta Tabela PROLOG'!$B:$B,0)) -> 51.117887 | E29: =INDEX('Proposta Tabela PROLOG'!I:I,MATCH($B29,'Proposta Tabela PROLOG'!$B:$B,0)) -> 100.58 | F29: =INDEX('Proposta Tabela PROLOG'!AI:AI,MATCH($B29,'Proposta Tabela PROLOG'!$B:$B,0)) -> 66.681357 | G29: =INDEX('Proposta Tabela PROLOG'!J:J,MATCH($B29,'Proposta Tabela PROLOG'!$B:$B,0)) -> 114.95 | H29: =INDEX('Proposta Tabela PROLOG'!AJ:AJ,MATCH($B29,'Proposta Tabela PROLOG'!$B:$B,0)) -> 74.208132 | I29: =INDEX('Proposta Tabela PROLOG'!K:K,MATCH($B29,'Proposta Tabela PROLOG'!$B:$B,0)) -> 114.95 | J29: =INDEX('Proposta Tabela PROLOG'!AK:AK,MATCH($B29,'Proposta Tabela PROLOG'!$B:$B,0)) -> 72.423696 | K29: =INDEX('Proposta Tabela PROLOG'!L:L,MATCH($B29,'Proposta Tabela PROLOG'!$B:$B,0)) -> 128.14 | L29: =INDEX('Proposta Tabela PROLOG'!AL:AL,MATCH($B29,'Proposta Tabela PROLOG'!$B:$B,0)) -> 77.67338 | M29: =INDEX('Proposta Tabela PROLOG'!M:M,MATCH($B29,'Proposta Tabela PROLOG'!$B:$B,0)) -> 149.5 | N29: =INDEX('Proposta Tabela PROLOG'!AM:AM,MATCH($B29,'Proposta Tabela PROLOG'!$B:$B,0)) -> 82.541232
B30: Duque de Caxias | C30: =INDEX('Proposta Tabela PROLOG'!H:H,MATCH($B30,'Proposta Tabela PROLOG'!$B:$B,0)) -> 46.98 | D30: =INDEX('Proposta Tabela PROLOG'!AH:AH,MATCH($B30,'Proposta Tabela PROLOG'!$B:$B,0)) -> 51.117887 | E30: =INDEX('Proposta Tabela PROLOG'!I:I,MATCH($B30,'Proposta Tabela PROLOG'!$B:$B,0)) -> 82.21 | F30: =INDEX('Proposta Tabela PROLOG'!AI:AI,MATCH($B30,'Proposta Tabela PROLOG'!$B:$B,0)) -> 66.681357 | G30: =INDEX('Proposta Tabela PROLOG'!J:J,MATCH($B30,'Proposta Tabela PROLOG'!$B:$B,0)) -> 93.97 | H30: =INDEX('Proposta Tabela PROLOG'!AJ:AJ,MATCH($B30,'Proposta Tabela PROLOG'!$B:$B,0)) -> 74.208132 | I30: =INDEX('Proposta Tabela PROLOG'!K:K,MATCH($B30,'Proposta Tabela PROLOG'!$B:$B,0)) -> 93.97 | J30: =INDEX('Proposta Tabela PROLOG'!AK:AK,MATCH($B30,'Proposta Tabela PROLOG'!$B:$B,0)) -> 72.423696 | K30: =INDEX('Proposta Tabela PROLOG'!L:L,MATCH($B30,'Proposta Tabela PROLOG'!$B:$B,0)) -> 112.3 | L30: =INDEX('Proposta Tabela PROLOG'!AL:AL,MATCH($B30,'Proposta Tabela PROLOG'!$B:$B,0)) -> 77.67338 | M30: =INDEX('Proposta Tabela PROLOG'!M:M,MATCH($B30,'Proposta Tabela PROLOG'!$B:$B,0)) -> 131.02 | N30: =INDEX('Proposta Tabela PROLOG'!AM:AM,MATCH($B30,'Proposta Tabela PROLOG'!$B:$B,0)) -> 82.541232
B31: Nova Iguaçu | C31: =INDEX('Proposta Tabela PROLOG'!H:H,MATCH($B31,'Proposta Tabela PROLOG'!$B:$B,0)) -> 46.98 | D31: =INDEX('Proposta Tabela PROLOG'!AH:AH,MATCH($B31,'Proposta Tabela PROLOG'!$B:$B,0)) -> 51.117887 | E31: =INDEX('Proposta Tabela PROLOG'!I:I,MATCH($B31,'Proposta Tabela PROLOG'!$B:$B,0)) -> 82.21 | F31: =INDEX('Proposta Tabela PROLOG'!AI:AI,MATCH($B31,'Proposta Tabela PROLOG'!$B:$B,0)) -> 66.681357 | G31: =INDEX('Proposta Tabela PROLOG'!J:J,MATCH($B31,'Proposta Tabela PROLOG'!$B:$B,0)) -> 93.97 | H31: =INDEX('Proposta Tabela PROLOG'!AJ:AJ,MATCH($B31,'Proposta Tabela PROLOG'!$B:$B,0)) -> 74.208132 | I31: =INDEX('Proposta Tabela PROLOG'!K:K,MATCH($B31,'Proposta Tabela PROLOG'!$B:$B,0)) -> 93.97 | J31: =INDEX('Proposta Tabela PROLOG'!AK:AK,MATCH($B31,'Proposta Tabela PROLOG'!$B:$B,0)) -> 72.423696 | K31: =INDEX('Proposta Tabela PROLOG'!L:L,MATCH($B31,'Proposta Tabela PROLOG'!$B:$B,0)) -> 112.3 | L31: =INDEX('Proposta Tabela PROLOG'!AL:AL,MATCH($B31,'Proposta Tabela PROLOG'!$B:$B,0)) -> 77.67338 | M31: =INDEX('Proposta Tabela PROLOG'!M:M,MATCH($B31,'Proposta Tabela PROLOG'!$B:$B,0)) -> 131.02 | N31: =INDEX('Proposta Tabela PROLOG'!AM:AM,MATCH($B31,'Proposta Tabela PROLOG'!$B:$B,0)) -> 82.541232
B32: Niterói | C32: =INDEX('Proposta Tabela PROLOG'!H:H,MATCH($B32,'Proposta Tabela PROLOG'!$B:$B,0)) -> 57.47 | D32: =INDEX('Proposta Tabela PROLOG'!AH:AH,MATCH($B32,'Proposta Tabela PROLOG'!$B:$B,0)) -> 51.117887 | E32: =INDEX('Proposta Tabela PROLOG'!I:I,MATCH($B32,'Proposta Tabela PROLOG'!$B:$B,0)) -> 100.58 | F32: =INDEX('Proposta Tabela PROLOG'!AI:AI,MATCH($B32,'Proposta Tabela PROLOG'!$B:$B,0)) -> 66.681357 | G32: =INDEX('Proposta Tabela PROLOG'!J:J,MATCH($B32,'Proposta Tabela PROLOG'!$B:$B,0)) -> 114.95 | H32: =INDEX('Proposta Tabela PROLOG'!AJ:AJ,MATCH($B32,'Proposta Tabela PROLOG'!$B:$B,0)) -> 74.208132 | I32: =INDEX('Proposta Tabela PROLOG'!K:K,MATCH($B32,'Proposta Tabela PROLOG'!$B:$B,0)) -> 114.95 | J32: =INDEX('Proposta Tabela PROLOG'!AK:AK,MATCH($B32,'Proposta Tabela PROLOG'!$B:$B,0)) -> 72.423696 | K32: =INDEX('Proposta Tabela PROLOG'!L:L,MATCH($B32,'Proposta Tabela PROLOG'!$B:$B,0)) -> 128.14 | L32: =INDEX('Proposta Tabela PROLOG'!AL:AL,MATCH($B32,'Proposta Tabela PROLOG'!$B:$B,0)) -> 77.67338 | M32: =INDEX('Proposta Tabela PROLOG'!M:M,MATCH($B32,'Proposta Tabela PROLOG'!$B:$B,0)) -> 149.5 | N32: =INDEX('Proposta Tabela PROLOG'!AM:AM,MATCH($B32,'Proposta Tabela PROLOG'!$B:$B,0)) -> 82.541232
B33: Campos dos Goytacazes | C33: =INDEX('Proposta Tabela PROLOG'!H:H,MATCH($B33,'Proposta Tabela PROLOG'!$B:$B,0)) -> 124.04 | D33: =INDEX('Proposta Tabela PROLOG'!AH:AH,MATCH($B33,'Proposta Tabela PROLOG'!$B:$B,0)) -> 55.347887 | E33: =INDEX('Proposta Tabela PROLOG'!I:I,MATCH($B33,'Proposta Tabela PROLOG'!$B:$B,0)) -> 138.29 | F33: =INDEX('Proposta Tabela PROLOG'!AI:AI,MATCH($B33,'Proposta Tabela PROLOG'!$B:$B,0)) -> 73.511357 | G33: =INDEX('Proposta Tabela PROLOG'!J:J,MATCH($B33,'Proposta Tabela PROLOG'!$B:$B,0)) -> 143.04 | H33: =INDEX('Proposta Tabela PROLOG'!AJ:AJ,MATCH($B33,'Proposta Tabela PROLOG'!$B:$B,0)) -> 82.348132 | I33: =INDEX('Proposta Tabela PROLOG'!K:K,MATCH($B33,'Proposta Tabela PROLOG'!$B:$B,0)) -> 152.54 | J33: =INDEX('Proposta Tabela PROLOG'!AK:AK,MATCH($B33,'Proposta Tabela PROLOG'!$B:$B,0)) -> 84.763696 | K33: =INDEX('Proposta Tabela PROLOG'!L:L,MATCH($B33,'Proposta Tabela PROLOG'!$B:$B,0)) -> 162.04 | L33: =INDEX('Proposta Tabela PROLOG'!AL:AL,MATCH($B33,'Proposta Tabela PROLOG'!$B:$B,0)) -> 90.27338 | M33: =INDEX('Proposta Tabela PROLOG'!M:M,MATCH($B33,'Proposta Tabela PROLOG'!$B:$B,0)) -> 171.54 | N33: =INDEX('Proposta Tabela PROLOG'!AM:AM,MATCH($B33,'Proposta Tabela PROLOG'!$B:$B,0)) -> 96.191232
B34: Belford Roxo | C34: =INDEX('Proposta Tabela PROLOG'!H:H,MATCH($B34,'Proposta Tabela PROLOG'!$B:$B,0)) -> 46.98 | D34: =INDEX('Proposta Tabela PROLOG'!AH:AH,MATCH($B34,'Proposta Tabela PROLOG'!$B:$B,0)) -> 51.117887 | E34: =INDEX('Proposta Tabela PROLOG'!I:I,MATCH($B34,'Proposta Tabela PROLOG'!$B:$B,0)) -> 82.21 | F34: =INDEX('Proposta Tabela PROLOG'!AI:AI,MATCH($B34,'Proposta Tabela PROLOG'!$B:$B,0)) -> 66.681357 | G34: =INDEX('Proposta Tabela PROLOG'!J:J,MATCH($B34,'Proposta Tabela PROLOG'!$B:$B,0)) -> 93.97 | H34: =INDEX('Proposta Tabela PROLOG'!AJ:AJ,MATCH($B34,'Proposta Tabela PROLOG'!$B:$B,0)) -> 74.208132 | I34: =INDEX('Proposta Tabela PROLOG'!K:K,MATCH($B34,'Proposta Tabela PROLOG'!$B:$B,0)) -> 93.97 | J34: =INDEX('Proposta Tabela PROLOG'!AK:AK,MATCH($B34,'Proposta Tabela PROLOG'!$B:$B,0)) -> 72.423696 | K34: =INDEX('Proposta Tabela PROLOG'!L:L,MATCH($B34,'Proposta Tabela PROLOG'!$B:$B,0)) -> 112.3 | L34: =INDEX('Proposta Tabela PROLOG'!AL:AL,MATCH($B34,'Proposta Tabela PROLOG'!$B:$B,0)) -> 77.67338 | M34: =INDEX('Proposta Tabela PROLOG'!M:M,MATCH($B34,'Proposta Tabela PROLOG'!$B:$B,0)) -> 131.02 | N34: =INDEX('Proposta Tabela PROLOG'!AM:AM,MATCH($B34,'Proposta Tabela PROLOG'!$B:$B,0)) -> 82.541232
B35: Macaé | C35: =INDEX('Proposta Tabela PROLOG'!H:H,MATCH($B35,'Proposta Tabela PROLOG'!$B:$B,0)) -> 124.04 | D35: =INDEX('Proposta Tabela PROLOG'!AH:AH,MATCH($B35,'Proposta Tabela PROLOG'!$B:$B,0)) -> 55.347887 | E35: =INDEX('Proposta Tabela PROLOG'!I:I,MATCH($B35,'Proposta Tabela PROLOG'!$B:$B,0)) -> 138.29 | F35: =INDEX('Proposta Tabela PROLOG'!AI:AI,MATCH($B35,'Proposta Tabela PROLOG'!$B:$B,0)) -> 73.511357 | G35: =INDEX('Proposta Tabela PROLOG'!J:J,MATCH($B35,'Proposta Tabela PROLOG'!$B:$B,0)) -> 143.04 | H35: =INDEX('Proposta Tabela PROLOG'!AJ:AJ,MATCH($B35,'Proposta Tabela PROLOG'!$B:$B,0)) -> 82.348132 | I35: =INDEX('Proposta Tabela PROLOG'!K:K,MATCH($B35,'Proposta Tabela PROLOG'!$B:$B,0)) -> 152.54 | J35: =INDEX('Proposta Tabela PROLOG'!AK:AK,MATCH($B35,'Proposta Tabela PROLOG'!$B:$B,0)) -> 84.763696 | K35: =INDEX('Proposta Tabela PROLOG'!L:L,MATCH($B35,'Proposta Tabela PROLOG'!$B:$B,0)) -> 162.04 | L35: =INDEX('Proposta Tabela PROLOG'!AL:AL,MATCH($B35,'Proposta Tabela PROLOG'!$B:$B,0)) -> 90.27338 | M35: =INDEX('Proposta Tabela PROLOG'!M:M,MATCH($B35,'Proposta Tabela PROLOG'!$B:$B,0)) -> 171.54 | N35: =INDEX('Proposta Tabela PROLOG'!AM:AM,MATCH($B35,'Proposta Tabela PROLOG'!$B:$B,0)) -> 96.191232
B36: Tabela completa (93 faixas de CEP × 13 faixas de peso) na aba "Proposta Tabela PROLOG".
B38: QUADRO 4 — SIMULADOR DE PROPOSTA (altere as células amarelas) | H38: o resultado recalcula sobre os 2.223 pedidos
B39: Parâmetro da proposta | C39: Valor | E39: Região | F39: Preço médio PROPOSTA | G39: PROPOSTA vs OUTRO PARCEIRO | H39: Cotações ganhas
B40: Redução linear no frete peso (%) | C40: 0.33 | E40: Capital | F40: =AVERAGEIFS(Pedidos!$AI$2:$AI$2224,Pedidos!$E$2:$E$2224,"Capital") -> 109.32065 | G40: =SUMIFS(Pedidos!$AI$2:$AI$2224,Pedidos!$E$2:$E$2224,"Capital")/SUMIFS(Pedidos!$S$2:$S$2224,Pedidos!$E$2:$E$2224,"Capital")-1 -> 0.02700456 | H40: =COUNTIFS(Pedidos!$E$2:$E$2224,"Capital",Pedidos!$AJ$2:$AJ$2224,"SIM")/COUNTIFS(Pedidos!$E$2:$E$2224,"Capital") -> 0.37961165
B41: TAS (R$ por pedido) — hoje R$ 1,00 | C41: 1 | E41: Metropolitana | F41: =AVERAGEIFS(Pedidos!$AI$2:$AI$2224,Pedidos!$E$2:$E$2224,"Metropolitana") -> 120.91249 | G41: =SUMIFS(Pedidos!$AI$2:$AI$2224,Pedidos!$E$2:$E$2224,"Metropolitana")/SUMIFS(Pedidos!$S$2:$S$2224,Pedidos!$E$2:$E$2224,"Metropolitana")-1 -> -0.049883525 | H41: =COUNTIFS(Pedidos!$E$2:$E$2224,"Metropolitana",Pedidos!$AJ$2:$AJ$2224,"SIM")/COUNTIFS(Pedidos!$E$2:$E$2224,"Metropolitana") -> 0.77490775
B42: Pedágio (R$ por 100 kg) — hoje R$ 4,50 | C42: 1.05 | E42: Interior | F42: =AVERAGEIFS(Pedidos!$AI$2:$AI$2224,Pedidos!$E$2:$E$2224,"Interior") -> 141.04962 | G42: =SUMIFS(Pedidos!$AI$2:$AI$2224,Pedidos!$E$2:$E$2224,"Interior")/SUMIFS(Pedidos!$S$2:$S$2224,Pedidos!$E$2:$E$2224,"Interior")-1 -> 0.01041218 | H42: =COUNTIFS(Pedidos!$E$2:$E$2224,"Interior",Pedidos!$AJ$2:$AJ$2224,"SIM")/COUNTIFS(Pedidos!$E$2:$E$2224,"Interior") -> 0.56989247
B43: CTe (R$ por kg) — hoje R$ 0,06 | C43: 0 | E43: TOTAL | F43: =AVERAGEIFS(Pedidos!$AI$2:$AI$2224,Pedidos!$E$2:$E$2224,"<>") -> 121.43866 | G43: =SUMIFS(Pedidos!$AI$2:$AI$2224,Pedidos!$E$2:$E$2224,"<>")/SUMIFS(Pedidos!$S$2:$S$2224,Pedidos!$E$2:$E$2224,"<>")-1 -> 0.0017301598 | H43: =COUNTIFS(Pedidos!$E$2:$E$2224,"<>",Pedidos!$AJ$2:$AJ$2224,"SIM")/COUNTIFS(Pedidos!$E$2:$E$2224,"<>") -> 0.5317139
B44: A taxa interna do embarcador (R$ 0,45/kg) e o ICMS 12% são mantidos — iguais para todos os parceiros.
B46: Cenários prontos de redução do frete peso (com TAS, pedágio e CTe do simulador)
B47: Redução no frete peso | C47: PROLOG vs OUTRO PARCEIRO | D47: Cotações ganhas
B48: 0 | C48: =(SUM(Pedidos!$AI$2:$AI$2224)+SUM(Pedidos!$T$2:$T$2224)*($C$40-B48)/(1-Resumo!$B$5))/SUM(Pedidos!$S$2:$S$2224)-1 -> 0.37199086 | D48: =SUMPRODUCT(--(Pedidos!$AI$2:$AI$2224+Pedidos!$T$2:$T$2224*($C$40-B48)/(1-Resumo!$B$5)<Pedidos!$S$2:$S$2224))/COUNTA(Pedidos!$D$2:$D$2224) -> 0.0072007201
B49: 0.2 | C49: =(SUM(Pedidos!$AI$2:$AI$2224)+SUM(Pedidos!$T$2:$T$2224)*($C$40-B49)/(1-Resumo!$B$5))/SUM(Pedidos!$S$2:$S$2224)-1 -> 0.14759043 | D49: =SUMPRODUCT(--(Pedidos!$AI$2:$AI$2224+Pedidos!$T$2:$T$2224*($C$40-B49)/(1-Resumo!$B$5)<Pedidos!$S$2:$S$2224))/COUNTA(Pedidos!$D$2:$D$2224) -> 0.11836184
B50: 0.25 | C50: =(SUM(Pedidos!$AI$2:$AI$2224)+SUM(Pedidos!$T$2:$T$2224)*($C$40-B50)/(1-Resumo!$B$5))/SUM(Pedidos!$S$2:$S$2224)-1 -> 0.091490329 | D50: =SUMPRODUCT(--(Pedidos!$AI$2:$AI$2224+Pedidos!$T$2:$T$2224*($C$40-B50)/(1-Resumo!$B$5)<Pedidos!$S$2:$S$2224))/COUNTA(Pedidos!$D$2:$D$2224) -> 0.18991899
B51: 0.3 | C51: =(SUM(Pedidos!$AI$2:$AI$2224)+SUM(Pedidos!$T$2:$T$2224)*($C$40-B51)/(1-Resumo!$B$5))/SUM(Pedidos!$S$2:$S$2224)-1 -> 0.035390223 | D51: =SUMPRODUCT(--(Pedidos!$AI$2:$AI$2224+Pedidos!$T$2:$T$2224*($C$40-B51)/(1-Resumo!$B$5)<Pedidos!$S$2:$S$2224))/COUNTA(Pedidos!$D$2:$D$2224) -> 0.35328533
B52: 0.35 | C52: =(SUM(Pedidos!$AI$2:$AI$2224)+SUM(Pedidos!$T$2:$T$2224)*($C$40-B52)/(1-Resumo!$B$5))/SUM(Pedidos!$S$2:$S$2224)-1 -> -0.020709882 | D52: =SUMPRODUCT(--(Pedidos!$AI$2:$AI$2224+Pedidos!$T$2:$T$2224*($C$40-B52)/(1-Resumo!$B$5)<Pedidos!$S$2:$S$2224))/COUNTA(Pedidos!$D$2:$D$2224) -> 0.6759676
B53: 0.4 | C53: =(SUM(Pedidos!$AI$2:$AI$2224)+SUM(Pedidos!$T$2:$T$2224)*($C$40-B53)/(1-Resumo!$B$5))/SUM(Pedidos!$S$2:$S$2224)-1 -> -0.076809988 | D53: =SUMPRODUCT(--(Pedidos!$AI$2:$AI$2224+Pedidos!$T$2:$T$2224*($C$40-B53)/(1-Resumo!$B$5)<Pedidos!$S$2:$S$2224))/COUNTA(Pedidos!$D$2:$D$2224) -> 0.84248425
B55: QUADRO 5 — O QUE A PROLOG PRECISA FAZER
B56: 1. FRETE PESO | C56: É o que mais pesa na diferença. A redução necessária para empatar está no Quadro 1, coluna I. Prioridade: Capital (46% dos pedidos), depois Interior (Macaé e Campos).
B57: 2. PEDÁGIO | C57: Passar de R$ 4,50 para cerca de R$ 1,05 a cada 100 kg (≈ R$ 3,70 por pedido).
B58: 3. CTe POR KG | C58: Zerar o CTe de R$ 0,06/kg (≈ R$ 3,00 por pedido).
B59: 4. MANTER A TAS | C59: A TAS de R$ 1,00 é a maior vantagem da PROLOG: o parceiro cobra CTe fixo de R$ 13,55 por pedido. Não trocar por taxa fixa maior.
B60: 5. PRAZO | C60: Na Capital e na Metropolitana o parceiro entrega em 2 dias úteis (PROLOG: 5 a 7). No Interior a PROLOG é mais rápida (6 a 11 contra 13).
B61: 6. EXCEDENTE > 250 kg | C61: Rever o excedente de R$ 7,71 a R$ 12,05/kg (mercado ≈ R$ 1,00 a R$ 1,35/kg).
B62: 7. FAIXAS LEVES | C62: Até 20 kg a PROLOG já está perto (≈ +10%); na Metropolitana até 20 kg empata. Bom ponto de partida.
B64: GRÁFICOS

Sheet Resumo
A1: PROLOG FILIAL SP x OUTRO PARCEIRO — pedidos RJ, origem FILIAL SP, jul–set/2026
A3: PREMISSAS (células em azul podem ser alteradas — todas as abas recalculam)
A4: Parâmetro | B4: PROLOG | C4: OUTRO PARCEIRO | D4: Fonte / observação
A5: ICMS por fora (total = subtotal / (1 − alíquota)) | B5: 0.12 | C5: 0.12 | D5: Confirmado: 12% por fora. Ambas as tabelas com "ICMS incluso = N".
A6: Ad valorem / frete valor (% NF) | B6: 0.001 | C6: 0 | D6: Tabelas Intelipost
A7: GRIS (% NF) | B7: 0.002 | C7: 0.0021 | D7: Tabelas Intelipost
A8: Seguro (% NF) | B8: 0 | C8: 0.0021 | D8: Tabela OUTRO PARCEIRO
A9: TAS / entrega fixo (R$ por pedido) | B9: 1 | C9: 0 | D9: PROLOG: TAS R$ 1,00
A10: Pedágio (R$ por fração de 100 kg) | B10: 4.5 | C10: 1.05 | D10: Tabelas Intelipost
A11: TRT (% sobre o subtotal) | B11: 0 | C11: 0 | D11: Nenhuma das duas tabelas cobra TRT
A12: CTe por kg (R$/kg) | B12: 0.06 | C12: 0 | D12: PROLOG: CTE FIXO 0,06 com faixa de 1 kg
A13: CTe fixo (R$ por pedido) | B13: 0 | C13: 13.55 | D13: OUTRO PARCEIRO: CTE VALOR FIXO R$ 13,55
A14: Taxa interna (R$ por kg) — levar o produto até a filial SP | B14: 0.45 | C14: 0.45 | D14: Taxa do embarcador, obrigatória e IGUAL para todos os parceiros (não negociável) — lançada como "outra taxa"
A15: Cubagem (kg/m³) | B15: 0 | C15: 300 | D15: Sem dimensões na base: simulado por peso real
A18: VISÃO GERAL — os mesmos 2.223 pedidos cotados pelas duas tabelas
A19: Indicador | B19: OUTRO PARCEIRO | C19: PROLOG FILIAL SP | D19: Diferença
A20: Pedidos | B20: =COUNTA(Pedidos!$D$2:$D$2224) -> 2222 | C20: =COUNTA(Pedidos!$D$2:$D$2224) -> 2222
A21: Custo total de frete | B21: =SUM(Pedidos!$S$2:$S$2224) -> 269491.88 | C21: =SUM(Pedidos!$AB$2:$AB$2224) -> 386659.64 | D21: =C21/B21-1 -> 0.4347729
A22: Custo médio por pedido | B22: =AVERAGE(Pedidos!$S$2:$S$2224) -> 121.22891 | C22: =AVERAGE(Pedidos!$AB$2:$AB$2224) -> 173.93596 | D22: =C22/B22-1 -> 0.4347729
A23: Frete / NF | B23: =SUM(Pedidos!$S$2:$S$2224)/SUM(Pedidos!$H$2:$H$2224) -> 0.18887878 | C23: =SUM(Pedidos!$AB$2:$AB$2224)/SUM(Pedidos!$H$2:$H$2224) -> 0.27099816 | D23: =C23-B23 -> 0.082119375
A24: % pedidos em que a PROLOG ganharia a cotação | C24: =COUNTIF(Pedidos!$AE$2:$AE$2224,"SIM")/B20 -> 0.0067506751
A25: Prazo médio (dias úteis) | B25: =AVERAGE(Pedidos!$AF$2:$AF$2224) -> 5.2213225 | C25: =AVERAGE(Pedidos!$AG$2:$AG$2224) -> 6.4669366 | D25: =C25-B25 -> 1.245614
A30: DE ONDE VEM A DIFERENÇA — média por pedido (R$)
A31: Componente | B31: OUTRO PARCEIRO | C31: PROLOG | D31: PROLOG − OUTRO PARCEIRO | E31: % da diferença
A32: Frete peso | B32: =AVERAGE(Pedidos!$I$2:$I$2224) -> 66.692083 | C32: =AVERAGE(Pedidos!$T$2:$T$2224) -> 119.69681 | D32: =C32-B32 -> 53.004723 | E32: =D32/$D$43 -> 1.0056478
A33: Ad valorem | B33: =AVERAGE(Pedidos!$J$2:$J$2224) -> 0 | C33: =AVERAGE(Pedidos!$U$2:$U$2224) -> 0.64183448 | D33: =C33-B33 -> 0.64183448 | E33: =D33/$D$43 -> 0.012177394
A34: GRIS | B34: =AVERAGE(Pedidos!$K$2:$K$2224) -> 1.3478524 | C34: =AVERAGE(Pedidos!$V$2:$V$2224) -> 1.283669 | D34: =C34-B34 -> -0.064183448 | E34: =D34/$D$43 -> -0.0012177394
A35: Seguro | B35: =AVERAGE(Pedidos!$L$2:$L$2224) -> 1.3478524 | C35: 0 | D35: =C35-B35 -> -1.3478524 | E35: =D35/$D$43 -> -0.025572528
A36: TAS / entrega | B36: =AVERAGE(Pedidos!$N$2:$N$2224) -> 0 | C36: =AVERAGE(Pedidos!$W$2:$W$2224) -> 1 | D36: =C36-B36 -> 1 | E36: =D36/$D$43 -> 0.018972795
A37: Pedágio | B37: =AVERAGE(Pedidos!$M$2:$M$2224) -> 1.1203779 | C37: =AVERAGE(Pedidos!$X$2:$X$2224) -> 4.8016194 | D37: =C37-B37 -> 3.6812416 | E37: =D37/$D$43 -> 0.069843443
A38: CTe (OUTRO PARCEIRO fixo R$ 13,55 / PROLOG R$ 0,06 por kg) | B38: =AVERAGE(Pedidos!$O$2:$O$2224) -> 13.55 | C38: =AVERAGE(Pedidos!$Y$2:$Y$2224) -> 3.0164372 | D38: =C38-B38 -> -10.533563 | E38: =D38/$D$43 -> -0.19985113
A39: Taxa interna R$ 0,45/kg | B39: =AVERAGE(Pedidos!$P$2:$P$2224) -> 22.623279 | C39: =AVERAGE(Pedidos!$Z$2:$Z$2224) -> 22.623279 | D39: =C39-B39 -> 0 | E39: =D39/$D$43 -> 0
A40: TRT | B40: =AVERAGE(Pedidos!$Q$2:$Q$2224) -> 0 | C40: 0 | D40: =C40-B40 -> 0 | E40: =D40/$D$43 -> 0
A41: ICMS 12% por fora | B41: =AVERAGE(Pedidos!$S$2:$S$2224)-AVERAGE(Pedidos!$R$2:$R$2224) -> 14.54747 | C41: =AVERAGE(Pedidos!$AB$2:$AB$2224)-AVERAGE(Pedidos!$AA$2:$AA$2224) -> 20.872315 | D41: =C41-B41 -> 6.3248456 | E41: =D41/$D$43 -> 0.12
A43: TOTAL | B43: =SUM(B32:B41) -> 121.22891 | C43: =SUM(C32:C41) -> 173.93596 | D43: =C43-B43 -> 52.707046 | E43: =D43/$D$43 -> 1

Sheet Comparativo Tabelas
A1: Estrutura das tabelas — principais diferenças (OUTRO PARCEIRO = tabela atualizada 17/07/2026)
A3: Item | B3: PROLOG FILIAL SP | C3: OUTRO PARCEIRO | D3: Quem leva vantagem | E3: Comentário / oportunidade
A4: Regionalização do RJ | B4: 93 faixas de CEP, 9 níveis de preço | C4: 93 faixas de CEP, 3 níveis: Capital, Metropolitana (10 faixas), Interior (82) | D4: — | E4: OUTRO PARCEIRO tem preço único por região; a PROLOG pode ser agressiva onde tem operação própria
A5: Frete peso — Capital até 20 kg | B5: R$ 46,98 | C5: R$ 33,42 | D5: OUTRO PARCEIRO | E5: +41%
A6: Frete peso — Capital 20 a 35 kg | B6: R$ 82,21 | C6: R$ 42,11 | D6: OUTRO PARCEIRO | E6: +95% — maior gap de valor (faixa mais vendida da capital)
A7: Frete peso — Capital 40 a 50 kg | B7: R$ 93,97 | C7: R$ 53,55 | D7: OUTRO PARCEIRO | E7: +75%
A8: Frete peso — Capital 50 a 60 kg | B8: R$ 112,30 | C8: R$ 58,60 | D8: OUTRO PARCEIRO | E8: +92%
A9: Frete peso — Capital 60 a 70 kg | B9: R$ 131,02 | C9: R$ 63,21 | D9: OUTRO PARCEIRO | E9: +107%
A10: Taxa fixa por pedido | B10: TAS R$ 1,00 | C10: CTe fixo R$ 13,55 | D10: PROLOG | E10: R$ 12,55 a menos por pedido — é a única vantagem relevante da PROLOG em taxas
A11: CTe por kg | B11: R$ 0,06 / kg | C11: não cobra | D11: OUTRO PARCEIRO | E11: ≈ R$ 3,00 por pedido; trocar por fixo ou zerar
A12: Taxa interna do embarcador | B12: R$ 0,45 / kg | C12: R$ 0,45 / kg | D12: Empate | E12: Igual para todos os parceiros, não negociável
A13: Ad valorem / Seguro | B13: 0,10% NF (ad valorem) | C13: 0,21% NF (seguro) | D13: PROLOG | E13: ≈ R$ 0,70 a favor
A14: GRIS | B14: 0,20% NF | C14: 0,21% NF | D14: PROLOG | E14: Pequeno
A15: TRT | B15: não cobra | C15: não cobra | D15: Empate
A16: Pedágio | B16: R$ 4,50 / 100 kg | C16: R$ 1,05 / 100 kg | D16: OUTRO PARCEIRO | E16: R$ 3,45 a mais por pedido — fácil de negociar
A17: Cubagem | B17: não aplica (0) | C17: 300 kg/m³ | D17: PROLOG | E17: Vantagem para volumosos (não medida: base sem dimensões)
A18: Excedente acima de 250 kg | B18: R$ 7,71 a 12,05 / kg | C18: R$ 0,96 a 1,34 / kg | D18: OUTRO PARCEIRO | E18: Sem pedidos acima de 250 kg; ainda assim fora de mercado
A19: Prazo — Capital e Metropolitana | B19: 5 a 7 dias úteis | C19: 2 dias úteis | D19: OUTRO PARCEIRO | E19: O OUTRO PARCEIRO oferece 2 du: a PROLOG perdeu a vantagem de prazo nas regiões de maior volume
A20: Prazo — Interior | B20: 6 a 11 dias úteis | C20: 13 dias úteis | D20: PROLOG | E20: 2 a 7 dias mais rápido

Sheet Top 20 Cidades
A1: Top 20 cidades RJ — preço final (com taxas e ICMS) PROLOG x OUTRO PARCEIRO nos mesmos pedidos
A3: # | B3: Cidade | C3: Região OUTRO PARCEIRO | D3: Pedidos | E3: % pedidos RJ | F3: Peso médio (kg) | G3: NF média | H3: OUTRO PARCEIRO médio | I3: PROLOG médio | J3: PROLOG vs OUTRO PARCEIRO | K3: Frete/NF OUTRO PARCEIRO | L3: Frete/NF PROLOG | M3: % pedidos PROLOG ganharia | N3: Frete peso PROLOG vs OUTRO PARCEIRO | O3: Prazo OUTRO PARCEIRO | P3: Prazo PROLOG | Q3: Redução necessária no preço PROLOG p/ empatar | R3: Avaliação
A4: 1 | B4: Rio de Janeiro | C4: =INDEX(Pedidos!$E$2:$E$2224,MATCH($B4,Pedidos!$D$2:$D$2224,0)) -> Capital | D4: =COUNTIFS(Pedidos!$D$2:$D$2224,$B4) -> 1030 | E4: =D4/Resumo!$B$20 -> 0.46354635 | F4: =AVERAGEIFS(Pedidos!$G$2:$G$2224,Pedidos!$D$2:$D$2224,$B4) -> 47.579631 | G4: =AVERAGEIFS(Pedidos!$H$2:$H$2224,Pedidos!$D$2:$D$2224,$B4) -> 617.43493 | H4: =AVERAGEIFS(Pedidos!$S$2:$S$2224,Pedidos!$D$2:$D$2224,$B4) -> 106.44612 | I4: =AVERAGEIFS(Pedidos!$AB$2:$AB$2224,Pedidos!$D$2:$D$2224,$B4) -> 156.29299 | J4: =I4/H4-1 -> 0.46828261 | K4: =SUMIFS(Pedidos!$S$2:$S$2224,Pedidos!$D$2:$D$2224,$B4)/SUMIFS(Pedidos!$H$2:$H$2224,Pedidos!$D$2:$D$2224,$B4) -> 0.17240055 | L4: =SUMIFS(Pedidos!$AB$2:$AB$2224,Pedidos!$D$2:$D$2224,$B4)/SUMIFS(Pedidos!$H$2:$H$2224,Pedidos!$D$2:$D$2224,$B4) -> 0.25313273 | M4: =COUNTIFS(Pedidos!$D$2:$D$2224,$B4,Pedidos!$AE$2:$AE$2224,"SIM")/D4 -> 0 | N4: =SUMIFS(Pedidos!$T$2:$T$2224,Pedidos!$D$2:$D$2224,$B4)/SUMIFS(Pedidos!$I$2:$I$2224,Pedidos!$D$2:$D$2224,$B4)-1 -> 0.923291 | O4: =AVERAGEIFS(Pedidos!$AF$2:$AF$2224,Pedidos!$D$2:$D$2224,$B4) -> 2 | P4: =AVERAGEIFS(Pedidos!$AG$2:$AG$2224,Pedidos!$D$2:$D$2224,$B4) -> 5 | Q4: =MAX(0,1-H4/I4) -> 0.31893221 | R4: =IF(J4<=0,"Muito bem",IF(J4<=0.32,"Melhor posição",IF(J4<=0.45,"Intermediária","Precisa melhorar"))) -> Precisa melhorar
A5: 2 | B5: São Gonçalo | C5: =INDEX(Pedidos!$E$2:$E$2224,MATCH($B5,Pedidos!$D$2:$D$2224,0)) -> Metropolitana | D5: =COUNTIFS(Pedidos!$D$2:$D$2224,$B5) -> 135 | E5: =D5/Resumo!$B$20 -> 0.060756076 | F5: =AVERAGEIFS(Pedidos!$G$2:$G$2224,Pedidos!$D$2:$D$2224,$B5) -> 50.268593 | G5: =AVERAGEIFS(Pedidos!$H$2:$H$2224,Pedidos!$D$2:$D$2224,$B5) -> 636.66911 | H5: =AVERAGEIFS(Pedidos!$S$2:$S$2224,Pedidos!$D$2:$D$2224,$B5) -> 124.74227 | I5: =AVERAGEIFS(Pedidos!$AB$2:$AB$2224,Pedidos!$D$2:$D$2224,$B5) -> 180.34462 | J5: =I5/H5-1 -> 0.44573788 | K5: =SUMIFS(Pedidos!$S$2:$S$2224,Pedidos!$D$2:$D$2224,$B5)/SUMIFS(Pedidos!$H$2:$H$2224,Pedidos!$D$2:$D$2224,$B5) -> 0.19592951 | L5: =SUMIFS(Pedidos!$AB$2:$AB$2224,Pedidos!$D$2:$D$2224,$B5)/SUMIFS(Pedidos!$H$2:$H$2224,Pedidos!$D$2:$D$2224,$B5) -> 0.28326272 | M5: =COUNTIFS(Pedidos!$D$2:$D$2224,$B5,Pedidos!$AE$2:$AE$2224,"SIM")/D5 -> 0 | N5: =SUMIFS(Pedidos!$T$2:$T$2224,Pedidos!$D$2:$D$2224,$B5)/SUMIFS(Pedidos!$I$2:$I$2224,Pedidos!$D$2:$D$2224,$B5)-1 -> 0.79754425 | O5: =AVERAGEIFS(Pedidos!$AF$2:$AF$2224,Pedidos!$D$2:$D$2224,$B5) -> 2 | P5: =AVERAGEIFS(Pedidos!$AG$2:$AG$2224,Pedidos!$D$2:$D$2224,$B5) -> 7 | Q5: =MAX(0,1-H5/I5) -> 0.30831168 | R5: =IF(J5<=0,"Muito bem",IF(J5<=0.32,"Melhor posição",IF(J5<=0.45,"Intermediária","Precisa melhorar"))) -> Intermediária
A6: 3 | B6: Duque de Caxias | C6: =INDEX(Pedidos!$E$2:$E$2224,MATCH($B6,Pedidos!$D$2:$D$2224,0)) -> Metropolitana | D6: =COUNTIFS(Pedidos!$D$2:$D$2224,$B6) -> 106 | E6: =D6/Resumo!$B$20 -> 0.04770477 | F6: =AVERAGEIFS(Pedidos!$G$2:$G$2224,Pedidos!$D$2:$D$2224,$B6) -> 52.422453 | G6: =AVERAGEIFS(Pedidos!$H$2:$H$2224,Pedidos!$D$2:$D$2224,$B6) -> 663.55302 | H6: =AVERAGEIFS(Pedidos!$S$2:$S$2224,Pedidos!$D$2:$D$2224,$B6) -> 127.67403 | I6: =AVERAGEIFS(Pedidos!$AB$2:$AB$2224,Pedidos!$D$2:$D$2224,$B6) -> 166.37382 | J6: =I6/H6-1 -> 0.30311399 | K6: =SUMIFS(Pedidos!$S$2:$S$2224,Pedidos!$D$2:$D$2224,$B6)/SUMIFS(Pedidos!$H$2:$H$2224,Pedidos!$D$2:$D$2224,$B6) -> 0.19240969 | L6: =SUMIFS(Pedidos!$AB$2:$AB$2224,Pedidos!$D$2:$D$2224,$B6)/SUMIFS(Pedidos!$H$2:$H$2224,Pedidos!$D$2:$D$2224,$B6) -> 0.25073176 | M6: =COUNTIFS(Pedidos!$D$2:$D$2224,$B6,Pedidos!$AE$2:$AE$2224,"SIM")/D6 -> 0.056603774 | N6: =SUMIFS(Pedidos!$T$2:$T$2224,Pedidos!$D$2:$D$2224,$B6)/SUMIFS(Pedidos!$I$2:$I$2224,Pedidos!$D$2:$D$2224,$B6)-1 -> 0.56939029 | O6: =AVERAGEIFS(Pedidos!$AF$2:$AF$2224,Pedidos!$D$2:$D$2224,$B6) -> 2 | P6: =AVERAGEIFS(Pedidos!$AG$2:$AG$2224,Pedidos!$D$2:$D$2224,$B6) -> 5 | Q6: =MAX(0,1-H6/I6) -> 0.23260743 | R6: =IF(J6<=0,"Muito bem",IF(J6<=0.32,"Melhor posição",IF(J6<=0.45,"Intermediária","Precisa melhorar"))) -> Melhor posição
A7: 4 | B7: Nova Iguaçu | C7: =INDEX(Pedidos!$E$2:$E$2224,MATCH($B7,Pedidos!$D$2:$D$2224,0)) -> Metropolitana | D7: =COUNTIFS(Pedidos!$D$2:$D$2224,$B7) -> 95 | E7: =D7/Resumo!$B$20 -> 0.042754275 | F7: =AVERAGEIFS(Pedidos!$G$2:$G$2224,Pedidos!$D$2:$D$2224,$B7) -> 55.083474 | G7: =AVERAGEIFS(Pedidos!$H$2:$H$2224,Pedidos!$D$2:$D$2224,$B7) -> 676.70926 | H7: =AVERAGEIFS(Pedidos!$S$2:$S$2224,Pedidos!$D$2:$D$2224,$B7) -> 130.8124 | I7: =AVERAGEIFS(Pedidos!$AB$2:$AB$2224,Pedidos!$D$2:$D$2224,$B7) -> 172.30948 | J7: =I7/H7-1 -> 0.31722581 | K7: =SUMIFS(Pedidos!$S$2:$S$2224,Pedidos!$D$2:$D$2224,$B7)/SUMIFS(Pedidos!$H$2:$H$2224,Pedidos!$D$2:$D$2224,$B7) -> 0.19330666 | L7: =SUMIFS(Pedidos!$AB$2:$AB$2224,Pedidos!$D$2:$D$2224,$B7)/SUMIFS(Pedidos!$H$2:$H$2224,Pedidos!$D$2:$D$2224,$B7) -> 0.25462852 | M7: =COUNTIFS(Pedidos!$D$2:$D$2224,$B7,Pedidos!$AE$2:$AE$2224,"SIM")/D7 -> 0.021052632 | N7: =SUMIFS(Pedidos!$T$2:$T$2224,Pedidos!$D$2:$D$2224,$B7)/SUMIFS(Pedidos!$I$2:$I$2224,Pedidos!$D$2:$D$2224,$B7)-1 -> 0.58921342 | O7: =AVERAGEIFS(Pedidos!$AF$2:$AF$2224,Pedidos!$D$2:$D$2224,$B7) -> 2 | P7: =AVERAGEIFS(Pedidos!$AG$2:$AG$2224,Pedidos!$D$2:$D$2224,$B7) -> 5 | Q7: =MAX(0,1-H7/I7) -> 0.24082872 | R7: =IF(J7<=0,"Muito bem",IF(J7<=0.32,"Melhor posição",IF(J7<=0.45,"Intermediária","Precisa melhorar"))) -> Melhor posição
A8: 5 | B8: Niterói | C8: =INDEX(Pedidos!$E$2:$E$2224,MATCH($B8,Pedidos!$D$2:$D$2224,0)) -> Metropolitana | D8: =COUNTIFS(Pedidos!$D$2:$D$2224,$B8) -> 68 | E8: =D8/Resumo!$B$20 -> 0.03060306 | F8: =AVERAGEIFS(Pedidos!$G$2:$G$2224,Pedidos!$D$2:$D$2224,$B8) -> 47.945882 | G8: =AVERAGEIFS(Pedidos!$H$2:$H$2224,Pedidos!$D$2:$D$2224,$B8) -> 603.64809 | H8: =AVERAGEIFS(Pedidos!$S$2:$S$2224,Pedidos!$D$2:$D$2224,$B8) -> 122.03111 | I8: =AVERAGEIFS(Pedidos!$AB$2:$AB$2224,Pedidos!$D$2:$D$2224,$B8) -> 175.73135 | J8: =I8/H8-1 -> 0.44005367 | K8: =SUMIFS(Pedidos!$S$2:$S$2224,Pedidos!$D$2:$D$2224,$B8)/SUMIFS(Pedidos!$H$2:$H$2224,Pedidos!$D$2:$D$2224,$B8) -> 0.20215605 | L8: =SUMIFS(Pedidos!$AB$2:$AB$2224,Pedidos!$D$2:$D$2224,$B8)/SUMIFS(Pedidos!$H$2:$H$2224,Pedidos!$D$2:$D$2224,$B8) -> 0.29111556 | M8: =COUNTIFS(Pedidos!$D$2:$D$2224,$B8,Pedidos!$AE$2:$AE$2224,"SIM")/D8 -> 0 | N8: =SUMIFS(Pedidos!$T$2:$T$2224,Pedidos!$D$2:$D$2224,$B8)/SUMIFS(Pedidos!$I$2:$I$2224,Pedidos!$D$2:$D$2224,$B8)-1 -> 0.78989311 | O8: =AVERAGEIFS(Pedidos!$AF$2:$AF$2224,Pedidos!$D$2:$D$2224,$B8) -> 2 | P8: =AVERAGEIFS(Pedidos!$AG$2:$AG$2224,Pedidos!$D$2:$D$2224,$B8) -> 7 | Q8: =MAX(0,1-H8/I8) -> 0.30558143 | R8: =IF(J8<=0,"Muito bem",IF(J8<=0.32,"Melhor posição",IF(J8<=0.45,"Intermediária","Precisa melhorar"))) -> Intermediária
A9: 6 | B9: Campos dos Goytacazes | C9: =INDEX(Pedidos!$E$2:$E$2224,MATCH($B9,Pedidos!$D$2:$D$2224,0)) -> Interior | D9: =COUNTIFS(Pedidos!$D$2:$D$2224,$B9) -> 53 | E9: =D9/Resumo!$B$20 -> 0.023852385 | F9: =AVERAGEIFS(Pedidos!$G$2:$G$2224,Pedidos!$D$2:$D$2224,$B9) -> 49.475283 | G9: =AVERAGEIFS(Pedidos!$H$2:$H$2224,Pedidos!$D$2:$D$2224,$B9) -> 649.88434 | H9: =AVERAGEIFS(Pedidos!$S$2:$S$2224,Pedidos!$D$2:$D$2224,$B9) -> 136.62809 | I9: =AVERAGEIFS(Pedidos!$AB$2:$AB$2224,Pedidos!$D$2:$D$2224,$B9) -> 218.07379 | J9: =I9/H9-1 -> 0.59611238 | K9: =SUMIFS(Pedidos!$S$2:$S$2224,Pedidos!$D$2:$D$2224,$B9)/SUMIFS(Pedidos!$H$2:$H$2224,Pedidos!$D$2:$D$2224,$B9) -> 0.21023447 | L9: =SUMIFS(Pedidos!$AB$2:$AB$2224,Pedidos!$D$2:$D$2224,$B9)/SUMIFS(Pedidos!$H$2:$H$2224,Pedidos!$D$2:$D$2224,$B9) -> 0.33555785 | M9: =COUNTIFS(Pedidos!$D$2:$D$2224,$B9,Pedidos!$AE$2:$AE$2224,"SIM")/D9 -> 0 | N9: =SUMIFS(Pedidos!$T$2:$T$2224,Pedidos!$D$2:$D$2224,$B9)/SUMIFS(Pedidos!$I$2:$I$2224,Pedidos!$D$2:$D$2224,$B9)-1 -> 0.973722 | O9: =AVERAGEIFS(Pedidos!$AF$2:$AF$2224,Pedidos!$D$2:$D$2224,$B9) -> 13 | P9: =AVERAGEIFS(Pedidos!$AG$2:$AG$2224,Pedidos!$D$2:$D$2224,$B9) -> 11 | Q9: =MAX(0,1-H9/I9) -> 0.3734777 | R9: =IF(J9<=0,"Muito bem",IF(J9<=0.32,"Melhor posição",IF(J9<=0.45,"Intermediária","Precisa melhorar"))) -> Precisa melhorar
A10: 7 | B10: Belford Roxo | C10: =INDEX(Pedidos!$E$2:$E$2224,MATCH($B10,Pedidos!$D$2:$D$2224,0)) -> Metropolitana | D10: =COUNTIFS(Pedidos!$D$2:$D$2224,$B10) -> 49 | E10: =D10/Resumo!$B$20 -> 0.022052205 | F10: =AVERAGEIFS(Pedidos!$G$2:$G$2224,Pedidos!$D$2:$D$2224,$B10) -> 54.08 | G10: =AVERAGEIFS(Pedidos!$H$2:$H$2224,Pedidos!$D$2:$D$2224,$B10) -> 687.52816 | H10: =AVERAGEIFS(Pedidos!$S$2:$S$2224,Pedidos!$D$2:$D$2224,$B10) -> 128.46784 | I10: =AVERAGEIFS(Pedidos!$AB$2:$AB$2224,Pedidos!$D$2:$D$2224,$B10) -> 166.98856 | J10: =I10/H10-1 -> 0.29984716 | K10: =SUMIFS(Pedidos!$S$2:$S$2224,Pedidos!$D$2:$D$2224,$B10)/SUMIFS(Pedidos!$H$2:$H$2224,Pedidos!$D$2:$D$2224,$B10) -> 0.18685466 | L10: =SUMIFS(Pedidos!$AB$2:$AB$2224,Pedidos!$D$2:$D$2224,$B10)/SUMIFS(Pedidos!$H$2:$H$2224,Pedidos!$D$2:$D$2224,$B10) -> 0.2428825 | M10: =COUNTIFS(Pedidos!$D$2:$D$2224,$B10,Pedidos!$AE$2:$AE$2224,"SIM")/D10 -> 0.081632653 | N10: =SUMIFS(Pedidos!$T$2:$T$2224,Pedidos!$D$2:$D$2224,$B10)/SUMIFS(Pedidos!$I$2:$I$2224,Pedidos!$D$2:$D$2224,$B10)-1 -> 0.56848399 | O10: =AVERAGEIFS(Pedidos!$AF$2:$AF$2224,Pedidos!$D$2:$D$2224,$B10) -> 2 | P10: =AVERAGEIFS(Pedidos!$AG$2:$AG$2224,Pedidos!$D$2:$D$2224,$B10) -> 5 | Q10: =MAX(0,1-H10/I10) -> 0.23067878 | R10: =IF(J10<=0,"Muito bem",IF(J10<=0.32,"Melhor posição",IF(J10<=0.45,"Intermediária","Precisa melhorar"))) -> Melhor posição
A11: 8 | B11: Macaé | C11: =INDEX(Pedidos!$E$2:$E$2224,MATCH($B11,Pedidos!$D$2:$D$2224,0)) -> Interior | D11: =COUNTIFS(Pedidos!$D$2:$D$2224,$B11) -> 45 | E11: =D11/Resumo!$B$20 -> 0.020252025 | F11: =AVERAGEIFS(Pedidos!$G$2:$G$2224,Pedidos!$D$2:$D$2224,$B11) -> 60.060222 | G11: =AVERAGEIFS(Pedidos!$H$2:$H$2224,Pedidos!$D$2:$D$2224,$B11) -> 746.16467 | H11: =AVERAGEIFS(Pedidos!$S$2:$S$2224,Pedidos!$D$2:$D$2224,$B11) -> 149.95366 | I11: =AVERAGEIFS(Pedidos!$AB$2:$AB$2224,Pedidos!$D$2:$D$2224,$B11) -> 241.39778 | J11: =I11/H11-1 -> 0.60981583 | K11: =SUMIFS(Pedidos!$S$2:$S$2224,Pedidos!$D$2:$D$2224,$B11)/SUMIFS(Pedidos!$H$2:$H$2224,Pedidos!$D$2:$D$2224,$B11) -> 0.20096591 | L11: =SUMIFS(Pedidos!$AB$2:$AB$2224,Pedidos!$D$2:$D$2224,$B11)/SUMIFS(Pedidos!$H$2:$H$2224,Pedidos!$D$2:$D$2224,$B11) -> 0.32351811 | M11: =COUNTIFS(Pedidos!$D$2:$D$2224,$B11,Pedidos!$AE$2:$AE$2224,"SIM")/D11 -> 0 | N11: =SUMIFS(Pedidos!$T$2:$T$2224,Pedidos!$D$2:$D$2224,$B11)/SUMIFS(Pedidos!$I$2:$I$2224,Pedidos!$D$2:$D$2224,$B11)-1 -> 0.99407972 | O11: =AVERAGEIFS(Pedidos!$AF$2:$AF$2224,Pedidos!$D$2:$D$2224,$B11) -> 13 | P11: =AVERAGEIFS(Pedidos!$AG$2:$AG$2224,Pedidos!$D$2:$D$2224,$B11) -> 11 | Q11: =MAX(0,1-H11/I11) -> 0.37881093 | R11: =IF(J11<=0,"Muito bem",IF(J11<=0.32,"Melhor posição",IF(J11<=0.45,"Intermediária","Precisa melhorar"))) -> Precisa melhorar
A12: 9 | B12: São João de Meriti | C12: =INDEX(Pedidos!$E$2:$E$2224,MATCH($B12,Pedidos!$D$2:$D$2224,0)) -> Metropolitana | D12: =COUNTIFS(Pedidos!$D$2:$D$2224,$B12) -> 37 | E12: =D12/Resumo!$B$20 -> 0.016651665 | F12: =AVERAGEIFS(Pedidos!$G$2:$G$2224,Pedidos!$D$2:$D$2224,$B12) -> 55.930541 | G12: =AVERAGEIFS(Pedidos!$H$2:$H$2224,Pedidos!$D$2:$D$2224,$B12) -> 698.24405 | H12: =AVERAGEIFS(Pedidos!$S$2:$S$2224,Pedidos!$D$2:$D$2224,$B12) -> 132.91637 | I12: =AVERAGEIFS(Pedidos!$AB$2:$AB$2224,Pedidos!$D$2:$D$2224,$B12) -> 175.04377 | J12: =I12/H12-1 -> 0.31694661 | K12: =SUMIFS(Pedidos!$S$2:$S$2224,Pedidos!$D$2:$D$2224,$B12)/SUMIFS(Pedidos!$H$2:$H$2224,Pedidos!$D$2:$D$2224,$B12) -> 0.19035805 | L12: =SUMIFS(Pedidos!$AB$2:$AB$2224,Pedidos!$D$2:$D$2224,$B12)/SUMIFS(Pedidos!$H$2:$H$2224,Pedidos!$D$2:$D$2224,$B12) -> 0.25069138 | M12: =COUNTIFS(Pedidos!$D$2:$D$2224,$B12,Pedidos!$AE$2:$AE$2224,"SIM")/D12 -> 0.027027027 | N12: =SUMIFS(Pedidos!$T$2:$T$2224,Pedidos!$D$2:$D$2224,$B12)/SUMIFS(Pedidos!$I$2:$I$2224,Pedidos!$D$2:$D$2224,$B12)-1 -> 0.58454207 | O12: =AVERAGEIFS(Pedidos!$AF$2:$AF$2224,Pedidos!$D$2:$D$2224,$B12) -> 2 | P12: =AVERAGEIFS(Pedidos!$AG$2:$AG$2224,Pedidos!$D$2:$D$2224,$B12) -> 5 | Q12: =MAX(0,1-H12/I12) -> 0.24066778 | R12: =IF(J12<=0,"Muito bem",IF(J12<=0.32,"Melhor posição",IF(J12<=0.45,"Intermediária","Precisa melhorar"))) -> Melhor posição
A13: 10 | B13: Volta Redonda | C13: =INDEX(Pedidos!$E$2:$E$2224,MATCH($B13,Pedidos!$D$2:$D$2224,0)) -> Interior | D13: =COUNTIFS(Pedidos!$D$2:$D$2224,$B13) -> 37 | E13: =D13/Resumo!$B$20 -> 0.016651665 | F13: =AVERAGEIFS(Pedidos!$G$2:$G$2224,Pedidos!$D$2:$D$2224,$B13) -> 50.886757 | G13: =AVERAGEIFS(Pedidos!$H$2:$H$2224,Pedidos!$D$2:$D$2224,$B13) -> 652.92108 | H13: =AVERAGEIFS(Pedidos!$S$2:$S$2224,Pedidos!$D$2:$D$2224,$B13) -> 139.16228 | I13: =AVERAGEIFS(Pedidos!$AB$2:$AB$2224,Pedidos!$D$2:$D$2224,$B13) -> 198.53821 | J13: =I13/H13-1 -> 0.42666683 | K13: =SUMIFS(Pedidos!$S$2:$S$2224,Pedidos!$D$2:$D$2224,$B13)/SUMIFS(Pedidos!$H$2:$H$2224,Pedidos!$D$2:$D$2224,$B13) -> 0.21313798 | L13: =SUMIFS(Pedidos!$AB$2:$AB$2224,Pedidos!$D$2:$D$2224,$B13)/SUMIFS(Pedidos!$H$2:$H$2224,Pedidos!$D$2:$D$2224,$B13) -> 0.30407689 | M13: =COUNTIFS(Pedidos!$D$2:$D$2224,$B13,Pedidos!$AE$2:$AE$2224,"SIM")/D13 -> 0 | N13: =SUMIFS(Pedidos!$T$2:$T$2224,Pedidos!$D$2:$D$2224,$B13)/SUMIFS(Pedidos!$I$2:$I$2224,Pedidos!$D$2:$D$2224,$B13)-1 -> 0.71827553 | O13: =AVERAGEIFS(Pedidos!$AF$2:$AF$2224,Pedidos!$D$2:$D$2224,$B13) -> 13 | P13: =AVERAGEIFS(Pedidos!$AG$2:$AG$2224,Pedidos!$D$2:$D$2224,$B13) -> 10 | Q13: =MAX(0,1-H13/I13) -> 0.2990655 | R13: =IF(J13<=0,"Muito bem",IF(J13<=0.32,"Melhor posição",IF(J13<=0.45,"Intermediária","Precisa melhorar"))) -> Intermediária
A14: 11 | B14: Angra dos Reis | C14: =INDEX(Pedidos!$E$2:$E$2224,MATCH($B14,Pedidos!$D$2:$D$2224,0)) -> Interior | D14: =COUNTIFS(Pedidos!$D$2:$D$2224,$B14) -> 35 | E14: =D14/Resumo!$B$20 -> 0.015751575 | F14: =AVERAGEIFS(Pedidos!$G$2:$G$2224,Pedidos!$D$2:$D$2224,$B14) -> 44.394286 | G14: =AVERAGEIFS(Pedidos!$H$2:$H$2224,Pedidos!$D$2:$D$2224,$B14) -> 596.41771 | H14: =AVERAGEIFS(Pedidos!$S$2:$S$2224,Pedidos!$D$2:$D$2224,$B14) -> 129.0381 | I14: =AVERAGEIFS(Pedidos!$AB$2:$AB$2224,Pedidos!$D$2:$D$2224,$B14) -> 179.38259 | J14: =I14/H14-1 -> 0.39015218 | K14: =SUMIFS(Pedidos!$S$2:$S$2224,Pedidos!$D$2:$D$2224,$B14)/SUMIFS(Pedidos!$H$2:$H$2224,Pedidos!$D$2:$D$2224,$B14) -> 0.21635524 | L14: =SUMIFS(Pedidos!$AB$2:$AB$2224,Pedidos!$D$2:$D$2224,$B14)/SUMIFS(Pedidos!$H$2:$H$2224,Pedidos!$D$2:$D$2224,$B14) -> 0.30076671 | M14: =COUNTIFS(Pedidos!$D$2:$D$2224,$B14,Pedidos!$AE$2:$AE$2224,"SIM")/D14 -> 0 | N14: =SUMIFS(Pedidos!$T$2:$T$2224,Pedidos!$D$2:$D$2224,$B14)/SUMIFS(Pedidos!$I$2:$I$2224,Pedidos!$D$2:$D$2224,$B14)-1 -> 0.67416202 | O14: =AVERAGEIFS(Pedidos!$AF$2:$AF$2224,Pedidos!$D$2:$D$2224,$B14) -> 13 | P14: =AVERAGEIFS(Pedidos!$AG$2:$AG$2224,Pedidos!$D$2:$D$2224,$B14) -> 10 | Q14: =MAX(0,1-H14/I14) -> 0.2806543 | R14: =IF(J14<=0,"Muito bem",IF(J14<=0.32,"Melhor posição",IF(J14<=0.45,"Intermediária","Precisa melhorar"))) -> Intermediária
A15: 12 | B15: Petrópolis | C15: =INDEX(Pedidos!$E$2:$E$2224,MATCH($B15,Pedidos!$D$2:$D$2224,0)) -> Interior | D15: =COUNTIFS(Pedidos!$D$2:$D$2224,$B15) -> 32 | E15: =D15/Resumo!$B$20 -> 0.01440144 | F15: =AVERAGEIFS(Pedidos!$G$2:$G$2224,Pedidos!$D$2:$D$2224,$B15) -> 58.889375 | G15: =AVERAGEIFS(Pedidos!$H$2:$H$2224,Pedidos!$D$2:$D$2224,$B15) -> 743.8225 | H15: =AVERAGEIFS(Pedidos!$S$2:$S$2224,Pedidos!$D$2:$D$2224,$B15) -> 149.95063 | I15: =AVERAGEIFS(Pedidos!$AB$2:$AB$2224,Pedidos!$D$2:$D$2224,$B15) -> 216.62809 | J15: =I15/H15-1 -> 0.44466274 | K15: =SUMIFS(Pedidos!$S$2:$S$2224,Pedidos!$D$2:$D$2224,$B15)/SUMIFS(Pedidos!$H$2:$H$2224,Pedidos!$D$2:$D$2224,$B15) -> 0.20159464 | L15: =SUMIFS(Pedidos!$AB$2:$AB$2224,Pedidos!$D$2:$D$2224,$B15)/SUMIFS(Pedidos!$H$2:$H$2224,Pedidos!$D$2:$D$2224,$B15) -> 0.29123627 | M15: =COUNTIFS(Pedidos!$D$2:$D$2224,$B15,Pedidos!$AE$2:$AE$2224,"SIM")/D15 -> 0 | N15: =SUMIFS(Pedidos!$T$2:$T$2224,Pedidos!$D$2:$D$2224,$B15)/SUMIFS(Pedidos!$I$2:$I$2224,Pedidos!$D$2:$D$2224,$B15)-1 -> 0.73994151 | O15: =AVERAGEIFS(Pedidos!$AF$2:$AF$2224,Pedidos!$D$2:$D$2224,$B15) -> 13 | P15: =AVERAGEIFS(Pedidos!$AG$2:$AG$2224,Pedidos!$D$2:$D$2224,$B15) -> 8 | Q15: =MAX(0,1-H15/I15) -> 0.30779692 | R15: =IF(J15<=0,"Muito bem",IF(J15<=0.32,"Melhor posição",IF(J15<=0.45,"Intermediária","Precisa melhorar"))) -> Intermediária
... A23: 20 | B23: Rio das Ostras | C23: =INDEX(Pedidos!$E$2:$E$2224,MATCH($B23,Pedidos!$D$2:$D$2224,0)) -> Interior | D23: =COUNTIFS(Pedidos!$D$2:$D$2224,$B23) -> 18 | E23: =D23/Resumo!$B$20 -> 0.0081008101 | F23: =AVERAGEIFS(Pedidos!$G$2:$G$2224,Pedidos!$D$2:$D$2224,$B23) -> 47.438889 | G23: =AVERAGEIFS(Pedidos!$H$2:$H$2224,Pedidos!$D$2:$D$2224,$B23) -> 604.15056 | H23: =AVERAGEIFS(Pedidos!$S$2:$S$2224,Pedidos!$D$2:$D$2224,$B23) -> 132.72499 | I23: =AVERAGEIFS(Pedidos!$AB$2:$AB$2224,Pedidos!$D$2:$D$2224,$B23) -> 190.52993 | J23: =I23/H23-1 -> 0.43552422 | K23: =SUMIFS(Pedidos!$S$2:$S$2224,Pedidos!$D$2:$D$2224,$B23)/SUMIFS(Pedidos!$H$2:$H$2224,Pedidos!$D$2:$D$2224,$B23) -> 0.21968859 | L23: =SUMIFS(Pedidos!$AB$2:$AB$2224,Pedidos!$D$2:$D$2224,$B23)/SUMIFS(Pedidos!$H$2:$H$2224,Pedidos!$D$2:$D$2224,$B23) -> 0.3153683 | M23: =COUNTIFS(Pedidos!$D$2:$D$2224,$B23,Pedidos!$AE$2:$AE$2224,"SIM")/D23 -> 0 | N23: =SUMIFS(Pedidos!$T$2:$T$2224,Pedidos!$D$2:$D$2224,$B23)/SUMIFS(Pedidos!$I$2:$I$2224,Pedidos!$D$2:$D$2224,$B23)-1 -> 0.73945688 | O23: =AVERAGEIFS(Pedidos!$AF$2:$AF$2224,Pedidos!$D$2:$D$2224,$B23) -> 13 | P23: =AVERAGEIFS(Pedidos!$AG$2:$AG$2224,Pedidos!$D$2:$D$2224,$B23) -> 10 | Q23: =MAX(0,1-H23/I23) -> 0.30339037 | R23: =IF(J23<=0,"Muito bem",IF(J23<=0.32,"Melhor posição",IF(J23<=0.45,"Intermediária","Precisa melhorar"))) -> Intermediária
B24: TOTAL TOP 20 | D24: =SUM(D4:D23) -> 1912 | E24: =D24/Resumo!$B$20 -> 0.86048605 | F24: =AVERAGEIFS(Pedidos!$G$2:$G$2224,Pedidos!$AH$2:$AH$2224,"SIM") -> 49.45444 | G24: =AVERAGEIFS(Pedidos!$H$2:$H$2224,Pedidos!$AH$2:$AH$2224,"SIM") -> 636.04536 | H24: =AVERAGEIFS(Pedidos!$S$2:$S$2224,Pedidos!$AH$2:$AH$2224,"SIM") -> 118.21998 | I24: =AVERAGEIFS(Pedidos!$AB$2:$AB$2224,Pedidos!$AH$2:$AH$2224,"SIM") -> 169.56633 | J24: =I24/H24-1 -> 0.43432883 | K24: =SUMIFS(Pedidos!$S$2:$S$2224,Pedidos!$AH$2:$AH$2224,"SIM")/SUMIFS(Pedidos!$H$2:$H$2224,Pedidos!$AH$2:$AH$2224,"SIM") -> 0.18586721 | L24: =SUMIFS(Pedidos!$AB$2:$AB$2224,Pedidos!$AH$2:$AH$2224,"SIM")/SUMIFS(Pedidos!$H$2:$H$2224,Pedidos!$AH$2:$AH$2224,"SIM") -> 0.2665947 | M24: =COUNTIFS(Pedidos!$AH$2:$AH$2224,"SIM",Pedidos!$AE$2:$AE$2224,"SIM")/D24 -> 0.0073221757 | N24: =SUMIFS(Pedidos!$T$2:$T$2224,Pedidos!$AH$2:$AH$2224,"SIM")/SUMIFS(Pedidos!$I$2:$I$2224,Pedidos!$AH$2:$AH$2224,"SIM")-1 -> 0.80659243 | O24: =AVERAGEIFS(Pedidos!$AF$2:$AF$2224,Pedidos!$AH$2:$AH$2224,"SIM") -> 4.1344142 | P24: =AVERAGEIFS(Pedidos!$AG$2:$AG$2224,Pedidos!$AH$2:$AH$2224,"SIM") -> 6.0690377 | Q24: =MAX(0,1-H24/I24) -> 0.3028098
A26: Avaliação: "Muito bem" = PROLOG mais barata; "Melhor posição" = até +32%; "Intermediária" = +32% a +45%; "Precisa melhorar" = acima de +45%.

Sheet Frete Peso Top 20
A1: Frete peso por faixa (valor de tabela, antes de taxas e ICMS) — PROLOG x OUTRO PARCEIRO nas top 20 cidades
A4: 1) PROLOG — frete peso (R$)
A5: Cidade | B5: Região OUTRO PARCEIRO | C5: 0-20 | D5: 20-35 | E5: 35-40 | F5: 40-50 | G5: 50-60 | H5: 60-70 | I5: 70-80 | J5: 80-100 | K5: 100-120 | L5: 120-150 | M5: 150-170 | N5: 170-200 | O5: 200-250
A6: Rio de Janeiro | B6: Capital | C6: 46.98 | D6: 82.21 | E6: 93.97 | F6: 93.97 | G6: 112.3 | H6: 131.02 | I6: 134.39 | J6: 167.99 | K6: 201.59 | L6: 239.25 | M6: 271.15 | N6: 319 | O6: 398.74
A7: São Gonçalo | B7: Metropolitana | C7: 57.47 | D7: 100.58 | E7: 114.95 | F7: 114.95 | G7: 128.14 | H7: 149.5 | I7: 142.74 | J7: 178.42 | K7: 214.11 | L7: 249.03 | M7: 282.23 | N7: 332.05 | O7: 415.05
A8: Duque de Caxias | B8: Metropolitana | C8: 46.98 | D8: 82.21 | E8: 93.97 | F8: 93.97 | G8: 112.3 | H8: 131.02 | I8: 134.39 | J8: 167.99 | K8: 201.59 | L8: 239.25 | M8: 271.15 | N8: 319 | O8: 398.74
A9: Nova Iguaçu | B9: Metropolitana | C9: 46.98 | D9: 82.21 | E9: 93.97 | F9: 93.97 | G9: 112.3 | H9: 131.02 | I9: 134.39 | J9: 167.99 | K9: 201.59 | L9: 239.25 | M9: 271.15 | N9: 319 | O9: 398.74
A10: Niterói | B10: Metropolitana | C10: 57.47 | D10: 100.58 | E10: 114.95 | F10: 114.95 | G10: 128.14 | H10: 149.5 | I10: 142.74 | J10: 178.42 | K10: 214.11 | L10: 249.03 | M10: 282.23 | N10: 332.05 | O10: 415.05
A11: Campos dos Goytacazes | B11: Interior | C11: 124.04 | D11: 138.29 | E11: 143.04 | F11: 152.54 | G11: 162.04 | H11: 171.54 | I11: 181.04 | J11: 200.04 | K11: 236.82 | L11: 264.84 | M11: 300.15 | N11: 353.17 | O11: 441.4
A12: Belford Roxo | B12: Metropolitana | C12: 46.98 | D12: 82.21 | E12: 93.97 | F12: 93.97 | G12: 112.3 | H12: 131.02 | I12: 134.39 | J12: 167.99 | K12: 201.59 | L12: 239.25 | M12: 271.15 | N12: 319 | O12: 398.74
A13: Macaé | B13: Interior | C13: 124.04 | D13: 138.29 | E13: 143.04 | F13: 152.54 | G13: 162.04 | H13: 171.54 | I13: 181.04 | J13: 200.04 | K13: 236.82 | L13: 264.84 | M13: 300.15 | N13: 353.17 | O13: 441.4
A14: São João de Meriti | B14: Metropolitana | C14: 46.98 | D14: 82.21 | E14: 93.97 | F14: 93.97 | G14: 112.3 | H14: 131.02 | I14: 134.39 | J14: 167.99 | K14: 201.59 | L14: 239.25 | M14: 271.15 | N14: 319 | O14: 398.74
A15: Volta Redonda | B15: Interior | C15: 77.35 | D15: 108.83 | E15: 124.38 | F15: 124.38 | G15: 142.32 | H15: 166.05 | I15: 157.88 | J15: 197.35 | K15: 236.82 | L15: 264.84 | M15: 300.15 | N15: 353.12 | O15: 441.4
A16: Angra dos Reis | B16: Interior | C16: 77.35 | D16: 108.83 | E16: 124.38 | F16: 124.38 | G16: 142.32 | H16: 166.05 | I16: 157.88 | J16: 197.35 | K16: 236.82 | L16: 264.84 | M16: 300.15 | N16: 353.12 | O16: 441.4
A17: Petrópolis | B17: Interior | C17: 89.03 | D17: 108.83 | E17: 124.38 | F17: 124.38 | G17: 142.32 | H17: 166.05 | I17: 166.05 | J17: 197.35 | K17: 236.82 | L17: 264.84 | M17: 300.15 | N17: 353.12 | O17: 441.4
... A25: Rio das Ostras | B25: Interior | C25: 100.7 | D25: 114.95 | E25: 124.38 | F25: 129.29 | G25: 142.32 | H25: 166.05 | I25: 166.05 | J25: 197.35 | K25: 236.82 | L25: 264.84 | M25: 300.15 | N25: 353.12 | O25: 441.4
A27: 2) OUTRO PARCEIRO — frete peso (R$)
A28: Cidade | B28: Região OUTRO PARCEIRO | C28: 0-20 | D28: 20-35 | E28: 35-40 | F28: 40-50 | G28: 50-60 | H28: 60-70 | I28: 70-80 | J28: 80-100 | K28: 100-120 | L28: 120-150 | M28: 150-170 | N28: 170-200 | O28: 200-250
A29: Rio de Janeiro | B29: Capital | C29: 33.42 | D29: 42.11 | E29: 48.35 | F29: 53.55 | G29: 58.6 | H29: 63.21 | I29: 68.88 | J29: 83.79 | K29: 92.34 | L29: 120.59 | M29: 130.31 | N29: 144.9 | O29: 181.55
A30: São Gonçalo | B30: Metropolitana | C30: 42.72 | D30: 58.8 | E30: 66.83 | F30: 65.36 | G30: 70.98 | H30: 76.55 | I30: 82.48 | J30: 92.32 | K30: 101.26 | L30: 129.62 | M30: 139.81 | N30: 155.09 | O30: 194.34
A31: Duque de Caxias | B31: Metropolitana | C31: 42.72 | D31: 58.8 | E31: 66.83 | F31: 65.36 | G31: 70.98 | H31: 76.55 | I31: 82.48 | J31: 92.32 | K31: 101.26 | L31: 129.62 | M31: 139.81 | N31: 155.09 | O31: 194.34
A32: Nova Iguaçu | B32: Metropolitana | C32: 42.72 | D32: 58.8 | E32: 66.83 | F32: 65.36 | G32: 70.98 | H32: 76.55 | I32: 82.48 | J32: 92.32 | K32: 101.26 | L32: 129.62 | M32: 139.81 | N32: 155.09 | O32: 194.34
A33: Niterói | B33: Metropolitana | C33: 42.72 | D33: 58.8 | E33: 66.83 | F33: 65.36 | G33: 70.98 | H33: 76.55 | I33: 82.48 | J33: 92.32 | K33: 101.26 | L33: 129.62 | M33: 139.81 | N33: 155.09 | O33: 194.34
A34: Campos dos Goytacazes | B34: Interior | C34: 46.95 | D34: 65.63 | E34: 74.97 | F34: 77.7 | G34: 83.58 | H34: 90.2 | I34: 96.77 | J34: 109.63 | K34: 119.5 | L34: 144.24 | M34: 155.09 | N34: 66.69 | O34: 214.88
A35: Belford Roxo | B35: Metropolitana | C35: 42.72 | D35: 58.8 | E35: 66.83 | F35: 65.36 | G35: 70.98 | H35: 76.55 | I35: 82.48 | J35: 92.32 | K35: 101.26 | L35: 129.62 | M35: 139.81 | N35: 155.09 | O35: 194.34
A36: Macaé | B36: Interior | C36: 46.95 | D36: 65.63 | E36: 74.97 | F36: 77.7 | G36: 83.58 | H36: 90.2 | I36: 96.77 | J36: 109.63 | K36: 119.5 | L36: 144.24 | M36: 155.09 | N36: 66.69 | O36: 214.88
A37: São João de Meriti | B37: Metropolitana | C37: 42.72 | D37: 58.8 | E37: 66.83 | F37: 65.36 | G37: 70.98 | H37: 76.55 | I37: 82.48 | J37: 92.32 | K37: 101.26 | L37: 129.62 | M37: 139.81 | N37: 155.09 | O37: 194.34
A38: Volta Redonda | B38: Interior | C38: 46.95 | D38: 65.63 | E38: 74.97 | F38: 77.7 | G38: 83.58 | H38: 90.2 | I38: 96.77 | J38: 109.63 | K38: 119.5 | L38: 144.24 | M38: 155.09 | N38: 66.69 | O38: 214.88
A39: Angra dos Reis | B39: Interior | C39: 46.95 | D39: 65.63 | E39: 74.97 | F39: 77.7 | G39: 83.58 | H39: 90.2 | I39: 96.77 | J39: 109.63 | K39: 119.5 | L39: 144.24 | M39: 155.09 | N39: 66.69 | O39: 214.88
A40: Petrópolis | B40: Interior | C40: 46.95 | D40: 65.63 | E40: 74.97 | F40: 77.7 | G40: 83.58 | H40: 90.2 | I40: 96.77 | J40: 109.63 | K40: 119.5 | L40: 144.24 | M40: 155.09 | N40: 66.69 | O40: 214.88
... A48: Rio das Ostras | B48: Interior | C48: 46.95 | D48: 65.63 | E48: 74.97 | F48: 77.7 | G48: 83.58 | H48: 90.2 | I48: 96.77 | J48: 109.63 | K48: 119.5 | L48: 144.24 | M48: 155.09 | N48: 66.69 | O48: 214.88
A50: 3) PROLOG vs OUTRO PARCEIRO (%)
A51: Cidade | B51: Região OUTRO PARCEIRO | C51: 0-20 | D51: 20-35 | E51: 35-40 | F51: 40-50 | G51: 50-60 | H51: 60-70 | I51: 70-80 | J51: 80-100 | K51: 100-120 | L51: 120-150 | M51: 150-170 | N51: 170-200 | O51: 200-250
A52: Rio de Janeiro | B52: Capital | C52: =C6/C29-1 -> 0.40574506 | D52: =D6/D29-1 -> 0.95226787 | E52: =E6/E29-1 -> 0.94353671 | F52: =F6/F29-1 -> 0.75480859 | G52: =G6/G29-1 -> 0.91638225 | H52: =H6/H29-1 -> 1.0727733 | I52: =I6/I29-1 -> 0.95107433 | J52: =J6/J29-1 -> 1.0048932 | ... O52: =O6/O29-1 -> 1.1963096
A53: São Gonçalo | B53: Metropolitana | C53: =C7/C30-1 -> 0.34527154 | D53: =D7/D30-1 -> 0.71054422 | E53: =E7/E30-1 -> 0.72003591 | F53: =F7/F30-1 -> 0.75872093 | G53: =G7/G30-1 -> 0.80529727 | H53: =H7/H30-1 -> 0.95297191 | I53: =I7/I30-1 -> 0.73060136 | J53: =J7/J30-1 -> 0.93262565 | ... O53: =O7/O30-1 -> 1.13569
A54: Duque de Caxias | B54: Metropolitana | C54: =C8/C31-1 -> 0.099719101 | D54: =D8/D31-1 -> 0.39812925 | E54: =E8/E31-1 -> 0.40610504 | F54: =F8/F31-1 -> 0.4377295 | G54: =G8/G31-1 -> 0.58213581 | H54: =H8/H31-1 -> 0.71156107 | I54: =I8/I31-1 -> 0.62936469 | J54: =J8/J31-1 -> 0.81964905 | ... O54: =O8/O31-1 -> 1.0517649
A55: Nova Iguaçu | B55: Metropolitana | C55: =C9/C32-1 -> 0.099719101 | D55: =D9/D32-1 -> 0.39812925 | E55: =E9/E32-1 -> 0.40610504 | F55: =F9/F32-1 -> 0.4377295 | G55: =G9/G32-1 -> 0.58213581 | H55: =H9/H32-1 -> 0.71156107 | I55: =I9/I32-1 -> 0.62936469 | J55: =J9/J32-1 -> 0.81964905 | ... O55: =O9/O32-1 -> 1.0517649
A56: Niterói | B56: Metropolitana | C56: =C10/C33-1 -> 0.34527154 | D56: =D10/D33-1 -> 0.71054422 | E56: =E10/E33-1 -> 0.72003591 | F56: =F10/F33-1 -> 0.75872093 | G56: =G10/G33-1 -> 0.80529727 | H56: =H10/H33-1 -> 0.95297191 | I56: =I10/I33-1 -> 0.73060136 | J56: =J10/J33-1 -> 0.93262565 | ... O56: =O10/O33-1 -> 1.13569
A57: Campos dos Goytacazes | B57: Interior | C57: =C11/C34-1 -> 1.6419595 | D57: =D11/D34-1 -> 1.1071156 | E57: =E11/E34-1 -> 0.90796319 | F57: =F11/F34-1 -> 0.96319176 | G57: =G11/G34-1 -> 0.93874133 | H57: =H11/H34-1 -> 0.90177384 | I57: =I11/I34-1 -> 0.87082774 | J57: =J11/J34-1 -> 0.82468302 | ... O57: =O11/O34-1 -> 1.0541698
A58: Belford Roxo | B58: Metropolitana | C58: =C12/C35-1 -> 0.099719101 | D58: =D12/D35-1 -> 0.39812925 | E58: =E12/E35-1 -> 0.40610504 | F58: =F12/F35-1 -> 0.4377295 | G58: =G12/G35-1 -> 0.58213581 | H58: =H12/H35-1 -> 0.71156107 | I58: =I12/I35-1 -> 0.62936469 | J58: =J12/J35-1 -> 0.81964905 | ... O58: =O12/O35-1 -> 1.0517649
A59: Macaé | B59: Interior | C59: =C13/C36-1 -> 1.6419595 | D59: =D13/D36-1 -> 1.1071156 | E59: =E13/E36-1 -> 0.90796319 | F59: =F13/F36-1 -> 0.96319176 | G59: =G13/G36-1 -> 0.93874133 | H59: =H13/H36-1 -> 0.90177384 | I59: =I13/I36-1 -> 0.87082774 | J59: =J13/J36-1 -> 0.82468302 | ... O59: =O13/O36-1 -> 1.0541698
A60: São João de Meriti | B60: Metropolitana | C60: =C14/C37-1 -> 0.099719101 | D60: =D14/D37-1 -> 0.39812925 | E60: =E14/E37-1 -> 0.40610504 | F60: =F14/F37-1 -> 0.4377295 | G60: =G14/G37-1 -> 0.58213581 | H60: =H14/H37-1 -> 0.71156107 | I60: =I14/I37-1 -> 0.62936469 | J60: =J14/J37-1 -> 0.81964905 | ... O60: =O14/O37-1 -> 1.0517649
A61: Volta Redonda | B61: Interior | C61: =C15/C38-1 -> 0.64749734 | D61: =D15/D38-1 -> 0.65823556 | E61: =E15/E38-1 -> 0.65906363 | F61: =F15/F38-1 -> 0.6007722 | G61: =G15/G38-1 -> 0.70279971 | H61: =H15/H38-1 -> 0.84090909 | I61: =I15/I38-1 -> 0.63149736 | J61: =J15/J38-1 -> 0.80014595 | ... O61: =O15/O38-1 -> 1.0541698
A62: Angra dos Reis | B62: Interior | C62: =C16/C39-1 -> 0.64749734 | D62: =D16/D39-1 -> 0.65823556 | E62: =E16/E39-1 -> 0.65906363 | F62: =F16/F39-1 -> 0.6007722 | G62: =G16/G39-1 -> 0.70279971 | H62: =H16/H39-1 -> 0.84090909 | I62: =I16/I39-1 -> 0.63149736 | J62: =J16/J39-1 -> 0.80014595 | ... O62: =O16/O39-1 -> 1.0541698
A63: Petrópolis | B63: Interior | C63: =C17/C40-1 -> 0.89627263 | D63: =D17/D40-1 -> 0.65823556 | E63: =E17/E40-1 -> 0.65906363 | F63: =F17/F40-1 -> 0.6007722 | G63: =G17/G40-1 -> 0.70279971 | H63: =H17/H40-1 -> 0.84090909 | I63: =I17/I40-1 -> 0.71592436 | J63: =J17/J40-1 -> 0.80014595 | ... O63: =O17/O40-1 -> 1.0541698
... A71: Rio das Ostras | B71: Interior | C71: =C25/C48-1 -> 1.1448349 | D71: =D25/D48-1 -> 0.7514856 | E71: =E25/E48-1 -> 0.65906363 | F71: =F25/F48-1 -> 0.66396396 | G71: =G25/G48-1 -> 0.70279971 | H71: =H25/H48-1 -> 0.84090909 | I71: =I25/I48-1 -> 0.71592436 | J71: =J25/J48-1 -> 0.80014595 | ... O71: =O25/O48-1 -> 1.0541698

Sheet Proposta Tabela PROLOG
A1: Frete peso ALVO para a PROLOG empatar com a OUTRO PARCEIRO (mantendo as taxas atuais da PROLOG, inclusive a taxa interna)
A2: Alvo = subtotal OUTRO PARCEIRO (frete peso + ad valorem + GRIS + seguro + pedágio + entrega + CTe fixo + taxa interna, × (1 + TRT)) − taxas PROLOG (ad valorem + GRIS + TAS + pedágio + CTe/kg + taxa interna), para um pedido de referência por faixa. O ICMS é igual nas duas e se anula.
AG3: Peso de referência (kg) → | AH3: =IFERROR(AVERAGEIFS(Pedidos!$G$2:$G$2224,Pedidos!$F$2:$F$2224,"0-20"),10) -> 17.66757 | AI3: =IFERROR(AVERAGEIFS(Pedidos!$G$2:$G$2224,Pedidos!$F$2:$F$2224,"20-35"),27.5) -> 28.310162 | AJ3: =IFERROR(AVERAGEIFS(Pedidos!$G$2:$G$2224,Pedidos!$F$2:$F$2224,"35-40"),37.5) -> 37.738563 | AK3: =IFERROR(AVERAGEIFS(Pedidos!$G$2:$G$2224,Pedidos!$F$2:$F$2224,"40-50"),45) -> 45.894767 | AL3: =IFERROR(AVERAGEIFS(Pedidos!$G$2:$G$2224,Pedidos!$F$2:$F$2224,"50-60"),55) -> 53.757837 | AM3: =IFERROR(AVERAGEIFS(Pedidos!$G$2:$G$2224,Pedidos!$F$2:$F$2224,"60-70"),65) -> 66.006227 | AN3: =IFERROR(AVERAGEIFS(Pedidos!$G$2:$G$2224,Pedidos!$F$2:$F$2224,"70-80"),75) -> 74.587333 | AO3: =IFERROR(AVERAGEIFS(Pedidos!$G$2:$G$2224,Pedidos!$F$2:$F$2224,"80-100"),90) -> 87.633333 | AP3: =IFERROR(AVERAGEIFS(Pedidos!$G$2:$G$2224,Pedidos!$F$2:$F$2224,"100-120"),110) -> 110.32245 | AQ3: =IFERROR(AVERAGEIFS(Pedidos!$G$2:$G$2224,Pedidos!$F$2:$F$2224,"120-150"),135) -> 128.14698 | AR3: =IFERROR(AVERAGEIFS(Pedidos!$G$2:$G$2224,Pedidos!$F$2:$F$2224,"150-170"),160) -> 160.63333 | AS3: =IFERROR(AVERAGEIFS(Pedidos!$G$2:$G$2224,Pedidos!$F$2:$F$2224,"170-200"),185) -> 188.4 | AT3: =IFERROR(AVERAGEIFS(Pedidos!$G$2:$G$2224,Pedidos!$F$2:$F$2224,"200-250"),225) -> 208.2
AG4: NF de referência (R$) → | AH4: =IFERROR(AVERAGEIFS(Pedidos!$H$2:$H$2224,Pedidos!$F$2:$F$2224,"0-20"),AH3*SUM(Pedidos!$H$2:$H$2224)/SUM(Pedidos!$G$2:$G$2224)) -> 314.90598 | AI4: =IFERROR(AVERAGEIFS(Pedidos!$H$2:$H$2224,Pedidos!$F$2:$F$2224,"20-35"),AI3*SUM(Pedidos!$H$2:$H$2224)/SUM(Pedidos!$G$2:$G$2224)) -> 434.46416 | AJ4: =IFERROR(AVERAGEIFS(Pedidos!$H$2:$H$2224,Pedidos!$F$2:$F$2224,"35-40"),AJ3*SUM(Pedidos!$H$2:$H$2224)/SUM(Pedidos!$G$2:$G$2224)) -> 465.11025 | AK4: =IFERROR(AVERAGEIFS(Pedidos!$H$2:$H$2224,Pedidos!$F$2:$F$2224,"40-50"),AK3*SUM(Pedidos!$H$2:$H$2224)/SUM(Pedidos!$G$2:$G$2224)) -> 603.08035 | AL4: =IFERROR(AVERAGEIFS(Pedidos!$H$2:$H$2224,Pedidos!$F$2:$F$2224,"50-60"),AL3*SUM(Pedidos!$H$2:$H$2224)/SUM(Pedidos!$G$2:$G$2224)) -> 694.48351 | AM4: =IFERROR(AVERAGEIFS(Pedidos!$H$2:$H$2224,Pedidos!$F$2:$F$2224,"60-70"),AM3*SUM(Pedidos!$H$2:$H$2224)/SUM(Pedidos!$G$2:$G$2224)) -> 759.36037 | AN4: =IFERROR(AVERAGEIFS(Pedidos!$H$2:$H$2224,Pedidos!$F$2:$F$2224,"70-80"),AN3*SUM(Pedidos!$H$2:$H$2224)/SUM(Pedidos!$G$2:$G$2224)) -> 951.882 | AO4: =IFERROR(AVERAGEIFS(Pedidos!$H$2:$H$2224,Pedidos!$F$2:$F$2224,"80-100"),AO3*SUM(Pedidos!$H$2:$H$2224)/SUM(Pedidos!$G$2:$G$2224)) -> 970.36649 | AP4: =IFERROR(AVERAGEIFS(Pedidos!$H$2:$H$2224,Pedidos!$F$2:$F$2224,"100-120"),AP3*SUM(Pedidos!$H$2:$H$2224)/SUM(Pedidos!$G$2:$G$2224)) -> 1259.4377 | AQ4: =IFERROR(AVERAGEIFS(Pedidos!$H$2:$H$2224,Pedidos!$F$2:$F$2224,"120-150"),AQ3*SUM(Pedidos!$H$2:$H$2224)/SUM(Pedidos!$G$2:$G$2224)) -> 1647.7808 | AR4: =IFERROR(AVERAGEIFS(Pedidos!$H$2:$H$2224,Pedidos!$F$2:$F$2224,"150-170"),AR3*SUM(Pedidos!$H$2:$H$2224)/SUM(Pedidos!$G$2:$G$2224)) -> 1909.1733 | AS4: =IFERROR(AVERAGEIFS(Pedidos!$H$2:$H$2224,Pedidos!$F$2:$F$2224,"170-200"),AS3*SUM(Pedidos!$H$2:$H$2224)/SUM(Pedidos!$G$2:$G$2224)) -> 1994 | AT4: =IFERROR(AVERAGEIFS(Pedidos!$H$2:$H$2224,Pedidos!$F$2:$F$2224,"200-250"),AT3*SUM(Pedidos!$H$2:$H$2224)/SUM(Pedidos!$G$2:$G$2224)) -> 3070.2767
H5: PROLOG atual — frete peso | U5: OUTRO PARCEIRO — frete peso | AH5: PROLOG ALVO (empate) | AU5: Redução necessária no frete peso PROLOG
A6: UF | B6: Cidade (tabela PROLOG) | C6: CEP inicial | D6: CEP final | E6: Região OUTRO PARCEIRO | F6: Prazo PROLOG / OUTRO PARCEIRO | G6: Pedidos no período | H6: 0-20 | I6: 20-35 | J6: 35-40 | K6: 40-50 | L6: 50-60 | M6: 60-70 | N6: 70-80 | O6: 80-100 | P6: 100-120 | Q6: 120-150 | R6: 150-170 | S6: 170-200 | T6: 200-250 | U6: 0-20 | V6: 20-35 | W6: 35-40 | X6: 40-50 | Y6: 50-60 | Z6: 60-70 | AA6: 70-80 | AB6: 80-100 | AC6: 100-120 | AD6: 120-150 | AE6: 150-170 | AF6: 170-200 | AG6: 200-250 | AH6: 0-20 | AI6: 20-35 | AJ6: 35-40 | AK6: 40-50 | AL6: 50-60 | AM6: 60-70 | AN6: 70-80 | AO6: 80-100 | AP6: 100-120 | AQ6: 120-150 | AR6: 150-170 | AS6: 170-200 | AT6: 200-250 | AU6: 0-20 | AV6: 20-35 | AW6: 35-40 | AX6: 40-50 | AY6: 50-60 | AZ6: 60-70 | BA6: 70-80 | BB6: 80-100 | BC6: 100-120 | BD6: 120-150 | BE6: 150-170 | BF6: 170-200 | BG6: 200-250
A7: RJ | B7: Rio de Janeiro | C7: 20000000 | D7: 23799999 | E7: Capital | F7: 5 / 2 | G7: =COUNTIFS(Pedidos!$C$2:$C$2224,">="&C7,Pedidos!$C$2:$C$2224,"<="&D7) -> 1030 | H7: 46.98 | I7: 82.21 | J7: 93.97 | K7: 93.97 | L7: 112.3 | M7: 131.02 | N7: 134.39 | O7: 167.99 | P7: 201.59 | Q7: 239.25 | R7: 271.15 | S7: 319 | T7: 398.74 | U7: 33.42 | V7: 42.11 | W7: 48.35 | X7: 53.55 | Y7: 58.6 | Z7: 63.21 | AA7: 68.88 | AB7: 83.79 | AC7: 92.34 | AD7: 120.59 | AE7: 130.31 | AF7: 144.9 | AG7: 181.55 | AH7: =(U7+AH$4*(Resumo!$C$6+Resumo!$C$7+Resumo!$C$8)+Resumo!$C$10*CEILING(AH$3/100,1)+Resumo!$C$9+Resumo!$C$13+Resumo!$C$14*CEILING(AH$3,1))*(1+Resumo!$C$11)-(AH$4*(Resumo!$B$6+Resumo!$B$7)+Resumo!$B$9+Resumo!$B$10*CEILING(AH$3/100,1)+(Resumo!$B$12+Resumo!$B$14)*CEILING(AH$3,1)) -> 41.817887 | AI7: =(V7+AI$4*(Resumo!$C$6+Resumo!$C$7+Resumo!$C$8)+Resumo!$C$10*CEILING(AI$3/100,1)+Resumo!$C$9+Resumo!$C$13+Resumo!$C$14*CEILING(AI$3,1))*(1+Resumo!$C$11)-(AI$4*(Resumo!$B$6+Resumo!$B$7)+Resumo!$B$9+Resumo!$B$10*CEILING(AI$3/100,1)+(Resumo!$B$12+Resumo!$B$14)*CEILING(AI$3,1)) -> 49.991357 | AJ7: =(W7+AJ$4*(Resumo!$C$6+Resumo!$C$7+Resumo!$C$8)+Resumo!$C$10*CEILING(AJ$3/100,1)+Resumo!$C$9+Resumo!$C$13+Resumo!$C$14*CEILING(AJ$3,1))*(1+Resumo!$C$11)-(AJ$4*(Resumo!$B$6+Resumo!$B$7)+Resumo!$B$9+Resumo!$B$10*CEILING(AJ$3/100,1)+(Resumo!$B$12+Resumo!$B$14)*CEILING(AJ$3,1)) -> 55.728132 | AK7: =(X7+AK$4*(Resumo!$C$6+Resumo!$C$7+Resumo!$C$8)+Resumo!$C$10*CEILING(AK$3/100,1)+Resumo!$C$9+Resumo!$C$13+Resumo!$C$14*CEILING(AK$3,1))*(1+Resumo!$C$11)-(AK$4*(Resumo!$B$6+Resumo!$B$7)+Resumo!$B$9+Resumo!$B$10*CEILING(AK$3/100,1)+(Resumo!$B$12+Resumo!$B$14)*CEILING(AK$3,1)) -> 60.613696 | AL7: =(Y7+AL$4*(Resumo!$C$6+Resumo!$C$7+Resumo!$C$8)+Resumo!$C$10*CEILING(AL$3/100,1)+Resumo!$C$9+Resumo!$C$13+Resumo!$C$14*CEILING(AL$3,1))*(1+Resumo!$C$11)-(AL$4*(Resumo!$B$6+Resumo!$B$7)+Resumo!$B$9+Resumo!$B$10*CEILING(AL$3/100,1)+(Resumo!$B$12+Resumo!$B$14)*CEILING(AL$3,1)) -> 65.29338 | AM7: =(Z7+AM$4*(Resumo!$C$6+Resumo!$C$7+Resumo!$C$8)+Resumo!$C$10*CEILING(AM$3/100,1)+Resumo!$C$9+Resumo!$C$13+Resumo!$C$14*CEILING(AM$3,1))*(1+Resumo!$C$11)-(AM$4*(Resumo!$B$6+Resumo!$B$7)+Resumo!$B$9+Resumo!$B$10*CEILING(AM$3/100,1)+(Resumo!$B$12+Resumo!$B$14)*CEILING(AM$3,1)) -> 69.201232 | AN7: =(AA7+AN$4*(Resumo!$C$6+Resumo!$C$7+Resumo!$C$8)+Resumo!$C$10*CEILING(AN$3/100,1)+Resumo!$C$9+Resumo!$C$13+Resumo!$C$14*CEILING(AN$3,1))*(1+Resumo!$C$11)-(AN$4*(Resumo!$B$6+Resumo!$B$7)+Resumo!$B$9+Resumo!$B$10*CEILING(AN$3/100,1)+(Resumo!$B$12+Resumo!$B$14)*CEILING(AN$3,1)) -> 74.622258 | AO7: =(AB7+AO$4*(Resumo!$C$6+Resumo!$C$7+Resumo!$C$8)+Resumo!$C$10*CEILING(AO$3/100,1)+Resumo!$C$9+Resumo!$C$13+Resumo!$C$14*CEILING(AO$3,1))*(1+Resumo!$C$11)-(AO$4*(Resumo!$B$6+Resumo!$B$7)+Resumo!$B$9+Resumo!$B$10*CEILING(AO$3/100,1)+(Resumo!$B$12+Resumo!$B$14)*CEILING(AO$3,1)) -> 88.77444 | ... AT7: =(AG7+AT$4*(Resumo!$C$6+Resumo!$C$7+Resumo!$C$8)+Resumo!$C$10*CEILING(AT$3/100,1)+Resumo!$C$9+Resumo!$C$13+Resumo!$C$14*CEILING(AT$3,1))*(1+Resumo!$C$11)-(AT$4*(Resumo!$B$6+Resumo!$B$7)+Resumo!$B$9+Resumo!$B$10*CEILING(AT$3/100,1)+(Resumo!$B$12+Resumo!$B$14)*CEILING(AT$3,1)) -> 174.89433 | AU7: =1-AH7/H7 -> 0.10987894 | AV7: =1-AI7/I7 -> 0.39190662 | AW7: =1-AJ7/J7 -> 0.40695826 | AX7: =1-AK7/K7 -> 0.35496758 | AY7: =1-AL7/L7 -> 0.41858076 | AZ7: =1-AM7/M7 -> 0.47182695 | BA7: =1-AN7/N7 -> 0.44473355 | BB7: =1-AO7/O7 -> 0.47154926 | ... BG7: =1-AT7/T7 -> 0.56138252
A8: RJ | B8: Itaguaí | C8: 23800000 | D8: 23859999 | E8: Interior | F8: 5 / 13 | G8: =COUNTIFS(Pedidos!$C$2:$C$2224,">="&C8,Pedidos!$C$2:$C$2224,"<="&D8) -> 7 | H8: 56.98 | I8: 92.21 | J8: 103.97 | K8: 103.97 | L8: 122.3 | M8: 141.02 | N8: 144.39 | O8: 177.99 | P8: 211.59 | Q8: 249.25 | R8: 281.15 | S8: 329 | T8: 408.74 | U8: 46.95 | V8: 65.63 | W8: 74.97 | X8: 77.7 | Y8: 83.58 | Z8: 90.2 | AA8: 96.77 | AB8: 109.63 | AC8: 119.5 | AD8: 144.24 | AE8: 155.09 | AF8: 66.69 | AG8: 214.88 | AH8: =(U8+AH$4*(Resumo!$C$6+Resumo!$C$7+Resumo!$C$8)+Resumo!$C$10*CEILING(AH$3/100,1)+Resumo!$C$9+Resumo!$C$13+Resumo!$C$14*CEILING(AH$3,1))*(1+Resumo!$C$11)-(AH$4*(Resumo!$B$6+Resumo!$B$7)+Resumo!$B$9+Resumo!$B$10*CEILING(AH$3/100,1)+(Resumo!$B$12+Resumo!$B$14)*CEILING(AH$3,1)) -> 55.347887 | AI8: =(V8+AI$4*(Resumo!$C$6+Resumo!$C$7+Resumo!$C$8)+Resumo!$C$10*CEILING(AI$3/100,1)+Resumo!$C$9+Resumo!$C$13+Resumo!$C$14*CEILING(AI$3,1))*(1+Resumo!$C$11)-(AI$4*(Resumo!$B$6+Resumo!$B$7)+Resumo!$B$9+Resumo!$B$10*CEILING(AI$3/100,1)+(Resumo!$B$12+Resumo!$B$14)*CEILING(AI$3,1)) -> 73.511357 | AJ8: =(W8+AJ$4*(Resumo!$C$6+Resumo!$C$7+Resumo!$C$8)+Resumo!$C$10*CEILING(AJ$3/100,1)+Resumo!$C$9+Resumo!$C$13+Resumo!$C$14*CEILING(AJ$3,1))*(1+Resumo!$C$11)-(AJ$4*(Resumo!$B$6+Resumo!$B$7)+Resumo!$B$9+Resumo!$B$10*CEILING(AJ$3/100,1)+(Resumo!$B$12+Resumo!$B$14)*CEILING(AJ$3,1)) -> 82.348132 | AK8: =(X8+AK$4*(Resumo!$C$6+Resumo!$C$7+Resumo!$C$8)+Resumo!$C$10*CEILING(AK$3/100,1)+Resumo!$C$9+Resumo!$C$13+Resumo!$C$14*CEILING(AK$3,1))*(1+Resumo!$C$11)-(AK$4*(Resumo!$B$6+Resumo!$B$7)+Resumo!$B$9+Resumo!$B$10*CEILING(AK$3/100,1)+(Resumo!$B$12+Resumo!$B$14)*CEILING(AK$3,1)) -> 84.763696 | AL8: =(Y8+AL$4*(Resumo!$C$6+Resumo!$C$7+Resumo!$C$8)+Resumo!$C$10*CEILING(AL$3/100,1)+Resumo!$C$9+Resumo!$C$13+Resumo!$C$14*CEILING(AL$3,1))*(1+Resumo!$C$11)-(AL$4*(Resumo!$B$6+Resumo!$B$7)+Resumo!$B$9+Resumo!$B$10*CEILING(AL$3/100,1)+(Resumo!$B$12+Resumo!$B$14)*CEILING(AL$3,1)) -> 90.27338 | AM8: =(Z8+AM$4*(Resumo!$C$6+Resumo!$C$7+Resumo!$C$8)+Resumo!$C$10*CEILING(AM$3/100,1)+Resumo!$C$9+Resumo!$C$13+Resumo!$C$14*CEILING(AM$3,1))*(1+Resumo!$C$11)-(AM$4*(Resumo!$B$6+Resumo!$B$7)+Resumo!$B$9+Resumo!$B$10*CEILING(AM$3/100,1)+(Resumo!$B$12+Resumo!$B$14)*CEILING(AM$3,1)) -> 96.191232 | AN8: =(AA8+AN$4*(Resumo!$C$6+Resumo!$C$7+Resumo!$C$8)+Resumo!$C$10*CEILING(AN$3/100,1)+Resumo!$C$9+Resumo!$C$13+Resumo!$C$14*CEILING(AN$3,1))*(1+Resumo!$C$11)-(AN$4*(Resumo!$B$6+Resumo!$B$7)+Resumo!$B$9+Resumo!$B$10*CEILING(AN$3/100,1)+(Resumo!$B$12+Resumo!$B$14)*CEILING(AN$3,1)) -> 102.51226 | AO8: =(AB8+AO$4*(Resumo!$C$6+Resumo!$C$7+Resumo!$C$8)+Resumo!$C$10*CEILING(AO$3/100,1)+Resumo!$C$9+Resumo!$C$13+Resumo!$C$14*CEILING(AO$3,1))*(1+Resumo!$C$11)-(AO$4*(Resumo!$B$6+Resumo!$B$7)+Resumo!$B$9+Resumo!$B$10*CEILING(AO$3/100,1)+(Resumo!$B$12+Resumo!$B$14)*CEILING(AO$3,1)) -> 114.61444 | ... AT8: =(AG8+AT$4*(Resumo!$C$6+Resumo!$C$7+Resumo!$C$8)+Resumo!$C$10*CEILING(AT$3/100,1)+Resumo!$C$9+Resumo!$C$13+Resumo!$C$14*CEILING(AT$3,1))*(1+Resumo!$C$11)-(AT$4*(Resumo!$B$6+Resumo!$B$7)+Resumo!$B$9+Resumo!$B$10*CEILING(AT$3/100,1)+(Resumo!$B$12+Resumo!$B$14)*CEILING(AT$3,1)) -> 208.22433 | AU8: =1-AH8/H8 -> 0.028643609 | AV8: =1-AI8/I8 -> 0.20278324 | AW8: =1-AJ8/J8 -> 0.20796256 | AX8: =1-AK8/K8 -> 0.18472928 | AY8: =1-AL8/L8 -> 0.26186934 | AZ8: =1-AM8/M8 -> 0.31788943 | BA8: =1-AN8/N8 -> 0.29003215 | BB8: =1-AO8/O8 -> 0.35606248 | ... BG8: =1-AT8/T8 -> 0.49057021
A9: RJ | B9: Mangaratiba | C9: 23860000 | D9: 23889999 | E9: Interior | F9: 10 / 13 | G9: =COUNTIFS(Pedidos!$C$2:$C$2224,">="&C9,Pedidos!$C$2:$C$2224,"<="&D9) -> 6 | H9: 77.35 | I9: 108.83 | J9: 124.38 | K9: 124.38 | L9: 142.32 | M9: 166.05 | N9: 157.88 | O9: 197.35 | P9: 236.82 | Q9: 264.84 | R9: 300.15 | S9: 353.12 | T9: 441.4 | U9: 46.95 | V9: 65.63 | W9: 74.97 | X9: 77.7 | Y9: 83.58 | Z9: 90.2 | AA9: 96.77 | AB9: 109.63 | AC9: 119.5 | AD9: 144.24 | AE9: 155.09 | AF9: 66.69 | AG9: 214.88 | AH9: =(U9+AH$4*(Resumo!$C$6+Resumo!$C$7+Resumo!$C$8)+Resumo!$C$10*CEILING(AH$3/100,1)+Resumo!$C$9+Resumo!$C$13+Resumo!$C$14*CEILING(AH$3,1))*(1+Resumo!$C$11)-(AH$4*(Resumo!$B$6+Resumo!$B$7)+Resumo!$B$9+Resumo!$B$10*CEILING(AH$3/100,1)+(Resumo!$B$12+Resumo!$B$14)*CEILING(AH$3,1)) -> 55.347887 | AI9: =(V9+AI$4*(Resumo!$C$6+Resumo!$C$7+Resumo!$C$8)+Resumo!$C$10*CEILING(AI$3/100,1)+Resumo!$C$9+Resumo!$C$13+Resumo!$C$14*CEILING(AI$3,1))*(1+Resumo!$C$11)-(AI$4*(Resumo!$B$6+Resumo!$B$7)+Resumo!$B$9+Resumo!$B$10*CEILING(AI$3/100,1)+(Resumo!$B$12+Resumo!$B$14)*CEILING(AI$3,1)) -> 73.511357 | AJ9: =(W9+AJ$4*(Resumo!$C$6+Resumo!$C$7+Resumo!$C$8)+Resumo!$C$10*CEILING(AJ$3/100,1)+Resumo!$C$9+Resumo!$C$13+Resumo!$C$14*CEILING(AJ$3,1))*(1+Resumo!$C$11)-(AJ$4*(Resumo!$B$6+Resumo!$B$7)+Resumo!$B$9+Resumo!$B$10*CEILING(AJ$3/100,1)+(Resumo!$B$12+Resumo!$B$14)*CEILING(AJ$3,1)) -> 82.348132 | AK9: =(X9+AK$4*(Resumo!$C$6+Resumo!$C$7+Resumo!$C$8)+Resumo!$C$10*CEILING(AK$3/100,1)+Resumo!$C$9+Resumo!$C$13+Resumo!$C$14*CEILING(AK$3,1))*(1+Resumo!$C$11)-(AK$4*(Resumo!$B$6+Resumo!$B$7)+Resumo!$B$9+Resumo!$B$10*CEILING(AK$3/100,1)+(Resumo!$B$12+Resumo!$B$14)*CEILING(AK$3,1)) -> 84.763696 | AL9: =(Y9+AL$4*(Resumo!$C$6+Resumo!$C$7+Resumo!$C$8)+Resumo!$C$10*CEILING(AL$3/100,1)+Resumo!$C$9+Resumo!$C$13+Resumo!$C$14*CEILING(AL$3,1))*(1+Resumo!$C$11)-(AL$4*(Resumo!$B$6+Resumo!$B$7)+Resumo!$B$9+Resumo!$B$10*CEILING(AL$3/100,1)+(Resumo!$B$12+Resumo!$B$14)*CEILING(AL$3,1)) -> 90.27338 | AM9: =(Z9+AM$4*(Resumo!$C$6+Resumo!$C$7+Resumo!$C$8)+Resumo!$C$10*CEILING(AM$3/100,1)+Resumo!$C$9+Resumo!$C$13+Resumo!$C$14*CEILING(AM$3,1))*(1+Resumo!$C$11)-(AM$4*(Resumo!$B$6+Resumo!$B$7)+Resumo!$B$9+Resumo!$B$10*CEILING(AM$3/100,1)+(Resumo!$B$12+Resumo!$B$14)*CEILING(AM$3,1)) -> 96.191232 | AN9: =(AA9+AN$4*(Resumo!$C$6+Resumo!$C$7+Resumo!$C$8)+Resumo!$C$10*CEILING(AN$3/100,1)+Resumo!$C$9+Resumo!$C$13+Resumo!$C$14*CEILING(AN$3,1))*(1+Resumo!$C$11)-(AN$4*(Resumo!$B$6+Resumo!$B$7)+Resumo!$B$9+Resumo!$B$10*CEILING(AN$3/100,1)+(Resumo!$B$12+Resumo!$B$14)*CEILING(AN$3,1)) -> 102.51226 | AO9: =(AB9+AO$4*(Resumo!$C$6+Resumo!$C$7+Resumo!$C$8)+Resumo!$C$10*CEILING(AO$3/100,1)+Resumo!$C$9+Resumo!$C$13+Resumo!$C$14*CEILING(AO$3,1))*(1+Resumo!$C$11)-(AO$4*(Resumo!$B$6+Resumo!$B$7)+Resumo!$B$9+Resumo!$B$10*CEILING(AO$3/100,1)+(Resumo!$B$12+Resumo!$B$14)*CEILING(AO$3,1)) -> 114.61444 | ... AT9: =(AG9+AT$4*(Resumo!$C$6+Resumo!$C$7+Resumo!$C$8)+Resumo!$C$10*CEILING(AT$3/100,1)+Resumo!$C$9+Resumo!$C$13+Resumo!$C$14*CEILING(AT$3,1))*(1+Resumo!$C$11)-(AT$4*(Resumo!$B$6+Resumo!$B$7)+Resumo!$B$9+Resumo!$B$10*CEILING(AT$3/100,1)+(Resumo!$B$12+Resumo!$B$14)*CEILING(AT$3,1)) -> 208.22433 | AU9: =1-AH9/H9 -> 0.28444878 | AV9: =1-AI9/I9 -> 0.3245304 | AW9: =1-AJ9/J9 -> 0.33793108 | AX9: =1-AK9/K9 -> 0.31851024 | AY9: =1-AL9/L9 -> 0.36570138 | AZ9: =1-AM9/M9 -> 0.42070923 | BA9: =1-AN9/N9 -> 0.3506951 | BB9: =1-AO9/O9 -> 0.41923263 | ... BG9: =1-AT9/T9 -> 0.52826386
A10: RJ | B10: Seropédica | C10: 23890000 | D10: 23899999 | E10: Interior | F10: 5 / 13 | G10: =COUNTIFS(Pedidos!$C$2:$C$2224,">="&C10,Pedidos!$C$2:$C$2224,"<="&D10) -> 13 | H10: 56.98 | I10: 92.21 | J10: 103.97 | K10: 103.97 | L10: 122.3 | M10: 141.02 | N10: 144.39 | O10: 177.99 | P10: 211.59 | Q10: 249.25 | R10: 281.15 | S10: 329 | T10: 408.74 | U10: 46.95 | V10: 65.63 | W10: 74.97 | X10: 77.7 | Y10: 83.58 | Z10: 90.2 | AA10: 96.77 | AB10: 109.63 | AC10: 119.5 | AD10: 144.24 | AE10: 155.09 | AF10: 66.69 | AG10: 214.88 | AH10: =(U10+AH$4*(Resumo!$C$6+Resumo!$C$7+Resumo!$C$8)+Resumo!$C$10*CEILING(AH$3/100,1)+Resumo!$C$9+Resumo!$C$13+Resumo!$C$14*CEILING(AH$3,1))*(1+Resumo!$C$11)-(AH$4*(Resumo!$B$6+Resumo!$B$7)+Resumo!$B$9+Resumo!$B$10*CEILING(AH$3/100,1)+(Resumo!$B$12+Resumo!$B$14)*CEILING(AH$3,1)) -> 55.347887 | AI10: =(V10+AI$4*(Resumo!$C$6+Resumo!$C$7+Resumo!$C$8)+Resumo!$C$10*CEILING(AI$3/100,1)+Resumo!$C$9+Resumo!$C$13+Resumo!$C$14*CEILING(AI$3,1))*(1+Resumo!$C$11)-(AI$4*(Resumo!$B$6+Resumo!$B$7)+Resumo!$B$9+Resumo!$B$10*CEILING(AI$3/100,1)+(Resumo!$B$12+Resumo!$B$14)*CEILING(AI$3,1)) -> 73.511357 | AJ10: =(W10+AJ$4*(Resumo!$C$6+Resumo!$C$7+Resumo!$C$8)+Resumo!$C$10*CEILING(AJ$3/100,1)+Resumo!$C$9+Resumo!$C$13+Resumo!$C$14*CEILING(AJ$3,1))*(1+Resumo!$C$11)-(AJ$4*(Resumo!$B$6+Resumo!$B$7)+Resumo!$B$9+Resumo!$B$10*CEILING(AJ$3/100,1)+(Resumo!$B$12+Resumo!$B$14)*CEILING(AJ$3,1)) -> 82.348132 | AK10: =(X10+AK$4*(Resumo!$C$6+Resumo!$C$7+Resumo!$C$8)+Resumo!$C$10*CEILING(AK$3/100,1)+Resumo!$C$9+Resumo!$C$13+Resumo!$C$14*CEILING(AK$3,1))*(1+Resumo!$C$11)-(AK$4*(Resumo!$B$6+Resumo!$B$7)+Resumo!$B$9+Resumo!$B$10*CEILING(AK$3/100,1)+(Resumo!$B$12+Resumo!$B$14)*CEILING(AK$3,1)) -> 84.763696 | AL10: =(Y10+AL$4*(Resumo!$C$6+Resumo!$C$7+Resumo!$C$8)+Resumo!$C$10*CEILING(AL$3/100,1)+Resumo!$C$9+Resumo!$C$13+Resumo!$C$14*CEILING(AL$3,1))*(1+Resumo!$C$11)-(AL$4*(Resumo!$B$6+Resumo!$B$7)+Resumo!$B$9+Resumo!$B$10*CEILING(AL$3/100,1)+(Resumo!$B$12+Resumo!$B$14)*CEILING(AL$3,1)) -> 90.27338 | AM10: =(Z10+AM$4*(Resumo!$C$6+Resumo!$C$7+Resumo!$C$8)+Resumo!$C$10*CEILING(AM$3/100,1)+Resumo!$C$9+Resumo!$C$13+Resumo!$C$14*CEILING(AM$3,1))*(1+Resumo!$C$11)-(AM$4*(Resumo!$B$6+Resumo!$B$7)+Resumo!$B$9+Resumo!$B$10*CEILING(AM$3/100,1)+(Resumo!$B$12+Resumo!$B$14)*CEILING(AM$3,1)) -> 96.191232 | AN10: =(AA10+AN$4*(Resumo!$C$6+Resumo!$C$7+Resumo!$C$8)+Resumo!$C$10*CEILING(AN$3/100,1)+Resumo!$C$9+Resumo!$C$13+Resumo!$C$14*CEILING(AN$3,1))*(1+Resumo!$C$11)-(AN$4*(Resumo!$B$6+Resumo!$B$7)+Resumo!$B$9+Resumo!$B$10*CEILING(AN$3/100,1)+(Resumo!$B$12+Resumo!$B$14)*CEILING(AN$3,1)) -> 102.51226 | AO10: =(AB10+AO$4*(Resumo!$C$6+Resumo!$C$7+Resumo!$C$8)+Resumo!$C$10*CEILING(AO$3/100,1)+Resumo!$C$9+Resumo!$C$13+Resumo!$C$14*CEILING(AO$3,1))*(1+Resumo!$C$11)-(AO$4*(Resumo!$B$6+Resumo!$B$7)+Resumo!$B$9+Resumo!$B$10*CEILING(AO$3/100,1)+(Resumo!$B$12+Resumo!$B$14)*CEILING(AO$3,1)) -> 114.61444 | ... AT10: =(AG10+AT$4*(Resumo!$C$6+Resumo!$C$7+Resumo!$C$8)+Resumo!$C$10*CEILING(AT$3/100,1)+Resumo!$C$9+Resumo!$C$13+Resumo!$C$14*CEILING(AT$3,1))*(1+Resumo!$C$11)-(AT$4*(Resumo!$B$6+Resumo!$B$7)+Resumo!$B$9+Resumo!$B$10*CEILING(AT$3/100,1)+(Resumo!$B$12+Resumo!$B$14)*CEILING(AT$3,1)) -> 208.22433 | AU10: =1-AH10/H10 -> 0.028643609 | AV10: =1-AI10/I10 -> 0.20278324 | AW10: =1-AJ10/J10 -> 0.20796256 | AX10: =1-AK10/K10 -> 0.18472928 | AY10: =1-AL10/L10 -> 0.26186934 | AZ10: =1-AM10/M10 -> 0.31788943 | BA10: =1-AN10/N10 -> 0.29003215 | BB10: =1-AO10/O10 -> 0.35606248 | ... BG10: =1-AT10/T10 -> 0.49057021
A11: RJ | B11: Angra dos Reis | C11: 23900000 | D11: 23969999 | E11: Interior | F11: 10 / 13 | G11: =COUNTIFS(Pedidos!$C$2:$C$2224,">="&C11,Pedidos!$C$2:$C$2224,"<="&D11) -> 35 | H11: 77.35 | I11: 108.83 | J11: 124.38 | K11: 124.38 | L11: 142.32 | M11: 166.05 | N11: 157.88 | O11: 197.35 | P11: 236.82 | Q11: 264.84 | R11: 300.15 | S11: 353.12 | T11: 441.4 | U11: 46.95 | V11: 65.63 | W11: 74.97 | X11: 77.7 | Y11: 83.58 | Z11: 90.2 | AA11: 96.77 | AB11: 109.63 | AC11: 119.5 | AD11: 144.24 | AE11: 155.09 | AF11: 66.69 | AG11: 214.88 | AH11: =(U11+AH$4*(Resumo!$C$6+Resumo!$C$7+Resumo!$C$8)+Resumo!$C$10*CEILING(AH$3/100,1)+Resumo!$C$9+Resumo!$C$13+Resumo!$C$14*CEILING(AH$3,1))*(1+Resumo!$C$11)-(AH$4*(Resumo!$B$6+Resumo!$B$7)+Resumo!$B$9+Resumo!$B$10*CEILING(AH$3/100,1)+(Resumo!$B$12+Resumo!$B$14)*CEILING(AH$3,1)) -> 55.347887 | AI11: =(V11+AI$4*(Resumo!$C$6+Resumo!$C$7+Resumo!$C$8)+Resumo!$C$10*CEILING(AI$3/100,1)+Resumo!$C$9+Resumo!$C$13+Resumo!$C$14*CEILING(AI$3,1))*(1+Resumo!$C$11)-(AI$4*(Resumo!$B$6+Resumo!$B$7)+Resumo!$B$9+Resumo!$B$10*CEILING(AI$3/100,1)+(Resumo!$B$12+Resumo!$B$14)*CEILING(AI$3,1)) -> 73.511357 | AJ11: =(W11+AJ$4*(Resumo!$C$6+Resumo!$C$7+Resumo!$C$8)+Resumo!$C$10*CEILING(AJ$3/100,1)+Resumo!$C$9+Resumo!$C$13+Resumo!$C$14*CEILING(AJ$3,1))*(1+Resumo!$C$11)-(AJ$4*(Resumo!$B$6+Resumo!$B$7)+Resumo!$B$9+Resumo!$B$10*CEILING(AJ$3/100,1)+(Resumo!$B$12+Resumo!$B$14)*CEILING(AJ$3,1)) -> 82.348132 | AK11: =(X11+AK$4*(Resumo!$C$6+Resumo!$C$7+Resumo!$C$8)+Resumo!$C$10*CEILING(AK$3/100,1)+Resumo!$C$9+Resumo!$C$13+Resumo!$C$14*CEILING(AK$3,1))*(1+Resumo!$C$11)-(AK$4*(Resumo!$B$6+Resumo!$B$7)+Resumo!$B$9+Resumo!$B$10*CEILING(AK$3/100,1)+(Resumo!$B$12+Resumo!$B$14)*CEILING(AK$3,1)) -> 84.763696 | AL11: =(Y11+AL$4*(Resumo!$C$6+Resumo!$C$7+Resumo!$C$8)+Resumo!$C$10*CEILING(AL$3/100,1)+Resumo!$C$9+Resumo!$C$13+Resumo!$C$14*CEILING(AL$3,1))*(1+Resumo!$C$11)-(AL$4*(Resumo!$B$6+Resumo!$B$7)+Resumo!$B$9+Resumo!$B$10*CEILING(AL$3/100,1)+(Resumo!$B$12+Resumo!$B$14)*CEILING(AL$3,1)) -> 90.27338 | AM11: =(Z11+AM$4*(Resumo!$C$6+Resumo!$C$7+Resumo!$C$8)+Resumo!$C$10*CEILING(AM$3/100,1)+Resumo!$C$9+Resumo!$C$13+Resumo!$C$14*CEILING(AM$3,1))*(1+Resumo!$C$11)-(AM$4*(Resumo!$B$6+Resumo!$B$7)+Resumo!$B$9+Resumo!$B$10*CEILING(AM$3/100,1)+(Resumo!$B$12+Resumo!$B$14)*CEILING(AM$3,1)) -> 96.191232 | AN11: =(AA11+AN$4*(Resumo!$C$6+Resumo!$C$7+Resumo!$C$8)+Resumo!$C$10*CEILING(AN$3/100,1)+Resumo!$C$9+Resumo!$C$13+Resumo!$C$14*CEILING(AN$3,1))*(1+Resumo!$C$11)-(AN$4*(Resumo!$B$6+Resumo!$B$7)+Resumo!$B$9+Resumo!$B$10*CEILING(AN$3/100,1)+(Resumo!$B$12+Resumo!$B$14)*CEILING(AN$3,1)) -> 102.51226 | AO11: =(AB11+AO$4*(Resumo!$C$6+Resumo!$C$7+Resumo!$C$8)+Resumo!$C$10*CEILING(AO$3/100,1)+Resumo!$C$9+Resumo!$C$13+Resumo!$C$14*CEILING(AO$3,1))*(1+Resumo!$C$11)-(AO$4*(Resumo!$B$6+Resumo!$B$7)+Resumo!$B$9+Resumo!$B$10*CEILING(AO$3/100,1)+(Resumo!$B$12+Resumo!$B$14)*CEILING(AO$3,1)) -> 114.61444 | ... AT11: =(AG11+AT$4*(Resumo!$C$6+Resumo!$C$7+Resumo!$C$8)+Resumo!$C$10*CEILING(AT$3/100,1)+Resumo!$C$9+Resumo!$C$13+Resumo!$C$14*CEILING(AT$3,1))*(1+Resumo!$C$11)-(AT$4*(Resumo!$B$6+Resumo!$B$7)+Resumo!$B$9+Resumo!$B$10*CEILING(AT$3/100,1)+(Resumo!$B$12+Resumo!$B$14)*CEILING(AT$3,1)) -> 208.22433 | AU11: =1-AH11/H11 -> 0.28444878 | AV11: =1-AI11/I11 -> 0.3245304 | AW11: =1-AJ11/J11 -> 0.33793108 | AX11: =1-AK11/K11 -> 0.31851024 | AY11: =1-AL11/L11 -> 0.36570138 | AZ11: =1-AM11/M11 -> 0.42070923 | BA11: =1-AN11/N11 -> 0.3506951 | BB11: =1-AO11/O11 -> 0.41923263 | ... BG11: =1-AT11/T11 -> 0.52826386
A12: RJ | B12: Paraty | C12: 23970000 | D12: 23999999 | E12: Interior | F12: 10 / 13 | G12: =COUNTIFS(Pedidos!$C$2:$C$2224,">="&C12,Pedidos!$C$2:$C$2224,"<="&D12) -> 5 | H12: 77.35 | I12: 108.83 | J12: 124.38 | K12: 124.38 | L12: 142.32 | M12: 166.05 | N12: 157.88 | O12: 197.35 | P12: 236.82 | Q12: 264.84 | R12: 300.15 | S12: 353.12 | T12: 441.4 | U12: 46.95 | V12: 65.63 | W12: 74.97 | X12: 77.7 | Y12: 83.58 | Z12: 90.2 | AA12: 96.77 | AB12: 109.63 | AC12: 119.5 | AD12: 144.24 | AE12: 155.09 | AF12: 66.69 | AG12: 214.88 | AH12: =(U12+AH$4*(Resumo!$C$6+Resumo!$C$7+Resumo!$C$8)+Resumo!$C$10*CEILING(AH$3/100,1)+Resumo!$C$9+Resumo!$C$13+Resumo!$C$14*CEILING(AH$3,1))*(1+Resumo!$C$11)-(AH$4*(Resumo!$B$6+Resumo!$B$7)+Resumo!$B$9+Resumo!$B$10*CEILING(AH$3/100,1)+(Resumo!$B$12+Resumo!$B$14)*CEILING(AH$3,1)) -> 55.347887 | AI12: =(V12+AI$4*(Resumo!$C$6+Resumo!$C$7+Resumo!$C$8)+Resumo!$C$10*CEILING(AI$3/100,1)+Resumo!$C$9+Resumo!$C$13+Resumo!$C$14*CEILING(AI$3,1))*(1+Resumo!$C$11)-(AI$4*(Resumo!$B$6+Resumo!$B$7)+Resumo!$B$9+Resumo!$B$10*CEILING(AI$3/100,1)+(Resumo!$B$12+Resumo!$B$14)*CEILING(AI$3,1)) -> 73.511357 | AJ12: =(W12+AJ$4*(Resumo!$C$6+Resumo!$C$7+Resumo!$C$8)+Resumo!$C$10*CEILING(AJ$3/100,1)+Resumo!$C$9+Resumo!$C$13+Resumo!$C$14*CEILING(AJ$3,1))*(1+Resumo!$C$11)-(AJ$4*(Resumo!$B$6+Resumo!$B$7)+Resumo!$B$9+Resumo!$B$10*CEILING(AJ$3/100,1)+(Resumo!$B$12+Resumo!$B$14)*CEILING(AJ$3,1)) -> 82.348132 | AK12: =(X12+AK$4*(Resumo!$C$6+Resumo!$C$7+Resumo!$C$8)+Resumo!$C$10*CEILING(AK$3/100,1)+Resumo!$C$9+Resumo!$C$13+Resumo!$C$14*CEILING(AK$3,1))*(1+Resumo!$C$11)-(AK$4*(Resumo!$B$6+Resumo!$B$7)+Resumo!$B$9+Resumo!$B$10*CEILING(AK$3/100,1)+(Resumo!$B$12+Resumo!$B$14)*CEILING(AK$3,1)) -> 84.763696 | AL12: =(Y12+AL$4*(Resumo!$C$6+Resumo!$C$7+Resumo!$C$8)+Resumo!$C$10*CEILING(AL$3/100,1)+Resumo!$C$9+Resumo!$C$13+Resumo!$C$14*CEILING(AL$3,1))*(1+Resumo!$C$11)-(AL$4*(Resumo!$B$6+Resumo!$B$7)+Resumo!$B$9+Resumo!$B$10*CEILING(AL$3/100,1)+(Resumo!$B$12+Resumo!$B$14)*CEILING(AL$3,1)) -> 90.27338 | AM12: =(Z12+AM$4*(Resumo!$C$6+Resumo!$C$7+Resumo!$C$8)+Resumo!$C$10*CEILING(AM$3/100,1)+Resumo!$C$9+Resumo!$C$13+Resumo!$C$14*CEILING(AM$3,1))*(1+Resumo!$C$11)-(AM$4*(Resumo!$B$6+Resumo!$B$7)+Resumo!$B$9+Resumo!$B$10*CEILING(AM$3/100,1)+(Resumo!$B$12+Resumo!$B$14)*CEILING(AM$3,1)) -> 96.191232 | AN12: =(AA12+AN$4*(Resumo!$C$6+Resumo!$C$7+Resumo!$C$8)+Resumo!$C$10*CEILING(AN$3/100,1)+Resumo!$C$9+Resumo!$C$13+Resumo!$C$14*CEILING(AN$3,1))*(1+Resumo!$C$11)-(AN$4*(Resumo!$B$6+Resumo!$B$7)+Resumo!$B$9+Resumo!$B$10*CEILING(AN$3/100,1)+(Resumo!$B$12+Resumo!$B$14)*CEILING(AN$3,1)) -> 102.51226 | AO12: =(AB12+AO$4*(Resumo!$C$6+Resumo!$C$7+Resumo!$C$8)+Resumo!$C$10*CEILING(AO$3/100,1)+Resumo!$C$9+Resumo!$C$13+Resumo!$C$14*CEILING(AO$3,1))*(1+Resumo!$C$11)-(AO$4*(Resumo!$B$6+Resumo!$B$7)+Resumo!$B$9+Resumo!$B$10*CEILING(AO$3/100,1)+(Resumo!$B$12+Resumo!$B$14)*CEILING(AO$3,1)) -> 114.61444 | ... AT12: =(AG12+AT$4*(Resumo!$C$6+Resumo!$C$7+Resumo!$C$8)+Resumo!$C$10*CEILING(AT$3/100,1)+Resumo!$C$9+Resumo!$C$13+Resumo!$C$14*CEILING(AT$3,1))*(1+Resumo!$C$11)-(AT$4*(Resumo!$B$6+Resumo!$B$7)+Resumo!$B$9+Resumo!$B$10*CEILING(AT$3/100,1)+(Resumo!$B$12+Resumo!$B$14)*CEILING(AT$3,1)) -> 208.22433 | AU12: =1-AH12/H12 -> 0.28444878 | AV12: =1-AI12/I12 -> 0.3245304 | AW12: =1-AJ12/J12 -> 0.33793108 | AX12: =1-AK12/K12 -> 0.31851024 | AY12: =1-AL12/L12 -> 0.36570138 | AZ12: =1-AM12/M12 -> 0.42070923 | BA12: =1-AN12/N12 -> 0.3506951 | BB12: =1-AO12/O12 -> 0.41923263 | ... BG12: =1-AT12/T12 -> 0.52826386
A13: RJ | B13: Niterói | C13: 24000000 | D13: 24399999 | E13: Metropolitana | F13: 7 / 2 | G13: =COUNTIFS(Pedidos!$C$2:$C$2224,">="&C13,Pedidos!$C$2:$C$2224,"<="&D13) -> 68 | H13: 57.47 | I13: 100.58 | J13: 114.95 | K13: 114.95 | L13: 128.14 | M13: 149.5 | N13: 142.74 | O13: 178.42 | P13: 214.11 | Q13: 249.03 | R13: 282.23 | S13: 332.05 | T13: 415.05 | U13: 42.72 | V13: 58.8 | W13: 66.83 | X13: 65.36 | Y13: 70.98 | Z13: 76.55 | AA13: 82.48 | AB13: 92.32 | AC13: 101.26 | AD13: 129.62 | AE13: 139.81 | AF13: 155.09 | AG13: 194.34 | AH13: =(U13+AH$4*(Resumo!$C$6+Resumo!$C$7+Resumo!$C$8)+Resumo!$C$10*CEILING(AH$3/100,1)+Resumo!$C$9+Resumo!$C$13+Resumo!$C$14*CEILING(AH$3,1))*(1+Resumo!$C$11)-(AH$4*(Resumo!$B$6+Resumo!$B$7)+Resumo!$B$9+Resumo!$B$10*CEILING(AH$3/100,1)+(Resumo!$B$12+Resumo!$B$14)*CEILING(AH$3,1)) -> 51.117887 | AI13: =(V13+AI$4*(Resumo!$C$6+Resumo!$C$7+Resumo!$C$8)+Resumo!$C$10*CEILING(AI$3/100,1)+Resumo!$C$9+Resumo!$C$13+Resumo!$C$14*CEILING(AI$3,1))*(1+Resumo!$C$11)-(AI$4*(Resumo!$B$6+Resumo!$B$7)+Resumo!$B$9+Resumo!$B$10*CEILING(AI$3/100,1)+(Resumo!$B$12+Resumo!$B$14)*CEILING(AI$3,1)) -> 66.681357 | AJ13: =(W13+AJ$4*(Resumo!$C$6+Resumo!$C$7+Resumo!$C$8)+Resumo!$C$10*CEILING(AJ$3/100,1)+Resumo!$C$9+Resumo!$C$13+Resumo!$C$14*CEILING(AJ$3,1))*(1+Resumo!$C$11)-(AJ$4*(Resumo!$B$6+Resumo!$B$7)+Resumo!$B$9+Resumo!$B$10*CEILING(AJ$3/100,1)+(Resumo!$B$12+Resumo!$B$14)*CEILING(AJ$3,1)) -> 74.208132 | AK13: =(X13+AK$4*(Resumo!$C$6+Resumo!$C$7+Resumo!$C$8)+Resumo!$C$10*CEILING(AK$3/100,1)+Resumo!$C$9+Resumo!$C$13+Resumo!$C$14*CEILING(AK$3,1))*(1+Resumo!$C$11)-(AK$4*(Resumo!$B$6+Resumo!$B$7)+Resumo!$B$9+Resumo!$B$10*CEILING(AK$3/100,1)+(Resumo!$B$12+Resumo!$B$14)*CEILING(AK$3,1)) -> 72.423696 | AL13: =(Y13+AL$4*(Resumo!$C$6+Resumo!$C$7+Resumo!$C$8)+Resumo!$C$10*CEILING(AL$3/100,1)+Resumo!$C$9+Resumo!$C$13+Resumo!$C$14*CEILING(AL$3,1))*(1+Resumo!$C$11)-(AL$4*(Resumo!$B$6+Resumo!$B$7)+Resumo!$B$9+Resumo!$B$10*CEILING(AL$3/100,1)+(Resumo!$B$12+Resumo!$B$14)*CEILING(AL$3,1)) -> 77.67338 | AM13: =(Z13+AM$4*(Resumo!$C$6+Resumo!$C$7+Resumo!$C$8)+Resumo!$C$10*CEILING(AM$3/100,1)+Resumo!$C$9+Resumo!$C$13+Resumo!$C$14*CEILING(AM$3,1))*(1+Resumo!$C$11)-(AM$4*(Resumo!$B$6+Resumo!$B$7)+Resumo!$B$9+Resumo!$B$10*CEILING(AM$3/100,1)+(Resumo!$B$12+Resumo!$B$14)*CEILING(AM$3,1)) -> 82.541232 | AN13: =(AA13+AN$4*(Resumo!$C$6+Resumo!$C$7+Resumo!$C$8)+Resumo!$C$10*CEILING(AN$3/100,1)+Resumo!$C$9+Resumo!$C$13+Resumo!$C$14*CEILING(AN$3,1))*(1+Resumo!$C$11)-(AN$4*(Resumo!$B$6+Resumo!$B$7)+Resumo!$B$9+Resumo!$B$10*CEILING(AN$3/100,1)+(Resumo!$B$12+Resumo!$B$14)*CEILING(AN$3,1)) -> 88.222258 | AO13: =(AB13+AO$4*(Resumo!$C$6+Resumo!$C$7+Resumo!$C$8)+Resumo!$C$10*CEILING(AO$3/100,1)+Resumo!$C$9+Resumo!$C$13+Resumo!$C$14*CEILING(AO$3,1))*(1+Resumo!$C$11)-(AO$4*(Resumo!$B$6+Resumo!$B$7)+Resumo!$B$9+Resumo!$B$10*CEILING(AO$3/100,1)+(Resumo!$B$12+Resumo!$B$14)*CEILING(AO$3,1)) -> 97.30444 | ... AT13: =(AG13+AT$4*(Resumo!$C$6+Resumo!$C$7+Resumo!$C$8)+Resumo!$C$10*CEILING(AT$3/100,1)+Resumo!$C$9+Resumo!$C$13+Resumo!$C$14*CEILING(AT$3,1))*(1+Resumo!$C$11)-(AT$4*(Resumo!$B$6+Resumo!$B$7)+Resumo!$B$9+Resumo!$B$10*CEILING(AT$3/100,1)+(Resumo!$B$12+Resumo!$B$14)*CEILING(AT$3,1)) -> 187.68433 | AU13: =1-AH13/H13 -> 0.11052919 | AV13: =1-AI13/I13 -> 0.33703165 | AW13: =1-AJ13/J13 -> 0.35443121 | AX13: =1-AK13/K13 -> 0.36995479 | AY13: =1-AL13/L13 -> 0.3938397 | AZ13: =1-AM13/M13 -> 0.44788473 | BA13: =1-AN13/N13 -> 0.38193738 | BB13: =1-AO13/O13 -> 0.45463267 | ... BG13: =1-AT13/T13 -> 0.54780308
A14: RJ | B14: São Gonçalo | C14: 24400000 | D14: 24799999 | E14: Metropolitana | F14: 7 / 2 | G14: =COUNTIFS(Pedidos!$C$2:$C$2224,">="&C14,Pedidos!$C$2:$C$2224,"<="&D14) -> 135 | H14: 57.47 | I14: 100.58 | J14: 114.95 | K14: 114.95 | L14: 128.14 | M14: 149.5 | N14: 142.74 | O14: 178.42 | P14: 214.11 | Q14: 249.03 | R14: 282.23 | S14: 332.05 | T14: 415.05 | U14: 42.72 | V14: 58.8 | W14: 66.83 | X14: 65.36 | Y14: 70.98 | Z14: 76.55 | AA14: 82.48 | AB14: 92.32 | AC14: 101.26 | AD14: 129.62 | AE14: 139.81 | AF14: 155.09 | AG14: 194.34 | AH14: =(U14+AH$4*(Resumo!$C$6+Resumo!$C$7+Resumo!$C$8)+Resumo!$C$10*CEILING(AH$3/100,1)+Resumo!$C$9+Resumo!$C$13+Resumo!$C$14*CEILING(AH$3,1))*(1+Resumo!$C$11)-(AH$4*(Resumo!$B$6+Resumo!$B$7)+Resumo!$B$9+Resumo!$B$10*CEILING(AH$3/100,1)+(Resumo!$B$12+Resumo!$B$14)*CEILING(AH$3,1)) -> 51.117887 | AI14: =(V14+AI$4*(Resumo!$C$6+Resumo!$C$7+Resumo!$C$8)+Resumo!$C$10*CEILING(AI$3/100,1)+Resumo!$C$9+Resumo!$C$13+Resumo!$C$14*CEILING(AI$3,1))*(1+Resumo!$C$11)-(AI$4*(Resumo!$B$6+Resumo!$B$7)+Resumo!$B$9+Resumo!$B$10*CEILING(AI$3/100,1)+(Resumo!$B$12+Resumo!$B$14)*CEILING(AI$3,1)) -> 66.681357 | AJ14: =(W14+AJ$4*(Resumo!$C$6+Resumo!$C$7+Resumo!$C$8)+Resumo!$C$10*CEILING(AJ$3/100,1)+Resumo!$C$9+Resumo!$C$13+Resumo!$C$14*CEILING(AJ$3,1))*(1+Resumo!$C$11)-(AJ$4*(Resumo!$B$6+Resumo!$B$7)+Resumo!$B$9+Resumo!$B$10*CEILING(AJ$3/100,1)+(Resumo!$B$12+Resumo!$B$14)*CEILING(AJ$3,1)) -> 74.208132 | AK14: =(X14+AK$4*(Resumo!$C$6+Resumo!$C$7+Resumo!$C$8)+Resumo!$C$10*CEILING(AK$3/100,1)+Resumo!$C$9+Resumo!$C$13+Resumo!$C$14*CEILING(AK$3,1))*(1+Resumo!$C$11)-(AK$4*(Resumo!$B$6+Resumo!$B$7)+Resumo!$B$9+Resumo!$B$10*CEILING(AK$3/100,1)+(Resumo!$B$12+Resumo!$B$14)*CEILING(AK$3,1)) -> 72.423696 | AL14: =(Y14+AL$4*(Resumo!$C$6+Resumo!$C$7+Resumo!$C$8)+Resumo!$C$10*CEILING(AL$3/100,1)+Resumo!$C$9+Resumo!$C$13+Resumo!$C$14*CEILING(AL$3,1))*(1+Resumo!$C$11)-(AL$4*(Resumo!$B$6+Resumo!$B$7)+Resumo!$B$9+Resumo!$B$10*CEILING(AL$3/100,1)+(Resumo!$B$12+Resumo!$B$14)*CEILING(AL$3,1)) -> 77.67338 | AM14: =(Z14+AM$4*(Resumo!$C$6+Resumo!$C$7+Resumo!$C$8)+Resumo!$C$10*CEILING(AM$3/100,1)+Resumo!$C$9+Resumo!$C$13+Resumo!$C$14*CEILING(AM$3,1))*(1+Resumo!$C$11)-(AM$4*(Resumo!$B$6+Resumo!$B$7)+Resumo!$B$9+Resumo!$B$10*CEILING(AM$3/100,1)+(Resumo!$B$12+Resumo!$B$14)*CEILING(AM$3,1)) -> 82.541232 | AN14: =(AA14+AN$4*(Resumo!$C$6+Resumo!$C$7+Resumo!$C$8)+Resumo!$C$10*CEILING(AN$3/100,1)+Resumo!$C$9+Resumo!$C$13+Resumo!$C$14*CEILING(AN$3,1))*(1+Resumo!$C$11)-(AN$4*(Resumo!$B$6+Resumo!$B$7)+Resumo!$B$9+Resumo!$B$10*CEILING(AN$3/100,1)+(Resumo!$B$12+Resumo!$B$14)*CEILING(AN$3,1)) -> 88.222258 | AO14: =(AB14+AO$4*(Resumo!$C$6+Resumo!$C$7+Resumo!$C$8)+Resumo!$C$10*CEILING(AO$3/100,1)+Resumo!$C$9+Resumo!$C$13+Resumo!$C$14*CEILING(AO$3,1))*(1+Resumo!$C$11)-(AO$4*(Resumo!$B$6+Resumo!$B$7)+Resumo!$B$9+Resumo!$B$10*CEILING(AO$3/100,1)+(Resumo!$B$12+Resumo!$B$14)*CEILING(AO$3,1)) -> 97.30444 | ... AT14: =(AG14+AT$4*(Resumo!$C$6+Resumo!$C$7+Resumo!$C$8)+Resumo!$C$10*CEILING(AT$3/100,1)+Resumo!$C$9+Resumo!$C$13+Resumo!$C$14*CEILING(AT$3,1))*(1+Resumo!$C$11)-(AT$4*(Resumo!$B$6+Resumo!$B$7)+Resumo!$B$9+Resumo!$B$10*CEILING(AT$3/100,1)+(Resumo!$B$12+Resumo!$B$14)*CEILING(AT$3,1)) -> 187.68433 | AU14: =1-AH14/H14 -> 0.11052919 | AV14: =1-AI14/I14 -> 0.33703165 | AW14: =1-AJ14/J14 -> 0.35443121 | AX14: =1-AK14/K14 -> 0.36995479 | AY14: =1-AL14/L14 -> 0.3938397 | AZ14: =1-AM14/M14 -> 0.44788473 | BA14: =1-AN14/N14 -> 0.38193738 | BB14: =1-AO14/O14 -> 0.45463267 | ... BG14: =1-AT14/T14 -> 0.54780308
A15: RJ | B15: Itaboraí | C15: 24800000 | D15: 24889999 | E15: Interior | F15: 7 / 13 | G15: =COUNTIFS(Pedidos!$C$2:$C$2224,">="&C15,Pedidos!$C$2:$C$2224,"<="&D15) -> 25 | H15: 57.47 | I15: 100.58 | J15: 114.95 | K15: 114.95 | L15: 128.14 | M15: 149.5 | N15: 142.74 | O15: 178.42 | P15: 214.11 | Q15: 249.03 | R15: 282.23 | S15: 332.05 | T15: 415.05 | U15: 46.95 | V15: 65.63 | W15: 74.97 | X15: 77.7 | Y15: 83.58 | Z15: 90.2 | AA15: 96.77 | AB15: 109.63 | AC15: 119.5 | AD15: 144.24 | AE15: 155.09 | AF15: 66.69 | AG15: 214.88 | AH15: =(U15+AH$4*(Resumo!$C$6+Resumo!$C$7+Resumo!$C$8)+Resumo!$C$10*CEILING(AH$3/100,1)+Resumo!$C$9+Resumo!$C$13+Resumo!$C$14*CEILING(AH$3,1))*(1+Resumo!$C$11)-(AH$4*(Resumo!$B$6+Resumo!$B$7)+Resumo!$B$9+Resumo!$B$10*CEILING(AH$3/100,1)+(Resumo!$B$12+Resumo!$B$14)*CEILING(AH$3,1)) -> 55.347887 | AI15: =(V15+AI$4*(Resumo!$C$6+Resumo!$C$7+Resumo!$C$8)+Resumo!$C$10*CEILING(AI$3/100,1)+Resumo!$C$9+Resumo!$C$13+Resumo!$C$14*CEILING(AI$3,1))*(1+Resumo!$C$11)-(AI$4*(Resumo!$B$6+Resumo!$B$7)+Resumo!$B$9+Resumo!$B$10*CEILING(AI$3/100,1)+(Resumo!$B$12+Resumo!$B$14)*CEILING(AI$3,1)) -> 73.511357 | AJ15: =(W15+AJ$4*(Resumo!$C$6+Resumo!$C$7+Resumo!$C$8)+Resumo!$C$10*CEILING(AJ$3/100,1)+Resumo!$C$9+Resumo!$C$13+Resumo!$C$14*CEILING(AJ$3,1))*(1+Resumo!$C$11)-(AJ$4*(Resumo!$B$6+Resumo!$B$7)+Resumo!$B$9+Resumo!$B$10*CEILING(AJ$3/100,1)+(Resumo!$B$12+Resumo!$B$14)*CEILING(AJ$3,1)) -> 82.348132 | AK15: =(X15+AK$4*(Resumo!$C$6+Resumo!$C$7+Resumo!$C$8)+Resumo!$C$10*CEILING(AK$3/100,1)+Resumo!$C$9+Resumo!$C$13+Resumo!$C$14*CEILING(AK$3,1))*(1+Resumo!$C$11)-(AK$4*(Resumo!$B$6+Resumo!$B$7)+Resumo!$B$9+Resumo!$B$10*CEILING(AK$3/100,1)+(Resumo!$B$12+Resumo!$B$14)*CEILING(AK$3,1)) -> 84.763696 | AL15: =(Y15+AL$4*(Resumo!$C$6+Resumo!$C$7+Resumo!$C$8)+Resumo!$C$10*CEILING(AL$3/100,1)+Resumo!$C$9+Resumo!$C$13+Resumo!$C$14*CEILING(AL$3,1))*(1+Resumo!$C$11)-(AL$4*(Resumo!$B$6+Resumo!$B$7)+Resumo!$B$9+Resumo!$B$10*CEILING(AL$3/100,1)+(Resumo!$B$12+Resumo!$B$14)*CEILING(AL$3,1)) -> 90.27338 | AM15: =(Z15+AM$4*(Resumo!$C$6+Resumo!$C$7+Resumo!$C$8)+Resumo!$C$10*CEILING(AM$3/100,1)+Resumo!$C$9+Resumo!$C$13+Resumo!$C$14*CEILING(AM$3,1))*(1+Resumo!$C$11)-(AM$4*(Resumo!$B$6+Resumo!$B$7)+Resumo!$B$9+Resumo!$B$10*CEILING(AM$3/100,1)+(Resumo!$B$12+Resumo!$B$14)*CEILING(AM$3,1)) -> 96.191232 | AN15: =(AA15+AN$4*(Resumo!$C$6+Resumo!$C$7+Resumo!$C$8)+Resumo!$C$10*CEILING(AN$3/100,1)+Resumo!$C$9+Resumo!$C$13+Resumo!$C$14*CEILING(AN$3,1))*(1+Resumo!$C$11)-(AN$4*(Resumo!$B$6+Resumo!$B$7)+Resumo!$B$9+Resumo!$B$10*CEILING(AN$3/100,1)+(Resumo!$B$12+Resumo!$B$14)*CEILING(AN$3,1)) -> 102.51226 | AO15: =(AB15+AO$4*(Resumo!$C$6+Resumo!$C$7+Resumo!$C$8)+Resumo!$C$10*CEILING(AO$3/100,1)+Resumo!$C$9+Resumo!$C$13+Resumo!$C$14*CEILING(AO$3,1))*(1+Resumo!$C$11)-(AO$4*(Resumo!$B$6+Resumo!$B$7)+Resumo!$B$9+Resumo!$B$10*CEILING(AO$3/100,1)+(Resumo!$B$12+Resumo!$B$14)*CEILING(AO$3,1)) -> 114.61444 | ... AT15: =(AG15+AT$4*(Resumo!$C$6+Resumo!$C$7+Resumo!$C$8)+Resumo!$C$10*CEILING(AT$3/100,1)+Resumo!$C$9+Resumo!$C$13+Resumo!$C$14*CEILING(AT$3,1))*(1+Resumo!$C$11)-(AT$4*(Resumo!$B$6+Resumo!$B$7)+Resumo!$B$9+Resumo!$B$10*CEILING(AT$3/100,1)+(Resumo!$B$12+Resumo!$B$14)*CEILING(AT$3,1)) -> 208.22433 | AU15: =1-AH15/H15 -> 0.036925575 | AV15: =1-AI15/I15 -> 0.2691255 | AW15: =1-AJ15/J15 -> 0.28361781 | AX15: =1-AK15/K15 -> 0.26260377 | AY15: =1-AL15/L15 -> 0.29550975 | AZ15: =1-AM15/M15 -> 0.35658039 | BA15: =1-AN15/N15 -> 0.28182529 | BB15: =1-AO15/O15 -> 0.35761439 | ... BG15: =1-AT15/T15 -> 0.49831507
A16: RJ | B16: Tanguá | C16: 24890000 | D16: 24899999 | E16: Interior | F16: 7 / 13 | G16: =COUNTIFS(Pedidos!$C$2:$C$2224,">="&C16,Pedidos!$C$2:$C$2224,"<="&D16) -> 0 | H16: 57.47 | I16: 100.58 | J16: 114.95 | K16: 114.95 | L16: 128.14 | M16: 149.5 | N16: 142.74 | O16: 178.42 | P16: 214.11 | Q16: 249.03 | R16: 282.23 | S16: 332.05 | T16: 415.05 | U16: 46.95 | V16: 65.63 | W16: 74.97 | X16: 77.7 | Y16: 83.58 | Z16: 90.2 | AA16: 96.77 | AB16: 109.63 | AC16: 119.5 | AD16: 144.24 | AE16: 155.09 | AF16: 66.69 | AG16: 214.88 | AH16: =(U16+AH$4*(Resumo!$C$6+Resumo!$C$7+Resumo!$C$8)+Resumo!$C$10*CEILING(AH$3/100,1)+Resumo!$C$9+Resumo!$C$13+Resumo!$C$14*CEILING(AH$3,1))*(1+Resumo!$C$11)-(AH$4*(Resumo!$B$6+Resumo!$B$7)+Resumo!$B$9+Resumo!$B$10*CEILING(AH$3/100,1)+(Resumo!$B$12+Resumo!$B$14)*CEILING(AH$3,1)) -> 55.347887 | AI16: =(V16+AI$4*(Resumo!$C$6+Resumo!$C$7+Resumo!$C$8)+Resumo!$C$10*CEILING(AI$3/100,1)+Resumo!$C$9+Resumo!$C$13+Resumo!$C$14*CEILING(AI$3,1))*(1+Resumo!$C$11)-(AI$4*(Resumo!$B$6+Resumo!$B$7)+Resumo!$B$9+Resumo!$B$10*CEILING(AI$3/100,1)+(Resumo!$B$12+Resumo!$B$14)*CEILING(AI$3,1)) -> 73.511357 | AJ16: =(W16+AJ$4*(Resumo!$C$6+Resumo!$C$7+Resumo!$C$8)+Resumo!$C$10*CEILING(AJ$3/100,1)+Resumo!$C$9+Resumo!$C$13+Resumo!$C$14*CEILING(AJ$3,1))*(1+Resumo!$C$11)-(AJ$4*(Resumo!$B$6+Resumo!$B$7)+Resumo!$B$9+Resumo!$B$10*CEILING(AJ$3/100,1)+(Resumo!$B$12+Resumo!$B$14)*CEILING(AJ$3,1)) -> 82.348132 | AK16: =(X16+AK$4*(Resumo!$C$6+Resumo!$C$7+Resumo!$C$8)+Resumo!$C$10*CEILING(AK$3/100,1)+Resumo!$C$9+Resumo!$C$13+Resumo!$C$14*CEILING(AK$3,1))*(1+Resumo!$C$11)-(AK$4*(Resumo!$B$6+Resumo!$B$7)+Resumo!$B$9+Resumo!$B$10*CEILING(AK$3/100,1)+(Resumo!$B$12+Resumo!$B$14)*CEILING(AK$3,1)) -> 84.763696 | AL16: =(Y16+AL$4*(Resumo!$C$6+Resumo!$C$7+Resumo!$C$8)+Resumo!$C$10*CEILING(AL$3/100,1)+Resumo!$C$9+Resumo!$C$13+Resumo!$C$14*CEILING(AL$3,1))*(1+Resumo!$C$11)-(AL$4*(Resumo!$B$6+Resumo!$B$7)+Resumo!$B$9+Resumo!$B$10*CEILING(AL$3/100,1)+(Resumo!$B$12+Resumo!$B$14)*CEILING(AL$3,1)) -> 90.27338 | AM16: =(Z16+AM$4*(Resumo!$C$6+Resumo!$C$7+Resumo!$C$8)+Resumo!$C$10*CEILING(AM$3/100,1)+Resumo!$C$9+Resumo!$C$13+Resumo!$C$14*CEILING(AM$3,1))*(1+Resumo!$C$11)-(AM$4*(Resumo!$B$6+Resumo!$B$7)+Resumo!$B$9+Resumo!$B$10*CEILING(AM$3/100,1)+(Resumo!$B$12+Resumo!$B$14)*CEILING(AM$3,1)) -> 96.191232 | AN16: =(AA16+AN$4*(Resumo!$C$6+Resumo!$C$7+Resumo!$C$8)+Resumo!$C$10*CEILING(AN$3/100,1)+Resumo!$C$9+Resumo!$C$13+Resumo!$C$14*CEILING(AN$3,1))*(1+Resumo!$C$11)-(AN$4*(Resumo!$B$6+Resumo!$B$7)+Resumo!$B$9+Resumo!$B$10*CEILING(AN$3/100,1)+(Resumo!$B$12+Resumo!$B$14)*CEILING(AN$3,1)) -> 102.51226 | AO16: =(AB16+AO$4*(Resumo!$C$6+Resumo!$C$7+Resumo!$C$8)+Resumo!$C$10*CEILING(AO$3/100,1)+Resumo!$C$9+Resumo!$C$13+Resumo!$C$14*CEILING(AO$3,1))*(1+Resumo!$C$11)-(AO$4*(Resumo!$B$6+Resumo!$B$7)+Resumo!$B$9+Resumo!$B$10*CEILING(AO$3/100,1)+(Resumo!$B$12+Resumo!$B$14)*CEILING(AO$3,1)) -> 114.61444 | ... AT16: =(AG16+AT$4*(Resumo!$C$6+Resumo!$C$7+Resumo!$C$8)+Resumo!$C$10*CEILING(AT$3/100,1)+Resumo!$C$9+Resumo!$C$13+Resumo!$C$14*CEILING(AT$3,1))*(1+Resumo!$C$11)-(AT$4*(Resumo!$B$6+Resumo!$B$7)+Resumo!$B$9+Resumo!$B$10*CEILING(AT$3/100,1)+(Resumo!$B$12+Resumo!$B$14)*CEILING(AT$3,1)) -> 208.22433 | AU16: =1-AH16/H16 -> 0.036925575 | AV16: =1-AI16/I16 -> 0.2691255 | AW16: =1-AJ16/J16 -> 0.28361781 | AX16: =1-AK16/K16 -> 0.26260377 | AY16: =1-AL16/L16 -> 0.29550975 | AZ16: =1-AM16/M16 -> 0.35658039 | BA16: =1-AN16/N16 -> 0.28182529 | BB16: =1-AO16/O16 -> 0.35761439 | ... BG16: =1-AT16/T16 -> 0.49831507
A17: RJ | B17: Maricá | C17: 24900000 | D17: 24999999 | E17: Interior | F17: 7 / 13 | G17: =COUNTIFS(Pedidos!$C$2:$C$2224,">="&C17,Pedidos!$C$2:$C$2224,"<="&D17) -> 32 | H17: 57.47 | I17: 100.58 | J17: 114.95 | K17: 114.95 | L17: 128.14 | M17: 149.5 | N17: 142.74 | O17: 178.42 | P17: 214.11 | Q17: 249.03 | R17: 282.23 | S17: 332.05 | T17: 415.05 | U17: 46.95 | V17: 65.63 | W17: 74.97 | X17: 77.7 | Y17: 83.58 | Z17: 90.2 | AA17: 96.77 | AB17: 109.63 | AC17: 119.5 | AD17: 144.24 | AE17: 155.09 | AF17: 66.69 | AG17: 214.88 | AH17: =(U17+AH$4*(Resumo!$C$6+Resumo!$C$7+Resumo!$C$8)+Resumo!$C$10*CEILING(AH$3/100,1)+Resumo!$C$9+Resumo!$C$13+Resumo!$C$14*CEILING(AH$3,1))*(1+Resumo!$C$11)-(AH$4*(Resumo!$B$6+Resumo!$B$7)+Resumo!$B$9+Resumo!$B$10*CEILING(AH$3/100,1)+(Resumo!$B$12+Resumo!$B$14)*CEILING(AH$3,1)) -> 55.347887 | AI17: =(V17+AI$4*(Resumo!$C$6+Resumo!$C$7+Resumo!$C$8)+Resumo!$C$10*CEILING(AI$3/100,1)+Resumo!$C$9+Resumo!$C$13+Resumo!$C$14*CEILING(AI$3,1))*(1+Resumo!$C$11)-(AI$4*(Resumo!$B$6+Resumo!$B$7)+Resumo!$B$9+Resumo!$B$10*CEILING(AI$3/100,1)+(Resumo!$B$12+Resumo!$B$14)*CEILING(AI$3,1)) -> 73.511357 | AJ17: =(W17+AJ$4*(Resumo!$C$6+Resumo!$C$7+Resumo!$C$8)+Resumo!$C$10*CEILING(AJ$3/100,1)+Resumo!$C$9+Resumo!$C$13+Resumo!$C$14*CEILING(AJ$3,1))*(1+Resumo!$C$11)-(AJ$4*(Resumo!$B$6+Resumo!$B$7)+Resumo!$B$9+Resumo!$B$10*CEILING(AJ$3/100,1)+(Resumo!$B$12+Resumo!$B$14)*CEILING(AJ$3,1)) -> 82.348132 | AK17: =(X17+AK$4*(Resumo!$C$6+Resumo!$C$7+Resumo!$C$8)+Resumo!$C$10*CEILING(AK$3/100,1)+Resumo!$C$9+Resumo!$C$13+Resumo!$C$14*CEILING(AK$3,1))*(1+Resumo!$C$11)-(AK$4*(Resumo!$B$6+Resumo!$B$7)+Resumo!$B$9+Resumo!$B$10*CEILING(AK$3/100,1)+(Resumo!$B$12+Resumo!$B$14)*CEILING(AK$3,1)) -> 84.763696 | AL17: =(Y17+AL$4*(Resumo!$C$6+Resumo!$C$7+Resumo!$C$8)+Resumo!$C$10*CEILING(AL$3/100,1)+Resumo!$C$9+Resumo!$C$13+Resumo!$C$14*CEILING(AL$3,1))*(1+Resumo!$C$11)-(AL$4*(Resumo!$B$6+Resumo!$B$7)+Resumo!$B$9+Resumo!$B$10*CEILING(AL$3/100,1)+(Resumo!$B$12+Resumo!$B$14)*CEILING(AL$3,1)) -> 90.27338 | AM17: =(Z17+AM$4*(Resumo!$C$6+Resumo!$C$7+Resumo!$C$8)+Resumo!$C$10*CEILING(AM$3/100,1)+Resumo!$C$9+Resumo!$C$13+Resumo!$C$14*CEILING(AM$3,1))*(1+Resumo!$C$11)-(AM$4*(Resumo!$B$6+Resumo!$B$7)+Resumo!$B$9+Resumo!$B$10*CEILING(AM$3/100,1)+(Resumo!$B$12+Resumo!$B$14)*CEILING(AM$3,1)) -> 96.191232 | AN17: =(AA17+AN$4*(Resumo!$C$6+Resumo!$C$7+Resumo!$C$8)+Resumo!$C$10*CEILING(AN$3/100,1)+Resumo!$C$9+Resumo!$C$13+Resumo!$C$14*CEILING(AN$3,1))*(1+Resumo!$C$11)-(AN$4*(Resumo!$B$6+Resumo!$B$7)+Resumo!$B$9+Resumo!$B$10*CEILING(AN$3/100,1)+(Resumo!$B$12+Resumo!$B$14)*CEILING(AN$3,1)) -> 102.51226 | AO17: =(AB17+AO$4*(Resumo!$C$6+Resumo!$C$7+Resumo!$C$8)+Resumo!$C$10*CEILING(AO$3/100,1)+Resumo!$C$9+Resumo!$C$13+Resumo!$C$14*CEILING(AO$3,1))*(1+Resumo!$C$11)-(AO$4*(Resumo!$B$6+Resumo!$B$7)+Resumo!$B$9+Resumo!$B$10*CEILING(AO$3/100,1)+(Resumo!$B$12+Resumo!$B$14)*CEILING(AO$3,1)) -> 114.61444 | ... AT17: =(AG17+AT$4*(Resumo!$C$6+Resumo!$C$7+Resumo!$C$8)+Resumo!$C$10*CEILING(AT$3/100,1)+Resumo!$C$9+Resumo!$C$13+Resumo!$C$14*CEILING(AT$3,1))*(1+Resumo!$C$11)-(AT$4*(Resumo!$B$6+Resumo!$B$7)+Resumo!$B$9+Resumo!$B$10*CEILING(AT$3/100,1)+(Resumo!$B$12+Resumo!$B$14)*CEILING(AT$3,1)) -> 208.22433 | AU17: =1-AH17/H17 -> 0.036925575 | AV17: =1-AI17/I17 -> 0.2691255 | AW17: =1-AJ17/J17 -> 0.28361781 | AX17: =1-AK17/K17 -> 0.26260377 | AY17: =1-AL17/L17 -> 0.29550975 | AZ17: =1-AM17/M17 -> 0.35658039 | BA17: =1-AN17/N17 -> 0.28182529 | BB17: =1-AO17/O17 -> 0.35761439 | ... BG17: =1-AT17/T17 -> 0.49831507
A18: RJ | B18: Duque de Caxias | C18: 25000000 | D18: 25499999 | E18: Metropolitana | F18: 5 / 2 | G18: =COUNTIFS(Pedidos!$C$2:$C$2224,">="&C18,Pedidos!$C$2:$C$2224,"<="&D18) -> 106 | H18: 46.98 | I18: 82.21 | J18: 93.97 | K18: 93.97 | L18: 112.3 | M18: 131.02 | N18: 134.39 | O18: 167.99 | P18: 201.59 | Q18: 239.25 | R18: 271.15 | S18: 319 | T18: 398.74 | U18: 42.72 | V18: 58.8 | W18: 66.83 | X18: 65.36 | Y18: 70.98 | Z18: 76.55 | AA18: 82.48 | AB18: 92.32 | AC18: 101.26 | AD18: 129.62 | AE18: 139.81 | AF18: 155.09 | AG18: 194.34 | AH18: =(U18+AH$4*(Resumo!$C$6+Resumo!$C$7+Resumo!$C$8)+Resumo!$C$10*CEILING(AH$3/100,1)+Resumo!$C$9+Resumo!$C$13+Resumo!$C$14*CEILING(AH$3,1))*(1+Resumo!$C$11)-(AH$4*(Resumo!$B$6+Resumo!$B$7)+Resumo!$B$9+Resumo!$B$10*CEILING(AH$3/100,1)+(Resumo!$B$12+Resumo!$B$14)*CEILING(AH$3,1)) -> 51.117887 | AI18: =(V18+AI$4*(Resumo!$C$6+Resumo!$C$7+Resumo!$C$8)+Resumo!$C$10*CEILING(AI$3/100,1)+Resumo!$C$9+Resumo!$C$13+Resumo!$C$14*CEILING(AI$3,1))*(1+Resumo!$C$11)-(AI$4*(Resumo!$B$6+Resumo!$B$7)+Resumo!$B$9+Resumo!$B$10*CEILING(AI$3/100,1)+(Resumo!$B$12+Resumo!$B$14)*CEILING(AI$3,1)) -> 66.681357 | AJ18: =(W18+AJ$4*(Resumo!$C$6+Resumo!$C$7+Resumo!$C$8)+Resumo!$C$10*CEILING(AJ$3/100,1)+Resumo!$C$9+Resumo!$C$13+Resumo!$C$14*CEILING(AJ$3,1))*(1+Resumo!$C$11)-(AJ$4*(Resumo!$B$6+Resumo!$B$7)+Resumo!$B$9+Resumo!$B$10*CEILING(AJ$3/100,1)+(Resumo!$B$12+Resumo!$B$14)*CEILING(AJ$3,1)) -> 74.208132 | AK18: =(X18+AK$4*(Resumo!$C$6+Resumo!$C$7+Resumo!$C$8)+Resumo!$C$10*CEILING(AK$3/100,1)+Resumo!$C$9+Resumo!$C$13+Resumo!$C$14*CEILING(AK$3,1))*(1+Resumo!$C$11)-(AK$4*(Resumo!$B$6+Resumo!$B$7)+Resumo!$B$9+Resumo!$B$10*CEILING(AK$3/100,1)+(Resumo!$B$12+Resumo!$B$14)*CEILING(AK$3,1)) -> 72.423696 | AL18: =(Y18+AL$4*(Resumo!$C$6+Resumo!$C$7+Resumo!$C$8)+Resumo!$C$10*CEILING(AL$3/100,1)+Resumo!$C$9+Resumo!$C$13+Resumo!$C$14*CEILING(AL$3,1))*(1+Resumo!$C$11)-(AL$4*(Resumo!$B$6+Resumo!$B$7)+Resumo!$B$9+Resumo!$B$10*CEILING(AL$3/100,1)+(Resumo!$B$12+Resumo!$B$14)*CEILING(AL$3,1)) -> 77.67338 | AM18: =(Z18+AM$4*(Resumo!$C$6+Resumo!$C$7+Resumo!$C$8)+Resumo!$C$10*CEILING(AM$3/100,1)+Resumo!$C$9+Resumo!$C$13+Resumo!$C$14*CEILING(AM$3,1))*(1+Resumo!$C$11)-(AM$4*(Resumo!$B$6+Resumo!$B$7)+Resumo!$B$9+Resumo!$B$10*CEILING(AM$3/100,1)+(Resumo!$B$12+Resumo!$B$14)*CEILING(AM$3,1)) -> 82.541232 | AN18: =(AA18+AN$4*(Resumo!$C$6+Resumo!$C$7+Resumo!$C$8)+Resumo!$C$10*CEILING(AN$3/100,1)+Resumo!$C$9+Resumo!$C$13+Resumo!$C$14*CEILING(AN$3,1))*(1+Resumo!$C$11)-(AN$4*(Resumo!$B$6+Resumo!$B$7)+Resumo!$B$9+Resumo!$B$10*CEILING(AN$3/100,1)+(Resumo!$B$12+Resumo!$B$14)*CEILING(AN$3,1)) -> 88.222258 | AO18: =(AB18+AO$4*(Resumo!$C$6+Resumo!$C$7+Resumo!$C$8)+Resumo!$C$10*CEILING(AO$3/100,1)+Resumo!$C$9+Resumo!$C$13+Resumo!$C$14*CEILING(AO$3,1))*(1+Resumo!$C$11)-(AO$4*(Resumo!$B$6+Resumo!$B$7)+Resumo!$B$9+Resumo!$B$10*CEILING(AO$3/100,1)+(Resumo!$B$12+Resumo!$B$14)*CEILING(AO$3,1)) -> 97.30444 | ... AT18: =(AG18+AT$4*(Resumo!$C$6+Resumo!$C$7+Resumo!$C$8)+Resumo!$C$10*CEILING(AT$3/100,1)+Resumo!$C$9+Resumo!$C$13+Resumo!$C$14*CEILING(AT$3,1))*(1+Resumo!$C$11)-(AT$4*(Resumo!$B$6+Resumo!$B$7)+Resumo!$B$9+Resumo!$B$10*CEILING(AT$3/100,1)+(Resumo!$B$12+Resumo!$B$14)*CEILING(AT$3,1)) -> 187.68433 | AU18: =1-AH18/H18 -> -0.088077633 | AV18: =1-AI18/I18 -> 0.18888995 | AW18: =1-AJ18/J18 -> 0.21029975 | AX18: =1-AK18/K18 -> 0.22928917 | AY18: =1-AL18/L18 -> 0.30834034 | AZ18: =1-AM18/M18 -> 0.37001044 | BA18: =1-AN18/N18 -> 0.34353554 | BB18: =1-AO18/O18 -> 0.42077243 | ... BG18: =1-AT18/T18 -> 0.52930649
... A99: RJ | B99: Saquarema | C99: 28990000 | D99: 28999999 | E99: Interior | F99: 10 / 13 | G99: =COUNTIFS(Pedidos!$C$2:$C$2224,">="&C99,Pedidos!$C$2:$C$2224,"<="&D99) -> 15 | H99: 100.7 | I99: 114.95 | J99: 124.38 | K99: 129.29 | L99: 142.32 | M99: 166.05 | N99: 166.05 | O99: 197.35 | P99: 236.82 | Q99: 264.84 | R99: 300.15 | S99: 353.12 | T99: 441.4 | U99: 46.95 | V99: 65.63 | W99: 74.97 | X99: 77.7 | Y99: 83.58 | Z99: 90.2 | AA99: 96.77 | AB99: 109.63 | AC99: 119.5 | AD99: 144.24 | AE99: 155.09 | AF99: 66.69 | AG99: 214.88 | AH99: =(U99+AH$4*(Resumo!$C$6+Resumo!$C$7+Resumo!$C$8)+Resumo!$C$10*CEILING(AH$3/100,1)+Resumo!$C$9+Resumo!$C$13+Resumo!$C$14*CEILING(AH$3,1))*(1+Resumo!$C$11)-(AH$4*(Resumo!$B$6+Resumo!$B$7)+Resumo!$B$9+Resumo!$B$10*CEILING(AH$3/100,1)+(Resumo!$B$12+Resumo!$B$14)*CEILING(AH$3,1)) -> 55.347887 | AI99: =(V99+AI$4*(Resumo!$C$6+Resumo!$C$7+Resumo!$C$8)+Resumo!$C$10*CEILING(AI$3/100,1)+Resumo!$C$9+Resumo!$C$13+Resumo!$C$14*CEILING(AI$3,1))*(1+Resumo!$C$11)-(AI$4*(Resumo!$B$6+Resumo!$B$7)+Resumo!$B$9+Resumo!$B$10*CEILING(AI$3/100,1)+(Resumo!$B$12+Resumo!$B$14)*CEILING(AI$3,1)) -> 73.511357 | AJ99: =(W99+AJ$4*(Resumo!$C$6+Resumo!$C$7+Resumo!$C$8)+Resumo!$C$10*CEILING(AJ$3/100,1)+Resumo!$C$9+Resumo!$C$13+Resumo!$C$14*CEILING(AJ$3,1))*(1+Resumo!$C$11)-(AJ$4*(Resumo!$B$6+Resumo!$B$7)+Resumo!$B$9+Resumo!$B$10*CEILING(AJ$3/100,1)+(Resumo!$B$12+Resumo!$B$14)*CEILING(AJ$3,1)) -> 82.348132 | AK99: =(X99+AK$4*(Resumo!$C$6+Resumo!$C$7+Resumo!$C$8)+Resumo!$C$10*CEILING(AK$3/100,1)+Resumo!$C$9+Resumo!$C$13+Resumo!$C$14*CEILING(AK$3,1))*(1+Resumo!$C$11)-(AK$4*(Resumo!$B$6+Resumo!$B$7)+Resumo!$B$9+Resumo!$B$10*CEILING(AK$3/100,1)+(Resumo!$B$12+Resumo!$B$14)*CEILING(AK$3,1)) -> 84.763696 | AL99: =(Y99+AL$4*(Resumo!$C$6+Resumo!$C$7+Resumo!$C$8)+Resumo!$C$10*CEILING(AL$3/100,1)+Resumo!$C$9+Resumo!$C$13+Resumo!$C$14*CEILING(AL$3,1))*(1+Resumo!$C$11)-(AL$4*(Resumo!$B$6+Resumo!$B$7)+Resumo!$B$9+Resumo!$B$10*CEILING(AL$3/100,1)+(Resumo!$B$12+Resumo!$B$14)*CEILING(AL$3,1)) -> 90.27338 | AM99: =(Z99+AM$4*(Resumo!$C$6+Resumo!$C$7+Resumo!$C$8)+Resumo!$C$10*CEILING(AM$3/100,1)+Resumo!$C$9+Resumo!$C$13+Resumo!$C$14*CEILING(AM$3,1))*(1+Resumo!$C$11)-(AM$4*(Resumo!$B$6+Resumo!$B$7)+Resumo!$B$9+Resumo!$B$10*CEILING(AM$3/100,1)+(Resumo!$B$12+Resumo!$B$14)*CEILING(AM$3,1)) -> 96.191232 | AN99: =(AA99+AN$4*(Resumo!$C$6+Resumo!$C$7+Resumo!$C$8)+Resumo!$C$10*CEILING(AN$3/100,1)+Resumo!$C$9+Resumo!$C$13+Resumo!$C$14*CEILING(AN$3,1))*(1+Resumo!$C$11)-(AN$4*(Resumo!$B$6+Resumo!$B$7)+Resumo!$B$9+Resumo!$B$10*CEILING(AN$3/100,1)+(Resumo!$B$12+Resumo!$B$14)*CEILING(AN$3,1)) -> 102.51226 | AO99: =(AB99+AO$4*(Resumo!$C$6+Resumo!$C$7+Resumo!$C$8)+Resumo!$C$10*CEILING(AO$3/100,1)+Resumo!$C$9+Resumo!$C$13+Resumo!$C$14*CEILING(AO$3,1))*(1+Resumo!$C$11)-(AO$4*(Resumo!$B$6+Resumo!$B$7)+Resumo!$B$9+Resumo!$B$10*CEILING(AO$3/100,1)+(Resumo!$B$12+Resumo!$B$14)*CEILING(AO$3,1)) -> 114.61444 | ... AT99: =(AG99+AT$4*(Resumo!$C$6+Resumo!$C$7+Resumo!$C$8)+Resumo!$C$10*CEILING(AT$3/100,1)+Resumo!$C$9+Resumo!$C$13+Resumo!$C$14*CEILING(AT$3,1))*(1+Resumo!$C$11)-(AT$4*(Resumo!$B$6+Resumo!$B$7)+Resumo!$B$9+Resumo!$B$10*CEILING(AT$3/100,1)+(Resumo!$B$12+Resumo!$B$14)*CEILING(AT$3,1)) -> 208.22433 | AU99: =1-AH99/H99 -> 0.45036855 | AV99: =1-AI99/I99 -> 0.36049276 | AW99: =1-AJ99/J99 -> 0.33793108 | AX99: =1-AK99/K99 -> 0.34439093 | AY99: =1-AL99/L99 -> 0.36570138 | AZ99: =1-AM99/M99 -> 0.42070923 | BA99: =1-AN99/N99 -> 0.38264223 | BB99: =1-AO99/O99 -> 0.41923263 | ... BG99: =1-AT99/T99 -> 0.52826386
B101: Redução negativa = a PROLOG já está abaixo do empate nessa faixa/cidade. Faixas com pouco ou nenhum volume (acima de 150 kg) devem ser tratadas caso a caso.

Sheet Faixa x Região
A1: Por faixa de peso e região OUTRO PARCEIRO — preço final PROLOG x OUTRO PARCEIRO (mesmos pedidos, top 20 cidades)
A3: Região: TODAS
A4: Faixa (kg) | B4: Pedidos | C4: OUTRO PARCEIRO médio | D4: PROLOG médio | E4: PROLOG vs OUTRO PARCEIRO | F4: OUTRO PARCEIRO frete peso | G4: PROLOG frete peso | H4: Frete peso PROLOG vs OUTRO PARCEIRO | I4: % pedidos PROLOG ganharia | J4: Redução necessária
A5: 0-20 | B5: =COUNTIFS(Pedidos!$AH$2:$AH$2224,"SIM",Pedidos!$F$2:$F$2224,$A5) -> 96 | C5: =IFERROR(AVERAGEIFS(Pedidos!$S$2:$S$2224,Pedidos!$AH$2:$AH$2224,"SIM",Pedidos!$F$2:$F$2224,$A5),"") -> 69.141532 | D5: =IFERROR(AVERAGEIFS(Pedidos!$AB$2:$AB$2224,Pedidos!$AH$2:$AH$2224,"SIM",Pedidos!$F$2:$F$2224,$A5),"") -> 76.075222 | E5: =IFERROR(D5/C5-1,"") -> 0.10028256 | F5: =IFERROR(AVERAGEIFS(Pedidos!$I$2:$I$2224,Pedidos!$AH$2:$AH$2224,"SIM",Pedidos!$F$2:$F$2224,$A5),"") -> 36.8725 | G5: =IFERROR(AVERAGEIFS(Pedidos!$T$2:$T$2224,Pedidos!$AH$2:$AH$2224,"SIM",Pedidos!$F$2:$F$2224,$A5),"") -> 51.369375 | H5: =IFERROR(G5/F5-1,"") -> 0.39316225 | I5: =IFERROR(COUNTIFS(Pedidos!$AH$2:$AH$2224,"SIM",Pedidos!$F$2:$F$2224,$A5,Pedidos!$AE$2:$AE$2224,"SIM")/B5,"") -> 0.14583333 | J5: =IFERROR(MAX(0,1-C5/D5),"") -> 0.091142549
A6: 20-35 | B6: =COUNTIFS(Pedidos!$AH$2:$AH$2224,"SIM",Pedidos!$F$2:$F$2224,$A6) -> 431 | C6: =IFERROR(AVERAGEIFS(Pedidos!$S$2:$S$2224,Pedidos!$AH$2:$AH$2224,"SIM",Pedidos!$F$2:$F$2224,$A6),"") -> 90.041443 | D6: =IFERROR(AVERAGEIFS(Pedidos!$AB$2:$AB$2224,Pedidos!$AH$2:$AH$2224,"SIM",Pedidos!$F$2:$F$2224,$A6),"") -> 127.44455 | E6: =IFERROR(D6/C6-1,"") -> 0.41539875 | F6: =IFERROR(AVERAGEIFS(Pedidos!$I$2:$I$2224,Pedidos!$AH$2:$AH$2224,"SIM",Pedidos!$F$2:$F$2224,$A6),"") -> 49.946752 | G6: =IFERROR(AVERAGEIFS(Pedidos!$T$2:$T$2224,Pedidos!$AH$2:$AH$2224,"SIM",Pedidos!$F$2:$F$2224,$A6),"") -> 90.763039 | H6: =IFERROR(G6/F6-1,"") -> 0.81719604 | I6: =IFERROR(COUNTIFS(Pedidos!$AH$2:$AH$2224,"SIM",Pedidos!$F$2:$F$2224,$A6,Pedidos!$AE$2:$AE$2224,"SIM")/B6,"") -> 0 | J6: =IFERROR(MAX(0,1-C6/D6),"") -> 0.29348532
A7: 35-40 | B7: =COUNTIFS(Pedidos!$AH$2:$AH$2224,"SIM",Pedidos!$F$2:$F$2224,$A7) -> 299 | C7: =IFERROR(AVERAGEIFS(Pedidos!$S$2:$S$2224,Pedidos!$AH$2:$AH$2224,"SIM",Pedidos!$F$2:$F$2224,$A7),"") -> 104.75381 | D7: =IFERROR(AVERAGEIFS(Pedidos!$AB$2:$AB$2224,Pedidos!$AH$2:$AH$2224,"SIM",Pedidos!$F$2:$F$2224,$A7),"") -> 146.77366 | E7: =IFERROR(D7/C7-1,"") -> 0.4011296 | F7: =IFERROR(AVERAGEIFS(Pedidos!$I$2:$I$2224,Pedidos!$AH$2:$AH$2224,"SIM",Pedidos!$F$2:$F$2224,$A7),"") -> 58.49796 | G7: =IFERROR(AVERAGEIFS(Pedidos!$T$2:$T$2224,Pedidos!$AH$2:$AH$2224,"SIM",Pedidos!$F$2:$F$2224,$A7),"") -> 102.8507 | H7: =IFERROR(G7/F7-1,"") -> 0.75819298 | I7: =IFERROR(COUNTIFS(Pedidos!$AH$2:$AH$2224,"SIM",Pedidos!$F$2:$F$2224,$A7,Pedidos!$AE$2:$AE$2224,"SIM")/B7,"") -> 0 | J7: =IFERROR(MAX(0,1-C7/D7),"") -> 0.28629015
A8: 40-50 | B8: =COUNTIFS(Pedidos!$AH$2:$AH$2224,"SIM",Pedidos!$F$2:$F$2224,$A8) -> 305 | C8: =IFERROR(AVERAGEIFS(Pedidos!$S$2:$S$2224,Pedidos!$AH$2:$AH$2224,"SIM",Pedidos!$F$2:$F$2224,$A8),"") -> 113.44319 | D8: =IFERROR(AVERAGEIFS(Pedidos!$AB$2:$AB$2224,Pedidos!$AH$2:$AH$2224,"SIM",Pedidos!$F$2:$F$2224,$A8),"") -> 153.47146 | E8: =IFERROR(D8/C8-1,"") -> 0.35284854 | F8: =IFERROR(AVERAGEIFS(Pedidos!$I$2:$I$2224,Pedidos!$AH$2:$AH$2224,"SIM",Pedidos!$F$2:$F$2224,$A8),"") -> 61.905377 | G8: =IFERROR(AVERAGEIFS(Pedidos!$T$2:$T$2224,Pedidos!$AH$2:$AH$2224,"SIM",Pedidos!$F$2:$F$2224,$A8),"") -> 104.18305 | H8: =IFERROR(G8/F8-1,"") -> 0.68294023 | I8: =IFERROR(COUNTIFS(Pedidos!$AH$2:$AH$2224,"SIM",Pedidos!$F$2:$F$2224,$A8,Pedidos!$AE$2:$AE$2224,"SIM")/B8,"") -> 0 | J8: =IFERROR(MAX(0,1-C8/D8),"") -> 0.26081895
A9: 50-60 | B9: =COUNTIFS(Pedidos!$AH$2:$AH$2224,"SIM",Pedidos!$F$2:$F$2224,$A9) -> 361 | C9: =IFERROR(AVERAGEIFS(Pedidos!$S$2:$S$2224,Pedidos!$AH$2:$AH$2224,"SIM",Pedidos!$F$2:$F$2224,$A9),"") -> 123.83699 | D9: =IFERROR(AVERAGEIFS(Pedidos!$AB$2:$AB$2224,Pedidos!$AH$2:$AH$2224,"SIM",Pedidos!$F$2:$F$2224,$A9),"") -> 176.4498 | E9: =IFERROR(D9/C9-1,"") -> 0.42485537 | F9: =IFERROR(AVERAGEIFS(Pedidos!$I$2:$I$2224,Pedidos!$AH$2:$AH$2224,"SIM",Pedidos!$F$2:$F$2224,$A9),"") -> 67.006648 | G9: =IFERROR(AVERAGEIFS(Pedidos!$T$2:$T$2224,Pedidos!$AH$2:$AH$2224,"SIM",Pedidos!$F$2:$F$2224,$A9),"") -> 119.98296 | H9: =IFERROR(G9/F9-1,"") -> 0.79061283 | I9: =IFERROR(COUNTIFS(Pedidos!$AH$2:$AH$2224,"SIM",Pedidos!$F$2:$F$2224,$A9,Pedidos!$AE$2:$AE$2224,"SIM")/B9,"") -> 0 | J9: =IFERROR(MAX(0,1-C9/D9),"") -> 0.29817438
A10: 60-70 | B10: =COUNTIFS(Pedidos!$AH$2:$AH$2224,"SIM",Pedidos!$F$2:$F$2224,$A10) -> 228 | C10: =IFERROR(AVERAGEIFS(Pedidos!$S$2:$S$2224,Pedidos!$AH$2:$AH$2224,"SIM",Pedidos!$F$2:$F$2224,$A10),"") -> 136.88541 | D10: =IFERROR(AVERAGEIFS(Pedidos!$AB$2:$AB$2224,Pedidos!$AH$2:$AH$2224,"SIM",Pedidos!$F$2:$F$2224,$A10),"") -> 206.19741 | E10: =IFERROR(D10/C10-1,"") -> 0.5063505 | F10: =IFERROR(AVERAGEIFS(Pedidos!$I$2:$I$2224,Pedidos!$AH$2:$AH$2224,"SIM",Pedidos!$F$2:$F$2224,$A10),"") -> 72.810833 | G10: =IFERROR(AVERAGEIFS(Pedidos!$T$2:$T$2224,Pedidos!$AH$2:$AH$2224,"SIM",Pedidos!$F$2:$F$2224,$A10),"") -> 139.83754 | H10: =IFERROR(G10/F10-1,"") -> 0.92055959 | I10: =IFERROR(COUNTIFS(Pedidos!$AH$2:$AH$2224,"SIM",Pedidos!$F$2:$F$2224,$A10,Pedidos!$AE$2:$AE$2224,"SIM")/B10,"") -> 0 | J10: =IFERROR(MAX(0,1-C10/D10),"") -> 0.33614388
A11: 70-80 | B11: =COUNTIFS(Pedidos!$AH$2:$AH$2224,"SIM",Pedidos!$F$2:$F$2224,$A11) -> 24 | C11: =IFERROR(AVERAGEIFS(Pedidos!$S$2:$S$2224,Pedidos!$AH$2:$AH$2224,"SIM",Pedidos!$F$2:$F$2224,$A11),"") -> 148.67077 | D11: =IFERROR(AVERAGEIFS(Pedidos!$AB$2:$AB$2224,Pedidos!$AH$2:$AH$2224,"SIM",Pedidos!$F$2:$F$2224,$A11),"") -> 211.16087 | E11: =IFERROR(D11/C11-1,"") -> 0.42032543 | F11: =IFERROR(AVERAGEIFS(Pedidos!$I$2:$I$2224,Pedidos!$AH$2:$AH$2224,"SIM",Pedidos!$F$2:$F$2224,$A11),"") -> 78.628333 | G11: =IFERROR(AVERAGEIFS(Pedidos!$T$2:$T$2224,Pedidos!$AH$2:$AH$2224,"SIM",Pedidos!$F$2:$F$2224,$A11),"") -> 139.39875 | H11: =IFERROR(G11/F11-1,"") -> 0.77288191 | I11: =IFERROR(COUNTIFS(Pedidos!$AH$2:$AH$2224,"SIM",Pedidos!$F$2:$F$2224,$A11,Pedidos!$AE$2:$AE$2224,"SIM")/B11,"") -> 0 | J11: =IFERROR(MAX(0,1-C11/D11),"") -> 0.295936
A12: 80-100 | B12: =COUNTIFS(Pedidos!$AH$2:$AH$2224,"SIM",Pedidos!$F$2:$F$2224,$A12) -> 43 | C12: =IFERROR(AVERAGEIFS(Pedidos!$S$2:$S$2224,Pedidos!$AH$2:$AH$2224,"SIM",Pedidos!$F$2:$F$2224,$A12),"") -> 172.64938 | D12: =IFERROR(AVERAGEIFS(Pedidos!$AB$2:$AB$2224,Pedidos!$AH$2:$AH$2224,"SIM",Pedidos!$F$2:$F$2224,$A12),"") -> 262.07559 | E12: =IFERROR(D12/C12-1,"") -> 0.5179643 | F12: =IFERROR(AVERAGEIFS(Pedidos!$I$2:$I$2224,Pedidos!$AH$2:$AH$2224,"SIM",Pedidos!$F$2:$F$2224,$A12),"") -> 93.784186 | G12: =IFERROR(AVERAGEIFS(Pedidos!$T$2:$T$2224,Pedidos!$AH$2:$AH$2224,"SIM",Pedidos!$F$2:$F$2224,$A12),"") -> 177.46651 | H12: =IFERROR(G12/F12-1,"") -> 0.8922861 | I12: =IFERROR(COUNTIFS(Pedidos!$AH$2:$AH$2224,"SIM",Pedidos!$F$2:$F$2224,$A12,Pedidos!$AE$2:$AE$2224,"SIM")/B12,"") -> 0 | J12: =IFERROR(MAX(0,1-C12/D12),"") -> 0.34122298
A13: 100-120 | B13: =COUNTIFS(Pedidos!$AH$2:$AH$2224,"SIM",Pedidos!$F$2:$F$2224,$A13) -> 47 | C13: =IFERROR(AVERAGEIFS(Pedidos!$S$2:$S$2224,Pedidos!$AH$2:$AH$2224,"SIM",Pedidos!$F$2:$F$2224,$A13),"") -> 194.29298 | D13: =IFERROR(AVERAGEIFS(Pedidos!$AB$2:$AB$2224,Pedidos!$AH$2:$AH$2224,"SIM",Pedidos!$F$2:$F$2224,$A13),"") -> 316.24233 | E13: =IFERROR(D13/C13-1,"") -> 0.62765697 | F13: =IFERROR(AVERAGEIFS(Pedidos!$I$2:$I$2224,Pedidos!$AH$2:$AH$2224,"SIM",Pedidos!$F$2:$F$2224,$A13),"") -> 100.37915 | G13: =IFERROR(AVERAGEIFS(Pedidos!$T$2:$T$2224,Pedidos!$AH$2:$AH$2224,"SIM",Pedidos!$F$2:$F$2224,$A13),"") -> 208.16894 | H13: =IFERROR(G13/F13-1,"") -> 1.0738265 | I13: =IFERROR(COUNTIFS(Pedidos!$AH$2:$AH$2224,"SIM",Pedidos!$F$2:$F$2224,$A13,Pedidos!$AE$2:$AE$2224,"SIM")/B13,"") -> 0 | J13: =IFERROR(MAX(0,1-C13/D13),"") -> 0.38561993
A14: 120-150 | B14: =COUNTIFS(Pedidos!$AH$2:$AH$2224,"SIM",Pedidos!$F$2:$F$2224,$A14) -> 73 | C14: =IFERROR(AVERAGEIFS(Pedidos!$S$2:$S$2224,Pedidos!$AH$2:$AH$2224,"SIM",Pedidos!$F$2:$F$2224,$A14),"") -> 237.12483 | D14: =IFERROR(AVERAGEIFS(Pedidos!$AB$2:$AB$2224,Pedidos!$AH$2:$AH$2224,"SIM",Pedidos!$F$2:$F$2224,$A14),"") -> 369.59085 | E14: =IFERROR(D14/C14-1,"") -> 0.55863414 | F14: =IFERROR(AVERAGEIFS(Pedidos!$I$2:$I$2224,Pedidos!$AH$2:$AH$2224,"SIM",Pedidos!$F$2:$F$2224,$A14),"") -> 128.00014 | G14: =IFERROR(AVERAGEIFS(Pedidos!$T$2:$T$2224,Pedidos!$AH$2:$AH$2224,"SIM",Pedidos!$F$2:$F$2224,$A14),"") -> 244.44575 | H14: =IFERROR(G14/F14-1,"") -> 0.9097304 | I14: =IFERROR(COUNTIFS(Pedidos!$AH$2:$AH$2224,"SIM",Pedidos!$F$2:$F$2224,$A14,Pedidos!$AE$2:$AE$2224,"SIM")/B14,"") -> 0 | J14: =IFERROR(MAX(0,1-C14/D14),"") -> 0.35841262
A15: 150-170 | B15: =COUNTIFS(Pedidos!$AH$2:$AH$2224,"SIM",Pedidos!$F$2:$F$2224,$A15) -> 3 | C15: =IFERROR(AVERAGEIFS(Pedidos!$S$2:$S$2224,Pedidos!$AH$2:$AH$2224,"SIM",Pedidos!$F$2:$F$2224,$A15),"") -> 260.90363 | D15: =IFERROR(AVERAGEIFS(Pedidos!$AB$2:$AB$2224,Pedidos!$AH$2:$AH$2224,"SIM",Pedidos!$F$2:$F$2224,$A15),"") -> 423.50097 | E15: =IFERROR(D15/C15-1,"") -> 0.62320842 | F15: =IFERROR(AVERAGEIFS(Pedidos!$I$2:$I$2224,Pedidos!$AH$2:$AH$2224,"SIM",Pedidos!$F$2:$F$2224,$A15),"") -> 133.47667 | G15: =IFERROR(AVERAGEIFS(Pedidos!$T$2:$T$2224,Pedidos!$AH$2:$AH$2224,"SIM",Pedidos!$F$2:$F$2224,$A15),"") -> 274.84333 | H15: =IFERROR(G15/F15-1,"") -> 1.0591115 | I15: =IFERROR(COUNTIFS(Pedidos!$AH$2:$AH$2224,"SIM",Pedidos!$F$2:$F$2224,$A15,Pedidos!$AE$2:$AE$2224,"SIM")/B15,"") -> 0 | J15: =IFERROR(MAX(0,1-C15/D15),"") -> 0.38393617
A16: 170-200 | B16: =COUNTIFS(Pedidos!$AH$2:$AH$2224,"SIM",Pedidos!$F$2:$F$2224,$A16) -> 1 | C16: =IFERROR(AVERAGEIFS(Pedidos!$S$2:$S$2224,Pedidos!$AH$2:$AH$2224,"SIM",Pedidos!$F$2:$F$2224,$A16),"") -> 199.73273 | D16: =IFERROR(AVERAGEIFS(Pedidos!$AB$2:$AB$2224,Pedidos!$AH$2:$AH$2224,"SIM",Pedidos!$F$2:$F$2224,$A16),"") -> 529.025 | E16: =IFERROR(D16/C16-1,"") -> 1.6486646 | F16: =IFERROR(AVERAGEIFS(Pedidos!$I$2:$I$2224,Pedidos!$AH$2:$AH$2224,"SIM",Pedidos!$F$2:$F$2224,$A16),"") -> 66.69 | G16: =IFERROR(AVERAGEIFS(Pedidos!$T$2:$T$2224,Pedidos!$AH$2:$AH$2224,"SIM",Pedidos!$F$2:$F$2224,$A16),"") -> 353.17 | H16: =IFERROR(G16/F16-1,"") -> 4.2956965 | I16: =IFERROR(COUNTIFS(Pedidos!$AH$2:$AH$2224,"SIM",Pedidos!$F$2:$F$2224,$A16,Pedidos!$AE$2:$AE$2224,"SIM")/B16,"") -> 0 | J16: =IFERROR(MAX(0,1-C16/D16),"") -> 0.62245125
A17: 200-250 | B17: =COUNTIFS(Pedidos!$AH$2:$AH$2224,"SIM",Pedidos!$F$2:$F$2224,$A17) -> 1 | C17: =IFERROR(AVERAGEIFS(Pedidos!$S$2:$S$2224,Pedidos!$AH$2:$AH$2224,"SIM",Pedidos!$F$2:$F$2224,$A17),"") -> 338.21471 | D17: =IFERROR(AVERAGEIFS(Pedidos!$AB$2:$AB$2224,Pedidos!$AH$2:$AH$2224,"SIM",Pedidos!$F$2:$F$2224,$A17),"") -> 593.32707 | E17: =IFERROR(D17/C17-1,"") -> 0.75429112 | F17: =IFERROR(AVERAGEIFS(Pedidos!$I$2:$I$2224,Pedidos!$AH$2:$AH$2224,"SIM",Pedidos!$F$2:$F$2224,$A17),"") -> 181.55 | G17: =IFERROR(AVERAGEIFS(Pedidos!$T$2:$T$2224,Pedidos!$AH$2:$AH$2224,"SIM",Pedidos!$F$2:$F$2224,$A17),"") -> 398.74 | H17: =IFERROR(G17/F17-1,"") -> 1.1963096 | I17: =IFERROR(COUNTIFS(Pedidos!$AH$2:$AH$2224,"SIM",Pedidos!$F$2:$F$2224,$A17,Pedidos!$AE$2:$AE$2224,"SIM")/B17,"") -> 0 | J17: =IFERROR(MAX(0,1-C17/D17),"") -> 0.42996918
A18: TOTAL | B18: =COUNTIFS(Pedidos!$AH$2:$AH$2224,"SIM") -> 1912 | C18: =IFERROR(AVERAGEIFS(Pedidos!$S$2:$S$2224,Pedidos!$AH$2:$AH$2224,"SIM"),"") -> 118.21998 | D18: =IFERROR(AVERAGEIFS(Pedidos!$AB$2:$AB$2224,Pedidos!$AH$2:$AH$2224,"SIM"),"") -> 169.56633 | E18: =IFERROR(D18/C18-1,"") -> 0.43432883 | F18: =IFERROR(AVERAGEIFS(Pedidos!$I$2:$I$2224,Pedidos!$AH$2:$AH$2224,"SIM"),"") -> 64.257014 | G18: =IFERROR(AVERAGEIFS(Pedidos!$T$2:$T$2224,Pedidos!$AH$2:$AH$2224,"SIM"),"") -> 116.08623 | H18: =IFERROR(G18/F18-1,"") -> 0.80659243 | I18: =IFERROR(COUNTIFS(Pedidos!$AH$2:$AH$2224,"SIM",Pedidos!$AE$2:$AE$2224,"SIM")/B18,"") -> 0.0073221757 | J18: =IFERROR(MAX(0,1-C18/D18),"") -> 0.3028098
A20: Região: Capital
A21: Faixa (kg) | B21: Pedidos | C21: OUTRO PARCEIRO médio | D21: PROLOG médio | E21: PROLOG vs OUTRO PARCEIRO | F21: OUTRO PARCEIRO frete peso | G21: PROLOG frete peso | H21: Frete peso PROLOG vs OUTRO PARCEIRO | I21: % pedidos PROLOG ganharia | J21: Redução necessária
A22: 0-20 | B22: =COUNTIFS(Pedidos!$AH$2:$AH$2224,"SIM",Pedidos!$E$2:$E$2224,"Capital",Pedidos!$F$2:$F$2224,$A22) -> 64 | C22: =IFERROR(AVERAGEIFS(Pedidos!$S$2:$S$2224,Pedidos!$AH$2:$AH$2224,"SIM",Pedidos!$E$2:$E$2224,"Capital",Pedidos!$F$2:$F$2224,$A22),"") -> 65.055134 | D22: =IFERROR(AVERAGEIFS(Pedidos!$AB$2:$AB$2224,Pedidos!$AH$2:$AH$2224,"SIM",Pedidos!$E$2:$E$2224,"Capital",Pedidos!$F$2:$F$2224,$A22),"") -> 70.923919 | E22: =IFERROR(D22/C22-1,"") -> 0.090212475 | F22: =IFERROR(AVERAGEIFS(Pedidos!$I$2:$I$2224,Pedidos!$AH$2:$AH$2224,"SIM",Pedidos!$E$2:$E$2224,"Capital",Pedidos!$F$2:$F$2224,$A22),"") -> 33.42 | G22: =IFERROR(AVERAGEIFS(Pedidos!$T$2:$T$2224,Pedidos!$AH$2:$AH$2224,"SIM",Pedidos!$E$2:$E$2224,"Capital",Pedidos!$F$2:$F$2224,$A22),"") -> 46.98 | H22: =IFERROR(G22/F22-1,"") -> 0.40574506 | I22: =IFERROR(COUNTIFS(Pedidos!$AH$2:$AH$2224,"SIM",Pedidos!$E$2:$E$2224,"Capital",Pedidos!$F$2:$F$2224,$A22,Pedidos!$AE$2:$AE$2224,"SIM")/B22,"") -> 0 | J22: =IFERROR(MAX(0,1-C22/D22),"") -> 0.082747608
A23: 20-35 | B23: =COUNTIFS(Pedidos!$AH$2:$AH$2224,"SIM",Pedidos!$E$2:$E$2224,"Capital",Pedidos!$F$2:$F$2224,$A23) -> 263 | C23: =IFERROR(AVERAGEIFS(Pedidos!$S$2:$S$2224,Pedidos!$AH$2:$AH$2224,"SIM",Pedidos!$E$2:$E$2224,"Capital",Pedidos!$F$2:$F$2224,$A23),"") -> 80.846529 | D23: =IFERROR(AVERAGEIFS(Pedidos!$AB$2:$AB$2224,Pedidos!$AH$2:$AH$2224,"SIM",Pedidos!$E$2:$E$2224,"Capital",Pedidos!$F$2:$F$2224,$A23),"") -> 117.40343 | E23: =IFERROR(D23/C23-1,"") -> 0.45217647 | F23: =IFERROR(AVERAGEIFS(Pedidos!$I$2:$I$2224,Pedidos!$AH$2:$AH$2224,"SIM",Pedidos!$E$2:$E$2224,"Capital",Pedidos!$F$2:$F$2224,$A23),"") -> 42.11 | G23: =IFERROR(AVERAGEIFS(Pedidos!$T$2:$T$2224,Pedidos!$AH$2:$AH$2224,"SIM",Pedidos!$E$2:$E$2224,"Capital",Pedidos!$F$2:$F$2224,$A23),"") -> 82.21 | H23: =IFERROR(G23/F23-1,"") -> 0.95226787 | I23: =IFERROR(COUNTIFS(Pedidos!$AH$2:$AH$2224,"SIM",Pedidos!$E$2:$E$2224,"Capital",Pedidos!$F$2:$F$2224,$A23,Pedidos!$AE$2:$AE$2224,"SIM")/B23,"") -> 0 | J23: =IFERROR(MAX(0,1-C23/D23),"") -> 0.31137846
A24: 35-40 | B24: =COUNTIFS(Pedidos!$AH$2:$AH$2224,"SIM",Pedidos!$E$2:$E$2224,"Capital",Pedidos!$F$2:$F$2224,$A24) -> 163 | C24: =IFERROR(AVERAGEIFS(Pedidos!$S$2:$S$2224,Pedidos!$AH$2:$AH$2224,"SIM",Pedidos!$E$2:$E$2224,"Capital",Pedidos!$F$2:$F$2224,$A24),"") -> 93.149782 | D24: =IFERROR(AVERAGEIFS(Pedidos!$AB$2:$AB$2224,Pedidos!$AH$2:$AH$2224,"SIM",Pedidos!$E$2:$E$2224,"Capital",Pedidos!$F$2:$F$2224,$A24),"") -> 136.60884 | E24: =IFERROR(D24/C24-1,"") -> 0.46655029 | F24: =IFERROR(AVERAGEIFS(Pedidos!$I$2:$I$2224,Pedidos!$AH$2:$AH$2224,"SIM",Pedidos!$E$2:$E$2224,"Capital",Pedidos!$F$2:$F$2224,$A24),"") -> 48.35 | G24: =IFERROR(AVERAGEIFS(Pedidos!$T$2:$T$2224,Pedidos!$AH$2:$AH$2224,"SIM",Pedidos!$E$2:$E$2224,"Capital",Pedidos!$F$2:$F$2224,$A24),"") -> 93.97 | H24: =IFERROR(G24/F24-1,"") -> 0.94353671 | I24: =IFERROR(COUNTIFS(Pedidos!$AH$2:$AH$2224,"SIM",Pedidos!$E$2:$E$2224,"Capital",Pedidos!$F$2:$F$2224,$A24,Pedidos!$AE$2:$AE$2224,"SIM")/B24,"") -> 0 | J24: =IFERROR(MAX(0,1-C24/D24),"") -> 0.31812771
A25: 40-50 | B25: =COUNTIFS(Pedidos!$AH$2:$AH$2224,"SIM",Pedidos!$E$2:$E$2224,"Capital",Pedidos!$F$2:$F$2224,$A25) -> 154 | C25: =IFERROR(AVERAGEIFS(Pedidos!$S$2:$S$2224,Pedidos!$AH$2:$AH$2224,"SIM",Pedidos!$E$2:$E$2224,"Capital",Pedidos!$F$2:$F$2224,$A25),"") -> 103.86877 | D25: =IFERROR(AVERAGEIFS(Pedidos!$AB$2:$AB$2224,Pedidos!$AH$2:$AH$2224,"SIM",Pedidos!$E$2:$E$2224,"Capital",Pedidos!$F$2:$F$2224,$A25),"") -> 141.78335 | E25: =IFERROR(D25/C25-1,"") -> 0.36502388 | F25: =IFERROR(AVERAGEIFS(Pedidos!$I$2:$I$2224,Pedidos!$AH$2:$AH$2224,"SIM",Pedidos!$E$2:$E$2224,"Capital",Pedidos!$F$2:$F$2224,$A25),"") -> 53.55 | G25: =IFERROR(AVERAGEIFS(Pedidos!$T$2:$T$2224,Pedidos!$AH$2:$AH$2224,"SIM",Pedidos!$E$2:$E$2224,"Capital",Pedidos!$F$2:$F$2224,$A25),"") -> 93.97 | H25: =IFERROR(G25/F25-1,"") -> 0.75480859 | I25: =IFERROR(COUNTIFS(Pedidos!$AH$2:$AH$2224,"SIM",Pedidos!$E$2:$E$2224,"Capital",Pedidos!$F$2:$F$2224,$A25,Pedidos!$AE$2:$AE$2224,"SIM")/B25,"") -> 0 | J25: =IFERROR(MAX(0,1-C25/D25),"") -> 0.26741208
A26: 50-60 | B26: =COUNTIFS(Pedidos!$AH$2:$AH$2224,"SIM",Pedidos!$E$2:$E$2224,"Capital",Pedidos!$F$2:$F$2224,$A26) -> 181 | C26: =IFERROR(AVERAGEIFS(Pedidos!$S$2:$S$2224,Pedidos!$AH$2:$AH$2224,"SIM",Pedidos!$E$2:$E$2224,"Capital",Pedidos!$F$2:$F$2224,$A26),"") -> 114.10877 | D26: =IFERROR(AVERAGEIFS(Pedidos!$AB$2:$AB$2224,Pedidos!$AH$2:$AH$2224,"SIM",Pedidos!$E$2:$E$2224,"Capital",Pedidos!$F$2:$F$2224,$A26),"") -> 167.53521 | E26: =IFERROR(D26/C26-1,"") -> 0.46820634 | F26: =IFERROR(AVERAGEIFS(Pedidos!$I$2:$I$2224,Pedidos!$AH$2:$AH$2224,"SIM",Pedidos!$E$2:$E$2224,"Capital",Pedidos!$F$2:$F$2224,$A26),"") -> 58.6 | G26: =IFERROR(AVERAGEIFS(Pedidos!$T$2:$T$2224,Pedidos!$AH$2:$AH$2224,"SIM",Pedidos!$E$2:$E$2224,"Capital",Pedidos!$F$2:$F$2224,$A26),"") -> 112.3 | H26: =IFERROR(G26/F26-1,"") -> 0.91638225 | I26: =IFERROR(COUNTIFS(Pedidos!$AH$2:$AH$2224,"SIM",Pedidos!$E$2:$E$2224,"Capital",Pedidos!$F$2:$F$2224,$A26,Pedidos!$AE$2:$AE$2224,"SIM")/B26,"") -> 0 | J26: =IFERROR(MAX(0,1-C26/D26),"") -> 0.31889682
A27: 60-70 | B27: =COUNTIFS(Pedidos!$AH$2:$AH$2224,"SIM",Pedidos!$E$2:$E$2224,"Capital",Pedidos!$F$2:$F$2224,$A27) -> 112 | C27: =IFERROR(AVERAGEIFS(Pedidos!$S$2:$S$2224,Pedidos!$AH$2:$AH$2224,"SIM",Pedidos!$E$2:$E$2224,"Capital",Pedidos!$F$2:$F$2224,$A27),"") -> 126.05791 | D27: =IFERROR(AVERAGEIFS(Pedidos!$AB$2:$AB$2224,Pedidos!$AH$2:$AH$2224,"SIM",Pedidos!$E$2:$E$2224,"Capital",Pedidos!$F$2:$F$2224,$A27),"") -> 196.26069 | E27: =IFERROR(D27/C27-1,"") -> 0.55690899 | F27: =IFERROR(AVERAGEIFS(Pedidos!$I$2:$I$2224,Pedidos!$AH$2:$AH$2224,"SIM",Pedidos!$E$2:$E$2224,"Capital",Pedidos!$F$2:$F$2224,$A27),"") -> 63.21 | G27: =IFERROR(AVERAGEIFS(Pedidos!$T$2:$T$2224,Pedidos!$AH$2:$AH$2224,"SIM",Pedidos!$E$2:$E$2224,"Capital",Pedidos!$F$2:$F$2224,$A27),"") -> 131.02 | H27: =IFERROR(G27/F27-1,"") -> 1.0727733 | I27: =IFERROR(COUNTIFS(Pedidos!$AH$2:$AH$2224,"SIM",Pedidos!$E$2:$E$2224,"Capital",Pedidos!$F$2:$F$2224,$A27,Pedidos!$AE$2:$AE$2224,"SIM")/B27,"") -> 0 | J27: =IFERROR(MAX(0,1-C27/D27),"") -> 0.3577017
A28: 70-80 | B28: =COUNTIFS(Pedidos!$AH$2:$AH$2224,"SIM",Pedidos!$E$2:$E$2224,"Capital",Pedidos!$F$2:$F$2224,$A28) -> 11 | C28: =IFERROR(AVERAGEIFS(Pedidos!$S$2:$S$2224,Pedidos!$AH$2:$AH$2224,"SIM",Pedidos!$E$2:$E$2224,"Capital",Pedidos!$F$2:$F$2224,$A28),"") -> 139.18836 | D28: =IFERROR(AVERAGEIFS(Pedidos!$AB$2:$AB$2224,Pedidos!$AH$2:$AH$2224,"SIM",Pedidos!$E$2:$E$2224,"Capital",Pedidos!$F$2:$F$2224,$A28),"") -> 207.02902 | E28: =IFERROR(D28/C28-1,"") -> 0.48740184 | F28: =IFERROR(AVERAGEIFS(Pedidos!$I$2:$I$2224,Pedidos!$AH$2:$AH$2224,"SIM",Pedidos!$E$2:$E$2224,"Capital",Pedidos!$F$2:$F$2224,$A28),"") -> 68.88 | G28: =IFERROR(AVERAGEIFS(Pedidos!$T$2:$T$2224,Pedidos!$AH$2:$AH$2224,"SIM",Pedidos!$E$2:$E$2224,"Capital",Pedidos!$F$2:$F$2224,$A28),"") -> 134.39 | H28: =IFERROR(G28/F28-1,"") -> 0.95107433 | I28: =IFERROR(COUNTIFS(Pedidos!$AH$2:$AH$2224,"SIM",Pedidos!$E$2:$E$2224,"Capital",Pedidos!$F$2:$F$2224,$A28,Pedidos!$AE$2:$AE$2224,"SIM")/B28,"") -> 0 | J28: =IFERROR(MAX(0,1-C28/D28),"") -> 0.32768673
A29: 80-100 | B29: =COUNTIFS(Pedidos!$AH$2:$AH$2224,"SIM",Pedidos!$E$2:$E$2224,"Capital",Pedidos!$F$2:$F$2224,$A29) -> 19 | C29: =IFERROR(AVERAGEIFS(Pedidos!$S$2:$S$2224,Pedidos!$AH$2:$AH$2224,"SIM",Pedidos!$E$2:$E$2224,"Capital",Pedidos!$F$2:$F$2224,$A29),"") -> 161.83109 | D29: =IFERROR(AVERAGEIFS(Pedidos!$AB$2:$AB$2224,Pedidos!$AH$2:$AH$2224,"SIM",Pedidos!$E$2:$E$2224,"Capital",Pedidos!$F$2:$F$2224,$A29),"") -> 251.89439 | E29: =IFERROR(D29/C29-1,"") -> 0.55652654 | F29: =IFERROR(AVERAGEIFS(Pedidos!$I$2:$I$2224,Pedidos!$AH$2:$AH$2224,"SIM",Pedidos!$E$2:$E$2224,"Capital",Pedidos!$F$2:$F$2224,$A29),"") -> 83.79 | G29: =IFERROR(AVERAGEIFS(Pedidos!$T$2:$T$2224,Pedidos!$AH$2:$AH$2224,"SIM",Pedidos!$E$2:$E$2224,"Capital",Pedidos!$F$2:$F$2224,$A29),"") -> 167.99 | H29: =IFERROR(G29/F29-1,"") -> 1.0048932 | I29: =IFERROR(COUNTIFS(Pedidos!$AH$2:$AH$2224,"SIM",Pedidos!$E$2:$E$2224,"Capital",Pedidos!$F$2:$F$2224,$A29,Pedidos!$AE$2:$AE$2224,"SIM")/B29,"") -> 0 | J29: =IFERROR(MAX(0,1-C29/D29),"") -> 0.35754388
A30: 100-120 | B30: =COUNTIFS(Pedidos!$AH$2:$AH$2224,"SIM",Pedidos!$E$2:$E$2224,"Capital",Pedidos!$F$2:$F$2224,$A30) -> 21 | C30: =IFERROR(AVERAGEIFS(Pedidos!$S$2:$S$2224,Pedidos!$AH$2:$AH$2224,"SIM",Pedidos!$E$2:$E$2224,"Capital",Pedidos!$F$2:$F$2224,$A30),"") -> 185.5082 | D30: =IFERROR(AVERAGEIFS(Pedidos!$AB$2:$AB$2224,Pedidos!$AH$2:$AH$2224,"SIM",Pedidos!$E$2:$E$2224,"Capital",Pedidos!$F$2:$F$2224,$A30),"") -> 309.11115 | E30: =IFERROR(D30/C30-1,"") -> 0.66629369 | F30: =IFERROR(AVERAGEIFS(Pedidos!$I$2:$I$2224,Pedidos!$AH$2:$AH$2224,"SIM",Pedidos!$E$2:$E$2224,"Capital",Pedidos!$F$2:$F$2224,$A30),"") -> 92.34 | G30: =IFERROR(AVERAGEIFS(Pedidos!$T$2:$T$2224,Pedidos!$AH$2:$AH$2224,"SIM",Pedidos!$E$2:$E$2224,"Capital",Pedidos!$F$2:$F$2224,$A30),"") -> 201.59 | H30: =IFERROR(G30/F30-1,"") -> 1.1831276 | I30: =IFERROR(COUNTIFS(Pedidos!$AH$2:$AH$2224,"SIM",Pedidos!$E$2:$E$2224,"Capital",Pedidos!$F$2:$F$2224,$A30,Pedidos!$AE$2:$AE$2224,"SIM")/B30,"") -> 0 | J30: =IFERROR(MAX(0,1-C30/D30),"") -> 0.3998657
A31: 120-150 | B31: =COUNTIFS(Pedidos!$AH$2:$AH$2224,"SIM",Pedidos!$E$2:$E$2224,"Capital",Pedidos!$F$2:$F$2224,$A31) -> 39 | C31: =IFERROR(AVERAGEIFS(Pedidos!$S$2:$S$2224,Pedidos!$AH$2:$AH$2224,"SIM",Pedidos!$E$2:$E$2224,"Capital",Pedidos!$F$2:$F$2224,$A31),"") -> 228.48404 | D31: =IFERROR(AVERAGEIFS(Pedidos!$AB$2:$AB$2224,Pedidos!$AH$2:$AH$2224,"SIM",Pedidos!$E$2:$E$2224,"Capital",Pedidos!$F$2:$F$2224,$A31),"") -> 363.47249 | E31: =IFERROR(D31/C31-1,"") -> 0.59080036 | F31: =IFERROR(AVERAGEIFS(Pedidos!$I$2:$I$2224,Pedidos!$AH$2:$AH$2224,"SIM",Pedidos!$E$2:$E$2224,"Capital",Pedidos!$F$2:$F$2224,$A31),"") -> 120.59 | G31: =IFERROR(AVERAGEIFS(Pedidos!$T$2:$T$2224,Pedidos!$AH$2:$AH$2224,"SIM",Pedidos!$E$2:$E$2224,"Capital",Pedidos!$F$2:$F$2224,$A31),"") -> 239.25 | H31: =IFERROR(G31/F31-1,"") -> 0.98399536 | I31: =IFERROR(COUNTIFS(Pedidos!$AH$2:$AH$2224,"SIM",Pedidos!$E$2:$E$2224,"Capital",Pedidos!$F$2:$F$2224,$A31,Pedidos!$AE$2:$AE$2224,"SIM")/B31,"") -> 0 | J31: =IFERROR(MAX(0,1-C31/D31),"") -> 0.37138561
A32: 150-170 | B32: =COUNTIFS(Pedidos!$AH$2:$AH$2224,"SIM",Pedidos!$E$2:$E$2224,"Capital",Pedidos!$F$2:$F$2224,$A32) -> 2 | C32: =IFERROR(AVERAGEIFS(Pedidos!$S$2:$S$2224,Pedidos!$AH$2:$AH$2224,"SIM",Pedidos!$E$2:$E$2224,"Capital",Pedidos!$F$2:$F$2224,$A32),"") -> 255.66683 | D32: =IFERROR(AVERAGEIFS(Pedidos!$AB$2:$AB$2224,Pedidos!$AH$2:$AH$2224,"SIM",Pedidos!$E$2:$E$2224,"Capital",Pedidos!$F$2:$F$2224,$A32),"") -> 417.59806 | E32: =IFERROR(D32/C32-1,"") -> 0.63336815 | F32: =IFERROR(AVERAGEIFS(Pedidos!$I$2:$I$2224,Pedidos!$AH$2:$AH$2224,"SIM",Pedidos!$E$2:$E$2224,"Capital",Pedidos!$F$2:$F$2224,$A32),"") -> 130.31 | G32: =IFERROR(AVERAGEIFS(Pedidos!$T$2:$T$2224,Pedidos!$AH$2:$AH$2224,"SIM",Pedidos!$E$2:$E$2224,"Capital",Pedidos!$F$2:$F$2224,$A32),"") -> 271.15 | H32: =IFERROR(G32/F32-1,"") -> 1.0808073 | I32: =IFERROR(COUNTIFS(Pedidos!$AH$2:$AH$2224,"SIM",Pedidos!$E$2:$E$2224,"Capital",Pedidos!$F$2:$F$2224,$A32,Pedidos!$AE$2:$AE$2224,"SIM")/B32,"") -> 0 | J32: =IFERROR(MAX(0,1-C32/D32),"") -> 0.38776815
A33: 170-200 | B33: =COUNTIFS(Pedidos!$AH$2:$AH$2224,"SIM",Pedidos!$E$2:$E$2224,"Capital",Pedidos!$F$2:$F$2224,$A33) -> 0 | C33: =IFERROR(AVERAGEIFS(Pedidos!$S$2:$S$2224,Pedidos!$AH$2:$AH$2224,"SIM",Pedidos!$E$2:$E$2224,"Capital",Pedidos!$F$2:$F$2224,$A33),"") | D33: =IFERROR(AVERAGEIFS(Pedidos!$AB$2:$AB$2224,Pedidos!$AH$2:$AH$2224,"SIM",Pedidos!$E$2:$E$2224,"Capital",Pedidos!$F$2:$F$2224,$A33),"") | E33: =IFERROR(D33/C33-1,"") | F33: =IFERROR(AVERAGEIFS(Pedidos!$I$2:$I$2224,Pedidos!$AH$2:$AH$2224,"SIM",Pedidos!$E$2:$E$2224,"Capital",Pedidos!$F$2:$F$2224,$A33),"") | G33: =IFERROR(AVERAGEIFS(Pedidos!$T$2:$T$2224,Pedidos!$AH$2:$AH$2224,"SIM",Pedidos!$E$2:$E$2224,"Capital",Pedidos!$F$2:$F$2224,$A33),"") | H33: =IFERROR(G33/F33-1,"") | I33: =IFERROR(COUNTIFS(Pedidos!$AH$2:$AH$2224,"SIM",Pedidos!$E$2:$E$2224,"Capital",Pedidos!$F$2:$F$2224,$A33,Pedidos!$AE$2:$AE$2224,"SIM")/B33,"") | J33: =IFERROR(MAX(0,1-C33/D33),"")
A34: 200-250 | B34: =COUNTIFS(Pedidos!$AH$2:$AH$2224,"SIM",Pedidos!$E$2:$E$2224,"Capital",Pedidos!$F$2:$F$2224,$A34) -> 1 | C34: =IFERROR(AVERAGEIFS(Pedidos!$S$2:$S$2224,Pedidos!$AH$2:$AH$2224,"SIM",Pedidos!$E$2:$E$2224,"Capital",Pedidos!$F$2:$F$2224,$A34),"") -> 338.21471 | D34: =IFERROR(AVERAGEIFS(Pedidos!$AB$2:$AB$2224,Pedidos!$AH$2:$AH$2224,"SIM",Pedidos!$E$2:$E$2224,"Capital",Pedidos!$F$2:$F$2224,$A34),"") -> 593.32707 | E34: =IFERROR(D34/C34-1,"") -> 0.75429112 | F34: =IFERROR(AVERAGEIFS(Pedidos!$I$2:$I$2224,Pedidos!$AH$2:$AH$2224,"SIM",Pedidos!$E$2:$E$2224,"Capital",Pedidos!$F$2:$F$2224,$A34),"") -> 181.55 | G34: =IFERROR(AVERAGEIFS(Pedidos!$T$2:$T$2224,Pedidos!$AH$2:$AH$2224,"SIM",Pedidos!$E$2:$E$2224,"Capital",Pedidos!$F$2:$F$2224,$A34),"") -> 398.74 | H34: =IFERROR(G34/F34-1,"") -> 1.1963096 | I34: =IFERROR(COUNTIFS(Pedidos!$AH$2:$AH$2224,"SIM",Pedidos!$E$2:$E$2224,"Capital",Pedidos!$F$2:$F$2224,$A34,Pedidos!$AE$2:$AE$2224,"SIM")/B34,"") -> 0 | J34: =IFERROR(MAX(0,1-C34/D34),"") -> 0.42996918
A35: TOTAL | B35: =COUNTIFS(Pedidos!$AH$2:$AH$2224,"SIM",Pedidos!$E$2:$E$2224,"Capital") -> 1030 | C35: =IFERROR(AVERAGEIFS(Pedidos!$S$2:$S$2224,Pedidos!$AH$2:$AH$2224,"SIM",Pedidos!$E$2:$E$2224,"Capital"),"") -> 106.44612 | D35: =IFERROR(AVERAGEIFS(Pedidos!$AB$2:$AB$2224,Pedidos!$AH$2:$AH$2224,"SIM",Pedidos!$E$2:$E$2224,"Capital"),"") -> 156.29299 | E35: =IFERROR(D35/C35-1,"") -> 0.46828261 | F35: =IFERROR(AVERAGEIFS(Pedidos!$I$2:$I$2224,Pedidos!$AH$2:$AH$2224,"SIM",Pedidos!$E$2:$E$2224,"Capital"),"") -> 54.817175 | G35: =IFERROR(AVERAGEIFS(Pedidos!$T$2:$T$2224,Pedidos!$AH$2:$AH$2224,"SIM",Pedidos!$E$2:$E$2224,"Capital"),"") -> 105.42938 | H35: =IFERROR(G35/F35-1,"") -> 0.923291 | I35: =IFERROR(COUNTIFS(Pedidos!$AH$2:$AH$2224,"SIM",Pedidos!$E$2:$E$2224,"Capital",Pedidos!$AE$2:$AE$2224,"SIM")/B35,"") -> 0 | J35: =IFERROR(MAX(0,1-C35/D35),"") -> 0.31893221
A37: Região: Metropolitana
A38: Faixa (kg) | B38: Pedidos | C38: OUTRO PARCEIRO médio | D38: PROLOG médio | E38: PROLOG vs OUTRO PARCEIRO | F38: OUTRO PARCEIRO frete peso | G38: PROLOG frete peso | H38: Frete peso PROLOG vs OUTRO PARCEIRO | I38: % pedidos PROLOG ganharia | J38: Redução necessária
A39: 0-20 | B39: =COUNTIFS(Pedidos!$AH$2:$AH$2224,"SIM",Pedidos!$E$2:$E$2224,"Metropolitana",Pedidos!$F$2:$F$2224,$A39) -> 24 | C39: =IFERROR(AVERAGEIFS(Pedidos!$S$2:$S$2224,Pedidos!$AH$2:$AH$2224,"SIM",Pedidos!$E$2:$E$2224,"Metropolitana",Pedidos!$F$2:$F$2224,$A39),"") -> 76.375653 | D39: =IFERROR(AVERAGEIFS(Pedidos!$AB$2:$AB$2224,Pedidos!$AH$2:$AH$2224,"SIM",Pedidos!$E$2:$E$2224,"Metropolitana",Pedidos!$F$2:$F$2224,$A39),"") -> 76.658069 | E39: =IFERROR(D39/C39-1,"") -> 0.0036977267 | F39: =IFERROR(AVERAGEIFS(Pedidos!$I$2:$I$2224,Pedidos!$AH$2:$AH$2224,"SIM",Pedidos!$E$2:$E$2224,"Metropolitana",Pedidos!$F$2:$F$2224,$A39),"") -> 42.72 | G39: =IFERROR(AVERAGEIFS(Pedidos!$T$2:$T$2224,Pedidos!$AH$2:$AH$2224,"SIM",Pedidos!$E$2:$E$2224,"Metropolitana",Pedidos!$F$2:$F$2224,$A39),"") -> 51.350833 | H39: =IFERROR(G39/F39-1,"") -> 0.20203262 | I39: =IFERROR(COUNTIFS(Pedidos!$AH$2:$AH$2224,"SIM",Pedidos!$E$2:$E$2224,"Metropolitana",Pedidos!$F$2:$F$2224,$A39,Pedidos!$AE$2:$AE$2224,"SIM")/B39,"") -> 0.58333333 | J39: =IFERROR(MAX(0,1-C39/D39),"") -> 0.0036841039
A40: 20-35 | B40: =COUNTIFS(Pedidos!$AH$2:$AH$2224,"SIM",Pedidos!$E$2:$E$2224,"Metropolitana",Pedidos!$F$2:$F$2224,$A40) -> 84 | C40: =IFERROR(AVERAGEIFS(Pedidos!$S$2:$S$2224,Pedidos!$AH$2:$AH$2224,"SIM",Pedidos!$E$2:$E$2224,"Metropolitana",Pedidos!$F$2:$F$2224,$A40),"") -> 100.40846 | D40: =IFERROR(AVERAGEIFS(Pedidos!$AB$2:$AB$2224,Pedidos!$AH$2:$AH$2224,"SIM",Pedidos!$E$2:$E$2224,"Metropolitana",Pedidos!$F$2:$F$2224,$A40),"") -> 128.00589 | E40: =IFERROR(D40/C40-1,"") -> 0.27485163 | F40: =IFERROR(AVERAGEIFS(Pedidos!$I$2:$I$2224,Pedidos!$AH$2:$AH$2224,"SIM",Pedidos!$E$2:$E$2224,"Metropolitana",Pedidos!$F$2:$F$2224,$A40),"") -> 58.8 | G40: =IFERROR(AVERAGEIFS(Pedidos!$T$2:$T$2224,Pedidos!$AH$2:$AH$2224,"SIM",Pedidos!$E$2:$E$2224,"Metropolitana",Pedidos!$F$2:$F$2224,$A40),"") -> 90.957619 | H40: =IFERROR(G40/F40-1,"") -> 0.54689828 | I40: =IFERROR(COUNTIFS(Pedidos!$AH$2:$AH$2224,"SIM",Pedidos!$E$2:$E$2224,"Metropolitana",Pedidos!$F$2:$F$2224,$A40,Pedidos!$AE$2:$AE$2224,"SIM")/B40,"") -> 0 | J40: =IFERROR(MAX(0,1-C40/D40),"") -> 0.215595
A41: 35-40 | B41: =COUNTIFS(Pedidos!$AH$2:$AH$2224,"SIM",Pedidos!$E$2:$E$2224,"Metropolitana",Pedidos!$F$2:$F$2224,$A41) -> 72 | C41: =IFERROR(AVERAGEIFS(Pedidos!$S$2:$S$2224,Pedidos!$AH$2:$AH$2224,"SIM",Pedidos!$E$2:$E$2224,"Metropolitana",Pedidos!$F$2:$F$2224,$A41),"") -> 114.34738 | D41: =IFERROR(AVERAGEIFS(Pedidos!$AB$2:$AB$2224,Pedidos!$AH$2:$AH$2224,"SIM",Pedidos!$E$2:$E$2224,"Metropolitana",Pedidos!$F$2:$F$2224,$A41),"") -> 146.40808 | E41: =IFERROR(D41/C41-1,"") -> 0.2803798 | F41: =IFERROR(AVERAGEIFS(Pedidos!$I$2:$I$2224,Pedidos!$AH$2:$AH$2224,"SIM",Pedidos!$E$2:$E$2224,"Metropolitana",Pedidos!$F$2:$F$2224,$A41),"") -> 66.83 | G41: =IFERROR(AVERAGEIFS(Pedidos!$T$2:$T$2224,Pedidos!$AH$2:$AH$2224,"SIM",Pedidos!$E$2:$E$2224,"Metropolitana",Pedidos!$F$2:$F$2224,$A41),"") -> 102.42028 | H41: =IFERROR(G41/F41-1,"") -> 0.53254942 | I41: =IFERROR(COUNTIFS(Pedidos!$AH$2:$AH$2224,"SIM",Pedidos!$E$2:$E$2224,"Metropolitana",Pedidos!$F$2:$F$2224,$A41,Pedidos!$AE$2:$AE$2224,"SIM")/B41,"") -> 0 | J41: =IFERROR(MAX(0,1-C41/D41),"") -> 0.21898175
A42: 40-50 | B42: =COUNTIFS(Pedidos!$AH$2:$AH$2224,"SIM",Pedidos!$E$2:$E$2224,"Metropolitana",Pedidos!$F$2:$F$2224,$A42) -> 89 | C42: =IFERROR(AVERAGEIFS(Pedidos!$S$2:$S$2224,Pedidos!$AH$2:$AH$2224,"SIM",Pedidos!$E$2:$E$2224,"Metropolitana",Pedidos!$F$2:$F$2224,$A42),"") -> 117.69656 | D42: =IFERROR(AVERAGEIFS(Pedidos!$AB$2:$AB$2224,Pedidos!$AH$2:$AH$2224,"SIM",Pedidos!$E$2:$E$2224,"Metropolitana",Pedidos!$F$2:$F$2224,$A42),"") -> 152.12309 | E42: =IFERROR(D42/C42-1,"") -> 0.29250245 | F42: =IFERROR(AVERAGEIFS(Pedidos!$I$2:$I$2224,Pedidos!$AH$2:$AH$2224,"SIM",Pedidos!$E$2:$E$2224,"Metropolitana",Pedidos!$F$2:$F$2224,$A42),"") -> 65.36 | G42: =IFERROR(AVERAGEIFS(Pedidos!$T$2:$T$2224,Pedidos!$AH$2:$AH$2224,"SIM",Pedidos!$E$2:$E$2224,"Metropolitana",Pedidos!$F$2:$F$2224,$A42),"") -> 102.69202 | H42: =IFERROR(G42/F42-1,"") -> 0.57117537 | I42: =IFERROR(COUNTIFS(Pedidos!$AH$2:$AH$2224,"SIM",Pedidos!$E$2:$E$2224,"Metropolitana",Pedidos!$F$2:$F$2224,$A42,Pedidos!$AE$2:$AE$2224,"SIM")/B42,"") -> 0 | J42: =IFERROR(MAX(0,1-C42/D42),"") -> 0.22630708
A43: 50-60 | B43: =COUNTIFS(Pedidos!$AH$2:$AH$2224,"SIM",Pedidos!$E$2:$E$2224,"Metropolitana",Pedidos!$F$2:$F$2224,$A43) -> 116 | C43: =IFERROR(AVERAGEIFS(Pedidos!$S$2:$S$2224,Pedidos!$AH$2:$AH$2224,"SIM",Pedidos!$E$2:$E$2224,"Metropolitana",Pedidos!$F$2:$F$2224,$A43),"") -> 128.35567 | D43: =IFERROR(AVERAGEIFS(Pedidos!$AB$2:$AB$2224,Pedidos!$AH$2:$AH$2224,"SIM",Pedidos!$E$2:$E$2224,"Metropolitana",Pedidos!$F$2:$F$2224,$A43),"") -> 174.56596 | E43: =IFERROR(D43/C43-1,"") -> 0.36001753 | F43: =IFERROR(AVERAGEIFS(Pedidos!$I$2:$I$2224,Pedidos!$AH$2:$AH$2224,"SIM",Pedidos!$E$2:$E$2224,"Metropolitana",Pedidos!$F$2:$F$2224,$A43),"") -> 70.98 | G43: =IFERROR(AVERAGEIFS(Pedidos!$T$2:$T$2224,Pedidos!$AH$2:$AH$2224,"SIM",Pedidos!$E$2:$E$2224,"Metropolitana",Pedidos!$F$2:$F$2224,$A43),"") -> 118.30828 | H43: =IFERROR(G43/F43-1,"") -> 0.66678326 | I43: =IFERROR(COUNTIFS(Pedidos!$AH$2:$AH$2224,"SIM",Pedidos!$E$2:$E$2224,"Metropolitana",Pedidos!$F$2:$F$2224,$A43,Pedidos!$AE$2:$AE$2224,"SIM")/B43,"") -> 0 | J43: =IFERROR(MAX(0,1-C43/D43),"") -> 0.26471536
A44: 60-70 | B44: =COUNTIFS(Pedidos!$AH$2:$AH$2224,"SIM",Pedidos!$E$2:$E$2224,"Metropolitana",Pedidos!$F$2:$F$2224,$A44) -> 69 | C44: =IFERROR(AVERAGEIFS(Pedidos!$S$2:$S$2224,Pedidos!$AH$2:$AH$2224,"SIM",Pedidos!$E$2:$E$2224,"Metropolitana",Pedidos!$F$2:$F$2224,$A44),"") -> 141.07674 | D44: =IFERROR(AVERAGEIFS(Pedidos!$AB$2:$AB$2224,Pedidos!$AH$2:$AH$2224,"SIM",Pedidos!$E$2:$E$2224,"Metropolitana",Pedidos!$F$2:$F$2224,$A44),"") -> 204.09088 | E44: =IFERROR(D44/C44-1,"") -> 0.4466657 | F44: =IFERROR(AVERAGEIFS(Pedidos!$I$2:$I$2224,Pedidos!$AH$2:$AH$2224,"SIM",Pedidos!$E$2:$E$2224,"Metropolitana",Pedidos!$F$2:$F$2224,$A44),"") -> 76.55 | G44: =IFERROR(AVERAGEIFS(Pedidos!$T$2:$T$2224,Pedidos!$AH$2:$AH$2224,"SIM",Pedidos!$E$2:$E$2224,"Metropolitana",Pedidos!$F$2:$F$2224,$A44),"") -> 137.98348 | H44: =IFERROR(G44/F44-1,"") -> 0.80252748 | I44: =IFERROR(COUNTIFS(Pedidos!$AH$2:$AH$2224,"SIM",Pedidos!$E$2:$E$2224,"Metropolitana",Pedidos!$F$2:$F$2224,$A44,Pedidos!$AE$2:$AE$2224,"SIM")/B44,"") -> 0 | J44: =IFERROR(MAX(0,1-C44/D44),"") -> 0.3087553
A45: 70-80 | B45: =COUNTIFS(Pedidos!$AH$2:$AH$2224,"SIM",Pedidos!$E$2:$E$2224,"Metropolitana",Pedidos!$F$2:$F$2224,$A45) -> 9 | C45: =IFERROR(AVERAGEIFS(Pedidos!$S$2:$S$2224,Pedidos!$AH$2:$AH$2224,"SIM",Pedidos!$E$2:$E$2224,"Metropolitana",Pedidos!$F$2:$F$2224,$A45),"") -> 151.89386 | D45: =IFERROR(AVERAGEIFS(Pedidos!$AB$2:$AB$2224,Pedidos!$AH$2:$AH$2224,"SIM",Pedidos!$E$2:$E$2224,"Metropolitana",Pedidos!$F$2:$F$2224,$A45),"") -> 207.51618 | E45: =IFERROR(D45/C45-1,"") -> 0.366192 | F45: =IFERROR(AVERAGEIFS(Pedidos!$I$2:$I$2224,Pedidos!$AH$2:$AH$2224,"SIM",Pedidos!$E$2:$E$2224,"Metropolitana",Pedidos!$F$2:$F$2224,$A45),"") -> 82.48 | G45: =IFERROR(AVERAGEIFS(Pedidos!$T$2:$T$2224,Pedidos!$AH$2:$AH$2224,"SIM",Pedidos!$E$2:$E$2224,"Metropolitana",Pedidos!$F$2:$F$2224,$A45),"") -> 137.17333 | H45: =IFERROR(G45/F45-1,"") -> 0.66311025 | I45: =IFERROR(COUNTIFS(Pedidos!$AH$2:$AH$2224,"SIM",Pedidos!$E$2:$E$2224,"Metropolitana",Pedidos!$F$2:$F$2224,$A45,Pedidos!$AE$2:$AE$2224,"SIM")/B45,"") -> 0 | J45: =IFERROR(MAX(0,1-C45/D45),"") -> 0.26803846
A46: 80-100 | B46: =COUNTIFS(Pedidos!$AH$2:$AH$2224,"SIM",Pedidos!$E$2:$E$2224,"Metropolitana",Pedidos!$F$2:$F$2224,$A46) -> 11 | C46: =IFERROR(AVERAGEIFS(Pedidos!$S$2:$S$2224,Pedidos!$AH$2:$AH$2224,"SIM",Pedidos!$E$2:$E$2224,"Metropolitana",Pedidos!$F$2:$F$2224,$A46),"") -> 170.55151 | D46: =IFERROR(AVERAGEIFS(Pedidos!$AB$2:$AB$2224,Pedidos!$AH$2:$AH$2224,"SIM",Pedidos!$E$2:$E$2224,"Metropolitana",Pedidos!$F$2:$F$2224,$A46),"") -> 255.11781 | E46: =IFERROR(D46/C46-1,"") -> 0.49584027 | F46: =IFERROR(AVERAGEIFS(Pedidos!$I$2:$I$2224,Pedidos!$AH$2:$AH$2224,"SIM",Pedidos!$E$2:$E$2224,"Metropolitana",Pedidos!$F$2:$F$2224,$A46),"") -> 92.32 | G46: =IFERROR(AVERAGEIFS(Pedidos!$T$2:$T$2224,Pedidos!$AH$2:$AH$2224,"SIM",Pedidos!$E$2:$E$2224,"Metropolitana",Pedidos!$F$2:$F$2224,$A46),"") -> 171.78273 | H46: =IFERROR(G46/F46-1,"") -> 0.86073145 | I46: =IFERROR(COUNTIFS(Pedidos!$AH$2:$AH$2224,"SIM",Pedidos!$E$2:$E$2224,"Metropolitana",Pedidos!$F$2:$F$2224,$A46,Pedidos!$AE$2:$AE$2224,"SIM")/B46,"") -> 0 | J46: =IFERROR(MAX(0,1-C46/D46),"") -> 0.33147943
A47: 100-120 | B47: =COUNTIFS(Pedidos!$AH$2:$AH$2224,"SIM",Pedidos!$E$2:$E$2224,"Metropolitana",Pedidos!$F$2:$F$2224,$A47) -> 18 | C47: =IFERROR(AVERAGEIFS(Pedidos!$S$2:$S$2224,Pedidos!$AH$2:$AH$2224,"SIM",Pedidos!$E$2:$E$2224,"Metropolitana",Pedidos!$F$2:$F$2224,$A47),"") -> 195.08744 | D47: =IFERROR(AVERAGEIFS(Pedidos!$AB$2:$AB$2224,Pedidos!$AH$2:$AH$2224,"SIM",Pedidos!$E$2:$E$2224,"Metropolitana",Pedidos!$F$2:$F$2224,$A47),"") -> 311.73706 | E47: =IFERROR(D47/C47-1,"") -> 0.59793507 | F47: =IFERROR(AVERAGEIFS(Pedidos!$I$2:$I$2224,Pedidos!$AH$2:$AH$2224,"SIM",Pedidos!$E$2:$E$2224,"Metropolitana",Pedidos!$F$2:$F$2224,$A47),"") -> 101.26 | G47: =IFERROR(AVERAGEIFS(Pedidos!$T$2:$T$2224,Pedidos!$AH$2:$AH$2224,"SIM",Pedidos!$E$2:$E$2224,"Metropolitana",Pedidos!$F$2:$F$2224,$A47),"") -> 204.37222 | H47: =IFERROR(G47/F47-1,"") -> 1.0182917 | I47: =IFERROR(COUNTIFS(Pedidos!$AH$2:$AH$2224,"SIM",Pedidos!$E$2:$E$2224,"Metropolitana",Pedidos!$F$2:$F$2224,$A47,Pedidos!$AE$2:$AE$2224,"SIM")/B47,"") -> 0 | J47: =IFERROR(MAX(0,1-C47/D47),"") -> 0.37419234
A48: 120-150 | B48: =COUNTIFS(Pedidos!$AH$2:$AH$2224,"SIM",Pedidos!$E$2:$E$2224,"Metropolitana",Pedidos!$F$2:$F$2224,$A48) -> 18 | C48: =IFERROR(AVERAGEIFS(Pedidos!$S$2:$S$2224,Pedidos!$AH$2:$AH$2224,"SIM",Pedidos!$E$2:$E$2224,"Metropolitana",Pedidos!$F$2:$F$2224,$A48),"") -> 239.50356 | D48: =IFERROR(AVERAGEIFS(Pedidos!$AB$2:$AB$2224,Pedidos!$AH$2:$AH$2224,"SIM",Pedidos!$E$2:$E$2224,"Metropolitana",Pedidos!$F$2:$F$2224,$A48),"") -> 367.45005 | E48: =IFERROR(D48/C48-1,"") -> 0.53421541 | F48: =IFERROR(AVERAGEIFS(Pedidos!$I$2:$I$2224,Pedidos!$AH$2:$AH$2224,"SIM",Pedidos!$E$2:$E$2224,"Metropolitana",Pedidos!$F$2:$F$2224,$A48),"") -> 129.62 | G48: =IFERROR(AVERAGEIFS(Pedidos!$T$2:$T$2224,Pedidos!$AH$2:$AH$2224,"SIM",Pedidos!$E$2:$E$2224,"Metropolitana",Pedidos!$F$2:$F$2224,$A48),"") -> 241.96667 | H48: =IFERROR(G48/F48-1,"") -> 0.86673867 | I48: =IFERROR(COUNTIFS(Pedidos!$AH$2:$AH$2224,"SIM",Pedidos!$E$2:$E$2224,"Metropolitana",Pedidos!$F$2:$F$2224,$A48,Pedidos!$AE$2:$AE$2224,"SIM")/B48,"") -> 0 | J48: =IFERROR(MAX(0,1-C48/D48),"") -> 0.34820105
A49: 150-170 | B49: =COUNTIFS(Pedidos!$AH$2:$AH$2224,"SIM",Pedidos!$E$2:$E$2224,"Metropolitana",Pedidos!$F$2:$F$2224,$A49) -> 1 | C49: =IFERROR(AVERAGEIFS(Pedidos!$S$2:$S$2224,Pedidos!$AH$2:$AH$2224,"SIM",Pedidos!$E$2:$E$2224,"Metropolitana",Pedidos!$F$2:$F$2224,$A49),"") -> 271.37723 | D49: =IFERROR(AVERAGEIFS(Pedidos!$AB$2:$AB$2224,Pedidos!$AH$2:$AH$2224,"SIM",Pedidos!$E$2:$E$2224,"Metropolitana",Pedidos!$F$2:$F$2224,$A49),"") -> 435.30678 | E49: =IFERROR(D49/C49-1,"") -> 0.60406528 | F49: =IFERROR(AVERAGEIFS(Pedidos!$I$2:$I$2224,Pedidos!$AH$2:$AH$2224,"SIM",Pedidos!$E$2:$E$2224,"Metropolitana",Pedidos!$F$2:$F$2224,$A49),"") -> 139.81 | G49: =IFERROR(AVERAGEIFS(Pedidos!$T$2:$T$2224,Pedidos!$AH$2:$AH$2224,"SIM",Pedidos!$E$2:$E$2224,"Metropolitana",Pedidos!$F$2:$F$2224,$A49),"") -> 282.23 | H49: =IFERROR(G49/F49-1,"") -> 1.0186682 | I49: =IFERROR(COUNTIFS(Pedidos!$AH$2:$AH$2224,"SIM",Pedidos!$E$2:$E$2224,"Metropolitana",Pedidos!$F$2:$F$2224,$A49,Pedidos!$AE$2:$AE$2224,"SIM")/B49,"") -> 0 | J49: =IFERROR(MAX(0,1-C49/D49),"") -> 0.37658397
A50: 170-200 | B50: =COUNTIFS(Pedidos!$AH$2:$AH$2224,"SIM",Pedidos!$E$2:$E$2224,"Metropolitana",Pedidos!$F$2:$F$2224,$A50) -> 0 | C50: =IFERROR(AVERAGEIFS(Pedidos!$S$2:$S$2224,Pedidos!$AH$2:$AH$2224,"SIM",Pedidos!$E$2:$E$2224,"Metropolitana",Pedidos!$F$2:$F$2224,$A50),"") | D50: =IFERROR(AVERAGEIFS(Pedidos!$AB$2:$AB$2224,Pedidos!$AH$2:$AH$2224,"SIM",Pedidos!$E$2:$E$2224,"Metropolitana",Pedidos!$F$2:$F$2224,$A50),"") | E50: =IFERROR(D50/C50-1,"") | F50: =IFERROR(AVERAGEIFS(Pedidos!$I$2:$I$2224,Pedidos!$AH$2:$AH$2224,"SIM",Pedidos!$E$2:$E$2224,"Metropolitana",Pedidos!$F$2:$F$2224,$A50),"") | G50: =IFERROR(AVERAGEIFS(Pedidos!$T$2:$T$2224,Pedidos!$AH$2:$AH$2224,"SIM",Pedidos!$E$2:$E$2224,"Metropolitana",Pedidos!$F$2:$F$2224,$A50),"") | H50: =IFERROR(G50/F50-1,"") | I50: =IFERROR(COUNTIFS(Pedidos!$AH$2:$AH$2224,"SIM",Pedidos!$E$2:$E$2224,"Metropolitana",Pedidos!$F$2:$F$2224,$A50,Pedidos!$AE$2:$AE$2224,"SIM")/B50,"") | J50: =IFERROR(MAX(0,1-C50/D50),"")
A51: 200-250 | B51: =COUNTIFS(Pedidos!$AH$2:$AH$2224,"SIM",Pedidos!$E$2:$E$2224,"Metropolitana",Pedidos!$F$2:$F$2224,$A51) -> 0 | C51: =IFERROR(AVERAGEIFS(Pedidos!$S$2:$S$2224,Pedidos!$AH$2:$AH$2224,"SIM",Pedidos!$E$2:$E$2224,"Metropolitana",Pedidos!$F$2:$F$2224,$A51),"") | D51: =IFERROR(AVERAGEIFS(Pedidos!$AB$2:$AB$2224,Pedidos!$AH$2:$AH$2224,"SIM",Pedidos!$E$2:$E$2224,"Metropolitana",Pedidos!$F$2:$F$2224,$A51),"") | E51: =IFERROR(D51/C51-1,"") | F51: =IFERROR(AVERAGEIFS(Pedidos!$I$2:$I$2224,Pedidos!$AH$2:$AH$2224,"SIM",Pedidos!$E$2:$E$2224,"Metropolitana",Pedidos!$F$2:$F$2224,$A51),"") | G51: =IFERROR(AVERAGEIFS(Pedidos!$T$2:$T$2224,Pedidos!$AH$2:$AH$2224,"SIM",Pedidos!$E$2:$E$2224,"Metropolitana",Pedidos!$F$2:$F$2224,$A51),"") | H51: =IFERROR(G51/F51-1,"") | I51: =IFERROR(COUNTIFS(Pedidos!$AH$2:$AH$2224,"SIM",Pedidos!$E$2:$E$2224,"Metropolitana",Pedidos!$F$2:$F$2224,$A51,Pedidos!$AE$2:$AE$2224,"SIM")/B51,"") | J51: =IFERROR(MAX(0,1-C51/D51),"")
A52: TOTAL | B52: =COUNTIFS(Pedidos!$AH$2:$AH$2224,"SIM",Pedidos!$E$2:$E$2224,"Metropolitana") -> 511 | C52: =IFERROR(AVERAGEIFS(Pedidos!$S$2:$S$2224,Pedidos!$AH$2:$AH$2224,"SIM",Pedidos!$E$2:$E$2224,"Metropolitana"),"") -> 127.07634 | D52: =IFERROR(AVERAGEIFS(Pedidos!$AB$2:$AB$2224,Pedidos!$AH$2:$AH$2224,"SIM",Pedidos!$E$2:$E$2224,"Metropolitana"),"") -> 172.87508 | E52: =IFERROR(D52/C52-1,"") -> 0.36040331 | F52: =IFERROR(AVERAGEIFS(Pedidos!$I$2:$I$2224,Pedidos!$AH$2:$AH$2224,"SIM",Pedidos!$E$2:$E$2224,"Metropolitana"),"") -> 70.767906 | G52: =IFERROR(AVERAGEIFS(Pedidos!$T$2:$T$2224,Pedidos!$AH$2:$AH$2224,"SIM",Pedidos!$E$2:$E$2224,"Metropolitana"),"") -> 117.5574 | H52: =IFERROR(G52/F52-1,"") -> 0.66116823 | I52: =IFERROR(COUNTIFS(Pedidos!$AH$2:$AH$2224,"SIM",Pedidos!$E$2:$E$2224,"Metropolitana",Pedidos!$AE$2:$AE$2224,"SIM")/B52,"") -> 0.02739726 | J52: =IFERROR(MAX(0,1-C52/D52),"") -> 0.26492387
A54: Região: Interior
A55: Faixa (kg) | B55: Pedidos | C55: OUTRO PARCEIRO médio | D55: PROLOG médio | E55: PROLOG vs OUTRO PARCEIRO | F55: OUTRO PARCEIRO frete peso | G55: PROLOG frete peso | H55: Frete peso PROLOG vs OUTRO PARCEIRO | I55: % pedidos PROLOG ganharia | J55: Redução necessária
A56: 0-20 | B56: =COUNTIFS(Pedidos!$AH$2:$AH$2224,"SIM",Pedidos!$E$2:$E$2224,"Interior",Pedidos!$F$2:$F$2224,$A56) -> 8 | C56: =IFERROR(AVERAGEIFS(Pedidos!$S$2:$S$2224,Pedidos!$AH$2:$AH$2224,"SIM",Pedidos!$E$2:$E$2224,"Interior",Pedidos!$F$2:$F$2224,$A56),"") -> 80.130354 | D56: =IFERROR(AVERAGEIFS(Pedidos!$AB$2:$AB$2224,Pedidos!$AH$2:$AH$2224,"SIM",Pedidos!$E$2:$E$2224,"Interior",Pedidos!$F$2:$F$2224,$A56),"") -> 115.5371 | E56: =IFERROR(D56/C56-1,"") -> 0.44186438 | F56: =IFERROR(AVERAGEIFS(Pedidos!$I$2:$I$2224,Pedidos!$AH$2:$AH$2224,"SIM",Pedidos!$E$2:$E$2224,"Interior",Pedidos!$F$2:$F$2224,$A56),"") -> 46.95 | G56: =IFERROR(AVERAGEIFS(Pedidos!$T$2:$T$2224,Pedidos!$AH$2:$AH$2224,"SIM",Pedidos!$E$2:$E$2224,"Interior",Pedidos!$F$2:$F$2224,$A56),"") -> 86.54 | H56: =IFERROR(G56/F56-1,"") -> 0.84323749 | I56: =IFERROR(COUNTIFS(Pedidos!$AH$2:$AH$2224,"SIM",Pedidos!$E$2:$E$2224,"Interior",Pedidos!$F$2:$F$2224,$A56,Pedidos!$AE$2:$AE$2224,"SIM")/B56,"") -> 0 | J56: =IFERROR(MAX(0,1-C56/D56),"") -> 0.3064535
A57: 20-35 | B57: =COUNTIFS(Pedidos!$AH$2:$AH$2224,"SIM",Pedidos!$E$2:$E$2224,"Interior",Pedidos!$F$2:$F$2224,$A57) -> 84 | C57: =IFERROR(AVERAGEIFS(Pedidos!$S$2:$S$2224,Pedidos!$AH$2:$AH$2224,"SIM",Pedidos!$E$2:$E$2224,"Interior",Pedidos!$F$2:$F$2224,$A57),"") -> 108.46327 | D57: =IFERROR(AVERAGEIFS(Pedidos!$AB$2:$AB$2224,Pedidos!$AH$2:$AH$2224,"SIM",Pedidos!$E$2:$E$2224,"Interior",Pedidos!$F$2:$F$2224,$A57),"") -> 158.32148 | E57: =IFERROR(D57/C57-1,"") -> 0.45967825 | F57: =IFERROR(AVERAGEIFS(Pedidos!$I$2:$I$2224,Pedidos!$AH$2:$AH$2224,"SIM",Pedidos!$E$2:$E$2224,"Interior",Pedidos!$F$2:$F$2224,$A57),"") -> 65.63 | G57: =IFERROR(AVERAGEIFS(Pedidos!$T$2:$T$2224,Pedidos!$AH$2:$AH$2224,"SIM",Pedidos!$E$2:$E$2224,"Interior",Pedidos!$F$2:$F$2224,$A57),"") -> 117.34762 | H57: =IFERROR(G57/F57-1,"") -> 0.78801797 | I57: =IFERROR(COUNTIFS(Pedidos!$AH$2:$AH$2224,"SIM",Pedidos!$E$2:$E$2224,"Interior",Pedidos!$F$2:$F$2224,$A57,Pedidos!$AE$2:$AE$2224,"SIM")/B57,"") -> 0 | J57: =IFERROR(MAX(0,1-C57/D57),"") -> 0.31491752
A58: 35-40 | B58: =COUNTIFS(Pedidos!$AH$2:$AH$2224,"SIM",Pedidos!$E$2:$E$2224,"Interior",Pedidos!$F$2:$F$2224,$A58) -> 64 | C58: =IFERROR(AVERAGEIFS(Pedidos!$S$2:$S$2224,Pedidos!$AH$2:$AH$2224,"SIM",Pedidos!$E$2:$E$2224,"Interior",Pedidos!$F$2:$F$2224,$A58),"") -> 123.51505 | D58: =IFERROR(AVERAGEIFS(Pedidos!$AB$2:$AB$2224,Pedidos!$AH$2:$AH$2224,"SIM",Pedidos!$E$2:$E$2224,"Interior",Pedidos!$F$2:$F$2224,$A58),"") -> 173.07348 | E58: =IFERROR(D58/C58-1,"") -> 0.40123395 | F58: =IFERROR(AVERAGEIFS(Pedidos!$I$2:$I$2224,Pedidos!$AH$2:$AH$2224,"SIM",Pedidos!$E$2:$E$2224,"Interior",Pedidos!$F$2:$F$2224,$A58),"") -> 74.97 | G58: =IFERROR(AVERAGEIFS(Pedidos!$T$2:$T$2224,Pedidos!$AH$2:$AH$2224,"SIM",Pedidos!$E$2:$E$2224,"Interior",Pedidos!$F$2:$F$2224,$A58),"") -> 125.95297 | H58: =IFERROR(G58/F58-1,"") -> 0.68004493 | I58: =IFERROR(COUNTIFS(Pedidos!$AH$2:$AH$2224,"SIM",Pedidos!$E$2:$E$2224,"Interior",Pedidos!$F$2:$F$2224,$A58,Pedidos!$AE$2:$AE$2224,"SIM")/B58,"") -> 0 | J58: =IFERROR(MAX(0,1-C58/D58),"") -> 0.2863433
A59: 40-50 | B59: =COUNTIFS(Pedidos!$AH$2:$AH$2224,"SIM",Pedidos!$E$2:$E$2224,"Interior",Pedidos!$F$2:$F$2224,$A59) -> 62 | C59: =IFERROR(AVERAGEIFS(Pedidos!$S$2:$S$2224,Pedidos!$AH$2:$AH$2224,"SIM",Pedidos!$E$2:$E$2224,"Interior",Pedidos!$F$2:$F$2224,$A59),"") -> 131.11919 | D59: =IFERROR(AVERAGEIFS(Pedidos!$AB$2:$AB$2224,Pedidos!$AH$2:$AH$2224,"SIM",Pedidos!$E$2:$E$2224,"Interior",Pedidos!$F$2:$F$2224,$A59),"") -> 184.43877 | E59: =IFERROR(D59/C59-1,"") -> 0.40664971 | F59: =IFERROR(AVERAGEIFS(Pedidos!$I$2:$I$2224,Pedidos!$AH$2:$AH$2224,"SIM",Pedidos!$E$2:$E$2224,"Interior",Pedidos!$F$2:$F$2224,$A59),"") -> 77.7 | G59: =IFERROR(AVERAGEIFS(Pedidos!$T$2:$T$2224,Pedidos!$AH$2:$AH$2224,"SIM",Pedidos!$E$2:$E$2224,"Interior",Pedidos!$F$2:$F$2224,$A59),"") -> 131.69129 | H59: =IFERROR(G59/F59-1,"") -> 0.6948686 | I59: =IFERROR(COUNTIFS(Pedidos!$AH$2:$AH$2224,"SIM",Pedidos!$E$2:$E$2224,"Interior",Pedidos!$F$2:$F$2224,$A59,Pedidos!$AE$2:$AE$2224,"SIM")/B59,"") -> 0 | J59: =IFERROR(MAX(0,1-C59/D59),"") -> 0.28909095
A60: 50-60 | B60: =COUNTIFS(Pedidos!$AH$2:$AH$2224,"SIM",Pedidos!$E$2:$E$2224,"Interior",Pedidos!$F$2:$F$2224,$A60) -> 64 | C60: =IFERROR(AVERAGEIFS(Pedidos!$S$2:$S$2224,Pedidos!$AH$2:$AH$2224,"SIM",Pedidos!$E$2:$E$2224,"Interior",Pedidos!$F$2:$F$2224,$A60),"") -> 143.15951 | D60: =IFERROR(AVERAGEIFS(Pedidos!$AB$2:$AB$2224,Pedidos!$AH$2:$AH$2224,"SIM",Pedidos!$E$2:$E$2224,"Interior",Pedidos!$F$2:$F$2224,$A60),"") -> 205.07581 | E60: =IFERROR(D60/C60-1,"") -> 0.43249871 | F60: =IFERROR(AVERAGEIFS(Pedidos!$I$2:$I$2224,Pedidos!$AH$2:$AH$2224,"SIM",Pedidos!$E$2:$E$2224,"Interior",Pedidos!$F$2:$F$2224,$A60),"") -> 83.58 | G60: =IFERROR(AVERAGEIFS(Pedidos!$T$2:$T$2224,Pedidos!$AH$2:$AH$2224,"SIM",Pedidos!$E$2:$E$2224,"Interior",Pedidos!$F$2:$F$2224,$A60),"") -> 144.74672 | H60: =IFERROR(G60/F60-1,"") -> 0.7318344 | I60: =IFERROR(COUNTIFS(Pedidos!$AH$2:$AH$2224,"SIM",Pedidos!$E$2:$E$2224,"Interior",Pedidos!$F$2:$F$2224,$A60,Pedidos!$AE$2:$AE$2224,"SIM")/B60,"") -> 0 | J60: =IFERROR(MAX(0,1-C60/D60),"") -> 0.30191909
A61: 60-70 | B61: =COUNTIFS(Pedidos!$AH$2:$AH$2224,"SIM",Pedidos!$E$2:$E$2224,"Interior",Pedidos!$F$2:$F$2224,$A61) -> 47 | C61: =IFERROR(AVERAGEIFS(Pedidos!$S$2:$S$2224,Pedidos!$AH$2:$AH$2224,"SIM",Pedidos!$E$2:$E$2224,"Interior",Pedidos!$F$2:$F$2224,$A61),"") -> 156.53388 | D61: =IFERROR(AVERAGEIFS(Pedidos!$AB$2:$AB$2224,Pedidos!$AH$2:$AH$2224,"SIM",Pedidos!$E$2:$E$2224,"Interior",Pedidos!$F$2:$F$2224,$A61),"") -> 232.96894 | E61: =IFERROR(D61/C61-1,"") -> 0.4882972 | F61: =IFERROR(AVERAGEIFS(Pedidos!$I$2:$I$2224,Pedidos!$AH$2:$AH$2224,"SIM",Pedidos!$E$2:$E$2224,"Interior",Pedidos!$F$2:$F$2224,$A61),"") -> 90.2 | G61: =IFERROR(AVERAGEIFS(Pedidos!$T$2:$T$2224,Pedidos!$AH$2:$AH$2224,"SIM",Pedidos!$E$2:$E$2224,"Interior",Pedidos!$F$2:$F$2224,$A61),"") -> 163.57149 | H61: =IFERROR(G61/F61-1,"") -> 0.81343115 | I61: =IFERROR(COUNTIFS(Pedidos!$AH$2:$AH$2224,"SIM",Pedidos!$E$2:$E$2224,"Interior",Pedidos!$F$2:$F$2224,$A61,Pedidos!$AE$2:$AE$2224,"SIM")/B61,"") -> 0 | J61: =IFERROR(MAX(0,1-C61/D61),"") -> 0.32809119
A62: 70-80 | B62: =COUNTIFS(Pedidos!$AH$2:$AH$2224,"SIM",Pedidos!$E$2:$E$2224,"Interior",Pedidos!$F$2:$F$2224,$A62) -> 4 | C62: =IFERROR(AVERAGEIFS(Pedidos!$S$2:$S$2224,Pedidos!$AH$2:$AH$2224,"SIM",Pedidos!$E$2:$E$2224,"Interior",Pedidos!$F$2:$F$2224,$A62),"") -> 167.49542 | D62: =IFERROR(AVERAGEIFS(Pedidos!$AB$2:$AB$2224,Pedidos!$AH$2:$AH$2224,"SIM",Pedidos!$E$2:$E$2224,"Interior",Pedidos!$F$2:$F$2224,$A62),"") -> 230.724 | E62: =IFERROR(D62/C62-1,"") -> 0.3774944 | F62: =IFERROR(AVERAGEIFS(Pedidos!$I$2:$I$2224,Pedidos!$AH$2:$AH$2224,"SIM",Pedidos!$E$2:$E$2224,"Interior",Pedidos!$F$2:$F$2224,$A62),"") -> 96.77 | G62: =IFERROR(AVERAGEIFS(Pedidos!$T$2:$T$2224,Pedidos!$AH$2:$AH$2224,"SIM",Pedidos!$E$2:$E$2224,"Interior",Pedidos!$F$2:$F$2224,$A62),"") -> 158.18 | H62: =IFERROR(G62/F62-1,"") -> 0.6345975 | I62: =IFERROR(COUNTIFS(Pedidos!$AH$2:$AH$2224,"SIM",Pedidos!$E$2:$E$2224,"Interior",Pedidos!$F$2:$F$2224,$A62,Pedidos!$AE$2:$AE$2224,"SIM")/B62,"") -> 0 | J62: =IFERROR(MAX(0,1-C62/D62),"") -> 0.27404423
A63: 80-100 | B63: =COUNTIFS(Pedidos!$AH$2:$AH$2224,"SIM",Pedidos!$E$2:$E$2224,"Interior",Pedidos!$F$2:$F$2224,$A63) -> 13 | C63: =IFERROR(AVERAGEIFS(Pedidos!$S$2:$S$2224,Pedidos!$AH$2:$AH$2224,"SIM",Pedidos!$E$2:$E$2224,"Interior",Pedidos!$F$2:$F$2224,$A63),"") -> 190.23584 | D63: =IFERROR(AVERAGEIFS(Pedidos!$AB$2:$AB$2224,Pedidos!$AH$2:$AH$2224,"SIM",Pedidos!$E$2:$E$2224,"Interior",Pedidos!$F$2:$F$2224,$A63),"") -> 282.84316 | E63: =IFERROR(D63/C63-1,"") -> 0.48680269 | F63: =IFERROR(AVERAGEIFS(Pedidos!$I$2:$I$2224,Pedidos!$AH$2:$AH$2224,"SIM",Pedidos!$E$2:$E$2224,"Interior",Pedidos!$F$2:$F$2224,$A63),"") -> 109.63 | G63: =IFERROR(AVERAGEIFS(Pedidos!$T$2:$T$2224,Pedidos!$AH$2:$AH$2224,"SIM",Pedidos!$E$2:$E$2224,"Interior",Pedidos!$F$2:$F$2224,$A63),"") -> 196.12615 | H63: =IFERROR(G63/F63-1,"") -> 0.78898252 | I63: =IFERROR(COUNTIFS(Pedidos!$AH$2:$AH$2224,"SIM",Pedidos!$E$2:$E$2224,"Interior",Pedidos!$F$2:$F$2224,$A63,Pedidos!$AE$2:$AE$2224,"SIM")/B63,"") -> 0 | J63: =IFERROR(MAX(0,1-C63/D63),"") -> 0.3274158
A64: 100-120 | B64: =COUNTIFS(Pedidos!$AH$2:$AH$2224,"SIM",Pedidos!$E$2:$E$2224,"Interior",Pedidos!$F$2:$F$2224,$A64) -> 8 | C64: =IFERROR(AVERAGEIFS(Pedidos!$S$2:$S$2224,Pedidos!$AH$2:$AH$2224,"SIM",Pedidos!$E$2:$E$2224,"Interior",Pedidos!$F$2:$F$2224,$A64),"") -> 215.56551 | D64: =IFERROR(AVERAGEIFS(Pedidos!$AB$2:$AB$2224,Pedidos!$AH$2:$AH$2224,"SIM",Pedidos!$E$2:$E$2224,"Interior",Pedidos!$F$2:$F$2224,$A64),"") -> 345.09854 | E64: =IFERROR(D64/C64-1,"") -> 0.60089867 | F64: =IFERROR(AVERAGEIFS(Pedidos!$I$2:$I$2224,Pedidos!$AH$2:$AH$2224,"SIM",Pedidos!$E$2:$E$2224,"Interior",Pedidos!$F$2:$F$2224,$A64),"") -> 119.5 | G64: =IFERROR(AVERAGEIFS(Pedidos!$T$2:$T$2224,Pedidos!$AH$2:$AH$2224,"SIM",Pedidos!$E$2:$E$2224,"Interior",Pedidos!$F$2:$F$2224,$A64),"") -> 233.98125 | H64: =IFERROR(G64/F64-1,"") -> 0.95800209 | I64: =IFERROR(COUNTIFS(Pedidos!$AH$2:$AH$2224,"SIM",Pedidos!$E$2:$E$2224,"Interior",Pedidos!$F$2:$F$2224,$A64,Pedidos!$AE$2:$AE$2224,"SIM")/B64,"") -> 0 | J64: =IFERROR(MAX(0,1-C64/D64),"") -> 0.37535084
A65: 120-150 | B65: =COUNTIFS(Pedidos!$AH$2:$AH$2224,"SIM",Pedidos!$E$2:$E$2224,"Interior",Pedidos!$F$2:$F$2224,$A65) -> 16 | C65: =IFERROR(AVERAGEIFS(Pedidos!$S$2:$S$2224,Pedidos!$AH$2:$AH$2224,"SIM",Pedidos!$E$2:$E$2224,"Interior",Pedidos!$F$2:$F$2224,$A65),"") -> 255.51067 | D65: =IFERROR(AVERAGEIFS(Pedidos!$AB$2:$AB$2224,Pedidos!$AH$2:$AH$2224,"SIM",Pedidos!$E$2:$E$2224,"Interior",Pedidos!$F$2:$F$2224,$A65),"") -> 386.91276 | E65: =IFERROR(D65/C65-1,"") -> 0.51427239 | F65: =IFERROR(AVERAGEIFS(Pedidos!$I$2:$I$2224,Pedidos!$AH$2:$AH$2224,"SIM",Pedidos!$E$2:$E$2224,"Interior",Pedidos!$F$2:$F$2224,$A65),"") -> 144.24 | G65: =IFERROR(AVERAGEIFS(Pedidos!$T$2:$T$2224,Pedidos!$AH$2:$AH$2224,"SIM",Pedidos!$E$2:$E$2224,"Interior",Pedidos!$F$2:$F$2224,$A65),"") -> 259.89938 | H65: =IFERROR(G65/F65-1,"") -> 0.80185368 | I65: =IFERROR(COUNTIFS(Pedidos!$AH$2:$AH$2224,"SIM",Pedidos!$E$2:$E$2224,"Interior",Pedidos!$F$2:$F$2224,$A65,Pedidos!$AE$2:$AE$2224,"SIM")/B65,"") -> 0 | J65: =IFERROR(MAX(0,1-C65/D65),"") -> 0.33961683
A66: 150-170 | B66: =COUNTIFS(Pedidos!$AH$2:$AH$2224,"SIM",Pedidos!$E$2:$E$2224,"Interior",Pedidos!$F$2:$F$2224,$A66) -> 0 | C66: =IFERROR(AVERAGEIFS(Pedidos!$S$2:$S$2224,Pedidos!$AH$2:$AH$2224,"SIM",Pedidos!$E$2:$E$2224,"Interior",Pedidos!$F$2:$F$2224,$A66),"") | D66: =IFERROR(AVERAGEIFS(Pedidos!$AB$2:$AB$2224,Pedidos!$AH$2:$AH$2224,"SIM",Pedidos!$E$2:$E$2224,"Interior",Pedidos!$F$2:$F$2224,$A66),"") | E66: =IFERROR(D66/C66-1,"") | F66: =IFERROR(AVERAGEIFS(Pedidos!$I$2:$I$2224,Pedidos!$AH$2:$AH$2224,"SIM",Pedidos!$E$2:$E$2224,"Interior",Pedidos!$F$2:$F$2224,$A66),"") | G66: =IFERROR(AVERAGEIFS(Pedidos!$T$2:$T$2224,Pedidos!$AH$2:$AH$2224,"SIM",Pedidos!$E$2:$E$2224,"Interior",Pedidos!$F$2:$F$2224,$A66),"") | H66: =IFERROR(G66/F66-1,"") | I66: =IFERROR(COUNTIFS(Pedidos!$AH$2:$AH$2224,"SIM",Pedidos!$E$2:$E$2224,"Interior",Pedidos!$F$2:$F$2224,$A66,Pedidos!$AE$2:$AE$2224,"SIM")/B66,"") | J66: =IFERROR(MAX(0,1-C66/D66),"")
A67: 170-200 | B67: =COUNTIFS(Pedidos!$AH$2:$AH$2224,"SIM",Pedidos!$E$2:$E$2224,"Interior",Pedidos!$F$2:$F$2224,$A67) -> 1 | C67: =IFERROR(AVERAGEIFS(Pedidos!$S$2:$S$2224,Pedidos!$AH$2:$AH$2224,"SIM",Pedidos!$E$2:$E$2224,"Interior",Pedidos!$F$2:$F$2224,$A67),"") -> 199.73273 | D67: =IFERROR(AVERAGEIFS(Pedidos!$AB$2:$AB$2224,Pedidos!$AH$2:$AH$2224,"SIM",Pedidos!$E$2:$E$2224,"Interior",Pedidos!$F$2:$F$2224,$A67),"") -> 529.025 | E67: =IFERROR(D67/C67-1,"") -> 1.6486646 | F67: =IFERROR(AVERAGEIFS(Pedidos!$I$2:$I$2224,Pedidos!$AH$2:$AH$2224,"SIM",Pedidos!$E$2:$E$2224,"Interior",Pedidos!$F$2:$F$2224,$A67),"") -> 66.69 | G67: =IFERROR(AVERAGEIFS(Pedidos!$T$2:$T$2224,Pedidos!$AH$2:$AH$2224,"SIM",Pedidos!$E$2:$E$2224,"Interior",Pedidos!$F$2:$F$2224,$A67),"") -> 353.17 | H67: =IFERROR(G67/F67-1,"") -> 4.2956965 | I67: =IFERROR(COUNTIFS(Pedidos!$AH$2:$AH$2224,"SIM",Pedidos!$E$2:$E$2224,"Interior",Pedidos!$F$2:$F$2224,$A67,Pedidos!$AE$2:$AE$2224,"SIM")/B67,"") -> 0 | J67: =IFERROR(MAX(0,1-C67/D67),"") -> 0.62245125
A68: 200-250 | B68: =COUNTIFS(Pedidos!$AH$2:$AH$2224,"SIM",Pedidos!$E$2:$E$2224,"Interior",Pedidos!$F$2:$F$2224,$A68) -> 0 | C68: =IFERROR(AVERAGEIFS(Pedidos!$S$2:$S$2224,Pedidos!$AH$2:$AH$2224,"SIM",Pedidos!$E$2:$E$2224,"Interior",Pedidos!$F$2:$F$2224,$A68),"") | D68: =IFERROR(AVERAGEIFS(Pedidos!$AB$2:$AB$2224,Pedidos!$AH$2:$AH$2224,"SIM",Pedidos!$E$2:$E$2224,"Interior",Pedidos!$F$2:$F$2224,$A68),"") | E68: =IFERROR(D68/C68-1,"") | F68: =IFERROR(AVERAGEIFS(Pedidos!$I$2:$I$2224,Pedidos!$AH$2:$AH$2224,"SIM",Pedidos!$E$2:$E$2224,"Interior",Pedidos!$F$2:$F$2224,$A68),"") | G68: =IFERROR(AVERAGEIFS(Pedidos!$T$2:$T$2224,Pedidos!$AH$2:$AH$2224,"SIM",Pedidos!$E$2:$E$2224,"Interior",Pedidos!$F$2:$F$2224,$A68),"") | H68: =IFERROR(G68/F68-1,"") | I68: =IFERROR(COUNTIFS(Pedidos!$AH$2:$AH$2224,"SIM",Pedidos!$E$2:$E$2224,"Interior",Pedidos!$F$2:$F$2224,$A68,Pedidos!$AE$2:$AE$2224,"SIM")/B68,"") | J68: =IFERROR(MAX(0,1-C68/D68),"")
A69: TOTAL | B69: =COUNTIFS(Pedidos!$AH$2:$AH$2224,"SIM",Pedidos!$E$2:$E$2224,"Interior") -> 371 | C69: =IFERROR(AVERAGEIFS(Pedidos!$S$2:$S$2224,Pedidos!$AH$2:$AH$2224,"SIM",Pedidos!$E$2:$E$2224,"Interior"),"") -> 138.70913 | D69: =IFERROR(AVERAGEIFS(Pedidos!$AB$2:$AB$2224,Pedidos!$AH$2:$AH$2224,"SIM",Pedidos!$E$2:$E$2224,"Interior"),"") -> 201.8595 | E69: =IFERROR(D69/C69-1,"") -> 0.45527191 | F69: =IFERROR(AVERAGEIFS(Pedidos!$I$2:$I$2224,Pedidos!$AH$2:$AH$2224,"SIM",Pedidos!$E$2:$E$2224,"Interior"),"") -> 81.496819 | G69: =IFERROR(AVERAGEIFS(Pedidos!$T$2:$T$2224,Pedidos!$AH$2:$AH$2224,"SIM",Pedidos!$E$2:$E$2224,"Interior"),"") -> 143.64633 | H69: =IFERROR(G69/F69-1,"") -> 0.7626005 | I69: =IFERROR(COUNTIFS(Pedidos!$AH$2:$AH$2224,"SIM",Pedidos!$E$2:$E$2224,"Interior",Pedidos!$AE$2:$AE$2224,"SIM")/B69,"") -> 0 | J69: =IFERROR(MAX(0,1-C69/D69),"") -> 0.31284319

Sheet Pedidos
A1: Data pagamento | B1: CEP | C1: CEP (nº) | D1: Cidade | E1: Região OUTRO PARCEIRO | F1: Faixa (kg) | G1: Peso (kg) | H1: Valor NF (R$) | I1: OUTRO PARCEIRO frete peso | J1: OUTRO PARCEIRO ad valorem | K1: OUTRO PARCEIRO GRIS | L1: OUTRO PARCEIRO seguro | M1: OUTRO PARCEIRO pedágio | N1: OUTRO PARCEIRO entrega | O1: OUTRO PARCEIRO CTe fixo | P1: OUTRO PARCEIRO taxa interna | Q1: OUTRO PARCEIRO TRT | R1: OUTRO PARCEIRO subtotal | S1: OUTRO PARCEIRO total c/ ICMS | T1: PROLOG frete peso | U1: PROLOG ad valorem | V1: PROLOG GRIS | W1: PROLOG TAS | X1: PROLOG pedágio | Y1: PROLOG CTe | Z1: PROLOG taxa interna | AA1: PROLOG subtotal | AB1: PROLOG total c/ ICMS | AC1: Dif. PROLOG − OUTRO PARCEIRO (R$) | AD1: Dif. % | AE1: PROLOG mais barata? | AF1: Prazo OUTRO PARCEIRO (du) | AG1: Prazo PROLOG (du) | AH1: Top 20? | AI1: PROLOG PROPOSTA c/ ICMS | AJ1: Proposta mais barata?
A2: 46204.421 | B2: 28913240 | C2: 28913240 | D2: Cabo Frio | E2: Interior | F2: 20-35 | G2: 33 | H2: 389.99 | I2: 65.63 | J2: =H2*Resumo!$C$6 -> 0 | K2: =H2*Resumo!$C$7 -> 0.818979 | L2: =H2*Resumo!$C$8 -> 0.818979 | M2: =Resumo!$C$10*CEILING(G2/100,1) -> 1.05 | N2: =Resumo!$C$9 -> 0 | O2: =Resumo!$C$13 -> 13.55 | P2: =Resumo!$C$14*CEILING(G2,1) -> 14.85 | Q2: =SUM(I2:P2)*Resumo!$C$11 -> 0 | R2: =SUM(I2:Q2) -> 96.717958 | S2: =R2/(1-Resumo!$C$5) -> 109.90677 | T2: 114.95 | U2: =H2*Resumo!$B$6 -> 0.38999 | V2: =H2*Resumo!$B$7 -> 0.77998 | W2: =Resumo!$B$9 -> 1 | X2: =Resumo!$B$10*CEILING(G2/100,1) -> 4.5 | Y2: =Resumo!$B$12*CEILING(G2,1) -> 1.98 | Z2: =Resumo!$B$14*CEILING(G2,1) -> 14.85 | AA2: =SUM(T2:Z2) -> 138.44997 | AB2: =AA2/(1-Resumo!$B$5) -> 157.32951 | AC2: =AB2-S2 -> 47.422741 | AD2: =AB2/S2-1 -> 0.43148152 | AE2: =IF(AB2<S2,"SIM","NÃO") -> NÃO | AF2: 13 | AG2: 10 | AH2: SIM | AI2: =(T2*(1-Painel!$C$40)+U2+V2+Painel!$C$41+Painel!$C$42*CEILING(G2/100,1)+Painel!$C$43*CEILING(G2,1)+Z2)/(1-Resumo!$B$5) -> 108.05281 | AJ2: =IF(AI2<S2,"SIM","NÃO") -> SIM
A3: 46204.475 | B3: 21032000 | C3: 21032000 | D3: Rio de Janeiro | E3: Capital | F3: 40-50 | G3: 49.6 | H3: 799.99 | I3: 53.55 | J3: =H3*Resumo!$C$6 -> 0 | K3: =H3*Resumo!$C$7 -> 1.679979 | L3: =H3*Resumo!$C$8 -> 1.679979 | M3: =Resumo!$C$10*CEILING(G3/100,1) -> 1.05 | N3: =Resumo!$C$9 -> 0 | O3: =Resumo!$C$13 -> 13.55 | P3: =Resumo!$C$14*CEILING(G3,1) -> 22.5 | Q3: =SUM(I3:P3)*Resumo!$C$11 -> 0 | R3: =SUM(I3:Q3) -> 94.009958 | S3: =R3/(1-Resumo!$C$5) -> 106.8295 | T3: 93.97 | U3: =H3*Resumo!$B$6 -> 0.79999 | V3: =H3*Resumo!$B$7 -> 1.59998 | W3: =Resumo!$B$9 -> 1 | X3: =Resumo!$B$10*CEILING(G3/100,1) -> 4.5 | Y3: =Resumo!$B$12*CEILING(G3,1) -> 3 | Z3: =Resumo!$B$14*CEILING(G3,1) -> 22.5 | AA3: =SUM(T3:Z3) -> 127.36997 | AB3: =AA3/(1-Resumo!$B$5) -> 144.7386 | AC3: =AB3-S3 -> 37.909105 | AD3: =AB3/S3-1 -> 0.35485615 | AE3: =IF(AB3<S3,"SIM","NÃO") -> NÃO | AF3: 2 | AG3: 5 | AH3: SIM | AI3: =(T3*(1-Painel!$C$40)+U3+V3+Painel!$C$41+Painel!$C$42*CEILING(G3/100,1)+Painel!$C$43*CEILING(G3,1)+Z3)/(1-Resumo!$B$5) -> 102.17031 | AJ3: =IF(AI3<S3,"SIM","NÃO") -> SIM
A4: 46204.587 | B4: 26545580 | C4: 26545580 | D4: Nilópolis | E4: Metropolitana | F4: 50-60 | G4: 58.5 | H4: 843.2 | I4: 70.98 | J4: =H4*Resumo!$C$6 -> 0 | K4: =H4*Resumo!$C$7 -> 1.77072 | L4: =H4*Resumo!$C$8 -> 1.77072 | M4: =Resumo!$C$10*CEILING(G4/100,1) -> 1.05 | N4: =Resumo!$C$9 -> 0 | O4: =Resumo!$C$13 -> 13.55 | P4: =Resumo!$C$14*CEILING(G4,1) -> 26.55 | Q4: =SUM(I4:P4)*Resumo!$C$11 -> 0 | R4: =SUM(I4:Q4) -> 115.67144 | S4: =R4/(1-Resumo!$C$5) -> 131.44482 | T4: 112.3 | U4: =H4*Resumo!$B$6 -> 0.8432 | V4: =H4*Resumo!$B$7 -> 1.6864 | W4: =Resumo!$B$9 -> 1 | X4: =Resumo!$B$10*CEILING(G4/100,1) -> 4.5 | Y4: =Resumo!$B$12*CEILING(G4,1) -> 3.54 | Z4: =Resumo!$B$14*CEILING(G4,1) -> 26.55 | AA4: =SUM(T4:Z4) -> 150.4196 | AB4: =AA4/(1-Resumo!$B$5) -> 170.93136 | AC4: =AB4-S4 -> 39.486545 | AD4: =AB4/S4-1 -> 0.30040397 | AE4: =IF(AB4<S4,"SIM","NÃO") -> NÃO | AF4: 2 | AG4: 5 | AH4: NÃO | AI4: =(T4*(1-Painel!$C$40)+U4+V4+Painel!$C$41+Painel!$C$42*CEILING(G4/100,1)+Painel!$C$43*CEILING(G4,1)+Z4)/(1-Resumo!$B$5) -> 120.87568 | AJ4: =IF(AI4<S4,"SIM","NÃO") -> SIM
A5: 46204.69 | B5: 22471150 | C5: 22471150 | D5: Rio de Janeiro | E5: Capital | F5: 35-40 | G5: 35.4 | H5: 543.69 | I5: 48.35 | J5: =H5*Resumo!$C$6 -> 0 | K5: =H5*Resumo!$C$7 -> 1.141749 | L5: =H5*Resumo!$C$8 -> 1.141749 | M5: =Resumo!$C$10*CEILING(G5/100,1) -> 1.05 | N5: =Resumo!$C$9 -> 0 | O5: =Resumo!$C$13 -> 13.55 | P5: =Resumo!$C$14*CEILING(G5,1) -> 16.2 | Q5: =SUM(I5:P5)*Resumo!$C$11 -> 0 | R5: =SUM(I5:Q5) -> 81.433498 | S5: =R5/(1-Resumo!$C$5) -> 92.538066 | T5: 93.97 | U5: =H5*Resumo!$B$6 -> 0.54369 | V5: =H5*Resumo!$B$7 -> 1.08738 | W5: =Resumo!$B$9 -> 1 | X5: =Resumo!$B$10*CEILING(G5/100,1) -> 4.5 | Y5: =Resumo!$B$12*CEILING(G5,1) -> 2.16 | Z5: =Resumo!$B$14*CEILING(G5,1) -> 16.2 | AA5: =SUM(T5:Z5) -> 119.46107 | AB5: =AA5/(1-Resumo!$B$5) -> 135.75122 | AC5: =AB5-S5 -> 43.21315 | AD5: =AB5/S5-1 -> 0.46697702 | AE5: =IF(AB5<S5,"SIM","NÃO") -> NÃO | AF5: 2 | AG5: 5 | AH5: SIM | AI5: =(T5*(1-Painel!$C$40)+U5+V5+Painel!$C$41+Painel!$C$42*CEILING(G5/100,1)+Painel!$C$43*CEILING(G5,1)+Z5)/(1-Resumo!$B$5) -> 94.137466 | AJ5: =IF(AI5<S5,"SIM","NÃO") -> NÃO
A6: 46204.75 | B6: 26325100 | C6: 26325100 | D6: Queimados | E6: Metropolitana | F6: 20-35 | G6: 27 | H6: 329.99 | I6: 58.8 | J6: =H6*Resumo!$C$6 -> 0 | K6: =H6*Resumo!$C$7 -> 0.692979 | L6: =H6*Resumo!$C$8 -> 0.692979 | M6: =Resumo!$C$10*CEILING(G6/100,1) -> 1.05 | N6: =Resumo!$C$9 -> 0 | O6: =Resumo!$C$13 -> 13.55 | P6: =Resumo!$C$14*CEILING(G6,1) -> 12.15 | Q6: =SUM(I6:P6)*Resumo!$C$11 -> 0 | R6: =SUM(I6:Q6) -> 86.935958 | S6: =R6/(1-Resumo!$C$5) -> 98.790861 | T6: 82.21 | U6: =H6*Resumo!$B$6 -> 0.32999 | V6: =H6*Resumo!$B$7 -> 0.65998 | W6: =Resumo!$B$9 -> 1 | X6: =Resumo!$B$10*CEILING(G6/100,1) -> 4.5 | Y6: =Resumo!$B$12*CEILING(G6,1) -> 1.62 | Z6: =Resumo!$B$14*CEILING(G6,1) -> 12.15 | AA6: =SUM(T6:Z6) -> 102.46997 | AB6: =AA6/(1-Resumo!$B$5) -> 116.44315 | AC6: =AB6-S6 -> 17.652286 | AD6: =AB6/S6-1 -> 0.17868339 | AE6: =IF(AB6<S6,"SIM","NÃO") -> NÃO | AF6: 2 | AG6: 5 | AH6: NÃO | AI6: =(T6*(1-Painel!$C$40)+U6+V6+Painel!$C$41+Painel!$C$42*CEILING(G6/100,1)+Painel!$C$43*CEILING(G6,1)+Z6)/(1-Resumo!$B$5) -> 79.853034 | AJ6: =IF(AI6<S6,"SIM","NÃO") -> SIM
A7: 46204.806 | B7: 21044020 | C7: 21044020 | D7: Rio de Janeiro | E7: Capital | F7: 50-60 | G7: 55 | H7: 739.98 | I7: 58.6 | J7: =H7*Resumo!$C$6 -> 0 | K7: =H7*Resumo!$C$7 -> 1.553958 | L7: =H7*Resumo!$C$8 -> 1.553958 | M7: =Resumo!$C$10*CEILING(G7/100,1) -> 1.05 | N7: =Resumo!$C$9 -> 0 | O7: =Resumo!$C$13 -> 13.55 | P7: =Resumo!$C$14*CEILING(G7,1) -> 24.75 | Q7: =SUM(I7:P7)*Resumo!$C$11 -> 0 | R7: =SUM(I7:Q7) -> 101.05792 | S7: =R7/(1-Resumo!$C$5) -> 114.83854 | T7: 112.3 | U7: =H7*Resumo!$B$6 -> 0.73998 | V7: =H7*Resumo!$B$7 -> 1.47996 | W7: =Resumo!$B$9 -> 1 | X7: =Resumo!$B$10*CEILING(G7/100,1) -> 4.5 | Y7: =Resumo!$B$12*CEILING(G7,1) -> 3.3 | Z7: =Resumo!$B$14*CEILING(G7,1) -> 24.75 | AA7: =SUM(T7:Z7) -> 148.06994 | AB7: =AA7/(1-Resumo!$B$5) -> 168.2613 | AC7: =AB7-S7 -> 53.422755 | AD7: =AB7/S7-1 -> 0.46519883 | AE7: =IF(AB7<S7,"SIM","NÃO") -> NÃO | AF7: 2 | AG7: 5 | AH7: SIM | AI7: =(T7*(1-Painel!$C$40)+U7+V7+Painel!$C$41+Painel!$C$42*CEILING(G7/100,1)+Painel!$C$43*CEILING(G7,1)+Z7)/(1-Resumo!$B$5) -> 118.47834 | AJ7: =IF(AI7<S7,"SIM","NÃO") -> NÃO
A8: 46204.911 | B8: 28025537 | C8: 28025537 | D8: Campos dos Goytacazes | E8: Interior | F8: 20-35 | G8: 35 | H8: 459.99 | I8: 65.63 | J8: =H8*Resumo!$C$6 -> 0 | K8: =H8*Resumo!$C$7 -> 0.965979 | L8: =H8*Resumo!$C$8 -> 0.965979 | M8: =Resumo!$C$10*CEILING(G8/100,1) -> 1.05 | N8: =Resumo!$C$9 -> 0 | O8: =Resumo!$C$13 -> 13.55 | P8: =Resumo!$C$14*CEILING(G8,1) -> 15.75 | Q8: =SUM(I8:P8)*Resumo!$C$11 -> 0 | R8: =SUM(I8:Q8) -> 97.911958 | S8: =R8/(1-Resumo!$C$5) -> 111.26359 | T8: 138.29 | U8: =H8*Resumo!$B$6 -> 0.45999 | V8: =H8*Resumo!$B$7 -> 0.91998 | W8: =Resumo!$B$9 -> 1 | X8: =Resumo!$B$10*CEILING(G8/100,1) -> 4.5 | Y8: =Resumo!$B$12*CEILING(G8,1) -> 2.1 | Z8: =Resumo!$B$14*CEILING(G8,1) -> 15.75 | AA8: =SUM(T8:Z8) -> 163.01997 | AB8: =AA8/(1-Resumo!$B$5) -> 185.24997 | AC8: =AB8-S8 -> 73.986377 | AD8: =AB8/S8-1 -> 0.66496487 | AE8: =IF(AB8<S8,"SIM","NÃO") -> NÃO | AF8: 13 | AG8: 11 | AH8: SIM | AI8: =(T8*(1-Painel!$C$40)+U8+V8+Painel!$C$41+Painel!$C$42*CEILING(G8/100,1)+Painel!$C$43*CEILING(G8,1)+Z8)/(1-Resumo!$B$5) -> 127.0844 | AJ8: =IF(AI8<S8,"SIM","NÃO") -> NÃO
A9: 46205.458 | B9: 25555570 | C9: 25555570 | D9: São João de Meriti | E9: Metropolitana | F9: 40-50 | G9: 46.8 | H9: 556.99 | I9: 65.36 | J9: =H9*Resumo!$C$6 -> 0 | K9: =H9*Resumo!$C$7 -> 1.169679 | L9: =H9*Resumo!$C$8 -> 1.169679 | M9: =Resumo!$C$10*CEILING(G9/100,1) -> 1.05 | N9: =Resumo!$C$9 -> 0 | O9: =Resumo!$C$13 -> 13.55 | P9: =Resumo!$C$14*CEILING(G9,1) -> 21.15 | Q9: =SUM(I9:P9)*Resumo!$C$11 -> 0 | R9: =SUM(I9:Q9) -> 103.44936 | S9: =R9/(1-Resumo!$C$5) -> 117.55609 | T9: 93.97 | U9: =H9*Resumo!$B$6 -> 0.55699 | V9: =H9*Resumo!$B$7 -> 1.11398 | W9: =Resumo!$B$9 -> 1 | X9: =Resumo!$B$10*CEILING(G9/100,1) -> 4.5 | Y9: =Resumo!$B$12*CEILING(G9,1) -> 2.82 | Z9: =Resumo!$B$14*CEILING(G9,1) -> 21.15 | AA9: =SUM(T9:Z9) -> 125.11097 | AB9: =AA9/(1-Resumo!$B$5) -> 142.17156 | AC9: =AB9-S9 -> 24.615468 | AD9: =AB9/S9-1 -> 0.20939339 | AE9: =IF(AB9<S9,"SIM","NÃO") -> NÃO | AF9: 2 | AG9: 5 | AH9: SIM | AI9: =(T9*(1-Painel!$C$40)+U9+V9+Painel!$C$41+Painel!$C$42*CEILING(G9/100,1)+Painel!$C$43*CEILING(G9,1)+Z9)/(1-Resumo!$B$5) -> 99.807807 | AJ9: =IF(AI9<S9,"SIM","NÃO") -> SIM
A10: 46205.461 | B10: 25947790 | C10: 25947790 | D10: Guapimirim | E10: Interior | F10: 40-50 | G10: 44.5 | H10: 735.99 | I10: 77.7 | J10: =H10*Resumo!$C$6 -> 0 | K10: =H10*Resumo!$C$7 -> 1.545579 | L10: =H10*Resumo!$C$8 -> 1.545579 | M10: =Resumo!$C$10*CEILING(G10/100,1) -> 1.05 | N10: =Resumo!$C$9 -> 0 | O10: =Resumo!$C$13 -> 13.55 | P10: =Resumo!$C$14*CEILING(G10,1) -> 20.25 | Q10: =SUM(I10:P10)*Resumo!$C$11 -> 0 | R10: =SUM(I10:Q10) -> 115.64116 | S10: =R10/(1-Resumo!$C$5) -> 131.41041 | T10: 117.23 | U10: =H10*Resumo!$B$6 -> 0.73599 | V10: =H10*Resumo!$B$7 -> 1.47198 | W10: =Resumo!$B$9 -> 1 | X10: =Resumo!$B$10*CEILING(G10/100,1) -> 4.5 | Y10: =Resumo!$B$12*CEILING(G10,1) -> 2.7 | Z10: =Resumo!$B$14*CEILING(G10,1) -> 20.25 | AA10: =SUM(T10:Z10) -> 147.88797 | AB10: =AA10/(1-Resumo!$B$5) -> 168.05451 | AC10: =AB10-S10 -> 36.644105 | AD10: =AB10/S10-1 -> 0.27885238 | AE10: =IF(AB10<S10,"SIM","NÃO") -> NÃO | AF10: 13 | AG10: 6 | AH10: NÃO | AI10: =(T10*(1-Painel!$C$40)+U10+V10+Painel!$C$41+Painel!$C$42*CEILING(G10/100,1)+Painel!$C$43*CEILING(G10,1)+Z10)/(1-Resumo!$B$5) -> 117.10462 | AJ10: =IF(AI10<S10,"SIM","NÃO") -> SIM
A11: 46205.62 | B11: 22790725 | C11: 22790725 | D11: Rio de Janeiro | E11: Capital | F11: 20-35 | G11: 29 | H11: 339.99 | I11: 42.11 | J11: =H11*Resumo!$C$6 -> 0 | K11: =H11*Resumo!$C$7 -> 0.713979 | L11: =H11*Resumo!$C$8 -> 0.713979 | M11: =Resumo!$C$10*CEILING(G11/100,1) -> 1.05 | N11: =Resumo!$C$9 -> 0 | O11: =Resumo!$C$13 -> 13.55 | P11: =Resumo!$C$14*CEILING(G11,1) -> 13.05 | Q11: =SUM(I11:P11)*Resumo!$C$11 -> 0 | R11: =SUM(I11:Q11) -> 71.187958 | S11: =R11/(1-Resumo!$C$5) -> 80.895407 | T11: 82.21 | U11: =H11*Resumo!$B$6 -> 0.33999 | V11: =H11*Resumo!$B$7 -> 0.67998 | W11: =Resumo!$B$9 -> 1 | X11: =Resumo!$B$10*CEILING(G11/100,1) -> 4.5 | Y11: =Resumo!$B$12*CEILING(G11,1) -> 1.74 | Z11: =Resumo!$B$14*CEILING(G11,1) -> 13.05 | AA11: =SUM(T11:Z11) -> 103.51997 | AB11: =AA11/(1-Resumo!$B$5) -> 117.63633 | AC11: =AB11-S11 -> 36.740923 | AD11: =AB11/S11-1 -> 0.45417811 | AE11: =IF(AB11<S11,"SIM","NÃO") -> NÃO | AF11: 2 | AG11: 5 | AH11: SIM | AI11: =(T11*(1-Painel!$C$40)+U11+V11+Painel!$C$41+Painel!$C$42*CEILING(G11/100,1)+Painel!$C$43*CEILING(G11,1)+Z11)/(1-Resumo!$B$5) -> 80.909852 | AJ11: =IF(AI11<S11,"SIM","NÃO") -> NÃO
A12: 46205.661 | B12: 25811005 | C12: 25811005 | D12: Três Rios | E12: Interior | F12: 40-50 | G12: 48.3 | H12: 459.99 | I12: 77.7 | J12: =H12*Resumo!$C$6 -> 0 | K12: =H12*Resumo!$C$7 -> 0.965979 | L12: =H12*Resumo!$C$8 -> 0.965979 | M12: =Resumo!$C$10*CEILING(G12/100,1) -> 1.05 | N12: =Resumo!$C$9 -> 0 | O12: =Resumo!$C$13 -> 13.55 | P12: =Resumo!$C$14*CEILING(G12,1) -> 22.05 | Q12: =SUM(I12:P12)*Resumo!$C$11 -> 0 | R12: =SUM(I12:Q12) -> 116.28196 | S12: =R12/(1-Resumo!$C$5) -> 132.13859 | T12: 124.38 | U12: =H12*Resumo!$B$6 -> 0.45999 | V12: =H12*Resumo!$B$7 -> 0.91998 | W12: =Resumo!$B$9 -> 1 | X12: =Resumo!$B$10*CEILING(G12/100,1) -> 4.5 | Y12: =Resumo!$B$12*CEILING(G12,1) -> 2.94 | Z12: =Resumo!$B$14*CEILING(G12,1) -> 22.05 | AA12: =SUM(T12:Z12) -> 156.24997 | AB12: =AA12/(1-Resumo!$B$5) -> 177.55678 | AC12: =AB12-S12 -> 45.418195 | AD12: =AB12/S12-1 -> 0.34371637 | AE12: =IF(AB12<S12,"SIM","NÃO") -> NÃO | AF12: 13 | AG12: 8 | AH12: NÃO | AI12: =(T12*(1-Painel!$C$40)+U12+V12+Painel!$C$41+Painel!$C$42*CEILING(G12/100,1)+Painel!$C$43*CEILING(G12,1)+Z12)/(1-Resumo!$B$5) -> 123.65292 | AJ12: =IF(AI12<S12,"SIM","NÃO") -> SIM
A13: 46205.811 | B13: 24467575 | C13: 24467575 | D13: São Gonçalo | E13: Metropolitana | F13: 35-40 | G13: 40 | H13: 599.99 | I13: 66.83 | J13: =H13*Resumo!$C$6 -> 0 | K13: =H13*Resumo!$C$7 -> 1.259979 | L13: =H13*Resumo!$C$8 -> 1.259979 | M13: =Resumo!$C$10*CEILING(G13/100,1) -> 1.05 | N13: =Resumo!$C$9 -> 0 | O13: =Resumo!$C$13 -> 13.55 | P13: =Resumo!$C$14*CEILING(G13,1) -> 18 | Q13: =SUM(I13:P13)*Resumo!$C$11 -> 0 | R13: =SUM(I13:Q13) -> 101.94996 | S13: =R13/(1-Resumo!$C$5) -> 115.85223 | T13: 114.95 | U13: =H13*Resumo!$B$6 -> 0.59999 | V13: =H13*Resumo!$B$7 -> 1.19998 | W13: =Resumo!$B$9 -> 1 | X13: =Resumo!$B$10*CEILING(G13/100,1) -> 4.5 | Y13: =Resumo!$B$12*CEILING(G13,1) -> 2.4 | Z13: =Resumo!$B$14*CEILING(G13,1) -> 18 | AA13: =SUM(T13:Z13) -> 142.64997 | AB13: =AA13/(1-Resumo!$B$5) -> 162.10224 | AC13: =AB13-S13 -> 46.250014 | AD13: =AB13/S13-1 -> 0.39921558 | AE13: =IF(AB13<S13,"SIM","NÃO") -> NÃO | AF13: 2 | AG13: 7 | AH13: SIM | AI13: =(T13*(1-Painel!$C$40)+U13+V13+Painel!$C$41+Painel!$C$42*CEILING(G13/100,1)+Painel!$C$43*CEILING(G13,1)+Z13)/(1-Resumo!$B$5) -> 112.34826 | AJ13: =IF(AI13<S13,"SIM","NÃO") -> SIM
... A1158: 46251.795 | B1158: 28949460 | C1158: 28949460 | D1158: São Pedro da Aldeia | E1158: Interior | F1158: 50-60 | G1158: 52.3 | H1158: 577.12 | I1158: 83.58 | J1158: =H1158*Resumo!$C$6 -> 0 | K1158: =H1158*Resumo!$C$7 -> 1.211952 | L1158: =H1158*Resumo!$C$8 -> 1.211952 | M1158: =Resumo!$C$10*CEILING(G1158/100,1) -> 1.05 | N1158: =Resumo!$C$9 -> 0 | O1158: =Resumo!$C$13 -> 13.55 | P1158: =Resumo!$C$14*CEILING(G1158,1) -> 23.85 | Q1158: =SUM(I1158:P1158)*Resumo!$C$11 -> 0 | R1158: =SUM(I1158:Q1158) -> 124.4539 | S1158: =R1158/(1-Resumo!$C$5) -> 141.42489 | T1158: 142.32 | U1158: =H1158*Resumo!$B$6 -> 0.57712 | V1158: =H1158*Resumo!$B$7 -> 1.15424 | W1158: =Resumo!$B$9 -> 1 | X1158: =Resumo!$B$10*CEILING(G1158/100,1) -> 4.5 | Y1158: =Resumo!$B$12*CEILING(G1158,1) -> 3.18 | Z1158: =Resumo!$B$14*CEILING(G1158,1) -> 23.85 | AA1158: =SUM(T1158:Z1158) -> 176.58136 | AB1158: =AA1158/(1-Resumo!$B$5) -> 200.66064 | AC1158: =AB1158-S1158 -> 59.235745 | AD1158: =AB1158/S1158-1 -> 0.4188495 | AE1158: =IF(AB1158<S1158,"SIM","NÃO") -> NÃO | AF1158: 13 | AG1158: 10 | AH1158: NÃO | AI1158: =(T1158*(1-Painel!$C$40)+U1158+V1158+Painel!$C$41+Painel!$C$42*CEILING(G1158/100,1)+Painel!$C$43*CEILING(G1158,1)+Z1158)/(1-Resumo!$B$5) -> 139.75655 | AJ1158: =IF(AI1158<S1158,"SIM","NÃO") -> SIM
A1159: 46251.803 | B1159: 27995000 | C1159: 27995000 | E1159: Interior | F1159: 40-50 | G1159: 44.6 | H1159: 579.99 | I1159: 77.7 | J1159: =H1159*Resumo!$C$6 -> 0 | K1159: =H1159*Resumo!$C$7 -> 1.217979 | L1159: =H1159*Resumo!$C$8 -> 1.217979 | M1159: =Resumo!$C$10*CEILING(G1159/100,1) -> 1.05 | N1159: =Resumo!$C$9 -> 0 | O1159: =Resumo!$C$13 -> 13.55 | P1159: =Resumo!$C$14*CEILING(G1159,1) -> 20.25 | Q1159: =SUM(I1159:P1159)*Resumo!$C$11 -> 0 | R1159: =SUM(I1159:Q1159) -> 114.98596 | S1159: =R1159/(1-Resumo!$C$5) -> 130.66586 | T1159: 152.54 | U1159: =H1159*Resumo!$B$6 -> 0.57999 | V1159: =H1159*Resumo!$B$7 -> 1.15998 | W1159: =Resumo!$B$9 -> 1 | X1159: =Resumo!$B$10*CEILING(G1159/100,1) -> 4.5 | Y1159: =Resumo!$B$12*CEILING(G1159,1) -> 2.7 | Z1159: =Resumo!$B$14*CEILING(G1159,1) -> 20.25 | AA1159: =SUM(T1159:Z1159) -> 182.72997 | AB1159: =AA1159/(1-Resumo!$B$5) -> 207.64769 | AC1159: =AB1159-S1159 -> 76.981832 | AD1159: =AB1159/S1159-1 -> 0.5891503 | AE1159: =IF(AB1159<S1159,"SIM","NÃO") -> NÃO | AF1159: 13 | AG1159: 11 | AH1159: NÃO | AI1159: =(T1159*(1-Painel!$C$40)+U1159+V1159+Painel!$C$41+Painel!$C$42*CEILING(G1159/100,1)+Painel!$C$43*CEILING(G1159,1)+Z1159)/(1-Resumo!$B$5) -> 143.45656 | AJ1159: =IF(AI1159<S1159,"SIM","NÃO") -> NÃO
A1160: 46251.81 | B1160: 23595200 | C1160: 23595200 | D1160: Rio de Janeiro | E1160: Capital | F1160: 35-40 | G1160: 37.6 | H1160: 399.59 | I1160: 48.35 | J1160: =H1160*Resumo!$C$6 -> 0 | K1160: =H1160*Resumo!$C$7 -> 0.839139 | L1160: =H1160*Resumo!$C$8 -> 0.839139 | M1160: =Resumo!$C$10*CEILING(G1160/100,1) -> 1.05 | N1160: =Resumo!$C$9 -> 0 | O1160: =Resumo!$C$13 -> 13.55 | P1160: =Resumo!$C$14*CEILING(G1160,1) -> 17.1 | Q1160: =SUM(I1160:P1160)*Resumo!$C$11 -> 0 | R1160: =SUM(I1160:Q1160) -> 81.728278 | S1160: =R1160/(1-Resumo!$C$5) -> 92.873043 | T1160: 93.97 | U1160: =H1160*Resumo!$B$6 -> 0.39959 | V1160: =H1160*Resumo!$B$7 -> 0.79918 | W1160: =Resumo!$B$9 -> 1 | X1160: =Resumo!$B$10*CEILING(G1160/100,1) -> 4.5 | Y1160: =Resumo!$B$12*CEILING(G1160,1) -> 2.28 | Z1160: =Resumo!$B$14*CEILING(G1160,1) -> 17.1 | AA1160: =SUM(T1160:Z1160) -> 120.04877 | AB1160: =AA1160/(1-Resumo!$B$5) -> 136.41906 | AC1160: =AB1160-S1160 -> 43.546014 | AD1160: =AB1160/S1160-1 -> 0.46887678 | AE1160: =IF(AB1160<S1160,"SIM","NÃO") -> NÃO | AF1160: 2 | AG1160: 5 | AH1160: SIM | AI1160: =(T1160*(1-Painel!$C$40)+U1160+V1160+Painel!$C$41+Painel!$C$42*CEILING(G1160/100,1)+Painel!$C$43*CEILING(G1160,1)+Z1160)/(1-Resumo!$B$5) -> 94.668943 | AJ1160: =IF(AI1160<S1160,"SIM","NÃO") -> NÃO
A1161: 46251.825 | B1161: 28634110 | C1161: 28634110 | D1161: Nova Friburgo | E1161: Interior | F1161: 120-150 | G1161: 141.5 | H1161: 1599.99 | I1161: 144.24 | J1161: =H1161*Resumo!$C$6 -> 0 | K1161: =H1161*Resumo!$C$7 -> 3.359979 | L1161: =H1161*Resumo!$C$8 -> 3.359979 | M1161: =Resumo!$C$10*CEILING(G1161/100,1) -> 2.1 | N1161: =Resumo!$C$9 -> 0 | O1161: =Resumo!$C$13 -> 13.55 | P1161: =Resumo!$C$14*CEILING(G1161,1) -> 63.9 | Q1161: =SUM(I1161:P1161)*Resumo!$C$11 -> 0 | R1161: =SUM(I1161:Q1161) -> 230.50996 | S1161: =R1161/(1-Resumo!$C$5) -> 261.94313 | T1161: 264.84 | U1161: =H1161*Resumo!$B$6 -> 1.59999 | V1161: =H1161*Resumo!$B$7 -> 3.19998 | W1161: =Resumo!$B$9 -> 1 | X1161: =Resumo!$B$10*CEILING(G1161/100,1) -> 9 | Y1161: =Resumo!$B$12*CEILING(G1161,1) -> 8.52 | Z1161: =Resumo!$B$14*CEILING(G1161,1) -> 63.9 | AA1161: =SUM(T1161:Z1161) -> 352.05997 | AB1161: =AA1161/(1-Resumo!$B$5) -> 400.06815 | AC1161: =AB1161-S1161 -> 138.12501 | AD1161: =AB1161/S1161-1 -> 0.52730916 | AE1161: =IF(AB1161<S1161,"SIM","NÃO") -> NÃO | AF1161: 13 | AG1161: 10 | AH1161: SIM | AI1161: =(T1161*(1-Painel!$C$40)+U1161+V1161+Painel!$C$41+Painel!$C$42*CEILING(G1161/100,1)+Painel!$C$43*CEILING(G1161,1)+Z1161)/(1-Resumo!$B$5) -> 283.23042 | AJ1161: =IF(AI1161<S1161,"SIM","NÃO") -> NÃO
A1162: 46251.846 | B1162: 24751000 | C1162: 24751000 | D1162: São Gonçalo | E1162: Metropolitana | F1162: 50-60 | G1162: 52.3 | H1162: 637.3 | I1162: 70.98 | J1162: =H1162*Resumo!$C$6 -> 0 | K1162: =H1162*Resumo!$C$7 -> 1.33833 | L1162: =H1162*Resumo!$C$8 -> 1.33833 | M1162: =Resumo!$C$10*CEILING(G1162/100,1) -> 1.05 | N1162: =Resumo!$C$9 -> 0 | O1162: =Resumo!$C$13 -> 13.55 | P1162: =Resumo!$C$14*CEILING(G1162,1) -> 23.85 | Q1162: =SUM(I1162:P1162)*Resumo!$C$11 -> 0 | R1162: =SUM(I1162:Q1162) -> 112.10666 | S1162: =R1162/(1-Resumo!$C$5) -> 127.39393 | T1162: 128.14 | U1162: =H1162*Resumo!$B$6 -> 0.6373 | V1162: =H1162*Resumo!$B$7 -> 1.2746 | W1162: =Resumo!$B$9 -> 1 | X1162: =Resumo!$B$10*CEILING(G1162/100,1) -> 4.5 | Y1162: =Resumo!$B$12*CEILING(G1162,1) -> 3.18 | Z1162: =Resumo!$B$14*CEILING(G1162,1) -> 23.85 | AA1162: =SUM(T1162:Z1162) -> 162.5819 | AB1162: =AA1162/(1-Resumo!$B$5) -> 184.75216 | AC1162: =AB1162-S1162 -> 57.358227 | AD1162: =AB1162/S1162-1 -> 0.45024301 | AE1162: =IF(AB1162<S1162,"SIM","NÃO") -> NÃO | AF1162: 2 | AG1162: 7 | AH1162: SIM | AI1162: =(T1162*(1-Painel!$C$40)+U1162+V1162+Painel!$C$41+Painel!$C$42*CEILING(G1162/100,1)+Painel!$C$43*CEILING(G1162,1)+Z1162)/(1-Resumo!$B$5) -> 129.16557 | AJ1162: =IF(AI1162<S1162,"SIM","NÃO") -> NÃO
A1163: 46251.864 | B1163: 27240559 | C1163: 27240559 | D1163: Volta Redonda | E1163: Interior | F1163: 50-60 | G1163: 51.3 | H1163: 649.99 | I1163: 83.58 | J1163: =H1163*Resumo!$C$6 -> 0 | K1163: =H1163*Resumo!$C$7 -> 1.364979 | L1163: =H1163*Resumo!$C$8 -> 1.364979 | M1163: =Resumo!$C$10*CEILING(G1163/100,1) -> 1.05 | N1163: =Resumo!$C$9 -> 0 | O1163: =Resumo!$C$13 -> 13.55 | P1163: =Resumo!$C$14*CEILING(G1163,1) -> 23.4 | Q1163: =SUM(I1163:P1163)*Resumo!$C$11 -> 0 | R1163: =SUM(I1163:Q1163) -> 124.30996 | S1163: =R1163/(1-Resumo!$C$5) -> 141.26132 | T1163: 142.32 | U1163: =H1163*Resumo!$B$6 -> 0.64999 | V1163: =H1163*Resumo!$B$7 -> 1.29998 | W1163: =Resumo!$B$9 -> 1 | X1163: =Resumo!$B$10*CEILING(G1163/100,1) -> 4.5 | Y1163: =Resumo!$B$12*CEILING(G1163,1) -> 3.12 | Z1163: =Resumo!$B$14*CEILING(G1163,1) -> 23.4 | AA1163: =SUM(T1163:Z1163) -> 176.28997 | AB1163: =AA1163/(1-Resumo!$B$5) -> 200.32951 | AC1163: =AB1163-S1163 -> 59.068195 | AD1163: =AB1163/S1163-1 -> 0.41814842 | AE1163: =IF(AB1163<S1163,"SIM","NÃO") -> NÃO | AF1163: 13 | AG1163: 10 | AH1163: SIM | AI1163: =(T1163*(1-Painel!$C$40)+U1163+V1163+Painel!$C$41+Painel!$C$42*CEILING(G1163/100,1)+Painel!$C$43*CEILING(G1163,1)+Z1163)/(1-Resumo!$B$5) -> 139.4936 | AJ1163: =IF(AI1163<S1163,"SIM","NÃO") -> SIM
A1164: 46251.867 | B1164: 24934275 | C1164: 24934275 | D1164: Maricá | E1164: Interior | F1164: 50-60 | G1164: 52.3 | H1164: 699.99 | I1164: 83.58 | J1164: =H1164*Resumo!$C$6 -> 0 | K1164: =H1164*Resumo!$C$7 -> 1.469979 | L1164: =H1164*Resumo!$C$8 -> 1.469979 | M1164: =Resumo!$C$10*CEILING(G1164/100,1) -> 1.05 | N1164: =Resumo!$C$9 -> 0 | O1164: =Resumo!$C$13 -> 13.55 | P1164: =Resumo!$C$14*CEILING(G1164,1) -> 23.85 | Q1164: =SUM(I1164:P1164)*Resumo!$C$11 -> 0 | R1164: =SUM(I1164:Q1164) -> 124.96996 | S1164: =R1164/(1-Resumo!$C$5) -> 142.01132 | T1164: 128.14 | U1164: =H1164*Resumo!$B$6 -> 0.69999 | V1164: =H1164*Resumo!$B$7 -> 1.39998 | W1164: =Resumo!$B$9 -> 1 | X1164: =Resumo!$B$10*CEILING(G1164/100,1) -> 4.5 | Y1164: =Resumo!$B$12*CEILING(G1164,1) -> 3.18 | Z1164: =Resumo!$B$14*CEILING(G1164,1) -> 23.85 | AA1164: =SUM(T1164:Z1164) -> 162.76997 | AB1164: =AA1164/(1-Resumo!$B$5) -> 184.96588 | AC1164: =AB1164-S1164 -> 42.954559 | AD1164: =AB1164/S1164-1 -> 0.30247279 | AE1164: =IF(AB1164<S1164,"SIM","NÃO") -> NÃO | AF1164: 13 | AG1164: 7 | AH1164: SIM | AI1164: =(T1164*(1-Painel!$C$40)+U1164+V1164+Painel!$C$41+Painel!$C$42*CEILING(G1164/100,1)+Painel!$C$43*CEILING(G1164,1)+Z1164)/(1-Resumo!$B$5) -> 129.37928 | AJ1164: =IF(AI1164<S1164,"SIM","NÃO") -> SIM
A1165: 46251.878 | B1165: 21875240 | C1165: 21875240 | D1165: Rio de Janeiro | E1165: Capital | F1165: 40-50 | G1165: 46.8 | H1165: 506.56 | I1165: 53.55 | J1165: =H1165*Resumo!$C$6 -> 0 | K1165: =H1165*Resumo!$C$7 -> 1.063776 | L1165: =H1165*Resumo!$C$8 -> 1.063776 | M1165: =Resumo!$C$10*CEILING(G1165/100,1) -> 1.05 | N1165: =Resumo!$C$9 -> 0 | O1165: =Resumo!$C$13 -> 13.55 | P1165: =Resumo!$C$14*CEILING(G1165,1) -> 21.15 | Q1165: =SUM(I1165:P1165)*Resumo!$C$11 -> 0 | R1165: =SUM(I1165:Q1165) -> 91.427552 | S1165: =R1165/(1-Resumo!$C$5) -> 103.89495 | T1165: 93.97 | U1165: =H1165*Resumo!$B$6 -> 0.50656 | V1165: =H1165*Resumo!$B$7 -> 1.01312 | W1165: =Resumo!$B$9 -> 1 | X1165: =Resumo!$B$10*CEILING(G1165/100,1) -> 4.5 | Y1165: =Resumo!$B$12*CEILING(G1165,1) -> 2.82 | Z1165: =Resumo!$B$14*CEILING(G1165,1) -> 21.15 | AA1165: =SUM(T1165:Z1165) -> 124.95968 | AB1165: =AA1165/(1-Resumo!$B$5) -> 141.99964 | AC1165: =AB1165-S1165 -> 38.104691 | AD1165: =AB1165/S1165-1 -> 0.36676174 | AE1165: =IF(AB1165<S1165,"SIM","NÃO") -> NÃO | AF1165: 2 | AG1165: 5 | AH1165: SIM | AI1165: =(T1165*(1-Painel!$C$40)+U1165+V1165+Painel!$C$41+Painel!$C$42*CEILING(G1165/100,1)+Painel!$C$43*CEILING(G1165,1)+Z1165)/(1-Resumo!$B$5) -> 99.635886 | AJ1165: =IF(AI1165<S1165,"SIM","NÃO") -> SIM
A1166: 46251.882 | B1166: 25268376 | C1166: 25268376 | D1166: Duque de Caxias | E1166: Metropolitana | F1166: 60-70 | G1166: 66.8 | H1166: 719.99 | I1166: 76.55 | J1166: =H1166*Resumo!$C$6 -> 0 | K1166: =H1166*Resumo!$C$7 -> 1.511979 | L1166: =H1166*Resumo!$C$8 -> 1.511979 | M1166: =Resumo!$C$10*CEILING(G1166/100,1) -> 1.05 | N1166: =Resumo!$C$9 -> 0 | O1166: =Resumo!$C$13 -> 13.55 | P1166: =Resumo!$C$14*CEILING(G1166,1) -> 30.15 | Q1166: =SUM(I1166:P1166)*Resumo!$C$11 -> 0 | R1166: =SUM(I1166:Q1166) -> 124.32396 | S1166: =R1166/(1-Resumo!$C$5) -> 141.27722 | T1166: 131.02 | U1166: =H1166*Resumo!$B$6 -> 0.71999 | V1166: =H1166*Resumo!$B$7 -> 1.43998 | W1166: =Resumo!$B$9 -> 1 | X1166: =Resumo!$B$10*CEILING(G1166/100,1) -> 4.5 | Y1166: =Resumo!$B$12*CEILING(G1166,1) -> 4.02 | Z1166: =Resumo!$B$14*CEILING(G1166,1) -> 30.15 | AA1166: =SUM(T1166:Z1166) -> 172.84997 | AB1166: =AA1166/(1-Resumo!$B$5) -> 196.42042 | AC1166: =AB1166-S1166 -> 55.143195 | AD1166: =AB1166/S1166-1 -> 0.39031907 | AE1166: =IF(AB1166<S1166,"SIM","NÃO") -> NÃO | AF1166: 2 | AG1166: 5 | AH1166: SIM | AI1166: =(T1166*(1-Painel!$C$40)+U1166+V1166+Painel!$C$41+Painel!$C$42*CEILING(G1166/100,1)+Painel!$C$43*CEILING(G1166,1)+Z1166)/(1-Resumo!$B$5) -> 138.79928 | AJ1166: =IF(AI1166<S1166,"SIM","NÃO") -> SIM
