Workbook

Sheet Resumo
A1: Simulação PROLOG FILIAL SP — Pedidos RJ com origem de cotação FILIAL SP (jul–set/2026)
A3: PREMISSAS
A5: Parâmetro | C5: Valor | D5: Fonte / observação
A6: Alíquota ICMS SP→RJ (gross-up, tabela marcada "ICMS já calculado? = N") | C6: 0.12 | D6: Interestadual SP→RJ 12%. Intelipost soma o ICMS por dentro: total = subtotal / (1 − alíquota).
A7: Ad valorem (% NF) | C7: 0.001 | D7: Da tabela: FRETE VALOR (%) = 0,1
A8: GRIS (% NF) | C8: 0.002 | D8: Da tabela: GRIS (%) = 0,2
A9: TAS (R$ por pedido) | C9: 1 | D9: Da tabela
A10: Pedágio (R$ por fração de 100 kg) | C10: 4.5 | D10: Da tabela: 4,50 / faixa 100 kg
A11: CTe (R$ por kg) | C11: 0.06 | D11: Da tabela: CTE FIXO 0,06 com faixa de 1 kg → cobrado por kg
A12: Outra taxa (R$ por kg) | C12: 0.45 | D12: Da tabela: OUTRA TAXA FIXO 0,45 com faixa de 1 kg → cobrado por kg
A13: Cubagem | C13: Não aplicada | D13: Fator de cubagem = 0 na tabela; usado PESO ITENS
A14: Peso > 250 kg | C14: Faixa 250 + excedente/kg | D14: Nenhum pedido no recorte passa de 250 kg
A16: Obs.: as taxas (exceto ICMS) estão calculadas por pedido na aba Pedidos (colunas K–Q); a célula C6 recalcula o total.
A18: VISÃO GERAL
A19: Indicador | C19: Atual (transportadoras cotadas) | D19: PROLOG FILIAL SP (simulado) | E19: Diferença
A20: Pedidos | C20: =COUNTA(Pedidos!$A$2:$A$2224) -> 2223 | D20: =COUNTA(Pedidos!$A$2:$A$2224) -> 2223
A21: Custo total de frete | C21: =SUM(Pedidos!$J$2:$J$2224) -> 269909.92 | D21: =SUM(Pedidos!$S$2:$S$2224) -> 386659.7 | E21: =D21/C21-1 -> 0.43255089
A22: Custo médio por pedido | C22: =AVERAGE(Pedidos!$J$2:$J$2224) -> 121.41697 | D22: =AVERAGE(Pedidos!$S$2:$S$2224) -> 173.93599 | E22: =D22/C22-1 -> 0.43255089
A23: Valor de NF total | C23: =SUM(Pedidos!$H$2:$H$2224) -> 1426798.1 | D23: =SUM(Pedidos!$H$2:$H$2224) -> 1426798.1
A24: Frete / NF (participação no custo) | C24: =C21/C23 -> 0.18917178 | D24: =D21/D23 -> 0.2709982 | E24: =D24-C24 -> 0.08182642
A25: % de pedidos em que PROLOG seria mais barata | D25: =COUNTIF(Pedidos!$V$2:$V$2224,"SIM")/C20 -> 0.0067476383
A27: DECOMPOSIÇÃO DO PREÇO MÉDIO PROLOG (por pedido)
A28: Componente | C28: R$ médio/pedido | D28: % do total PROLOG
A29: Frete peso | C29: =AVERAGE(Pedidos!$K$2:$K$2224) -> 119.69681 | D29: =C29/$C$37 -> 0.68816585
A30: Ad valorem | C30: =AVERAGE(Pedidos!$L$2:$L$2224) -> 0.64184197 | D30: =C30/$C$37 -> 0.0036901045
A31: GRIS | C31: =AVERAGE(Pedidos!$M$2:$M$2224) -> 1.2836836 | D31: =C31/$C$37 -> 0.007380207
A32: TAS | C32: =AVERAGE(Pedidos!$N$2:$N$2224) -> 1 | D32: =C32/$C$37 -> 0.0057492416
A33: Pedágio | C33: =AVERAGE(Pedidos!$O$2:$O$2224) -> 4.8016194 | D33: =C33/$C$37 -> 0.02760567
A34: CTe (R$/kg) | C34: =AVERAGE(Pedidos!$P$2:$P$2224) -> 3.0164372 | D34: =C34/$C$37 -> 0.017342226
A35: Outra taxa (R$/kg) | C35: =AVERAGE(Pedidos!$Q$2:$Q$2224) -> 22.623279 | D35: =C35/$C$37 -> 0.1300667
A36: ICMS 12% (gross-up) | C36: =AVERAGE(Pedidos!$S$2:$S$2224)-AVERAGE(Pedidos!$R$2:$R$2224) -> 20.872318 | D36: =C36/$C$37 -> 0.12
A37: TOTAL PROLOG | C37: =SUM(C29:C36) -> 173.93599 | D37: =C37/$C$37 -> 1
A38: Custo médio atual (comparação) | C38: =C22 -> 121.41697
A40: SENSIBILIDADE — quanto cada premissa pesa (diferença do custo total PROLOG vs atual)
A41: Cenário | C41: Custo total PROLOG | D41: vs atual | E41: % pedidos PROLOG mais barata
A42: A) Tabela literal (taxas por kg + ICMS 12%) | C42: =SUM(Pedidos!$S$2:$S$2224) -> 386659.7 | D42: =C42/$C$21-1 -> 0.43255089 | E42: =SUMPRODUCT(--(Pedidos!$S$2:$S$2224<Pedidos!$J$2:$J$2224))/C20 -> 0.0067476383
A43: B) Sem ICMS gross-up | C43: =SUM(Pedidos!$R$2:$R$2224) -> 340260.53 | D43: =C43/$C$21-1 -> 0.26064479 | E43: =SUMPRODUCT(--(Pedidos!$R$2:$R$2224<Pedidos!$J$2:$J$2224))/C20 -> 0.048582996
A44: C) Sem as taxas por kg (CTe e outra taxa) + ICMS | C44: =(SUM(Pedidos!$R$2:$R$2224)-SUM(Pedidos!$P$2:$P$2224)-SUM(Pedidos!$Q$2:$Q$2224))/(1-$C$6) -> 321890.28 | D44: =C44/$C$21-1 -> 0.19258409 | E44: =SUMPRODUCT(--((Pedidos!$R$2:$R$2224-Pedidos!$P$2:$P$2224-Pedidos!$Q$2:$Q$2224)/(1-$C$6)<Pedidos!$J$2:$J$2224))/C20 -> 0.093567251
A45: D) Sem taxas por kg e sem ICMS | C45: =SUM(Pedidos!$R$2:$R$2224)-SUM(Pedidos!$P$2:$P$2224)-SUM(Pedidos!$Q$2:$Q$2224) -> 283263.44 | D45: =C45/$C$21-1 -> 0.049474 | E45: =SUMPRODUCT(--((Pedidos!$R$2:$R$2224-Pedidos!$P$2:$P$2224-Pedidos!$Q$2:$Q$2224)<Pedidos!$J$2:$J$2224))/C20 -> 0.28205128
A46: E) Somente frete peso | C46: =SUM(Pedidos!$K$2:$K$2224) -> 266086 | D46: =C46/$C$21-1 -> -0.014167393 | E46: =SUMPRODUCT(--(Pedidos!$K$2:$K$2224<Pedidos!$J$2:$J$2224))/C20 -> 0.5465587

Sheet Top 20 Cidades
A1: Top 20 cidades do RJ (por nº de pedidos) — custo atual x PROLOG FILIAL SP simulado
A3: # | B3: Cidade | C3: Pedidos | D3: % dos pedidos RJ | E3: Peso médio (kg) | F3: NF média (R$) | G3: Custo médio atual (R$) | H3: PROLOG médio (R$) | I3: Diferença média (R$) | J3: PROLOG vs atual (%) | K3: Frete/NF atual | L3: Frete/NF PROLOG | M3: % pedidos PROLOG mais barata | N3: PROLOG só frete peso (R$) | O3: Frete peso vs atual (%) | P3: Desconto necessário p/ empatar | Q3: Prazo PROLOG (du) | R3: Avaliação
A4: 1 | B4: Rio de Janeiro | C4: =COUNTIFS(Pedidos!$E$2:$E$2224,$B4) -> 1030 | D4: =C4/Resumo!$C$20 -> 0.46333783 | E4: =AVERAGEIFS(Pedidos!$G$2:$G$2224,Pedidos!$E$2:$E$2224,$B4) -> 47.579631 | F4: =AVERAGEIFS(Pedidos!$H$2:$H$2224,Pedidos!$E$2:$E$2224,$B4) -> 617.43493 | G4: =AVERAGEIFS(Pedidos!$J$2:$J$2224,Pedidos!$E$2:$E$2224,$B4) -> 106.83918 | H4: =AVERAGEIFS(Pedidos!$S$2:$S$2224,Pedidos!$E$2:$E$2224,$B4) -> 156.29301 | I4: =H4-G4 -> 49.453828 | J4: =H4/G4-1 -> 0.46288099 | K4: =SUMIFS(Pedidos!$J$2:$J$2224,Pedidos!$E$2:$E$2224,$B4)/SUMIFS(Pedidos!$H$2:$H$2224,Pedidos!$E$2:$E$2224,$B4) -> 0.17303716 | L4: =SUMIFS(Pedidos!$S$2:$S$2224,Pedidos!$E$2:$E$2224,$B4)/SUMIFS(Pedidos!$H$2:$H$2224,Pedidos!$E$2:$E$2224,$B4) -> 0.25313277 | M4: =COUNTIFS(Pedidos!$E$2:$E$2224,$B4,Pedidos!$V$2:$V$2224,"SIM")/C4 -> 0 | N4: =AVERAGEIFS(Pedidos!$K$2:$K$2224,Pedidos!$E$2:$E$2224,$B4) -> 105.42938 | O4: =N4/G4-1 -> -0.013195588 | P4: =MAX(0,1-G4/H4) -> 0.31641739 | Q4: =AVERAGEIFS(Pedidos!$W$2:$W$2224,Pedidos!$E$2:$E$2224,$B4) -> 5 | R4: =IF(J4<=0,"Muito bem",IF(J4<=0.32,"Melhor posição relativa",IF(J4<=0.45,"Intermediária","Precisa melhorar"))) -> Precisa melhorar
A5: 2 | B5: São Gonçalo | C5: =COUNTIFS(Pedidos!$E$2:$E$2224,$B5) -> 135 | D5: =C5/Resumo!$C$20 -> 0.060728745 | E5: =AVERAGEIFS(Pedidos!$G$2:$G$2224,Pedidos!$E$2:$E$2224,$B5) -> 50.268593 | F5: =AVERAGEIFS(Pedidos!$H$2:$H$2224,Pedidos!$E$2:$E$2224,$B5) -> 636.66911 | G5: =AVERAGEIFS(Pedidos!$J$2:$J$2224,Pedidos!$E$2:$E$2224,$B5) -> 124.5983 | H5: =AVERAGEIFS(Pedidos!$S$2:$S$2224,Pedidos!$E$2:$E$2224,$B5) -> 180.34465 | I5: =H5-G5 -> 55.746352 | J5: =H5/G5-1 -> 0.44740862 | K5: =SUMIFS(Pedidos!$J$2:$J$2224,Pedidos!$E$2:$E$2224,$B5)/SUMIFS(Pedidos!$H$2:$H$2224,Pedidos!$E$2:$E$2224,$B5) -> 0.19570338 | L5: =SUMIFS(Pedidos!$S$2:$S$2224,Pedidos!$E$2:$E$2224,$B5)/SUMIFS(Pedidos!$H$2:$H$2224,Pedidos!$E$2:$E$2224,$B5) -> 0.28326276 | M5: =COUNTIFS(Pedidos!$E$2:$E$2224,$B5,Pedidos!$V$2:$V$2224,"SIM")/C5 -> 0 | N5: =AVERAGEIFS(Pedidos!$K$2:$K$2224,Pedidos!$E$2:$E$2224,$B5) -> 125.20548 | O5: =N5/G5-1 -> 0.004873142 | P5: =MAX(0,1-G5/H5) -> 0.3091101 | Q5: =AVERAGEIFS(Pedidos!$W$2:$W$2224,Pedidos!$E$2:$E$2224,$B5) -> 7 | R5: =IF(J5<=0,"Muito bem",IF(J5<=0.32,"Melhor posição relativa",IF(J5<=0.45,"Intermediária","Precisa melhorar"))) -> Intermediária
A6: 3 | B6: Duque de Caxias | C6: =COUNTIFS(Pedidos!$E$2:$E$2224,$B6) -> 106 | D6: =C6/Resumo!$C$20 -> 0.047683311 | E6: =AVERAGEIFS(Pedidos!$G$2:$G$2224,Pedidos!$E$2:$E$2224,$B6) -> 52.422453 | F6: =AVERAGEIFS(Pedidos!$H$2:$H$2224,Pedidos!$E$2:$E$2224,$B6) -> 663.55302 | G6: =AVERAGEIFS(Pedidos!$J$2:$J$2224,Pedidos!$E$2:$E$2224,$B6) -> 128.07689 | H6: =AVERAGEIFS(Pedidos!$S$2:$S$2224,Pedidos!$E$2:$E$2224,$B6) -> 166.37385 | I6: =H6-G6 -> 38.296959 | J6: =H6/G6-1 -> 0.29901538 | K6: =SUMIFS(Pedidos!$J$2:$J$2224,Pedidos!$E$2:$E$2224,$B6)/SUMIFS(Pedidos!$H$2:$H$2224,Pedidos!$E$2:$E$2224,$B6) -> 0.19301681 | L6: =SUMIFS(Pedidos!$S$2:$S$2224,Pedidos!$E$2:$E$2224,$B6)/SUMIFS(Pedidos!$H$2:$H$2224,Pedidos!$E$2:$E$2224,$B6) -> 0.2507318 | M6: =COUNTIFS(Pedidos!$E$2:$E$2224,$B6,Pedidos!$V$2:$V$2224,"SIM")/C6 -> 0.056603774 | N6: =AVERAGEIFS(Pedidos!$K$2:$K$2224,Pedidos!$E$2:$E$2224,$B6) -> 111.60245 | O6: =N6/G6-1 -> -0.12862925 | P6: =MAX(0,1-G6/H6) -> 0.23018617 | Q6: =AVERAGEIFS(Pedidos!$W$2:$W$2224,Pedidos!$E$2:$E$2224,$B6) -> 5 | R6: =IF(J6<=0,"Muito bem",IF(J6<=0.32,"Melhor posição relativa",IF(J6<=0.45,"Intermediária","Precisa melhorar"))) -> Melhor posição relativa
A7: 4 | B7: Nova Iguaçu | C7: =COUNTIFS(Pedidos!$E$2:$E$2224,$B7) -> 95 | D7: =C7/Resumo!$C$20 -> 0.042735043 | E7: =AVERAGEIFS(Pedidos!$G$2:$G$2224,Pedidos!$E$2:$E$2224,$B7) -> 55.083474 | F7: =AVERAGEIFS(Pedidos!$H$2:$H$2224,Pedidos!$E$2:$E$2224,$B7) -> 676.70926 | G7: =AVERAGEIFS(Pedidos!$J$2:$J$2224,Pedidos!$E$2:$E$2224,$B7) -> 130.55305 | H7: =AVERAGEIFS(Pedidos!$S$2:$S$2224,Pedidos!$E$2:$E$2224,$B7) -> 172.3095 | I7: =H7-G7 -> 41.756451 | J7: =H7/G7-1 -> 0.31984278 | K7: =SUMIFS(Pedidos!$J$2:$J$2224,Pedidos!$E$2:$E$2224,$B7)/SUMIFS(Pedidos!$H$2:$H$2224,Pedidos!$E$2:$E$2224,$B7) -> 0.1929234 | L7: =SUMIFS(Pedidos!$S$2:$S$2224,Pedidos!$E$2:$E$2224,$B7)/SUMIFS(Pedidos!$H$2:$H$2224,Pedidos!$E$2:$E$2224,$B7) -> 0.25462856 | M7: =COUNTIFS(Pedidos!$E$2:$E$2224,$B7,Pedidos!$V$2:$V$2224,"SIM")/C7 -> 0.021052632 | N7: =AVERAGEIFS(Pedidos!$K$2:$K$2224,Pedidos!$E$2:$E$2224,$B7) -> 115.36284 | O7: =N7/G7-1 -> -0.11635278 | P7: =MAX(0,1-G7/H7) -> 0.242334 | Q7: =AVERAGEIFS(Pedidos!$W$2:$W$2224,Pedidos!$E$2:$E$2224,$B7) -> 5 | R7: =IF(J7<=0,"Muito bem",IF(J7<=0.32,"Melhor posição relativa",IF(J7<=0.45,"Intermediária","Precisa melhorar"))) -> Melhor posição relativa
A8: 5 | B8: Niterói | C8: =COUNTIFS(Pedidos!$E$2:$E$2224,$B8) -> 68 | D8: =C8/Resumo!$C$20 -> 0.030589294 | E8: =AVERAGEIFS(Pedidos!$G$2:$G$2224,Pedidos!$E$2:$E$2224,$B8) -> 47.945882 | F8: =AVERAGEIFS(Pedidos!$H$2:$H$2224,Pedidos!$E$2:$E$2224,$B8) -> 603.64809 | G8: =AVERAGEIFS(Pedidos!$J$2:$J$2224,Pedidos!$E$2:$E$2224,$B8) -> 122.04441 | H8: =AVERAGEIFS(Pedidos!$S$2:$S$2224,Pedidos!$E$2:$E$2224,$B8) -> 175.73137 | I8: =H8-G8 -> 53.686962 | J8: =H8/G8-1 -> 0.43989693 | K8: =SUMIFS(Pedidos!$J$2:$J$2224,Pedidos!$E$2:$E$2224,$B8)/SUMIFS(Pedidos!$H$2:$H$2224,Pedidos!$E$2:$E$2224,$B8) -> 0.20217808 | L8: =SUMIFS(Pedidos!$S$2:$S$2224,Pedidos!$E$2:$E$2224,$B8)/SUMIFS(Pedidos!$H$2:$H$2224,Pedidos!$E$2:$E$2224,$B8) -> 0.2911156 | M8: =COUNTIFS(Pedidos!$E$2:$E$2224,$B8,Pedidos!$V$2:$V$2224,"SIM")/C8 -> 0 | N8: =AVERAGEIFS(Pedidos!$K$2:$K$2224,Pedidos!$E$2:$E$2224,$B8) -> 122.54029 | O8: =N8/G8-1 -> 0.0040631303 | P8: =MAX(0,1-G8/H8) -> 0.30550585 | Q8: =AVERAGEIFS(Pedidos!$W$2:$W$2224,Pedidos!$E$2:$E$2224,$B8) -> 7 | R8: =IF(J8<=0,"Muito bem",IF(J8<=0.32,"Melhor posição relativa",IF(J8<=0.45,"Intermediária","Precisa melhorar"))) -> Intermediária
A9: 6 | B9: Campos dos Goytacazes | C9: =COUNTIFS(Pedidos!$E$2:$E$2224,$B9) -> 53 | D9: =C9/Resumo!$C$20 -> 0.023841655 | E9: =AVERAGEIFS(Pedidos!$G$2:$G$2224,Pedidos!$E$2:$E$2224,$B9) -> 49.475283 | F9: =AVERAGEIFS(Pedidos!$H$2:$H$2224,Pedidos!$E$2:$E$2224,$B9) -> 649.88434 | G9: =AVERAGEIFS(Pedidos!$J$2:$J$2224,Pedidos!$E$2:$E$2224,$B9) -> 136.86038 | H9: =AVERAGEIFS(Pedidos!$S$2:$S$2224,Pedidos!$E$2:$E$2224,$B9) -> 218.07381 | I9: =H9-G9 -> 81.213435 | J9: =H9/G9-1 -> 0.59340356 | K9: =SUMIFS(Pedidos!$J$2:$J$2224,Pedidos!$E$2:$E$2224,$B9)/SUMIFS(Pedidos!$H$2:$H$2224,Pedidos!$E$2:$E$2224,$B9) -> 0.2105919 | L9: =SUMIFS(Pedidos!$S$2:$S$2224,Pedidos!$E$2:$E$2224,$B9)/SUMIFS(Pedidos!$H$2:$H$2224,Pedidos!$E$2:$E$2224,$B9) -> 0.33555788 | M9: =COUNTIFS(Pedidos!$E$2:$E$2224,$B9,Pedidos!$V$2:$V$2224,"SIM")/C9 -> 0 | N9: =AVERAGEIFS(Pedidos!$K$2:$K$2224,Pedidos!$E$2:$E$2224,$B9) -> 158.72151 | O9: =N9/G9-1 -> 0.1597331 | P9: =MAX(0,1-G9/H9) -> 0.3724126 | Q9: =AVERAGEIFS(Pedidos!$W$2:$W$2224,Pedidos!$E$2:$E$2224,$B9) -> 11 | R9: =IF(J9<=0,"Muito bem",IF(J9<=0.32,"Melhor posição relativa",IF(J9<=0.45,"Intermediária","Precisa melhorar"))) -> Precisa melhorar
A10: 7 | B10: Belford Roxo | C10: =COUNTIFS(Pedidos!$E$2:$E$2224,$B10) -> 49 | D10: =C10/Resumo!$C$20 -> 0.022042285 | E10: =AVERAGEIFS(Pedidos!$G$2:$G$2224,Pedidos!$E$2:$E$2224,$B10) -> 54.08 | F10: =AVERAGEIFS(Pedidos!$H$2:$H$2224,Pedidos!$E$2:$E$2224,$B10) -> 687.52816 | G10: =AVERAGEIFS(Pedidos!$J$2:$J$2224,Pedidos!$E$2:$E$2224,$B10) -> 128.08959 | H10: =AVERAGEIFS(Pedidos!$S$2:$S$2224,Pedidos!$E$2:$E$2224,$B10) -> 166.98858 | I10: =H10-G10 -> 38.898989 | J10: =H10/G10-1 -> 0.30368579 | K10: =SUMIFS(Pedidos!$J$2:$J$2224,Pedidos!$E$2:$E$2224,$B10)/SUMIFS(Pedidos!$H$2:$H$2224,Pedidos!$E$2:$E$2224,$B10) -> 0.1863045 | L10: =SUMIFS(Pedidos!$S$2:$S$2224,Pedidos!$E$2:$E$2224,$B10)/SUMIFS(Pedidos!$H$2:$H$2224,Pedidos!$E$2:$E$2224,$B10) -> 0.24288253 | M10: =COUNTIFS(Pedidos!$E$2:$E$2224,$B10,Pedidos!$V$2:$V$2224,"SIM")/C10 -> 0.081632653 | N10: =AVERAGEIFS(Pedidos!$K$2:$K$2224,Pedidos!$E$2:$E$2224,$B10) -> 111.30122 | O10: =N10/G10-1 -> -0.13106738 | P10: =MAX(0,1-G10/H10) -> 0.23294401 | Q10: =AVERAGEIFS(Pedidos!$W$2:$W$2224,Pedidos!$E$2:$E$2224,$B10) -> 5 | R10: =IF(J10<=0,"Muito bem",IF(J10<=0.32,"Melhor posição relativa",IF(J10<=0.45,"Intermediária","Precisa melhorar"))) -> Melhor posição relativa
A11: 8 | B11: Macaé | C11: =COUNTIFS(Pedidos!$E$2:$E$2224,$B11) -> 45 | D11: =C11/Resumo!$C$20 -> 0.020242915 | E11: =AVERAGEIFS(Pedidos!$G$2:$G$2224,Pedidos!$E$2:$E$2224,$B11) -> 60.060222 | F11: =AVERAGEIFS(Pedidos!$H$2:$H$2224,Pedidos!$E$2:$E$2224,$B11) -> 746.16467 | G11: =AVERAGEIFS(Pedidos!$J$2:$J$2224,Pedidos!$E$2:$E$2224,$B11) -> 150.53156 | H11: =AVERAGEIFS(Pedidos!$S$2:$S$2224,Pedidos!$E$2:$E$2224,$B11) -> 241.39782 | I11: =H11-G11 -> 90.86626 | J11: =H11/G11-1 -> 0.60363596 | K11: =SUMIFS(Pedidos!$J$2:$J$2224,Pedidos!$E$2:$E$2224,$B11)/SUMIFS(Pedidos!$H$2:$H$2224,Pedidos!$E$2:$E$2224,$B11) -> 0.2017404 | L11: =SUMIFS(Pedidos!$S$2:$S$2224,Pedidos!$E$2:$E$2224,$B11)/SUMIFS(Pedidos!$H$2:$H$2224,Pedidos!$E$2:$E$2224,$B11) -> 0.32351815 | M11: =COUNTIFS(Pedidos!$E$2:$E$2224,$B11,Pedidos!$V$2:$V$2224,"SIM")/C11 -> 0 | N11: =AVERAGEIFS(Pedidos!$K$2:$K$2224,Pedidos!$E$2:$E$2224,$B11) -> 173.27622 | O11: =N11/G11-1 -> 0.15109567 | P11: =MAX(0,1-G11/H11) -> 0.37641708 | Q11: =AVERAGEIFS(Pedidos!$W$2:$W$2224,Pedidos!$E$2:$E$2224,$B11) -> 11 | R11: =IF(J11<=0,"Muito bem",IF(J11<=0.32,"Melhor posição relativa",IF(J11<=0.45,"Intermediária","Precisa melhorar"))) -> Precisa melhorar
A12: 9 | B12: São João de Meriti | C12: =COUNTIFS(Pedidos!$E$2:$E$2224,$B12) -> 37 | D12: =C12/Resumo!$C$20 -> 0.016644175 | E12: =AVERAGEIFS(Pedidos!$G$2:$G$2224,Pedidos!$E$2:$E$2224,$B12) -> 55.930541 | F12: =AVERAGEIFS(Pedidos!$H$2:$H$2224,Pedidos!$E$2:$E$2224,$B12) -> 698.24405 | G12: =AVERAGEIFS(Pedidos!$J$2:$J$2224,Pedidos!$E$2:$E$2224,$B12) -> 131.78351 | H12: =AVERAGEIFS(Pedidos!$S$2:$S$2224,Pedidos!$E$2:$E$2224,$B12) -> 175.0438 | I12: =H12-G12 -> 43.260283 | J12: =H12/G12-1 -> 0.32826779 | K12: =SUMIFS(Pedidos!$J$2:$J$2224,Pedidos!$E$2:$E$2224,$B12)/SUMIFS(Pedidos!$H$2:$H$2224,Pedidos!$E$2:$E$2224,$B12) -> 0.1887356 | L12: =SUMIFS(Pedidos!$S$2:$S$2224,Pedidos!$E$2:$E$2224,$B12)/SUMIFS(Pedidos!$H$2:$H$2224,Pedidos!$E$2:$E$2224,$B12) -> 0.25069142 | M12: =COUNTIFS(Pedidos!$E$2:$E$2224,$B12,Pedidos!$V$2:$V$2224,"SIM")/C12 -> 0.027027027 | N12: =AVERAGEIFS(Pedidos!$K$2:$K$2224,Pedidos!$E$2:$E$2224,$B12) -> 117.27324 | O12: =N12/G12-1 -> -0.11010687 | P12: =MAX(0,1-G12/H12) -> 0.24713976 | Q12: =AVERAGEIFS(Pedidos!$W$2:$W$2224,Pedidos!$E$2:$E$2224,$B12) -> 5 | R12: =IF(J12<=0,"Muito bem",IF(J12<=0.32,"Melhor posição relativa",IF(J12<=0.45,"Intermediária","Precisa melhorar"))) -> Intermediária
A13: 10 | B13: Volta Redonda | C13: =COUNTIFS(Pedidos!$E$2:$E$2224,$B13) -> 37 | D13: =C13/Resumo!$C$20 -> 0.016644175 | E13: =AVERAGEIFS(Pedidos!$G$2:$G$2224,Pedidos!$E$2:$E$2224,$B13) -> 50.886757 | F13: =AVERAGEIFS(Pedidos!$H$2:$H$2224,Pedidos!$E$2:$E$2224,$B13) -> 652.92108 | G13: =AVERAGEIFS(Pedidos!$J$2:$J$2224,Pedidos!$E$2:$E$2224,$B13) -> 139.23459 | H13: =AVERAGEIFS(Pedidos!$S$2:$S$2224,Pedidos!$E$2:$E$2224,$B13) -> 198.53824 | I13: =H13-G13 -> 59.303643 | J13: =H13/G13-1 -> 0.42592606 | K13: =SUMIFS(Pedidos!$J$2:$J$2224,Pedidos!$E$2:$E$2224,$B13)/SUMIFS(Pedidos!$H$2:$H$2224,Pedidos!$E$2:$E$2224,$B13) -> 0.21324873 | L13: =SUMIFS(Pedidos!$S$2:$S$2224,Pedidos!$E$2:$E$2224,$B13)/SUMIFS(Pedidos!$H$2:$H$2224,Pedidos!$E$2:$E$2224,$B13) -> 0.30407693 | M13: =COUNTIFS(Pedidos!$E$2:$E$2224,$B13,Pedidos!$V$2:$V$2224,"SIM")/C13 -> 0 | N13: =AVERAGEIFS(Pedidos!$K$2:$K$2224,Pedidos!$E$2:$E$2224,$B13) -> 140.82243 | O13: =N13/G13-1 -> 0.011404047 | P13: =MAX(0,1-G13/H13) -> 0.29870137 | Q13: =AVERAGEIFS(Pedidos!$W$2:$W$2224,Pedidos!$E$2:$E$2224,$B13) -> 10 | R13: =IF(J13<=0,"Muito bem",IF(J13<=0.32,"Melhor posição relativa",IF(J13<=0.45,"Intermediária","Precisa melhorar"))) -> Intermediária
A14: 11 | B14: Angra dos Reis | C14: =COUNTIFS(Pedidos!$E$2:$E$2224,$B14) -> 35 | D14: =C14/Resumo!$C$20 -> 0.015744489 | E14: =AVERAGEIFS(Pedidos!$G$2:$G$2224,Pedidos!$E$2:$E$2224,$B14) -> 44.394286 | F14: =AVERAGEIFS(Pedidos!$H$2:$H$2224,Pedidos!$E$2:$E$2224,$B14) -> 596.41771 | G14: =AVERAGEIFS(Pedidos!$J$2:$J$2224,Pedidos!$E$2:$E$2224,$B14) -> 129.24743 | H14: =AVERAGEIFS(Pedidos!$S$2:$S$2224,Pedidos!$E$2:$E$2224,$B14) -> 179.38262 | I14: =H14-G14 -> 50.135188 | J14: =H14/G14-1 -> 0.38790086 | K14: =SUMIFS(Pedidos!$J$2:$J$2224,Pedidos!$E$2:$E$2224,$B14)/SUMIFS(Pedidos!$H$2:$H$2224,Pedidos!$E$2:$E$2224,$B14) -> 0.21670622 | L14: =SUMIFS(Pedidos!$S$2:$S$2224,Pedidos!$E$2:$E$2224,$B14)/SUMIFS(Pedidos!$H$2:$H$2224,Pedidos!$E$2:$E$2224,$B14) -> 0.30076675 | M14: =COUNTIFS(Pedidos!$E$2:$E$2224,$B14,Pedidos!$V$2:$V$2224,"SIM")/C14 -> 0 | N14: =AVERAGEIFS(Pedidos!$K$2:$K$2224,Pedidos!$E$2:$E$2224,$B14) -> 127.71943 | O14: =N14/G14-1 -> -0.011822285 | P14: =MAX(0,1-G14/H14) -> 0.27948744 | Q14: =AVERAGEIFS(Pedidos!$W$2:$W$2224,Pedidos!$E$2:$E$2224,$B14) -> 10 | R14: =IF(J14<=0,"Muito bem",IF(J14<=0.32,"Melhor posição relativa",IF(J14<=0.45,"Intermediária","Precisa melhorar"))) -> Intermediária
A15: 12 | B15: Petrópolis | C15: =COUNTIFS(Pedidos!$E$2:$E$2224,$B15) -> 32 | D15: =C15/Resumo!$C$20 -> 0.014394962 | E15: =AVERAGEIFS(Pedidos!$G$2:$G$2224,Pedidos!$E$2:$E$2224,$B15) -> 58.889375 | F15: =AVERAGEIFS(Pedidos!$H$2:$H$2224,Pedidos!$E$2:$E$2224,$B15) -> 743.8225 | G15: =AVERAGEIFS(Pedidos!$J$2:$J$2224,Pedidos!$E$2:$E$2224,$B15) -> 149.76844 | H15: =AVERAGEIFS(Pedidos!$S$2:$S$2224,Pedidos!$E$2:$E$2224,$B15) -> 216.62811 | I15: =H15-G15 -> 66.859677 | J15: =H15/G15-1 -> 0.44642034 | K15: =SUMIFS(Pedidos!$J$2:$J$2224,Pedidos!$E$2:$E$2224,$B15)/SUMIFS(Pedidos!$H$2:$H$2224,Pedidos!$E$2:$E$2224,$B15) -> 0.2013497 | L15: =SUMIFS(Pedidos!$S$2:$S$2224,Pedidos!$E$2:$E$2224,$B15)/SUMIFS(Pedidos!$H$2:$H$2224,Pedidos!$E$2:$E$2224,$B15) -> 0.2912363 | M15: =COUNTIFS(Pedidos!$E$2:$E$2224,$B15,Pedidos!$V$2:$V$2224,"SIM")/C15 -> 0 | N15: =AVERAGEIFS(Pedidos!$K$2:$K$2224,Pedidos!$E$2:$E$2224,$B15) -> 152.08937 | O15: =N15/G15-1 -> 0.01549684 | P15: =MAX(0,1-G15/H15) -> 0.30863804 | Q15: =AVERAGEIFS(Pedidos!$W$2:$W$2224,Pedidos!$E$2:$E$2224,$B15) -> 8 | R15: =IF(J15<=0,"Muito bem",IF(J15<=0.32,"Melhor posição relativa",IF(J15<=0.45,"Intermediária","Precisa melhorar"))) -> Intermediária
... A23: 20 | B23: Rio das Ostras | C23: =COUNTIFS(Pedidos!$E$2:$E$2224,$B23) -> 18 | D23: =C23/Resumo!$C$20 -> 0.008097166 | E23: =AVERAGEIFS(Pedidos!$G$2:$G$2224,Pedidos!$E$2:$E$2224,$B23) -> 47.438889 | F23: =AVERAGEIFS(Pedidos!$H$2:$H$2224,Pedidos!$E$2:$E$2224,$B23) -> 604.15056 | G23: =AVERAGEIFS(Pedidos!$J$2:$J$2224,Pedidos!$E$2:$E$2224,$B23) -> 132.50556 | H23: =AVERAGEIFS(Pedidos!$S$2:$S$2224,Pedidos!$E$2:$E$2224,$B23) -> 190.52996 | I23: =H23-G23 -> 58.024407 | J23: =H23/G23-1 -> 0.43790169 | K23: =SUMIFS(Pedidos!$J$2:$J$2224,Pedidos!$E$2:$E$2224,$B23)/SUMIFS(Pedidos!$H$2:$H$2224,Pedidos!$E$2:$E$2224,$B23) -> 0.21932539 | L23: =SUMIFS(Pedidos!$S$2:$S$2224,Pedidos!$E$2:$E$2224,$B23)/SUMIFS(Pedidos!$H$2:$H$2224,Pedidos!$E$2:$E$2224,$B23) -> 0.31536835 | M23: =COUNTIFS(Pedidos!$E$2:$E$2224,$B23,Pedidos!$V$2:$V$2224,"SIM")/C23 -> 0 | N23: =AVERAGEIFS(Pedidos!$K$2:$K$2224,Pedidos!$E$2:$E$2224,$B23) -> 136.04389 | O23: =N23/G23-1 -> 0.026703283 | P23: =MAX(0,1-G23/H23) -> 0.30454216 | Q23: =AVERAGEIFS(Pedidos!$W$2:$W$2224,Pedidos!$E$2:$E$2224,$B23) -> 10 | R23: =IF(J23<=0,"Muito bem",IF(J23<=0.32,"Melhor posição relativa",IF(J23<=0.45,"Intermediária","Precisa melhorar"))) -> Intermediária
B24: TOTAL TOP 20 | C24: =SUM(C4:C23) -> 1912 | D24: =C24/Resumo!$C$20 -> 0.86009897 | E24: =AVERAGEIFS(Pedidos!$G$2:$G$2224,Pedidos!$X$2:$X$2224,"SIM") -> 49.45444 | F24: =AVERAGEIFS(Pedidos!$H$2:$H$2224,Pedidos!$X$2:$X$2224,"SIM") -> 636.04536 | G24: =AVERAGEIFS(Pedidos!$J$2:$J$2224,Pedidos!$X$2:$X$2224,"SIM") -> 118.41855 | H24: =AVERAGEIFS(Pedidos!$S$2:$S$2224,Pedidos!$X$2:$X$2224,"SIM") -> 169.56635 | I24: =H24-G24 -> 51.147804 | J24: =H24/G24-1 -> 0.43192393 | K24: =SUMIFS(Pedidos!$J$2:$J$2224,Pedidos!$X$2:$X$2224,"SIM")/SUMIFS(Pedidos!$H$2:$H$2224,Pedidos!$X$2:$X$2224,"SIM") -> 0.1861794 | L24: =SUMIFS(Pedidos!$S$2:$S$2224,Pedidos!$X$2:$X$2224,"SIM")/SUMIFS(Pedidos!$H$2:$H$2224,Pedidos!$X$2:$X$2224,"SIM") -> 0.26659474 | M24: =COUNTIFS(Pedidos!$X$2:$X$2224,"SIM",Pedidos!$V$2:$V$2224,"SIM")/C24 -> 0.0073221757 | N24: =AVERAGEIFS(Pedidos!$K$2:$K$2224,Pedidos!$X$2:$X$2224,"SIM") -> 116.08623 | O24: =N24/G24-1 -> -0.019695494 | P24: =MAX(0,1-G24/H24) -> 0.30163888 | Q24: =AVERAGEIFS(Pedidos!$W$2:$W$2224,Pedidos!$X$2:$X$2224,"SIM") -> 6.0690377
A26: Avaliação (coluna R): "Muito bem" = PROLOG mais barata que o atual; "Melhor posição relativa" = até +32%; "Intermediária" = +32% a +45%; "Precisa melhorar" = acima de +45%. Faixas definidas pela distribuição observada (média RJ ≈ +43%).
A27: "PROLOG só frete peso" = valor da faixa de peso da tabela, sem ad valorem, GRIS, TAS, pedágio, taxas por kg e ICMS — mostra onde a base da tabela é competitiva e o peso das taxas adicionais.

Sheet Faixa x Transportadora
A1: Top 20 cidades — por faixa de peso: transportadoras atuais x PROLOG simulado nos MESMOS pedidos
A3: Transportadora atual: TODAS
A4: Faixa (kg) | B4: Pedidos | C4: Peso médio | D4: Custo médio atual (R$) | E4: PROLOG médio (R$) | F4: PROLOG vs atual (%) | G4: Frete/NF atual | H4: Frete/NF PROLOG | I4: % pedidos PROLOG mais barata | J4: PROLOG só frete peso (R$) | K4: Desconto necessário p/ empatar
A5: 0-20 | B5: =COUNTIFS(Pedidos!$X$2:$X$2224,"SIM",Pedidos!$F$2:$F$2224,$A5) -> 96 | C5: =IFERROR(AVERAGEIFS(Pedidos!$G$2:$G$2224,Pedidos!$X$2:$X$2224,"SIM",Pedidos!$F$2:$F$2224,$A5),"") -> 17.503438 | D5: =IFERROR(AVERAGEIFS(Pedidos!$J$2:$J$2224,Pedidos!$X$2:$X$2224,"SIM",Pedidos!$F$2:$F$2224,$A5),"") -> 69.142083 | E5: =IFERROR(AVERAGEIFS(Pedidos!$S$2:$S$2224,Pedidos!$X$2:$X$2224,"SIM",Pedidos!$F$2:$F$2224,$A5),"") -> 76.075249 | F5: =IFERROR(E5/D5-1,"") -> 0.10027417 | G5: =IFERROR(SUMIFS(Pedidos!$J$2:$J$2224,Pedidos!$X$2:$X$2224,"SIM",Pedidos!$F$2:$F$2224,$A5)/SUMIFS(Pedidos!$H$2:$H$2224,Pedidos!$X$2:$X$2224,"SIM",Pedidos!$F$2:$F$2224,$A5),"") -> 0.22335232 | H5: =IFERROR(SUMIFS(Pedidos!$S$2:$S$2224,Pedidos!$X$2:$X$2224,"SIM",Pedidos!$F$2:$F$2224,$A5)/SUMIFS(Pedidos!$H$2:$H$2224,Pedidos!$X$2:$X$2224,"SIM",Pedidos!$F$2:$F$2224,$A5),"") -> 0.24574879 | I5: =IFERROR(COUNTIFS(Pedidos!$X$2:$X$2224,"SIM",Pedidos!$F$2:$F$2224,$A5,Pedidos!$V$2:$V$2224,"SIM")/B5,"") -> 0.14583333 | J5: =IFERROR(AVERAGEIFS(Pedidos!$K$2:$K$2224,Pedidos!$X$2:$X$2224,"SIM",Pedidos!$F$2:$F$2224,$A5),"") -> 51.369375 | K5: =IFERROR(MAX(0,1-D5/E5),"") -> 0.091135624
A6: 20-35 | B6: =COUNTIFS(Pedidos!$X$2:$X$2224,"SIM",Pedidos!$F$2:$F$2224,$A6) -> 431 | C6: =IFERROR(AVERAGEIFS(Pedidos!$G$2:$G$2224,Pedidos!$X$2:$X$2224,"SIM",Pedidos!$F$2:$F$2224,$A6),"") -> 28.263202 | D6: =IFERROR(AVERAGEIFS(Pedidos!$J$2:$J$2224,Pedidos!$X$2:$X$2224,"SIM",Pedidos!$F$2:$F$2224,$A6),"") -> 90.953759 | E6: =IFERROR(AVERAGEIFS(Pedidos!$S$2:$S$2224,Pedidos!$X$2:$X$2224,"SIM",Pedidos!$F$2:$F$2224,$A6),"") -> 127.44457 | F6: =IFERROR(E6/D6-1,"") -> 0.40120182 | G6: =IFERROR(SUMIFS(Pedidos!$J$2:$J$2224,Pedidos!$X$2:$X$2224,"SIM",Pedidos!$F$2:$F$2224,$A6)/SUMIFS(Pedidos!$H$2:$H$2224,Pedidos!$X$2:$X$2224,"SIM",Pedidos!$F$2:$F$2224,$A6),"") -> 0.21057819 | H6: =IFERROR(SUMIFS(Pedidos!$S$2:$S$2224,Pedidos!$X$2:$X$2224,"SIM",Pedidos!$F$2:$F$2224,$A6)/SUMIFS(Pedidos!$H$2:$H$2224,Pedidos!$X$2:$X$2224,"SIM",Pedidos!$F$2:$F$2224,$A6),"") -> 0.29506255 | I6: =IFERROR(COUNTIFS(Pedidos!$X$2:$X$2224,"SIM",Pedidos!$F$2:$F$2224,$A6,Pedidos!$V$2:$V$2224,"SIM")/B6,"") -> 0 | J6: =IFERROR(AVERAGEIFS(Pedidos!$K$2:$K$2224,Pedidos!$X$2:$X$2224,"SIM",Pedidos!$F$2:$F$2224,$A6),"") -> 90.763039 | K6: =IFERROR(MAX(0,1-D6/E6),"") -> 0.28632694
A7: 35-40 | B7: =COUNTIFS(Pedidos!$X$2:$X$2224,"SIM",Pedidos!$F$2:$F$2224,$A7) -> 299 | C7: =IFERROR(AVERAGEIFS(Pedidos!$G$2:$G$2224,Pedidos!$X$2:$X$2224,"SIM",Pedidos!$F$2:$F$2224,$A7),"") -> 37.708027 | D7: =IFERROR(AVERAGEIFS(Pedidos!$J$2:$J$2224,Pedidos!$X$2:$X$2224,"SIM",Pedidos!$F$2:$F$2224,$A7),"") -> 103.90311 | E7: =IFERROR(AVERAGEIFS(Pedidos!$S$2:$S$2224,Pedidos!$X$2:$X$2224,"SIM",Pedidos!$F$2:$F$2224,$A7),"") -> 146.77369 | F7: =IFERROR(E7/D7-1,"") -> 0.41260147 | G7: =IFERROR(SUMIFS(Pedidos!$J$2:$J$2224,Pedidos!$X$2:$X$2224,"SIM",Pedidos!$F$2:$F$2224,$A7)/SUMIFS(Pedidos!$H$2:$H$2224,Pedidos!$X$2:$X$2224,"SIM",Pedidos!$F$2:$F$2224,$A7),"") -> 0.22301406 | H7: =IFERROR(SUMIFS(Pedidos!$S$2:$S$2224,Pedidos!$X$2:$X$2224,"SIM",Pedidos!$F$2:$F$2224,$A7)/SUMIFS(Pedidos!$H$2:$H$2224,Pedidos!$X$2:$X$2224,"SIM",Pedidos!$F$2:$F$2224,$A7),"") -> 0.31503 | I7: =IFERROR(COUNTIFS(Pedidos!$X$2:$X$2224,"SIM",Pedidos!$F$2:$F$2224,$A7,Pedidos!$V$2:$V$2224,"SIM")/B7,"") -> 0 | J7: =IFERROR(AVERAGEIFS(Pedidos!$K$2:$K$2224,Pedidos!$X$2:$X$2224,"SIM",Pedidos!$F$2:$F$2224,$A7),"") -> 102.8507 | K7: =IFERROR(MAX(0,1-D7/E7),"") -> 0.29208626
A8: 40-50 | B8: =COUNTIFS(Pedidos!$X$2:$X$2224,"SIM",Pedidos!$F$2:$F$2224,$A8) -> 305 | C8: =IFERROR(AVERAGEIFS(Pedidos!$G$2:$G$2224,Pedidos!$X$2:$X$2224,"SIM",Pedidos!$F$2:$F$2224,$A8),"") -> 45.845246 | D8: =IFERROR(AVERAGEIFS(Pedidos!$J$2:$J$2224,Pedidos!$X$2:$X$2224,"SIM",Pedidos!$F$2:$F$2224,$A8),"") -> 113.34272 | E8: =IFERROR(AVERAGEIFS(Pedidos!$S$2:$S$2224,Pedidos!$X$2:$X$2224,"SIM",Pedidos!$F$2:$F$2224,$A8),"") -> 153.47148 | F8: =IFERROR(E8/D8-1,"") -> 0.35404797 | G8: =IFERROR(SUMIFS(Pedidos!$J$2:$J$2224,Pedidos!$X$2:$X$2224,"SIM",Pedidos!$F$2:$F$2224,$A8)/SUMIFS(Pedidos!$H$2:$H$2224,Pedidos!$X$2:$X$2224,"SIM",Pedidos!$F$2:$F$2224,$A8),"") -> 0.1877047 | H8: =IFERROR(SUMIFS(Pedidos!$S$2:$S$2224,Pedidos!$X$2:$X$2224,"SIM",Pedidos!$F$2:$F$2224,$A8)/SUMIFS(Pedidos!$H$2:$H$2224,Pedidos!$X$2:$X$2224,"SIM",Pedidos!$F$2:$F$2224,$A8),"") -> 0.25416117 | I8: =IFERROR(COUNTIFS(Pedidos!$X$2:$X$2224,"SIM",Pedidos!$F$2:$F$2224,$A8,Pedidos!$V$2:$V$2224,"SIM")/B8,"") -> 0 | J8: =IFERROR(AVERAGEIFS(Pedidos!$K$2:$K$2224,Pedidos!$X$2:$X$2224,"SIM",Pedidos!$F$2:$F$2224,$A8),"") -> 104.18305 | K8: =IFERROR(MAX(0,1-D8/E8),"") -> 0.26147373
A9: 50-60 | B9: =COUNTIFS(Pedidos!$X$2:$X$2224,"SIM",Pedidos!$F$2:$F$2224,$A9) -> 361 | C9: =IFERROR(AVERAGEIFS(Pedidos!$G$2:$G$2224,Pedidos!$X$2:$X$2224,"SIM",Pedidos!$F$2:$F$2224,$A9),"") -> 53.752382 | D9: =IFERROR(AVERAGEIFS(Pedidos!$J$2:$J$2224,Pedidos!$X$2:$X$2224,"SIM",Pedidos!$F$2:$F$2224,$A9),"") -> 124.19161 | E9: =IFERROR(AVERAGEIFS(Pedidos!$S$2:$S$2224,Pedidos!$X$2:$X$2224,"SIM",Pedidos!$F$2:$F$2224,$A9),"") -> 176.44982 | F9: =IFERROR(E9/D9-1,"") -> 0.42078699 | G9: =IFERROR(SUMIFS(Pedidos!$J$2:$J$2224,Pedidos!$X$2:$X$2224,"SIM",Pedidos!$F$2:$F$2224,$A9)/SUMIFS(Pedidos!$H$2:$H$2224,Pedidos!$X$2:$X$2224,"SIM",Pedidos!$F$2:$F$2224,$A9),"") -> 0.17823196 | H9: =IFERROR(SUMIFS(Pedidos!$S$2:$S$2224,Pedidos!$X$2:$X$2224,"SIM",Pedidos!$F$2:$F$2224,$A9)/SUMIFS(Pedidos!$H$2:$H$2224,Pedidos!$X$2:$X$2224,"SIM",Pedidos!$F$2:$F$2224,$A9),"") -> 0.25322965 | I9: =IFERROR(COUNTIFS(Pedidos!$X$2:$X$2224,"SIM",Pedidos!$F$2:$F$2224,$A9,Pedidos!$V$2:$V$2224,"SIM")/B9,"") -> 0 | J9: =IFERROR(AVERAGEIFS(Pedidos!$K$2:$K$2224,Pedidos!$X$2:$X$2224,"SIM",Pedidos!$F$2:$F$2224,$A9),"") -> 119.98296 | K9: =IFERROR(MAX(0,1-D9/E9),"") -> 0.29616473
A10: 60-70 | B10: =COUNTIFS(Pedidos!$X$2:$X$2224,"SIM",Pedidos!$F$2:$F$2224,$A10) -> 228 | C10: =IFERROR(AVERAGEIFS(Pedidos!$G$2:$G$2224,Pedidos!$X$2:$X$2224,"SIM",Pedidos!$F$2:$F$2224,$A10),"") -> 66.008026 | D10: =IFERROR(AVERAGEIFS(Pedidos!$J$2:$J$2224,Pedidos!$X$2:$X$2224,"SIM",Pedidos!$F$2:$F$2224,$A10),"") -> 135.94289 | E10: =IFERROR(AVERAGEIFS(Pedidos!$S$2:$S$2224,Pedidos!$X$2:$X$2224,"SIM",Pedidos!$F$2:$F$2224,$A10),"") -> 206.19743 | F10: =IFERROR(E10/D10-1,"") -> 0.51679448 | G10: =IFERROR(SUMIFS(Pedidos!$J$2:$J$2224,Pedidos!$X$2:$X$2224,"SIM",Pedidos!$F$2:$F$2224,$A10)/SUMIFS(Pedidos!$H$2:$H$2224,Pedidos!$X$2:$X$2224,"SIM",Pedidos!$F$2:$F$2224,$A10),"") -> 0.17873894 | H10: =IFERROR(SUMIFS(Pedidos!$S$2:$S$2224,Pedidos!$X$2:$X$2224,"SIM",Pedidos!$F$2:$F$2224,$A10)/SUMIFS(Pedidos!$H$2:$H$2224,Pedidos!$X$2:$X$2224,"SIM",Pedidos!$F$2:$F$2224,$A10),"") -> 0.27111024 | I10: =IFERROR(COUNTIFS(Pedidos!$X$2:$X$2224,"SIM",Pedidos!$F$2:$F$2224,$A10,Pedidos!$V$2:$V$2224,"SIM")/B10,"") -> 0 | J10: =IFERROR(AVERAGEIFS(Pedidos!$K$2:$K$2224,Pedidos!$X$2:$X$2224,"SIM",Pedidos!$F$2:$F$2224,$A10),"") -> 139.83754 | K10: =IFERROR(MAX(0,1-D10/E10),"") -> 0.3407149
A11: 70-80 | B11: =COUNTIFS(Pedidos!$X$2:$X$2224,"SIM",Pedidos!$F$2:$F$2224,$A11) -> 24 | C11: =IFERROR(AVERAGEIFS(Pedidos!$G$2:$G$2224,Pedidos!$X$2:$X$2224,"SIM",Pedidos!$F$2:$F$2224,$A11),"") -> 74.3625 | D11: =IFERROR(AVERAGEIFS(Pedidos!$J$2:$J$2224,Pedidos!$X$2:$X$2224,"SIM",Pedidos!$F$2:$F$2224,$A11),"") -> 148.41333 | E11: =IFERROR(AVERAGEIFS(Pedidos!$S$2:$S$2224,Pedidos!$X$2:$X$2224,"SIM",Pedidos!$F$2:$F$2224,$A11),"") -> 211.16089 | F11: =IFERROR(E11/D11-1,"") -> 0.42278925 | G11: =IFERROR(SUMIFS(Pedidos!$J$2:$J$2224,Pedidos!$X$2:$X$2224,"SIM",Pedidos!$F$2:$F$2224,$A11)/SUMIFS(Pedidos!$H$2:$H$2224,Pedidos!$X$2:$X$2224,"SIM",Pedidos!$F$2:$F$2224,$A11),"") -> 0.15431244 | H11: =IFERROR(SUMIFS(Pedidos!$S$2:$S$2224,Pedidos!$X$2:$X$2224,"SIM",Pedidos!$F$2:$F$2224,$A11)/SUMIFS(Pedidos!$H$2:$H$2224,Pedidos!$X$2:$X$2224,"SIM",Pedidos!$F$2:$F$2224,$A11),"") -> 0.21955408 | I11: =IFERROR(COUNTIFS(Pedidos!$X$2:$X$2224,"SIM",Pedidos!$F$2:$F$2224,$A11,Pedidos!$V$2:$V$2224,"SIM")/B11,"") -> 0 | J11: =IFERROR(AVERAGEIFS(Pedidos!$K$2:$K$2224,Pedidos!$X$2:$X$2224,"SIM",Pedidos!$F$2:$F$2224,$A11),"") -> 139.39875 | K11: =IFERROR(MAX(0,1-D11/E11),"") -> 0.29715522
A12: 80-100 | B12: =COUNTIFS(Pedidos!$X$2:$X$2224,"SIM",Pedidos!$F$2:$F$2224,$A12) -> 43 | C12: =IFERROR(AVERAGEIFS(Pedidos!$G$2:$G$2224,Pedidos!$X$2:$X$2224,"SIM",Pedidos!$F$2:$F$2224,$A12),"") -> 87.476744 | D12: =IFERROR(AVERAGEIFS(Pedidos!$J$2:$J$2224,Pedidos!$X$2:$X$2224,"SIM",Pedidos!$F$2:$F$2224,$A12),"") -> 174.62372 | E12: =IFERROR(AVERAGEIFS(Pedidos!$S$2:$S$2224,Pedidos!$X$2:$X$2224,"SIM",Pedidos!$F$2:$F$2224,$A12),"") -> 262.07562 | F12: =IFERROR(E12/D12-1,"") -> 0.50080194 | G12: =IFERROR(SUMIFS(Pedidos!$J$2:$J$2224,Pedidos!$X$2:$X$2224,"SIM",Pedidos!$F$2:$F$2224,$A12)/SUMIFS(Pedidos!$H$2:$H$2224,Pedidos!$X$2:$X$2224,"SIM",Pedidos!$F$2:$F$2224,$A12),"") -> 0.18147433 | H12: =IFERROR(SUMIFS(Pedidos!$S$2:$S$2224,Pedidos!$X$2:$X$2224,"SIM",Pedidos!$F$2:$F$2224,$A12)/SUMIFS(Pedidos!$H$2:$H$2224,Pedidos!$X$2:$X$2224,"SIM",Pedidos!$F$2:$F$2224,$A12),"") -> 0.27235703 | I12: =IFERROR(COUNTIFS(Pedidos!$X$2:$X$2224,"SIM",Pedidos!$F$2:$F$2224,$A12,Pedidos!$V$2:$V$2224,"SIM")/B12,"") -> 0 | J12: =IFERROR(AVERAGEIFS(Pedidos!$K$2:$K$2224,Pedidos!$X$2:$X$2224,"SIM",Pedidos!$F$2:$F$2224,$A12),"") -> 177.46651 | K12: =IFERROR(MAX(0,1-D12/E12),"") -> 0.33368956
A13: 100-120 | B13: =COUNTIFS(Pedidos!$X$2:$X$2224,"SIM",Pedidos!$F$2:$F$2224,$A13) -> 47 | C13: =IFERROR(AVERAGEIFS(Pedidos!$G$2:$G$2224,Pedidos!$X$2:$X$2224,"SIM",Pedidos!$F$2:$F$2224,$A13),"") -> 110.29234 | D13: =IFERROR(AVERAGEIFS(Pedidos!$J$2:$J$2224,Pedidos!$X$2:$X$2224,"SIM",Pedidos!$F$2:$F$2224,$A13),"") -> 194.59979 | E13: =IFERROR(AVERAGEIFS(Pedidos!$S$2:$S$2224,Pedidos!$X$2:$X$2224,"SIM",Pedidos!$F$2:$F$2224,$A13),"") -> 316.24235 | F13: =IFERROR(E13/D13-1,"") -> 0.62509093 | G13: =IFERROR(SUMIFS(Pedidos!$J$2:$J$2224,Pedidos!$X$2:$X$2224,"SIM",Pedidos!$F$2:$F$2224,$A13)/SUMIFS(Pedidos!$H$2:$H$2224,Pedidos!$X$2:$X$2224,"SIM",Pedidos!$F$2:$F$2224,$A13),"") -> 0.15923706 | H13: =IFERROR(SUMIFS(Pedidos!$S$2:$S$2224,Pedidos!$X$2:$X$2224,"SIM",Pedidos!$F$2:$F$2224,$A13)/SUMIFS(Pedidos!$H$2:$H$2224,Pedidos!$X$2:$X$2224,"SIM",Pedidos!$F$2:$F$2224,$A13),"") -> 0.25877471 | I13: =IFERROR(COUNTIFS(Pedidos!$X$2:$X$2224,"SIM",Pedidos!$F$2:$F$2224,$A13,Pedidos!$V$2:$V$2224,"SIM")/B13,"") -> 0 | J13: =IFERROR(AVERAGEIFS(Pedidos!$K$2:$K$2224,Pedidos!$X$2:$X$2224,"SIM",Pedidos!$F$2:$F$2224,$A13),"") -> 208.16894 | K13: =IFERROR(MAX(0,1-D13/E13),"") -> 0.38464982
A14: 120-150 | B14: =COUNTIFS(Pedidos!$X$2:$X$2224,"SIM",Pedidos!$F$2:$F$2224,$A14) -> 73 | C14: =IFERROR(AVERAGEIFS(Pedidos!$G$2:$G$2224,Pedidos!$X$2:$X$2224,"SIM",Pedidos!$F$2:$F$2224,$A14),"") -> 128.52932 | D14: =IFERROR(AVERAGEIFS(Pedidos!$J$2:$J$2224,Pedidos!$X$2:$X$2224,"SIM",Pedidos!$F$2:$F$2224,$A14),"") -> 240.82521 | E14: =IFERROR(AVERAGEIFS(Pedidos!$S$2:$S$2224,Pedidos!$X$2:$X$2224,"SIM",Pedidos!$F$2:$F$2224,$A14),"") -> 369.59088 | F14: =IFERROR(E14/D14-1,"") -> 0.53468522 | G14: =IFERROR(SUMIFS(Pedidos!$J$2:$J$2224,Pedidos!$X$2:$X$2224,"SIM",Pedidos!$F$2:$F$2224,$A14)/SUMIFS(Pedidos!$H$2:$H$2224,Pedidos!$X$2:$X$2224,"SIM",Pedidos!$F$2:$F$2224,$A14),"") -> 0.14641807 | H14: =IFERROR(SUMIFS(Pedidos!$S$2:$S$2224,Pedidos!$X$2:$X$2224,"SIM",Pedidos!$F$2:$F$2224,$A14)/SUMIFS(Pedidos!$H$2:$H$2224,Pedidos!$X$2:$X$2224,"SIM",Pedidos!$F$2:$F$2224,$A14),"") -> 0.22470564 | I14: =IFERROR(COUNTIFS(Pedidos!$X$2:$X$2224,"SIM",Pedidos!$F$2:$F$2224,$A14,Pedidos!$V$2:$V$2224,"SIM")/B14,"") -> 0 | J14: =IFERROR(AVERAGEIFS(Pedidos!$K$2:$K$2224,Pedidos!$X$2:$X$2224,"SIM",Pedidos!$F$2:$F$2224,$A14),"") -> 244.44575 | K14: =IFERROR(MAX(0,1-D14/E14),"") -> 0.34840058
A15: 150-170 | B15: =COUNTIFS(Pedidos!$X$2:$X$2224,"SIM",Pedidos!$F$2:$F$2224,$A15) -> 3 | C15: =IFERROR(AVERAGEIFS(Pedidos!$G$2:$G$2224,Pedidos!$X$2:$X$2224,"SIM",Pedidos!$F$2:$F$2224,$A15),"") -> 160.63333 | D15: =IFERROR(AVERAGEIFS(Pedidos!$J$2:$J$2224,Pedidos!$X$2:$X$2224,"SIM",Pedidos!$F$2:$F$2224,$A15),"") -> 259.73 | E15: =IFERROR(AVERAGEIFS(Pedidos!$S$2:$S$2224,Pedidos!$X$2:$X$2224,"SIM",Pedidos!$F$2:$F$2224,$A15),"") -> 423.50102 | F15: =IFERROR(E15/D15-1,"") -> 0.63054334 | G15: =IFERROR(SUMIFS(Pedidos!$J$2:$J$2224,Pedidos!$X$2:$X$2224,"SIM",Pedidos!$F$2:$F$2224,$A15)/SUMIFS(Pedidos!$H$2:$H$2224,Pedidos!$X$2:$X$2224,"SIM",Pedidos!$F$2:$F$2224,$A15),"") -> 0.13604317 | H15: =IFERROR(SUMIFS(Pedidos!$S$2:$S$2224,Pedidos!$X$2:$X$2224,"SIM",Pedidos!$F$2:$F$2224,$A15)/SUMIFS(Pedidos!$H$2:$H$2224,Pedidos!$X$2:$X$2224,"SIM",Pedidos!$F$2:$F$2224,$A15),"") -> 0.22182429 | I15: =IFERROR(COUNTIFS(Pedidos!$X$2:$X$2224,"SIM",Pedidos!$F$2:$F$2224,$A15,Pedidos!$V$2:$V$2224,"SIM")/B15,"") -> 0 | J15: =IFERROR(AVERAGEIFS(Pedidos!$K$2:$K$2224,Pedidos!$X$2:$X$2224,"SIM",Pedidos!$F$2:$F$2224,$A15),"") -> 274.84333 | K15: =IFERROR(MAX(0,1-D15/E15),"") -> 0.3867075
A16: 170-200 | B16: =COUNTIFS(Pedidos!$X$2:$X$2224,"SIM",Pedidos!$F$2:$F$2224,$A16) -> 1 | C16: =IFERROR(AVERAGEIFS(Pedidos!$G$2:$G$2224,Pedidos!$X$2:$X$2224,"SIM",Pedidos!$F$2:$F$2224,$A16),"") -> 188.4 | D16: =IFERROR(AVERAGEIFS(Pedidos!$J$2:$J$2224,Pedidos!$X$2:$X$2224,"SIM",Pedidos!$F$2:$F$2224,$A16),"") -> 198.28 | E16: =IFERROR(AVERAGEIFS(Pedidos!$S$2:$S$2224,Pedidos!$X$2:$X$2224,"SIM",Pedidos!$F$2:$F$2224,$A16),"") -> 529.025 | F16: =IFERROR(E16/D16-1,"") -> 1.6680704 | G16: =IFERROR(SUMIFS(Pedidos!$J$2:$J$2224,Pedidos!$X$2:$X$2224,"SIM",Pedidos!$F$2:$F$2224,$A16)/SUMIFS(Pedidos!$H$2:$H$2224,Pedidos!$X$2:$X$2224,"SIM",Pedidos!$F$2:$F$2224,$A16),"") -> 0.099438315 | H16: =IFERROR(SUMIFS(Pedidos!$S$2:$S$2224,Pedidos!$X$2:$X$2224,"SIM",Pedidos!$F$2:$F$2224,$A16)/SUMIFS(Pedidos!$H$2:$H$2224,Pedidos!$X$2:$X$2224,"SIM",Pedidos!$F$2:$F$2224,$A16),"") -> 0.26530843 | I16: =IFERROR(COUNTIFS(Pedidos!$X$2:$X$2224,"SIM",Pedidos!$F$2:$F$2224,$A16,Pedidos!$V$2:$V$2224,"SIM")/B16,"") -> 0 | J16: =IFERROR(AVERAGEIFS(Pedidos!$K$2:$K$2224,Pedidos!$X$2:$X$2224,"SIM",Pedidos!$F$2:$F$2224,$A16),"") -> 353.17 | K16: =IFERROR(MAX(0,1-D16/E16),"") -> 0.6251973
... A18: >250 | B18: =COUNTIFS(Pedidos!$X$2:$X$2224,"SIM",Pedidos!$F$2:$F$2224,$A18) -> 0 | C18: =IFERROR(AVERAGEIFS(Pedidos!$G$2:$G$2224,Pedidos!$X$2:$X$2224,"SIM",Pedidos!$F$2:$F$2224,$A18),"") | D18: =IFERROR(AVERAGEIFS(Pedidos!$J$2:$J$2224,Pedidos!$X$2:$X$2224,"SIM",Pedidos!$F$2:$F$2224,$A18),"") | E18: =IFERROR(AVERAGEIFS(Pedidos!$S$2:$S$2224,Pedidos!$X$2:$X$2224,"SIM",Pedidos!$F$2:$F$2224,$A18),"") | F18: =IFERROR(E18/D18-1,"") | G18: =IFERROR(SUMIFS(Pedidos!$J$2:$J$2224,Pedidos!$X$2:$X$2224,"SIM",Pedidos!$F$2:$F$2224,$A18)/SUMIFS(Pedidos!$H$2:$H$2224,Pedidos!$X$2:$X$2224,"SIM",Pedidos!$F$2:$F$2224,$A18),"") | H18: =IFERROR(SUMIFS(Pedidos!$S$2:$S$2224,Pedidos!$X$2:$X$2224,"SIM",Pedidos!$F$2:$F$2224,$A18)/SUMIFS(Pedidos!$H$2:$H$2224,Pedidos!$X$2:$X$2224,"SIM",Pedidos!$F$2:$F$2224,$A18),"") | I18: =IFERROR(COUNTIFS(Pedidos!$X$2:$X$2224,"SIM",Pedidos!$F$2:$F$2224,$A18,Pedidos!$V$2:$V$2224,"SIM")/B18,"") | J18: =IFERROR(AVERAGEIFS(Pedidos!$K$2:$K$2224,Pedidos!$X$2:$X$2224,"SIM",Pedidos!$F$2:$F$2224,$A18),"") | K18: =IFERROR(MAX(0,1-D18/E18),"")
A19: TOTAL | B19: =COUNTIFS(Pedidos!$X$2:$X$2224,"SIM") -> 1912 | C19: =IFERROR(AVERAGEIFS(Pedidos!$G$2:$G$2224,Pedidos!$X$2:$X$2224,"SIM"),"") -> 49.45444 | D19: =IFERROR(AVERAGEIFS(Pedidos!$J$2:$J$2224,Pedidos!$X$2:$X$2224,"SIM"),"") -> 118.41855 | E19: =IFERROR(AVERAGEIFS(Pedidos!$S$2:$S$2224,Pedidos!$X$2:$X$2224,"SIM"),"") -> 169.56635 | F19: =IFERROR(E19/D19-1,"") -> 0.43192393 | G19: =IFERROR(SUMIFS(Pedidos!$J$2:$J$2224,Pedidos!$X$2:$X$2224,"SIM")/SUMIFS(Pedidos!$H$2:$H$2224,Pedidos!$X$2:$X$2224,"SIM"),"") -> 0.1861794 | H19: =IFERROR(SUMIFS(Pedidos!$S$2:$S$2224,Pedidos!$X$2:$X$2224,"SIM")/SUMIFS(Pedidos!$H$2:$H$2224,Pedidos!$X$2:$X$2224,"SIM"),"") -> 0.26659474 | I19: =IFERROR(COUNTIFS(Pedidos!$X$2:$X$2224,"SIM",Pedidos!$V$2:$V$2224,"SIM")/B19,"") -> 0.0073221757 | J19: =IFERROR(AVERAGEIFS(Pedidos!$K$2:$K$2224,Pedidos!$X$2:$X$2224,"SIM"),"") -> 116.08623 | K19: =IFERROR(MAX(0,1-D19/E19),"") -> 0.30163888
A21: Transportadora atual: Tsl Filial Sp
A22: Faixa (kg) | B22: Pedidos | C22: Peso médio | D22: Custo médio atual (R$) | E22: PROLOG médio (R$) | F22: PROLOG vs atual (%) | G22: Frete/NF atual | H22: Frete/NF PROLOG | I22: % pedidos PROLOG mais barata | J22: PROLOG só frete peso (R$) | K22: Desconto necessário p/ empatar
A23: 0-20 | B23: =COUNTIFS(Pedidos!$X$2:$X$2224,"SIM",Pedidos!$I$2:$I$2224,"Tsl Filial Sp",Pedidos!$F$2:$F$2224,$A23) -> 60 | C23: =IFERROR(AVERAGEIFS(Pedidos!$G$2:$G$2224,Pedidos!$X$2:$X$2224,"SIM",Pedidos!$I$2:$I$2224,"Tsl Filial Sp",Pedidos!$F$2:$F$2224,$A23),"") -> 16.952167 | D23: =IFERROR(AVERAGEIFS(Pedidos!$J$2:$J$2224,Pedidos!$X$2:$X$2224,"SIM",Pedidos!$I$2:$I$2224,"Tsl Filial Sp",Pedidos!$F$2:$F$2224,$A23),"") -> 68.086 | E23: =IFERROR(AVERAGEIFS(Pedidos!$S$2:$S$2224,Pedidos!$X$2:$X$2224,"SIM",Pedidos!$I$2:$I$2224,"Tsl Filial Sp",Pedidos!$F$2:$F$2224,$A23),"") -> 76.187824 | F23: =IFERROR(E23/D23-1,"") -> 0.11899398 | G23: =IFERROR(SUMIFS(Pedidos!$J$2:$J$2224,Pedidos!$X$2:$X$2224,"SIM",Pedidos!$I$2:$I$2224,"Tsl Filial Sp",Pedidos!$F$2:$F$2224,$A23)/SUMIFS(Pedidos!$H$2:$H$2224,Pedidos!$X$2:$X$2224,"SIM",Pedidos!$I$2:$I$2224,"Tsl Filial Sp",Pedidos!$F$2:$F$2224,$A23),"") -> 0.22374005 | H23: =IFERROR(SUMIFS(Pedidos!$S$2:$S$2224,Pedidos!$X$2:$X$2224,"SIM",Pedidos!$I$2:$I$2224,"Tsl Filial Sp",Pedidos!$F$2:$F$2224,$A23)/SUMIFS(Pedidos!$H$2:$H$2224,Pedidos!$X$2:$X$2224,"SIM",Pedidos!$I$2:$I$2224,"Tsl Filial Sp",Pedidos!$F$2:$F$2224,$A23),"") -> 0.25036377 | I23: =IFERROR(COUNTIFS(Pedidos!$X$2:$X$2224,"SIM",Pedidos!$I$2:$I$2224,"Tsl Filial Sp",Pedidos!$F$2:$F$2224,$A23,Pedidos!$V$2:$V$2224,"SIM")/B23,"") -> 0.13333333 | J23: =IFERROR(AVERAGEIFS(Pedidos!$K$2:$K$2224,Pedidos!$X$2:$X$2224,"SIM",Pedidos!$I$2:$I$2224,"Tsl Filial Sp",Pedidos!$F$2:$F$2224,$A23),"") -> 51.766833 | K23: =IFERROR(MAX(0,1-D23/E23),"") -> 0.10634014
A24: 20-35 | B24: =COUNTIFS(Pedidos!$X$2:$X$2224,"SIM",Pedidos!$I$2:$I$2224,"Tsl Filial Sp",Pedidos!$F$2:$F$2224,$A24) -> 347 | C24: =IFERROR(AVERAGEIFS(Pedidos!$G$2:$G$2224,Pedidos!$X$2:$X$2224,"SIM",Pedidos!$I$2:$I$2224,"Tsl Filial Sp",Pedidos!$F$2:$F$2224,$A24),"") -> 28.226138 | D24: =IFERROR(AVERAGEIFS(Pedidos!$J$2:$J$2224,Pedidos!$X$2:$X$2224,"SIM",Pedidos!$I$2:$I$2224,"Tsl Filial Sp",Pedidos!$F$2:$F$2224,$A24),"") -> 90.233487 | E24: =IFERROR(AVERAGEIFS(Pedidos!$S$2:$S$2224,Pedidos!$X$2:$X$2224,"SIM",Pedidos!$I$2:$I$2224,"Tsl Filial Sp",Pedidos!$F$2:$F$2224,$A24),"") -> 126.04516 | F24: =IFERROR(E24/D24-1,"") -> 0.39687787 | G24: =IFERROR(SUMIFS(Pedidos!$J$2:$J$2224,Pedidos!$X$2:$X$2224,"SIM",Pedidos!$I$2:$I$2224,"Tsl Filial Sp",Pedidos!$F$2:$F$2224,$A24)/SUMIFS(Pedidos!$H$2:$H$2224,Pedidos!$X$2:$X$2224,"SIM",Pedidos!$I$2:$I$2224,"Tsl Filial Sp",Pedidos!$F$2:$F$2224,$A24),"") -> 0.2080639 | H24: =IFERROR(SUMIFS(Pedidos!$S$2:$S$2224,Pedidos!$X$2:$X$2224,"SIM",Pedidos!$I$2:$I$2224,"Tsl Filial Sp",Pedidos!$F$2:$F$2224,$A24)/SUMIFS(Pedidos!$H$2:$H$2224,Pedidos!$X$2:$X$2224,"SIM",Pedidos!$I$2:$I$2224,"Tsl Filial Sp",Pedidos!$F$2:$F$2224,$A24),"") -> 0.29063986 | I24: =IFERROR(COUNTIFS(Pedidos!$X$2:$X$2224,"SIM",Pedidos!$I$2:$I$2224,"Tsl Filial Sp",Pedidos!$F$2:$F$2224,$A24,Pedidos!$V$2:$V$2224,"SIM")/B24,"") -> 0 | J24: =IFERROR(AVERAGEIFS(Pedidos!$K$2:$K$2224,Pedidos!$X$2:$X$2224,"SIM",Pedidos!$I$2:$I$2224,"Tsl Filial Sp",Pedidos!$F$2:$F$2224,$A24),"") -> 89.543256 | K24: =IFERROR(MAX(0,1-D24/E24),"") -> 0.2841178
A25: 35-40 | B25: =COUNTIFS(Pedidos!$X$2:$X$2224,"SIM",Pedidos!$I$2:$I$2224,"Tsl Filial Sp",Pedidos!$F$2:$F$2224,$A25) -> 231 | C25: =IFERROR(AVERAGEIFS(Pedidos!$G$2:$G$2224,Pedidos!$X$2:$X$2224,"SIM",Pedidos!$I$2:$I$2224,"Tsl Filial Sp",Pedidos!$F$2:$F$2224,$A25),"") -> 37.73645 | D25: =IFERROR(AVERAGEIFS(Pedidos!$J$2:$J$2224,Pedidos!$X$2:$X$2224,"SIM",Pedidos!$I$2:$I$2224,"Tsl Filial Sp",Pedidos!$F$2:$F$2224,$A25),"") -> 102.1158 | E25: =IFERROR(AVERAGEIFS(Pedidos!$S$2:$S$2224,Pedidos!$X$2:$X$2224,"SIM",Pedidos!$I$2:$I$2224,"Tsl Filial Sp",Pedidos!$F$2:$F$2224,$A25),"") -> 144.7635 | F25: =IFERROR(E25/D25-1,"") -> 0.41764052 | G25: =IFERROR(SUMIFS(Pedidos!$J$2:$J$2224,Pedidos!$X$2:$X$2224,"SIM",Pedidos!$I$2:$I$2224,"Tsl Filial Sp",Pedidos!$F$2:$F$2224,$A25)/SUMIFS(Pedidos!$H$2:$H$2224,Pedidos!$X$2:$X$2224,"SIM",Pedidos!$I$2:$I$2224,"Tsl Filial Sp",Pedidos!$F$2:$F$2224,$A25),"") -> 0.2187463 | H25: =IFERROR(SUMIFS(Pedidos!$S$2:$S$2224,Pedidos!$X$2:$X$2224,"SIM",Pedidos!$I$2:$I$2224,"Tsl Filial Sp",Pedidos!$F$2:$F$2224,$A25)/SUMIFS(Pedidos!$H$2:$H$2224,Pedidos!$X$2:$X$2224,"SIM",Pedidos!$I$2:$I$2224,"Tsl Filial Sp",Pedidos!$F$2:$F$2224,$A25),"") -> 0.31010362 | I25: =IFERROR(COUNTIFS(Pedidos!$X$2:$X$2224,"SIM",Pedidos!$I$2:$I$2224,"Tsl Filial Sp",Pedidos!$F$2:$F$2224,$A25,Pedidos!$V$2:$V$2224,"SIM")/B25,"") -> 0 | J25: =IFERROR(AVERAGEIFS(Pedidos!$K$2:$K$2224,Pedidos!$X$2:$X$2224,"SIM",Pedidos!$I$2:$I$2224,"Tsl Filial Sp",Pedidos!$F$2:$F$2224,$A25),"") -> 101.06502 | K25: =IFERROR(MAX(0,1-D25/E25),"") -> 0.29460255
A26: 40-50 | B26: =COUNTIFS(Pedidos!$X$2:$X$2224,"SIM",Pedidos!$I$2:$I$2224,"Tsl Filial Sp",Pedidos!$F$2:$F$2224,$A26) -> 230 | C26: =IFERROR(AVERAGEIFS(Pedidos!$G$2:$G$2224,Pedidos!$X$2:$X$2224,"SIM",Pedidos!$I$2:$I$2224,"Tsl Filial Sp",Pedidos!$F$2:$F$2224,$A26),"") -> 46.013478 | D26: =IFERROR(AVERAGEIFS(Pedidos!$J$2:$J$2224,Pedidos!$X$2:$X$2224,"SIM",Pedidos!$I$2:$I$2224,"Tsl Filial Sp",Pedidos!$F$2:$F$2224,$A26),"") -> 111.57261 | E26: =IFERROR(AVERAGEIFS(Pedidos!$S$2:$S$2224,Pedidos!$X$2:$X$2224,"SIM",Pedidos!$I$2:$I$2224,"Tsl Filial Sp",Pedidos!$F$2:$F$2224,$A26),"") -> 151.21398 | F26: =IFERROR(E26/D26-1,"") -> 0.3552966 | G26: =IFERROR(SUMIFS(Pedidos!$J$2:$J$2224,Pedidos!$X$2:$X$2224,"SIM",Pedidos!$I$2:$I$2224,"Tsl Filial Sp",Pedidos!$F$2:$F$2224,$A26)/SUMIFS(Pedidos!$H$2:$H$2224,Pedidos!$X$2:$X$2224,"SIM",Pedidos!$I$2:$I$2224,"Tsl Filial Sp",Pedidos!$F$2:$F$2224,$A26),"") -> 0.18307816 | H26: =IFERROR(SUMIFS(Pedidos!$S$2:$S$2224,Pedidos!$X$2:$X$2224,"SIM",Pedidos!$I$2:$I$2224,"Tsl Filial Sp",Pedidos!$F$2:$F$2224,$A26)/SUMIFS(Pedidos!$H$2:$H$2224,Pedidos!$X$2:$X$2224,"SIM",Pedidos!$I$2:$I$2224,"Tsl Filial Sp",Pedidos!$F$2:$F$2224,$A26),"") -> 0.24812521 | I26: =IFERROR(COUNTIFS(Pedidos!$X$2:$X$2224,"SIM",Pedidos!$I$2:$I$2224,"Tsl Filial Sp",Pedidos!$F$2:$F$2224,$A26,Pedidos!$V$2:$V$2224,"SIM")/B26,"") -> 0 | J26: =IFERROR(AVERAGEIFS(Pedidos!$K$2:$K$2224,Pedidos!$X$2:$X$2224,"SIM",Pedidos!$I$2:$I$2224,"Tsl Filial Sp",Pedidos!$F$2:$F$2224,$A26),"") -> 102.09596 | K26: =IFERROR(MAX(0,1-D26/E26),"") -> 0.26215413
A27: 50-60 | B27: =COUNTIFS(Pedidos!$X$2:$X$2224,"SIM",Pedidos!$I$2:$I$2224,"Tsl Filial Sp",Pedidos!$F$2:$F$2224,$A27) -> 230 | C27: =IFERROR(AVERAGEIFS(Pedidos!$G$2:$G$2224,Pedidos!$X$2:$X$2224,"SIM",Pedidos!$I$2:$I$2224,"Tsl Filial Sp",Pedidos!$F$2:$F$2224,$A27),"") -> 53.869435 | D27: =IFERROR(AVERAGEIFS(Pedidos!$J$2:$J$2224,Pedidos!$X$2:$X$2224,"SIM",Pedidos!$I$2:$I$2224,"Tsl Filial Sp",Pedidos!$F$2:$F$2224,$A27),"") -> 122.18887 | E27: =IFERROR(AVERAGEIFS(Pedidos!$S$2:$S$2224,Pedidos!$X$2:$X$2224,"SIM",Pedidos!$I$2:$I$2224,"Tsl Filial Sp",Pedidos!$F$2:$F$2224,$A27),"") -> 174.17349 | F27: =IFERROR(E27/D27-1,"") -> 0.42544478 | G27: =IFERROR(SUMIFS(Pedidos!$J$2:$J$2224,Pedidos!$X$2:$X$2224,"SIM",Pedidos!$I$2:$I$2224,"Tsl Filial Sp",Pedidos!$F$2:$F$2224,$A27)/SUMIFS(Pedidos!$H$2:$H$2224,Pedidos!$X$2:$X$2224,"SIM",Pedidos!$I$2:$I$2224,"Tsl Filial Sp",Pedidos!$F$2:$F$2224,$A27),"") -> 0.17585563 | H27: =IFERROR(SUMIFS(Pedidos!$S$2:$S$2224,Pedidos!$X$2:$X$2224,"SIM",Pedidos!$I$2:$I$2224,"Tsl Filial Sp",Pedidos!$F$2:$F$2224,$A27)/SUMIFS(Pedidos!$H$2:$H$2224,Pedidos!$X$2:$X$2224,"SIM",Pedidos!$I$2:$I$2224,"Tsl Filial Sp",Pedidos!$F$2:$F$2224,$A27),"") -> 0.25067248 | I27: =IFERROR(COUNTIFS(Pedidos!$X$2:$X$2224,"SIM",Pedidos!$I$2:$I$2224,"Tsl Filial Sp",Pedidos!$F$2:$F$2224,$A27,Pedidos!$V$2:$V$2224,"SIM")/B27,"") -> 0 | J27: =IFERROR(AVERAGEIFS(Pedidos!$K$2:$K$2224,Pedidos!$X$2:$X$2224,"SIM",Pedidos!$I$2:$I$2224,"Tsl Filial Sp",Pedidos!$F$2:$F$2224,$A27),"") -> 117.93309 | K27: =IFERROR(MAX(0,1-D27/E27),"") -> 0.29846458
A28: 60-70 | B28: =COUNTIFS(Pedidos!$X$2:$X$2224,"SIM",Pedidos!$I$2:$I$2224,"Tsl Filial Sp",Pedidos!$F$2:$F$2224,$A28) -> 178 | C28: =IFERROR(AVERAGEIFS(Pedidos!$G$2:$G$2224,Pedidos!$X$2:$X$2224,"SIM",Pedidos!$I$2:$I$2224,"Tsl Filial Sp",Pedidos!$F$2:$F$2224,$A28),"") -> 66.23809 | D28: =IFERROR(AVERAGEIFS(Pedidos!$J$2:$J$2224,Pedidos!$X$2:$X$2224,"SIM",Pedidos!$I$2:$I$2224,"Tsl Filial Sp",Pedidos!$F$2:$F$2224,$A28),"") -> 133.63685 | E28: =IFERROR(AVERAGEIFS(Pedidos!$S$2:$S$2224,Pedidos!$X$2:$X$2224,"SIM",Pedidos!$I$2:$I$2224,"Tsl Filial Sp",Pedidos!$F$2:$F$2224,$A28),"") -> 203.43675 | F28: =IFERROR(E28/D28-1,"") -> 0.52231026 | G28: =IFERROR(SUMIFS(Pedidos!$J$2:$J$2224,Pedidos!$X$2:$X$2224,"SIM",Pedidos!$I$2:$I$2224,"Tsl Filial Sp",Pedidos!$F$2:$F$2224,$A28)/SUMIFS(Pedidos!$H$2:$H$2224,Pedidos!$X$2:$X$2224,"SIM",Pedidos!$I$2:$I$2224,"Tsl Filial Sp",Pedidos!$F$2:$F$2224,$A28),"") -> 0.17527255 | H28: =IFERROR(SUMIFS(Pedidos!$S$2:$S$2224,Pedidos!$X$2:$X$2224,"SIM",Pedidos!$I$2:$I$2224,"Tsl Filial Sp",Pedidos!$F$2:$F$2224,$A28)/SUMIFS(Pedidos!$H$2:$H$2224,Pedidos!$X$2:$X$2224,"SIM",Pedidos!$I$2:$I$2224,"Tsl Filial Sp",Pedidos!$F$2:$F$2224,$A28),"") -> 0.26681921 | I28: =IFERROR(COUNTIFS(Pedidos!$X$2:$X$2224,"SIM",Pedidos!$I$2:$I$2224,"Tsl Filial Sp",Pedidos!$F$2:$F$2224,$A28,Pedidos!$V$2:$V$2224,"SIM")/B28,"") -> 0 | J28: =IFERROR(AVERAGEIFS(Pedidos!$K$2:$K$2224,Pedidos!$X$2:$X$2224,"SIM",Pedidos!$I$2:$I$2224,"Tsl Filial Sp",Pedidos!$F$2:$F$2224,$A28),"") -> 137.27899 | K28: =IFERROR(MAX(0,1-D28/E28),"") -> 0.34310368
A29: 70-80 | B29: =COUNTIFS(Pedidos!$X$2:$X$2224,"SIM",Pedidos!$I$2:$I$2224,"Tsl Filial Sp",Pedidos!$F$2:$F$2224,$A29) -> 19 | C29: =IFERROR(AVERAGEIFS(Pedidos!$G$2:$G$2224,Pedidos!$X$2:$X$2224,"SIM",Pedidos!$I$2:$I$2224,"Tsl Filial Sp",Pedidos!$F$2:$F$2224,$A29),"") -> 74.105263 | D29: =IFERROR(AVERAGEIFS(Pedidos!$J$2:$J$2224,Pedidos!$X$2:$X$2224,"SIM",Pedidos!$I$2:$I$2224,"Tsl Filial Sp",Pedidos!$F$2:$F$2224,$A29),"") -> 147.00842 | E29: =IFERROR(AVERAGEIFS(Pedidos!$S$2:$S$2224,Pedidos!$X$2:$X$2224,"SIM",Pedidos!$I$2:$I$2224,"Tsl Filial Sp",Pedidos!$F$2:$F$2224,$A29),"") -> 211.5 | F29: =IFERROR(E29/D29-1,"") -> 0.43869309 | G29: =IFERROR(SUMIFS(Pedidos!$J$2:$J$2224,Pedidos!$X$2:$X$2224,"SIM",Pedidos!$I$2:$I$2224,"Tsl Filial Sp",Pedidos!$F$2:$F$2224,$A29)/SUMIFS(Pedidos!$H$2:$H$2224,Pedidos!$X$2:$X$2224,"SIM",Pedidos!$I$2:$I$2224,"Tsl Filial Sp",Pedidos!$F$2:$F$2224,$A29),"") -> 0.15307905 | H29: =IFERROR(SUMIFS(Pedidos!$S$2:$S$2224,Pedidos!$X$2:$X$2224,"SIM",Pedidos!$I$2:$I$2224,"Tsl Filial Sp",Pedidos!$F$2:$F$2224,$A29)/SUMIFS(Pedidos!$H$2:$H$2224,Pedidos!$X$2:$X$2224,"SIM",Pedidos!$I$2:$I$2224,"Tsl Filial Sp",Pedidos!$F$2:$F$2224,$A29),"") -> 0.22023378 | I29: =IFERROR(COUNTIFS(Pedidos!$X$2:$X$2224,"SIM",Pedidos!$I$2:$I$2224,"Tsl Filial Sp",Pedidos!$F$2:$F$2224,$A29,Pedidos!$V$2:$V$2224,"SIM")/B29,"") -> 0 | J29: =IFERROR(AVERAGEIFS(Pedidos!$K$2:$K$2224,Pedidos!$X$2:$X$2224,"SIM",Pedidos!$I$2:$I$2224,"Tsl Filial Sp",Pedidos!$F$2:$F$2224,$A29),"") -> 139.83789 | K29: =IFERROR(MAX(0,1-D29/E29),"") -> 0.30492472
A30: 80-100 | B30: =COUNTIFS(Pedidos!$X$2:$X$2224,"SIM",Pedidos!$I$2:$I$2224,"Tsl Filial Sp",Pedidos!$F$2:$F$2224,$A30) -> 38 | C30: =IFERROR(AVERAGEIFS(Pedidos!$G$2:$G$2224,Pedidos!$X$2:$X$2224,"SIM",Pedidos!$I$2:$I$2224,"Tsl Filial Sp",Pedidos!$F$2:$F$2224,$A30),"") -> 87.921053 | D30: =IFERROR(AVERAGEIFS(Pedidos!$J$2:$J$2224,Pedidos!$X$2:$X$2224,"SIM",Pedidos!$I$2:$I$2224,"Tsl Filial Sp",Pedidos!$F$2:$F$2224,$A30),"") -> 174.32053 | E30: =IFERROR(AVERAGEIFS(Pedidos!$S$2:$S$2224,Pedidos!$X$2:$X$2224,"SIM",Pedidos!$I$2:$I$2224,"Tsl Filial Sp",Pedidos!$F$2:$F$2224,$A30),"") -> 262.49897 | F30: =IFERROR(E30/D30-1,"") -> 0.50584084 | G30: =IFERROR(SUMIFS(Pedidos!$J$2:$J$2224,Pedidos!$X$2:$X$2224,"SIM",Pedidos!$I$2:$I$2224,"Tsl Filial Sp",Pedidos!$F$2:$F$2224,$A30)/SUMIFS(Pedidos!$H$2:$H$2224,Pedidos!$X$2:$X$2224,"SIM",Pedidos!$I$2:$I$2224,"Tsl Filial Sp",Pedidos!$F$2:$F$2224,$A30),"") -> 0.18016082 | H30: =IFERROR(SUMIFS(Pedidos!$S$2:$S$2224,Pedidos!$X$2:$X$2224,"SIM",Pedidos!$I$2:$I$2224,"Tsl Filial Sp",Pedidos!$F$2:$F$2224,$A30)/SUMIFS(Pedidos!$H$2:$H$2224,Pedidos!$X$2:$X$2224,"SIM",Pedidos!$I$2:$I$2224,"Tsl Filial Sp",Pedidos!$F$2:$F$2224,$A30),"") -> 0.27129352 | I30: =IFERROR(COUNTIFS(Pedidos!$X$2:$X$2224,"SIM",Pedidos!$I$2:$I$2224,"Tsl Filial Sp",Pedidos!$F$2:$F$2224,$A30,Pedidos!$V$2:$V$2224,"SIM")/B30,"") -> 0 | J30: =IFERROR(AVERAGEIFS(Pedidos!$K$2:$K$2224,Pedidos!$X$2:$X$2224,"SIM",Pedidos!$I$2:$I$2224,"Tsl Filial Sp",Pedidos!$F$2:$F$2224,$A30),"") -> 177.59553 | K30: =IFERROR(MAX(0,1-D30/E30),"") -> 0.33591919
A31: 100-120 | B31: =COUNTIFS(Pedidos!$X$2:$X$2224,"SIM",Pedidos!$I$2:$I$2224,"Tsl Filial Sp",Pedidos!$F$2:$F$2224,$A31) -> 35 | C31: =IFERROR(AVERAGEIFS(Pedidos!$G$2:$G$2224,Pedidos!$X$2:$X$2224,"SIM",Pedidos!$I$2:$I$2224,"Tsl Filial Sp",Pedidos!$F$2:$F$2224,$A31),"") -> 110.18971 | D31: =IFERROR(AVERAGEIFS(Pedidos!$J$2:$J$2224,Pedidos!$X$2:$X$2224,"SIM",Pedidos!$I$2:$I$2224,"Tsl Filial Sp",Pedidos!$F$2:$F$2224,$A31),"") -> 192.25486 | E31: =IFERROR(AVERAGEIFS(Pedidos!$S$2:$S$2224,Pedidos!$X$2:$X$2224,"SIM",Pedidos!$I$2:$I$2224,"Tsl Filial Sp",Pedidos!$F$2:$F$2224,$A31),"") -> 313.39016 | F31: =IFERROR(E31/D31-1,"") -> 0.6300767 | G31: =IFERROR(SUMIFS(Pedidos!$J$2:$J$2224,Pedidos!$X$2:$X$2224,"SIM",Pedidos!$I$2:$I$2224,"Tsl Filial Sp",Pedidos!$F$2:$F$2224,$A31)/SUMIFS(Pedidos!$H$2:$H$2224,Pedidos!$X$2:$X$2224,"SIM",Pedidos!$I$2:$I$2224,"Tsl Filial Sp",Pedidos!$F$2:$F$2224,$A31),"") -> 0.15673408 | H31: =IFERROR(SUMIFS(Pedidos!$S$2:$S$2224,Pedidos!$X$2:$X$2224,"SIM",Pedidos!$I$2:$I$2224,"Tsl Filial Sp",Pedidos!$F$2:$F$2224,$A31)/SUMIFS(Pedidos!$H$2:$H$2224,Pedidos!$X$2:$X$2224,"SIM",Pedidos!$I$2:$I$2224,"Tsl Filial Sp",Pedidos!$F$2:$F$2224,$A31),"") -> 0.25548857 | I31: =IFERROR(COUNTIFS(Pedidos!$X$2:$X$2224,"SIM",Pedidos!$I$2:$I$2224,"Tsl Filial Sp",Pedidos!$F$2:$F$2224,$A31,Pedidos!$V$2:$V$2224,"SIM")/B31,"") -> 0 | J31: =IFERROR(AVERAGEIFS(Pedidos!$K$2:$K$2224,Pedidos!$X$2:$X$2224,"SIM",Pedidos!$I$2:$I$2224,"Tsl Filial Sp",Pedidos!$F$2:$F$2224,$A31),"") -> 205.68286 | K31: =IFERROR(MAX(0,1-D31/E31),"") -> 0.38653193
A32: 120-150 | B32: =COUNTIFS(Pedidos!$X$2:$X$2224,"SIM",Pedidos!$I$2:$I$2224,"Tsl Filial Sp",Pedidos!$F$2:$F$2224,$A32) -> 48 | C32: =IFERROR(AVERAGEIFS(Pedidos!$G$2:$G$2224,Pedidos!$X$2:$X$2224,"SIM",Pedidos!$I$2:$I$2224,"Tsl Filial Sp",Pedidos!$F$2:$F$2224,$A32),"") -> 128.26542 | D32: =IFERROR(AVERAGEIFS(Pedidos!$J$2:$J$2224,Pedidos!$X$2:$X$2224,"SIM",Pedidos!$I$2:$I$2224,"Tsl Filial Sp",Pedidos!$F$2:$F$2224,$A32),"") -> 239.57979 | E32: =IFERROR(AVERAGEIFS(Pedidos!$S$2:$S$2224,Pedidos!$X$2:$X$2224,"SIM",Pedidos!$I$2:$I$2224,"Tsl Filial Sp",Pedidos!$F$2:$F$2224,$A32),"") -> 366.89616 | F32: =IFERROR(E32/D32-1,"") -> 0.53141529 | G32: =IFERROR(SUMIFS(Pedidos!$J$2:$J$2224,Pedidos!$X$2:$X$2224,"SIM",Pedidos!$I$2:$I$2224,"Tsl Filial Sp",Pedidos!$F$2:$F$2224,$A32)/SUMIFS(Pedidos!$H$2:$H$2224,Pedidos!$X$2:$X$2224,"SIM",Pedidos!$I$2:$I$2224,"Tsl Filial Sp",Pedidos!$F$2:$F$2224,$A32),"") -> 0.14535132 | H32: =IFERROR(SUMIFS(Pedidos!$S$2:$S$2224,Pedidos!$X$2:$X$2224,"SIM",Pedidos!$I$2:$I$2224,"Tsl Filial Sp",Pedidos!$F$2:$F$2224,$A32)/SUMIFS(Pedidos!$H$2:$H$2224,Pedidos!$X$2:$X$2224,"SIM",Pedidos!$I$2:$I$2224,"Tsl Filial Sp",Pedidos!$F$2:$F$2224,$A32),"") -> 0.22259323 | I32: =IFERROR(COUNTIFS(Pedidos!$X$2:$X$2224,"SIM",Pedidos!$I$2:$I$2224,"Tsl Filial Sp",Pedidos!$F$2:$F$2224,$A32,Pedidos!$V$2:$V$2224,"SIM")/B32,"") -> 0 | J32: =IFERROR(AVERAGEIFS(Pedidos!$K$2:$K$2224,Pedidos!$X$2:$X$2224,"SIM",Pedidos!$I$2:$I$2224,"Tsl Filial Sp",Pedidos!$F$2:$F$2224,$A32),"") -> 242.1975 | K32: =IFERROR(MAX(0,1-D32/E32),"") -> 0.34700926
A33: 150-170 | B33: =COUNTIFS(Pedidos!$X$2:$X$2224,"SIM",Pedidos!$I$2:$I$2224,"Tsl Filial Sp",Pedidos!$F$2:$F$2224,$A33) -> 3 | C33: =IFERROR(AVERAGEIFS(Pedidos!$G$2:$G$2224,Pedidos!$X$2:$X$2224,"SIM",Pedidos!$I$2:$I$2224,"Tsl Filial Sp",Pedidos!$F$2:$F$2224,$A33),"") -> 160.63333 | D33: =IFERROR(AVERAGEIFS(Pedidos!$J$2:$J$2224,Pedidos!$X$2:$X$2224,"SIM",Pedidos!$I$2:$I$2224,"Tsl Filial Sp",Pedidos!$F$2:$F$2224,$A33),"") -> 259.73 | E33: =IFERROR(AVERAGEIFS(Pedidos!$S$2:$S$2224,Pedidos!$X$2:$X$2224,"SIM",Pedidos!$I$2:$I$2224,"Tsl Filial Sp",Pedidos!$F$2:$F$2224,$A33),"") -> 423.50102 | F33: =IFERROR(E33/D33-1,"") -> 0.63054334 | G33: =IFERROR(SUMIFS(Pedidos!$J$2:$J$2224,Pedidos!$X$2:$X$2224,"SIM",Pedidos!$I$2:$I$2224,"Tsl Filial Sp",Pedidos!$F$2:$F$2224,$A33)/SUMIFS(Pedidos!$H$2:$H$2224,Pedidos!$X$2:$X$2224,"SIM",Pedidos!$I$2:$I$2224,"Tsl Filial Sp",Pedidos!$F$2:$F$2224,$A33),"") -> 0.13604317 | H33: =IFERROR(SUMIFS(Pedidos!$S$2:$S$2224,Pedidos!$X$2:$X$2224,"SIM",Pedidos!$I$2:$I$2224,"Tsl Filial Sp",Pedidos!$F$2:$F$2224,$A33)/SUMIFS(Pedidos!$H$2:$H$2224,Pedidos!$X$2:$X$2224,"SIM",Pedidos!$I$2:$I$2224,"Tsl Filial Sp",Pedidos!$F$2:$F$2224,$A33),"") -> 0.22182429 | I33: =IFERROR(COUNTIFS(Pedidos!$X$2:$X$2224,"SIM",Pedidos!$I$2:$I$2224,"Tsl Filial Sp",Pedidos!$F$2:$F$2224,$A33,Pedidos!$V$2:$V$2224,"SIM")/B33,"") -> 0 | J33: =IFERROR(AVERAGEIFS(Pedidos!$K$2:$K$2224,Pedidos!$X$2:$X$2224,"SIM",Pedidos!$I$2:$I$2224,"Tsl Filial Sp",Pedidos!$F$2:$F$2224,$A33),"") -> 274.84333 | K33: =IFERROR(MAX(0,1-D33/E33),"") -> 0.3867075
A34: 170-200 | B34: =COUNTIFS(Pedidos!$X$2:$X$2224,"SIM",Pedidos!$I$2:$I$2224,"Tsl Filial Sp",Pedidos!$F$2:$F$2224,$A34) -> 1 | C34: =IFERROR(AVERAGEIFS(Pedidos!$G$2:$G$2224,Pedidos!$X$2:$X$2224,"SIM",Pedidos!$I$2:$I$2224,"Tsl Filial Sp",Pedidos!$F$2:$F$2224,$A34),"") -> 188.4 | D34: =IFERROR(AVERAGEIFS(Pedidos!$J$2:$J$2224,Pedidos!$X$2:$X$2224,"SIM",Pedidos!$I$2:$I$2224,"Tsl Filial Sp",Pedidos!$F$2:$F$2224,$A34),"") -> 198.28 | E34: =IFERROR(AVERAGEIFS(Pedidos!$S$2:$S$2224,Pedidos!$X$2:$X$2224,"SIM",Pedidos!$I$2:$I$2224,"Tsl Filial Sp",Pedidos!$F$2:$F$2224,$A34),"") -> 529.025 | F34: =IFERROR(E34/D34-1,"") -> 1.6680704 | G34: =IFERROR(SUMIFS(Pedidos!$J$2:$J$2224,Pedidos!$X$2:$X$2224,"SIM",Pedidos!$I$2:$I$2224,"Tsl Filial Sp",Pedidos!$F$2:$F$2224,$A34)/SUMIFS(Pedidos!$H$2:$H$2224,Pedidos!$X$2:$X$2224,"SIM",Pedidos!$I$2:$I$2224,"Tsl Filial Sp",Pedidos!$F$2:$F$2224,$A34),"") -> 0.099438315 | H34: =IFERROR(SUMIFS(Pedidos!$S$2:$S$2224,Pedidos!$X$2:$X$2224,"SIM",Pedidos!$I$2:$I$2224,"Tsl Filial Sp",Pedidos!$F$2:$F$2224,$A34)/SUMIFS(Pedidos!$H$2:$H$2224,Pedidos!$X$2:$X$2224,"SIM",Pedidos!$I$2:$I$2224,"Tsl Filial Sp",Pedidos!$F$2:$F$2224,$A34),"") -> 0.26530843 | I34: =IFERROR(COUNTIFS(Pedidos!$X$2:$X$2224,"SIM",Pedidos!$I$2:$I$2224,"Tsl Filial Sp",Pedidos!$F$2:$F$2224,$A34,Pedidos!$V$2:$V$2224,"SIM")/B34,"") -> 0 | J34: =IFERROR(AVERAGEIFS(Pedidos!$K$2:$K$2224,Pedidos!$X$2:$X$2224,"SIM",Pedidos!$I$2:$I$2224,"Tsl Filial Sp",Pedidos!$F$2:$F$2224,$A34),"") -> 353.17 | K34: =IFERROR(MAX(0,1-D34/E34),"") -> 0.6251973
... A36: >250 | B36: =COUNTIFS(Pedidos!$X$2:$X$2224,"SIM",Pedidos!$I$2:$I$2224,"Tsl Filial Sp",Pedidos!$F$2:$F$2224,$A36) -> 0 | C36: =IFERROR(AVERAGEIFS(Pedidos!$G$2:$G$2224,Pedidos!$X$2:$X$2224,"SIM",Pedidos!$I$2:$I$2224,"Tsl Filial Sp",Pedidos!$F$2:$F$2224,$A36),"") | D36: =IFERROR(AVERAGEIFS(Pedidos!$J$2:$J$2224,Pedidos!$X$2:$X$2224,"SIM",Pedidos!$I$2:$I$2224,"Tsl Filial Sp",Pedidos!$F$2:$F$2224,$A36),"") | E36: =IFERROR(AVERAGEIFS(Pedidos!$S$2:$S$2224,Pedidos!$X$2:$X$2224,"SIM",Pedidos!$I$2:$I$2224,"Tsl Filial Sp",Pedidos!$F$2:$F$2224,$A36),"") | F36: =IFERROR(E36/D36-1,"") | G36: =IFERROR(SUMIFS(Pedidos!$J$2:$J$2224,Pedidos!$X$2:$X$2224,"SIM",Pedidos!$I$2:$I$2224,"Tsl Filial Sp",Pedidos!$F$2:$F$2224,$A36)/SUMIFS(Pedidos!$H$2:$H$2224,Pedidos!$X$2:$X$2224,"SIM",Pedidos!$I$2:$I$2224,"Tsl Filial Sp",Pedidos!$F$2:$F$2224,$A36),"") | H36: =IFERROR(SUMIFS(Pedidos!$S$2:$S$2224,Pedidos!$X$2:$X$2224,"SIM",Pedidos!$I$2:$I$2224,"Tsl Filial Sp",Pedidos!$F$2:$F$2224,$A36)/SUMIFS(Pedidos!$H$2:$H$2224,Pedidos!$X$2:$X$2224,"SIM",Pedidos!$I$2:$I$2224,"Tsl Filial Sp",Pedidos!$F$2:$F$2224,$A36),"") | I36: =IFERROR(COUNTIFS(Pedidos!$X$2:$X$2224,"SIM",Pedidos!$I$2:$I$2224,"Tsl Filial Sp",Pedidos!$F$2:$F$2224,$A36,Pedidos!$V$2:$V$2224,"SIM")/B36,"") | J36: =IFERROR(AVERAGEIFS(Pedidos!$K$2:$K$2224,Pedidos!$X$2:$X$2224,"SIM",Pedidos!$I$2:$I$2224,"Tsl Filial Sp",Pedidos!$F$2:$F$2224,$A36),"") | K36: =IFERROR(MAX(0,1-D36/E36),"")
A37: TOTAL | B37: =COUNTIFS(Pedidos!$X$2:$X$2224,"SIM",Pedidos!$I$2:$I$2224,"Tsl Filial Sp") -> 1420 | C37: =IFERROR(AVERAGEIFS(Pedidos!$G$2:$G$2224,Pedidos!$X$2:$X$2224,"SIM",Pedidos!$I$2:$I$2224,"Tsl Filial Sp"),"") -> 49.102007 | D37: =IFERROR(AVERAGEIFS(Pedidos!$J$2:$J$2224,Pedidos!$X$2:$X$2224,"SIM",Pedidos!$I$2:$I$2224,"Tsl Filial Sp"),"") -> 116.31056 | E37: =IFERROR(AVERAGEIFS(Pedidos!$S$2:$S$2224,Pedidos!$X$2:$X$2224,"SIM",Pedidos!$I$2:$I$2224,"Tsl Filial Sp"),"") -> 167.02312 | F37: =IFERROR(E37/D37-1,"") -> 0.43600996 | G37: =IFERROR(SUMIFS(Pedidos!$J$2:$J$2224,Pedidos!$X$2:$X$2224,"SIM",Pedidos!$I$2:$I$2224,"Tsl Filial Sp")/SUMIFS(Pedidos!$H$2:$H$2224,Pedidos!$X$2:$X$2224,"SIM",Pedidos!$I$2:$I$2224,"Tsl Filial Sp"),"") -> 0.18411323 | H37: =IFERROR(SUMIFS(Pedidos!$S$2:$S$2224,Pedidos!$X$2:$X$2224,"SIM",Pedidos!$I$2:$I$2224,"Tsl Filial Sp")/SUMIFS(Pedidos!$H$2:$H$2224,Pedidos!$X$2:$X$2224,"SIM",Pedidos!$I$2:$I$2224,"Tsl Filial Sp"),"") -> 0.26438844 | I37: =IFERROR(COUNTIFS(Pedidos!$X$2:$X$2224,"SIM",Pedidos!$I$2:$I$2224,"Tsl Filial Sp",Pedidos!$V$2:$V$2224,"SIM")/B37,"") -> 0.0056338028 | J37: =IFERROR(AVERAGEIFS(Pedidos!$K$2:$K$2224,Pedidos!$X$2:$X$2224,"SIM",Pedidos!$I$2:$I$2224,"Tsl Filial Sp"),"") -> 114.06585 | K37: =IFERROR(MAX(0,1-D37/E37),"") -> 0.303626
A39: Transportadora atual: Tsl Transportes
A40: Faixa (kg) | B40: Pedidos | C40: Peso médio | D40: Custo médio atual (R$) | E40: PROLOG médio (R$) | F40: PROLOG vs atual (%) | G40: Frete/NF atual | H40: Frete/NF PROLOG | I40: % pedidos PROLOG mais barata | J40: PROLOG só frete peso (R$) | K40: Desconto necessário p/ empatar
A41: 0-20 | B41: =COUNTIFS(Pedidos!$X$2:$X$2224,"SIM",Pedidos!$I$2:$I$2224,"Tsl Transportes",Pedidos!$F$2:$F$2224,$A41) -> 32 | C41: =IFERROR(AVERAGEIFS(Pedidos!$G$2:$G$2224,Pedidos!$X$2:$X$2224,"SIM",Pedidos!$I$2:$I$2224,"Tsl Transportes",Pedidos!$F$2:$F$2224,$A41),"") -> 18.25 | D41: =IFERROR(AVERAGEIFS(Pedidos!$J$2:$J$2224,Pedidos!$X$2:$X$2224,"SIM",Pedidos!$I$2:$I$2224,"Tsl Transportes",Pedidos!$F$2:$F$2224,$A41),"") -> 71.07625 | E41: =IFERROR(AVERAGEIFS(Pedidos!$S$2:$S$2224,Pedidos!$X$2:$X$2224,"SIM",Pedidos!$I$2:$I$2224,"Tsl Transportes",Pedidos!$F$2:$F$2224,$A41),"") -> 76.341335 | F41: =IFERROR(E41/D41-1,"") -> 0.074076576 | G41: =IFERROR(SUMIFS(Pedidos!$J$2:$J$2224,Pedidos!$X$2:$X$2224,"SIM",Pedidos!$I$2:$I$2224,"Tsl Transportes",Pedidos!$F$2:$F$2224,$A41)/SUMIFS(Pedidos!$H$2:$H$2224,Pedidos!$X$2:$X$2224,"SIM",Pedidos!$I$2:$I$2224,"Tsl Transportes",Pedidos!$F$2:$F$2224,$A41),"") -> 0.22188684 | H41: =IFERROR(SUMIFS(Pedidos!$S$2:$S$2224,Pedidos!$X$2:$X$2224,"SIM",Pedidos!$I$2:$I$2224,"Tsl Transportes",Pedidos!$F$2:$F$2224,$A41)/SUMIFS(Pedidos!$H$2:$H$2224,Pedidos!$X$2:$X$2224,"SIM",Pedidos!$I$2:$I$2224,"Tsl Transportes",Pedidos!$F$2:$F$2224,$A41),"") -> 0.23832346 | I41: =IFERROR(COUNTIFS(Pedidos!$X$2:$X$2224,"SIM",Pedidos!$I$2:$I$2224,"Tsl Transportes",Pedidos!$F$2:$F$2224,$A41,Pedidos!$V$2:$V$2224,"SIM")/B41,"") -> 0.1875 | J41: =IFERROR(AVERAGEIFS(Pedidos!$K$2:$K$2224,Pedidos!$X$2:$X$2224,"SIM",Pedidos!$I$2:$I$2224,"Tsl Transportes",Pedidos!$F$2:$F$2224,$A41),"") -> 51.172812 | K41: =IFERROR(MAX(0,1-D41/E41),"") -> 0.068967686
A42: 20-35 | B42: =COUNTIFS(Pedidos!$X$2:$X$2224,"SIM",Pedidos!$I$2:$I$2224,"Tsl Transportes",Pedidos!$F$2:$F$2224,$A42) -> 77 | C42: =IFERROR(AVERAGEIFS(Pedidos!$G$2:$G$2224,Pedidos!$X$2:$X$2224,"SIM",Pedidos!$I$2:$I$2224,"Tsl Transportes",Pedidos!$F$2:$F$2224,$A42),"") -> 28.903506 | D42: =IFERROR(AVERAGEIFS(Pedidos!$J$2:$J$2224,Pedidos!$X$2:$X$2224,"SIM",Pedidos!$I$2:$I$2224,"Tsl Transportes",Pedidos!$F$2:$F$2224,$A42),"") -> 94.671818 | E42: =IFERROR(AVERAGEIFS(Pedidos!$S$2:$S$2224,Pedidos!$X$2:$X$2224,"SIM",Pedidos!$I$2:$I$2224,"Tsl Transportes",Pedidos!$F$2:$F$2224,$A42),"") -> 134.3675 | F42: =IFERROR(E42/D42-1,"") -> 0.41929781 | G42: =IFERROR(SUMIFS(Pedidos!$J$2:$J$2224,Pedidos!$X$2:$X$2224,"SIM",Pedidos!$I$2:$I$2224,"Tsl Transportes",Pedidos!$F$2:$F$2224,$A42)/SUMIFS(Pedidos!$H$2:$H$2224,Pedidos!$X$2:$X$2224,"SIM",Pedidos!$I$2:$I$2224,"Tsl Transportes",Pedidos!$F$2:$F$2224,$A42),"") -> 0.22413773 | H42: =IFERROR(SUMIFS(Pedidos!$S$2:$S$2224,Pedidos!$X$2:$X$2224,"SIM",Pedidos!$I$2:$I$2224,"Tsl Transportes",Pedidos!$F$2:$F$2224,$A42)/SUMIFS(Pedidos!$H$2:$H$2224,Pedidos!$X$2:$X$2224,"SIM",Pedidos!$I$2:$I$2224,"Tsl Transportes",Pedidos!$F$2:$F$2224,$A42),"") -> 0.31811819 | I42: =IFERROR(COUNTIFS(Pedidos!$X$2:$X$2224,"SIM",Pedidos!$I$2:$I$2224,"Tsl Transportes",Pedidos!$F$2:$F$2224,$A42,Pedidos!$V$2:$V$2224,"SIM")/B42,"") -> 0 | J42: =IFERROR(AVERAGEIFS(Pedidos!$K$2:$K$2224,Pedidos!$X$2:$X$2224,"SIM",Pedidos!$I$2:$I$2224,"Tsl Transportes",Pedidos!$F$2:$F$2224,$A42),"") -> 96.56039 | K42: =IFERROR(MAX(0,1-D42/E42),"") -> 0.29542624
A43: 35-40 | B43: =COUNTIFS(Pedidos!$X$2:$X$2224,"SIM",Pedidos!$I$2:$I$2224,"Tsl Transportes",Pedidos!$F$2:$F$2224,$A43) -> 68 | C43: =IFERROR(AVERAGEIFS(Pedidos!$G$2:$G$2224,Pedidos!$X$2:$X$2224,"SIM",Pedidos!$I$2:$I$2224,"Tsl Transportes",Pedidos!$F$2:$F$2224,$A43),"") -> 37.611471 | D43: =IFERROR(AVERAGEIFS(Pedidos!$J$2:$J$2224,Pedidos!$X$2:$X$2224,"SIM",Pedidos!$I$2:$I$2224,"Tsl Transportes",Pedidos!$F$2:$F$2224,$A43),"") -> 109.97471 | E43: =IFERROR(AVERAGEIFS(Pedidos!$S$2:$S$2224,Pedidos!$X$2:$X$2224,"SIM",Pedidos!$I$2:$I$2224,"Tsl Transportes",Pedidos!$F$2:$F$2224,$A43),"") -> 153.60242 | F43: =IFERROR(E43/D43-1,"") -> 0.39670682 | G43: =IFERROR(SUMIFS(Pedidos!$J$2:$J$2224,Pedidos!$X$2:$X$2224,"SIM",Pedidos!$I$2:$I$2224,"Tsl Transportes",Pedidos!$F$2:$F$2224,$A43)/SUMIFS(Pedidos!$H$2:$H$2224,Pedidos!$X$2:$X$2224,"SIM",Pedidos!$I$2:$I$2224,"Tsl Transportes",Pedidos!$F$2:$F$2224,$A43),"") -> 0.23763852 | H43: =IFERROR(SUMIFS(Pedidos!$S$2:$S$2224,Pedidos!$X$2:$X$2224,"SIM",Pedidos!$I$2:$I$2224,"Tsl Transportes",Pedidos!$F$2:$F$2224,$A43)/SUMIFS(Pedidos!$H$2:$H$2224,Pedidos!$X$2:$X$2224,"SIM",Pedidos!$I$2:$I$2224,"Tsl Transportes",Pedidos!$F$2:$F$2224,$A43),"") -> 0.33191135 | I43: =IFERROR(COUNTIFS(Pedidos!$X$2:$X$2224,"SIM",Pedidos!$I$2:$I$2224,"Tsl Transportes",Pedidos!$F$2:$F$2224,$A43,Pedidos!$V$2:$V$2224,"SIM")/B43,"") -> 0 | J43: =IFERROR(AVERAGEIFS(Pedidos!$K$2:$K$2224,Pedidos!$X$2:$X$2224,"SIM",Pedidos!$I$2:$I$2224,"Tsl Transportes",Pedidos!$F$2:$F$2224,$A43),"") -> 108.91676 | K43: =IFERROR(MAX(0,1-D43/E43),"") -> 0.28403013
A44: 40-50 | B44: =COUNTIFS(Pedidos!$X$2:$X$2224,"SIM",Pedidos!$I$2:$I$2224,"Tsl Transportes",Pedidos!$F$2:$F$2224,$A44) -> 75 | C44: =IFERROR(AVERAGEIFS(Pedidos!$G$2:$G$2224,Pedidos!$X$2:$X$2224,"SIM",Pedidos!$I$2:$I$2224,"Tsl Transportes",Pedidos!$F$2:$F$2224,$A44),"") -> 45.329333 | D44: =IFERROR(AVERAGEIFS(Pedidos!$J$2:$J$2224,Pedidos!$X$2:$X$2224,"SIM",Pedidos!$I$2:$I$2224,"Tsl Transportes",Pedidos!$F$2:$F$2224,$A44),"") -> 118.77107 | E44: =IFERROR(AVERAGEIFS(Pedidos!$S$2:$S$2224,Pedidos!$X$2:$X$2224,"SIM",Pedidos!$I$2:$I$2224,"Tsl Transportes",Pedidos!$F$2:$F$2224,$A44),"") -> 160.3945 | F44: =IFERROR(E44/D44-1,"") -> 0.35045091 | G44: =IFERROR(SUMIFS(Pedidos!$J$2:$J$2224,Pedidos!$X$2:$X$2224,"SIM",Pedidos!$I$2:$I$2224,"Tsl Transportes",Pedidos!$F$2:$F$2224,$A44)/SUMIFS(Pedidos!$H$2:$H$2224,Pedidos!$X$2:$X$2224,"SIM",Pedidos!$I$2:$I$2224,"Tsl Transportes",Pedidos!$F$2:$F$2224,$A44),"") -> 0.20244258 | H44: =IFERROR(SUMIFS(Pedidos!$S$2:$S$2224,Pedidos!$X$2:$X$2224,"SIM",Pedidos!$I$2:$I$2224,"Tsl Transportes",Pedidos!$F$2:$F$2224,$A44)/SUMIFS(Pedidos!$H$2:$H$2224,Pedidos!$X$2:$X$2224,"SIM",Pedidos!$I$2:$I$2224,"Tsl Transportes",Pedidos!$F$2:$F$2224,$A44),"") -> 0.27338877 | I44: =IFERROR(COUNTIFS(Pedidos!$X$2:$X$2224,"SIM",Pedidos!$I$2:$I$2224,"Tsl Transportes",Pedidos!$F$2:$F$2224,$A44,Pedidos!$V$2:$V$2224,"SIM")/B44,"") -> 0 | J44: =IFERROR(AVERAGEIFS(Pedidos!$K$2:$K$2224,Pedidos!$X$2:$X$2224,"SIM",Pedidos!$I$2:$I$2224,"Tsl Transportes",Pedidos!$F$2:$F$2224,$A44),"") -> 110.58347 | K44: =IFERROR(MAX(0,1-D44/E44),"") -> 0.25950659
A45: 50-60 | B45: =COUNTIFS(Pedidos!$X$2:$X$2224,"SIM",Pedidos!$I$2:$I$2224,"Tsl Transportes",Pedidos!$F$2:$F$2224,$A45) -> 131 | C45: =IFERROR(AVERAGEIFS(Pedidos!$G$2:$G$2224,Pedidos!$X$2:$X$2224,"SIM",Pedidos!$I$2:$I$2224,"Tsl Transportes",Pedidos!$F$2:$F$2224,$A45),"") -> 53.54687 | D45: =IFERROR(AVERAGEIFS(Pedidos!$J$2:$J$2224,Pedidos!$X$2:$X$2224,"SIM",Pedidos!$I$2:$I$2224,"Tsl Transportes",Pedidos!$F$2:$F$2224,$A45),"") -> 127.70786 | E45: =IFERROR(AVERAGEIFS(Pedidos!$S$2:$S$2224,Pedidos!$X$2:$X$2224,"SIM",Pedidos!$I$2:$I$2224,"Tsl Transportes",Pedidos!$F$2:$F$2224,$A45),"") -> 180.44643 | F45: =IFERROR(E45/D45-1,"") -> 0.4129626 | G45: =IFERROR(SUMIFS(Pedidos!$J$2:$J$2224,Pedidos!$X$2:$X$2224,"SIM",Pedidos!$I$2:$I$2224,"Tsl Transportes",Pedidos!$F$2:$F$2224,$A45)/SUMIFS(Pedidos!$H$2:$H$2224,Pedidos!$X$2:$X$2224,"SIM",Pedidos!$I$2:$I$2224,"Tsl Transportes",Pedidos!$F$2:$F$2224,$A45),"") -> 0.18237177 | H45: =IFERROR(SUMIFS(Pedidos!$S$2:$S$2224,Pedidos!$X$2:$X$2224,"SIM",Pedidos!$I$2:$I$2224,"Tsl Transportes",Pedidos!$F$2:$F$2224,$A45)/SUMIFS(Pedidos!$H$2:$H$2224,Pedidos!$X$2:$X$2224,"SIM",Pedidos!$I$2:$I$2224,"Tsl Transportes",Pedidos!$F$2:$F$2224,$A45),"") -> 0.25768449 | I45: =IFERROR(COUNTIFS(Pedidos!$X$2:$X$2224,"SIM",Pedidos!$I$2:$I$2224,"Tsl Transportes",Pedidos!$F$2:$F$2224,$A45,Pedidos!$V$2:$V$2224,"SIM")/B45,"") -> 0 | J45: =IFERROR(AVERAGEIFS(Pedidos!$K$2:$K$2224,Pedidos!$X$2:$X$2224,"SIM",Pedidos!$I$2:$I$2224,"Tsl Transportes",Pedidos!$F$2:$F$2224,$A45),"") -> 123.58198 | K45: =IFERROR(MAX(0,1-D45/E45),"") -> 0.29226719
A46: 60-70 | B46: =COUNTIFS(Pedidos!$X$2:$X$2224,"SIM",Pedidos!$I$2:$I$2224,"Tsl Transportes",Pedidos!$F$2:$F$2224,$A46) -> 50 | C46: =IFERROR(AVERAGEIFS(Pedidos!$G$2:$G$2224,Pedidos!$X$2:$X$2224,"SIM",Pedidos!$I$2:$I$2224,"Tsl Transportes",Pedidos!$F$2:$F$2224,$A46),"") -> 65.189 | D46: =IFERROR(AVERAGEIFS(Pedidos!$J$2:$J$2224,Pedidos!$X$2:$X$2224,"SIM",Pedidos!$I$2:$I$2224,"Tsl Transportes",Pedidos!$F$2:$F$2224,$A46),"") -> 144.1524 | E46: =IFERROR(AVERAGEIFS(Pedidos!$S$2:$S$2224,Pedidos!$X$2:$X$2224,"SIM",Pedidos!$I$2:$I$2224,"Tsl Transportes",Pedidos!$F$2:$F$2224,$A46),"") -> 216.02545 | F46: =IFERROR(E46/D46-1,"") -> 0.49859071 | G46: =IFERROR(SUMIFS(Pedidos!$J$2:$J$2224,Pedidos!$X$2:$X$2224,"SIM",Pedidos!$I$2:$I$2224,"Tsl Transportes",Pedidos!$F$2:$F$2224,$A46)/SUMIFS(Pedidos!$H$2:$H$2224,Pedidos!$X$2:$X$2224,"SIM",Pedidos!$I$2:$I$2224,"Tsl Transportes",Pedidos!$F$2:$F$2224,$A46),"") -> 0.19121997 | H46: =IFERROR(SUMIFS(Pedidos!$S$2:$S$2224,Pedidos!$X$2:$X$2224,"SIM",Pedidos!$I$2:$I$2224,"Tsl Transportes",Pedidos!$F$2:$F$2224,$A46)/SUMIFS(Pedidos!$H$2:$H$2224,Pedidos!$X$2:$X$2224,"SIM",Pedidos!$I$2:$I$2224,"Tsl Transportes",Pedidos!$F$2:$F$2224,$A46),"") -> 0.28656047 | I46: =IFERROR(COUNTIFS(Pedidos!$X$2:$X$2224,"SIM",Pedidos!$I$2:$I$2224,"Tsl Transportes",Pedidos!$F$2:$F$2224,$A46,Pedidos!$V$2:$V$2224,"SIM")/B46,"") -> 0 | J46: =IFERROR(AVERAGEIFS(Pedidos!$K$2:$K$2224,Pedidos!$X$2:$X$2224,"SIM",Pedidos!$I$2:$I$2224,"Tsl Transportes",Pedidos!$F$2:$F$2224,$A46),"") -> 148.946 | K46: =IFERROR(MAX(0,1-D46/E46),"") -> 0.33270639
A47: 70-80 | B47: =COUNTIFS(Pedidos!$X$2:$X$2224,"SIM",Pedidos!$I$2:$I$2224,"Tsl Transportes",Pedidos!$F$2:$F$2224,$A47) -> 5 | C47: =IFERROR(AVERAGEIFS(Pedidos!$G$2:$G$2224,Pedidos!$X$2:$X$2224,"SIM",Pedidos!$I$2:$I$2224,"Tsl Transportes",Pedidos!$F$2:$F$2224,$A47),"") -> 75.34 | D47: =IFERROR(AVERAGEIFS(Pedidos!$J$2:$J$2224,Pedidos!$X$2:$X$2224,"SIM",Pedidos!$I$2:$I$2224,"Tsl Transportes",Pedidos!$F$2:$F$2224,$A47),"") -> 153.752 | E47: =IFERROR(AVERAGEIFS(Pedidos!$S$2:$S$2224,Pedidos!$X$2:$X$2224,"SIM",Pedidos!$I$2:$I$2224,"Tsl Transportes",Pedidos!$F$2:$F$2224,$A47),"") -> 209.8723 | F47: =IFERROR(E47/D47-1,"") -> 0.3650053 | G47: =IFERROR(SUMIFS(Pedidos!$J$2:$J$2224,Pedidos!$X$2:$X$2224,"SIM",Pedidos!$I$2:$I$2224,"Tsl Transportes",Pedidos!$F$2:$F$2224,$A47)/SUMIFS(Pedidos!$H$2:$H$2224,Pedidos!$X$2:$X$2224,"SIM",Pedidos!$I$2:$I$2224,"Tsl Transportes",Pedidos!$F$2:$F$2224,$A47),"") -> 0.15896609 | H47: =IFERROR(SUMIFS(Pedidos!$S$2:$S$2224,Pedidos!$X$2:$X$2224,"SIM",Pedidos!$I$2:$I$2224,"Tsl Transportes",Pedidos!$F$2:$F$2224,$A47)/SUMIFS(Pedidos!$H$2:$H$2224,Pedidos!$X$2:$X$2224,"SIM",Pedidos!$I$2:$I$2224,"Tsl Transportes",Pedidos!$F$2:$F$2224,$A47),"") -> 0.21698955 | I47: =IFERROR(COUNTIFS(Pedidos!$X$2:$X$2224,"SIM",Pedidos!$I$2:$I$2224,"Tsl Transportes",Pedidos!$F$2:$F$2224,$A47,Pedidos!$V$2:$V$2224,"SIM")/B47,"") -> 0 | J47: =IFERROR(AVERAGEIFS(Pedidos!$K$2:$K$2224,Pedidos!$X$2:$X$2224,"SIM",Pedidos!$I$2:$I$2224,"Tsl Transportes",Pedidos!$F$2:$F$2224,$A47),"") -> 137.73 | K47: =IFERROR(MAX(0,1-D47/E47),"") -> 0.26740211
A48: 80-100 | B48: =COUNTIFS(Pedidos!$X$2:$X$2224,"SIM",Pedidos!$I$2:$I$2224,"Tsl Transportes",Pedidos!$F$2:$F$2224,$A48) -> 5 | C48: =IFERROR(AVERAGEIFS(Pedidos!$G$2:$G$2224,Pedidos!$X$2:$X$2224,"SIM",Pedidos!$I$2:$I$2224,"Tsl Transportes",Pedidos!$F$2:$F$2224,$A48),"") -> 84.1 | D48: =IFERROR(AVERAGEIFS(Pedidos!$J$2:$J$2224,Pedidos!$X$2:$X$2224,"SIM",Pedidos!$I$2:$I$2224,"Tsl Transportes",Pedidos!$F$2:$F$2224,$A48),"") -> 176.928 | E48: =IFERROR(AVERAGEIFS(Pedidos!$S$2:$S$2224,Pedidos!$X$2:$X$2224,"SIM",Pedidos!$I$2:$I$2224,"Tsl Transportes",Pedidos!$F$2:$F$2224,$A48),"") -> 258.85816 | F48: =IFERROR(E48/D48-1,"") -> 0.46307062 | G48: =IFERROR(SUMIFS(Pedidos!$J$2:$J$2224,Pedidos!$X$2:$X$2224,"SIM",Pedidos!$I$2:$I$2224,"Tsl Transportes",Pedidos!$F$2:$F$2224,$A48)/SUMIFS(Pedidos!$H$2:$H$2224,Pedidos!$X$2:$X$2224,"SIM",Pedidos!$I$2:$I$2224,"Tsl Transportes",Pedidos!$F$2:$F$2224,$A48),"") -> 0.19195376 | H48: =IFERROR(SUMIFS(Pedidos!$S$2:$S$2224,Pedidos!$X$2:$X$2224,"SIM",Pedidos!$I$2:$I$2224,"Tsl Transportes",Pedidos!$F$2:$F$2224,$A48)/SUMIFS(Pedidos!$H$2:$H$2224,Pedidos!$X$2:$X$2224,"SIM",Pedidos!$I$2:$I$2224,"Tsl Transportes",Pedidos!$F$2:$F$2224,$A48),"") -> 0.2808419 | I48: =IFERROR(COUNTIFS(Pedidos!$X$2:$X$2224,"SIM",Pedidos!$I$2:$I$2224,"Tsl Transportes",Pedidos!$F$2:$F$2224,$A48,Pedidos!$V$2:$V$2224,"SIM")/B48,"") -> 0 | J48: =IFERROR(AVERAGEIFS(Pedidos!$K$2:$K$2224,Pedidos!$X$2:$X$2224,"SIM",Pedidos!$I$2:$I$2224,"Tsl Transportes",Pedidos!$F$2:$F$2224,$A48),"") -> 176.486 | K48: =IFERROR(MAX(0,1-D48/E48),"") -> 0.31650599
A49: 100-120 | B49: =COUNTIFS(Pedidos!$X$2:$X$2224,"SIM",Pedidos!$I$2:$I$2224,"Tsl Transportes",Pedidos!$F$2:$F$2224,$A49) -> 12 | C49: =IFERROR(AVERAGEIFS(Pedidos!$G$2:$G$2224,Pedidos!$X$2:$X$2224,"SIM",Pedidos!$I$2:$I$2224,"Tsl Transportes",Pedidos!$F$2:$F$2224,$A49),"") -> 110.59167 | D49: =IFERROR(AVERAGEIFS(Pedidos!$J$2:$J$2224,Pedidos!$X$2:$X$2224,"SIM",Pedidos!$I$2:$I$2224,"Tsl Transportes",Pedidos!$F$2:$F$2224,$A49),"") -> 201.43917 | E49: =IFERROR(AVERAGEIFS(Pedidos!$S$2:$S$2224,Pedidos!$X$2:$X$2224,"SIM",Pedidos!$I$2:$I$2224,"Tsl Transportes",Pedidos!$F$2:$F$2224,$A49),"") -> 324.56123 | F49: =IFERROR(E49/D49-1,"") -> 0.61121214 | G49: =IFERROR(SUMIFS(Pedidos!$J$2:$J$2224,Pedidos!$X$2:$X$2224,"SIM",Pedidos!$I$2:$I$2224,"Tsl Transportes",Pedidos!$F$2:$F$2224,$A49)/SUMIFS(Pedidos!$H$2:$H$2224,Pedidos!$X$2:$X$2224,"SIM",Pedidos!$I$2:$I$2224,"Tsl Transportes",Pedidos!$F$2:$F$2224,$A49),"") -> 0.16664518 | H49: =IFERROR(SUMIFS(Pedidos!$S$2:$S$2224,Pedidos!$X$2:$X$2224,"SIM",Pedidos!$I$2:$I$2224,"Tsl Transportes",Pedidos!$F$2:$F$2224,$A49)/SUMIFS(Pedidos!$H$2:$H$2224,Pedidos!$X$2:$X$2224,"SIM",Pedidos!$I$2:$I$2224,"Tsl Transportes",Pedidos!$F$2:$F$2224,$A49),"") -> 0.26850074 | I49: =IFERROR(COUNTIFS(Pedidos!$X$2:$X$2224,"SIM",Pedidos!$I$2:$I$2224,"Tsl Transportes",Pedidos!$F$2:$F$2224,$A49,Pedidos!$V$2:$V$2224,"SIM")/B49,"") -> 0 | J49: =IFERROR(AVERAGEIFS(Pedidos!$K$2:$K$2224,Pedidos!$X$2:$X$2224,"SIM",Pedidos!$I$2:$I$2224,"Tsl Transportes",Pedidos!$F$2:$F$2224,$A49),"") -> 215.42 | K49: =IFERROR(MAX(0,1-D49/E49),"") -> 0.37934926
A50: 120-150 | B50: =COUNTIFS(Pedidos!$X$2:$X$2224,"SIM",Pedidos!$I$2:$I$2224,"Tsl Transportes",Pedidos!$F$2:$F$2224,$A50) -> 25 | C50: =IFERROR(AVERAGEIFS(Pedidos!$G$2:$G$2224,Pedidos!$X$2:$X$2224,"SIM",Pedidos!$I$2:$I$2224,"Tsl Transportes",Pedidos!$F$2:$F$2224,$A50),"") -> 129.036 | D50: =IFERROR(AVERAGEIFS(Pedidos!$J$2:$J$2224,Pedidos!$X$2:$X$2224,"SIM",Pedidos!$I$2:$I$2224,"Tsl Transportes",Pedidos!$F$2:$F$2224,$A50),"") -> 243.2164 | E50: =IFERROR(AVERAGEIFS(Pedidos!$S$2:$S$2224,Pedidos!$X$2:$X$2224,"SIM",Pedidos!$I$2:$I$2224,"Tsl Transportes",Pedidos!$F$2:$F$2224,$A50),"") -> 374.76476 | F50: =IFERROR(E50/D50-1,"") -> 0.54086963 | G50: =IFERROR(SUMIFS(Pedidos!$J$2:$J$2224,Pedidos!$X$2:$X$2224,"SIM",Pedidos!$I$2:$I$2224,"Tsl Transportes",Pedidos!$F$2:$F$2224,$A50)/SUMIFS(Pedidos!$H$2:$H$2224,Pedidos!$X$2:$X$2224,"SIM",Pedidos!$I$2:$I$2224,"Tsl Transportes",Pedidos!$F$2:$F$2224,$A50),"") -> 0.14847901 | H50: =IFERROR(SUMIFS(Pedidos!$S$2:$S$2224,Pedidos!$X$2:$X$2224,"SIM",Pedidos!$I$2:$I$2224,"Tsl Transportes",Pedidos!$F$2:$F$2224,$A50)/SUMIFS(Pedidos!$H$2:$H$2224,Pedidos!$X$2:$X$2224,"SIM",Pedidos!$I$2:$I$2224,"Tsl Transportes",Pedidos!$F$2:$F$2224,$A50),"") -> 0.2287868 | I50: =IFERROR(COUNTIFS(Pedidos!$X$2:$X$2224,"SIM",Pedidos!$I$2:$I$2224,"Tsl Transportes",Pedidos!$F$2:$F$2224,$A50,Pedidos!$V$2:$V$2224,"SIM")/B50,"") -> 0 | J50: =IFERROR(AVERAGEIFS(Pedidos!$K$2:$K$2224,Pedidos!$X$2:$X$2224,"SIM",Pedidos!$I$2:$I$2224,"Tsl Transportes",Pedidos!$F$2:$F$2224,$A50),"") -> 248.7624 | K50: =IFERROR(MAX(0,1-D50/E50),"") -> 0.35101583
A51: 150-170 | B51: =COUNTIFS(Pedidos!$X$2:$X$2224,"SIM",Pedidos!$I$2:$I$2224,"Tsl Transportes",Pedidos!$F$2:$F$2224,$A51) -> 0 | C51: =IFERROR(AVERAGEIFS(Pedidos!$G$2:$G$2224,Pedidos!$X$2:$X$2224,"SIM",Pedidos!$I$2:$I$2224,"Tsl Transportes",Pedidos!$F$2:$F$2224,$A51),"") | D51: =IFERROR(AVERAGEIFS(Pedidos!$J$2:$J$2224,Pedidos!$X$2:$X$2224,"SIM",Pedidos!$I$2:$I$2224,"Tsl Transportes",Pedidos!$F$2:$F$2224,$A51),"") | E51: =IFERROR(AVERAGEIFS(Pedidos!$S$2:$S$2224,Pedidos!$X$2:$X$2224,"SIM",Pedidos!$I$2:$I$2224,"Tsl Transportes",Pedidos!$F$2:$F$2224,$A51),"") | F51: =IFERROR(E51/D51-1,"") | G51: =IFERROR(SUMIFS(Pedidos!$J$2:$J$2224,Pedidos!$X$2:$X$2224,"SIM",Pedidos!$I$2:$I$2224,"Tsl Transportes",Pedidos!$F$2:$F$2224,$A51)/SUMIFS(Pedidos!$H$2:$H$2224,Pedidos!$X$2:$X$2224,"SIM",Pedidos!$I$2:$I$2224,"Tsl Transportes",Pedidos!$F$2:$F$2224,$A51),"") | H51: =IFERROR(SUMIFS(Pedidos!$S$2:$S$2224,Pedidos!$X$2:$X$2224,"SIM",Pedidos!$I$2:$I$2224,"Tsl Transportes",Pedidos!$F$2:$F$2224,$A51)/SUMIFS(Pedidos!$H$2:$H$2224,Pedidos!$X$2:$X$2224,"SIM",Pedidos!$I$2:$I$2224,"Tsl Transportes",Pedidos!$F$2:$F$2224,$A51),"") | I51: =IFERROR(COUNTIFS(Pedidos!$X$2:$X$2224,"SIM",Pedidos!$I$2:$I$2224,"Tsl Transportes",Pedidos!$F$2:$F$2224,$A51,Pedidos!$V$2:$V$2224,"SIM")/B51,"") | J51: =IFERROR(AVERAGEIFS(Pedidos!$K$2:$K$2224,Pedidos!$X$2:$X$2224,"SIM",Pedidos!$I$2:$I$2224,"Tsl Transportes",Pedidos!$F$2:$F$2224,$A51),"") | K51: =IFERROR(MAX(0,1-D51/E51),"")
A52: 170-200 | B52: =COUNTIFS(Pedidos!$X$2:$X$2224,"SIM",Pedidos!$I$2:$I$2224,"Tsl Transportes",Pedidos!$F$2:$F$2224,$A52) -> 0 | C52: =IFERROR(AVERAGEIFS(Pedidos!$G$2:$G$2224,Pedidos!$X$2:$X$2224,"SIM",Pedidos!$I$2:$I$2224,"Tsl Transportes",Pedidos!$F$2:$F$2224,$A52),"") | D52: =IFERROR(AVERAGEIFS(Pedidos!$J$2:$J$2224,Pedidos!$X$2:$X$2224,"SIM",Pedidos!$I$2:$I$2224,"Tsl Transportes",Pedidos!$F$2:$F$2224,$A52),"") | E52: =IFERROR(AVERAGEIFS(Pedidos!$S$2:$S$2224,Pedidos!$X$2:$X$2224,"SIM",Pedidos!$I$2:$I$2224,"Tsl Transportes",Pedidos!$F$2:$F$2224,$A52),"") | F52: =IFERROR(E52/D52-1,"") | G52: =IFERROR(SUMIFS(Pedidos!$J$2:$J$2224,Pedidos!$X$2:$X$2224,"SIM",Pedidos!$I$2:$I$2224,"Tsl Transportes",Pedidos!$F$2:$F$2224,$A52)/SUMIFS(Pedidos!$H$2:$H$2224,Pedidos!$X$2:$X$2224,"SIM",Pedidos!$I$2:$I$2224,"Tsl Transportes",Pedidos!$F$2:$F$2224,$A52),"") | H52: =IFERROR(SUMIFS(Pedidos!$S$2:$S$2224,Pedidos!$X$2:$X$2224,"SIM",Pedidos!$I$2:$I$2224,"Tsl Transportes",Pedidos!$F$2:$F$2224,$A52)/SUMIFS(Pedidos!$H$2:$H$2224,Pedidos!$X$2:$X$2224,"SIM",Pedidos!$I$2:$I$2224,"Tsl Transportes",Pedidos!$F$2:$F$2224,$A52),"") | I52: =IFERROR(COUNTIFS(Pedidos!$X$2:$X$2224,"SIM",Pedidos!$I$2:$I$2224,"Tsl Transportes",Pedidos!$F$2:$F$2224,$A52,Pedidos!$V$2:$V$2224,"SIM")/B52,"") | J52: =IFERROR(AVERAGEIFS(Pedidos!$K$2:$K$2224,Pedidos!$X$2:$X$2224,"SIM",Pedidos!$I$2:$I$2224,"Tsl Transportes",Pedidos!$F$2:$F$2224,$A52),"") | K52: =IFERROR(MAX(0,1-D52/E52),"")
... A54: >250 | B54: =COUNTIFS(Pedidos!$X$2:$X$2224,"SIM",Pedidos!$I$2:$I$2224,"Tsl Transportes",Pedidos!$F$2:$F$2224,$A54) -> 0 | C54: =IFERROR(AVERAGEIFS(Pedidos!$G$2:$G$2224,Pedidos!$X$2:$X$2224,"SIM",Pedidos!$I$2:$I$2224,"Tsl Transportes",Pedidos!$F$2:$F$2224,$A54),"") | D54: =IFERROR(AVERAGEIFS(Pedidos!$J$2:$J$2224,Pedidos!$X$2:$X$2224,"SIM",Pedidos!$I$2:$I$2224,"Tsl Transportes",Pedidos!$F$2:$F$2224,$A54),"") | E54: =IFERROR(AVERAGEIFS(Pedidos!$S$2:$S$2224,Pedidos!$X$2:$X$2224,"SIM",Pedidos!$I$2:$I$2224,"Tsl Transportes",Pedidos!$F$2:$F$2224,$A54),"") | F54: =IFERROR(E54/D54-1,"") | G54: =IFERROR(SUMIFS(Pedidos!$J$2:$J$2224,Pedidos!$X$2:$X$2224,"SIM",Pedidos!$I$2:$I$2224,"Tsl Transportes",Pedidos!$F$2:$F$2224,$A54)/SUMIFS(Pedidos!$H$2:$H$2224,Pedidos!$X$2:$X$2224,"SIM",Pedidos!$I$2:$I$2224,"Tsl Transportes",Pedidos!$F$2:$F$2224,$A54),"") | H54: =IFERROR(SUMIFS(Pedidos!$S$2:$S$2224,Pedidos!$X$2:$X$2224,"SIM",Pedidos!$I$2:$I$2224,"Tsl Transportes",Pedidos!$F$2:$F$2224,$A54)/SUMIFS(Pedidos!$H$2:$H$2224,Pedidos!$X$2:$X$2224,"SIM",Pedidos!$I$2:$I$2224,"Tsl Transportes",Pedidos!$F$2:$F$2224,$A54),"") | I54: =IFERROR(COUNTIFS(Pedidos!$X$2:$X$2224,"SIM",Pedidos!$I$2:$I$2224,"Tsl Transportes",Pedidos!$F$2:$F$2224,$A54,Pedidos!$V$2:$V$2224,"SIM")/B54,"") | J54: =IFERROR(AVERAGEIFS(Pedidos!$K$2:$K$2224,Pedidos!$X$2:$X$2224,"SIM",Pedidos!$I$2:$I$2224,"Tsl Transportes",Pedidos!$F$2:$F$2224,$A54),"") | K54: =IFERROR(MAX(0,1-D54/E54),"")
A55: TOTAL | B55: =COUNTIFS(Pedidos!$X$2:$X$2224,"SIM",Pedidos!$I$2:$I$2224,"Tsl Transportes") -> 481 | C55: =IFERROR(AVERAGEIFS(Pedidos!$G$2:$G$2224,Pedidos!$X$2:$X$2224,"SIM",Pedidos!$I$2:$I$2224,"Tsl Transportes"),"") -> 51.125655 | D55: =IFERROR(AVERAGEIFS(Pedidos!$J$2:$J$2224,Pedidos!$X$2:$X$2224,"SIM",Pedidos!$I$2:$I$2224,"Tsl Transportes"),"") -> 125.52372 | E55: =IFERROR(AVERAGEIFS(Pedidos!$S$2:$S$2224,Pedidos!$X$2:$X$2224,"SIM",Pedidos!$I$2:$I$2224,"Tsl Transportes"),"") -> 178.59534 | F55: =IFERROR(E55/D55-1,"") -> 0.42280154 | G55: =IFERROR(SUMIFS(Pedidos!$J$2:$J$2224,Pedidos!$X$2:$X$2224,"SIM",Pedidos!$I$2:$I$2224,"Tsl Transportes")/SUMIFS(Pedidos!$H$2:$H$2224,Pedidos!$X$2:$X$2224,"SIM",Pedidos!$I$2:$I$2224,"Tsl Transportes"),"") -> 0.19185596 | H55: =IFERROR(SUMIFS(Pedidos!$S$2:$S$2224,Pedidos!$X$2:$X$2224,"SIM",Pedidos!$I$2:$I$2224,"Tsl Transportes")/SUMIFS(Pedidos!$H$2:$H$2224,Pedidos!$X$2:$X$2224,"SIM",Pedidos!$I$2:$I$2224,"Tsl Transportes"),"") -> 0.27297295 | I55: =IFERROR(COUNTIFS(Pedidos!$X$2:$X$2224,"SIM",Pedidos!$I$2:$I$2224,"Tsl Transportes",Pedidos!$V$2:$V$2224,"SIM")/B55,"") -> 0.012474012 | J55: =IFERROR(AVERAGEIFS(Pedidos!$K$2:$K$2224,Pedidos!$X$2:$X$2224,"SIM",Pedidos!$I$2:$I$2224,"Tsl Transportes"),"") -> 123.04208 | K55: =IFERROR(MAX(0,1-D55/E55),"") -> 0.29716129
A57: Transportadora atual: Jadlog Standard
A58: Faixa (kg) | B58: Pedidos | C58: Peso médio | D58: Custo médio atual (R$) | E58: PROLOG médio (R$) | F58: PROLOG vs atual (%) | G58: Frete/NF atual | H58: Frete/NF PROLOG | I58: % pedidos PROLOG mais barata | J58: PROLOG só frete peso (R$) | K58: Desconto necessário p/ empatar
A59: 0-20 | B59: =COUNTIFS(Pedidos!$X$2:$X$2224,"SIM",Pedidos!$I$2:$I$2224,"Jadlog Standard",Pedidos!$F$2:$F$2224,$A59) -> 4 | C59: =IFERROR(AVERAGEIFS(Pedidos!$G$2:$G$2224,Pedidos!$X$2:$X$2224,"SIM",Pedidos!$I$2:$I$2224,"Jadlog Standard",Pedidos!$F$2:$F$2224,$A59),"") -> 19.8 | D59: =IFERROR(AVERAGEIFS(Pedidos!$J$2:$J$2224,Pedidos!$X$2:$X$2224,"SIM",Pedidos!$I$2:$I$2224,"Jadlog Standard",Pedidos!$F$2:$F$2224,$A59),"") -> 69.51 | E59: =IFERROR(AVERAGEIFS(Pedidos!$S$2:$S$2224,Pedidos!$X$2:$X$2224,"SIM",Pedidos!$I$2:$I$2224,"Jadlog Standard",Pedidos!$F$2:$F$2224,$A59),"") -> 72.257926 | F59: =IFERROR(E59/D59-1,"") -> 0.039532817 | G59: =IFERROR(SUMIFS(Pedidos!$J$2:$J$2224,Pedidos!$X$2:$X$2224,"SIM",Pedidos!$I$2:$I$2224,"Jadlog Standard",Pedidos!$F$2:$F$2224,$A59)/SUMIFS(Pedidos!$H$2:$H$2224,Pedidos!$X$2:$X$2224,"SIM",Pedidos!$I$2:$I$2224,"Jadlog Standard",Pedidos!$F$2:$F$2224,$A59),"") -> 0.22992004 | H59: =IFERROR(SUMIFS(Pedidos!$S$2:$S$2224,Pedidos!$X$2:$X$2224,"SIM",Pedidos!$I$2:$I$2224,"Jadlog Standard",Pedidos!$F$2:$F$2224,$A59)/SUMIFS(Pedidos!$H$2:$H$2224,Pedidos!$X$2:$X$2224,"SIM",Pedidos!$I$2:$I$2224,"Jadlog Standard",Pedidos!$F$2:$F$2224,$A59),"") -> 0.23900942 | I59: =IFERROR(COUNTIFS(Pedidos!$X$2:$X$2224,"SIM",Pedidos!$I$2:$I$2224,"Jadlog Standard",Pedidos!$F$2:$F$2224,$A59,Pedidos!$V$2:$V$2224,"SIM")/B59,"") -> 0 | J59: =IFERROR(AVERAGEIFS(Pedidos!$K$2:$K$2224,Pedidos!$X$2:$X$2224,"SIM",Pedidos!$I$2:$I$2224,"Jadlog Standard",Pedidos!$F$2:$F$2224,$A59),"") -> 46.98 | K59: =IFERROR(MAX(0,1-D59/E59),"") -> 0.038029408
A60: 20-35 | B60: =COUNTIFS(Pedidos!$X$2:$X$2224,"SIM",Pedidos!$I$2:$I$2224,"Jadlog Standard",Pedidos!$F$2:$F$2224,$A60) -> 6 | C60: =IFERROR(AVERAGEIFS(Pedidos!$G$2:$G$2224,Pedidos!$X$2:$X$2224,"SIM",Pedidos!$I$2:$I$2224,"Jadlog Standard",Pedidos!$F$2:$F$2224,$A60),"") -> 21.4 | D60: =IFERROR(AVERAGEIFS(Pedidos!$J$2:$J$2224,Pedidos!$X$2:$X$2224,"SIM",Pedidos!$I$2:$I$2224,"Jadlog Standard",Pedidos!$F$2:$F$2224,$A60),"") -> 86.358333 | E60: =IFERROR(AVERAGEIFS(Pedidos!$S$2:$S$2224,Pedidos!$X$2:$X$2224,"SIM",Pedidos!$I$2:$I$2224,"Jadlog Standard",Pedidos!$F$2:$F$2224,$A60),"") -> 120.72441 | F60: =IFERROR(E60/D60-1,"") -> 0.39794746 | G60: =IFERROR(SUMIFS(Pedidos!$J$2:$J$2224,Pedidos!$X$2:$X$2224,"SIM",Pedidos!$I$2:$I$2224,"Jadlog Standard",Pedidos!$F$2:$F$2224,$A60)/SUMIFS(Pedidos!$H$2:$H$2224,Pedidos!$X$2:$X$2224,"SIM",Pedidos!$I$2:$I$2224,"Jadlog Standard",Pedidos!$F$2:$F$2224,$A60),"") -> 0.1913221 | H60: =IFERROR(SUMIFS(Pedidos!$S$2:$S$2224,Pedidos!$X$2:$X$2224,"SIM",Pedidos!$I$2:$I$2224,"Jadlog Standard",Pedidos!$F$2:$F$2224,$A60)/SUMIFS(Pedidos!$H$2:$H$2224,Pedidos!$X$2:$X$2224,"SIM",Pedidos!$I$2:$I$2224,"Jadlog Standard",Pedidos!$F$2:$F$2224,$A60),"") -> 0.26745825 | I60: =IFERROR(COUNTIFS(Pedidos!$X$2:$X$2224,"SIM",Pedidos!$I$2:$I$2224,"Jadlog Standard",Pedidos!$F$2:$F$2224,$A60,Pedidos!$V$2:$V$2224,"SIM")/B60,"") -> 0 | J60: =IFERROR(AVERAGEIFS(Pedidos!$K$2:$K$2224,Pedidos!$X$2:$X$2224,"SIM",Pedidos!$I$2:$I$2224,"Jadlog Standard",Pedidos!$F$2:$F$2224,$A60),"") -> 88.333333 | K60: =IFERROR(MAX(0,1-D60/E60),"") -> 0.28466553
A61: 35-40 | B61: =COUNTIFS(Pedidos!$X$2:$X$2224,"SIM",Pedidos!$I$2:$I$2224,"Jadlog Standard",Pedidos!$F$2:$F$2224,$A61) -> 0 | C61: =IFERROR(AVERAGEIFS(Pedidos!$G$2:$G$2224,Pedidos!$X$2:$X$2224,"SIM",Pedidos!$I$2:$I$2224,"Jadlog Standard",Pedidos!$F$2:$F$2224,$A61),"") | D61: =IFERROR(AVERAGEIFS(Pedidos!$J$2:$J$2224,Pedidos!$X$2:$X$2224,"SIM",Pedidos!$I$2:$I$2224,"Jadlog Standard",Pedidos!$F$2:$F$2224,$A61),"") | E61: =IFERROR(AVERAGEIFS(Pedidos!$S$2:$S$2224,Pedidos!$X$2:$X$2224,"SIM",Pedidos!$I$2:$I$2224,"Jadlog Standard",Pedidos!$F$2:$F$2224,$A61),"") | F61: =IFERROR(E61/D61-1,"") | G61: =IFERROR(SUMIFS(Pedidos!$J$2:$J$2224,Pedidos!$X$2:$X$2224,"SIM",Pedidos!$I$2:$I$2224,"Jadlog Standard",Pedidos!$F$2:$F$2224,$A61)/SUMIFS(Pedidos!$H$2:$H$2224,Pedidos!$X$2:$X$2224,"SIM",Pedidos!$I$2:$I$2224,"Jadlog Standard",Pedidos!$F$2:$F$2224,$A61),"") | H61: =IFERROR(SUMIFS(Pedidos!$S$2:$S$2224,Pedidos!$X$2:$X$2224,"SIM",Pedidos!$I$2:$I$2224,"Jadlog Standard",Pedidos!$F$2:$F$2224,$A61)/SUMIFS(Pedidos!$H$2:$H$2224,Pedidos!$X$2:$X$2224,"SIM",Pedidos!$I$2:$I$2224,"Jadlog Standard",Pedidos!$F$2:$F$2224,$A61),"") | I61: =IFERROR(COUNTIFS(Pedidos!$X$2:$X$2224,"SIM",Pedidos!$I$2:$I$2224,"Jadlog Standard",Pedidos!$F$2:$F$2224,$A61,Pedidos!$V$2:$V$2224,"SIM")/B61,"") | J61: =IFERROR(AVERAGEIFS(Pedidos!$K$2:$K$2224,Pedidos!$X$2:$X$2224,"SIM",Pedidos!$I$2:$I$2224,"Jadlog Standard",Pedidos!$F$2:$F$2224,$A61),"") | K61: =IFERROR(MAX(0,1-D61/E61),"")
A62: 40-50 | B62: =COUNTIFS(Pedidos!$X$2:$X$2224,"SIM",Pedidos!$I$2:$I$2224,"Jadlog Standard",Pedidos!$F$2:$F$2224,$A62) -> 0 | C62: =IFERROR(AVERAGEIFS(Pedidos!$G$2:$G$2224,Pedidos!$X$2:$X$2224,"SIM",Pedidos!$I$2:$I$2224,"Jadlog Standard",Pedidos!$F$2:$F$2224,$A62),"") | D62: =IFERROR(AVERAGEIFS(Pedidos!$J$2:$J$2224,Pedidos!$X$2:$X$2224,"SIM",Pedidos!$I$2:$I$2224,"Jadlog Standard",Pedidos!$F$2:$F$2224,$A62),"") | E62: =IFERROR(AVERAGEIFS(Pedidos!$S$2:$S$2224,Pedidos!$X$2:$X$2224,"SIM",Pedidos!$I$2:$I$2224,"Jadlog Standard",Pedidos!$F$2:$F$2224,$A62),"") | F62: =IFERROR(E62/D62-1,"") | G62: =IFERROR(SUMIFS(Pedidos!$J$2:$J$2224,Pedidos!$X$2:$X$2224,"SIM",Pedidos!$I$2:$I$2224,"Jadlog Standard",Pedidos!$F$2:$F$2224,$A62)/SUMIFS(Pedidos!$H$2:$H$2224,Pedidos!$X$2:$X$2224,"SIM",Pedidos!$I$2:$I$2224,"Jadlog Standard",Pedidos!$F$2:$F$2224,$A62),"") | H62: =IFERROR(SUMIFS(Pedidos!$S$2:$S$2224,Pedidos!$X$2:$X$2224,"SIM",Pedidos!$I$2:$I$2224,"Jadlog Standard",Pedidos!$F$2:$F$2224,$A62)/SUMIFS(Pedidos!$H$2:$H$2224,Pedidos!$X$2:$X$2224,"SIM",Pedidos!$I$2:$I$2224,"Jadlog Standard",Pedidos!$F$2:$F$2224,$A62),"") | I62: =IFERROR(COUNTIFS(Pedidos!$X$2:$X$2224,"SIM",Pedidos!$I$2:$I$2224,"Jadlog Standard",Pedidos!$F$2:$F$2224,$A62,Pedidos!$V$2:$V$2224,"SIM")/B62,"") | J62: =IFERROR(AVERAGEIFS(Pedidos!$K$2:$K$2224,Pedidos!$X$2:$X$2224,"SIM",Pedidos!$I$2:$I$2224,"Jadlog Standard",Pedidos!$F$2:$F$2224,$A62),"") | K62: =IFERROR(MAX(0,1-D62/E62),"")
A63: 50-60 | B63: =COUNTIFS(Pedidos!$X$2:$X$2224,"SIM",Pedidos!$I$2:$I$2224,"Jadlog Standard",Pedidos!$F$2:$F$2224,$A63) -> 0 | C63: =IFERROR(AVERAGEIFS(Pedidos!$G$2:$G$2224,Pedidos!$X$2:$X$2224,"SIM",Pedidos!$I$2:$I$2224,"Jadlog Standard",Pedidos!$F$2:$F$2224,$A63),"") | D63: =IFERROR(AVERAGEIFS(Pedidos!$J$2:$J$2224,Pedidos!$X$2:$X$2224,"SIM",Pedidos!$I$2:$I$2224,"Jadlog Standard",Pedidos!$F$2:$F$2224,$A63),"") | E63: =IFERROR(AVERAGEIFS(Pedidos!$S$2:$S$2224,Pedidos!$X$2:$X$2224,"SIM",Pedidos!$I$2:$I$2224,"Jadlog Standard",Pedidos!$F$2:$F$2224,$A63),"") | F63: =IFERROR(E63/D63-1,"") | G63: =IFERROR(SUMIFS(Pedidos!$J$2:$J$2224,Pedidos!$X$2:$X$2224,"SIM",Pedidos!$I$2:$I$2224,"Jadlog Standard",Pedidos!$F$2:$F$2224,$A63)/SUMIFS(Pedidos!$H$2:$H$2224,Pedidos!$X$2:$X$2224,"SIM",Pedidos!$I$2:$I$2224,"Jadlog Standard",Pedidos!$F$2:$F$2224,$A63),"") | H63: =IFERROR(SUMIFS(Pedidos!$S$2:$S$2224,Pedidos!$X$2:$X$2224,"SIM",Pedidos!$I$2:$I$2224,"Jadlog Standard",Pedidos!$F$2:$F$2224,$A63)/SUMIFS(Pedidos!$H$2:$H$2224,Pedidos!$X$2:$X$2224,"SIM",Pedidos!$I$2:$I$2224,"Jadlog Standard",Pedidos!$F$2:$F$2224,$A63),"") | I63: =IFERROR(COUNTIFS(Pedidos!$X$2:$X$2224,"SIM",Pedidos!$I$2:$I$2224,"Jadlog Standard",Pedidos!$F$2:$F$2224,$A63,Pedidos!$V$2:$V$2224,"SIM")/B63,"") | J63: =IFERROR(AVERAGEIFS(Pedidos!$K$2:$K$2224,Pedidos!$X$2:$X$2224,"SIM",Pedidos!$I$2:$I$2224,"Jadlog Standard",Pedidos!$F$2:$F$2224,$A63),"") | K63: =IFERROR(MAX(0,1-D63/E63),"")
A64: 60-70 | B64: =COUNTIFS(Pedidos!$X$2:$X$2224,"SIM",Pedidos!$I$2:$I$2224,"Jadlog Standard",Pedidos!$F$2:$F$2224,$A64) -> 0 | C64: =IFERROR(AVERAGEIFS(Pedidos!$G$2:$G$2224,Pedidos!$X$2:$X$2224,"SIM",Pedidos!$I$2:$I$2224,"Jadlog Standard",Pedidos!$F$2:$F$2224,$A64),"") | D64: =IFERROR(AVERAGEIFS(Pedidos!$J$2:$J$2224,Pedidos!$X$2:$X$2224,"SIM",Pedidos!$I$2:$I$2224,"Jadlog Standard",Pedidos!$F$2:$F$2224,$A64),"") | E64: =IFERROR(AVERAGEIFS(Pedidos!$S$2:$S$2224,Pedidos!$X$2:$X$2224,"SIM",Pedidos!$I$2:$I$2224,"Jadlog Standard",Pedidos!$F$2:$F$2224,$A64),"") | F64: =IFERROR(E64/D64-1,"") | G64: =IFERROR(SUMIFS(Pedidos!$J$2:$J$2224,Pedidos!$X$2:$X$2224,"SIM",Pedidos!$I$2:$I$2224,"Jadlog Standard",Pedidos!$F$2:$F$2224,$A64)/SUMIFS(Pedidos!$H$2:$H$2224,Pedidos!$X$2:$X$2224,"SIM",Pedidos!$I$2:$I$2224,"Jadlog Standard",Pedidos!$F$2:$F$2224,$A64),"") | H64: =IFERROR(SUMIFS(Pedidos!$S$2:$S$2224,Pedidos!$X$2:$X$2224,"SIM",Pedidos!$I$2:$I$2224,"Jadlog Standard",Pedidos!$F$2:$F$2224,$A64)/SUMIFS(Pedidos!$H$2:$H$2224,Pedidos!$X$2:$X$2224,"SIM",Pedidos!$I$2:$I$2224,"Jadlog Standard",Pedidos!$F$2:$F$2224,$A64),"") | I64: =IFERROR(COUNTIFS(Pedidos!$X$2:$X$2224,"SIM",Pedidos!$I$2:$I$2224,"Jadlog Standard",Pedidos!$F$2:$F$2224,$A64,Pedidos!$V$2:$V$2224,"SIM")/B64,"") | J64: =IFERROR(AVERAGEIFS(Pedidos!$K$2:$K$2224,Pedidos!$X$2:$X$2224,"SIM",Pedidos!$I$2:$I$2224,"Jadlog Standard",Pedidos!$F$2:$F$2224,$A64),"") | K64: =IFERROR(MAX(0,1-D64/E64),"")
A65: 70-80 | B65: =COUNTIFS(Pedidos!$X$2:$X$2224,"SIM",Pedidos!$I$2:$I$2224,"Jadlog Standard",Pedidos!$F$2:$F$2224,$A65) -> 0 | C65: =IFERROR(AVERAGEIFS(Pedidos!$G$2:$G$2224,Pedidos!$X$2:$X$2224,"SIM",Pedidos!$I$2:$I$2224,"Jadlog Standard",Pedidos!$F$2:$F$2224,$A65),"") | D65: =IFERROR(AVERAGEIFS(Pedidos!$J$2:$J$2224,Pedidos!$X$2:$X$2224,"SIM",Pedidos!$I$2:$I$2224,"Jadlog Standard",Pedidos!$F$2:$F$2224,$A65),"") | E65: =IFERROR(AVERAGEIFS(Pedidos!$S$2:$S$2224,Pedidos!$X$2:$X$2224,"SIM",Pedidos!$I$2:$I$2224,"Jadlog Standard",Pedidos!$F$2:$F$2224,$A65),"") | F65: =IFERROR(E65/D65-1,"") | G65: =IFERROR(SUMIFS(Pedidos!$J$2:$J$2224,Pedidos!$X$2:$X$2224,"SIM",Pedidos!$I$2:$I$2224,"Jadlog Standard",Pedidos!$F$2:$F$2224,$A65)/SUMIFS(Pedidos!$H$2:$H$2224,Pedidos!$X$2:$X$2224,"SIM",Pedidos!$I$2:$I$2224,"Jadlog Standard",Pedidos!$F$2:$F$2224,$A65),"") | H65: =IFERROR(SUMIFS(Pedidos!$S$2:$S$2224,Pedidos!$X$2:$X$2224,"SIM",Pedidos!$I$2:$I$2224,"Jadlog Standard",Pedidos!$F$2:$F$2224,$A65)/SUMIFS(Pedidos!$H$2:$H$2224,Pedidos!$X$2:$X$2224,"SIM",Pedidos!$I$2:$I$2224,"Jadlog Standard",Pedidos!$F$2:$F$2224,$A65),"") | I65: =IFERROR(COUNTIFS(Pedidos!$X$2:$X$2224,"SIM",Pedidos!$I$2:$I$2224,"Jadlog Standard",Pedidos!$F$2:$F$2224,$A65,Pedidos!$V$2:$V$2224,"SIM")/B65,"") | J65: =IFERROR(AVERAGEIFS(Pedidos!$K$2:$K$2224,Pedidos!$X$2:$X$2224,"SIM",Pedidos!$I$2:$I$2224,"Jadlog Standard",Pedidos!$F$2:$F$2224,$A65),"") | K65: =IFERROR(MAX(0,1-D65/E65),"")
A66: 80-100 | B66: =COUNTIFS(Pedidos!$X$2:$X$2224,"SIM",Pedidos!$I$2:$I$2224,"Jadlog Standard",Pedidos!$F$2:$F$2224,$A66) -> 0 | C66: =IFERROR(AVERAGEIFS(Pedidos!$G$2:$G$2224,Pedidos!$X$2:$X$2224,"SIM",Pedidos!$I$2:$I$2224,"Jadlog Standard",Pedidos!$F$2:$F$2224,$A66),"") | D66: =IFERROR(AVERAGEIFS(Pedidos!$J$2:$J$2224,Pedidos!$X$2:$X$2224,"SIM",Pedidos!$I$2:$I$2224,"Jadlog Standard",Pedidos!$F$2:$F$2224,$A66),"") | E66: =IFERROR(AVERAGEIFS(Pedidos!$S$2:$S$2224,Pedidos!$X$2:$X$2224,"SIM",Pedidos!$I$2:$I$2224,"Jadlog Standard",Pedidos!$F$2:$F$2224,$A66),"") | F66: =IFERROR(E66/D66-1,"") | G66: =IFERROR(SUMIFS(Pedidos!$J$2:$J$2224,Pedidos!$X$2:$X$2224,"SIM",Pedidos!$I$2:$I$2224,"Jadlog Standard",Pedidos!$F$2:$F$2224,$A66)/SUMIFS(Pedidos!$H$2:$H$2224,Pedidos!$X$2:$X$2224,"SIM",Pedidos!$I$2:$I$2224,"Jadlog Standard",Pedidos!$F$2:$F$2224,$A66),"") | H66: =IFERROR(SUMIFS(Pedidos!$S$2:$S$2224,Pedidos!$X$2:$X$2224,"SIM",Pedidos!$I$2:$I$2224,"Jadlog Standard",Pedidos!$F$2:$F$2224,$A66)/SUMIFS(Pedidos!$H$2:$H$2224,Pedidos!$X$2:$X$2224,"SIM",Pedidos!$I$2:$I$2224,"Jadlog Standard",Pedidos!$F$2:$F$2224,$A66),"") | I66: =IFERROR(COUNTIFS(Pedidos!$X$2:$X$2224,"SIM",Pedidos!$I$2:$I$2224,"Jadlog Standard",Pedidos!$F$2:$F$2224,$A66,Pedidos!$V$2:$V$2224,"SIM")/B66,"") | J66: =IFERROR(AVERAGEIFS(Pedidos!$K$2:$K$2224,Pedidos!$X$2:$X$2224,"SIM",Pedidos!$I$2:$I$2224,"Jadlog Standard",Pedidos!$F$2:$F$2224,$A66),"") | K66: =IFERROR(MAX(0,1-D66/E66),"")
A67: 100-120 | B67: =COUNTIFS(Pedidos!$X$2:$X$2224,"SIM",Pedidos!$I$2:$I$2224,"Jadlog Standard",Pedidos!$F$2:$F$2224,$A67) -> 0 | C67: =IFERROR(AVERAGEIFS(Pedidos!$G$2:$G$2224,Pedidos!$X$2:$X$2224,"SIM",Pedidos!$I$2:$I$2224,"Jadlog Standard",Pedidos!$F$2:$F$2224,$A67),"") | D67: =IFERROR(AVERAGEIFS(Pedidos!$J$2:$J$2224,Pedidos!$X$2:$X$2224,"SIM",Pedidos!$I$2:$I$2224,"Jadlog Standard",Pedidos!$F$2:$F$2224,$A67),"") | E67: =IFERROR(AVERAGEIFS(Pedidos!$S$2:$S$2224,Pedidos!$X$2:$X$2224,"SIM",Pedidos!$I$2:$I$2224,"Jadlog Standard",Pedidos!$F$2:$F$2224,$A67),"") | F67: =IFERROR(E67/D67-1,"") | G67: =IFERROR(SUMIFS(Pedidos!$J$2:$J$2224,Pedidos!$X$2:$X$2224,"SIM",Pedidos!$I$2:$I$2224,"Jadlog Standard",Pedidos!$F$2:$F$2224,$A67)/SUMIFS(Pedidos!$H$2:$H$2224,Pedidos!$X$2:$X$2224,"SIM",Pedidos!$I$2:$I$2224,"Jadlog Standard",Pedidos!$F$2:$F$2224,$A67),"") | H67: =IFERROR(SUMIFS(Pedidos!$S$2:$S$2224,Pedidos!$X$2:$X$2224,"SIM",Pedidos!$I$2:$I$2224,"Jadlog Standard",Pedidos!$F$2:$F$2224,$A67)/SUMIFS(Pedidos!$H$2:$H$2224,Pedidos!$X$2:$X$2224,"SIM",Pedidos!$I$2:$I$2224,"Jadlog Standard",Pedidos!$F$2:$F$2224,$A67),"") | I67: =IFERROR(COUNTIFS(Pedidos!$X$2:$X$2224,"SIM",Pedidos!$I$2:$I$2224,"Jadlog Standard",Pedidos!$F$2:$F$2224,$A67,Pedidos!$V$2:$V$2224,"SIM")/B67,"") | J67: =IFERROR(AVERAGEIFS(Pedidos!$K$2:$K$2224,Pedidos!$X$2:$X$2224,"SIM",Pedidos!$I$2:$I$2224,"Jadlog Standard",Pedidos!$F$2:$F$2224,$A67),"") | K67: =IFERROR(MAX(0,1-D67/E67),"")
A68: 120-150 | B68: =COUNTIFS(Pedidos!$X$2:$X$2224,"SIM",Pedidos!$I$2:$I$2224,"Jadlog Standard",Pedidos!$F$2:$F$2224,$A68) -> 0 | C68: =IFERROR(AVERAGEIFS(Pedidos!$G$2:$G$2224,Pedidos!$X$2:$X$2224,"SIM",Pedidos!$I$2:$I$2224,"Jadlog Standard",Pedidos!$F$2:$F$2224,$A68),"") | D68: =IFERROR(AVERAGEIFS(Pedidos!$J$2:$J$2224,Pedidos!$X$2:$X$2224,"SIM",Pedidos!$I$2:$I$2224,"Jadlog Standard",Pedidos!$F$2:$F$2224,$A68),"") | E68: =IFERROR(AVERAGEIFS(Pedidos!$S$2:$S$2224,Pedidos!$X$2:$X$2224,"SIM",Pedidos!$I$2:$I$2224,"Jadlog Standard",Pedidos!$F$2:$F$2224,$A68),"") | F68: =IFERROR(E68/D68-1,"") | G68: =IFERROR(SUMIFS(Pedidos!$J$2:$J$2224,Pedidos!$X$2:$X$2224,"SIM",Pedidos!$I$2:$I$2224,"Jadlog Standard",Pedidos!$F$2:$F$2224,$A68)/SUMIFS(Pedidos!$H$2:$H$2224,Pedidos!$X$2:$X$2224,"SIM",Pedidos!$I$2:$I$2224,"Jadlog Standard",Pedidos!$F$2:$F$2224,$A68),"") | H68: =IFERROR(SUMIFS(Pedidos!$S$2:$S$2224,Pedidos!$X$2:$X$2224,"SIM",Pedidos!$I$2:$I$2224,"Jadlog Standard",Pedidos!$F$2:$F$2224,$A68)/SUMIFS(Pedidos!$H$2:$H$2224,Pedidos!$X$2:$X$2224,"SIM",Pedidos!$I$2:$I$2224,"Jadlog Standard",Pedidos!$F$2:$F$2224,$A68),"") | I68: =IFERROR(COUNTIFS(Pedidos!$X$2:$X$2224,"SIM",Pedidos!$I$2:$I$2224,"Jadlog Standard",Pedidos!$F$2:$F$2224,$A68,Pedidos!$V$2:$V$2224,"SIM")/B68,"") | J68: =IFERROR(AVERAGEIFS(Pedidos!$K$2:$K$2224,Pedidos!$X$2:$X$2224,"SIM",Pedidos!$I$2:$I$2224,"Jadlog Standard",Pedidos!$F$2:$F$2224,$A68),"") | K68: =IFERROR(MAX(0,1-D68/E68),"")
A69: 150-170 | B69: =COUNTIFS(Pedidos!$X$2:$X$2224,"SIM",Pedidos!$I$2:$I$2224,"Jadlog Standard",Pedidos!$F$2:$F$2224,$A69) -> 0 | C69: =IFERROR(AVERAGEIFS(Pedidos!$G$2:$G$2224,Pedidos!$X$2:$X$2224,"SIM",Pedidos!$I$2:$I$2224,"Jadlog Standard",Pedidos!$F$2:$F$2224,$A69),"") | D69: =IFERROR(AVERAGEIFS(Pedidos!$J$2:$J$2224,Pedidos!$X$2:$X$2224,"SIM",Pedidos!$I$2:$I$2224,"Jadlog Standard",Pedidos!$F$2:$F$2224,$A69),"") | E69: =IFERROR(AVERAGEIFS(Pedidos!$S$2:$S$2224,Pedidos!$X$2:$X$2224,"SIM",Pedidos!$I$2:$I$2224,"Jadlog Standard",Pedidos!$F$2:$F$2224,$A69),"") | F69: =IFERROR(E69/D69-1,"") | G69: =IFERROR(SUMIFS(Pedidos!$J$2:$J$2224,Pedidos!$X$2:$X$2224,"SIM",Pedidos!$I$2:$I$2224,"Jadlog Standard",Pedidos!$F$2:$F$2224,$A69)/SUMIFS(Pedidos!$H$2:$H$2224,Pedidos!$X$2:$X$2224,"SIM",Pedidos!$I$2:$I$2224,"Jadlog Standard",Pedidos!$F$2:$F$2224,$A69),"") | H69: =IFERROR(SUMIFS(Pedidos!$S$2:$S$2224,Pedidos!$X$2:$X$2224,"SIM",Pedidos!$I$2:$I$2224,"Jadlog Standard",Pedidos!$F$2:$F$2224,$A69)/SUMIFS(Pedidos!$H$2:$H$2224,Pedidos!$X$2:$X$2224,"SIM",Pedidos!$I$2:$I$2224,"Jadlog Standard",Pedidos!$F$2:$F$2224,$A69),"") | I69: =IFERROR(COUNTIFS(Pedidos!$X$2:$X$2224,"SIM",Pedidos!$I$2:$I$2224,"Jadlog Standard",Pedidos!$F$2:$F$2224,$A69,Pedidos!$V$2:$V$2224,"SIM")/B69,"") | J69: =IFERROR(AVERAGEIFS(Pedidos!$K$2:$K$2224,Pedidos!$X$2:$X$2224,"SIM",Pedidos!$I$2:$I$2224,"Jadlog Standard",Pedidos!$F$2:$F$2224,$A69),"") | K69: =IFERROR(MAX(0,1-D69/E69),"")
A70: 170-200 | B70: =COUNTIFS(Pedidos!$X$2:$X$2224,"SIM",Pedidos!$I$2:$I$2224,"Jadlog Standard",Pedidos!$F$2:$F$2224,$A70) -> 0 | C70: =IFERROR(AVERAGEIFS(Pedidos!$G$2:$G$2224,Pedidos!$X$2:$X$2224,"SIM",Pedidos!$I$2:$I$2224,"Jadlog Standard",Pedidos!$F$2:$F$2224,$A70),"") | D70: =IFERROR(AVERAGEIFS(Pedidos!$J$2:$J$2224,Pedidos!$X$2:$X$2224,"SIM",Pedidos!$I$2:$I$2224,"Jadlog Standard",Pedidos!$F$2:$F$2224,$A70),"") | E70: =IFERROR(AVERAGEIFS(Pedidos!$S$2:$S$2224,Pedidos!$X$2:$X$2224,"SIM",Pedidos!$I$2:$I$2224,"Jadlog Standard",Pedidos!$F$2:$F$2224,$A70),"") | F70: =IFERROR(E70/D70-1,"") | G70: =IFERROR(SUMIFS(Pedidos!$J$2:$J$2224,Pedidos!$X$2:$X$2224,"SIM",Pedidos!$I$2:$I$2224,"Jadlog Standard",Pedidos!$F$2:$F$2224,$A70)/SUMIFS(Pedidos!$H$2:$H$2224,Pedidos!$X$2:$X$2224,"SIM",Pedidos!$I$2:$I$2224,"Jadlog Standard",Pedidos!$F$2:$F$2224,$A70),"") | H70: =IFERROR(SUMIFS(Pedidos!$S$2:$S$2224,Pedidos!$X$2:$X$2224,"SIM",Pedidos!$I$2:$I$2224,"Jadlog Standard",Pedidos!$F$2:$F$2224,$A70)/SUMIFS(Pedidos!$H$2:$H$2224,Pedidos!$X$2:$X$2224,"SIM",Pedidos!$I$2:$I$2224,"Jadlog Standard",Pedidos!$F$2:$F$2224,$A70),"") | I70: =IFERROR(COUNTIFS(Pedidos!$X$2:$X$2224,"SIM",Pedidos!$I$2:$I$2224,"Jadlog Standard",Pedidos!$F$2:$F$2224,$A70,Pedidos!$V$2:$V$2224,"SIM")/B70,"") | J70: =IFERROR(AVERAGEIFS(Pedidos!$K$2:$K$2224,Pedidos!$X$2:$X$2224,"SIM",Pedidos!$I$2:$I$2224,"Jadlog Standard",Pedidos!$F$2:$F$2224,$A70),"") | K70: =IFERROR(MAX(0,1-D70/E70),"")
... A72: >250 | B72: =COUNTIFS(Pedidos!$X$2:$X$2224,"SIM",Pedidos!$I$2:$I$2224,"Jadlog Standard",Pedidos!$F$2:$F$2224,$A72) -> 0 | C72: =IFERROR(AVERAGEIFS(Pedidos!$G$2:$G$2224,Pedidos!$X$2:$X$2224,"SIM",Pedidos!$I$2:$I$2224,"Jadlog Standard",Pedidos!$F$2:$F$2224,$A72),"") | D72: =IFERROR(AVERAGEIFS(Pedidos!$J$2:$J$2224,Pedidos!$X$2:$X$2224,"SIM",Pedidos!$I$2:$I$2224,"Jadlog Standard",Pedidos!$F$2:$F$2224,$A72),"") | E72: =IFERROR(AVERAGEIFS(Pedidos!$S$2:$S$2224,Pedidos!$X$2:$X$2224,"SIM",Pedidos!$I$2:$I$2224,"Jadlog Standard",Pedidos!$F$2:$F$2224,$A72),"") | F72: =IFERROR(E72/D72-1,"") | G72: =IFERROR(SUMIFS(Pedidos!$J$2:$J$2224,Pedidos!$X$2:$X$2224,"SIM",Pedidos!$I$2:$I$2224,"Jadlog Standard",Pedidos!$F$2:$F$2224,$A72)/SUMIFS(Pedidos!$H$2:$H$2224,Pedidos!$X$2:$X$2224,"SIM",Pedidos!$I$2:$I$2224,"Jadlog Standard",Pedidos!$F$2:$F$2224,$A72),"") | H72: =IFERROR(SUMIFS(Pedidos!$S$2:$S$2224,Pedidos!$X$2:$X$2224,"SIM",Pedidos!$I$2:$I$2224,"Jadlog Standard",Pedidos!$F$2:$F$2224,$A72)/SUMIFS(Pedidos!$H$2:$H$2224,Pedidos!$X$2:$X$2224,"SIM",Pedidos!$I$2:$I$2224,"Jadlog Standard",Pedidos!$F$2:$F$2224,$A72),"") | I72: =IFERROR(COUNTIFS(Pedidos!$X$2:$X$2224,"SIM",Pedidos!$I$2:$I$2224,"Jadlog Standard",Pedidos!$F$2:$F$2224,$A72,Pedidos!$V$2:$V$2224,"SIM")/B72,"") | J72: =IFERROR(AVERAGEIFS(Pedidos!$K$2:$K$2224,Pedidos!$X$2:$X$2224,"SIM",Pedidos!$I$2:$I$2224,"Jadlog Standard",Pedidos!$F$2:$F$2224,$A72),"") | K72: =IFERROR(MAX(0,1-D72/E72),"")
A73: TOTAL | B73: =COUNTIFS(Pedidos!$X$2:$X$2224,"SIM",Pedidos!$I$2:$I$2224,"Jadlog Standard") -> 10 | C73: =IFERROR(AVERAGEIFS(Pedidos!$G$2:$G$2224,Pedidos!$X$2:$X$2224,"SIM",Pedidos!$I$2:$I$2224,"Jadlog Standard"),"") -> 20.76 | D73: =IFERROR(AVERAGEIFS(Pedidos!$J$2:$J$2224,Pedidos!$X$2:$X$2224,"SIM",Pedidos!$I$2:$I$2224,"Jadlog Standard"),"") -> 79.619 | E73: =IFERROR(AVERAGEIFS(Pedidos!$S$2:$S$2224,Pedidos!$X$2:$X$2224,"SIM",Pedidos!$I$2:$I$2224,"Jadlog Standard"),"") -> 101.33782 | F73: =IFERROR(E73/D73-1,"") -> 0.27278436 | G73: =IFERROR(SUMIFS(Pedidos!$J$2:$J$2224,Pedidos!$X$2:$X$2224,"SIM",Pedidos!$I$2:$I$2224,"Jadlog Standard")/SUMIFS(Pedidos!$H$2:$H$2224,Pedidos!$X$2:$X$2224,"SIM",Pedidos!$I$2:$I$2224,"Jadlog Standard"),"") -> 0.20323672 | H73: =IFERROR(SUMIFS(Pedidos!$S$2:$S$2224,Pedidos!$X$2:$X$2224,"SIM",Pedidos!$I$2:$I$2224,"Jadlog Standard")/SUMIFS(Pedidos!$H$2:$H$2224,Pedidos!$X$2:$X$2224,"SIM",Pedidos!$I$2:$I$2224,"Jadlog Standard"),"") -> 0.25867652 | I73: =IFERROR(COUNTIFS(Pedidos!$X$2:$X$2224,"SIM",Pedidos!$I$2:$I$2224,"Jadlog Standard",Pedidos!$V$2:$V$2224,"SIM")/B73,"") -> 0 | J73: =IFERROR(AVERAGEIFS(Pedidos!$K$2:$K$2224,Pedidos!$X$2:$X$2224,"SIM",Pedidos!$I$2:$I$2224,"Jadlog Standard"),"") -> 71.792 | K73: =IFERROR(MAX(0,1-D73/E73),"") -> 0.21432096
A75: Transportadora atual: Prolog Transportes
A76: Faixa (kg) | B76: Pedidos | C76: Peso médio | D76: Custo médio atual (R$) | E76: PROLOG médio (R$) | F76: PROLOG vs atual (%) | G76: Frete/NF atual | H76: Frete/NF PROLOG | I76: % pedidos PROLOG mais barata | J76: PROLOG só frete peso (R$) | K76: Desconto necessário p/ empatar
A77: 0-20 | B77: =COUNTIFS(Pedidos!$X$2:$X$2224,"SIM",Pedidos!$I$2:$I$2224,"Prolog Transportes",Pedidos!$F$2:$F$2224,$A77) -> 0 | C77: =IFERROR(AVERAGEIFS(Pedidos!$G$2:$G$2224,Pedidos!$X$2:$X$2224,"SIM",Pedidos!$I$2:$I$2224,"Prolog Transportes",Pedidos!$F$2:$F$2224,$A77),"") | D77: =IFERROR(AVERAGEIFS(Pedidos!$J$2:$J$2224,Pedidos!$X$2:$X$2224,"SIM",Pedidos!$I$2:$I$2224,"Prolog Transportes",Pedidos!$F$2:$F$2224,$A77),"") | E77: =IFERROR(AVERAGEIFS(Pedidos!$S$2:$S$2224,Pedidos!$X$2:$X$2224,"SIM",Pedidos!$I$2:$I$2224,"Prolog Transportes",Pedidos!$F$2:$F$2224,$A77),"") | F77: =IFERROR(E77/D77-1,"") | G77: =IFERROR(SUMIFS(Pedidos!$J$2:$J$2224,Pedidos!$X$2:$X$2224,"SIM",Pedidos!$I$2:$I$2224,"Prolog Transportes",Pedidos!$F$2:$F$2224,$A77)/SUMIFS(Pedidos!$H$2:$H$2224,Pedidos!$X$2:$X$2224,"SIM",Pedidos!$I$2:$I$2224,"Prolog Transportes",Pedidos!$F$2:$F$2224,$A77),"") | H77: =IFERROR(SUMIFS(Pedidos!$S$2:$S$2224,Pedidos!$X$2:$X$2224,"SIM",Pedidos!$I$2:$I$2224,"Prolog Transportes",Pedidos!$F$2:$F$2224,$A77)/SUMIFS(Pedidos!$H$2:$H$2224,Pedidos!$X$2:$X$2224,"SIM",Pedidos!$I$2:$I$2224,"Prolog Transportes",Pedidos!$F$2:$F$2224,$A77),"") | I77: =IFERROR(COUNTIFS(Pedidos!$X$2:$X$2224,"SIM",Pedidos!$I$2:$I$2224,"Prolog Transportes",Pedidos!$F$2:$F$2224,$A77,Pedidos!$V$2:$V$2224,"SIM")/B77,"") | J77: =IFERROR(AVERAGEIFS(Pedidos!$K$2:$K$2224,Pedidos!$X$2:$X$2224,"SIM",Pedidos!$I$2:$I$2224,"Prolog Transportes",Pedidos!$F$2:$F$2224,$A77),"") | K77: =IFERROR(MAX(0,1-D77/E77),"")
A78: 20-35 | B78: =COUNTIFS(Pedidos!$X$2:$X$2224,"SIM",Pedidos!$I$2:$I$2224,"Prolog Transportes",Pedidos!$F$2:$F$2224,$A78) -> 1 | C78: =IFERROR(AVERAGEIFS(Pedidos!$G$2:$G$2224,Pedidos!$X$2:$X$2224,"SIM",Pedidos!$I$2:$I$2224,"Prolog Transportes",Pedidos!$F$2:$F$2224,$A78),"") -> 33 | D78: =IFERROR(AVERAGEIFS(Pedidos!$J$2:$J$2224,Pedidos!$X$2:$X$2224,"SIM",Pedidos!$I$2:$I$2224,"Prolog Transportes",Pedidos!$F$2:$F$2224,$A78),"") -> 82.17 | E78: =IFERROR(AVERAGEIFS(Pedidos!$S$2:$S$2224,Pedidos!$X$2:$X$2224,"SIM",Pedidos!$I$2:$I$2224,"Prolog Transportes",Pedidos!$F$2:$F$2224,$A78),"") -> 120.29545 | F78: =IFERROR(E78/D78-1,"") -> 0.46398265 | G78: =IFERROR(SUMIFS(Pedidos!$J$2:$J$2224,Pedidos!$X$2:$X$2224,"SIM",Pedidos!$I$2:$I$2224,"Prolog Transportes",Pedidos!$F$2:$F$2224,$A78)/SUMIFS(Pedidos!$H$2:$H$2224,Pedidos!$X$2:$X$2224,"SIM",Pedidos!$I$2:$I$2224,"Prolog Transportes",Pedidos!$F$2:$F$2224,$A78),"") -> 0.18675424 | H78: =IFERROR(SUMIFS(Pedidos!$S$2:$S$2224,Pedidos!$X$2:$X$2224,"SIM",Pedidos!$I$2:$I$2224,"Prolog Transportes",Pedidos!$F$2:$F$2224,$A78)/SUMIFS(Pedidos!$H$2:$H$2224,Pedidos!$X$2:$X$2224,"SIM",Pedidos!$I$2:$I$2224,"Prolog Transportes",Pedidos!$F$2:$F$2224,$A78),"") -> 0.27340497 | I78: =IFERROR(COUNTIFS(Pedidos!$X$2:$X$2224,"SIM",Pedidos!$I$2:$I$2224,"Prolog Transportes",Pedidos!$F$2:$F$2224,$A78,Pedidos!$V$2:$V$2224,"SIM")/B78,"") -> 0 | J78: =IFERROR(AVERAGEIFS(Pedidos!$K$2:$K$2224,Pedidos!$X$2:$X$2224,"SIM",Pedidos!$I$2:$I$2224,"Prolog Transportes",Pedidos!$F$2:$F$2224,$A78),"") -> 82.21 | K78: =IFERROR(MAX(0,1-D78/E78),"") -> 0.3169318
A79: 35-40 | B79: =COUNTIFS(Pedidos!$X$2:$X$2224,"SIM",Pedidos!$I$2:$I$2224,"Prolog Transportes",Pedidos!$F$2:$F$2224,$A79) -> 0 | C79: =IFERROR(AVERAGEIFS(Pedidos!$G$2:$G$2224,Pedidos!$X$2:$X$2224,"SIM",Pedidos!$I$2:$I$2224,"Prolog Transportes",Pedidos!$F$2:$F$2224,$A79),"") | D79: =IFERROR(AVERAGEIFS(Pedidos!$J$2:$J$2224,Pedidos!$X$2:$X$2224,"SIM",Pedidos!$I$2:$I$2224,"Prolog Transportes",Pedidos!$F$2:$F$2224,$A79),"") | E79: =IFERROR(AVERAGEIFS(Pedidos!$S$2:$S$2224,Pedidos!$X$2:$X$2224,"SIM",Pedidos!$I$2:$I$2224,"Prolog Transportes",Pedidos!$F$2:$F$2224,$A79),"") | F79: =IFERROR(E79/D79-1,"") | G79: =IFERROR(SUMIFS(Pedidos!$J$2:$J$2224,Pedidos!$X$2:$X$2224,"SIM",Pedidos!$I$2:$I$2224,"Prolog Transportes",Pedidos!$F$2:$F$2224,$A79)/SUMIFS(Pedidos!$H$2:$H$2224,Pedidos!$X$2:$X$2224,"SIM",Pedidos!$I$2:$I$2224,"Prolog Transportes",Pedidos!$F$2:$F$2224,$A79),"") | H79: =IFERROR(SUMIFS(Pedidos!$S$2:$S$2224,Pedidos!$X$2:$X$2224,"SIM",Pedidos!$I$2:$I$2224,"Prolog Transportes",Pedidos!$F$2:$F$2224,$A79)/SUMIFS(Pedidos!$H$2:$H$2224,Pedidos!$X$2:$X$2224,"SIM",Pedidos!$I$2:$I$2224,"Prolog Transportes",Pedidos!$F$2:$F$2224,$A79),"") | I79: =IFERROR(COUNTIFS(Pedidos!$X$2:$X$2224,"SIM",Pedidos!$I$2:$I$2224,"Prolog Transportes",Pedidos!$F$2:$F$2224,$A79,Pedidos!$V$2:$V$2224,"SIM")/B79,"") | J79: =IFERROR(AVERAGEIFS(Pedidos!$K$2:$K$2224,Pedidos!$X$2:$X$2224,"SIM",Pedidos!$I$2:$I$2224,"Prolog Transportes",Pedidos!$F$2:$F$2224,$A79),"") | K79: =IFERROR(MAX(0,1-D79/E79),"")
A80: 40-50 | B80: =COUNTIFS(Pedidos!$X$2:$X$2224,"SIM",Pedidos!$I$2:$I$2224,"Prolog Transportes",Pedidos!$F$2:$F$2224,$A80) -> 0 | C80: =IFERROR(AVERAGEIFS(Pedidos!$G$2:$G$2224,Pedidos!$X$2:$X$2224,"SIM",Pedidos!$I$2:$I$2224,"Prolog Transportes",Pedidos!$F$2:$F$2224,$A80),"") | D80: =IFERROR(AVERAGEIFS(Pedidos!$J$2:$J$2224,Pedidos!$X$2:$X$2224,"SIM",Pedidos!$I$2:$I$2224,"Prolog Transportes",Pedidos!$F$2:$F$2224,$A80),"") | E80: =IFERROR(AVERAGEIFS(Pedidos!$S$2:$S$2224,Pedidos!$X$2:$X$2224,"SIM",Pedidos!$I$2:$I$2224,"Prolog Transportes",Pedidos!$F$2:$F$2224,$A80),"") | F80: =IFERROR(E80/D80-1,"") | G80: =IFERROR(SUMIFS(Pedidos!$J$2:$J$2224,Pedidos!$X$2:$X$2224,"SIM",Pedidos!$I$2:$I$2224,"Prolog Transportes",Pedidos!$F$2:$F$2224,$A80)/SUMIFS(Pedidos!$H$2:$H$2224,Pedidos!$X$2:$X$2224,"SIM",Pedidos!$I$2:$I$2224,"Prolog Transportes",Pedidos!$F$2:$F$2224,$A80),"") | H80: =IFERROR(SUMIFS(Pedidos!$S$2:$S$2224,Pedidos!$X$2:$X$2224,"SIM",Pedidos!$I$2:$I$2224,"Prolog Transportes",Pedidos!$F$2:$F$2224,$A80)/SUMIFS(Pedidos!$H$2:$H$2224,Pedidos!$X$2:$X$2224,"SIM",Pedidos!$I$2:$I$2224,"Prolog Transportes",Pedidos!$F$2:$F$2224,$A80),"") | I80: =IFERROR(COUNTIFS(Pedidos!$X$2:$X$2224,"SIM",Pedidos!$I$2:$I$2224,"Prolog Transportes",Pedidos!$F$2:$F$2224,$A80,Pedidos!$V$2:$V$2224,"SIM")/B80,"") | J80: =IFERROR(AVERAGEIFS(Pedidos!$K$2:$K$2224,Pedidos!$X$2:$X$2224,"SIM",Pedidos!$I$2:$I$2224,"Prolog Transportes",Pedidos!$F$2:$F$2224,$A80),"") | K80: =IFERROR(MAX(0,1-D80/E80),"")
A81: 50-60 | B81: =COUNTIFS(Pedidos!$X$2:$X$2224,"SIM",Pedidos!$I$2:$I$2224,"Prolog Transportes",Pedidos!$F$2:$F$2224,$A81) -> 0 | C81: =IFERROR(AVERAGEIFS(Pedidos!$G$2:$G$2224,Pedidos!$X$2:$X$2224,"SIM",Pedidos!$I$2:$I$2224,"Prolog Transportes",Pedidos!$F$2:$F$2224,$A81),"") | D81: =IFERROR(AVERAGEIFS(Pedidos!$J$2:$J$2224,Pedidos!$X$2:$X$2224,"SIM",Pedidos!$I$2:$I$2224,"Prolog Transportes",Pedidos!$F$2:$F$2224,$A81),"") | E81: =IFERROR(AVERAGEIFS(Pedidos!$S$2:$S$2224,Pedidos!$X$2:$X$2224,"SIM",Pedidos!$I$2:$I$2224,"Prolog Transportes",Pedidos!$F$2:$F$2224,$A81),"") | F81: =IFERROR(E81/D81-1,"") | G81: =IFERROR(SUMIFS(Pedidos!$J$2:$J$2224,Pedidos!$X$2:$X$2224,"SIM",Pedidos!$I$2:$I$2224,"Prolog Transportes",Pedidos!$F$2:$F$2224,$A81)/SUMIFS(Pedidos!$H$2:$H$2224,Pedidos!$X$2:$X$2224,"SIM",Pedidos!$I$2:$I$2224,"Prolog Transportes",Pedidos!$F$2:$F$2224,$A81),"") | H81: =IFERROR(SUMIFS(Pedidos!$S$2:$S$2224,Pedidos!$X$2:$X$2224,"SIM",Pedidos!$I$2:$I$2224,"Prolog Transportes",Pedidos!$F$2:$F$2224,$A81)/SUMIFS(Pedidos!$H$2:$H$2224,Pedidos!$X$2:$X$2224,"SIM",Pedidos!$I$2:$I$2224,"Prolog Transportes",Pedidos!$F$2:$F$2224,$A81),"") | I81: =IFERROR(COUNTIFS(Pedidos!$X$2:$X$2224,"SIM",Pedidos!$I$2:$I$2224,"Prolog Transportes",Pedidos!$F$2:$F$2224,$A81,Pedidos!$V$2:$V$2224,"SIM")/B81,"") | J81: =IFERROR(AVERAGEIFS(Pedidos!$K$2:$K$2224,Pedidos!$X$2:$X$2224,"SIM",Pedidos!$I$2:$I$2224,"Prolog Transportes",Pedidos!$F$2:$F$2224,$A81),"") | K81: =IFERROR(MAX(0,1-D81/E81),"")
A82: 60-70 | B82: =COUNTIFS(Pedidos!$X$2:$X$2224,"SIM",Pedidos!$I$2:$I$2224,"Prolog Transportes",Pedidos!$F$2:$F$2224,$A82) -> 0 | C82: =IFERROR(AVERAGEIFS(Pedidos!$G$2:$G$2224,Pedidos!$X$2:$X$2224,"SIM",Pedidos!$I$2:$I$2224,"Prolog Transportes",Pedidos!$F$2:$F$2224,$A82),"") | D82: =IFERROR(AVERAGEIFS(Pedidos!$J$2:$J$2224,Pedidos!$X$2:$X$2224,"SIM",Pedidos!$I$2:$I$2224,"Prolog Transportes",Pedidos!$F$2:$F$2224,$A82),"") | E82: =IFERROR(AVERAGEIFS(Pedidos!$S$2:$S$2224,Pedidos!$X$2:$X$2224,"SIM",Pedidos!$I$2:$I$2224,"Prolog Transportes",Pedidos!$F$2:$F$2224,$A82),"") | F82: =IFERROR(E82/D82-1,"") | G82: =IFERROR(SUMIFS(Pedidos!$J$2:$J$2224,Pedidos!$X$2:$X$2224,"SIM",Pedidos!$I$2:$I$2224,"Prolog Transportes",Pedidos!$F$2:$F$2224,$A82)/SUMIFS(Pedidos!$H$2:$H$2224,Pedidos!$X$2:$X$2224,"SIM",Pedidos!$I$2:$I$2224,"Prolog Transportes",Pedidos!$F$2:$F$2224,$A82),"") | H82: =IFERROR(SUMIFS(Pedidos!$S$2:$S$2224,Pedidos!$X$2:$X$2224,"SIM",Pedidos!$I$2:$I$2224,"Prolog Transportes",Pedidos!$F$2:$F$2224,$A82)/SUMIFS(Pedidos!$H$2:$H$2224,Pedidos!$X$2:$X$2224,"SIM",Pedidos!$I$2:$I$2224,"Prolog Transportes",Pedidos!$F$2:$F$2224,$A82),"") | I82: =IFERROR(COUNTIFS(Pedidos!$X$2:$X$2224,"SIM",Pedidos!$I$2:$I$2224,"Prolog Transportes",Pedidos!$F$2:$F$2224,$A82,Pedidos!$V$2:$V$2224,"SIM")/B82,"") | J82: =IFERROR(AVERAGEIFS(Pedidos!$K$2:$K$2224,Pedidos!$X$2:$X$2224,"SIM",Pedidos!$I$2:$I$2224,"Prolog Transportes",Pedidos!$F$2:$F$2224,$A82),"") | K82: =IFERROR(MAX(0,1-D82/E82),"")
A83: 70-80 | B83: =COUNTIFS(Pedidos!$X$2:$X$2224,"SIM",Pedidos!$I$2:$I$2224,"Prolog Transportes",Pedidos!$F$2:$F$2224,$A83) -> 0 | C83: =IFERROR(AVERAGEIFS(Pedidos!$G$2:$G$2224,Pedidos!$X$2:$X$2224,"SIM",Pedidos!$I$2:$I$2224,"Prolog Transportes",Pedidos!$F$2:$F$2224,$A83),"") | D83: =IFERROR(AVERAGEIFS(Pedidos!$J$2:$J$2224,Pedidos!$X$2:$X$2224,"SIM",Pedidos!$I$2:$I$2224,"Prolog Transportes",Pedidos!$F$2:$F$2224,$A83),"") | E83: =IFERROR(AVERAGEIFS(Pedidos!$S$2:$S$2224,Pedidos!$X$2:$X$2224,"SIM",Pedidos!$I$2:$I$2224,"Prolog Transportes",Pedidos!$F$2:$F$2224,$A83),"") | F83: =IFERROR(E83/D83-1,"") | G83: =IFERROR(SUMIFS(Pedidos!$J$2:$J$2224,Pedidos!$X$2:$X$2224,"SIM",Pedidos!$I$2:$I$2224,"Prolog Transportes",Pedidos!$F$2:$F$2224,$A83)/SUMIFS(Pedidos!$H$2:$H$2224,Pedidos!$X$2:$X$2224,"SIM",Pedidos!$I$2:$I$2224,"Prolog Transportes",Pedidos!$F$2:$F$2224,$A83),"") | H83: =IFERROR(SUMIFS(Pedidos!$S$2:$S$2224,Pedidos!$X$2:$X$2224,"SIM",Pedidos!$I$2:$I$2224,"Prolog Transportes",Pedidos!$F$2:$F$2224,$A83)/SUMIFS(Pedidos!$H$2:$H$2224,Pedidos!$X$2:$X$2224,"SIM",Pedidos!$I$2:$I$2224,"Prolog Transportes",Pedidos!$F$2:$F$2224,$A83),"") | I83: =IFERROR(COUNTIFS(Pedidos!$X$2:$X$2224,"SIM",Pedidos!$I$2:$I$2224,"Prolog Transportes",Pedidos!$F$2:$F$2224,$A83,Pedidos!$V$2:$V$2224,"SIM")/B83,"") | J83: =IFERROR(AVERAGEIFS(Pedidos!$K$2:$K$2224,Pedidos!$X$2:$X$2224,"SIM",Pedidos!$I$2:$I$2224,"Prolog Transportes",Pedidos!$F$2:$F$2224,$A83),"") | K83: =IFERROR(MAX(0,1-D83/E83),"")
A84: 80-100 | B84: =COUNTIFS(Pedidos!$X$2:$X$2224,"SIM",Pedidos!$I$2:$I$2224,"Prolog Transportes",Pedidos!$F$2:$F$2224,$A84) -> 0 | C84: =IFERROR(AVERAGEIFS(Pedidos!$G$2:$G$2224,Pedidos!$X$2:$X$2224,"SIM",Pedidos!$I$2:$I$2224,"Prolog Transportes",Pedidos!$F$2:$F$2224,$A84),"") | D84: =IFERROR(AVERAGEIFS(Pedidos!$J$2:$J$2224,Pedidos!$X$2:$X$2224,"SIM",Pedidos!$I$2:$I$2224,"Prolog Transportes",Pedidos!$F$2:$F$2224,$A84),"") | E84: =IFERROR(AVERAGEIFS(Pedidos!$S$2:$S$2224,Pedidos!$X$2:$X$2224,"SIM",Pedidos!$I$2:$I$2224,"Prolog Transportes",Pedidos!$F$2:$F$2224,$A84),"") | F84: =IFERROR(E84/D84-1,"") | G84: =IFERROR(SUMIFS(Pedidos!$J$2:$J$2224,Pedidos!$X$2:$X$2224,"SIM",Pedidos!$I$2:$I$2224,"Prolog Transportes",Pedidos!$F$2:$F$2224,$A84)/SUMIFS(Pedidos!$H$2:$H$2224,Pedidos!$X$2:$X$2224,"SIM",Pedidos!$I$2:$I$2224,"Prolog Transportes",Pedidos!$F$2:$F$2224,$A84),"") | H84: =IFERROR(SUMIFS(Pedidos!$S$2:$S$2224,Pedidos!$X$2:$X$2224,"SIM",Pedidos!$I$2:$I$2224,"Prolog Transportes",Pedidos!$F$2:$F$2224,$A84)/SUMIFS(Pedidos!$H$2:$H$2224,Pedidos!$X$2:$X$2224,"SIM",Pedidos!$I$2:$I$2224,"Prolog Transportes",Pedidos!$F$2:$F$2224,$A84),"") | I84: =IFERROR(COUNTIFS(Pedidos!$X$2:$X$2224,"SIM",Pedidos!$I$2:$I$2224,"Prolog Transportes",Pedidos!$F$2:$F$2224,$A84,Pedidos!$V$2:$V$2224,"SIM")/B84,"") | J84: =IFERROR(AVERAGEIFS(Pedidos!$K$2:$K$2224,Pedidos!$X$2:$X$2224,"SIM",Pedidos!$I$2:$I$2224,"Prolog Transportes",Pedidos!$F$2:$F$2224,$A84),"") | K84: =IFERROR(MAX(0,1-D84/E84),"")
A85: 100-120 | B85: =COUNTIFS(Pedidos!$X$2:$X$2224,"SIM",Pedidos!$I$2:$I$2224,"Prolog Transportes",Pedidos!$F$2:$F$2224,$A85) -> 0 | C85: =IFERROR(AVERAGEIFS(Pedidos!$G$2:$G$2224,Pedidos!$X$2:$X$2224,"SIM",Pedidos!$I$2:$I$2224,"Prolog Transportes",Pedidos!$F$2:$F$2224,$A85),"") | D85: =IFERROR(AVERAGEIFS(Pedidos!$J$2:$J$2224,Pedidos!$X$2:$X$2224,"SIM",Pedidos!$I$2:$I$2224,"Prolog Transportes",Pedidos!$F$2:$F$2224,$A85),"") | E85: =IFERROR(AVERAGEIFS(Pedidos!$S$2:$S$2224,Pedidos!$X$2:$X$2224,"SIM",Pedidos!$I$2:$I$2224,"Prolog Transportes",Pedidos!$F$2:$F$2224,$A85),"") | F85: =IFERROR(E85/D85-1,"") | G85: =IFERROR(SUMIFS(Pedidos!$J$2:$J$2224,Pedidos!$X$2:$X$2224,"SIM",Pedidos!$I$2:$I$2224,"Prolog Transportes",Pedidos!$F$2:$F$2224,$A85)/SUMIFS(Pedidos!$H$2:$H$2224,Pedidos!$X$2:$X$2224,"SIM",Pedidos!$I$2:$I$2224,"Prolog Transportes",Pedidos!$F$2:$F$2224,$A85),"") | H85: =IFERROR(SUMIFS(Pedidos!$S$2:$S$2224,Pedidos!$X$2:$X$2224,"SIM",Pedidos!$I$2:$I$2224,"Prolog Transportes",Pedidos!$F$2:$F$2224,$A85)/SUMIFS(Pedidos!$H$2:$H$2224,Pedidos!$X$2:$X$2224,"SIM",Pedidos!$I$2:$I$2224,"Prolog Transportes",Pedidos!$F$2:$F$2224,$A85),"") | I85: =IFERROR(COUNTIFS(Pedidos!$X$2:$X$2224,"SIM",Pedidos!$I$2:$I$2224,"Prolog Transportes",Pedidos!$F$2:$F$2224,$A85,Pedidos!$V$2:$V$2224,"SIM")/B85,"") | J85: =IFERROR(AVERAGEIFS(Pedidos!$K$2:$K$2224,Pedidos!$X$2:$X$2224,"SIM",Pedidos!$I$2:$I$2224,"Prolog Transportes",Pedidos!$F$2:$F$2224,$A85),"") | K85: =IFERROR(MAX(0,1-D85/E85),"")
A86: 120-150 | B86: =COUNTIFS(Pedidos!$X$2:$X$2224,"SIM",Pedidos!$I$2:$I$2224,"Prolog Transportes",Pedidos!$F$2:$F$2224,$A86) -> 0 | C86: =IFERROR(AVERAGEIFS(Pedidos!$G$2:$G$2224,Pedidos!$X$2:$X$2224,"SIM",Pedidos!$I$2:$I$2224,"Prolog Transportes",Pedidos!$F$2:$F$2224,$A86),"") | D86: =IFERROR(AVERAGEIFS(Pedidos!$J$2:$J$2224,Pedidos!$X$2:$X$2224,"SIM",Pedidos!$I$2:$I$2224,"Prolog Transportes",Pedidos!$F$2:$F$2224,$A86),"") | E86: =IFERROR(AVERAGEIFS(Pedidos!$S$2:$S$2224,Pedidos!$X$2:$X$2224,"SIM",Pedidos!$I$2:$I$2224,"Prolog Transportes",Pedidos!$F$2:$F$2224,$A86),"") | F86: =IFERROR(E86/D86-1,"") | G86: =IFERROR(SUMIFS(Pedidos!$J$2:$J$2224,Pedidos!$X$2:$X$2224,"SIM",Pedidos!$I$2:$I$2224,"Prolog Transportes",Pedidos!$F$2:$F$2224,$A86)/SUMIFS(Pedidos!$H$2:$H$2224,Pedidos!$X$2:$X$2224,"SIM",Pedidos!$I$2:$I$2224,"Prolog Transportes",Pedidos!$F$2:$F$2224,$A86),"") | H86: =IFERROR(SUMIFS(Pedidos!$S$2:$S$2224,Pedidos!$X$2:$X$2224,"SIM",Pedidos!$I$2:$I$2224,"Prolog Transportes",Pedidos!$F$2:$F$2224,$A86)/SUMIFS(Pedidos!$H$2:$H$2224,Pedidos!$X$2:$X$2224,"SIM",Pedidos!$I$2:$I$2224,"Prolog Transportes",Pedidos!$F$2:$F$2224,$A86),"") | I86: =IFERROR(COUNTIFS(Pedidos!$X$2:$X$2224,"SIM",Pedidos!$I$2:$I$2224,"Prolog Transportes",Pedidos!$F$2:$F$2224,$A86,Pedidos!$V$2:$V$2224,"SIM")/B86,"") | J86: =IFERROR(AVERAGEIFS(Pedidos!$K$2:$K$2224,Pedidos!$X$2:$X$2224,"SIM",Pedidos!$I$2:$I$2224,"Prolog Transportes",Pedidos!$F$2:$F$2224,$A86),"") | K86: =IFERROR(MAX(0,1-D86/E86),"")
A87: 150-170 | B87: =COUNTIFS(Pedidos!$X$2:$X$2224,"SIM",Pedidos!$I$2:$I$2224,"Prolog Transportes",Pedidos!$F$2:$F$2224,$A87) -> 0 | C87: =IFERROR(AVERAGEIFS(Pedidos!$G$2:$G$2224,Pedidos!$X$2:$X$2224,"SIM",Pedidos!$I$2:$I$2224,"Prolog Transportes",Pedidos!$F$2:$F$2224,$A87),"") | D87: =IFERROR(AVERAGEIFS(Pedidos!$J$2:$J$2224,Pedidos!$X$2:$X$2224,"SIM",Pedidos!$I$2:$I$2224,"Prolog Transportes",Pedidos!$F$2:$F$2224,$A87),"") | E87: =IFERROR(AVERAGEIFS(Pedidos!$S$2:$S$2224,Pedidos!$X$2:$X$2224,"SIM",Pedidos!$I$2:$I$2224,"Prolog Transportes",Pedidos!$F$2:$F$2224,$A87),"") | F87: =IFERROR(E87/D87-1,"") | G87: =IFERROR(SUMIFS(Pedidos!$J$2:$J$2224,Pedidos!$X$2:$X$2224,"SIM",Pedidos!$I$2:$I$2224,"Prolog Transportes",Pedidos!$F$2:$F$2224,$A87)/SUMIFS(Pedidos!$H$2:$H$2224,Pedidos!$X$2:$X$2224,"SIM",Pedidos!$I$2:$I$2224,"Prolog Transportes",Pedidos!$F$2:$F$2224,$A87),"") | H87: =IFERROR(SUMIFS(Pedidos!$S$2:$S$2224,Pedidos!$X$2:$X$2224,"SIM",Pedidos!$I$2:$I$2224,"Prolog Transportes",Pedidos!$F$2:$F$2224,$A87)/SUMIFS(Pedidos!$H$2:$H$2224,Pedidos!$X$2:$X$2224,"SIM",Pedidos!$I$2:$I$2224,"Prolog Transportes",Pedidos!$F$2:$F$2224,$A87),"") | I87: =IFERROR(COUNTIFS(Pedidos!$X$2:$X$2224,"SIM",Pedidos!$I$2:$I$2224,"Prolog Transportes",Pedidos!$F$2:$F$2224,$A87,Pedidos!$V$2:$V$2224,"SIM")/B87,"") | J87: =IFERROR(AVERAGEIFS(Pedidos!$K$2:$K$2224,Pedidos!$X$2:$X$2224,"SIM",Pedidos!$I$2:$I$2224,"Prolog Transportes",Pedidos!$F$2:$F$2224,$A87),"") | K87: =IFERROR(MAX(0,1-D87/E87),"")
A88: 170-200 | B88: =COUNTIFS(Pedidos!$X$2:$X$2224,"SIM",Pedidos!$I$2:$I$2224,"Prolog Transportes",Pedidos!$F$2:$F$2224,$A88) -> 0 | C88: =IFERROR(AVERAGEIFS(Pedidos!$G$2:$G$2224,Pedidos!$X$2:$X$2224,"SIM",Pedidos!$I$2:$I$2224,"Prolog Transportes",Pedidos!$F$2:$F$2224,$A88),"") | D88: =IFERROR(AVERAGEIFS(Pedidos!$J$2:$J$2224,Pedidos!$X$2:$X$2224,"SIM",Pedidos!$I$2:$I$2224,"Prolog Transportes",Pedidos!$F$2:$F$2224,$A88),"") | E88: =IFERROR(AVERAGEIFS(Pedidos!$S$2:$S$2224,Pedidos!$X$2:$X$2224,"SIM",Pedidos!$I$2:$I$2224,"Prolog Transportes",Pedidos!$F$2:$F$2224,$A88),"") | F88: =IFERROR(E88/D88-1,"") | G88: =IFERROR(SUMIFS(Pedidos!$J$2:$J$2224,Pedidos!$X$2:$X$2224,"SIM",Pedidos!$I$2:$I$2224,"Prolog Transportes",Pedidos!$F$2:$F$2224,$A88)/SUMIFS(Pedidos!$H$2:$H$2224,Pedidos!$X$2:$X$2224,"SIM",Pedidos!$I$2:$I$2224,"Prolog Transportes",Pedidos!$F$2:$F$2224,$A88),"") | H88: =IFERROR(SUMIFS(Pedidos!$S$2:$S$2224,Pedidos!$X$2:$X$2224,"SIM",Pedidos!$I$2:$I$2224,"Prolog Transportes",Pedidos!$F$2:$F$2224,$A88)/SUMIFS(Pedidos!$H$2:$H$2224,Pedidos!$X$2:$X$2224,"SIM",Pedidos!$I$2:$I$2224,"Prolog Transportes",Pedidos!$F$2:$F$2224,$A88),"") | I88: =IFERROR(COUNTIFS(Pedidos!$X$2:$X$2224,"SIM",Pedidos!$I$2:$I$2224,"Prolog Transportes",Pedidos!$F$2:$F$2224,$A88,Pedidos!$V$2:$V$2224,"SIM")/B88,"") | J88: =IFERROR(AVERAGEIFS(Pedidos!$K$2:$K$2224,Pedidos!$X$2:$X$2224,"SIM",Pedidos!$I$2:$I$2224,"Prolog Transportes",Pedidos!$F$2:$F$2224,$A88),"") | K88: =IFERROR(MAX(0,1-D88/E88),"")
... A90: >250 | B90: =COUNTIFS(Pedidos!$X$2:$X$2224,"SIM",Pedidos!$I$2:$I$2224,"Prolog Transportes",Pedidos!$F$2:$F$2224,$A90) -> 0 | C90: =IFERROR(AVERAGEIFS(Pedidos!$G$2:$G$2224,Pedidos!$X$2:$X$2224,"SIM",Pedidos!$I$2:$I$2224,"Prolog Transportes",Pedidos!$F$2:$F$2224,$A90),"") | D90: =IFERROR(AVERAGEIFS(Pedidos!$J$2:$J$2224,Pedidos!$X$2:$X$2224,"SIM",Pedidos!$I$2:$I$2224,"Prolog Transportes",Pedidos!$F$2:$F$2224,$A90),"") | E90: =IFERROR(AVERAGEIFS(Pedidos!$S$2:$S$2224,Pedidos!$X$2:$X$2224,"SIM",Pedidos!$I$2:$I$2224,"Prolog Transportes",Pedidos!$F$2:$F$2224,$A90),"") | F90: =IFERROR(E90/D90-1,"") | G90: =IFERROR(SUMIFS(Pedidos!$J$2:$J$2224,Pedidos!$X$2:$X$2224,"SIM",Pedidos!$I$2:$I$2224,"Prolog Transportes",Pedidos!$F$2:$F$2224,$A90)/SUMIFS(Pedidos!$H$2:$H$2224,Pedidos!$X$2:$X$2224,"SIM",Pedidos!$I$2:$I$2224,"Prolog Transportes",Pedidos!$F$2:$F$2224,$A90),"") | H90: =IFERROR(SUMIFS(Pedidos!$S$2:$S$2224,Pedidos!$X$2:$X$2224,"SIM",Pedidos!$I$2:$I$2224,"Prolog Transportes",Pedidos!$F$2:$F$2224,$A90)/SUMIFS(Pedidos!$H$2:$H$2224,Pedidos!$X$2:$X$2224,"SIM",Pedidos!$I$2:$I$2224,"Prolog Transportes",Pedidos!$F$2:$F$2224,$A90),"") | I90: =IFERROR(COUNTIFS(Pedidos!$X$2:$X$2224,"SIM",Pedidos!$I$2:$I$2224,"Prolog Transportes",Pedidos!$F$2:$F$2224,$A90,Pedidos!$V$2:$V$2224,"SIM")/B90,"") | J90: =IFERROR(AVERAGEIFS(Pedidos!$K$2:$K$2224,Pedidos!$X$2:$X$2224,"SIM",Pedidos!$I$2:$I$2224,"Prolog Transportes",Pedidos!$F$2:$F$2224,$A90),"") | K90: =IFERROR(MAX(0,1-D90/E90),"")
A91: TOTAL | B91: =COUNTIFS(Pedidos!$X$2:$X$2224,"SIM",Pedidos!$I$2:$I$2224,"Prolog Transportes") -> 1 | C91: =IFERROR(AVERAGEIFS(Pedidos!$G$2:$G$2224,Pedidos!$X$2:$X$2224,"SIM",Pedidos!$I$2:$I$2224,"Prolog Transportes"),"") -> 33 | D91: =IFERROR(AVERAGEIFS(Pedidos!$J$2:$J$2224,Pedidos!$X$2:$X$2224,"SIM",Pedidos!$I$2:$I$2224,"Prolog Transportes"),"") -> 82.17 | E91: =IFERROR(AVERAGEIFS(Pedidos!$S$2:$S$2224,Pedidos!$X$2:$X$2224,"SIM",Pedidos!$I$2:$I$2224,"Prolog Transportes"),"") -> 120.29545 | F91: =IFERROR(E91/D91-1,"") -> 0.46398265 | G91: =IFERROR(SUMIFS(Pedidos!$J$2:$J$2224,Pedidos!$X$2:$X$2224,"SIM",Pedidos!$I$2:$I$2224,"Prolog Transportes")/SUMIFS(Pedidos!$H$2:$H$2224,Pedidos!$X$2:$X$2224,"SIM",Pedidos!$I$2:$I$2224,"Prolog Transportes"),"") -> 0.18675424 | H91: =IFERROR(SUMIFS(Pedidos!$S$2:$S$2224,Pedidos!$X$2:$X$2224,"SIM",Pedidos!$I$2:$I$2224,"Prolog Transportes")/SUMIFS(Pedidos!$H$2:$H$2224,Pedidos!$X$2:$X$2224,"SIM",Pedidos!$I$2:$I$2224,"Prolog Transportes"),"") -> 0.27340497 | I91: =IFERROR(COUNTIFS(Pedidos!$X$2:$X$2224,"SIM",Pedidos!$I$2:$I$2224,"Prolog Transportes",Pedidos!$V$2:$V$2224,"SIM")/B91,"") -> 0 | J91: =IFERROR(AVERAGEIFS(Pedidos!$K$2:$K$2224,Pedidos!$X$2:$X$2224,"SIM",Pedidos!$I$2:$I$2224,"Prolog Transportes"),"") -> 82.21 | K91: =IFERROR(MAX(0,1-D91/E91),"") -> 0.3169318

Sheet Cidade x Faixa
A1: Top 20 cidades × faixa de peso — PROLOG vs custo atual (%) | verde = PROLOG mais competitiva, vermelho = precisa melhorar
A3: 1) Quantidade de pedidos
A4: Cidade | B4: 0-20 | C4: 20-35 | D4: 35-40 | E4: 40-50 | F4: 50-60 | G4: 60-70 | H4: 70-80 | I4: 80-100 | J4: 100-120 | K4: 120-150 | L4: 150-170 | M4: 170-200 | N4: 200-250 | O4: >250 | P4: Total
A5: Rio de Janeiro | B5: =COUNTIFS(Pedidos!$E$2:$E$2224,$A5,Pedidos!$F$2:$F$2224,"0-20") -> 64 | C5: =COUNTIFS(Pedidos!$E$2:$E$2224,$A5,Pedidos!$F$2:$F$2224,"20-35") -> 263 | D5: =COUNTIFS(Pedidos!$E$2:$E$2224,$A5,Pedidos!$F$2:$F$2224,"35-40") -> 163 | E5: =COUNTIFS(Pedidos!$E$2:$E$2224,$A5,Pedidos!$F$2:$F$2224,"40-50") -> 154 | F5: =COUNTIFS(Pedidos!$E$2:$E$2224,$A5,Pedidos!$F$2:$F$2224,"50-60") -> 181 | G5: =COUNTIFS(Pedidos!$E$2:$E$2224,$A5,Pedidos!$F$2:$F$2224,"60-70") -> 112 | H5: =COUNTIFS(Pedidos!$E$2:$E$2224,$A5,Pedidos!$F$2:$F$2224,"70-80") -> 11 | I5: =COUNTIFS(Pedidos!$E$2:$E$2224,$A5,Pedidos!$F$2:$F$2224,"80-100") -> 19 | J5: =COUNTIFS(Pedidos!$E$2:$E$2224,$A5,Pedidos!$F$2:$F$2224,"100-120") -> 21 | K5: =COUNTIFS(Pedidos!$E$2:$E$2224,$A5,Pedidos!$F$2:$F$2224,"120-150") -> 39 | L5: =COUNTIFS(Pedidos!$E$2:$E$2224,$A5,Pedidos!$F$2:$F$2224,"150-170") -> 2 | M5: =COUNTIFS(Pedidos!$E$2:$E$2224,$A5,Pedidos!$F$2:$F$2224,"170-200") -> 0 | N5: =COUNTIFS(Pedidos!$E$2:$E$2224,$A5,Pedidos!$F$2:$F$2224,"200-250") -> 1 | O5: =COUNTIFS(Pedidos!$E$2:$E$2224,$A5,Pedidos!$F$2:$F$2224,">250") -> 0 | P5: =COUNTIFS(Pedidos!$E$2:$E$2224,$A5) -> 1030
A6: São Gonçalo | B6: =COUNTIFS(Pedidos!$E$2:$E$2224,$A6,Pedidos!$F$2:$F$2224,"0-20") -> 8 | C6: =COUNTIFS(Pedidos!$E$2:$E$2224,$A6,Pedidos!$F$2:$F$2224,"20-35") -> 29 | D6: =COUNTIFS(Pedidos!$E$2:$E$2224,$A6,Pedidos!$F$2:$F$2224,"35-40") -> 18 | E6: =COUNTIFS(Pedidos!$E$2:$E$2224,$A6,Pedidos!$F$2:$F$2224,"40-50") -> 22 | F6: =COUNTIFS(Pedidos!$E$2:$E$2224,$A6,Pedidos!$F$2:$F$2224,"50-60") -> 25 | G6: =COUNTIFS(Pedidos!$E$2:$E$2224,$A6,Pedidos!$F$2:$F$2224,"60-70") -> 19 | H6: =COUNTIFS(Pedidos!$E$2:$E$2224,$A6,Pedidos!$F$2:$F$2224,"70-80") -> 3 | I6: =COUNTIFS(Pedidos!$E$2:$E$2224,$A6,Pedidos!$F$2:$F$2224,"80-100") -> 3 | J6: =COUNTIFS(Pedidos!$E$2:$E$2224,$A6,Pedidos!$F$2:$F$2224,"100-120") -> 3 | K6: =COUNTIFS(Pedidos!$E$2:$E$2224,$A6,Pedidos!$F$2:$F$2224,"120-150") -> 4 | L6: =COUNTIFS(Pedidos!$E$2:$E$2224,$A6,Pedidos!$F$2:$F$2224,"150-170") -> 1 | M6: =COUNTIFS(Pedidos!$E$2:$E$2224,$A6,Pedidos!$F$2:$F$2224,"170-200") -> 0 | N6: =COUNTIFS(Pedidos!$E$2:$E$2224,$A6,Pedidos!$F$2:$F$2224,"200-250") -> 0 | O6: =COUNTIFS(Pedidos!$E$2:$E$2224,$A6,Pedidos!$F$2:$F$2224,">250") -> 0 | P6: =COUNTIFS(Pedidos!$E$2:$E$2224,$A6) -> 135
A7: Duque de Caxias | B7: =COUNTIFS(Pedidos!$E$2:$E$2224,$A7,Pedidos!$F$2:$F$2224,"0-20") -> 6 | C7: =COUNTIFS(Pedidos!$E$2:$E$2224,$A7,Pedidos!$F$2:$F$2224,"20-35") -> 16 | D7: =COUNTIFS(Pedidos!$E$2:$E$2224,$A7,Pedidos!$F$2:$F$2224,"35-40") -> 11 | E7: =COUNTIFS(Pedidos!$E$2:$E$2224,$A7,Pedidos!$F$2:$F$2224,"40-50") -> 16 | F7: =COUNTIFS(Pedidos!$E$2:$E$2224,$A7,Pedidos!$F$2:$F$2224,"50-60") -> 34 | G7: =COUNTIFS(Pedidos!$E$2:$E$2224,$A7,Pedidos!$F$2:$F$2224,"60-70") -> 12 | H7: =COUNTIFS(Pedidos!$E$2:$E$2224,$A7,Pedidos!$F$2:$F$2224,"70-80") -> 1 | I7: =COUNTIFS(Pedidos!$E$2:$E$2224,$A7,Pedidos!$F$2:$F$2224,"80-100") -> 1 | J7: =COUNTIFS(Pedidos!$E$2:$E$2224,$A7,Pedidos!$F$2:$F$2224,"100-120") -> 4 | K7: =COUNTIFS(Pedidos!$E$2:$E$2224,$A7,Pedidos!$F$2:$F$2224,"120-150") -> 5 | L7: =COUNTIFS(Pedidos!$E$2:$E$2224,$A7,Pedidos!$F$2:$F$2224,"150-170") -> 0 | M7: =COUNTIFS(Pedidos!$E$2:$E$2224,$A7,Pedidos!$F$2:$F$2224,"170-200") -> 0 | N7: =COUNTIFS(Pedidos!$E$2:$E$2224,$A7,Pedidos!$F$2:$F$2224,"200-250") -> 0 | O7: =COUNTIFS(Pedidos!$E$2:$E$2224,$A7,Pedidos!$F$2:$F$2224,">250") -> 0 | P7: =COUNTIFS(Pedidos!$E$2:$E$2224,$A7) -> 106
A8: Nova Iguaçu | B8: =COUNTIFS(Pedidos!$E$2:$E$2224,$A8,Pedidos!$F$2:$F$2224,"0-20") -> 2 | C8: =COUNTIFS(Pedidos!$E$2:$E$2224,$A8,Pedidos!$F$2:$F$2224,"20-35") -> 17 | D8: =COUNTIFS(Pedidos!$E$2:$E$2224,$A8,Pedidos!$F$2:$F$2224,"35-40") -> 15 | E8: =COUNTIFS(Pedidos!$E$2:$E$2224,$A8,Pedidos!$F$2:$F$2224,"40-50") -> 12 | F8: =COUNTIFS(Pedidos!$E$2:$E$2224,$A8,Pedidos!$F$2:$F$2224,"50-60") -> 19 | G8: =COUNTIFS(Pedidos!$E$2:$E$2224,$A8,Pedidos!$F$2:$F$2224,"60-70") -> 17 | H8: =COUNTIFS(Pedidos!$E$2:$E$2224,$A8,Pedidos!$F$2:$F$2224,"70-80") -> 2 | I8: =COUNTIFS(Pedidos!$E$2:$E$2224,$A8,Pedidos!$F$2:$F$2224,"80-100") -> 2 | J8: =COUNTIFS(Pedidos!$E$2:$E$2224,$A8,Pedidos!$F$2:$F$2224,"100-120") -> 5 | K8: =COUNTIFS(Pedidos!$E$2:$E$2224,$A8,Pedidos!$F$2:$F$2224,"120-150") -> 4 | L8: =COUNTIFS(Pedidos!$E$2:$E$2224,$A8,Pedidos!$F$2:$F$2224,"150-170") -> 0 | M8: =COUNTIFS(Pedidos!$E$2:$E$2224,$A8,Pedidos!$F$2:$F$2224,"170-200") -> 0 | N8: =COUNTIFS(Pedidos!$E$2:$E$2224,$A8,Pedidos!$F$2:$F$2224,"200-250") -> 0 | O8: =COUNTIFS(Pedidos!$E$2:$E$2224,$A8,Pedidos!$F$2:$F$2224,">250") -> 0 | P8: =COUNTIFS(Pedidos!$E$2:$E$2224,$A8) -> 95
A9: Niterói | B9: =COUNTIFS(Pedidos!$E$2:$E$2224,$A9,Pedidos!$F$2:$F$2224,"0-20") -> 2 | C9: =COUNTIFS(Pedidos!$E$2:$E$2224,$A9,Pedidos!$F$2:$F$2224,"20-35") -> 11 | D9: =COUNTIFS(Pedidos!$E$2:$E$2224,$A9,Pedidos!$F$2:$F$2224,"35-40") -> 11 | E9: =COUNTIFS(Pedidos!$E$2:$E$2224,$A9,Pedidos!$F$2:$F$2224,"40-50") -> 15 | F9: =COUNTIFS(Pedidos!$E$2:$E$2224,$A9,Pedidos!$F$2:$F$2224,"50-60") -> 19 | G9: =COUNTIFS(Pedidos!$E$2:$E$2224,$A9,Pedidos!$F$2:$F$2224,"60-70") -> 7 | H9: =COUNTIFS(Pedidos!$E$2:$E$2224,$A9,Pedidos!$F$2:$F$2224,"70-80") -> 0 | I9: =COUNTIFS(Pedidos!$E$2:$E$2224,$A9,Pedidos!$F$2:$F$2224,"80-100") -> 1 | J9: =COUNTIFS(Pedidos!$E$2:$E$2224,$A9,Pedidos!$F$2:$F$2224,"100-120") -> 1 | K9: =COUNTIFS(Pedidos!$E$2:$E$2224,$A9,Pedidos!$F$2:$F$2224,"120-150") -> 1 | L9: =COUNTIFS(Pedidos!$E$2:$E$2224,$A9,Pedidos!$F$2:$F$2224,"150-170") -> 0 | M9: =COUNTIFS(Pedidos!$E$2:$E$2224,$A9,Pedidos!$F$2:$F$2224,"170-200") -> 0 | N9: =COUNTIFS(Pedidos!$E$2:$E$2224,$A9,Pedidos!$F$2:$F$2224,"200-250") -> 0 | O9: =COUNTIFS(Pedidos!$E$2:$E$2224,$A9,Pedidos!$F$2:$F$2224,">250") -> 0 | P9: =COUNTIFS(Pedidos!$E$2:$E$2224,$A9) -> 68
A10: Campos dos Goytacazes | B10: =COUNTIFS(Pedidos!$E$2:$E$2224,$A10,Pedidos!$F$2:$F$2224,"0-20") -> 0 | C10: =COUNTIFS(Pedidos!$E$2:$E$2224,$A10,Pedidos!$F$2:$F$2224,"20-35") -> 16 | D10: =COUNTIFS(Pedidos!$E$2:$E$2224,$A10,Pedidos!$F$2:$F$2224,"35-40") -> 8 | E10: =COUNTIFS(Pedidos!$E$2:$E$2224,$A10,Pedidos!$F$2:$F$2224,"40-50") -> 8 | F10: =COUNTIFS(Pedidos!$E$2:$E$2224,$A10,Pedidos!$F$2:$F$2224,"50-60") -> 9 | G10: =COUNTIFS(Pedidos!$E$2:$E$2224,$A10,Pedidos!$F$2:$F$2224,"60-70") -> 6 | H10: =COUNTIFS(Pedidos!$E$2:$E$2224,$A10,Pedidos!$F$2:$F$2224,"70-80") -> 0 | I10: =COUNTIFS(Pedidos!$E$2:$E$2224,$A10,Pedidos!$F$2:$F$2224,"80-100") -> 2 | J10: =COUNTIFS(Pedidos!$E$2:$E$2224,$A10,Pedidos!$F$2:$F$2224,"100-120") -> 4 | K10: =COUNTIFS(Pedidos!$E$2:$E$2224,$A10,Pedidos!$F$2:$F$2224,"120-150") -> 0 | L10: =COUNTIFS(Pedidos!$E$2:$E$2224,$A10,Pedidos!$F$2:$F$2224,"150-170") -> 0 | M10: =COUNTIFS(Pedidos!$E$2:$E$2224,$A10,Pedidos!$F$2:$F$2224,"170-200") -> 0 | N10: =COUNTIFS(Pedidos!$E$2:$E$2224,$A10,Pedidos!$F$2:$F$2224,"200-250") -> 0 | O10: =COUNTIFS(Pedidos!$E$2:$E$2224,$A10,Pedidos!$F$2:$F$2224,">250") -> 0 | P10: =COUNTIFS(Pedidos!$E$2:$E$2224,$A10) -> 53
A11: Belford Roxo | B11: =COUNTIFS(Pedidos!$E$2:$E$2224,$A11,Pedidos!$F$2:$F$2224,"0-20") -> 4 | C11: =COUNTIFS(Pedidos!$E$2:$E$2224,$A11,Pedidos!$F$2:$F$2224,"20-35") -> 3 | D11: =COUNTIFS(Pedidos!$E$2:$E$2224,$A11,Pedidos!$F$2:$F$2224,"35-40") -> 6 | E11: =COUNTIFS(Pedidos!$E$2:$E$2224,$A11,Pedidos!$F$2:$F$2224,"40-50") -> 11 | F11: =COUNTIFS(Pedidos!$E$2:$E$2224,$A11,Pedidos!$F$2:$F$2224,"50-60") -> 10 | G11: =COUNTIFS(Pedidos!$E$2:$E$2224,$A11,Pedidos!$F$2:$F$2224,"60-70") -> 7 | H11: =COUNTIFS(Pedidos!$E$2:$E$2224,$A11,Pedidos!$F$2:$F$2224,"70-80") -> 3 | I11: =COUNTIFS(Pedidos!$E$2:$E$2224,$A11,Pedidos!$F$2:$F$2224,"80-100") -> 2 | J11: =COUNTIFS(Pedidos!$E$2:$E$2224,$A11,Pedidos!$F$2:$F$2224,"100-120") -> 2 | K11: =COUNTIFS(Pedidos!$E$2:$E$2224,$A11,Pedidos!$F$2:$F$2224,"120-150") -> 1 | L11: =COUNTIFS(Pedidos!$E$2:$E$2224,$A11,Pedidos!$F$2:$F$2224,"150-170") -> 0 | M11: =COUNTIFS(Pedidos!$E$2:$E$2224,$A11,Pedidos!$F$2:$F$2224,"170-200") -> 0 | N11: =COUNTIFS(Pedidos!$E$2:$E$2224,$A11,Pedidos!$F$2:$F$2224,"200-250") -> 0 | O11: =COUNTIFS(Pedidos!$E$2:$E$2224,$A11,Pedidos!$F$2:$F$2224,">250") -> 0 | P11: =COUNTIFS(Pedidos!$E$2:$E$2224,$A11) -> 49
A12: Macaé | B12: =COUNTIFS(Pedidos!$E$2:$E$2224,$A12,Pedidos!$F$2:$F$2224,"0-20") -> 1 | C12: =COUNTIFS(Pedidos!$E$2:$E$2224,$A12,Pedidos!$F$2:$F$2224,"20-35") -> 8 | D12: =COUNTIFS(Pedidos!$E$2:$E$2224,$A12,Pedidos!$F$2:$F$2224,"35-40") -> 4 | E12: =COUNTIFS(Pedidos!$E$2:$E$2224,$A12,Pedidos!$F$2:$F$2224,"40-50") -> 8 | F12: =COUNTIFS(Pedidos!$E$2:$E$2224,$A12,Pedidos!$F$2:$F$2224,"50-60") -> 8 | G12: =COUNTIFS(Pedidos!$E$2:$E$2224,$A12,Pedidos!$F$2:$F$2224,"60-70") -> 7 | H12: =COUNTIFS(Pedidos!$E$2:$E$2224,$A12,Pedidos!$F$2:$F$2224,"70-80") -> 0 | I12: =COUNTIFS(Pedidos!$E$2:$E$2224,$A12,Pedidos!$F$2:$F$2224,"80-100") -> 3 | J12: =COUNTIFS(Pedidos!$E$2:$E$2224,$A12,Pedidos!$F$2:$F$2224,"100-120") -> 0 | K12: =COUNTIFS(Pedidos!$E$2:$E$2224,$A12,Pedidos!$F$2:$F$2224,"120-150") -> 5 | L12: =COUNTIFS(Pedidos!$E$2:$E$2224,$A12,Pedidos!$F$2:$F$2224,"150-170") -> 0 | M12: =COUNTIFS(Pedidos!$E$2:$E$2224,$A12,Pedidos!$F$2:$F$2224,"170-200") -> 1 | N12: =COUNTIFS(Pedidos!$E$2:$E$2224,$A12,Pedidos!$F$2:$F$2224,"200-250") -> 0 | O12: =COUNTIFS(Pedidos!$E$2:$E$2224,$A12,Pedidos!$F$2:$F$2224,">250") -> 0 | P12: =COUNTIFS(Pedidos!$E$2:$E$2224,$A12) -> 45
A13: São João de Meriti | B13: =COUNTIFS(Pedidos!$E$2:$E$2224,$A13,Pedidos!$F$2:$F$2224,"0-20") -> 1 | C13: =COUNTIFS(Pedidos!$E$2:$E$2224,$A13,Pedidos!$F$2:$F$2224,"20-35") -> 5 | D13: =COUNTIFS(Pedidos!$E$2:$E$2224,$A13,Pedidos!$F$2:$F$2224,"35-40") -> 6 | E13: =COUNTIFS(Pedidos!$E$2:$E$2224,$A13,Pedidos!$F$2:$F$2224,"40-50") -> 8 | F13: =COUNTIFS(Pedidos!$E$2:$E$2224,$A13,Pedidos!$F$2:$F$2224,"50-60") -> 7 | G13: =COUNTIFS(Pedidos!$E$2:$E$2224,$A13,Pedidos!$F$2:$F$2224,"60-70") -> 4 | H13: =COUNTIFS(Pedidos!$E$2:$E$2224,$A13,Pedidos!$F$2:$F$2224,"70-80") -> 0 | I13: =COUNTIFS(Pedidos!$E$2:$E$2224,$A13,Pedidos!$F$2:$F$2224,"80-100") -> 2 | J13: =COUNTIFS(Pedidos!$E$2:$E$2224,$A13,Pedidos!$F$2:$F$2224,"100-120") -> 1 | K13: =COUNTIFS(Pedidos!$E$2:$E$2224,$A13,Pedidos!$F$2:$F$2224,"120-150") -> 3 | L13: =COUNTIFS(Pedidos!$E$2:$E$2224,$A13,Pedidos!$F$2:$F$2224,"150-170") -> 0 | M13: =COUNTIFS(Pedidos!$E$2:$E$2224,$A13,Pedidos!$F$2:$F$2224,"170-200") -> 0 | N13: =COUNTIFS(Pedidos!$E$2:$E$2224,$A13,Pedidos!$F$2:$F$2224,"200-250") -> 0 | O13: =COUNTIFS(Pedidos!$E$2:$E$2224,$A13,Pedidos!$F$2:$F$2224,">250") -> 0 | P13: =COUNTIFS(Pedidos!$E$2:$E$2224,$A13) -> 37
A14: Volta Redonda | B14: =COUNTIFS(Pedidos!$E$2:$E$2224,$A14,Pedidos!$F$2:$F$2224,"0-20") -> 0 | C14: =COUNTIFS(Pedidos!$E$2:$E$2224,$A14,Pedidos!$F$2:$F$2224,"20-35") -> 8 | D14: =COUNTIFS(Pedidos!$E$2:$E$2224,$A14,Pedidos!$F$2:$F$2224,"35-40") -> 8 | E14: =COUNTIFS(Pedidos!$E$2:$E$2224,$A14,Pedidos!$F$2:$F$2224,"40-50") -> 5 | F14: =COUNTIFS(Pedidos!$E$2:$E$2224,$A14,Pedidos!$F$2:$F$2224,"50-60") -> 7 | G14: =COUNTIFS(Pedidos!$E$2:$E$2224,$A14,Pedidos!$F$2:$F$2224,"60-70") -> 5 | H14: =COUNTIFS(Pedidos!$E$2:$E$2224,$A14,Pedidos!$F$2:$F$2224,"70-80") -> 0 | I14: =COUNTIFS(Pedidos!$E$2:$E$2224,$A14,Pedidos!$F$2:$F$2224,"80-100") -> 2 | J14: =COUNTIFS(Pedidos!$E$2:$E$2224,$A14,Pedidos!$F$2:$F$2224,"100-120") -> 1 | K14: =COUNTIFS(Pedidos!$E$2:$E$2224,$A14,Pedidos!$F$2:$F$2224,"120-150") -> 1 | L14: =COUNTIFS(Pedidos!$E$2:$E$2224,$A14,Pedidos!$F$2:$F$2224,"150-170") -> 0 | M14: =COUNTIFS(Pedidos!$E$2:$E$2224,$A14,Pedidos!$F$2:$F$2224,"170-200") -> 0 | N14: =COUNTIFS(Pedidos!$E$2:$E$2224,$A14,Pedidos!$F$2:$F$2224,"200-250") -> 0 | O14: =COUNTIFS(Pedidos!$E$2:$E$2224,$A14,Pedidos!$F$2:$F$2224,">250") -> 0 | P14: =COUNTIFS(Pedidos!$E$2:$E$2224,$A14) -> 37
A15: Angra dos Reis | B15: =COUNTIFS(Pedidos!$E$2:$E$2224,$A15,Pedidos!$F$2:$F$2224,"0-20") -> 3 | C15: =COUNTIFS(Pedidos!$E$2:$E$2224,$A15,Pedidos!$F$2:$F$2224,"20-35") -> 6 | D15: =COUNTIFS(Pedidos!$E$2:$E$2224,$A15,Pedidos!$F$2:$F$2224,"35-40") -> 5 | E15: =COUNTIFS(Pedidos!$E$2:$E$2224,$A15,Pedidos!$F$2:$F$2224,"40-50") -> 8 | F15: =COUNTIFS(Pedidos!$E$2:$E$2224,$A15,Pedidos!$F$2:$F$2224,"50-60") -> 9 | G15: =COUNTIFS(Pedidos!$E$2:$E$2224,$A15,Pedidos!$F$2:$F$2224,"60-70") -> 2 | H15: =COUNTIFS(Pedidos!$E$2:$E$2224,$A15,Pedidos!$F$2:$F$2224,"70-80") -> 1 | I15: =COUNTIFS(Pedidos!$E$2:$E$2224,$A15,Pedidos!$F$2:$F$2224,"80-100") -> 1 | J15: =COUNTIFS(Pedidos!$E$2:$E$2224,$A15,Pedidos!$F$2:$F$2224,"100-120") -> 0 | K15: =COUNTIFS(Pedidos!$E$2:$E$2224,$A15,Pedidos!$F$2:$F$2224,"120-150") -> 0 | L15: =COUNTIFS(Pedidos!$E$2:$E$2224,$A15,Pedidos!$F$2:$F$2224,"150-170") -> 0 | M15: =COUNTIFS(Pedidos!$E$2:$E$2224,$A15,Pedidos!$F$2:$F$2224,"170-200") -> 0 | N15: =COUNTIFS(Pedidos!$E$2:$E$2224,$A15,Pedidos!$F$2:$F$2224,"200-250") -> 0 | O15: =COUNTIFS(Pedidos!$E$2:$E$2224,$A15,Pedidos!$F$2:$F$2224,">250") -> 0 | P15: =COUNTIFS(Pedidos!$E$2:$E$2224,$A15) -> 35
A16: Petrópolis | B16: =COUNTIFS(Pedidos!$E$2:$E$2224,$A16,Pedidos!$F$2:$F$2224,"0-20") -> 0 | C16: =COUNTIFS(Pedidos!$E$2:$E$2224,$A16,Pedidos!$F$2:$F$2224,"20-35") -> 5 | D16: =COUNTIFS(Pedidos!$E$2:$E$2224,$A16,Pedidos!$F$2:$F$2224,"35-40") -> 7 | E16: =COUNTIFS(Pedidos!$E$2:$E$2224,$A16,Pedidos!$F$2:$F$2224,"40-50") -> 3 | F16: =COUNTIFS(Pedidos!$E$2:$E$2224,$A16,Pedidos!$F$2:$F$2224,"50-60") -> 6 | G16: =COUNTIFS(Pedidos!$E$2:$E$2224,$A16,Pedidos!$F$2:$F$2224,"60-70") -> 5 | H16: =COUNTIFS(Pedidos!$E$2:$E$2224,$A16,Pedidos!$F$2:$F$2224,"70-80") -> 1 | I16: =COUNTIFS(Pedidos!$E$2:$E$2224,$A16,Pedidos!$F$2:$F$2224,"80-100") -> 1 | J16: =COUNTIFS(Pedidos!$E$2:$E$2224,$A16,Pedidos!$F$2:$F$2224,"100-120") -> 1 | K16: =COUNTIFS(Pedidos!$E$2:$E$2224,$A16,Pedidos!$F$2:$F$2224,"120-150") -> 3 | L16: =COUNTIFS(Pedidos!$E$2:$E$2224,$A16,Pedidos!$F$2:$F$2224,"150-170") -> 0 | M16: =COUNTIFS(Pedidos!$E$2:$E$2224,$A16,Pedidos!$F$2:$F$2224,"170-200") -> 0 | N16: =COUNTIFS(Pedidos!$E$2:$E$2224,$A16,Pedidos!$F$2:$F$2224,"200-250") -> 0 | O16: =COUNTIFS(Pedidos!$E$2:$E$2224,$A16,Pedidos!$F$2:$F$2224,">250") -> 0 | P16: =COUNTIFS(Pedidos!$E$2:$E$2224,$A16) -> 32
... A24: Rio das Ostras | B24: =COUNTIFS(Pedidos!$E$2:$E$2224,$A24,Pedidos!$F$2:$F$2224,"0-20") -> 0 | C24: =COUNTIFS(Pedidos!$E$2:$E$2224,$A24,Pedidos!$F$2:$F$2224,"20-35") -> 6 | D24: =COUNTIFS(Pedidos!$E$2:$E$2224,$A24,Pedidos!$F$2:$F$2224,"35-40") -> 2 | E24: =COUNTIFS(Pedidos!$E$2:$E$2224,$A24,Pedidos!$F$2:$F$2224,"40-50") -> 3 | F24: =COUNTIFS(Pedidos!$E$2:$E$2224,$A24,Pedidos!$F$2:$F$2224,"50-60") -> 3 | G24: =COUNTIFS(Pedidos!$E$2:$E$2224,$A24,Pedidos!$F$2:$F$2224,"60-70") -> 3 | H24: =COUNTIFS(Pedidos!$E$2:$E$2224,$A24,Pedidos!$F$2:$F$2224,"70-80") -> 0 | I24: =COUNTIFS(Pedidos!$E$2:$E$2224,$A24,Pedidos!$F$2:$F$2224,"80-100") -> 1 | J24: =COUNTIFS(Pedidos!$E$2:$E$2224,$A24,Pedidos!$F$2:$F$2224,"100-120") -> 0 | K24: =COUNTIFS(Pedidos!$E$2:$E$2224,$A24,Pedidos!$F$2:$F$2224,"120-150") -> 0 | L24: =COUNTIFS(Pedidos!$E$2:$E$2224,$A24,Pedidos!$F$2:$F$2224,"150-170") -> 0 | M24: =COUNTIFS(Pedidos!$E$2:$E$2224,$A24,Pedidos!$F$2:$F$2224,"170-200") -> 0 | N24: =COUNTIFS(Pedidos!$E$2:$E$2224,$A24,Pedidos!$F$2:$F$2224,"200-250") -> 0 | O24: =COUNTIFS(Pedidos!$E$2:$E$2224,$A24,Pedidos!$F$2:$F$2224,">250") -> 0 | P24: =COUNTIFS(Pedidos!$E$2:$E$2224,$A24) -> 18
A27: 2) PROLOG total simulado vs custo atual (%) — preço completo com taxas e ICMS
A28: Cidade | B28: 0-20 | C28: 20-35 | D28: 35-40 | E28: 40-50 | F28: 50-60 | G28: 60-70 | H28: 70-80 | I28: 80-100 | J28: 100-120 | K28: 120-150 | L28: 150-170 | M28: 170-200 | N28: 200-250 | O28: >250 | P28: Total
A29: Rio de Janeiro | B29: =IFERROR(AVERAGEIFS(Pedidos!$S$2:$S$2224,Pedidos!$E$2:$E$2224,$A29,Pedidos!$F$2:$F$2224,"0-20")/AVERAGEIFS(Pedidos!$J$2:$J$2224,Pedidos!$E$2:$E$2224,$A29,Pedidos!$F$2:$F$2224,"0-20")-1,"") -> 0.088437458 | C29: =IFERROR(AVERAGEIFS(Pedidos!$S$2:$S$2224,Pedidos!$E$2:$E$2224,$A29,Pedidos!$F$2:$F$2224,"20-35")/AVERAGEIFS(Pedidos!$J$2:$J$2224,Pedidos!$E$2:$E$2224,$A29,Pedidos!$F$2:$F$2224,"20-35")-1,"") -> 0.42881505 | D29: =IFERROR(AVERAGEIFS(Pedidos!$S$2:$S$2224,Pedidos!$E$2:$E$2224,$A29,Pedidos!$F$2:$F$2224,"35-40")/AVERAGEIFS(Pedidos!$J$2:$J$2224,Pedidos!$E$2:$E$2224,$A29,Pedidos!$F$2:$F$2224,"35-40")-1,"") -> 0.48138394 | E29: =IFERROR(AVERAGEIFS(Pedidos!$S$2:$S$2224,Pedidos!$E$2:$E$2224,$A29,Pedidos!$F$2:$F$2224,"40-50")/AVERAGEIFS(Pedidos!$J$2:$J$2224,Pedidos!$E$2:$E$2224,$A29,Pedidos!$F$2:$F$2224,"40-50")-1,"") -> 0.36317574 | F29: =IFERROR(AVERAGEIFS(Pedidos!$S$2:$S$2224,Pedidos!$E$2:$E$2224,$A29,Pedidos!$F$2:$F$2224,"50-60")/AVERAGEIFS(Pedidos!$J$2:$J$2224,Pedidos!$E$2:$E$2224,$A29,Pedidos!$F$2:$F$2224,"50-60")-1,"") -> 0.46154311 | G29: =IFERROR(AVERAGEIFS(Pedidos!$S$2:$S$2224,Pedidos!$E$2:$E$2224,$A29,Pedidos!$F$2:$F$2224,"60-70")/AVERAGEIFS(Pedidos!$J$2:$J$2224,Pedidos!$E$2:$E$2224,$A29,Pedidos!$F$2:$F$2224,"60-70")-1,"") -> 0.57090936 | H29: =IFERROR(AVERAGEIFS(Pedidos!$S$2:$S$2224,Pedidos!$E$2:$E$2224,$A29,Pedidos!$F$2:$F$2224,"70-80")/AVERAGEIFS(Pedidos!$J$2:$J$2224,Pedidos!$E$2:$E$2224,$A29,Pedidos!$F$2:$F$2224,"70-80")-1,"") -> 0.5004675 | I29: =IFERROR(AVERAGEIFS(Pedidos!$S$2:$S$2224,Pedidos!$E$2:$E$2224,$A29,Pedidos!$F$2:$F$2224,"80-100")/AVERAGEIFS(Pedidos!$J$2:$J$2224,Pedidos!$E$2:$E$2224,$A29,Pedidos!$F$2:$F$2224,"80-100")-1,"") -> 0.53819751 | J29: =IFERROR(AVERAGEIFS(Pedidos!$S$2:$S$2224,Pedidos!$E$2:$E$2224,$A29,Pedidos!$F$2:$F$2224,"100-120")/AVERAGEIFS(Pedidos!$J$2:$J$2224,Pedidos!$E$2:$E$2224,$A29,Pedidos!$F$2:$F$2224,"100-120")-1,"") -> 0.66351916 | K29: =IFERROR(AVERAGEIFS(Pedidos!$S$2:$S$2224,Pedidos!$E$2:$E$2224,$A29,Pedidos!$F$2:$F$2224,"120-150")/AVERAGEIFS(Pedidos!$J$2:$J$2224,Pedidos!$E$2:$E$2224,$A29,Pedidos!$F$2:$F$2224,"120-150")-1,"") -> 0.55888027 | L29: =IFERROR(AVERAGEIFS(Pedidos!$S$2:$S$2224,Pedidos!$E$2:$E$2224,$A29,Pedidos!$F$2:$F$2224,"150-170")/AVERAGEIFS(Pedidos!$J$2:$J$2224,Pedidos!$E$2:$E$2224,$A29,Pedidos!$F$2:$F$2224,"150-170")-1,"") -> 0.63283724 | M29: =IFERROR(AVERAGEIFS(Pedidos!$S$2:$S$2224,Pedidos!$E$2:$E$2224,$A29,Pedidos!$F$2:$F$2224,"170-200")/AVERAGEIFS(Pedidos!$J$2:$J$2224,Pedidos!$E$2:$E$2224,$A29,Pedidos!$F$2:$F$2224,"170-200")-1,"") | N29: =IFERROR(AVERAGEIFS(Pedidos!$S$2:$S$2224,Pedidos!$E$2:$E$2224,$A29,Pedidos!$F$2:$F$2224,"200-250")/AVERAGEIFS(Pedidos!$J$2:$J$2224,Pedidos!$E$2:$E$2224,$A29,Pedidos!$F$2:$F$2224,"200-250")-1,"") -> 0.75436737 | O29: =IFERROR(AVERAGEIFS(Pedidos!$S$2:$S$2224,Pedidos!$E$2:$E$2224,$A29,Pedidos!$F$2:$F$2224,">250")/AVERAGEIFS(Pedidos!$J$2:$J$2224,Pedidos!$E$2:$E$2224,$A29,Pedidos!$F$2:$F$2224,">250")-1,"") | P29: =IFERROR(AVERAGEIFS(Pedidos!$S$2:$S$2224,Pedidos!$E$2:$E$2224,$A29)/AVERAGEIFS(Pedidos!$J$2:$J$2224,Pedidos!$E$2:$E$2224,$A29)-1,"") -> 0.46288099
A30: São Gonçalo | B30: =IFERROR(AVERAGEIFS(Pedidos!$S$2:$S$2224,Pedidos!$E$2:$E$2224,$A30,Pedidos!$F$2:$F$2224,"0-20")/AVERAGEIFS(Pedidos!$J$2:$J$2224,Pedidos!$E$2:$E$2224,$A30,Pedidos!$F$2:$F$2224,"0-20")-1,"") -> 0.095225145 | C30: =IFERROR(AVERAGEIFS(Pedidos!$S$2:$S$2224,Pedidos!$E$2:$E$2224,$A30,Pedidos!$F$2:$F$2224,"20-35")/AVERAGEIFS(Pedidos!$J$2:$J$2224,Pedidos!$E$2:$E$2224,$A30,Pedidos!$F$2:$F$2224,"20-35")-1,"") -> 0.38375778 | D30: =IFERROR(AVERAGEIFS(Pedidos!$S$2:$S$2224,Pedidos!$E$2:$E$2224,$A30,Pedidos!$F$2:$F$2224,"35-40")/AVERAGEIFS(Pedidos!$J$2:$J$2224,Pedidos!$E$2:$E$2224,$A30,Pedidos!$F$2:$F$2224,"35-40")-1,"") -> 0.41188608 | E30: =IFERROR(AVERAGEIFS(Pedidos!$S$2:$S$2224,Pedidos!$E$2:$E$2224,$A30,Pedidos!$F$2:$F$2224,"40-50")/AVERAGEIFS(Pedidos!$J$2:$J$2224,Pedidos!$E$2:$E$2224,$A30,Pedidos!$F$2:$F$2224,"40-50")-1,"") -> 0.41811011 | F30: =IFERROR(AVERAGEIFS(Pedidos!$S$2:$S$2224,Pedidos!$E$2:$E$2224,$A30,Pedidos!$F$2:$F$2224,"50-60")/AVERAGEIFS(Pedidos!$J$2:$J$2224,Pedidos!$E$2:$E$2224,$A30,Pedidos!$F$2:$F$2224,"50-60")-1,"") -> 0.44716014 | G30: =IFERROR(AVERAGEIFS(Pedidos!$S$2:$S$2224,Pedidos!$E$2:$E$2224,$A30,Pedidos!$F$2:$F$2224,"60-70")/AVERAGEIFS(Pedidos!$J$2:$J$2224,Pedidos!$E$2:$E$2224,$A30,Pedidos!$F$2:$F$2224,"60-70")-1,"") -> 0.54809679 | H30: =IFERROR(AVERAGEIFS(Pedidos!$S$2:$S$2224,Pedidos!$E$2:$E$2224,$A30,Pedidos!$F$2:$F$2224,"70-80")/AVERAGEIFS(Pedidos!$J$2:$J$2224,Pedidos!$E$2:$E$2224,$A30,Pedidos!$F$2:$F$2224,"70-80")-1,"") -> 0.40175028 | I30: =IFERROR(AVERAGEIFS(Pedidos!$S$2:$S$2224,Pedidos!$E$2:$E$2224,$A30,Pedidos!$F$2:$F$2224,"80-100")/AVERAGEIFS(Pedidos!$J$2:$J$2224,Pedidos!$E$2:$E$2224,$A30,Pedidos!$F$2:$F$2224,"80-100")-1,"") -> 0.51837619 | J30: =IFERROR(AVERAGEIFS(Pedidos!$S$2:$S$2224,Pedidos!$E$2:$E$2224,$A30,Pedidos!$F$2:$F$2224,"100-120")/AVERAGEIFS(Pedidos!$J$2:$J$2224,Pedidos!$E$2:$E$2224,$A30,Pedidos!$F$2:$F$2224,"100-120")-1,"") -> 0.6493065 | K30: =IFERROR(AVERAGEIFS(Pedidos!$S$2:$S$2224,Pedidos!$E$2:$E$2224,$A30,Pedidos!$F$2:$F$2224,"120-150")/AVERAGEIFS(Pedidos!$J$2:$J$2224,Pedidos!$E$2:$E$2224,$A30,Pedidos!$F$2:$F$2224,"120-150")-1,"") -> 0.55096929 | L30: =IFERROR(AVERAGEIFS(Pedidos!$S$2:$S$2224,Pedidos!$E$2:$E$2224,$A30,Pedidos!$F$2:$F$2224,"150-170")/AVERAGEIFS(Pedidos!$J$2:$J$2224,Pedidos!$E$2:$E$2224,$A30,Pedidos!$F$2:$F$2224,"150-170")-1,"") -> 0.62616018 | M30: =IFERROR(AVERAGEIFS(Pedidos!$S$2:$S$2224,Pedidos!$E$2:$E$2224,$A30,Pedidos!$F$2:$F$2224,"170-200")/AVERAGEIFS(Pedidos!$J$2:$J$2224,Pedidos!$E$2:$E$2224,$A30,Pedidos!$F$2:$F$2224,"170-200")-1,"") | N30: =IFERROR(AVERAGEIFS(Pedidos!$S$2:$S$2224,Pedidos!$E$2:$E$2224,$A30,Pedidos!$F$2:$F$2224,"200-250")/AVERAGEIFS(Pedidos!$J$2:$J$2224,Pedidos!$E$2:$E$2224,$A30,Pedidos!$F$2:$F$2224,"200-250")-1,"") | O30: =IFERROR(AVERAGEIFS(Pedidos!$S$2:$S$2224,Pedidos!$E$2:$E$2224,$A30,Pedidos!$F$2:$F$2224,">250")/AVERAGEIFS(Pedidos!$J$2:$J$2224,Pedidos!$E$2:$E$2224,$A30,Pedidos!$F$2:$F$2224,">250")-1,"") | P30: =IFERROR(AVERAGEIFS(Pedidos!$S$2:$S$2224,Pedidos!$E$2:$E$2224,$A30)/AVERAGEIFS(Pedidos!$J$2:$J$2224,Pedidos!$E$2:$E$2224,$A30)-1,"") -> 0.44740862
A31: Duque de Caxias | B31: =IFERROR(AVERAGEIFS(Pedidos!$S$2:$S$2224,Pedidos!$E$2:$E$2224,$A31,Pedidos!$F$2:$F$2224,"0-20")/AVERAGEIFS(Pedidos!$J$2:$J$2224,Pedidos!$E$2:$E$2224,$A31,Pedidos!$F$2:$F$2224,"0-20")-1,"") -> -0.062430304 | C31: =IFERROR(AVERAGEIFS(Pedidos!$S$2:$S$2224,Pedidos!$E$2:$E$2224,$A31,Pedidos!$F$2:$F$2224,"20-35")/AVERAGEIFS(Pedidos!$J$2:$J$2224,Pedidos!$E$2:$E$2224,$A31,Pedidos!$F$2:$F$2224,"20-35")-1,"") -> 0.15383384 | D31: =IFERROR(AVERAGEIFS(Pedidos!$S$2:$S$2224,Pedidos!$E$2:$E$2224,$A31,Pedidos!$F$2:$F$2224,"35-40")/AVERAGEIFS(Pedidos!$J$2:$J$2224,Pedidos!$E$2:$E$2224,$A31,Pedidos!$F$2:$F$2224,"35-40")-1,"") -> 0.21221854 | E31: =IFERROR(AVERAGEIFS(Pedidos!$S$2:$S$2224,Pedidos!$E$2:$E$2224,$A31,Pedidos!$F$2:$F$2224,"40-50")/AVERAGEIFS(Pedidos!$J$2:$J$2224,Pedidos!$E$2:$E$2224,$A31,Pedidos!$F$2:$F$2224,"40-50")-1,"") -> 0.2094749 | F31: =IFERROR(AVERAGEIFS(Pedidos!$S$2:$S$2224,Pedidos!$E$2:$E$2224,$A31,Pedidos!$F$2:$F$2224,"50-60")/AVERAGEIFS(Pedidos!$J$2:$J$2224,Pedidos!$E$2:$E$2224,$A31,Pedidos!$F$2:$F$2224,"50-60")-1,"") -> 0.30288558 | G31: =IFERROR(AVERAGEIFS(Pedidos!$S$2:$S$2224,Pedidos!$E$2:$E$2224,$A31,Pedidos!$F$2:$F$2224,"60-70")/AVERAGEIFS(Pedidos!$J$2:$J$2224,Pedidos!$E$2:$E$2224,$A31,Pedidos!$F$2:$F$2224,"60-70")-1,"") -> 0.39839511 | H31: =IFERROR(AVERAGEIFS(Pedidos!$S$2:$S$2224,Pedidos!$E$2:$E$2224,$A31,Pedidos!$F$2:$F$2224,"70-80")/AVERAGEIFS(Pedidos!$J$2:$J$2224,Pedidos!$E$2:$E$2224,$A31,Pedidos!$F$2:$F$2224,"70-80")-1,"") -> 0.3401295 | I31: =IFERROR(AVERAGEIFS(Pedidos!$S$2:$S$2224,Pedidos!$E$2:$E$2224,$A31,Pedidos!$F$2:$F$2224,"80-100")/AVERAGEIFS(Pedidos!$J$2:$J$2224,Pedidos!$E$2:$E$2224,$A31,Pedidos!$F$2:$F$2224,"80-100")-1,"") -> 0.46883655 | J31: =IFERROR(AVERAGEIFS(Pedidos!$S$2:$S$2224,Pedidos!$E$2:$E$2224,$A31,Pedidos!$F$2:$F$2224,"100-120")/AVERAGEIFS(Pedidos!$J$2:$J$2224,Pedidos!$E$2:$E$2224,$A31,Pedidos!$F$2:$F$2224,"100-120")-1,"") -> 0.57028655 | K31: =IFERROR(AVERAGEIFS(Pedidos!$S$2:$S$2224,Pedidos!$E$2:$E$2224,$A31,Pedidos!$F$2:$F$2224,"120-150")/AVERAGEIFS(Pedidos!$J$2:$J$2224,Pedidos!$E$2:$E$2224,$A31,Pedidos!$F$2:$F$2224,"120-150")-1,"") -> 0.49815213 | L31: =IFERROR(AVERAGEIFS(Pedidos!$S$2:$S$2224,Pedidos!$E$2:$E$2224,$A31,Pedidos!$F$2:$F$2224,"150-170")/AVERAGEIFS(Pedidos!$J$2:$J$2224,Pedidos!$E$2:$E$2224,$A31,Pedidos!$F$2:$F$2224,"150-170")-1,"") | M31: =IFERROR(AVERAGEIFS(Pedidos!$S$2:$S$2224,Pedidos!$E$2:$E$2224,$A31,Pedidos!$F$2:$F$2224,"170-200")/AVERAGEIFS(Pedidos!$J$2:$J$2224,Pedidos!$E$2:$E$2224,$A31,Pedidos!$F$2:$F$2224,"170-200")-1,"") | N31: =IFERROR(AVERAGEIFS(Pedidos!$S$2:$S$2224,Pedidos!$E$2:$E$2224,$A31,Pedidos!$F$2:$F$2224,"200-250")/AVERAGEIFS(Pedidos!$J$2:$J$2224,Pedidos!$E$2:$E$2224,$A31,Pedidos!$F$2:$F$2224,"200-250")-1,"") | O31: =IFERROR(AVERAGEIFS(Pedidos!$S$2:$S$2224,Pedidos!$E$2:$E$2224,$A31,Pedidos!$F$2:$F$2224,">250")/AVERAGEIFS(Pedidos!$J$2:$J$2224,Pedidos!$E$2:$E$2224,$A31,Pedidos!$F$2:$F$2224,">250")-1,"") | P31: =IFERROR(AVERAGEIFS(Pedidos!$S$2:$S$2224,Pedidos!$E$2:$E$2224,$A31)/AVERAGEIFS(Pedidos!$J$2:$J$2224,Pedidos!$E$2:$E$2224,$A31)-1,"") -> 0.29901538
A32: Nova Iguaçu | B32: =IFERROR(AVERAGEIFS(Pedidos!$S$2:$S$2224,Pedidos!$E$2:$E$2224,$A32,Pedidos!$F$2:$F$2224,"0-20")/AVERAGEIFS(Pedidos!$J$2:$J$2224,Pedidos!$E$2:$E$2224,$A32,Pedidos!$F$2:$F$2224,"0-20")-1,"") -> -0.041282418 | C32: =IFERROR(AVERAGEIFS(Pedidos!$S$2:$S$2224,Pedidos!$E$2:$E$2224,$A32,Pedidos!$F$2:$F$2224,"20-35")/AVERAGEIFS(Pedidos!$J$2:$J$2224,Pedidos!$E$2:$E$2224,$A32,Pedidos!$F$2:$F$2224,"20-35")-1,"") -> 0.17824188 | D32: =IFERROR(AVERAGEIFS(Pedidos!$S$2:$S$2224,Pedidos!$E$2:$E$2224,$A32,Pedidos!$F$2:$F$2224,"35-40")/AVERAGEIFS(Pedidos!$J$2:$J$2224,Pedidos!$E$2:$E$2224,$A32,Pedidos!$F$2:$F$2224,"35-40")-1,"") -> 0.20589259 | E32: =IFERROR(AVERAGEIFS(Pedidos!$S$2:$S$2224,Pedidos!$E$2:$E$2224,$A32,Pedidos!$F$2:$F$2224,"40-50")/AVERAGEIFS(Pedidos!$J$2:$J$2224,Pedidos!$E$2:$E$2224,$A32,Pedidos!$F$2:$F$2224,"40-50")-1,"") -> 0.22065476 | F32: =IFERROR(AVERAGEIFS(Pedidos!$S$2:$S$2224,Pedidos!$E$2:$E$2224,$A32,Pedidos!$F$2:$F$2224,"50-60")/AVERAGEIFS(Pedidos!$J$2:$J$2224,Pedidos!$E$2:$E$2224,$A32,Pedidos!$F$2:$F$2224,"50-60")-1,"") -> 0.30402967 | G32: =IFERROR(AVERAGEIFS(Pedidos!$S$2:$S$2224,Pedidos!$E$2:$E$2224,$A32,Pedidos!$F$2:$F$2224,"60-70")/AVERAGEIFS(Pedidos!$J$2:$J$2224,Pedidos!$E$2:$E$2224,$A32,Pedidos!$F$2:$F$2224,"60-70")-1,"") -> 0.40378508 | H32: =IFERROR(AVERAGEIFS(Pedidos!$S$2:$S$2224,Pedidos!$E$2:$E$2224,$A32,Pedidos!$F$2:$F$2224,"70-80")/AVERAGEIFS(Pedidos!$J$2:$J$2224,Pedidos!$E$2:$E$2224,$A32,Pedidos!$F$2:$F$2224,"70-80")-1,"") -> 0.34046965 | I32: =IFERROR(AVERAGEIFS(Pedidos!$S$2:$S$2224,Pedidos!$E$2:$E$2224,$A32,Pedidos!$F$2:$F$2224,"80-100")/AVERAGEIFS(Pedidos!$J$2:$J$2224,Pedidos!$E$2:$E$2224,$A32,Pedidos!$F$2:$F$2224,"80-100")-1,"") -> 0.43504621 | J32: =IFERROR(AVERAGEIFS(Pedidos!$S$2:$S$2224,Pedidos!$E$2:$E$2224,$A32,Pedidos!$F$2:$F$2224,"100-120")/AVERAGEIFS(Pedidos!$J$2:$J$2224,Pedidos!$E$2:$E$2224,$A32,Pedidos!$F$2:$F$2224,"100-120")-1,"") -> 0.58555967 | K32: =IFERROR(AVERAGEIFS(Pedidos!$S$2:$S$2224,Pedidos!$E$2:$E$2224,$A32,Pedidos!$F$2:$F$2224,"120-150")/AVERAGEIFS(Pedidos!$J$2:$J$2224,Pedidos!$E$2:$E$2224,$A32,Pedidos!$F$2:$F$2224,"120-150")-1,"") -> 0.48747108 | L32: =IFERROR(AVERAGEIFS(Pedidos!$S$2:$S$2224,Pedidos!$E$2:$E$2224,$A32,Pedidos!$F$2:$F$2224,"150-170")/AVERAGEIFS(Pedidos!$J$2:$J$2224,Pedidos!$E$2:$E$2224,$A32,Pedidos!$F$2:$F$2224,"150-170")-1,"") | M32: =IFERROR(AVERAGEIFS(Pedidos!$S$2:$S$2224,Pedidos!$E$2:$E$2224,$A32,Pedidos!$F$2:$F$2224,"170-200")/AVERAGEIFS(Pedidos!$J$2:$J$2224,Pedidos!$E$2:$E$2224,$A32,Pedidos!$F$2:$F$2224,"170-200")-1,"") | N32: =IFERROR(AVERAGEIFS(Pedidos!$S$2:$S$2224,Pedidos!$E$2:$E$2224,$A32,Pedidos!$F$2:$F$2224,"200-250")/AVERAGEIFS(Pedidos!$J$2:$J$2224,Pedidos!$E$2:$E$2224,$A32,Pedidos!$F$2:$F$2224,"200-250")-1,"") | O32: =IFERROR(AVERAGEIFS(Pedidos!$S$2:$S$2224,Pedidos!$E$2:$E$2224,$A32,Pedidos!$F$2:$F$2224,">250")/AVERAGEIFS(Pedidos!$J$2:$J$2224,Pedidos!$E$2:$E$2224,$A32,Pedidos!$F$2:$F$2224,">250")-1,"") | P32: =IFERROR(AVERAGEIFS(Pedidos!$S$2:$S$2224,Pedidos!$E$2:$E$2224,$A32)/AVERAGEIFS(Pedidos!$J$2:$J$2224,Pedidos!$E$2:$E$2224,$A32)-1,"") -> 0.31984278
A33: Niterói | B33: =IFERROR(AVERAGEIFS(Pedidos!$S$2:$S$2224,Pedidos!$E$2:$E$2224,$A33,Pedidos!$F$2:$F$2224,"0-20")/AVERAGEIFS(Pedidos!$J$2:$J$2224,Pedidos!$E$2:$E$2224,$A33,Pedidos!$F$2:$F$2224,"0-20")-1,"") -> 0.1108869 | C33: =IFERROR(AVERAGEIFS(Pedidos!$S$2:$S$2224,Pedidos!$E$2:$E$2224,$A33,Pedidos!$F$2:$F$2224,"20-35")/AVERAGEIFS(Pedidos!$J$2:$J$2224,Pedidos!$E$2:$E$2224,$A33,Pedidos!$F$2:$F$2224,"20-35")-1,"") -> 0.37458845 | D33: =IFERROR(AVERAGEIFS(Pedidos!$S$2:$S$2224,Pedidos!$E$2:$E$2224,$A33,Pedidos!$F$2:$F$2224,"35-40")/AVERAGEIFS(Pedidos!$J$2:$J$2224,Pedidos!$E$2:$E$2224,$A33,Pedidos!$F$2:$F$2224,"35-40")-1,"") -> 0.41942743 | E33: =IFERROR(AVERAGEIFS(Pedidos!$S$2:$S$2224,Pedidos!$E$2:$E$2224,$A33,Pedidos!$F$2:$F$2224,"40-50")/AVERAGEIFS(Pedidos!$J$2:$J$2224,Pedidos!$E$2:$E$2224,$A33,Pedidos!$F$2:$F$2224,"40-50")-1,"") -> 0.41473648 | F33: =IFERROR(AVERAGEIFS(Pedidos!$S$2:$S$2224,Pedidos!$E$2:$E$2224,$A33,Pedidos!$F$2:$F$2224,"50-60")/AVERAGEIFS(Pedidos!$J$2:$J$2224,Pedidos!$E$2:$E$2224,$A33,Pedidos!$F$2:$F$2224,"50-60")-1,"") -> 0.44001172 | G33: =IFERROR(AVERAGEIFS(Pedidos!$S$2:$S$2224,Pedidos!$E$2:$E$2224,$A33,Pedidos!$F$2:$F$2224,"60-70")/AVERAGEIFS(Pedidos!$J$2:$J$2224,Pedidos!$E$2:$E$2224,$A33,Pedidos!$F$2:$F$2224,"60-70")-1,"") -> 0.55520155 | H33: =IFERROR(AVERAGEIFS(Pedidos!$S$2:$S$2224,Pedidos!$E$2:$E$2224,$A33,Pedidos!$F$2:$F$2224,"70-80")/AVERAGEIFS(Pedidos!$J$2:$J$2224,Pedidos!$E$2:$E$2224,$A33,Pedidos!$F$2:$F$2224,"70-80")-1,"") | I33: =IFERROR(AVERAGEIFS(Pedidos!$S$2:$S$2224,Pedidos!$E$2:$E$2224,$A33,Pedidos!$F$2:$F$2224,"80-100")/AVERAGEIFS(Pedidos!$J$2:$J$2224,Pedidos!$E$2:$E$2224,$A33,Pedidos!$F$2:$F$2224,"80-100")-1,"") -> 0.54750477 | J33: =IFERROR(AVERAGEIFS(Pedidos!$S$2:$S$2224,Pedidos!$E$2:$E$2224,$A33,Pedidos!$F$2:$F$2224,"100-120")/AVERAGEIFS(Pedidos!$J$2:$J$2224,Pedidos!$E$2:$E$2224,$A33,Pedidos!$F$2:$F$2224,"100-120")-1,"") -> 0.63940725 | K33: =IFERROR(AVERAGEIFS(Pedidos!$S$2:$S$2224,Pedidos!$E$2:$E$2224,$A33,Pedidos!$F$2:$F$2224,"120-150")/AVERAGEIFS(Pedidos!$J$2:$J$2224,Pedidos!$E$2:$E$2224,$A33,Pedidos!$F$2:$F$2224,"120-150")-1,"") -> 0.52452949 | L33: =IFERROR(AVERAGEIFS(Pedidos!$S$2:$S$2224,Pedidos!$E$2:$E$2224,$A33,Pedidos!$F$2:$F$2224,"150-170")/AVERAGEIFS(Pedidos!$J$2:$J$2224,Pedidos!$E$2:$E$2224,$A33,Pedidos!$F$2:$F$2224,"150-170")-1,"") | M33: =IFERROR(AVERAGEIFS(Pedidos!$S$2:$S$2224,Pedidos!$E$2:$E$2224,$A33,Pedidos!$F$2:$F$2224,"170-200")/AVERAGEIFS(Pedidos!$J$2:$J$2224,Pedidos!$E$2:$E$2224,$A33,Pedidos!$F$2:$F$2224,"170-200")-1,"") | N33: =IFERROR(AVERAGEIFS(Pedidos!$S$2:$S$2224,Pedidos!$E$2:$E$2224,$A33,Pedidos!$F$2:$F$2224,"200-250")/AVERAGEIFS(Pedidos!$J$2:$J$2224,Pedidos!$E$2:$E$2224,$A33,Pedidos!$F$2:$F$2224,"200-250")-1,"") | O33: =IFERROR(AVERAGEIFS(Pedidos!$S$2:$S$2224,Pedidos!$E$2:$E$2224,$A33,Pedidos!$F$2:$F$2224,">250")/AVERAGEIFS(Pedidos!$J$2:$J$2224,Pedidos!$E$2:$E$2224,$A33,Pedidos!$F$2:$F$2224,">250")-1,"") | P33: =IFERROR(AVERAGEIFS(Pedidos!$S$2:$S$2224,Pedidos!$E$2:$E$2224,$A33)/AVERAGEIFS(Pedidos!$J$2:$J$2224,Pedidos!$E$2:$E$2224,$A33)-1,"") -> 0.43989693
A34: Campos dos Goytacazes | B34: =IFERROR(AVERAGEIFS(Pedidos!$S$2:$S$2224,Pedidos!$E$2:$E$2224,$A34,Pedidos!$F$2:$F$2224,"0-20")/AVERAGEIFS(Pedidos!$J$2:$J$2224,Pedidos!$E$2:$E$2224,$A34,Pedidos!$F$2:$F$2224,"0-20")-1,"") | C34: =IFERROR(AVERAGEIFS(Pedidos!$S$2:$S$2224,Pedidos!$E$2:$E$2224,$A34,Pedidos!$F$2:$F$2224,"20-35")/AVERAGEIFS(Pedidos!$J$2:$J$2224,Pedidos!$E$2:$E$2224,$A34,Pedidos!$F$2:$F$2224,"20-35")-1,"") -> 0.66669707 | D34: =IFERROR(AVERAGEIFS(Pedidos!$S$2:$S$2224,Pedidos!$E$2:$E$2224,$A34,Pedidos!$F$2:$F$2224,"35-40")/AVERAGEIFS(Pedidos!$J$2:$J$2224,Pedidos!$E$2:$E$2224,$A34,Pedidos!$F$2:$F$2224,"35-40")-1,"") -> 0.56316691 | E34: =IFERROR(AVERAGEIFS(Pedidos!$S$2:$S$2224,Pedidos!$E$2:$E$2224,$A34,Pedidos!$F$2:$F$2224,"40-50")/AVERAGEIFS(Pedidos!$J$2:$J$2224,Pedidos!$E$2:$E$2224,$A34,Pedidos!$F$2:$F$2224,"40-50")-1,"") -> 0.58645809 | F34: =IFERROR(AVERAGEIFS(Pedidos!$S$2:$S$2224,Pedidos!$E$2:$E$2224,$A34,Pedidos!$F$2:$F$2224,"50-60")/AVERAGEIFS(Pedidos!$J$2:$J$2224,Pedidos!$E$2:$E$2224,$A34,Pedidos!$F$2:$F$2224,"50-60")-1,"") -> 0.57188056 | G34: =IFERROR(AVERAGEIFS(Pedidos!$S$2:$S$2224,Pedidos!$E$2:$E$2224,$A34,Pedidos!$F$2:$F$2224,"60-70")/AVERAGEIFS(Pedidos!$J$2:$J$2224,Pedidos!$E$2:$E$2224,$A34,Pedidos!$F$2:$F$2224,"60-70")-1,"") -> 0.55142742 | H34: =IFERROR(AVERAGEIFS(Pedidos!$S$2:$S$2224,Pedidos!$E$2:$E$2224,$A34,Pedidos!$F$2:$F$2224,"70-80")/AVERAGEIFS(Pedidos!$J$2:$J$2224,Pedidos!$E$2:$E$2224,$A34,Pedidos!$F$2:$F$2224,"70-80")-1,"") | I34: =IFERROR(AVERAGEIFS(Pedidos!$S$2:$S$2224,Pedidos!$E$2:$E$2224,$A34,Pedidos!$F$2:$F$2224,"80-100")/AVERAGEIFS(Pedidos!$J$2:$J$2224,Pedidos!$E$2:$E$2224,$A34,Pedidos!$F$2:$F$2224,"80-100")-1,"") -> 0.49863706 | J34: =IFERROR(AVERAGEIFS(Pedidos!$S$2:$S$2224,Pedidos!$E$2:$E$2224,$A34,Pedidos!$F$2:$F$2224,"100-120")/AVERAGEIFS(Pedidos!$J$2:$J$2224,Pedidos!$E$2:$E$2224,$A34,Pedidos!$F$2:$F$2224,"100-120")-1,"") -> 0.60783864 | K34: =IFERROR(AVERAGEIFS(Pedidos!$S$2:$S$2224,Pedidos!$E$2:$E$2224,$A34,Pedidos!$F$2:$F$2224,"120-150")/AVERAGEIFS(Pedidos!$J$2:$J$2224,Pedidos!$E$2:$E$2224,$A34,Pedidos!$F$2:$F$2224,"120-150")-1,"") | L34: =IFERROR(AVERAGEIFS(Pedidos!$S$2:$S$2224,Pedidos!$E$2:$E$2224,$A34,Pedidos!$F$2:$F$2224,"150-170")/AVERAGEIFS(Pedidos!$J$2:$J$2224,Pedidos!$E$2:$E$2224,$A34,Pedidos!$F$2:$F$2224,"150-170")-1,"") | M34: =IFERROR(AVERAGEIFS(Pedidos!$S$2:$S$2224,Pedidos!$E$2:$E$2224,$A34,Pedidos!$F$2:$F$2224,"170-200")/AVERAGEIFS(Pedidos!$J$2:$J$2224,Pedidos!$E$2:$E$2224,$A34,Pedidos!$F$2:$F$2224,"170-200")-1,"") | N34: =IFERROR(AVERAGEIFS(Pedidos!$S$2:$S$2224,Pedidos!$E$2:$E$2224,$A34,Pedidos!$F$2:$F$2224,"200-250")/AVERAGEIFS(Pedidos!$J$2:$J$2224,Pedidos!$E$2:$E$2224,$A34,Pedidos!$F$2:$F$2224,"200-250")-1,"") | O34: =IFERROR(AVERAGEIFS(Pedidos!$S$2:$S$2224,Pedidos!$E$2:$E$2224,$A34,Pedidos!$F$2:$F$2224,">250")/AVERAGEIFS(Pedidos!$J$2:$J$2224,Pedidos!$E$2:$E$2224,$A34,Pedidos!$F$2:$F$2224,">250")-1,"") | P34: =IFERROR(AVERAGEIFS(Pedidos!$S$2:$S$2224,Pedidos!$E$2:$E$2224,$A34)/AVERAGEIFS(Pedidos!$J$2:$J$2224,Pedidos!$E$2:$E$2224,$A34)-1,"") -> 0.59340356
A35: Belford Roxo | B35: =IFERROR(AVERAGEIFS(Pedidos!$S$2:$S$2224,Pedidos!$E$2:$E$2224,$A35,Pedidos!$F$2:$F$2224,"0-20")/AVERAGEIFS(Pedidos!$J$2:$J$2224,Pedidos!$E$2:$E$2224,$A35,Pedidos!$F$2:$F$2224,"0-20")-1,"") -> -0.05985665 | C35: =IFERROR(AVERAGEIFS(Pedidos!$S$2:$S$2224,Pedidos!$E$2:$E$2224,$A35,Pedidos!$F$2:$F$2224,"20-35")/AVERAGEIFS(Pedidos!$J$2:$J$2224,Pedidos!$E$2:$E$2224,$A35,Pedidos!$F$2:$F$2224,"20-35")-1,"") -> 0.22615406 | D35: =IFERROR(AVERAGEIFS(Pedidos!$S$2:$S$2224,Pedidos!$E$2:$E$2224,$A35,Pedidos!$F$2:$F$2224,"35-40")/AVERAGEIFS(Pedidos!$J$2:$J$2224,Pedidos!$E$2:$E$2224,$A35,Pedidos!$F$2:$F$2224,"35-40")-1,"") -> 0.19972091 | E35: =IFERROR(AVERAGEIFS(Pedidos!$S$2:$S$2224,Pedidos!$E$2:$E$2224,$A35,Pedidos!$F$2:$F$2224,"40-50")/AVERAGEIFS(Pedidos!$J$2:$J$2224,Pedidos!$E$2:$E$2224,$A35,Pedidos!$F$2:$F$2224,"40-50")-1,"") -> 0.21129982 | F35: =IFERROR(AVERAGEIFS(Pedidos!$S$2:$S$2224,Pedidos!$E$2:$E$2224,$A35,Pedidos!$F$2:$F$2224,"50-60")/AVERAGEIFS(Pedidos!$J$2:$J$2224,Pedidos!$E$2:$E$2224,$A35,Pedidos!$F$2:$F$2224,"50-60")-1,"") -> 0.30663022 | G35: =IFERROR(AVERAGEIFS(Pedidos!$S$2:$S$2224,Pedidos!$E$2:$E$2224,$A35,Pedidos!$F$2:$F$2224,"60-70")/AVERAGEIFS(Pedidos!$J$2:$J$2224,Pedidos!$E$2:$E$2224,$A35,Pedidos!$F$2:$F$2224,"60-70")-1,"") -> 0.39194301 | H35: =IFERROR(AVERAGEIFS(Pedidos!$S$2:$S$2224,Pedidos!$E$2:$E$2224,$A35,Pedidos!$F$2:$F$2224,"70-80")/AVERAGEIFS(Pedidos!$J$2:$J$2224,Pedidos!$E$2:$E$2224,$A35,Pedidos!$F$2:$F$2224,"70-80")-1,"") -> 0.34319355 | I35: =IFERROR(AVERAGEIFS(Pedidos!$S$2:$S$2224,Pedidos!$E$2:$E$2224,$A35,Pedidos!$F$2:$F$2224,"80-100")/AVERAGEIFS(Pedidos!$J$2:$J$2224,Pedidos!$E$2:$E$2224,$A35,Pedidos!$F$2:$F$2224,"80-100")-1,"") -> 0.46079866 | J35: =IFERROR(AVERAGEIFS(Pedidos!$S$2:$S$2224,Pedidos!$E$2:$E$2224,$A35,Pedidos!$F$2:$F$2224,"100-120")/AVERAGEIFS(Pedidos!$J$2:$J$2224,Pedidos!$E$2:$E$2224,$A35,Pedidos!$F$2:$F$2224,"100-120")-1,"") -> 0.59150574 | K35: =IFERROR(AVERAGEIFS(Pedidos!$S$2:$S$2224,Pedidos!$E$2:$E$2224,$A35,Pedidos!$F$2:$F$2224,"120-150")/AVERAGEIFS(Pedidos!$J$2:$J$2224,Pedidos!$E$2:$E$2224,$A35,Pedidos!$F$2:$F$2224,"120-150")-1,"") -> 0.50521819 | L35: =IFERROR(AVERAGEIFS(Pedidos!$S$2:$S$2224,Pedidos!$E$2:$E$2224,$A35,Pedidos!$F$2:$F$2224,"150-170")/AVERAGEIFS(Pedidos!$J$2:$J$2224,Pedidos!$E$2:$E$2224,$A35,Pedidos!$F$2:$F$2224,"150-170")-1,"") | M35: =IFERROR(AVERAGEIFS(Pedidos!$S$2:$S$2224,Pedidos!$E$2:$E$2224,$A35,Pedidos!$F$2:$F$2224,"170-200")/AVERAGEIFS(Pedidos!$J$2:$J$2224,Pedidos!$E$2:$E$2224,$A35,Pedidos!$F$2:$F$2224,"170-200")-1,"") | N35: =IFERROR(AVERAGEIFS(Pedidos!$S$2:$S$2224,Pedidos!$E$2:$E$2224,$A35,Pedidos!$F$2:$F$2224,"200-250")/AVERAGEIFS(Pedidos!$J$2:$J$2224,Pedidos!$E$2:$E$2224,$A35,Pedidos!$F$2:$F$2224,"200-250")-1,"") | O35: =IFERROR(AVERAGEIFS(Pedidos!$S$2:$S$2224,Pedidos!$E$2:$E$2224,$A35,Pedidos!$F$2:$F$2224,">250")/AVERAGEIFS(Pedidos!$J$2:$J$2224,Pedidos!$E$2:$E$2224,$A35,Pedidos!$F$2:$F$2224,">250")-1,"") | P35: =IFERROR(AVERAGEIFS(Pedidos!$S$2:$S$2224,Pedidos!$E$2:$E$2224,$A35)/AVERAGEIFS(Pedidos!$J$2:$J$2224,Pedidos!$E$2:$E$2224,$A35)-1,"") -> 0.30368579
A36: Macaé | B36: =IFERROR(AVERAGEIFS(Pedidos!$S$2:$S$2224,Pedidos!$E$2:$E$2224,$A36,Pedidos!$F$2:$F$2224,"0-20")/AVERAGEIFS(Pedidos!$J$2:$J$2224,Pedidos!$E$2:$E$2224,$A36,Pedidos!$F$2:$F$2224,"0-20")-1,"") -> 0.964974 | C36: =IFERROR(AVERAGEIFS(Pedidos!$S$2:$S$2224,Pedidos!$E$2:$E$2224,$A36,Pedidos!$F$2:$F$2224,"20-35")/AVERAGEIFS(Pedidos!$J$2:$J$2224,Pedidos!$E$2:$E$2224,$A36,Pedidos!$F$2:$F$2224,"20-35")-1,"") -> 0.67860185 | D36: =IFERROR(AVERAGEIFS(Pedidos!$S$2:$S$2224,Pedidos!$E$2:$E$2224,$A36,Pedidos!$F$2:$F$2224,"35-40")/AVERAGEIFS(Pedidos!$J$2:$J$2224,Pedidos!$E$2:$E$2224,$A36,Pedidos!$F$2:$F$2224,"35-40")-1,"") -> 0.56221865 | E36: =IFERROR(AVERAGEIFS(Pedidos!$S$2:$S$2224,Pedidos!$E$2:$E$2224,$A36,Pedidos!$F$2:$F$2224,"40-50")/AVERAGEIFS(Pedidos!$J$2:$J$2224,Pedidos!$E$2:$E$2224,$A36,Pedidos!$F$2:$F$2224,"40-50")-1,"") -> 0.58517016 | F36: =IFERROR(AVERAGEIFS(Pedidos!$S$2:$S$2224,Pedidos!$E$2:$E$2224,$A36,Pedidos!$F$2:$F$2224,"50-60")/AVERAGEIFS(Pedidos!$J$2:$J$2224,Pedidos!$E$2:$E$2224,$A36,Pedidos!$F$2:$F$2224,"50-60")-1,"") -> 0.56883491 | G36: =IFERROR(AVERAGEIFS(Pedidos!$S$2:$S$2224,Pedidos!$E$2:$E$2224,$A36,Pedidos!$F$2:$F$2224,"60-70")/AVERAGEIFS(Pedidos!$J$2:$J$2224,Pedidos!$E$2:$E$2224,$A36,Pedidos!$F$2:$F$2224,"60-70")-1,"") -> 0.55270985 | H36: =IFERROR(AVERAGEIFS(Pedidos!$S$2:$S$2224,Pedidos!$E$2:$E$2224,$A36,Pedidos!$F$2:$F$2224,"70-80")/AVERAGEIFS(Pedidos!$J$2:$J$2224,Pedidos!$E$2:$E$2224,$A36,Pedidos!$F$2:$F$2224,"70-80")-1,"") | I36: =IFERROR(AVERAGEIFS(Pedidos!$S$2:$S$2224,Pedidos!$E$2:$E$2224,$A36,Pedidos!$F$2:$F$2224,"80-100")/AVERAGEIFS(Pedidos!$J$2:$J$2224,Pedidos!$E$2:$E$2224,$A36,Pedidos!$F$2:$F$2224,"80-100")-1,"") -> 0.4913862 | J36: =IFERROR(AVERAGEIFS(Pedidos!$S$2:$S$2224,Pedidos!$E$2:$E$2224,$A36,Pedidos!$F$2:$F$2224,"100-120")/AVERAGEIFS(Pedidos!$J$2:$J$2224,Pedidos!$E$2:$E$2224,$A36,Pedidos!$F$2:$F$2224,"100-120")-1,"") | K36: =IFERROR(AVERAGEIFS(Pedidos!$S$2:$S$2224,Pedidos!$E$2:$E$2224,$A36,Pedidos!$F$2:$F$2224,"120-150")/AVERAGEIFS(Pedidos!$J$2:$J$2224,Pedidos!$E$2:$E$2224,$A36,Pedidos!$F$2:$F$2224,"120-150")-1,"") -> 0.52119647 | L36: =IFERROR(AVERAGEIFS(Pedidos!$S$2:$S$2224,Pedidos!$E$2:$E$2224,$A36,Pedidos!$F$2:$F$2224,"150-170")/AVERAGEIFS(Pedidos!$J$2:$J$2224,Pedidos!$E$2:$E$2224,$A36,Pedidos!$F$2:$F$2224,"150-170")-1,"") | M36: =IFERROR(AVERAGEIFS(Pedidos!$S$2:$S$2224,Pedidos!$E$2:$E$2224,$A36,Pedidos!$F$2:$F$2224,"170-200")/AVERAGEIFS(Pedidos!$J$2:$J$2224,Pedidos!$E$2:$E$2224,$A36,Pedidos!$F$2:$F$2224,"170-200")-1,"") -> 1.6680704 | N36: =IFERROR(AVERAGEIFS(Pedidos!$S$2:$S$2224,Pedidos!$E$2:$E$2224,$A36,Pedidos!$F$2:$F$2224,"200-250")/AVERAGEIFS(Pedidos!$J$2:$J$2224,Pedidos!$E$2:$E$2224,$A36,Pedidos!$F$2:$F$2224,"200-250")-1,"") | O36: =IFERROR(AVERAGEIFS(Pedidos!$S$2:$S$2224,Pedidos!$E$2:$E$2224,$A36,Pedidos!$F$2:$F$2224,">250")/AVERAGEIFS(Pedidos!$J$2:$J$2224,Pedidos!$E$2:$E$2224,$A36,Pedidos!$F$2:$F$2224,">250")-1,"") | P36: =IFERROR(AVERAGEIFS(Pedidos!$S$2:$S$2224,Pedidos!$E$2:$E$2224,$A36)/AVERAGEIFS(Pedidos!$J$2:$J$2224,Pedidos!$E$2:$E$2224,$A36)-1,"") -> 0.60363596
A37: São João de Meriti | B37: =IFERROR(AVERAGEIFS(Pedidos!$S$2:$S$2224,Pedidos!$E$2:$E$2224,$A37,Pedidos!$F$2:$F$2224,"0-20")/AVERAGEIFS(Pedidos!$J$2:$J$2224,Pedidos!$E$2:$E$2224,$A37,Pedidos!$F$2:$F$2224,"0-20")-1,"") -> -0.060040706 | C37: =IFERROR(AVERAGEIFS(Pedidos!$S$2:$S$2224,Pedidos!$E$2:$E$2224,$A37,Pedidos!$F$2:$F$2224,"20-35")/AVERAGEIFS(Pedidos!$J$2:$J$2224,Pedidos!$E$2:$E$2224,$A37,Pedidos!$F$2:$F$2224,"20-35")-1,"") -> 0.2482408 | D37: =IFERROR(AVERAGEIFS(Pedidos!$S$2:$S$2224,Pedidos!$E$2:$E$2224,$A37,Pedidos!$F$2:$F$2224,"35-40")/AVERAGEIFS(Pedidos!$J$2:$J$2224,Pedidos!$E$2:$E$2224,$A37,Pedidos!$F$2:$F$2224,"35-40")-1,"") -> 0.19993841 | E37: =IFERROR(AVERAGEIFS(Pedidos!$S$2:$S$2224,Pedidos!$E$2:$E$2224,$A37,Pedidos!$F$2:$F$2224,"40-50")/AVERAGEIFS(Pedidos!$J$2:$J$2224,Pedidos!$E$2:$E$2224,$A37,Pedidos!$F$2:$F$2224,"40-50")-1,"") -> 0.21730961 | F37: =IFERROR(AVERAGEIFS(Pedidos!$S$2:$S$2224,Pedidos!$E$2:$E$2224,$A37,Pedidos!$F$2:$F$2224,"50-60")/AVERAGEIFS(Pedidos!$J$2:$J$2224,Pedidos!$E$2:$E$2224,$A37,Pedidos!$F$2:$F$2224,"50-60")-1,"") -> 0.30810968 | G37: =IFERROR(AVERAGEIFS(Pedidos!$S$2:$S$2224,Pedidos!$E$2:$E$2224,$A37,Pedidos!$F$2:$F$2224,"60-70")/AVERAGEIFS(Pedidos!$J$2:$J$2224,Pedidos!$E$2:$E$2224,$A37,Pedidos!$F$2:$F$2224,"60-70")-1,"") -> 0.40009887 | H37: =IFERROR(AVERAGEIFS(Pedidos!$S$2:$S$2224,Pedidos!$E$2:$E$2224,$A37,Pedidos!$F$2:$F$2224,"70-80")/AVERAGEIFS(Pedidos!$J$2:$J$2224,Pedidos!$E$2:$E$2224,$A37,Pedidos!$F$2:$F$2224,"70-80")-1,"") | I37: =IFERROR(AVERAGEIFS(Pedidos!$S$2:$S$2224,Pedidos!$E$2:$E$2224,$A37,Pedidos!$F$2:$F$2224,"80-100")/AVERAGEIFS(Pedidos!$J$2:$J$2224,Pedidos!$E$2:$E$2224,$A37,Pedidos!$F$2:$F$2224,"80-100")-1,"") -> 0.47069713 | J37: =IFERROR(AVERAGEIFS(Pedidos!$S$2:$S$2224,Pedidos!$E$2:$E$2224,$A37,Pedidos!$F$2:$F$2224,"100-120")/AVERAGEIFS(Pedidos!$J$2:$J$2224,Pedidos!$E$2:$E$2224,$A37,Pedidos!$F$2:$F$2224,"100-120")-1,"") -> 0.57530244 | K37: =IFERROR(AVERAGEIFS(Pedidos!$S$2:$S$2224,Pedidos!$E$2:$E$2224,$A37,Pedidos!$F$2:$F$2224,"120-150")/AVERAGEIFS(Pedidos!$J$2:$J$2224,Pedidos!$E$2:$E$2224,$A37,Pedidos!$F$2:$F$2224,"120-150")-1,"") -> 0.52229396 | L37: =IFERROR(AVERAGEIFS(Pedidos!$S$2:$S$2224,Pedidos!$E$2:$E$2224,$A37,Pedidos!$F$2:$F$2224,"150-170")/AVERAGEIFS(Pedidos!$J$2:$J$2224,Pedidos!$E$2:$E$2224,$A37,Pedidos!$F$2:$F$2224,"150-170")-1,"") | M37: =IFERROR(AVERAGEIFS(Pedidos!$S$2:$S$2224,Pedidos!$E$2:$E$2224,$A37,Pedidos!$F$2:$F$2224,"170-200")/AVERAGEIFS(Pedidos!$J$2:$J$2224,Pedidos!$E$2:$E$2224,$A37,Pedidos!$F$2:$F$2224,"170-200")-1,"") | N37: =IFERROR(AVERAGEIFS(Pedidos!$S$2:$S$2224,Pedidos!$E$2:$E$2224,$A37,Pedidos!$F$2:$F$2224,"200-250")/AVERAGEIFS(Pedidos!$J$2:$J$2224,Pedidos!$E$2:$E$2224,$A37,Pedidos!$F$2:$F$2224,"200-250")-1,"") | O37: =IFERROR(AVERAGEIFS(Pedidos!$S$2:$S$2224,Pedidos!$E$2:$E$2224,$A37,Pedidos!$F$2:$F$2224,">250")/AVERAGEIFS(Pedidos!$J$2:$J$2224,Pedidos!$E$2:$E$2224,$A37,Pedidos!$F$2:$F$2224,">250")-1,"") | P37: =IFERROR(AVERAGEIFS(Pedidos!$S$2:$S$2224,Pedidos!$E$2:$E$2224,$A37)/AVERAGEIFS(Pedidos!$J$2:$J$2224,Pedidos!$E$2:$E$2224,$A37)-1,"") -> 0.32826779
A38: Volta Redonda | B38: =IFERROR(AVERAGEIFS(Pedidos!$S$2:$S$2224,Pedidos!$E$2:$E$2224,$A38,Pedidos!$F$2:$F$2224,"0-20")/AVERAGEIFS(Pedidos!$J$2:$J$2224,Pedidos!$E$2:$E$2224,$A38,Pedidos!$F$2:$F$2224,"0-20")-1,"") | C38: =IFERROR(AVERAGEIFS(Pedidos!$S$2:$S$2224,Pedidos!$E$2:$E$2224,$A38,Pedidos!$F$2:$F$2224,"20-35")/AVERAGEIFS(Pedidos!$J$2:$J$2224,Pedidos!$E$2:$E$2224,$A38,Pedidos!$F$2:$F$2224,"20-35")-1,"") -> 0.36158564 | D38: =IFERROR(AVERAGEIFS(Pedidos!$S$2:$S$2224,Pedidos!$E$2:$E$2224,$A38,Pedidos!$F$2:$F$2224,"35-40")/AVERAGEIFS(Pedidos!$J$2:$J$2224,Pedidos!$E$2:$E$2224,$A38,Pedidos!$F$2:$F$2224,"35-40")-1,"") -> 0.3938567 | E38: =IFERROR(AVERAGEIFS(Pedidos!$S$2:$S$2224,Pedidos!$E$2:$E$2224,$A38,Pedidos!$F$2:$F$2224,"40-50")/AVERAGEIFS(Pedidos!$J$2:$J$2224,Pedidos!$E$2:$E$2224,$A38,Pedidos!$F$2:$F$2224,"40-50")-1,"") -> 0.33765969 | F38: =IFERROR(AVERAGEIFS(Pedidos!$S$2:$S$2224,Pedidos!$E$2:$E$2224,$A38,Pedidos!$F$2:$F$2224,"50-60")/AVERAGEIFS(Pedidos!$J$2:$J$2224,Pedidos!$E$2:$E$2224,$A38,Pedidos!$F$2:$F$2224,"50-60")-1,"") -> 0.41594308 | G38: =IFERROR(AVERAGEIFS(Pedidos!$S$2:$S$2224,Pedidos!$E$2:$E$2224,$A38,Pedidos!$F$2:$F$2224,"60-70")/AVERAGEIFS(Pedidos!$J$2:$J$2224,Pedidos!$E$2:$E$2224,$A38,Pedidos!$F$2:$F$2224,"60-70")-1,"") -> 0.5152838 | H38: =IFERROR(AVERAGEIFS(Pedidos!$S$2:$S$2224,Pedidos!$E$2:$E$2224,$A38,Pedidos!$F$2:$F$2224,"70-80")/AVERAGEIFS(Pedidos!$J$2:$J$2224,Pedidos!$E$2:$E$2224,$A38,Pedidos!$F$2:$F$2224,"70-80")-1,"") | I38: =IFERROR(AVERAGEIFS(Pedidos!$S$2:$S$2224,Pedidos!$E$2:$E$2224,$A38,Pedidos!$F$2:$F$2224,"80-100")/AVERAGEIFS(Pedidos!$J$2:$J$2224,Pedidos!$E$2:$E$2224,$A38,Pedidos!$F$2:$F$2224,"80-100")-1,"") -> 0.49546641 | J38: =IFERROR(AVERAGEIFS(Pedidos!$S$2:$S$2224,Pedidos!$E$2:$E$2224,$A38,Pedidos!$F$2:$F$2224,"100-120")/AVERAGEIFS(Pedidos!$J$2:$J$2224,Pedidos!$E$2:$E$2224,$A38,Pedidos!$F$2:$F$2224,"100-120")-1,"") -> 0.61470139 | K38: =IFERROR(AVERAGEIFS(Pedidos!$S$2:$S$2224,Pedidos!$E$2:$E$2224,$A38,Pedidos!$F$2:$F$2224,"120-150")/AVERAGEIFS(Pedidos!$J$2:$J$2224,Pedidos!$E$2:$E$2224,$A38,Pedidos!$F$2:$F$2224,"120-150")-1,"") -> 0.49522771 | L38: =IFERROR(AVERAGEIFS(Pedidos!$S$2:$S$2224,Pedidos!$E$2:$E$2224,$A38,Pedidos!$F$2:$F$2224,"150-170")/AVERAGEIFS(Pedidos!$J$2:$J$2224,Pedidos!$E$2:$E$2224,$A38,Pedidos!$F$2:$F$2224,"150-170")-1,"") | M38: =IFERROR(AVERAGEIFS(Pedidos!$S$2:$S$2224,Pedidos!$E$2:$E$2224,$A38,Pedidos!$F$2:$F$2224,"170-200")/AVERAGEIFS(Pedidos!$J$2:$J$2224,Pedidos!$E$2:$E$2224,$A38,Pedidos!$F$2:$F$2224,"170-200")-1,"") | N38: =IFERROR(AVERAGEIFS(Pedidos!$S$2:$S$2224,Pedidos!$E$2:$E$2224,$A38,Pedidos!$F$2:$F$2224,"200-250")/AVERAGEIFS(Pedidos!$J$2:$J$2224,Pedidos!$E$2:$E$2224,$A38,Pedidos!$F$2:$F$2224,"200-250")-1,"") | O38: =IFERROR(AVERAGEIFS(Pedidos!$S$2:$S$2224,Pedidos!$E$2:$E$2224,$A38,Pedidos!$F$2:$F$2224,">250")/AVERAGEIFS(Pedidos!$J$2:$J$2224,Pedidos!$E$2:$E$2224,$A38,Pedidos!$F$2:$F$2224,">250")-1,"") | P38: =IFERROR(AVERAGEIFS(Pedidos!$S$2:$S$2224,Pedidos!$E$2:$E$2224,$A38)/AVERAGEIFS(Pedidos!$J$2:$J$2224,Pedidos!$E$2:$E$2224,$A38)-1,"") -> 0.42592606
A39: Angra dos Reis | B39: =IFERROR(AVERAGEIFS(Pedidos!$S$2:$S$2224,Pedidos!$E$2:$E$2224,$A39,Pedidos!$F$2:$F$2224,"0-20")/AVERAGEIFS(Pedidos!$J$2:$J$2224,Pedidos!$E$2:$E$2224,$A39,Pedidos!$F$2:$F$2224,"0-20")-1,"") -> 0.31208581 | C39: =IFERROR(AVERAGEIFS(Pedidos!$S$2:$S$2224,Pedidos!$E$2:$E$2224,$A39,Pedidos!$F$2:$F$2224,"20-35")/AVERAGEIFS(Pedidos!$J$2:$J$2224,Pedidos!$E$2:$E$2224,$A39,Pedidos!$F$2:$F$2224,"20-35")-1,"") -> 0.36396603 | D39: =IFERROR(AVERAGEIFS(Pedidos!$S$2:$S$2224,Pedidos!$E$2:$E$2224,$A39,Pedidos!$F$2:$F$2224,"35-40")/AVERAGEIFS(Pedidos!$J$2:$J$2224,Pedidos!$E$2:$E$2224,$A39,Pedidos!$F$2:$F$2224,"35-40")-1,"") -> 0.3932031 | E39: =IFERROR(AVERAGEIFS(Pedidos!$S$2:$S$2224,Pedidos!$E$2:$E$2224,$A39,Pedidos!$F$2:$F$2224,"40-50")/AVERAGEIFS(Pedidos!$J$2:$J$2224,Pedidos!$E$2:$E$2224,$A39,Pedidos!$F$2:$F$2224,"40-50")-1,"") -> 0.34606633 | F39: =IFERROR(AVERAGEIFS(Pedidos!$S$2:$S$2224,Pedidos!$E$2:$E$2224,$A39,Pedidos!$F$2:$F$2224,"50-60")/AVERAGEIFS(Pedidos!$J$2:$J$2224,Pedidos!$E$2:$E$2224,$A39,Pedidos!$F$2:$F$2224,"50-60")-1,"") -> 0.41036143 | G39: =IFERROR(AVERAGEIFS(Pedidos!$S$2:$S$2224,Pedidos!$E$2:$E$2224,$A39,Pedidos!$F$2:$F$2224,"60-70")/AVERAGEIFS(Pedidos!$J$2:$J$2224,Pedidos!$E$2:$E$2224,$A39,Pedidos!$F$2:$F$2224,"60-70")-1,"") -> 0.50131112 | H39: =IFERROR(AVERAGEIFS(Pedidos!$S$2:$S$2224,Pedidos!$E$2:$E$2224,$A39,Pedidos!$F$2:$F$2224,"70-80")/AVERAGEIFS(Pedidos!$J$2:$J$2224,Pedidos!$E$2:$E$2224,$A39,Pedidos!$F$2:$F$2224,"70-80")-1,"") -> 0.36903377 | I39: =IFERROR(AVERAGEIFS(Pedidos!$S$2:$S$2224,Pedidos!$E$2:$E$2224,$A39,Pedidos!$F$2:$F$2224,"80-100")/AVERAGEIFS(Pedidos!$J$2:$J$2224,Pedidos!$E$2:$E$2224,$A39,Pedidos!$F$2:$F$2224,"80-100")-1,"") -> 0.45623985 | J39: =IFERROR(AVERAGEIFS(Pedidos!$S$2:$S$2224,Pedidos!$E$2:$E$2224,$A39,Pedidos!$F$2:$F$2224,"100-120")/AVERAGEIFS(Pedidos!$J$2:$J$2224,Pedidos!$E$2:$E$2224,$A39,Pedidos!$F$2:$F$2224,"100-120")-1,"") | K39: =IFERROR(AVERAGEIFS(Pedidos!$S$2:$S$2224,Pedidos!$E$2:$E$2224,$A39,Pedidos!$F$2:$F$2224,"120-150")/AVERAGEIFS(Pedidos!$J$2:$J$2224,Pedidos!$E$2:$E$2224,$A39,Pedidos!$F$2:$F$2224,"120-150")-1,"") | L39: =IFERROR(AVERAGEIFS(Pedidos!$S$2:$S$2224,Pedidos!$E$2:$E$2224,$A39,Pedidos!$F$2:$F$2224,"150-170")/AVERAGEIFS(Pedidos!$J$2:$J$2224,Pedidos!$E$2:$E$2224,$A39,Pedidos!$F$2:$F$2224,"150-170")-1,"") | M39: =IFERROR(AVERAGEIFS(Pedidos!$S$2:$S$2224,Pedidos!$E$2:$E$2224,$A39,Pedidos!$F$2:$F$2224,"170-200")/AVERAGEIFS(Pedidos!$J$2:$J$2224,Pedidos!$E$2:$E$2224,$A39,Pedidos!$F$2:$F$2224,"170-200")-1,"") | N39: =IFERROR(AVERAGEIFS(Pedidos!$S$2:$S$2224,Pedidos!$E$2:$E$2224,$A39,Pedidos!$F$2:$F$2224,"200-250")/AVERAGEIFS(Pedidos!$J$2:$J$2224,Pedidos!$E$2:$E$2224,$A39,Pedidos!$F$2:$F$2224,"200-250")-1,"") | O39: =IFERROR(AVERAGEIFS(Pedidos!$S$2:$S$2224,Pedidos!$E$2:$E$2224,$A39,Pedidos!$F$2:$F$2224,">250")/AVERAGEIFS(Pedidos!$J$2:$J$2224,Pedidos!$E$2:$E$2224,$A39,Pedidos!$F$2:$F$2224,">250")-1,"") | P39: =IFERROR(AVERAGEIFS(Pedidos!$S$2:$S$2224,Pedidos!$E$2:$E$2224,$A39)/AVERAGEIFS(Pedidos!$J$2:$J$2224,Pedidos!$E$2:$E$2224,$A39)-1,"") -> 0.38790086
A40: Petrópolis | B40: =IFERROR(AVERAGEIFS(Pedidos!$S$2:$S$2224,Pedidos!$E$2:$E$2224,$A40,Pedidos!$F$2:$F$2224,"0-20")/AVERAGEIFS(Pedidos!$J$2:$J$2224,Pedidos!$E$2:$E$2224,$A40,Pedidos!$F$2:$F$2224,"0-20")-1,"") | C40: =IFERROR(AVERAGEIFS(Pedidos!$S$2:$S$2224,Pedidos!$E$2:$E$2224,$A40,Pedidos!$F$2:$F$2224,"20-35")/AVERAGEIFS(Pedidos!$J$2:$J$2224,Pedidos!$E$2:$E$2224,$A40,Pedidos!$F$2:$F$2224,"20-35")-1,"") -> 0.37247 | D40: =IFERROR(AVERAGEIFS(Pedidos!$S$2:$S$2224,Pedidos!$E$2:$E$2224,$A40,Pedidos!$F$2:$F$2224,"35-40")/AVERAGEIFS(Pedidos!$J$2:$J$2224,Pedidos!$E$2:$E$2224,$A40,Pedidos!$F$2:$F$2224,"35-40")-1,"") -> 0.39728277 | E40: =IFERROR(AVERAGEIFS(Pedidos!$S$2:$S$2224,Pedidos!$E$2:$E$2224,$A40,Pedidos!$F$2:$F$2224,"40-50")/AVERAGEIFS(Pedidos!$J$2:$J$2224,Pedidos!$E$2:$E$2224,$A40,Pedidos!$F$2:$F$2224,"40-50")-1,"") -> 0.3429075 | F40: =IFERROR(AVERAGEIFS(Pedidos!$S$2:$S$2224,Pedidos!$E$2:$E$2224,$A40,Pedidos!$F$2:$F$2224,"50-60")/AVERAGEIFS(Pedidos!$J$2:$J$2224,Pedidos!$E$2:$E$2224,$A40,Pedidos!$F$2:$F$2224,"50-60")-1,"") -> 0.4148266 | G40: =IFERROR(AVERAGEIFS(Pedidos!$S$2:$S$2224,Pedidos!$E$2:$E$2224,$A40,Pedidos!$F$2:$F$2224,"60-70")/AVERAGEIFS(Pedidos!$J$2:$J$2224,Pedidos!$E$2:$E$2224,$A40,Pedidos!$F$2:$F$2224,"60-70")-1,"") -> 0.51121807 | H40: =IFERROR(AVERAGEIFS(Pedidos!$S$2:$S$2224,Pedidos!$E$2:$E$2224,$A40,Pedidos!$F$2:$F$2224,"70-80")/AVERAGEIFS(Pedidos!$J$2:$J$2224,Pedidos!$E$2:$E$2224,$A40,Pedidos!$F$2:$F$2224,"70-80")-1,"") -> 0.42406595 | I40: =IFERROR(AVERAGEIFS(Pedidos!$S$2:$S$2224,Pedidos!$E$2:$E$2224,$A40,Pedidos!$F$2:$F$2224,"80-100")/AVERAGEIFS(Pedidos!$J$2:$J$2224,Pedidos!$E$2:$E$2224,$A40,Pedidos!$F$2:$F$2224,"80-100")-1,"") -> 0.48195451 | J40: =IFERROR(AVERAGEIFS(Pedidos!$S$2:$S$2224,Pedidos!$E$2:$E$2224,$A40,Pedidos!$F$2:$F$2224,"100-120")/AVERAGEIFS(Pedidos!$J$2:$J$2224,Pedidos!$E$2:$E$2224,$A40,Pedidos!$F$2:$F$2224,"100-120")-1,"") -> 0.62016844 | K40: =IFERROR(AVERAGEIFS(Pedidos!$S$2:$S$2224,Pedidos!$E$2:$E$2224,$A40,Pedidos!$F$2:$F$2224,"120-150")/AVERAGEIFS(Pedidos!$J$2:$J$2224,Pedidos!$E$2:$E$2224,$A40,Pedidos!$F$2:$F$2224,"120-150")-1,"") -> 0.52463628 | L40: =IFERROR(AVERAGEIFS(Pedidos!$S$2:$S$2224,Pedidos!$E$2:$E$2224,$A40,Pedidos!$F$2:$F$2224,"150-170")/AVERAGEIFS(Pedidos!$J$2:$J$2224,Pedidos!$E$2:$E$2224,$A40,Pedidos!$F$2:$F$2224,"150-170")-1,"") | M40: =IFERROR(AVERAGEIFS(Pedidos!$S$2:$S$2224,Pedidos!$E$2:$E$2224,$A40,Pedidos!$F$2:$F$2224,"170-200")/AVERAGEIFS(Pedidos!$J$2:$J$2224,Pedidos!$E$2:$E$2224,$A40,Pedidos!$F$2:$F$2224,"170-200")-1,"") | N40: =IFERROR(AVERAGEIFS(Pedidos!$S$2:$S$2224,Pedidos!$E$2:$E$2224,$A40,Pedidos!$F$2:$F$2224,"200-250")/AVERAGEIFS(Pedidos!$J$2:$J$2224,Pedidos!$E$2:$E$2224,$A40,Pedidos!$F$2:$F$2224,"200-250")-1,"") | O40: =IFERROR(AVERAGEIFS(Pedidos!$S$2:$S$2224,Pedidos!$E$2:$E$2224,$A40,Pedidos!$F$2:$F$2224,">250")/AVERAGEIFS(Pedidos!$J$2:$J$2224,Pedidos!$E$2:$E$2224,$A40,Pedidos!$F$2:$F$2224,">250")-1,"") | P40: =IFERROR(AVERAGEIFS(Pedidos!$S$2:$S$2224,Pedidos!$E$2:$E$2224,$A40)/AVERAGEIFS(Pedidos!$J$2:$J$2224,Pedidos!$E$2:$E$2224,$A40)-1,"") -> 0.44642034
... A48: Rio das Ostras | B48: =IFERROR(AVERAGEIFS(Pedidos!$S$2:$S$2224,Pedidos!$E$2:$E$2224,$A48,Pedidos!$F$2:$F$2224,"0-20")/AVERAGEIFS(Pedidos!$J$2:$J$2224,Pedidos!$E$2:$E$2224,$A48,Pedidos!$F$2:$F$2224,"0-20")-1,"") | C48: =IFERROR(AVERAGEIFS(Pedidos!$S$2:$S$2224,Pedidos!$E$2:$E$2224,$A48,Pedidos!$F$2:$F$2224,"20-35")/AVERAGEIFS(Pedidos!$J$2:$J$2224,Pedidos!$E$2:$E$2224,$A48,Pedidos!$F$2:$F$2224,"20-35")-1,"") -> 0.43562394 | D48: =IFERROR(AVERAGEIFS(Pedidos!$S$2:$S$2224,Pedidos!$E$2:$E$2224,$A48,Pedidos!$F$2:$F$2224,"35-40")/AVERAGEIFS(Pedidos!$J$2:$J$2224,Pedidos!$E$2:$E$2224,$A48,Pedidos!$F$2:$F$2224,"35-40")-1,"") -> 0.39749945 | E48: =IFERROR(AVERAGEIFS(Pedidos!$S$2:$S$2224,Pedidos!$E$2:$E$2224,$A48,Pedidos!$F$2:$F$2224,"40-50")/AVERAGEIFS(Pedidos!$J$2:$J$2224,Pedidos!$E$2:$E$2224,$A48,Pedidos!$F$2:$F$2224,"40-50")-1,"") -> 0.39222417 | F48: =IFERROR(AVERAGEIFS(Pedidos!$S$2:$S$2224,Pedidos!$E$2:$E$2224,$A48,Pedidos!$F$2:$F$2224,"50-60")/AVERAGEIFS(Pedidos!$J$2:$J$2224,Pedidos!$E$2:$E$2224,$A48,Pedidos!$F$2:$F$2224,"50-60")-1,"") -> 0.40668924 | G48: =IFERROR(AVERAGEIFS(Pedidos!$S$2:$S$2224,Pedidos!$E$2:$E$2224,$A48,Pedidos!$F$2:$F$2224,"60-70")/AVERAGEIFS(Pedidos!$J$2:$J$2224,Pedidos!$E$2:$E$2224,$A48,Pedidos!$F$2:$F$2224,"60-70")-1,"") -> 0.520098 | H48: =IFERROR(AVERAGEIFS(Pedidos!$S$2:$S$2224,Pedidos!$E$2:$E$2224,$A48,Pedidos!$F$2:$F$2224,"70-80")/AVERAGEIFS(Pedidos!$J$2:$J$2224,Pedidos!$E$2:$E$2224,$A48,Pedidos!$F$2:$F$2224,"70-80")-1,"") | I48: =IFERROR(AVERAGEIFS(Pedidos!$S$2:$S$2224,Pedidos!$E$2:$E$2224,$A48,Pedidos!$F$2:$F$2224,"80-100")/AVERAGEIFS(Pedidos!$J$2:$J$2224,Pedidos!$E$2:$E$2224,$A48,Pedidos!$F$2:$F$2224,"80-100")-1,"") -> 0.46204275 | J48: =IFERROR(AVERAGEIFS(Pedidos!$S$2:$S$2224,Pedidos!$E$2:$E$2224,$A48,Pedidos!$F$2:$F$2224,"100-120")/AVERAGEIFS(Pedidos!$J$2:$J$2224,Pedidos!$E$2:$E$2224,$A48,Pedidos!$F$2:$F$2224,"100-120")-1,"") | K48: =IFERROR(AVERAGEIFS(Pedidos!$S$2:$S$2224,Pedidos!$E$2:$E$2224,$A48,Pedidos!$F$2:$F$2224,"120-150")/AVERAGEIFS(Pedidos!$J$2:$J$2224,Pedidos!$E$2:$E$2224,$A48,Pedidos!$F$2:$F$2224,"120-150")-1,"") | L48: =IFERROR(AVERAGEIFS(Pedidos!$S$2:$S$2224,Pedidos!$E$2:$E$2224,$A48,Pedidos!$F$2:$F$2224,"150-170")/AVERAGEIFS(Pedidos!$J$2:$J$2224,Pedidos!$E$2:$E$2224,$A48,Pedidos!$F$2:$F$2224,"150-170")-1,"") | M48: =IFERROR(AVERAGEIFS(Pedidos!$S$2:$S$2224,Pedidos!$E$2:$E$2224,$A48,Pedidos!$F$2:$F$2224,"170-200")/AVERAGEIFS(Pedidos!$J$2:$J$2224,Pedidos!$E$2:$E$2224,$A48,Pedidos!$F$2:$F$2224,"170-200")-1,"") | N48: =IFERROR(AVERAGEIFS(Pedidos!$S$2:$S$2224,Pedidos!$E$2:$E$2224,$A48,Pedidos!$F$2:$F$2224,"200-250")/AVERAGEIFS(Pedidos!$J$2:$J$2224,Pedidos!$E$2:$E$2224,$A48,Pedidos!$F$2:$F$2224,"200-250")-1,"") | O48: =IFERROR(AVERAGEIFS(Pedidos!$S$2:$S$2224,Pedidos!$E$2:$E$2224,$A48,Pedidos!$F$2:$F$2224,">250")/AVERAGEIFS(Pedidos!$J$2:$J$2224,Pedidos!$E$2:$E$2224,$A48,Pedidos!$F$2:$F$2224,">250")-1,"") | P48: =IFERROR(AVERAGEIFS(Pedidos!$S$2:$S$2224,Pedidos!$E$2:$E$2224,$A48)/AVERAGEIFS(Pedidos!$J$2:$J$2224,Pedidos!$E$2:$E$2224,$A48)-1,"") -> 0.43790169
A51: 3) Somente frete peso PROLOG vs custo atual (%) — onde a BASE da tabela já é competitiva
A52: Cidade | B52: 0-20 | C52: 20-35 | D52: 35-40 | E52: 40-50 | F52: 50-60 | G52: 60-70 | H52: 70-80 | I52: 80-100 | J52: 100-120 | K52: 120-150 | L52: 150-170 | M52: 170-200 | N52: 200-250 | O52: >250 | P52: Total
A53: Rio de Janeiro | B53: =IFERROR(AVERAGEIFS(Pedidos!$K$2:$K$2224,Pedidos!$E$2:$E$2224,$A53,Pedidos!$F$2:$F$2224,"0-20")/AVERAGEIFS(Pedidos!$J$2:$J$2224,Pedidos!$E$2:$E$2224,$A53,Pedidos!$F$2:$F$2224,"0-20")-1,"") -> -0.27901936 | C53: =IFERROR(AVERAGEIFS(Pedidos!$K$2:$K$2224,Pedidos!$E$2:$E$2224,$A53,Pedidos!$F$2:$F$2224,"20-35")/AVERAGEIFS(Pedidos!$J$2:$J$2224,Pedidos!$E$2:$E$2224,$A53,Pedidos!$F$2:$F$2224,"20-35")-1,"") -> 0.00050624031 | D53: =IFERROR(AVERAGEIFS(Pedidos!$K$2:$K$2224,Pedidos!$E$2:$E$2224,$A53,Pedidos!$F$2:$F$2224,"35-40")/AVERAGEIFS(Pedidos!$J$2:$J$2224,Pedidos!$E$2:$E$2224,$A53,Pedidos!$F$2:$F$2224,"35-40")-1,"") -> 0.0190089 | E53: =IFERROR(AVERAGEIFS(Pedidos!$K$2:$K$2224,Pedidos!$E$2:$E$2224,$A53,Pedidos!$F$2:$F$2224,"40-50")/AVERAGEIFS(Pedidos!$J$2:$J$2224,Pedidos!$E$2:$E$2224,$A53,Pedidos!$F$2:$F$2224,"40-50")-1,"") -> -0.096525796 | F53: =IFERROR(AVERAGEIFS(Pedidos!$K$2:$K$2224,Pedidos!$E$2:$E$2224,$A53,Pedidos!$F$2:$F$2224,"50-60")/AVERAGEIFS(Pedidos!$J$2:$J$2224,Pedidos!$E$2:$E$2224,$A53,Pedidos!$F$2:$F$2224,"50-60")-1,"") -> -0.020317768 | G53: =IFERROR(AVERAGEIFS(Pedidos!$K$2:$K$2224,Pedidos!$E$2:$E$2224,$A53,Pedidos!$F$2:$F$2224,"60-70")/AVERAGEIFS(Pedidos!$J$2:$J$2224,Pedidos!$E$2:$E$2224,$A53,Pedidos!$F$2:$F$2224,"60-70")-1,"") -> 0.048709824 | H53: =IFERROR(AVERAGEIFS(Pedidos!$K$2:$K$2224,Pedidos!$E$2:$E$2224,$A53,Pedidos!$F$2:$F$2224,"70-80")/AVERAGEIFS(Pedidos!$J$2:$J$2224,Pedidos!$E$2:$E$2224,$A53,Pedidos!$F$2:$F$2224,"70-80")-1,"") -> -0.025992594 | I53: =IFERROR(AVERAGEIFS(Pedidos!$K$2:$K$2224,Pedidos!$E$2:$E$2224,$A53,Pedidos!$F$2:$F$2224,"80-100")/AVERAGEIFS(Pedidos!$J$2:$J$2224,Pedidos!$E$2:$E$2224,$A53,Pedidos!$F$2:$F$2224,"80-100")-1,"") -> 0.025833781 | J53: =IFERROR(AVERAGEIFS(Pedidos!$K$2:$K$2224,Pedidos!$E$2:$E$2224,$A53,Pedidos!$F$2:$F$2224,"100-120")/AVERAGEIFS(Pedidos!$J$2:$J$2224,Pedidos!$E$2:$E$2224,$A53,Pedidos!$F$2:$F$2224,"100-120")-1,"") -> 0.084880976 | K53: =IFERROR(AVERAGEIFS(Pedidos!$K$2:$K$2224,Pedidos!$E$2:$E$2224,$A53,Pedidos!$F$2:$F$2224,"120-150")/AVERAGEIFS(Pedidos!$J$2:$J$2224,Pedidos!$E$2:$E$2224,$A53,Pedidos!$F$2:$F$2224,"120-150")-1,"") -> 0.026108119 | L53: =IFERROR(AVERAGEIFS(Pedidos!$K$2:$K$2224,Pedidos!$E$2:$E$2224,$A53,Pedidos!$F$2:$F$2224,"150-170")/AVERAGEIFS(Pedidos!$J$2:$J$2224,Pedidos!$E$2:$E$2224,$A53,Pedidos!$F$2:$F$2224,"150-170")-1,"") -> 0.060215054 | M53: =IFERROR(AVERAGEIFS(Pedidos!$K$2:$K$2224,Pedidos!$E$2:$E$2224,$A53,Pedidos!$F$2:$F$2224,"170-200")/AVERAGEIFS(Pedidos!$J$2:$J$2224,Pedidos!$E$2:$E$2224,$A53,Pedidos!$F$2:$F$2224,"170-200")-1,"") | N53: =IFERROR(AVERAGEIFS(Pedidos!$K$2:$K$2224,Pedidos!$E$2:$E$2224,$A53,Pedidos!$F$2:$F$2224,"200-250")/AVERAGEIFS(Pedidos!$J$2:$J$2224,Pedidos!$E$2:$E$2224,$A53,Pedidos!$F$2:$F$2224,"200-250")-1,"") -> 0.17900651 | O53: =IFERROR(AVERAGEIFS(Pedidos!$K$2:$K$2224,Pedidos!$E$2:$E$2224,$A53,Pedidos!$F$2:$F$2224,">250")/AVERAGEIFS(Pedidos!$J$2:$J$2224,Pedidos!$E$2:$E$2224,$A53,Pedidos!$F$2:$F$2224,">250")-1,"") | P53: =IFERROR(AVERAGEIFS(Pedidos!$K$2:$K$2224,Pedidos!$E$2:$E$2224,$A53)/AVERAGEIFS(Pedidos!$J$2:$J$2224,Pedidos!$E$2:$E$2224,$A53)-1,"") -> -0.013195588
A54: São Gonçalo | B54: =IFERROR(AVERAGEIFS(Pedidos!$K$2:$K$2224,Pedidos!$E$2:$E$2224,$A54,Pedidos!$F$2:$F$2224,"0-20")/AVERAGEIFS(Pedidos!$J$2:$J$2224,Pedidos!$E$2:$E$2224,$A54,Pedidos!$F$2:$F$2224,"0-20")-1,"") -> -0.24738083 | C54: =IFERROR(AVERAGEIFS(Pedidos!$K$2:$K$2224,Pedidos!$E$2:$E$2224,$A54,Pedidos!$F$2:$F$2224,"20-35")/AVERAGEIFS(Pedidos!$J$2:$J$2224,Pedidos!$E$2:$E$2224,$A54,Pedidos!$F$2:$F$2224,"20-35")-1,"") -> 0.0024745499 | D54: =IFERROR(AVERAGEIFS(Pedidos!$K$2:$K$2224,Pedidos!$E$2:$E$2224,$A54,Pedidos!$F$2:$F$2224,"35-40")/AVERAGEIFS(Pedidos!$J$2:$J$2224,Pedidos!$E$2:$E$2224,$A54,Pedidos!$F$2:$F$2224,"35-40")-1,"") -> 0.011621597 | E54: =IFERROR(AVERAGEIFS(Pedidos!$K$2:$K$2224,Pedidos!$E$2:$E$2224,$A54,Pedidos!$F$2:$F$2224,"40-50")/AVERAGEIFS(Pedidos!$J$2:$J$2224,Pedidos!$E$2:$E$2224,$A54,Pedidos!$F$2:$F$2224,"40-50")-1,"") -> -0.01934248 | F54: =IFERROR(AVERAGEIFS(Pedidos!$K$2:$K$2224,Pedidos!$E$2:$E$2224,$A54,Pedidos!$F$2:$F$2224,"50-60")/AVERAGEIFS(Pedidos!$J$2:$J$2224,Pedidos!$E$2:$E$2224,$A54,Pedidos!$F$2:$F$2224,"50-60")-1,"") -> -0.005602893 | G54: =IFERROR(AVERAGEIFS(Pedidos!$K$2:$K$2224,Pedidos!$E$2:$E$2224,$A54,Pedidos!$F$2:$F$2224,"60-70")/AVERAGEIFS(Pedidos!$J$2:$J$2224,Pedidos!$E$2:$E$2224,$A54,Pedidos!$F$2:$F$2224,"60-70")-1,"") -> 0.064890662 | H54: =IFERROR(AVERAGEIFS(Pedidos!$K$2:$K$2224,Pedidos!$E$2:$E$2224,$A54,Pedidos!$F$2:$F$2224,"70-80")/AVERAGEIFS(Pedidos!$J$2:$J$2224,Pedidos!$E$2:$E$2224,$A54,Pedidos!$F$2:$F$2224,"70-80")-1,"") -> -0.070904752 | I54: =IFERROR(AVERAGEIFS(Pedidos!$K$2:$K$2224,Pedidos!$E$2:$E$2224,$A54,Pedidos!$F$2:$F$2224,"80-100")/AVERAGEIFS(Pedidos!$J$2:$J$2224,Pedidos!$E$2:$E$2224,$A54,Pedidos!$F$2:$F$2224,"80-100")-1,"") -> 0.044165269 | J54: =IFERROR(AVERAGEIFS(Pedidos!$K$2:$K$2224,Pedidos!$E$2:$E$2224,$A54,Pedidos!$F$2:$F$2224,"100-120")/AVERAGEIFS(Pedidos!$J$2:$J$2224,Pedidos!$E$2:$E$2224,$A54,Pedidos!$F$2:$F$2224,"100-120")-1,"") -> 0.098788874 | K54: =IFERROR(AVERAGEIFS(Pedidos!$K$2:$K$2224,Pedidos!$E$2:$E$2224,$A54,Pedidos!$F$2:$F$2224,"120-150")/AVERAGEIFS(Pedidos!$J$2:$J$2224,Pedidos!$E$2:$E$2224,$A54,Pedidos!$F$2:$F$2224,"120-150")-1,"") -> 0.036103223 | L54: =IFERROR(AVERAGEIFS(Pedidos!$K$2:$K$2224,Pedidos!$E$2:$E$2224,$A54,Pedidos!$F$2:$F$2224,"150-170")/AVERAGEIFS(Pedidos!$J$2:$J$2224,Pedidos!$E$2:$E$2224,$A54,Pedidos!$F$2:$F$2224,"150-170")-1,"") -> 0.05431656 | M54: =IFERROR(AVERAGEIFS(Pedidos!$K$2:$K$2224,Pedidos!$E$2:$E$2224,$A54,Pedidos!$F$2:$F$2224,"170-200")/AVERAGEIFS(Pedidos!$J$2:$J$2224,Pedidos!$E$2:$E$2224,$A54,Pedidos!$F$2:$F$2224,"170-200")-1,"") | N54: =IFERROR(AVERAGEIFS(Pedidos!$K$2:$K$2224,Pedidos!$E$2:$E$2224,$A54,Pedidos!$F$2:$F$2224,"200-250")/AVERAGEIFS(Pedidos!$J$2:$J$2224,Pedidos!$E$2:$E$2224,$A54,Pedidos!$F$2:$F$2224,"200-250")-1,"") | O54: =IFERROR(AVERAGEIFS(Pedidos!$K$2:$K$2224,Pedidos!$E$2:$E$2224,$A54,Pedidos!$F$2:$F$2224,">250")/AVERAGEIFS(Pedidos!$J$2:$J$2224,Pedidos!$E$2:$E$2224,$A54,Pedidos!$F$2:$F$2224,">250")-1,"") | P54: =IFERROR(AVERAGEIFS(Pedidos!$K$2:$K$2224,Pedidos!$E$2:$E$2224,$A54)/AVERAGEIFS(Pedidos!$J$2:$J$2224,Pedidos!$E$2:$E$2224,$A54)-1,"") -> 0.004873142
A55: Duque de Caxias | B55: =IFERROR(AVERAGEIFS(Pedidos!$K$2:$K$2224,Pedidos!$E$2:$E$2224,$A55,Pedidos!$F$2:$F$2224,"0-20")/AVERAGEIFS(Pedidos!$J$2:$J$2224,Pedidos!$E$2:$E$2224,$A55,Pedidos!$F$2:$F$2224,"0-20")-1,"") -> -0.37699193 | C55: =IFERROR(AVERAGEIFS(Pedidos!$K$2:$K$2224,Pedidos!$E$2:$E$2224,$A55,Pedidos!$F$2:$F$2224,"20-35")/AVERAGEIFS(Pedidos!$J$2:$J$2224,Pedidos!$E$2:$E$2224,$A55,Pedidos!$F$2:$F$2224,"20-35")-1,"") -> -0.18935043 | D55: =IFERROR(AVERAGEIFS(Pedidos!$K$2:$K$2224,Pedidos!$E$2:$E$2224,$A55,Pedidos!$F$2:$F$2224,"35-40")/AVERAGEIFS(Pedidos!$J$2:$J$2224,Pedidos!$E$2:$E$2224,$A55,Pedidos!$F$2:$F$2224,"35-40")-1,"") -> -0.17003629 | E55: =IFERROR(AVERAGEIFS(Pedidos!$K$2:$K$2224,Pedidos!$E$2:$E$2224,$A55,Pedidos!$F$2:$F$2224,"40-50")/AVERAGEIFS(Pedidos!$J$2:$J$2224,Pedidos!$E$2:$E$2224,$A55,Pedidos!$F$2:$F$2224,"40-50")-1,"") -> -0.19704778 | F55: =IFERROR(AVERAGEIFS(Pedidos!$K$2:$K$2224,Pedidos!$E$2:$E$2224,$A55,Pedidos!$F$2:$F$2224,"50-60")/AVERAGEIFS(Pedidos!$J$2:$J$2224,Pedidos!$E$2:$E$2224,$A55,Pedidos!$F$2:$F$2224,"50-60")-1,"") -> -0.12730248 | G55: =IFERROR(AVERAGEIFS(Pedidos!$K$2:$K$2224,Pedidos!$E$2:$E$2224,$A55,Pedidos!$F$2:$F$2224,"60-70")/AVERAGEIFS(Pedidos!$J$2:$J$2224,Pedidos!$E$2:$E$2224,$A55,Pedidos!$F$2:$F$2224,"60-70")-1,"") -> -0.063736028 | H55: =IFERROR(AVERAGEIFS(Pedidos!$K$2:$K$2224,Pedidos!$E$2:$E$2224,$A55,Pedidos!$F$2:$F$2224,"70-80")/AVERAGEIFS(Pedidos!$J$2:$J$2224,Pedidos!$E$2:$E$2224,$A55,Pedidos!$F$2:$F$2224,"70-80")-1,"") -> -0.11434032 | I55: =IFERROR(AVERAGEIFS(Pedidos!$K$2:$K$2224,Pedidos!$E$2:$E$2224,$A55,Pedidos!$F$2:$F$2224,"80-100")/AVERAGEIFS(Pedidos!$J$2:$J$2224,Pedidos!$E$2:$E$2224,$A55,Pedidos!$F$2:$F$2224,"80-100")-1,"") -> -0.032482866 | J55: =IFERROR(AVERAGEIFS(Pedidos!$K$2:$K$2224,Pedidos!$E$2:$E$2224,$A55,Pedidos!$F$2:$F$2224,"100-120")/AVERAGEIFS(Pedidos!$J$2:$J$2224,Pedidos!$E$2:$E$2224,$A55,Pedidos!$F$2:$F$2224,"100-120")-1,"") -> 0.031573022 | K55: =IFERROR(AVERAGEIFS(Pedidos!$K$2:$K$2224,Pedidos!$E$2:$E$2224,$A55,Pedidos!$F$2:$F$2224,"120-150")/AVERAGEIFS(Pedidos!$J$2:$J$2224,Pedidos!$E$2:$E$2224,$A55,Pedidos!$F$2:$F$2224,"120-150")-1,"") -> -0.020815598 | L55: =IFERROR(AVERAGEIFS(Pedidos!$K$2:$K$2224,Pedidos!$E$2:$E$2224,$A55,Pedidos!$F$2:$F$2224,"150-170")/AVERAGEIFS(Pedidos!$J$2:$J$2224,Pedidos!$E$2:$E$2224,$A55,Pedidos!$F$2:$F$2224,"150-170")-1,"") | M55: =IFERROR(AVERAGEIFS(Pedidos!$K$2:$K$2224,Pedidos!$E$2:$E$2224,$A55,Pedidos!$F$2:$F$2224,"170-200")/AVERAGEIFS(Pedidos!$J$2:$J$2224,Pedidos!$E$2:$E$2224,$A55,Pedidos!$F$2:$F$2224,"170-200")-1,"") | N55: =IFERROR(AVERAGEIFS(Pedidos!$K$2:$K$2224,Pedidos!$E$2:$E$2224,$A55,Pedidos!$F$2:$F$2224,"200-250")/AVERAGEIFS(Pedidos!$J$2:$J$2224,Pedidos!$E$2:$E$2224,$A55,Pedidos!$F$2:$F$2224,"200-250")-1,"") | O55: =IFERROR(AVERAGEIFS(Pedidos!$K$2:$K$2224,Pedidos!$E$2:$E$2224,$A55,Pedidos!$F$2:$F$2224,">250")/AVERAGEIFS(Pedidos!$J$2:$J$2224,Pedidos!$E$2:$E$2224,$A55,Pedidos!$F$2:$F$2224,">250")-1,"") | P55: =IFERROR(AVERAGEIFS(Pedidos!$K$2:$K$2224,Pedidos!$E$2:$E$2224,$A55)/AVERAGEIFS(Pedidos!$J$2:$J$2224,Pedidos!$E$2:$E$2224,$A55)-1,"") -> -0.12862925
A56: Nova Iguaçu | B56: =IFERROR(AVERAGEIFS(Pedidos!$K$2:$K$2224,Pedidos!$E$2:$E$2224,$A56,Pedidos!$F$2:$F$2224,"0-20")/AVERAGEIFS(Pedidos!$J$2:$J$2224,Pedidos!$E$2:$E$2224,$A56,Pedidos!$F$2:$F$2224,"0-20")-1,"") -> -0.37865362 | C56: =IFERROR(AVERAGEIFS(Pedidos!$K$2:$K$2224,Pedidos!$E$2:$E$2224,$A56,Pedidos!$F$2:$F$2224,"20-35")/AVERAGEIFS(Pedidos!$J$2:$J$2224,Pedidos!$E$2:$E$2224,$A56,Pedidos!$F$2:$F$2224,"20-35")-1,"") -> -0.19064496 | D56: =IFERROR(AVERAGEIFS(Pedidos!$K$2:$K$2224,Pedidos!$E$2:$E$2224,$A56,Pedidos!$F$2:$F$2224,"35-40")/AVERAGEIFS(Pedidos!$J$2:$J$2224,Pedidos!$E$2:$E$2224,$A56,Pedidos!$F$2:$F$2224,"35-40")-1,"") -> -0.16803896 | E56: =IFERROR(AVERAGEIFS(Pedidos!$K$2:$K$2224,Pedidos!$E$2:$E$2224,$A56,Pedidos!$F$2:$F$2224,"40-50")/AVERAGEIFS(Pedidos!$J$2:$J$2224,Pedidos!$E$2:$E$2224,$A56,Pedidos!$F$2:$F$2224,"40-50")-1,"") -> -0.19712925 | F56: =IFERROR(AVERAGEIFS(Pedidos!$K$2:$K$2224,Pedidos!$E$2:$E$2224,$A56,Pedidos!$F$2:$F$2224,"50-60")/AVERAGEIFS(Pedidos!$J$2:$J$2224,Pedidos!$E$2:$E$2224,$A56,Pedidos!$F$2:$F$2224,"50-60")-1,"") -> -0.12496258 | G56: =IFERROR(AVERAGEIFS(Pedidos!$K$2:$K$2224,Pedidos!$E$2:$E$2224,$A56,Pedidos!$F$2:$F$2224,"60-70")/AVERAGEIFS(Pedidos!$J$2:$J$2224,Pedidos!$E$2:$E$2224,$A56,Pedidos!$F$2:$F$2224,"60-70")-1,"") -> -0.064543767 | H56: =IFERROR(AVERAGEIFS(Pedidos!$K$2:$K$2224,Pedidos!$E$2:$E$2224,$A56,Pedidos!$F$2:$F$2224,"70-80")/AVERAGEIFS(Pedidos!$J$2:$J$2224,Pedidos!$E$2:$E$2224,$A56,Pedidos!$F$2:$F$2224,"70-80")-1,"") -> -0.11390235 | I56: =IFERROR(AVERAGEIFS(Pedidos!$K$2:$K$2224,Pedidos!$E$2:$E$2224,$A56,Pedidos!$F$2:$F$2224,"80-100")/AVERAGEIFS(Pedidos!$J$2:$J$2224,Pedidos!$E$2:$E$2224,$A56,Pedidos!$F$2:$F$2224,"80-100")-1,"") -> -0.028594559 | J56: =IFERROR(AVERAGEIFS(Pedidos!$K$2:$K$2224,Pedidos!$E$2:$E$2224,$A56,Pedidos!$F$2:$F$2224,"100-120")/AVERAGEIFS(Pedidos!$J$2:$J$2224,Pedidos!$E$2:$E$2224,$A56,Pedidos!$F$2:$F$2224,"100-120")-1,"") -> 0.02982345 | K56: =IFERROR(AVERAGEIFS(Pedidos!$K$2:$K$2224,Pedidos!$E$2:$E$2224,$A56,Pedidos!$F$2:$F$2224,"120-150")/AVERAGEIFS(Pedidos!$J$2:$J$2224,Pedidos!$E$2:$E$2224,$A56,Pedidos!$F$2:$F$2224,"120-150")-1,"") -> -0.021872445 | L56: =IFERROR(AVERAGEIFS(Pedidos!$K$2:$K$2224,Pedidos!$E$2:$E$2224,$A56,Pedidos!$F$2:$F$2224,"150-170")/AVERAGEIFS(Pedidos!$J$2:$J$2224,Pedidos!$E$2:$E$2224,$A56,Pedidos!$F$2:$F$2224,"150-170")-1,"") | M56: =IFERROR(AVERAGEIFS(Pedidos!$K$2:$K$2224,Pedidos!$E$2:$E$2224,$A56,Pedidos!$F$2:$F$2224,"170-200")/AVERAGEIFS(Pedidos!$J$2:$J$2224,Pedidos!$E$2:$E$2224,$A56,Pedidos!$F$2:$F$2224,"170-200")-1,"") | N56: =IFERROR(AVERAGEIFS(Pedidos!$K$2:$K$2224,Pedidos!$E$2:$E$2224,$A56,Pedidos!$F$2:$F$2224,"200-250")/AVERAGEIFS(Pedidos!$J$2:$J$2224,Pedidos!$E$2:$E$2224,$A56,Pedidos!$F$2:$F$2224,"200-250")-1,"") | O56: =IFERROR(AVERAGEIFS(Pedidos!$K$2:$K$2224,Pedidos!$E$2:$E$2224,$A56,Pedidos!$F$2:$F$2224,">250")/AVERAGEIFS(Pedidos!$J$2:$J$2224,Pedidos!$E$2:$E$2224,$A56,Pedidos!$F$2:$F$2224,">250")-1,"") | P56: =IFERROR(AVERAGEIFS(Pedidos!$K$2:$K$2224,Pedidos!$E$2:$E$2224,$A56)/AVERAGEIFS(Pedidos!$J$2:$J$2224,Pedidos!$E$2:$E$2224,$A56)-1,"") -> -0.11635278
A57: Niterói | B57: =IFERROR(AVERAGEIFS(Pedidos!$K$2:$K$2224,Pedidos!$E$2:$E$2224,$A57,Pedidos!$F$2:$F$2224,"0-20")/AVERAGEIFS(Pedidos!$J$2:$J$2224,Pedidos!$E$2:$E$2224,$A57,Pedidos!$F$2:$F$2224,"0-20")-1,"") -> -0.23556797 | C57: =IFERROR(AVERAGEIFS(Pedidos!$K$2:$K$2224,Pedidos!$E$2:$E$2224,$A57,Pedidos!$F$2:$F$2224,"20-35")/AVERAGEIFS(Pedidos!$J$2:$J$2224,Pedidos!$E$2:$E$2224,$A57,Pedidos!$F$2:$F$2224,"20-35")-1,"") -> -0.0062336076 | D57: =IFERROR(AVERAGEIFS(Pedidos!$K$2:$K$2224,Pedidos!$E$2:$E$2224,$A57,Pedidos!$F$2:$F$2224,"35-40")/AVERAGEIFS(Pedidos!$J$2:$J$2224,Pedidos!$E$2:$E$2224,$A57,Pedidos!$F$2:$F$2224,"35-40")-1,"") -> 0.013822853 | E57: =IFERROR(AVERAGEIFS(Pedidos!$K$2:$K$2224,Pedidos!$E$2:$E$2224,$A57,Pedidos!$F$2:$F$2224,"40-50")/AVERAGEIFS(Pedidos!$J$2:$J$2224,Pedidos!$E$2:$E$2224,$A57,Pedidos!$F$2:$F$2224,"40-50")-1,"") -> -0.016198421 | F57: =IFERROR(AVERAGEIFS(Pedidos!$K$2:$K$2224,Pedidos!$E$2:$E$2224,$A57,Pedidos!$F$2:$F$2224,"50-60")/AVERAGEIFS(Pedidos!$J$2:$J$2224,Pedidos!$E$2:$E$2224,$A57,Pedidos!$F$2:$F$2224,"50-60")-1,"") -> -0.0027116922 | G57: =IFERROR(AVERAGEIFS(Pedidos!$K$2:$K$2224,Pedidos!$E$2:$E$2224,$A57,Pedidos!$F$2:$F$2224,"60-70")/AVERAGEIFS(Pedidos!$J$2:$J$2224,Pedidos!$E$2:$E$2224,$A57,Pedidos!$F$2:$F$2224,"60-70")-1,"") -> 0.068380431 | H57: =IFERROR(AVERAGEIFS(Pedidos!$K$2:$K$2224,Pedidos!$E$2:$E$2224,$A57,Pedidos!$F$2:$F$2224,"70-80")/AVERAGEIFS(Pedidos!$J$2:$J$2224,Pedidos!$E$2:$E$2224,$A57,Pedidos!$F$2:$F$2224,"70-80")-1,"") | I57: =IFERROR(AVERAGEIFS(Pedidos!$K$2:$K$2224,Pedidos!$E$2:$E$2224,$A57,Pedidos!$F$2:$F$2224,"80-100")/AVERAGEIFS(Pedidos!$J$2:$J$2224,Pedidos!$E$2:$E$2224,$A57,Pedidos!$F$2:$F$2224,"80-100")-1,"") -> 0.023872375 | J57: =IFERROR(AVERAGEIFS(Pedidos!$K$2:$K$2224,Pedidos!$E$2:$E$2224,$A57,Pedidos!$F$2:$F$2224,"100-120")/AVERAGEIFS(Pedidos!$J$2:$J$2224,Pedidos!$E$2:$E$2224,$A57,Pedidos!$F$2:$F$2224,"100-120")-1,"") -> 0.090450726 | K57: =IFERROR(AVERAGEIFS(Pedidos!$K$2:$K$2224,Pedidos!$E$2:$E$2224,$A57,Pedidos!$F$2:$F$2224,"120-150")/AVERAGEIFS(Pedidos!$J$2:$J$2224,Pedidos!$E$2:$E$2224,$A57,Pedidos!$F$2:$F$2224,"120-150")-1,"") -> 0.020280236 | L57: =IFERROR(AVERAGEIFS(Pedidos!$K$2:$K$2224,Pedidos!$E$2:$E$2224,$A57,Pedidos!$F$2:$F$2224,"150-170")/AVERAGEIFS(Pedidos!$J$2:$J$2224,Pedidos!$E$2:$E$2224,$A57,Pedidos!$F$2:$F$2224,"150-170")-1,"") | M57: =IFERROR(AVERAGEIFS(Pedidos!$K$2:$K$2224,Pedidos!$E$2:$E$2224,$A57,Pedidos!$F$2:$F$2224,"170-200")/AVERAGEIFS(Pedidos!$J$2:$J$2224,Pedidos!$E$2:$E$2224,$A57,Pedidos!$F$2:$F$2224,"170-200")-1,"") | N57: =IFERROR(AVERAGEIFS(Pedidos!$K$2:$K$2224,Pedidos!$E$2:$E$2224,$A57,Pedidos!$F$2:$F$2224,"200-250")/AVERAGEIFS(Pedidos!$J$2:$J$2224,Pedidos!$E$2:$E$2224,$A57,Pedidos!$F$2:$F$2224,"200-250")-1,"") | O57: =IFERROR(AVERAGEIFS(Pedidos!$K$2:$K$2224,Pedidos!$E$2:$E$2224,$A57,Pedidos!$F$2:$F$2224,">250")/AVERAGEIFS(Pedidos!$J$2:$J$2224,Pedidos!$E$2:$E$2224,$A57,Pedidos!$F$2:$F$2224,">250")-1,"") | P57: =IFERROR(AVERAGEIFS(Pedidos!$K$2:$K$2224,Pedidos!$E$2:$E$2224,$A57)/AVERAGEIFS(Pedidos!$J$2:$J$2224,Pedidos!$E$2:$E$2224,$A57)-1,"") -> 0.0040631303
A58: Campos dos Goytacazes | B58: =IFERROR(AVERAGEIFS(Pedidos!$K$2:$K$2224,Pedidos!$E$2:$E$2224,$A58,Pedidos!$F$2:$F$2224,"0-20")/AVERAGEIFS(Pedidos!$J$2:$J$2224,Pedidos!$E$2:$E$2224,$A58,Pedidos!$F$2:$F$2224,"0-20")-1,"") | C58: =IFERROR(AVERAGEIFS(Pedidos!$K$2:$K$2224,Pedidos!$E$2:$E$2224,$A58,Pedidos!$F$2:$F$2224,"20-35")/AVERAGEIFS(Pedidos!$J$2:$J$2224,Pedidos!$E$2:$E$2224,$A58,Pedidos!$F$2:$F$2224,"20-35")-1,"") -> 0.26570374 | D58: =IFERROR(AVERAGEIFS(Pedidos!$K$2:$K$2224,Pedidos!$E$2:$E$2224,$A58,Pedidos!$F$2:$F$2224,"35-40")/AVERAGEIFS(Pedidos!$J$2:$J$2224,Pedidos!$E$2:$E$2224,$A58,Pedidos!$F$2:$F$2224,"35-40")-1,"") -> 0.15969759 | E58: =IFERROR(AVERAGEIFS(Pedidos!$K$2:$K$2224,Pedidos!$E$2:$E$2224,$A58,Pedidos!$F$2:$F$2224,"40-50")/AVERAGEIFS(Pedidos!$J$2:$J$2224,Pedidos!$E$2:$E$2224,$A58,Pedidos!$F$2:$F$2224,"40-50")-1,"") -> 0.16701094 | F58: =IFERROR(AVERAGEIFS(Pedidos!$K$2:$K$2224,Pedidos!$E$2:$E$2224,$A58,Pedidos!$F$2:$F$2224,"50-60")/AVERAGEIFS(Pedidos!$J$2:$J$2224,Pedidos!$E$2:$E$2224,$A58,Pedidos!$F$2:$F$2224,"50-60")-1,"") -> 0.13483985 | G58: =IFERROR(AVERAGEIFS(Pedidos!$K$2:$K$2224,Pedidos!$E$2:$E$2224,$A58,Pedidos!$F$2:$F$2224,"60-70")/AVERAGEIFS(Pedidos!$J$2:$J$2224,Pedidos!$E$2:$E$2224,$A58,Pedidos!$F$2:$F$2224,"60-70")-1,"") -> 0.099086977 | H58: =IFERROR(AVERAGEIFS(Pedidos!$K$2:$K$2224,Pedidos!$E$2:$E$2224,$A58,Pedidos!$F$2:$F$2224,"70-80")/AVERAGEIFS(Pedidos!$J$2:$J$2224,Pedidos!$E$2:$E$2224,$A58,Pedidos!$F$2:$F$2224,"70-80")-1,"") | I58: =IFERROR(AVERAGEIFS(Pedidos!$K$2:$K$2224,Pedidos!$E$2:$E$2224,$A58,Pedidos!$F$2:$F$2224,"80-100")/AVERAGEIFS(Pedidos!$J$2:$J$2224,Pedidos!$E$2:$E$2224,$A58,Pedidos!$F$2:$F$2224,"80-100")-1,"") -> 0.037067759 | J58: =IFERROR(AVERAGEIFS(Pedidos!$K$2:$K$2224,Pedidos!$E$2:$E$2224,$A58,Pedidos!$F$2:$F$2224,"100-120")/AVERAGEIFS(Pedidos!$J$2:$J$2224,Pedidos!$E$2:$E$2224,$A58,Pedidos!$F$2:$F$2224,"100-120")-1,"") -> 0.094210599 | K58: =IFERROR(AVERAGEIFS(Pedidos!$K$2:$K$2224,Pedidos!$E$2:$E$2224,$A58,Pedidos!$F$2:$F$2224,"120-150")/AVERAGEIFS(Pedidos!$J$2:$J$2224,Pedidos!$E$2:$E$2224,$A58,Pedidos!$F$2:$F$2224,"120-150")-1,"") | L58: =IFERROR(AVERAGEIFS(Pedidos!$K$2:$K$2224,Pedidos!$E$2:$E$2224,$A58,Pedidos!$F$2:$F$2224,"150-170")/AVERAGEIFS(Pedidos!$J$2:$J$2224,Pedidos!$E$2:$E$2224,$A58,Pedidos!$F$2:$F$2224,"150-170")-1,"") | M58: =IFERROR(AVERAGEIFS(Pedidos!$K$2:$K$2224,Pedidos!$E$2:$E$2224,$A58,Pedidos!$F$2:$F$2224,"170-200")/AVERAGEIFS(Pedidos!$J$2:$J$2224,Pedidos!$E$2:$E$2224,$A58,Pedidos!$F$2:$F$2224,"170-200")-1,"") | N58: =IFERROR(AVERAGEIFS(Pedidos!$K$2:$K$2224,Pedidos!$E$2:$E$2224,$A58,Pedidos!$F$2:$F$2224,"200-250")/AVERAGEIFS(Pedidos!$J$2:$J$2224,Pedidos!$E$2:$E$2224,$A58,Pedidos!$F$2:$F$2224,"200-250")-1,"") | O58: =IFERROR(AVERAGEIFS(Pedidos!$K$2:$K$2224,Pedidos!$E$2:$E$2224,$A58,Pedidos!$F$2:$F$2224,">250")/AVERAGEIFS(Pedidos!$J$2:$J$2224,Pedidos!$E$2:$E$2224,$A58,Pedidos!$F$2:$F$2224,">250")-1,"") | P58: =IFERROR(AVERAGEIFS(Pedidos!$K$2:$K$2224,Pedidos!$E$2:$E$2224,$A58)/AVERAGEIFS(Pedidos!$J$2:$J$2224,Pedidos!$E$2:$E$2224,$A58)-1,"") -> 0.1597331
